Workbook

Sheet Sheet1
A1: Initalization
A2: 0. GAFI Black List | D2: exclude_gafi_black
A3: 1. GAFI Grey List | D3: exclude_gafi_grey
A4: 2. Countries non fiscally cooperative with EU | D4: exclude_non_fiscal_coop
A5: 3. Subsectors | D5: exclude_subsector
A6: 4. UNGC controversies | D6: exclude_nbr_red
A7: 5. Tobacco Production | D7: exclude_tobacco_prod
A8: 6. Tobacco Distribution | D8: exclude_tobacco_dist
A9: 7. Biological weapons | D9: exclude_biological_weapons
A10: 8. Chemical weapons | D10: exclude_chemical_weapons
A11: 9. Nuclear weapons | D11: exclude_nuclear_weapons_inside_npt
A12: 10. Nuclear non-NPT weapons | D12: exclude_nuclear_weapons_outside_npt
A13: 11. Cluster munitions | D13: exclude_cluster_munitions
... A32: 30. Worst 10% avg soc gov score | D32: exclude_sg_bottom_10
A33: 35. Final Selection
D34: Excluded
D35: Exclusion_Reason
D36: itr_scope123_target_filled
D37: itr_scope12_trend_filled
D38: cdp_temperature_score
D39: bonus_malus
D40: climate_score
A41: 31. Non EU Taxonomy pocket
A42: 32. Rank Non EU Taxonomy by supersector | D42: SG_Score
A43: 33. Non EU Taxonomy initial selection
A44: 34. Non EU Taxonomy final selection
A45: 36. Dummy FFMC Weight

Sheet Selected Companies
A1: Rank | B1: Ticker | C1: Company | D1: ISIN Code | E1: MIC | F1: Number of Shares | G1: Price (EUR) | H1: Currency | I1: Mcap in EUR | J1: index | K1: VOL_AV_3M | L1: Free Float | M1: FFMC_CO | N1: Close Prc | O1: FX/Index Ccy | P1: FFMC_WD | Q1: Price_WD | R1: Subsector Code | S1: Supersector Code | T1: itr_scope123_target | U1: itr_scope12_trend | V1: CDP_climate_score | W1: NBR Overall Flag | X1: Tobacco - Production Maximum Percentage of Revenues (%) | Y1: Tobacco - Distribution Maximum Percentage of Revenues (%) | Z1: Biological Weapons - Overall Flag | AA1: Chemical Weapons - Overall Flag | AB1: Nuclear Weapons Outside NPT - Overall Flag | AC1: Nuclear Weapons Inside NPT - Overall Flag | AD1: Cluster Munitions - Overall Flag | AE1: Depleted Uranium - Overall Flag | AF1: Anti-personnel Mines - Overall Flag | AG1: coal_mining_and_power_gen_maximum_percentage_of_revenues-values | AH1: Fossil Fuel - Total Maximum Percentage of Revenues (%) | AI1: power_generation_thermal_maximum_percentage_of_revenues-values | AJ1: shale_oil_and_or_gas_involvement_tie | AK1: arctic_drilling_share_max-values | AL1: deepwater_drilling_involvement | AM1: HydraulicFracturingInvolvement | AN1: CoalMiningExpInvolved | AO1: OilGasExtractExpInvolved | AP1: OtherFFInfraInvolved | AQ1: NuclearPowerInvolvement | AR1: NuclearPowerRevShareMax-values | AS1: NuclearPowerUraniumRevShareMax-values | AT1: CivFARevShareMax-values | AU1: MilitaryEqmtDistMaxRev-values | AV1: Social Rating (Num) | AW1: Governance Rating (Num) | AX1: NACE | AY1: High_Climate_Impact | AZ1: EU_Taxonomy | BA1: Country_Code | BB1: GAFI_Black_List | BC1: GAFI_Grey_List | BD1: Non_Fiscally_Cooperative | BE1: exclude_gafi_black | BF1: exclude_gafi_grey | BG1: exclude_non_fiscal_coop | BH1: exclude_subsector | BI1: exclude_nbr_red | BJ1: exclude_tobacco_prod | BK1: exclude_tobacco_dist | BL1: exclude_biological_weapons | BM1: exclude_chemical_weapons | BN1: exclude_nuclear_weapons_inside_npt | BO1: exclude_nuclear_weapons_outside_npt | BP1: exclude_cluster_munitions | BQ1: exclude_depleted_uranium | BR1: exclude_anti_personnel_mines | BS1: exclude_coal_mining | BT1: exclude_fossil_fuel | BU1: exclude_thermal_power | BV1: exclude_shale_oil_gas | BW1: exclude_arctic_drilling | BX1: exclude_deepwater_drilling | BY1: exclude_hydraulic_fracturing | BZ1: exclude_coal_mining_expansion | CA1: exclude_oil_gas_extraction_expansion | CB1: exclude_other_fossil_fuel_infra | CC1: exclude_nuclear_power | CD1: exclude_nuclear_power_revenue | CE1: exclude_nuclear_uranium | CF1: exclude_civilian_firearms | CG1: exclude_military_equipment | CH1: SG_Score | CI1: exclude_sg_bottom_10 | CJ1: Excluded | CK1: Exclusion_Reason | CL1: itr_scope123_target_filled | CM1: itr_scope12_trend_filled | CN1: cdp_temperature_score | CO1: bonus_malus | CP1: climate_score | CQ1: PAB_Flag | CR1: Liquidity_Cap | CS1: Liquidity_Floor
A2: 67 | B2: ALO-FR | C2: ALSTOM | D2: FR0010220475 | E2: XPAR | F2: 461510538 | G2: 20.09 | H2: EUR | I2: 9.2717467e+09 | J2: EU500;EZ300 | K2: 23095735 | L2: 0.75 | M2: 6.95381e+09 | N2: 19.87 | O2: 1 | P2: 6.8776608e+09 | Q2: 19.87 | R2: 50202010 | S2: 5020 | T2: 1.9980521 | U2: 3.1 | V2: A | W2: Green | X2: 0 | Y2: 0 | Z2: Green | AA2: Green | AB2: Green | AC2: Green | AD2: Green | AE2: Green | AF2: Green | AG2: 0 | AH2: 0 | AI2: 0 | AK2: 0 | AL2: F | AN2: F | AO2: F | AP2: F | AR2: 0 | AS2: 0 | AT2: 0 | AU2: 0 | AV2: 2.795 | AW2: 3.363 | AX2: C | AY2: 1 | AZ2: 1 | BA2: FR | BB2: 0 | BC2: 0 | BD2: 0 | CH2: 3.079 | CJ2: No | CL2: 1.9980521 | CM2: 3.1 | CN2: 2.5490261 | CO2: -0.3 | CP2: 2.2490261 | CQ2: 0 | CR2: 0.019975527 | CS2: 0
A3: 254 | B3: CAST-SE | C3: CASTELLUM AB | D3: SE0000379190 | E3: XSTO | F3: 492601440 | G3: 10.55657 | H3: SEK | I3: 5.2001816e+09 | J3: EU500 | K3: 15217501 | L3: 0.9 | M3: 4.6801634e+09 | N3: 111.95 | O3: 0.08996851 | P3: 4.4653223e+09 | Q3: 10.071975 | R3: 35101010 | S3: 3510 | T3: 1.9835888 | V3: A | W3: Green | X3: 0 | Y3: 0 | Z3: Green | AA3: Green | AB3: Green | AC3: Green | AD3: Green | AE3: Green | AF3: Green | AG3: 0 | AH3: 0 | AI3: 0 | AK3: 0 | AL3: F | AN3: F | AO3: F | AP3: F | AR3: 0 | AS3: 0 | AT3: 0 | AU3: 0 | AV3: 2.359 | AW3: 2.663 | AX3: L | AY3: 1 | AZ3: 1 | BA3: SE | BB3: 0 | BC3: 0 | BD3: 0 | CH3: 2.511 | CJ3: No | CL3: 1.9835888 | CM3: 3.1 | CN3: 2.5417944 | CO3: -0.3 | CP3: 2.2417944 | CQ3: 0 | CR3: 0.013136057 | CS3: 0
A4: 368 | B4: DSY-FR | C4: DASSAULT SYSTEMES | D4: FR0014003TT8 | E4: XPAR | F4: 1338435363 | G4: 39.72 | H4: EUR | I4: 5.3162653e+10 | J4: EU500;EZ300 | K4: 57311403 | L4: 0.5 | M4: 2.6581326e+10 | N4: 33.54 | O4: 1 | P4: 2.2445561e+10 | Q4: 33.54 | R4: 10101015 | S4: 1010 | T4: 1.9943237 | V4: B | W4: Green | X4: 0 | Y4: 0 | Z4: Green | AA4: Green | AB4: Green | AC4: Green | AD4: Green | AE4: Green | AF4: Green | AG4: 0 | AH4: 0 | AI4: 0 | AK4: 0 | AL4: F | AN4: F | AO4: F | AP4: F | AR4: 0 | AS4: 0 | AT4: 0 | AU4: 0 | AV4: 2.636 | AW4: 3.304 | AX4: J | AY4: 0 | AZ4: 1 | BA4: FR | BB4: 0 | BC4: 0 | BD4: 0 | CH4: 2.97 | CJ4: No | CL4: 1.9943237 | CM4: 3.1 | CN4: 2.5471619 | CO4: -0.18 | CP4: 2.3671619 | CQ4: 0 | CR4: 0.051644106 | CS4: 0
A5: 652 | B5: INPST-NL | C5: INPOST | D5: LU2290522684 | E5: XAMS | F5: 500000000 | G5: 17.46 | H5: EUR | I5: 8730000000 | J5: EU500;EZ300 | K5: 7745434.2 | L5: 0.4 | M5: 3492000000 | N5: 13.22 | O5: 1 | P5: 2644000000 | Q5: 13.22 | R5: 50206040 | S5: 5020 | T5: 3.3134401 | V5: A | W5: Green | X5: 0 | Y5: 0 | Z5: Green | AA5: Green | AB5: Green | AC5: Green | AD5: Green | AE5: Green | AF5: Green | AG5: 0 | AH5: 0 | AI5: 0 | AK5: 0 | AL5: F | AN5: F | AO5: F | AP5: F | AR5: 0 | AS5: 0 | AT5: 0 | AU5: 0 | AV5: 2.05 | AW5: 3.117 | AX5: H | AY5: 1 | AZ5: 1 | BA5: LU | BB5: 0 | BC5: 0 | BD5: 0 | CH5: 2.5835 | CJ5: No | CL5: 3.3134401 | CM5: 3.1 | CN5: 3.2067201 | CO5: -0.3 | CP5: 2.9067201 | CQ5: 0 | CR5: 0.0068292552 | CS5: 0
A6: 748 | B6: KRX-IE | C6: KINGSPAN GROUP PLC | D6: IE0004927939 | E6: XMSM | F6: 181964859 | G6: 75.5 | H6: EUR | I6: 1.3738347e+10 | J6: EU500;EZ300 | K6: 27712784 | L6: 0.85 | M6: 1.1677595e+10 | N6: 74.4 | O6: 1 | P6: 1.1507458e+10 | Q6: 74.4 | R6: 50101035 | S6: 5010 | T6: 1.9783312 | U6: 3.1 | V6: A | W6: Green | X6: 0 | Y6: 0 | Z6: Green | AA6: Green | AB6: Green | AC6: Green | AD6: Green | AE6: Green | AF6: Green | AG6: 0 | AH6: 0 | AI6: 0 | AK6: 0 | AL6: F | AN6: F | AO6: F | AP6: F | AR6: 0 | AS6: 0 | AT6: 0 | AU6: 0 | AV6: 2.108 | AW6: 2.617 | AX6: C | AY6: 1 | AZ6: 1 | BA6: IE | BB6: 0 | BC6: 0 | BD6: 0 | CH6: 2.3625 | CJ6: No | CL6: 1.9783312 | CM6: 3.1 | CN6: 2.5391656 | CO6: -0.3 | CP6: 2.2391656 | CQ6: 0 | CR6: 0.025224706 | CS6: 0
A7: 755 | B7: KBX-DE | C7: KNORR-BREMSE AG | D7: DE000KBX1006 | E7: XETR | F7: 161200000 | G7: 82.2 | H7: EUR | I7: 13250640000 | J7: EU500;EZ300 | K7: 9423306.8 | L7: 0.4 | M7: 5300256000 | N7: 81.25 | O7: 1 | P7: 5239000000 | Q7: 81.25 | R7: 50206025 | S7: 5020 | T7: 1.9989892 | V7: A- | W7: Green | X7: 0 | Y7: 0 | Z7: Green | AA7: Green | AB7: Green | AC7: Green | AD7: Green | AE7: Green | AF7: Green | AG7: 0 | AH7: 0 | AI7: 0 | AK7: 0 | AL7: F | AN7: F | AO7: F | AP7: F | AR7: 0 | AS7: 0 | AT7: 0 | AU7: 0 | AV7: 2.78 | AW7: 2.888 | AX7: C | AY7: 1 | AZ7: 1 | BA7: DE | BB7: 0 | BC7: 0 | BD7: 0 | CH7: 2.834 | CJ7: No | CL7: 1.9989892 | CM7: 3.1 | CN7: 2.5494946 | CO7: -0.24 | CP7: 2.3094946 | CQ7: 0 | CR7: 0.0090889328 | CS7: 0
A8: 865 | B8: METSO-FI | C8: METSO CORPORATION | D8: FI0009014575 | E8: XHEL | F8: 828972400 | G8: 10.98 | H8: EUR | I8: 9102116952 | J8: EU500;EZ300 | K8: 13202646 | L8: 0.85 | M8: 7.7367994e+09 | N8: 8.644 | O8: 1 | P8: 6.0907918e+09 | Q8: 8.644 | R8: 50204020 | S8: 5020 | T8: 1.9935451 | V8: B | W8: Green | X8: 0 | Y8: 0 | Z8: Green | AA8: Green | AB8: Green | AC8: Green | AD8: Green | AE8: Green | AF8: Green | AG8: 0 | AH8: 0 | AI8: 0 | AK8: 0 | AL8: F | AN8: F | AO8: F | AP8: F | AR8: 0 | AS8: 0 | AT8: 0 | AU8: 0 | AV8: 2.559 | AW8: 2.673 | AX8: C | AY8: 1 | AZ8: 1 | BA8: FI | BB8: 0 | BC8: 0 | BD8: 0 | CH8: 2.616 | CJ8: No | CL8: 1.9935451 | CM8: 3.1 | CN8: 2.5467726 | CO8: -0.18 | CP8: 2.3667726 | CQ8: 0 | CR8: 0.012252098 | CS8: 0
A9: 970 | B9: NHY-NO | C9: NORSK HYDRO | D9: NO0005052605 | E9: XOSL | F9: 2009015998 | G9: 5.713564 | H9: NOK | I9: 1.1478641e+10 | J9: EU500 | K9: 22699024 | L9: 0.65 | M9: 7.461117e+09 | N9: 54 | O9: 0.08336807 | P9: 5.8788213e+09 | Q9: 4.5018758 | R9: 55102035 | S9: 5510 | T9: 2.728329 | U9: 1.5 | V9: C | W9: Green | X9: 0 | Y9: 0 | Z9: Green | AA9: Green | AB9: Green | AC9: Green | AD9: Green | AE9: Green | AF9: Green | AG9: 0 | AH9: 0 | AI9: 0 | AK9: 0 | AL9: F | AN9: F | AO9: F | AP9: F | AR9: 0 | AS9: 0 | AT9: 0 | AU9: 0 | AV9: 2.861 | AW9: 3.723 | AX9: C | AY9: 1 | AZ9: 1 | BA9: NO | BB9: 0 | BC9: 0 | BD9: 0 | CH9: 3.292 | CJ9: No | CL9: 2.728329 | CM9: 1.5 | CN9: 2.1141645 | CO9: 0 | CP9: 2.1141645 | CQ9: 0 | CR9: 0.019292594 | CS9: 0
A10: 1092 | B10: RED-ES | C10: REDEIA CORP | D10: ES0173093024 | E10: XMAD | F10: 541080000 | G10: 16.83 | H10: EUR | I10: 9106376400 | J10: EU500;EZ300 | K10: 15311685 | L10: 0.75 | M10: 6829782300 | N10: 19.08 | O10: 1 | P10: 7742854800 | Q10: 19.08 | R10: 65101015 | S10: 6510 | T10: 1.5959603 | V10: A | W10: Green | X10: 0 | Y10: 0 | Z10: Green | AA10: Green | AB10: Green | AC10: Green | AD10: Green | AE10: Green | AF10: Green | AG10: 0 | AH10: 0 | AI10: 0 | AK10: 0 | AL10: F | AN10: F | AO10: F | AP10: F | AR10: 0 | AS10: 0 | AT10: 0 | AU10: 0 | AV10: 2.938 | AW10: 2.874 | AX10: D | AY10: 1 | AZ10: 1 | BA10: ES | BB10: 0 | BC10: 0 | BD10: 0 | CH10: 2.906 | CJ10: No | CL10: 1.5959603 | CM10: 3.1 | CN10: 2.3479802 | CO10: -0.3 | CP10: 2.0479802 | CQ10: 0 | CR10: 0.014471321 | CS10: 0
A11: 1119 | B11: ROCK.B-DK | C11: ROCKWOOL B | D11: DK0063855168 | E11: XCSE | F11: 117541060 | G11: 37.53242 | H11: DKK | I11: 4.4116004e+09 | J11: EU500 | K11: 13834313 | L11: 0.85 | M11: 3.7498604e+09 | N11: 282.2 | O11: 0.13395578 | P11: 3.7768262e+09 | Q11: 37.802321 | R11: 50101035 | S11: 5010 | T11: 1.8363484 | U11: 3.1 | V11: B | W11: Green | X11: 0 | Y11: 0 | Z11: Green | AA11: Green | AB11: Green | AC11: Green | AD11: Green | AE11: Green | AF11: Green | AG11: 0 | AH11: 0 | AI11: 0 | AK11: 0 | AL11: F | AN11: F | AO11: F | AP11: F | AR11: 0 | AS11: 0 | AT11: 0 | AU11: 0 | AV11: 2.152 | AW11: 2.604 | AX11: C | AY11: 1 | AZ11: 1 | BA11: DK | BB11: 0 | BC11: 0 | BD11: 0 | CH11: 2.378 | CJ11: No | CL11: 1.8363484 | CM11: 3.1 | CN11: 2.4681742 | CO11: -0.18 | CP11: 2.2881742 | CQ11: 0 | CR11: 0.011833012 | CS11: 0
A12: 1192 | B12: SVT-GB | C12: SEVERN TRENT | D12: GB00B1FH8J72 | E12: XLON | F12: 300209100 | G12: 29.42568 | H12: GBX | I12: 8.8338569e+09 | J12: EU500 | K12: 14800849 | L12: 0.9 | M12: 7.9504712e+09 | N12: 2699 | O12: 0.01169249 | P12: 8.5266071e+09 | Q12: 31.558031 | R12: 65102030 | S12: 6510 | T12: 1.7824348 | U12: 1.5 | V12: A- | W12: Green | X12: 0 | Y12: 0 | Z12: Green | AA12: Green | AB12: Green | AC12: Green | AD12: Green | AE12: Green | AF12: Green | AG12: 0 | AH12: 0 | AI12: 0 | AK12: 0 | AL12: F | AN12: F | AO12: F | AP12: F | AR12: 0 | AS12: 0 | AT12: 0 | AU12: 0 | AV12: 2.826 | AW12: 3.137 | AX12: E | AY12: 1 | AZ12: 1 | BA12: GB | BB12: 0 | BC12: 0 | BD12: 0 | CH12: 2.9815 | CJ12: No | CL12: 1.7824348 | CM12: 1.5 | CN12: 1.6412174 | CO12: -0.24 | CP12: 1.4012174 | CQ12: 1 | CR12: 0.014390603 | CS12: 0
A13: 1359 | B13: TRN-IT | C13: TERNA | D13: IT0003242622 | E13: MTAA | F13: 2009992000 | G13: 7.826 | H13: EUR | I13: 15730197392 | J13: EU500;EZ300 | K13: 30108575 | L13: 0.7 | M13: 1.1011138e+10 | N13: 8.336 | O13: 1 | P13: 1.1728705e+10 | Q13: 8.336 | R13: 65101015 | S13: 6510 | T13: 1.7449211 | V13: A- | W13: Green | X13: 0 | Y13: 0 | Z13: Green | AA13: Green | AB13: Green | AC13: Green | AD13: Green | AE13: Green | AF13: Green | AG13: 0 | AH13: 0 | AI13: 0 | AK13: 0 | AL13: F | AN13: F | AO13: F | AP13: F | AR13: 0 | AS13: 0 | AT13: 0 | AU13: 0 | AV13: 2.853 | AW13: 3.169 | AX13: D | AY13: 1 | AZ13: 1 | BA13: IT | BB13: 0 | BC13: 0 | BD13: 0 | CH13: 3.011 | CJ13: No | CL13: 1.7449211 | CM13: 3.1 | CN13: 2.4224605 | CO13: -0.24 | CP13: 2.1824605 | CQ13: 0 | CR13: 0.027106918 | CS13: 0
A14: 1462 | B14: VWS-DK | C14: VESTAS WIND SYSTEMS | D14: DK0061539921 | E14: XCSE | F14: 1009867250 | G14: 13.13903 | H14: DKK | I14: 1.3268676e+10 | J14: EU500 | K14: 50667588 | L14: 1 | M14: 1.3268676e+10 | N14: 90.6 | O14: 0.13395578 | P14: 1.2256146e+10 | Q14: 12.136394 | R14: 60102020 | S14: 6010 | T14: 1.9940728 | U14: 3.1 | V14: D | W14: Green | X14: 0 | Y14: 0 | Z14: Green | AA14: Green | AB14: Green | AC14: Green | AD14: Green | AE14: Green | AF14: Green | AG14: 0 | AH14: 0 | AI14: 0 | AK14: 0 | AL14: F | AN14: F | AO14: F | AP14: F | AR14: 0 | AS14: 0 | AT14: 0 | AU14: 0 | AV14: 2.304 | AW14: 3.223 | AX14: C | AY14: 1 | AZ14: 1 | BA14: DK | BB14: 0 | BC14: 0 | BD14: 0 | CH14: 2.7635 | CJ14: No | CL14: 1.9940728 | CM14: 3.1 | CN14: 2.5470364 | CO14: 0.18 | CP14: 2.7270364 | CQ14: 0 | CR14: 0.042729689 | CS14: 0
A15: 1505 | B15: WIE-AT | C15: WIENERBERGER AG | D15: AT0000831706 | E15: WBAH | F15: 111732346 | G15: 29.66 | H15: EUR | I15: 3.3139814e+09 | J15: EU500;EZ300 | K15: 6821360.8 | L15: 1 | M15: 3.3139814e+09 | N15: 30.3 | O15: 1 | P15: 3.3854901e+09 | Q15: 30.3 | R15: 50101035 | S15: 5010 | V15: B | W15: Green | X15: 0 | Y15: 0 | Z15: Green | AA15: Green | AB15: Green | AC15: Green | AD15: Green | AE15: Green | AF15: Green | AG15: 0 | AH15: 0 | AI15: 0 | AK15: 0 | AL15: F | AN15: F | AO15: F | AP15: F | AR15: 0 | AS15: 0 | AT15: 0 | AU15: 0 | AV15: 2.441 | AW15: 3.471 | AX15: C | AY15: 1 | AZ15: 1 | BA15: AT | BB15: 0 | BC15: 0 | BD15: 0 | CH15: 2.956 | CJ15: No | CL15: 3.4 | CM15: 3.1 | CN15: 3.25 | CO15: -0.18 | CP15: 3.07 | CQ15: 0 | CR15: 0.006422302 | CS15: 0
A16: 1139 | B16: SGE-GB | C16: SAGE GROUP PLC/THE | D16: GB00B8C3BL03 | E16: XLON | F16: 995756840 | G16: 15.69208 | H16: GBX | I16: 1.5625496e+10 | J16: EU500 | K16: 29289351 | L16: 1 | M16: 1.5625496e+10 | N16: 1180.5 | O16: 0.01169249 | P16: 1.3744416e+10 | Q16: 13.802984 | R16: 10101015 | S16: 1010 | T16: 1.7465783 | U16: 1.5 | V16: A | W16: Green | X16: 0 | Y16: 0 | Z16: Green | AA16: Green | AB16: Green | AC16: Green | AD16: Green | AE16: Green | AF16: Green | AG16: 0 | AH16: 0 | AI16: 0 | AK16: 0 | AL16: F | AN16: F | AO16: F | AP16: F | AR16: 0 | AS16: 0 | AT16: 0 | AU16: 0 | AV16: 2.41 | AW16: 3.306 | AX16: J | AY16: 0 | AZ16: 0 | BA16: GB | BB16: 0 | BC16: 0 | BD16: 0 | CH16: 2.858 | CJ16: No | CL16: 1.7465783 | CM16: 1.5 | CN16: 1.6232892 | CO16: -0.3 | CP16: 1.3232892 | CQ16: 1 | CR16: 0.014090048 | CS16: 0
A17: 1098 | B17: REN-NL | C17: RELX | D17: GB00B2B0DG97 | E17: XAMS | F17: 1907070957 | G17: 47.26 | H17: EUR | I17: 9.0128173e+10 | J17: EU500;EZ300 | K17: 34161920 | L17: 1 | M17: 9.0128173e+10 | N17: 45.6 | O17: 1 | P17: 8.6962436e+10 | Q17: 45.6 | R17: 10101010 | S17: 1010 | T17: 1.9831747 | U17: 1.5 | V17: B | W17: Green | X17: 0 | Y17: 0 | Z17: Green | AA17: Green | AB17: Green | AC17: Green | AD17: Green | AE17: Green | AF17: Green | AG17: 0 | AH17: 0 | AI17: 0 | AK17: 0 | AL17: F | AN17: F | AO17: F | AP17: F | AR17: 0 | AS17: 0 | AT17: 0 | AU17: 0 | AV17: 2.474 | AW17: 3.295 | AX17: M | AY17: 0 | AZ17: 0 | BA17: GB | BB17: 0 | BC17: 0 | BD17: 0 | CH17: 2.8845 | CJ17: No | CL17: 1.9831747 | CM17: 1.5 | CN17: 1.7415873 | CO17: -0.18 | CP17: 1.5615873 | CQ17: 1 | CR17: 0.043802775 | CS17: 0.023305623
A18: 119 | B18: ASM-NL | C18: ASM INTERNATIONAL | D18: NL0000334118 | E18: XAMS | F18: 49328548 | G18: 569.8 | H18: EUR | I18: 2.8107407e+10 | J18: EU500;EZ300 | K18: 78679459 | L18: 0.95 | M18: 2.6702036e+10 | N18: 408 | O18: 1 | P18: 1.9119745e+10 | Q18: 408 | R18: 10102020 | S18: 1010 | T18: 1.7486641 | U18: 3.1 | V18: A | W18: Green | X18: 0 | Y18: 0 | Z18: Green | AA18: Green | AB18: Green | AC18: Green | AD18: Green | AE18: Green | AF18: Green | AG18: 0 | AH18: 0 | AI18: 0 | AK18: 0 | AL18: F | AN18: F | AO18: F | AP18: F | AR18: 0 | AS18: 0 | AT18: 0 | AU18: 0 | AV18: 2.446 | AW18: 3.219 | AX18: C | AY18: 1 | AZ18: 0 | BA18: NL | BB18: 0 | BC18: 0 | BD18: 0 | CH18: 2.8325 | CJ18: No | CL18: 1.7486641 | CM18: 3.1 | CN18: 2.4243321 | CO18: -0.3 | CP18: 2.1243321 | CQ18: 0 | CR18: 0.030981135 | CS18: 0
A19: 805 | B19: LOGN-CH | C19: LOGITECH INTL SA | D19: CH0025751329 | E19: XSWX | F19: 168994140 | G19: 99.48116 | H19: CHF | I19: 1.6811733e+10 | J19: EU500 | K19: 53427463 | L19: 0.9 | M19: 1.513056e+10 | N19: 59.66 | O19: 1.079797 | P19: 9.798047e+09 | Q19: 64.420689 | R19: 10102030 | S19: 1010 | T19: 1.7497523 | V19: A | W19: Green | X19: 0 | Y19: 0 | Z19: Green | AA19: Green | AB19: Green | AC19: Green | AD19: Green | AE19: Green | AF19: Green | AG19: 0 | AH19: 0 | AI19: 0 | AK19: 0 | AL19: F | AN19: F | AO19: F | AP19: F | AR19: 0 | AS19: 0 | AT19: 0 | AU19: 0 | AV19: 2.565 | AW19: 3.4 | AX19: C | AY19: 1 | AZ19: 0 | BA19: CH | BB19: 0 | BC19: 0 | BD19: 0 | CH19: 2.9825 | CJ19: No | CL19: 1.7497523 | CM19: 3.1 | CN19: 2.4248762 | CO19: -0.3 | CP19: 2.1248762 | CQ19: 0 | CR19: 0.019808786 | CS19: 0
A20: 1348 | B20: TEF-ES | C20: TELEFONICA | D20: ES0178430E18 | E20: XMAD | F20: 5670161600 | G20: 4.174 | H20: EUR | I20: 2.3667255e+10 | J20: EU500;EZ300 | K20: 53268601 | L20: 0.7 | M20: 1.6567078e+10 | N20: 4.166 | O20: 1 | P20: 1.6535325e+10 | Q20: 4.166 | R20: 15102015 | S20: 1510 | T20: 1.7233601 | U20: 1.5 | V20: A | W20: Green | X20: 0 | Y20: 0 | Z20: Green | AA20: Green | AB20: Green | AC20: Green | AD20: Green | AE20: Green | AF20: Green | AG20: 0 | AH20: 0 | AI20: 0 | AK20: 0 | AL20: F | AN20: F | AO20: F | AP20: F | AR20: 0 | AS20: 0 | AT20: 0 | AU20: 0 | AV20: 3.103 | AW20: 2.885 | AX20: J | AY20: 0 | AZ20: 0 | BA20: ES | BB20: 0 | BC20: 0 | BD20: 0 | CH20: 2.994 | CJ20: No | CL20: 1.7233601 | CM20: 1.5 | CN20: 1.61168 | CO20: -0.3 | CP20: 1.31168 | CQ20: 1 | CR20: 0.022360687 | CS20: 0
A21: 1471 | B21: VOD-GB | C21: VODAFONE GROUP | D21: GB00BH4HKS39 | E21: XLON | F21: 25081295000 | G21: 0.8003203 | H21: GBX | I21: 2.007307e+10 | J21: EU500 | K21: 51438057 | L21: 0.8 | M21: 1.6058456e+10 | N21: 69.26 | O21: 0.01169249 | P21: 1.6249105e+10 | Q21: 0.80982186 | R21: 15102015 | S21: 1510 | T21: 1.7280905 | U21: 1.5 | V21: A | W21: Green | X21: 0 | Y21: 0 | Z21: Green | AA21: Green | AB21: Green | AC21: Green | AD21: Green | AE21: Green | AF21: Green | AG21: 0 | AH21: 0 | AI21: 0 | AK21: 0 | AL21: F | AN21: F | AO21: F | AP21: F | AR21: 0 | AS21: 0 | AT21: 0 | AU21: 0 | AV21: 2.765 | AW21: 3.141 | AX21: J | AY21: 0 | AZ21: 0 | BA21: GB | BB21: 0 | BC21: 0 | BD21: 0 | CH21: 2.953 | CJ21: No | CL21: 1.7280905 | CM21: 1.5 | CN21: 1.6140453 | CO21: -0.3 | CP21: 1.3140453 | CQ21: 1 | CR21: 0.021701086 | CS21: 0
A22: 1002 | B22: ORA-FR | C22: ORANGE | D22: FR0000133308 | E22: XPAR | F22: 2660056599 | G22: 11.075 | H22: EUR | I22: 2.9460127e+10 | J22: EU500;EZ300 | K22: 71522746 | L22: 0.65 | M22: 1.9149082e+10 | N22: 12.39 | O22: 1 | P22: 2.1422766e+10 | Q22: 12.39 | R22: 15102015 | S22: 1510 | T22: 1.7104133 | U22: 2.39 | V22: B | W22: Green | X22: 0 | Y22: 0 | Z22: Green | AA22: Green | AB22: Green | AC22: Green | AD22: Green | AE22: Green | AF22: Green | AG22: 0 | AH22: 0 | AI22: 0 | AK22: 0 | AL22: F | AN22: F | AO22: F | AP22: F | AR22: 0 | AS22: 0 | AT22: 0 | AU22: 0 | AV22: 2.716 | AW22: 2.747 | AX22: J | AY22: 0 | AZ22: 0 | BA22: FR | BB22: 0 | BC22: 0 | BD22: 0 | CH22: 2.7315 | CJ22: No | CL22: 1.7104133 | CM22: 2.39 | CN22: 2.0502067 | CO22: -0.18 | CP22: 1.8702067 | CQ22: 0 | CR22: 0.029722735 | CS22: 0
A23: 1350 | B23: TEL-NO | C23: TELENOR | D23: NO0010063308 | E23: XOSL | F23: 1368349989 | G23: 12.14261 | H23: NOK | I23: 1.661534e+10 | J23: EU500 | K23: 14604406 | L23: 0.45 | M23: 7.4769031e+09 | N23: 146.7 | O23: 0.08336807 | P23: 7.5307732e+09 | Q23: 12.230096 | R23: 15102015 | S23: 1510 | T23: 1.6924228 | U23: 2.7 | V23: A- | W23: Green | X23: 0 | Y23: 0 | Z23: Green | AA23: Green | AB23: Green | AC23: Green | AD23: Green | AE23: Green | AF23: Green | AG23: 0 | AH23: 0 | AI23: 0 | AK23: 0 | AL23: F | AN23: F | AO23: F | AP23: F | AR23: 0 | AS23: 0 | AT23: 0 | AU23: 0 | AV23: 2.337 | AW23: 2.934 | AX23: J | AY23: 0 | AZ23: 0 | BA23: NO | BB23: 0 | BC23: 0 | BD23: 0 | CH23: 2.6355 | CJ23: No | CL23: 1.6924228 | CM23: 2.7 | CN23: 2.1962114 | CO23: -0.24 | CP23: 1.9562114 | CQ23: 0 | CR23: 0.0072870485 | CS23: 0
A24: 976 | B24: NSIS.B-DK | C24: NOVONESIS | D24: DK0060336014 | E24: XCSE | F24: 414555050 | G24: 53.64455 | H24: DKK | I24: 2.2238619e+10 | J24: EU500 | K24: 28551145 | L24: 0.85 | M24: 1.8902826e+10 | N24: 410 | O24: 0.13395578 | P24: 1.9352918e+10 | Q24: 54.92187 | R24: 20103010 | S24: 2010 | T24: 1.704606 | U24: 1.5 | V24: A | W24: Green | X24: 0 | Y24: 0 | Z24: Green | AA24: Green | AB24: Green | AC24: Green | AD24: Green | AE24: Green | AF24: Green | AG24: 0 | AH24: 0 | AI24: 0 | AK24: 0 | AL24: F | AN24: F | AO24: F | AP24: F | AR24: 0 | AS24: 0 | AT24: 0 | AU24: 0 | AV24: 2.575 | AW24: 2.876 | AX24: C | AY24: 1 | AZ24: 0 | BA24: DK | BB24: 0 | BC24: 0 | BD24: 0 | CH24: 2.7255 | CJ24: No | CL24: 1.704606 | CM24: 1.5 | CN24: 1.602303 | CO24: -0.3 | CP24: 1.302303 | CQ24: 1 | CR24: 0.01603261 | CS24: 0
A25: 566 | B25: GSK-GB | C25: GSK PLC | D25: GB00BN7SWP63 | E25: XLON | F25: 4145945300 | G25: 17.2758 | H25: GBX | I25: 7.1624522e+10 | J25: EU500 | K25: 94231735 | L25: 1 | M25: 7.1624522e+10 | N25: 1346 | O25: 0.01169249 | P25: 6.5249267e+10 | Q25: 15.738092 | R25: 20103015 | S25: 2010 | T25: 1.7306923 | U25: 1.5 | V25: A | W25: Green | X25: 0 | Y25: 0 | Z25: Green | AA25: Green | AB25: Green | AC25: Green | AD25: Green | AE25: Green | AF25: Green | AG25: 0 | AH25: 0 | AI25: 0 | AK25: 0 | AL25: F | AN25: F | AO25: F | AP25: F | AR25: 0 | AS25: 0 | AT25: 0 | AU25: 0 | AV25: 3.198 | AW25: 2.788 | AX25: C | AY25: 1 | AZ25: 0 | BA25: GB | BB25: 0 | BC25: 0 | BD25: 0 | CH25: 2.993 | CJ25: No | CL25: 1.7306923 | CM25: 1.5 | CN25: 1.6153462 | CO25: -0.3 | CP25: 1.3153462 | CQ25: 1 | CR25: 0.053445758 | CS25: 0
A26: 974 | B26: NOVN-CH | C26: NOVARTIS | D26: CH0012005267 | E26: XSWX | F26: 2189930400 | G26: 104.3617 | H26: CHF | I26: 2.2854486e+11 | J26: EU500 | K26: 3.4805244e+08 | L26: 0.95 | M26: 2.1711762e+11 | N26: 90.2 | O26: 1.079797 | P26: 2.0262945e+11 | Q26: 97.397689 | R26: 20103015 | S26: 2010 | T26: 1.7351436 | U26: 1.5 | V26: A | W26: Green | X26: 0 | Y26: 0 | Z26: Green | AA26: Green | AB26: Green | AC26: Green | AD26: Green | AE26: Green | AF26: Green | AG26: 0 | AH26: 0 | AI26: 0 | AK26: 0 | AL26: F | AN26: F | AO26: F | AP26: F | AR26: 0 | AS26: 0 | AT26: 0 | AU26: 0 | AV26: 2.978 | AW26: 2.973 | AX26: C | AY26: 1 | AZ26: 0 | BA26: CH | BB26: 0 | BC26: 0 | BD26: 0 | CH26: 2.9755 | CJ26: No | CL26: 1.7351436 | CM26: 1.5 | CN26: 1.6175718 | CO26: -0.3 | CP26: 1.3175718 | CQ26: 1 | CR26: 0.1 | CS26: 0
A27: 126 | B27: AZN-GB | C27: ASTRAZENECA | D27: GB0009895292 | E27: XLON | F27: 1550581200 | G27: 141.5431 | H27: GBX | I27: 2.1947407e+11 | J27: EU500 | K27: 1.7576966e+08 | L27: 1 | M27: 2.1947407e+11 | N27: 10280 | O27: 0.01169249 | P27: 1.86378e+11 | Q27: 120.1988 | R27: 20103015 | S27: 2010 | T27: 1.7400925 | U27: 1.5 | V27: A | W27: Green | X27: 0 | Y27: 0 | Z27: Green | AA27: Green | AB27: Green | AC27: Green | AD27: Green | AE27: Green | AF27: Green | AG27: 0 | AH27: 0 | AI27: 0 | AK27: 0 | AL27: F | AN27: F | AO27: F | AP27: F | AR27: 0 | AS27: 0 | AT27: 0 | AU27: 0 | AV27: 2.777 | AW27: 2.399 | AX27: C | AY27: 1 | AZ27: 0 | BA27: GB | BB27: 0 | BC27: 0 | BD27: 0 | CH27: 2.588 | CJ27: No | CL27: 1.7400925 | CM27: 1.5 | CN27: 1.6200463 | CO27: -0.3 | CP27: 1.3200463 | CQ27: 1 | CR27: 0.1 | CS27: 0.019182503
A28: 1151 | B28: SAN-FR | C28: SANOFI | D28: FR0000120578 | E28: XPAR | F28: 1263122721 | G28: 104.12 | H28: EUR | I28: 1.3151634e+11 | J28: EU500;EZ300 | K28: 1.5479623e+08 | L28: 0.95 | M28: 1.2494052e+11 | N28: 91.62 | O28: 1 | P28: 1.0994094e+11 | Q28: 91.62 | R28: 20103015 | S28: 2010 | T28: 1.7231997 | U28: 1.5 | V28: A- | W28: Green | X28: 0 | Y28: 0 | Z28: Green | AA28: Green | AB28: Green | AC28: Green | AD28: Green | AE28: Green | AF28: Green | AG28: 0 | AH28: 0 | AI28: 0 | AK28: 0 | AL28: F | AN28: F | AO28: F | AP28: F | AR28: 0 | AS28: 0 | AT28: 0 | AU28: 0 | AV28: 2.98 | AW28: 2.774 | AX28: C | AY28: 1 | AZ28: 0 | BA28: FR | BB28: 0 | BC28: 0 | BD28: 0 | CH28: 2.877 | CJ28: No | CL28: 1.7231997 | CM28: 1.5 | CN28: 1.6115998 | CO28: -0.24 | CP28: 1.3715998 | CQ28: 1 | CR28: 0.088859254 | CS28: 0
A29: 1426 | B29: UCB-BE | C29: UCB | D29: BE0003739530 | E29: XBRU | F29: 194505658 | G29: 181.8 | H29: EUR | I29: 3.5361129e+10 | J29: EU500;EZ300 | K29: 36834331 | L29: 0.65 | M29: 2.2984734e+10 | N29: 142.5 | O29: 1 | P29: 1.8016087e+10 | Q29: 142.5 | R29: 20103015 | S29: 2010 | T29: 1.7415642 | U29: 1.77 | V29: A- | W29: Green | X29: 0 | Y29: 0 | Z29: Green | AA29: Green | AB29: Green | AC29: Green | AD29: Green | AE29: Green | AF29: Green | AG29: 0 | AH29: 0 | AI29: 0 | AK29: 0 | AL29: F | AN29: F | AO29: F | AP29: F | AR29: 0 | AS29: 0 | AT29: 0 | AU29: 0 | AV29: 2.661 | AW29: 2.861 | AX29: M | AY29: 0 | AZ29: 0 | BA29: BE | BB29: 0 | BC29: 0 | BD29: 0 | CH29: 2.761 | CJ29: No | CL29: 1.7415642 | CM29: 1.77 | CN29: 1.7557821 | CO29: -0.24 | CP29: 1.5157821 | CQ29: 1 | CR29: 0.018001753 | CS29: 0
A30: 322 | B30: CTEC-GB | C30: CONVATEC GROUP PLC | D30: GB00BD3VFW73 | E30: XLON | F30: 2049789600 | G30: 2.990925 | H30: GBX | I30: 6.130767e+09 | J30: EU500 | K30: 9155054.9 | L30: 0.8 | M30: 4.9046136e+09 | N30: 259 | O30: 0.01169249 | P30: 4.9659923e+09 | Q30: 3.0283549 | R30: 20102015 | S30: 2010 | T30: 1.9742318 | U30: 1.5 | V30: B | W30: Green | X30: 0 | Y30: 0 | Z30: Green | AA30: Green | AB30: Green | AC30: Green | AD30: Green | AE30: Green | AF30: Green | AG30: 0 | AH30: 0 | AI30: 0 | AK30: 0 | AL30: F | AN30: F | AO30: F | AP30: F | AR30: 0 | AS30: 0 | AT30: 0 | AU30: 0 | AV30: 2.786 | AW30: 3.001 | AX30: C | AY30: 1 | AZ30: 0 | BA30: GB | BB30: 0 | BC30: 0 | BD30: 0 | CH30: 2.8935 | CJ30: No | CL30: 1.9742318 | CM30: 1.5 | CN30: 1.7371159 | CO30: -0.18 | CP30: 1.5571159 | CQ30: 1 | CR30: 0.00466263 | CS30: 0
A31: 73 | B31: AMBU.B-DK | C31: AMBU A/S CLASS B | D31: DK0060946788 | E31: XCSE | F31: 234974400 | G31: 18.71929 | H31: DKK | I31: 4.3985539e+09 | J31: EU500 | K31: 7606684.2 | L31: 0.85 | M31: 3.7387708e+09 | N31: 117.9 | O31: 0.13395578 | P31: 3.1543853e+09 | Q31: 15.793386 | R31: 20102010 | S31: 2010 | T31: 1.9159909 | U31: 1.5 | V31: D | W31: Green | X31: 0 | Y31: 0 | Z31: Green | AA31: Green | AB31: Green | AC31: Green | AD31: Green | AE31: Green | AF31: Green | AG31: 0 | AH31: 0 | AI31: 0 | AK31: 0 | AL31: F | AN31: F | AO31: F | AP31: F | AR31: 0 | AS31: 0 | AT31: 0 | AU31: 0 | AV31: 2.627 | AW31: 2.753 | AX31: C | AY31: 1 | AZ31: 0 | BA31: DK | BB31: 0 | BC31: 0 | BD31: 0 | CH31: 2.69 | CJ31: No | CL31: 1.9159909 | CM31: 1.5 | CN31: 1.7079955 | CO31: 0.18 | CP31: 1.8879955 | CQ31: 1 | CR31: 0.0034991155 | CS31: 0
... A44: 1431 | B44: UCG-IT | C44: UNICREDIT | D44: IT0005239360 | E44: MTAA | F44: 1557675176 | G44: 47.785 | H44: EUR | I44: 7.4433508e+10 | J44: EU500;EZ300 | K44: 3.2895438e+08 | L44: 1 | M44: 7.4433508e+10 | N44: 49.65 | O44: 1 | P44: 7.7338572e+10 | Q44: 49.65 | R44: 30101010 | S44: 3010 | T44: 3.4 | U44: 1.5 | V44: B | W44: Green | X44: 0 | Y44: 0 | Z44: Green | AA44: Green | AB44: Green | AC44: Green | AD44: Green | AE44: Green | AF44: Green | AG44: 0 | AH44: 0 | AI44: 0 | AK44: 0 | AL44: F | AN44: F | AO44: F | AP44: F | AR44: 0 | AS44: 0 | AT44: 0 | AU44: 0 | AV44: 2.355 | AW44: 3.066 | AX44: K | AY44: 0 | AZ44: 0 | BA44: IT | BB44: 0 | BC44: 0 | BD44: 0 | CH44: 2.7105 | CJ44: No | CL44: 3.4 | CM44: 1.5 | CN44: 2.45 | CO44: -0.18 | CP44: 2.27 | CQ44: 0 | CR44: 0.1 | CS44: 0
A45: 919 | B45: NWG-GB | C45: NATWEST GROUP | D45: GB00BM8PJY71 | E45: XLON | F45: 8058562000 | G45: 5.462005 | H45: GBX | I45: 4.4015906e+10 | J45: EU500 | K45: 81343299 | L45: 0.9 | M45: 3.9614315e+10 | N45: 456.9 | O45: 0.01169249 | P45: 3.8746121e+10 | Q45: 5.3422987 | R45: 30101010 | S45: 3010 | T45: 1.9993422 | V45: A- | W45: Green | X45: 0 | Y45: 0 | Z45: Green | AA45: Green | AB45: Green | AC45: Green | AD45: Green | AE45: Green | AF45: Green | AG45: 0 | AH45: 0 | AI45: 0 | AK45: 0 | AL45: F | AN45: F | AO45: F | AP45: F | AR45: 0 | AS45: 0 | AT45: 0 | AU45: 0 | AV45: 2.414 | AW45: 2.734 | AX45: K | AY45: 0 | AZ45: 0 | BA45: GB | BB45: 0 | BC45: 0 | BD45: 0 | CH45: 2.574 | CJ45: No | CL45: 1.9993422 | CM45: 3.1 | CN45: 2.5496711 | CO45: -0.24 | CP45: 2.3096711 | CQ45: 0 | CR45: 0.039353066 | CS45: 0
A46: 165 | B46: BIRG-IE | C46: BANK OF IRELAND GP | D46: IE00BD1RP616 | E46: XMSM | F46: 1003409101 | G46: 10.44 | H46: EUR | I46: 1.0475591e+10 | J46: EU500;EZ300 | K46: 17800026 | L46: 1 | M46: 1.0475591e+10 | N46: 10.49 | O46: 1 | P46: 1.0525761e+10 | Q46: 10.49 | R46: 30101010 | S46: 3010 | T46: 1.9796332 | V46: C | W46: Green | X46: 0 | Y46: 0 | Z46: Green | AA46: Green | AB46: Green | AC46: Green | AD46: Green | AE46: Green | AF46: Green | AG46: 0 | AH46: 0 | AI46: 0 | AK46: 0 | AL46: F | AN46: F | AO46: F | AP46: F | AR46: 0 | AS46: 0 | AT46: 0 | AU46: 0 | AV46: 2.317 | AW46: 2.543 | AX46: K | AY46: 0 | AZ46: 0 | BA46: IE | BB46: 0 | BC46: 0 | BD46: 0 | CH46: 2.43 | CJ46: No | CL46: 1.9796332 | CM46: 3.1 | CN46: 2.5398166 | CO46: 0 | CP46: 2.5398166 | CQ46: 0 | CR46: 0.0094013419 | CS46: 0
A47: 712 | B47: BAER-CH | C47: JULIUS BAER GRUPPE | D47: CH0102484968 | E47: XSWX | F47: 206001790 | G47: 62.62763 | H47: CHF | I47: 1.2901404e+10 | J47: EU500 | K47: 34741509 | L47: 1 | M47: 1.2901404e+10 | N47: 49.83 | O47: 1.079797 | P47: 1.1084191e+10 | Q47: 53.806285 | R47: 30202010 | S47: 3020 | T47: 1.9981675 | U47: 2.7 | V47: B | W47: Green | X47: 0 | Y47: 0 | Z47: Green | AA47: Green | AB47: Green | AC47: Green | AD47: Green | AE47: Green | AF47: Green | AG47: 0 | AH47: 0 | AI47: 0 | AK47: 0 | AL47: F | AN47: F | AO47: F | AP47: F | AR47: 0 | AS47: 0 | AT47: 0 | AU47: 0 | AV47: 2.184 | AW47: 2.667 | AX47: K | AY47: 0 | AZ47: 0 | BA47: CH | BB47: 0 | BC47: 0 | BD47: 0 | CH47: 2.4255 | CJ47: No | CL47: 1.9981675 | CM47: 2.7 | CN47: 2.3490837 | CO47: -0.18 | CP47: 2.1690837 | CQ47: 0 | CR47: 0.014699255 | CS47: 0
A48: 533 | B48: GBLB-BE | C48: GBL | D48: BE0003797140 | E48: XBRU | F48: 138400000 | G48: 68.55 | H48: EUR | I48: 9487320000 | J48: EU500;EZ300 | K48: 6900889.3 | L48: 0.55 | M48: 5218026000 | N48: 68.6 | O48: 1 | P48: 5221832000 | Q48: 68.6 | R48: 30202000 | S48: 3020 | T48: 1.8920545 | V48: A | W48: Green | X48: 0 | Y48: 0 | Z48: Green | AA48: Green | AB48: Green | AC48: Green | AD48: Green | AE48: Green | AF48: Green | AG48: 0 | AH48: 0 | AI48: 0 | AK48: 0 | AL48: F | AN48: F | AO48: F | AP48: F | AR48: 0 | AS48: 0 | AT48: 0 | AU48: 0 | AV48: 2.205 | AW48: 2.864 | AX48: K | AY48: 0 | AZ48: 0 | BA48: BE | BB48: 0 | BC48: 0 | BD48: 0 | CH48: 2.5345 | CJ48: No | CL48: 1.8920545 | CM48: 3.1 | CN48: 2.4960272 | CO48: -0.3 | CP48: 2.1960272 | CQ48: 0 | CR48: 0.0040850953 | CS48: 0
A49: 384 | B49: DB1-DE | C49: DEUTSCHE BOERSE AG | D49: DE0005810055 | E49: XETR | F49: 188300000 | G49: 246.4 | H49: EUR | I49: 46397120000 | J49: EU500;EZ300 | K49: 64953417 | L49: 1 | M49: 46397120000 | N49: 271.1 | O49: 1 | P49: 5.104813e+10 | Q49: 271.1 | R49: 30202015 | S49: 3020 | T49: 1.7390817 | V49: B | W49: Green | X49: 0 | Y49: 0 | Z49: Green | AA49: Green | AB49: Green | AC49: Green | AD49: Green | AE49: Green | AF49: Green | AG49: 0 | AH49: 0 | AI49: 0 | AK49: 0 | AL49: F | AN49: F | AO49: F | AP49: F | AR49: 0 | AS49: 0 | AT49: 0 | AU49: 0 | AV49: 2.382 | AW49: 3.231 | AX49: K | AY49: 0 | AZ49: 0 | BA49: DE | BB49: 0 | BC49: 0 | BD49: 0 | CH49: 2.8065 | CJ49: No | CL49: 1.7390817 | CM49: 3.1 | CN49: 2.4195408 | CO49: -0.18 | CP49: 2.2395408 | CQ49: 0 | CR49: 0.039182796 | CS49: 0.00021074519
A50: 806 | B50: LSEG-GB | C50: LONDON STOCK EXCHANG | D50: GB00B0SWJX34 | E50: XLON | F50: 531451840 | G50: 140.0561 | H50: GBX | I50: 7.4433072e+10 | J50: EU500 | K50: 76651155 | L50: 0.95 | M50: 7.0711418e+10 | N50: 11390 | O50: 0.01169249 | P50: 6.7238536e+10 | Q50: 133.17746 | R50: 30201030 | S50: 3020 | T50: 1.9964408 | V50: A- | W50: Green | X50: 0 | Y50: 0 | Z50: Green | AA50: Green | AB50: Green | AC50: Green | AD50: Green | AE50: Green | AF50: Green | AG50: 0 | AH50: 0 | AI50: 0 | AK50: 0 | AL50: F | AN50: F | AO50: F | AP50: F | AR50: 0 | AS50: 0 | AT50: 0 | AU50: 0 | AV50: 2.301 | AW50: 3.03 | AX50: K | AY50: 0 | AZ50: 0 | BA50: GB | BB50: 0 | BC50: 0 | BD50: 0 | CH50: 2.6655 | CJ50: No | CL50: 1.9964408 | CM50: 3.1 | CN50: 2.5482204 | CO50: -0.24 | CP50: 2.3082204 | CQ50: 0 | CR50: 0.048939138 | CS50: 0.0029484444
A51: 660 | B51: ICG-GB | C51: INTERMEDIATE CAPITAL | D51: GB00BYT1DJ19 | E51: XLON | F51: 290636470 | G51: 28.9421 | H51: GBX | I51: 8.4116298e+09 | J51: EU500 | K51: 15022769 | L51: 1 | M51: 8.4116298e+09 | N51: 1816 | O51: 0.01169249 | P51: 6.1712475e+09 | Q51: 21.233562 | R51: 30202010 | S51: 3020 | T51: 1.9965142 | V51: A- | W51: Green | X51: 0 | Y51: 0 | Z51: Green | AA51: Green | AB51: Green | AC51: Green | AD51: Green | AE51: Green | AF51: Green | AG51: 0 | AH51: 0 | AI51: 0 | AK51: 0 | AL51: F | AN51: F | AO51: F | AP51: F | AR51: 0 | AS51: 0 | AT51: 0 | AU51: 0 | AV51: 2.117 | AW51: 2.916 | AX51: K | AY51: 0 | AZ51: 0 | BA51: GB | BB51: 0 | BC51: 0 | BD51: 0 | CH51: 2.5165 | CJ51: No | CL51: 1.9965142 | CM51: 3.1 | CN51: 2.5482571 | CO51: -0.24 | CP51: 2.3082571 | CQ51: 0 | CR51: 0.0068879882 | CS51: 0
A52: 470 | B52: ENX-FR | C52: EURONEXT | D52: NL0006294274 | E52: XPAR | F52: 104235507 | G52: 119 | H52: EUR | I52: 12404025333 | J52: EU500;EZ300 | K52: 23304183 | L52: 0.75 | M52: 9.303019e+09 | N52: 138 | O52: 1 | P52: 1.0788375e+10 | Q52: 138 | R52: 30202015 | S52: 3020 | T52: 1.9783808 | U52: 3.1 | V52: B | W52: Green | X52: 0 | Y52: 0 | Z52: Green | AA52: Green | AB52: Green | AC52: Green | AD52: Green | AE52: Green | AF52: Green | AG52: 0 | AH52: 0 | AI52: 0 | AK52: 0 | AL52: F | AN52: F | AO52: F | AP52: F | AR52: 0 | AS52: 0 | AT52: 0 | AU52: 0 | AV52: 2.37 | AW52: 3.108 | AX52: K | AY52: 0 | AZ52: 0 | BA52: NL | BB52: 0 | BC52: 0 | BD52: 0 | CH52: 2.739 | CJ52: No | CL52: 1.9783808 | CM52: 3.1 | CN52: 2.5391904 | CO52: -0.18 | CP52: 2.3591904 | CQ52: 0 | CR52: 0.011153918 | CS52: 0
A53: 786 | B53: LGEN-GB | C53: LEGAL AND GENERAL | D53: GB0005603997 | E53: XLON | F53: 5893244000 | G53: 2.878494 | H53: GBX | I53: 1.6963667e+10 | J53: EU500 | K53: 32798434 | L53: 1 | M53: 1.6963667e+10 | N53: 243 | O53: 0.01169249 | P53: 1.6744327e+10 | Q53: 2.8412751 | R53: 30301010 | S53: 3030 | T53: 1.9883504 | U53: 1.5 | V53: A | W53: Green | X53: 0 | Y53: 0 | Z53: Green | AA53: Green | AB53: Green | AC53: Green | AD53: Green | AE53: Green | AF53: Green | AG53: 0 | AH53: 0 | AI53: 0 | AK53: 0 | AL53: F | AN53: F | AO53: F | AP53: F | AR53: 0 | AS53: 0 | AT53: 0 | AU53: 0 | AV53: 2.244 | AW53: 2.638 | AX53: K | AY53: 0 | AZ53: 0 | BA53: GB | BB53: 0 | BC53: 0 | BD53: 0 | CH53: 2.441 | CJ53: No | CL53: 1.9883504 | CM53: 1.5 | CN53: 1.7441752 | CO53: -0.3 | CP53: 1.4441752 | CQ53: 1 | CR53: 0.016300279 | CS53: 0
A54: 543 | B54: G-IT | C54: GENERALI | D54: IT0000062072 | E54: MTAA | F54: 1569420004 | G54: 31.33 | H54: EUR | I54: 4.9169929e+10 | J54: EU500;EZ300 | K54: 1.0440709e+08 | L54: 0.7 | M54: 3.441895e+10 | N54: 30.37 | O54: 1 | P54: 3.33643e+10 | Q54: 30.37 | R54: 30302010 | S54: 3030 | T54: 2.9259268 | U54: 1.5 | V54: B | W54: Green | X54: 0 | Y54: 0 | Z54: Green | AA54: Green | AB54: Green | AC54: Green | AD54: Green | AE54: Green | AF54: Green | AG54: 0 | AH54: 0 | AI54: 0 | AK54: 0 | AL54: F | AN54: F | AO54: F | AP54: F | AR54: 0 | AS54: 0 | AT54: 0 | AU54: 0 | AV54: 2.379 | AW54: 3.209 | AX54: K | AY54: 0 | AZ54: 0 | BA54: IT | BB54: 0 | BC54: 0 | BD54: 0 | CH54: 2.794 | CJ54: No | CL54: 2.9259268 | CM54: 1.5 | CN54: 2.2129634 | CO54: -0.18 | CP54: 2.0329634 | CQ54: 0 | CR54: 0.044195644 | CS54: 0
A55: 1277 | B55: STB-NO | C55: STOREBRAND | D55: NO0003053605 | E55: XOSL | F55: 447972681 | G55: 10.61189 | H55: NOK | I55: 4.7538368e+09 | J55: EU500 | K55: 7342922.2 | L55: 1 | M55: 4.7538368e+09 | N55: 121 | O55: 0.08336807 | P55: 4.5189408e+09 | Q55: 10.087536 | R55: 30301010 | S55: 3030 | T55: 1.9999941 | V55: A- | W55: Green | X55: 0 | Y55: 0 | Z55: Green | AA55: Green | AB55: Green | AC55: Green | AD55: Green | AE55: Green | AF55: Green | AG55: 0 | AH55: 0 | AI55: 0 | AK55: 0 | AL55: F | AN55: F | AO55: F | AP55: F | AR55: 0 | AS55: 0 | AT55: 0 | AU55: 0 | AV55: 2.201 | AW55: 3.418 | AX55: K | AY55: 0 | AZ55: 0 | BA55: NO | BB55: 0 | BC55: 0 | BD55: 0 | CH55: 2.8095 | CJ55: No | CL55: 1.9999941 | CM55: 3.1 | CN55: 2.5499971 | CO55: -0.24 | CP55: 2.3099971 | CQ55: 0 | CR55: 0.0039464966 | CS55: 0
A56: 25 | B56: ADM-GB | C56: ADMIRAL GROUP PLC | D56: GB00B02J6398 | E56: XLON | F56: 306304700 | G56: 33.85041 | H56: GBX | I56: 1.036854e+10 | J56: EU500 | K56: 10015140 | L56: 0.7 | M56: 7.2579778e+09 | N56: 3180 | O56: 0.01169249 | P56: 7.9723403e+09 | Q56: 37.182118 | R56: 30302025 | S56: 3030 | T56: 1.998809 | U56: 2.7 | V56: C | W56: Green | X56: 0 | Y56: 0 | Z56: Green | AA56: Green | AB56: Green | AC56: Green | AD56: Green | AE56: Green | AF56: Green | AG56: 0 | AH56: 0 | AI56: 0 | AK56: 0 | AL56: F | AN56: F | AO56: F | AP56: F | AR56: 0 | AS56: 0 | AT56: 0 | AU56: 0 | AV56: 1.88 | AW56: 2.7 | AX56: K | AY56: 0 | AZ56: 0 | BA56: GB | BB56: 0 | BC56: 0 | BD56: 0 | CH56: 2.29 | CJ56: No | CL56: 1.998809 | CM56: 2.7 | CN56: 2.3494045 | CO56: 0 | CP56: 2.3494045 | CQ56: 0 | CR56: 0.0060806459 | CS56: 7.1562076e-05
A57: 397 | B57: DLG-GB | C57: DIRECT LINE INSURANC | D57: GB00BY9D0Y18 | E57: XLON | F57: 1311388200 | G57: 3.189192 | H57: GBX | I57: 4.1822688e+09 | J57: EU500 | K57: 12673712 | L57: 1 | M57: 4.1822688e+09 | N57: 274.2 | O57: 0.01169249 | P57: 4.2044165e+09 | Q57: 3.2060808 | R57: 30302025 | S57: 3030 | T57: 1.9926433 | V57: B | W57: Green | X57: 0 | Y57: 0 | Z57: Green | AA57: Green | AB57: Green | AC57: Green | AD57: Green | AE57: Green | AF57: Green | AG57: 0 | AH57: 0 | AI57: 0 | AK57: 0 | AL57: F | AN57: F | AO57: F | AP57: F | AR57: 0 | AS57: 0 | AT57: 0 | AU57: 0 | AV57: 1.884 | AW57: 2.643 | AX57: K | AY57: 0 | AZ57: 0 | BA57: GB | BB57: 0 | BC57: 0 | BD57: 0 | CH57: 2.2635 | CJ57: No | CL57: 1.9926433 | CM57: 3.1 | CN57: 2.5463216 | CO57: -0.18 | CP57: 2.3663216 | CQ57: 0 | CR57: 0.0054243754 | CS57: 0
A58: 143 | B58: AV-GB | C58: AVIVA | D58: GB00BPQY8M80 | E58: XLON | F58: 2677649400 | G58: 6.027791 | H58: GBX | I58: 1.6140311e+10 | J58: EU500 | K58: 29758651 | L58: 1 | M58: 1.6140311e+10 | N58: 522.6 | O58: 0.01169249 | P58: 1.6361764e+10 | Q58: 6.1104953 | R58: 30301010 | S58: 3030 | T58: 1.999421 | V58: B | W58: Green | X58: 0 | Y58: 0 | Z58: Green | AA58: Green | AB58: Green | AC58: Green | AD58: Green | AE58: Green | AF58: Green | AG58: 0 | AH58: 0 | AI58: 0 | AK58: 0 | AL58: F | AN58: F | AO58: F | AP58: F | AR58: 0 | AS58: 0 | AT58: 0 | AU58: 0 | AV58: 2.22 | AW58: 3.325 | AX58: K | AY58: 0 | AZ58: 0 | BA58: GB | BB58: 0 | BC58: 0 | BD58: 0 | CH58: 2.7725 | CJ58: No | CL58: 1.999421 | CM58: 3.1 | CN58: 2.5497105 | CO58: -0.18 | CP58: 2.3697105 | CQ58: 0 | CR58: 0.015240734 | CS58: 0
A59: 145 | B59: CS-FR | C59: AXA | D59: FR0000120628 | E59: XPAR | F59: 2214797873 | G59: 36.98 | H59: EUR | I59: 8.1903225e+10 | J59: EU500;EZ300 | K59: 1.4129308e+08 | L59: 0.85 | M59: 6.9617742e+10 | N59: 38.88 | O59: 1 | P59: 7.319464e+10 | Q59: 38.88 | R59: 30302010 | S59: 3030 | T59: 3.2733333 | U59: 1.5 | V59: C | W59: Green | X59: 0 | Y59: 0 | Z59: Green | AA59: Green | AB59: Green | AC59: Green | AD59: Green | AE59: Green | AF59: Green | AG59: 0 | AH59: 0 | AI59: 0 | AK59: 0 | AL59: F | AN59: F | AO59: F | AP59: F | AR59: 0 | AS59: 0 | AT59: 0 | AU59: 0 | AV59: 2.342 | AW59: 2.624 | AX59: K | AY59: 0 | AZ59: 0 | BA59: FR | BB59: 0 | BC59: 0 | BD59: 0 | CH59: 2.483 | CJ59: No | CL59: 3.2733333 | CM59: 1.5 | CN59: 2.3866667 | CO59: 0 | CP59: 2.3866667 | CQ59: 0 | CR59: 0.07062986 | CS59: 0
A60: 781 | B60: LAND-GB | C60: LAND SECURITIES | D60: GB00BYW0PQ60 | E60: XLON | F60: 744937900 | G60: 6.89702 | H60: GBX | I60: 5.1378516e+09 | J60: EU500 | K60: 14821728 | L60: 1 | M60: 5.1378516e+09 | N60: 552.5 | O60: 0.01169249 | P60: 4.8123739e+09 | Q60: 6.4601007 | R60: 35102000 | S60: 3510 | T60: 1.739563 | U60: 1.5 | V60: A | W60: Green | X60: 0 | Y60: 0 | Z60: Green | AA60: Green | AB60: Green | AC60: Green | AD60: Green | AE60: Green | AF60: Green | AG60: 0 | AH60: 0 | AI60: 0 | AK60: 0 | AL60: F | AN60: F | AO60: F | AP60: F | AR60: 0 | AS60: 0 | AT60: 0 | AU60: 0 | AV60: 2.242 | AW60: 2.879 | AX60: L | AY60: 1 | AZ60: 0 | BA60: GB | BB60: 0 | BC60: 0 | BD60: 0 | CH60: 2.5605 | CJ60: No | CL60: 1.739563 | CM60: 1.5 | CN60: 1.6197815 | CO60: -0.3 | CP60: 1.3197815 | CQ60: 1 | CR60: 0.0063033588 | CS60: 0
A61: 1429 | B61: URW-FR | C61: UNIBAIL-RODAMCO-WE | D61: FR0013326246 | E61: XPAR | F61: 142625428 | G61: 82.02 | H61: EUR | I61: 1.1698138e+10 | J61: EU500;EZ300 | K61: 24417918 | L61: 0.85 | M61: 9.943417e+09 | N61: 70.1 | O61: 1 | P61: 8.4983361e+09 | Q61: 70.1 | R61: 35102045 | S61: 3510 | T61: 1.746375 | U61: 2.7 | V61: A | W61: Green | X61: 0 | Y61: 0 | Z61: Green | AA61: Green | AB61: Green | AC61: Green | AD61: Green | AE61: Green | AF61: Green | AG61: 0 | AH61: 0 | AI61: 0 | AK61: 0 | AL61: F | AN61: F | AO61: F | AP61: F | AR61: 0 | AS61: 0 | AT61: 0 | AU61: 0 | AV61: 2.611 | AW61: 3.167 | AX61: L | AY61: 1 | AZ61: 0 | BA61: FR | BB61: 0 | BC61: 0 | BD61: 0 | CH61: 2.889 | CJ61: No | CL61: 1.746375 | CM61: 2.7 | CN61: 2.2231875 | CO61: -0.3 | CP61: 1.9231875 | CQ61: 0 | CR61: 0.010604433 | CS61: 0
A62: 539 | B62: GFC-FR | C62: GECINA | D62: FR0010040865 | E62: XPAR | F62: 76738691 | G62: 91.9 | H62: EUR | I62: 7.0522857e+09 | J62: EU500;EZ300 | K62: 10616905 | L62: 0.6 | M62: 4.2313714e+09 | N62: 88.4 | O62: 1 | P62: 4.0702202e+09 | Q62: 88.4 | R62: 35102030 | S62: 3510 | T62: 2.2375872 | U62: 2.08 | V62: B | W62: Green | X62: 0 | Y62: 0 | Z62: Green | AA62: Green | AB62: Green | AC62: Green | AD62: Green | AE62: Green | AF62: Green | AG62: 0 | AH62: 0 | AI62: 0 | AK62: 0 | AL62: F | AN62: F | AO62: F | AP62: F | AR62: 0 | AS62: 0 | AT62: 0 | AU62: 0 | AV62: 2.18 | AW62: 3.102 | AX62: L | AY62: 1 | AZ62: 0 | BA62: FR | BB62: 0 | BC62: 0 | BD62: 0 | CH62: 2.641 | CJ62: No | CL62: 2.2375872 | CM62: 2.08 | CN62: 2.1587936 | CO62: -0.18 | CP62: 1.9787936 | CQ62: 0 | CR62: 0.0047555539 | CS62: 0
A63: 862 | B63: MRL-ES | C63: MERLIN PROPERTIES | D63: ES0105025003 | E63: XMAD | F63: 563724900 | G63: 10.87 | H63: EUR | I63: 6127689663 | J63: EU500;EZ300 | K63: 8755069.4 | L63: 0.65 | M63: 3.9829983e+09 | N63: 9.5 | O63: 1 | P63: 3.4810013e+09 | Q63: 9.5 | R63: 35102000 | S63: 3510 | T63: 1.7450068 | V63: B | W63: Green | X63: 0 | Y63: 0 | Z63: Green | AA63: Green | AB63: Green | AC63: Green | AD63: Green | AE63: Green | AF63: Green | AG63: 0 | AH63: 0 | AI63: 0 | AK63: 0 | AL63: F | AN63: F | AO63: F | AP63: F | AR63: 0 | AS63: 0 | AT63: 0 | AU63: 0 | AV63: 2.177 | AW63: 2.626 | AX63: L | AY63: 1 | AZ63: 0 | BA63: ES | BB63: 0 | BC63: 0 | BD63: 0 | CH63: 2.4015 | CJ63: No | CL63: 1.7450068 | CM63: 3.1 | CN63: 2.4225034 | CO63: -0.18 | CP63: 2.2425034 | CQ63: 0 | CR63: 0.0039696549 | CS63: 0
A64: 202 | B64: BMW-DE | C64: BMW | D64: DE0005190003 | E64: XETR | F64: 579795650 | G64: 82.58 | H64: EUR | I64: 47879524777 | J64: EU500;EZ300 | K64: 97231109 | L64: 0.5 | M64: 2.3939762e+10 | N64: 70.14 | O64: 1 | P64: 2.0333433e+10 | Q64: 70.14 | R64: 40101020 | S64: 4010 | T64: 1.7483805 | U64: 1.5 | V64: A- | W64: Green | X64: 0 | Y64: 0 | Z64: Green | AA64: Green | AB64: Green | AC64: Green | AD64: Green | AE64: Green | AF64: Green | AG64: 0 | AH64: 0 | AI64: 0 | AK64: 0 | AL64: F | AN64: F | AO64: F | AP64: F | AR64: 0 | AS64: 0 | AT64: 0 | AU64: 0 | AV64: 2.396 | AW64: 2.312 | AX64: C | AY64: 1 | AZ64: 0 | BA64: DE | BB64: 0 | BC64: 0 | BD64: 0 | CH64: 2.354 | CJ64: No | CL64: 1.7483805 | CM64: 1.5 | CN64: 1.6241903 | CO64: -0.24 | CP64: 1.3841903 | CQ64: 1 | CR64: 0.037014928 | CS64: 0
A65: 321 | B65: CON-DE | C65: CONTINENTAL AG | D65: DE0005439004 | E65: XETR | F65: 200005980 | G65: 69 | H65: EUR | I65: 13800412620 | J65: EU500;EZ300 | K65: 24556942 | L65: 0.55 | M65: 7.5902269e+09 | N65: 64.46 | O65: 1 | P65: 7.090812e+09 | Q65: 64.46 | R65: 40101025 | S65: 4010 | T65: 1.9953776 | U65: 1.5 | V65: A- | W65: Green | X65: 0 | Y65: 0 | Z65: Green | AA65: Green | AB65: Green | AC65: Green | AD65: Green | AE65: Green | AF65: Green | AG65: 0 | AH65: 0 | AI65: 0 | AK65: 0 | AL65: F | AN65: F | AO65: F | AP65: F | AR65: 0 | AS65: 0 | AT65: 0 | AU65: 0 | AV65: 2.406 | AW65: 2.632 | AX65: C | AY65: 1 | AZ65: 0 | BA65: DE | BB65: 0 | BC65: 0 | BD65: 0 | CH65: 2.519 | CJ65: No | CL65: 1.9953776 | CM65: 1.5 | CN65: 1.7476888 | CO65: -0.24 | CP65: 1.5076888 | CQ65: 1 | CR65: 0.010103052 | CS65: 0
A66: 809 | B66: OR-FR | C66: L'OREAL | D66: FR0000120321 | E66: XPAR | F66: 534311946 | G66: 346.1 | H66: EUR | I66: 1.8492536e+11 | J66: EU500;EZ300 | K66: 1.5000772e+08 | L66: 0.45 | M66: 8.3216414e+10 | N66: 343.8 | O66: 1 | P66: 8.2663401e+10 | Q66: 343.8 | R66: 40204035 | S66: 4020 | T66: 1.7493832 | U66: 1.5 | V66: A | W66: Green | X66: 0 | Y66: 0 | Z66: Green | AA66: Green | AB66: Green | AC66: Green | AD66: Green | AE66: Green | AF66: Green | AG66: 0 | AH66: 0 | AI66: 0 | AK66: 0 | AL66: F | AN66: F | AO66: F | AP66: F | AR66: 0 | AS66: 0 | AT66: 0 | AU66: 0 | AV66: 2.447 | AW66: 2.842 | AX66: C | AY66: 1 | AZ66: 0 | BA66: FR | BB66: 0 | BC66: 0 | BD66: 0 | CH66: 2.6445 | CJ66: No | CL66: 1.7493832 | CM66: 1.5 | CN66: 1.6246916 | CO66: -0.3 | CP66: 1.3246916 | CQ66: 1 | CR66: 0.076897745 | CS66: 0
A67: 1336 | B67: TW-GB | C67: TAYLOR WIMPEY PLC | D67: GB0008782301 | E67: XLON | F67: 3540041300 | G67: 1.382426 | H67: GBX | I67: 4.8938451e+09 | J67: EU500 | K67: 19580322 | L67: 1 | M67: 4.8938451e+09 | N67: 109 | O67: 0.01169249 | P67: 4.5117168e+09 | Q67: 1.2744814 | R67: 40202010 | S67: 4020 | T67: 1.748051 | U67: 1.5 | V67: A- | W67: Green | X67: 0 | Y67: 0 | Z67: Green | AA67: Green | AB67: Green | AC67: Green | AD67: Green | AE67: Green | AF67: Green | AG67: 0 | AH67: 0 | AI67: 0 | AK67: 0 | AL67: F | AN67: F | AO67: F | AP67: F | AR67: 0 | AS67: 0 | AT67: 0 | AU67: 0 | AV67: 2.49 | AW67: 2.768 | AX67: F | AY67: 1 | AZ67: 0 | BA67: GB | BB67: 0 | BC67: 0 | BD67: 0 | CH67: 2.629 | CJ67: No | CL67: 1.748051 | CM67: 1.5 | CN67: 1.6240255 | CO67: -0.24 | CP67: 1.3840255 | CQ67: 1 | CR67: 0.0076149293 | CS67: 0
A68: 171 | B68: BTRW-GB | C68: BARRATT REDROW PLC | D68: GB0000811801 | E68: XLON | F68: 1450318700 | G68: 5.133173 | H68: GBX | I68: 7.4447368e+09 | J68: EU500 | K68: 20081176 | L68: 1 | M68: 7.4447368e+09 | N68: 427.7 | O68: 0.01169249 | P68: 7.2528668e+09 | Q68: 5.000878 | R68: 40202010 | S68: 4020 | T68: 1.7482664 | U68: 1.77 | V68: A | W68: Green | X68: 0 | Y68: 0 | Z68: Green | AA68: Green | AB68: Green | AC68: Green | AD68: Green | AE68: Green | AF68: Green | AG68: 0 | AH68: 0 | AI68: 0 | AK68: 0 | AL68: F | AN68: F | AO68: F | AP68: F | AR68: 0 | AS68: 0 | AT68: 0 | AU68: 0 | AV68: 2.49 | AW68: 3.299 | AX68: F | AY68: 1 | AZ68: 0 | BA68: GB | BB68: 0 | BC68: 0 | BD68: 0 | CH68: 2.8945 | CJ68: No | CL68: 1.7482664 | CM68: 1.77 | CN68: 1.7591332 | CO68: -0.3 | CP68: 1.4591332 | CQ68: 1 | CR68: 0.00882285 | CS68: 0
A69: 1033 | B69: PSN-GB | C69: PERSIMMON | D69: GB0006825383 | E69: XLON | F69: 319915900 | G69: 14.61008 | H69: GBX | I69: 4.6739969e+09 | J69: EU500 | K69: 15670414 | L69: 1 | M69: 4.6739969e+09 | N69: 1176 | O69: 0.01169249 | P69: 4.3989614e+09 | Q69: 13.750368 | R69: 40202010 | S69: 4020 | T69: 1.9955323 | U69: 1.5 | V69: A- | W69: Green | X69: 0 | Y69: 0 | Z69: Green | AA69: Green | AB69: Green | AC69: Green | AD69: Green | AE69: Green | AF69: Green | AG69: 0 | AH69: 0 | AI69: 0 | AK69: 0 | AL69: F | AN69: F | AO69: F | AP69: F | AR69: 0 | AS69: 0 | AT69: 0 | AU69: 0 | AV69: 2.157 | AW69: 2.876 | AX69: F | AY69: 1 | AZ69: 0 | BA69: GB | BB69: 0 | BC69: 0 | BD69: 0 | CH69: 2.5165 | CJ69: No | CL69: 1.9955323 | CM69: 1.5 | CN69: 1.7477662 | CO69: -0.24 | CP69: 1.5077662 | CQ69: 1 | CR69: 0.0063984504 | CS69: 0
A70: 189 | B70: BWY-GB | C70: BELLWAY P.L.C. | D70: GB0000904986 | E70: XLON | F70: 118657364 | G70: 28.04748 | H70: GBX | I70: 3.32804e+09 | J70: EU500 | K70: 10092470 | L70: 1 | M70: 3.32804e+09 | N70: 2430 | O70: 0.01169249 | P70: 3.3713821e+09 | Q70: 28.412751 | R70: 40202010 | S70: 4020 | T70: 1.996686 | U70: 2.08 | V70: B | W70: Green | X70: 0 | Y70: 0 | Z70: Green | AA70: Green | AB70: Green | AC70: Green | AD70: Green | AE70: Green | AF70: Green | AG70: 0 | AH70: 0 | AI70: 0 | AK70: 0 | AL70: F | AN70: F | AO70: F | AP70: F | AR70: 0 | AS70: 0 | AT70: 0 | AU70: 0 | AV70: 1.786 | AW70: 2.78 | AX70: F | AY70: 1 | AZ70: 0 | BA70: GB | BB70: 0 | BC70: 0 | BD70: 0 | CH70: 2.283 | CJ70: No | CL70: 1.996686 | CM70: 2.08 | CN70: 2.038343 | CO70: -0.18 | CP70: 1.858343 | CQ70: 0 | CR70: 0.0043285789 | CS70: 0
A71: 1512 | B71: WKL-NL | C71: WOLTERS KLUWER | D71: NL0000395903 | E71: XAMS | F71: 238516153 | G71: 172.6 | H71: EUR | I71: 4.1167888e+10 | J71: EU500;EZ300 | K71: 74863714 | L71: 1 | M71: 4.1167888e+10 | N71: 152.3 | O71: 1 | P71: 3.632601e+10 | Q71: 152.3 | R71: 40301030 | S71: 4030 | T71: 1.5670645 | U71: 1.5 | V71: B | W71: Green | X71: 0 | Y71: 0 | Z71: Green | AA71: Green | AB71: Green | AC71: Green | AD71: Green | AE71: Green | AF71: Green | AG71: 0 | AH71: 0 | AI71: 0 | AK71: 0 | AL71: F | AN71: F | AO71: F | AP71: F | AR71: 0 | AS71: 0 | AT71: 0 | AU71: 0 | AV71: 2.13 | AW71: 3.66 | AX71: M | AY71: 0 | AZ71: 0 | BA71: NL | BB71: 0 | BC71: 0 | BD71: 0 | CH71: 2.895 | CJ71: No | CL71: 1.5670645 | CM71: 1.5 | CN71: 1.5335322 | CO71: -0.18 | CP71: 1.3535322 | CQ71: 1 | CR71: 0.036475398 | CS71: 0
A72: 1517 | B72: WPP-GB | C72: WPP | D72: JE00B8KF9B49 | E72: XLON | F72: 1078802400 | G72: 9.110596 | H72: GBX | I72: 9.8285328e+09 | J72: EU500 | K72: 20881891 | L72: 0.95 | M72: 9.3371062e+09 | N72: 554 | O72: 0.01169249 | P72: 6.6386883e+09 | Q72: 6.4776395 | R72: 40301020 | S72: 4030 | T72: 1.9934118 | U72: 1.5 | V72: B | W72: Green | X72: 0 | Y72: 0 | Z72: Green | AA72: Green | AB72: Green | AC72: Green | AD72: Green | AE72: Green | AF72: Green | AG72: 0 | AH72: 0 | AI72: 0 | AK72: 0 | AL72: F | AN72: F | AO72: F | AP72: F | AR72: 0 | AS72: 0 | AT72: 0 | AU72: 0 | AV72: 2.243 | AW72: 3.066 | AX72: M | AY72: 0 | AZ72: 0 | BA72: JE | BB72: 0 | BC72: 0 | BD72: 0 | CH72: 2.6545 | CJ72: No | CL72: 1.9934118 | CM72: 1.5 | CN72: 1.7467059 | CO72: -0.18 | CP72: 1.5667059 | CQ72: 1 | CR72: 0.0088260857 | CS72: 0
A73: 747 | B73: KGF-GB | C73: KINGFISHER | D73: GB0033195214 | E73: XLON | F73: 1788668100 | G73: 2.966746 | H73: GBX | I73: 5.3065239e+09 | J73: EU500 | K73: 14671963 | L73: 0.85 | M73: 4.5105453e+09 | N73: 266.8 | O73: 0.01169249 | P73: 4.7428733e+09 | Q73: 3.1195563 | R73: 40401025 | S73: 4040 | T73: 1.9967992 | U73: 1.5 | V73: A- | W73: Green | X73: 0 | Y73: 0 | Z73: Green | AA73: Green | AB73: Green | AC73: Green | AD73: Green | AE73: Green | AF73: Green | AG73: 0 | AH73: 0 | AI73: 0 | AK73: 0 | AL73: F | AN73: F | AO73: F | AP73: F | AR73: 0 | AS73: 0 | AT73: 0 | AU73: 0 | AV73: 2.332 | AW73: 3.358 | AX73: G | AY73: 1 | AZ73: 0 | BA73: GB | BB73: 0 | BC73: 0 | BD73: 0 | CH73: 2.845 | CJ73: No | CL73: 1.9967992 | CM73: 1.5 | CN73: 1.7483996 | CO73: -0.24 | CP73: 1.5083996 | CQ73: 1 | CR73: 0.0062316124 | CS73: 0
A74: 931 | B74: NXT-GB | C74: NEXT | D74: GB0032089863 | E74: XLON | F74: 123443540 | G74: 121.0757 | H74: GBX | I74: 1.4946013e+10 | J74: EU500 | K74: 22701104 | L74: 0.9 | M74: 1.3451412e+10 | N74: 11960 | O74: 0.01169249 | P74: 1.5536352e+10 | Q74: 139.84218 | R74: 40401010 | S74: 4040 | T74: 1.9886989 | U74: 1.5 | V74: B | W74: Green | X74: 0 | Y74: 0 | Z74: Green | AA74: Green | AB74: Green | AC74: Green | AD74: Green | AE74: Green | AF74: Green | AG74: 0 | AH74: 0 | AI74: 0 | AK74: 0 | AL74: F | AN74: F | AO74: F | AP74: F | AR74: 0 | AS74: 0 | AT74: 0 | AU74: 0 | AV74: 2.357 | AW74: 2.1 | AX74: G | AY74: 1 | AZ74: 0 | BA74: GB | BB74: 0 | BC74: 0 | BD74: 0 | CH74: 2.2285 | CJ74: No | CL74: 1.9886989 | CM74: 1.5 | CN74: 1.7443494 | CO74: -0.18 | CP74: 1.5643494 | CQ74: 1 | CR74: 0.012804987 | CS74: 0
A75: 1419 | B75: TUI1-DE | C75: TUI AG | D75: DE000TUAG505 | E75: XETR | F75: 507431030 | G75: 6.576 | H75: EUR | I75: 3.3368665e+09 | J75: EU500;EZ300 | K75: 30812669 | L75: 0.9 | M75: 3.0031798e+09 | N75: 6.308 | O75: 1 | P75: 2.8807874e+09 | Q75: 6.308 | R75: 40501015 | S75: 4050 | T75: 1.7681542 | U75: 1.5 | V75: A | W75: Green | X75: 0 | Y75: 0.01 | Z75: Green | AA75: Green | AB75: Green | AC75: Green | AD75: Green | AE75: Green | AF75: Green | AG75: 0 | AH75: 0 | AI75: 0 | AK75: 0 | AL75: F | AN75: F | AO75: F | AP75: F | AR75: 0 | AS75: 0 | AT75: 0 | AU75: 0 | AV75: 2.591 | AW75: 2.93 | AX75: N | AY75: 0 | AZ75: 0 | BA75: DE | BB75: 0 | BC75: 0 | BD75: 0 | CH75: 2.7605 | CJ75: No | CL75: 1.7681542 | CM75: 1.5 | CN75: 1.6340771 | CO75: -0.3 | CP75: 1.3340771 | CQ75: 1 | CR75: 0.010355344 | CS75: 0
... A87: 123 | B87: ASSA.B-SE | C87: ASSA ABLOY AB-B | D87: SE0007100581 | E87: XSTO | F87: 1055050400 | G87: 29.5566 | H87: SEK | I87: 3.1183703e+10 | J87: EU500 | K87: 42342444 | L87: 0.95 | M87: 2.9624518e+10 | N87: 283.8 | O87: 0.08996851 | P87: 2.5591735e+10 | Q87: 25.533063 | R87: 50101035 | S87: 5010 | T87: 1.7488745 | U87: 1.5 | V87: B | W87: Green | X87: 0 | Y87: 0 | Z87: Green | AA87: Green | AB87: Green | AC87: Green | AD87: Green | AE87: Green | AF87: Green | AG87: 0 | AH87: 0 | AI87: 0 | AK87: 0 | AL87: F | AN87: F | AO87: F | AP87: F | AR87: 0 | AS87: 0 | AT87: 0 | AU87: 0 | AV87: 1.956 | AW87: 3.042 | AX87: N | AY87: 0 | AZ87: 0 | BA87: SE | BB87: 0 | BC87: 0 | BD87: 0 | CH87: 2.499 | CJ87: No | CL87: 1.7488745 | CM87: 1.5 | CN87: 1.6244372 | CO87: -0.18 | CP87: 1.4444372 | CQ87: 1 | CR87: 0.022577229 | CS87: 0
A88: 1218 | B88: SIKA-CH | C88: SIKA AG | D88: CH0418792922 | E88: XSWX | F88: 160479300 | G88: 252.8497 | H88: CHF | I88: 4.0577143e+10 | J88: EU500 | K88: 92114433 | L88: 1 | M88: 4.0577143e+10 | N88: 198.55 | O88: 1.079797 | P88: 3.440575e+10 | Q88: 214.39369 | R88: 50101035 | S88: 5010 | T88: 1.7439056 | V88: C | W88: Green | X88: 0 | Y88: 0 | Z88: Green | AA88: Green | AB88: Green | AC88: Green | AD88: Green | AE88: Green | AF88: Green | AG88: 0 | AH88: 0 | AI88: 0 | AK88: 0 | AL88: F | AN88: F | AO88: F | AP88: F | AR88: 0 | AS88: 0 | AT88: 0 | AU88: 0 | AV88: 2.678 | AW88: 2.95 | AX88: C | AY88: 1 | AZ88: 0 | BA88: CH | BB88: 0 | BC88: 0 | BD88: 0 | CH88: 2.814 | CJ88: No | CL88: 1.7439056 | CM88: 3.1 | CN88: 2.4219528 | CO88: 0 | CP88: 2.4219528 | CQ88: 0 | CR88: 0.040909687 | CS88: 0
A89: 895 | B89: MNDI-GB | C89: MONDI PLC | D89: GB00BMWC6P49 | E89: XLON | F89: 441412540 | G89: 14.97881 | H89: GBX | I89: 6.6118346e+09 | J89: EU500 | K89: 15552732 | L89: 1 | M89: 6.6118346e+09 | N89: 1111.5 | O89: 0.01169249 | P89: 5.7366868e+09 | Q89: 12.996203 | R89: 50203030 | S89: 5020 | T89: 1.6338402 | U89: 1.5 | V89: A | W89: Green | X89: 0 | Y89: 0 | Z89: Green | AA89: Green | AB89: Green | AC89: Green | AD89: Green | AE89: Green | AF89: Green | AG89: 0 | AH89: 0 | AI89: 0 | AK89: 0 | AL89: F | AN89: F | AO89: F | AP89: F | AR89: 0 | AS89: 0 | AT89: 0 | AU89: 0 | AV89: 2.396 | AW89: 3.284 | AX89: C | AY89: 1 | AZ89: 0 | BA89: GB | BB89: 0 | BC89: 0 | BD89: 0 | CH89: 2.84 | CJ89: No | CL89: 1.6338402 | CM89: 1.5 | CN89: 1.5669201 | CO89: -0.3 | CP89: 1.2669201 | CQ89: 1 | CR89: 0.0068793033 | CS89: 0
A90: 787 | B90: LR-FR | C90: LEGRAND | D90: FR0010307819 | E90: XPAR | F90: 262245733 | G90: 110.3 | H90: EUR | I90: 2.8925704e+10 | J90: EU500;EZ300 | K90: 56619308 | L90: 1 | M90: 2.8925704e+10 | N90: 94.52 | O90: 1 | P90: 2.4787467e+10 | Q90: 94.52 | R90: 50202010 | S90: 5020 | T90: 1.7418068 | U90: 1.5 | V90: A | W90: Green | X90: 0 | Y90: 0 | Z90: Green | AA90: Green | AB90: Green | AC90: Green | AD90: Green | AE90: Green | AF90: Green | AG90: 0 | AH90: 0 | AI90: 0 | AK90: 0 | AL90: F | AN90: F | AO90: F | AP90: F | AR90: 0 | AS90: 0 | AT90: 0 | AU90: 0 | AV90: 2.525 | AW90: 3.005 | AX90: C | AY90: 1 | AZ90: 0 | BA90: FR | BB90: 0 | BC90: 0 | BD90: 0 | CH90: 2.765 | CJ90: No | CL90: 1.7418068 | CM90: 1.5 | CN90: 1.6209034 | CO90: -0.3 | CP90: 1.3209034 | CQ90: 1 | CR90: 0.026549963 | CS90: 0
A91: 480 | B91: EXPN-GB | C91: EXPERIAN | D91: GB00B19NLV48 | E91: XLON | F91: 919566160 | G91: 46.38715 | H91: GBX | I91: 4.2656053e+10 | J91: EU500 | K91: 53659581 | L91: 1 | M91: 4.2656053e+10 | N91: 3486 | O91: 0.01169249 | P91: 3.7481535e+10 | Q91: 40.76002 | R91: 50205020 | S91: 5020 | T91: 1.9678575 | U91: 1.5 | V91: A- | W91: Green | X91: 0 | Y91: 0 | Z91: Green | AA91: Green | AB91: Green | AC91: Green | AD91: Green | AE91: Green | AF91: Green | AG91: 0 | AH91: 0 | AI91: 0 | AK91: 0 | AL91: F | AN91: F | AO91: F | AP91: F | AR91: 0 | AS91: 0 | AT91: 0 | AU91: 0 | AV91: 2.413 | AW91: 3.26 | AX91: J | AY91: 0 | AZ91: 0 | BA91: GB | BB91: 0 | BC91: 0 | BD91: 0 | CH91: 2.8365 | CJ91: No | CL91: 1.9678575 | CM91: 1.5 | CN91: 1.7339287 | CO91: -0.24 | CP91: 1.4939287 | CQ91: 1 | CR91: 0.030560014 | CS91: 0
A92: 624 | B92: HUH1V-FI | C92: HUHTAMAKI OYJ | D92: FI0009000459 | E92: XHEL | F92: 107760380 | G92: 37.44 | H92: EUR | I92: 4.0345486e+09 | J92: EU500;EZ300 | K92: 5079227 | L92: 0.9 | M92: 3.6310938e+09 | N92: 32.68 | O92: 1 | P92: 3.1694483e+09 | Q92: 32.68 | R92: 50203030 | S92: 5020 | T92: 1.9600431 | U92: 1.77 | V92: A- | W92: Green | X92: 0 | Y92: 0 | Z92: Green | AA92: Green | AB92: Green | AC92: Green | AD92: Green | AE92: Green | AF92: Green | AG92: 0 | AH92: 0 | AI92: 0 | AK92: 0 | AL92: F | AN92: F | AO92: F | AP92: F | AR92: 0 | AS92: 0 | AT92: 0 | AU92: 0 | AV92: 2.701 | AW92: 2.963 | AX92: C | AY92: 1 | AZ92: 0 | BA92: FI | BB92: 0 | BC92: 0 | BD92: 0 | CH92: 2.832 | CJ92: No | CL92: 1.9600431 | CM92: 1.77 | CN92: 1.8650216 | CO92: -0.24 | CP92: 1.6250216 | CQ92: 1 | CR92: 0.0027466904 | CS92: 0
A93: 762 | B93: KNEBV-FI | C93: KONE OYJ | D93: FI0009013403 | E93: XHEL | F93: 453187130 | G93: 55.22 | H93: EUR | I93: 2.5024993e+10 | J93: EU500;EZ300 | K93: 26322525 | L93: 0.85 | M93: 2.1271244e+10 | N93: 51.48 | O93: 1 | P93: 1.9830562e+10 | Q93: 51.48 | R93: 50204000 | S93: 5020 | T93: 1.9953067 | U93: 2.08 | V93: A | W93: Green | X93: 0 | Y93: 0 | Z93: Green | AA93: Green | AB93: Green | AC93: Green | AD93: Green | AE93: Green | AF93: Green | AG93: 0 | AH93: 0 | AI93: 0 | AK93: 0 | AL93: F | AN93: F | AO93: F | AP93: F | AR93: 0 | AS93: 0 | AT93: 0 | AU93: 0 | AV93: 2.6 | AW93: 2.884 | AX93: C | AY93: 1 | AZ93: 0 | BA93: FI | BB93: 0 | BC93: 0 | BD93: 0 | CH93: 2.742 | CJ93: No | CL93: 1.9953067 | CM93: 2.08 | CN93: 2.0376534 | CO93: -0.3 | CP93: 1.7376534 | CQ93: 0 | CR93: 0.015548322 | CS93: 0
A94: 1108 | B94: RXL-FR | C94: REXEL | D94: FR0010451203 | E94: XPAR | F94: 298233069 | G94: 26.56 | H94: EUR | I94: 7.9210703e+09 | J94: EU500;EZ300 | K94: 13654330 | L94: 0.7 | M94: 5.5447492e+09 | N94: 22.46 | O94: 1 | P94: 4.6888203e+09 | Q94: 22.46 | R94: 50202010 | S94: 5020 | T94: 1.749349 | U94: 2.39 | V94: A | W94: Green | X94: 0 | Y94: 0 | Z94: Green | AA94: Green | AB94: Green | AC94: Green | AD94: Green | AE94: Green | AF94: Green | AG94: 0 | AH94: 0 | AI94: 0 | AK94: 0 | AL94: F | AN94: F | AO94: F | AP94: F | AR94: 0 | AS94: 0 | AT94: 0 | AU94: 0 | AV94: 2.152 | AW94: 3.182 | AX94: G | AY94: 1 | AZ94: 0 | BA94: FR | BB94: 0 | BC94: 0 | BD94: 0 | CH94: 2.667 | CJ94: No | CL94: 1.749349 | CM94: 2.39 | CN94: 2.0696745 | CO94: -0.3 | CP94: 1.7696745 | CQ94: 0 | CR94: 0.0059054665 | CS94: 0
A95: 436 | B95: ELIS-FR | C95: ELIS | D95: FR0012435121 | E95: XPAR | F95: 236664445 | G95: 19.15 | H95: EUR | I95: 4.5321241e+09 | J95: EU500;EZ300 | K95: 6519939.4 | L95: 0.7 | M95: 3.1724869e+09 | N95: 21.4 | O95: 1 | P95: 3.5452334e+09 | Q95: 21.4 | R95: 50205010 | S95: 5020 | T95: 1.8621326 | U95: 2.39 | V95: A | W95: Green | X95: 0 | Y95: 0 | Z95: Green | AA95: Green | AB95: Green | AC95: Green | AD95: Green | AE95: Green | AF95: Green | AG95: 0 | AH95: 0 | AI95: 0 | AK95: 0 | AL95: F | AN95: F | AO95: F | AP95: F | AR95: 0 | AS95: 0 | AT95: 0 | AU95: 0 | AV95: 2.284 | AW95: 2.815 | AX95: N | AY95: 0 | AZ95: 0 | BA95: FR | BB95: 0 | BC95: 0 | BD95: 0 | CH95: 2.5495 | CJ95: No | CL95: 1.8621326 | CM95: 2.39 | CN95: 2.1260663 | CO95: -0.3 | CP95: 1.8260663 | CQ95: 0 | CR95: 0.0033238997 | CS95: 0
A96: 228 | B96: BNZL-GB | C96: BUNZL | D96: GB00B0744B38 | E96: XLON | F96: 329765630 | G96: 40.69302 | H96: GBX | I96: 1.3419159e+10 | J96: EU500 | K96: 20420662 | L96: 1 | M96: 1.3419159e+10 | N96: 3078 | O96: 0.01169249 | P96: 1.1868095e+10 | Q96: 35.989484 | R96: 50203000 | S96: 5020 | T96: 1.746324 | U96: 2.39 | V96: B | W96: Green | X96: 0 | Y96: 0 | Z96: Green | AA96: Green | AB96: Green | AC96: Green | AD96: Green | AE96: Green | AF96: Green | AG96: 0 | AH96: 0 | AI96: 0 | AK96: 0 | AL96: F | AN96: F | AO96: F | AP96: F | AR96: 0 | AS96: 0 | AT96: 0 | AU96: 0 | AV96: 2.001 | AW96: 2.996 | AX96: G | AY96: 1 | AZ96: 0 | BA96: GB | BB96: 0 | BC96: 0 | BD96: 0 | CH96: 2.4985 | CJ96: No | CL96: 1.746324 | CM96: 2.39 | CN96: 2.068162 | CO96: -0.18 | CP96: 1.888162 | CQ96: 0 | CR96: 0.010705468 | CS96: 0
A97: 1276 | B97: STERV-FI | C97: STORA ENSO OYJ | D97: FI0009005961 | E97: XHEL | F97: 613066600 | G97: 10.71 | H97: EUR | I97: 6.5659433e+09 | J97: EU500;EZ300 | K97: 19128822 | L97: 1 | M97: 6.5659433e+09 | N97: 7.678 | O97: 1 | P97: 4.7071254e+09 | Q97: 7.678 | R97: 55101015 | S97: 5510 | T97: 1.8865312 | U97: 1.5 | V97: A | W97: Amber | X97: 0 | Y97: 0 | Z97: Green | AA97: Green | AB97: Green | AC97: Green | AD97: Green | AE97: Green | AF97: Green | AG97: 0 | AH97: 0 | AI97: 0 | AK97: 0 | AL97: F | AN97: F | AO97: F | AP97: F | AR97: 0 | AS97: 0 | AT97: 0 | AU97: 0 | AV97: 2.58 | AW97: 3.142 | AX97: C | AY97: 1 | AZ97: 0 | BA97: FI | BB97: 0 | BC97: 0 | BD97: 0 | CH97: 2.861 | CJ97: No | CL97: 1.8865312 | CM97: 1.5 | CN97: 1.6932656 | CO97: -0.3 | CP97: 1.3932656 | CQ97: 1 | CR97: 0.0075548769 | CS97: 0
A98: 1302 | B98: SCA.B-SE | C98: SVENSKA CELLULOSA B | D98: SE0000112724 | E98: XSTO | F98: 638676100 | G98: 13.48346 | H98: SEK | I98: 8.6115636e+09 | J98: EU500 | K98: 18512720 | L98: 0.85 | M98: 7.3198291e+09 | N98: 128.5 | O98: 0.08996851 | P98: 6.276149e+09 | Q98: 11.560954 | R98: 55101010 | S98: 5510 | T98: 1.5109333 | V98: A- | W98: Green | X98: 0 | Y98: 0 | Z98: Green | AA98: Green | AB98: Green | AC98: Green | AD98: Green | AE98: Green | AF98: Green | AG98: 0 | AH98: 0 | AI98: 0 | AK98: 0 | AL98: F | AN98: F | AO98: F | AP98: F | AR98: 0 | AS98: 0 | AT98: 0 | AU98: 0 | AV98: 2.326 | AW98: 2.961 | AX98: C | AY98: 1 | AZ98: 0 | BA98: SE | BB98: 0 | BC98: 0 | BD98: 0 | CH98: 2.6435 | CJ98: No | CL98: 1.5109333 | CM98: 3.1 | CN98: 2.3054666 | CO98: -0.24 | CP98: 2.0654666 | CQ98: 0 | CR98: 0.0079754495 | CS98: 0
A99: 553 | B99: GIVN-CH | C99: GIVAUDAN SA | D99: CH0010645932 | E99: XSWX | F99: 9233586 | G99: 4175.529 | H99: CHF | I99: 3.8555106e+10 | J99: EU500 | K99: 73350479 | L99: 0.9 | M99: 3.4699596e+10 | N99: 3772 | O99: 1.079797 | P99: 3.3847509e+10 | Q99: 4072.9943 | R99: 55201020 | S99: 5520 | T99: 1.7371145 | U99: 2.08 | V99: A | W99: Green | X99: 0 | Y99: 0 | Z99: Green | AA99: Green | AB99: Green | AC99: Green | AD99: Green | AE99: Green | AF99: Green | AG99: 0 | AH99: 0 | AI99: 0 | AK99: 0 | AL99: F | AN99: F | AO99: F | AP99: F | AR99: 0 | AS99: 0 | AT99: 0 | AU99: 0 | AV99: 2.127 | AW99: 2.834 | AX99: C | AY99: 1 | AZ99: 0 | BA99: CH | BB99: 0 | BC99: 0 | BD99: 0 | CH99: 2.4805 | CJ99: No | CL99: 1.7371145 | CM99: 2.08 | CN99: 1.9085573 | CO99: -0.3 | CP99: 1.6085573 | CQ99: 1 | CR99: 0.035065105 | CS99: 0
A100: 1316 | B100: SY1-DE | C100: SYMRISE AG | D100: DE000SYM9999 | E100: XETR | F100: 139772050 | G100: 98.02 | H100: EUR | I100: 13700456341 | J100: EU500;EZ300 | K100: 28548769 | L100: 0.9 | M100: 1.2330411e+10 | N100: 95.88 | O100: 1 | P100: 1.206121e+10 | Q100: 95.88 | R100: 55201000 | S100: 5520 | T100: 1.9236905 | U100: 3.1 | V100: A | W100: Green | X100: 0 | Y100: 0 | Z100: Green | AA100: Green | AB100: Green | AC100: Green | AD100: Green | AE100: Green | AF100: Green | AG100: 0 | AH100: 0 | AI100: 0 | AK100: 0 | AL100: F | AN100: F | AO100: F | AP100: F | AR100: 0 | AS100: 0 | AT100: 0 | AU100: 0 | AV100: 2.639 | AW100: 3.008 | AX100: C | AY100: 1 | AZ100: 0 | BA100: DE | BB100: 0 | BC100: 0 | BD100: 0 | CH100: 2.8235 | CJ100: No | CL100: 1.9236905 | CM100: 3.1 | CN100: 2.5118453 | CO100: -0.3 | CP100: 2.2118453 | CQ100: 0 | CR100: 0.013218413 | CS100: 0
A101: 1442 | B101: UU-GB | C101: UNTD UTILITIES GRP | D101: GB00B39J2M42 | E101: XLON | F101: 681888400 | G101: 11.62278 | H101: GBX | I101: 7.9254389e+09 | J101: EU500 | K101: 15580051 | L101: 1 | M101: 7.9254389e+09 | N101: 1102 | O101: 0.01169249 | P101: 8.7862166e+09 | Q101: 12.885124 | R101: 65102030 | S101: 6510 | T101: 1.696365 | V101: A | W101: Green | X101: 0 | Y101: 0 | Z101: Green | AA101: Green | AB101: Green | AC101: Green | AD101: Green | AE101: Green | AF101: Green | AG101: 0 | AH101: 0 | AI101: 0 | AK101: 0 | AL101: F | AN101: F | AO101: F | AP101: F | AR101: 0 | AS101: 0 | AT101: 0 | AU101: 0 | AV101: 2.96 | AW101: 2.392 | AX101: E | AY101: 1 | AZ101: 0 | BA101: GB | BB101: 0 | BC101: 0 | BD101: 0 | CH101: 2.676 | CJ101: No | CL101: 1.696365 | CM101: 3.1 | CN101: 2.3981825 | CO101: -0.3 | CP101: 2.0981825 | CQ101: 0 | CR101: 0.0080641512 | CS101: 0

Sheet Sheet2
A1: Date | B1: Name | C1: ISIN Code | D1: MIC | E1: Weight Initial universe | F1: Weight Index | G1: Subsector Code | H1: GAFI Black List | I1: GAFI Grey List | J1: Countries non fiscally cooperative with EU | K1: Subsectors | L1: UNGC controversies | M1: Tobacco Production | N1: Tobacco Distribution | O1: Biological weapons | P1: Chemical weapons | Q1: Nuclear weapons | R1: Nuclear non-NPT weapons | S1: Cluster munitions | T1: Depleted uranium | U1: AP mines | V1: Coal mining | W1: Fossil fuel | X1: Power generation | Y1: Shale oil gas involvement | Z1: Arctic drilling involvement | AA1: Deepwater drilling involvement | AB1: Hydraulic Fracturing involvement | AC1: Coal mining expansion involvement | AD1: Oil gas extraction involvement | AE1: Other fossil fuel involvement | AF1: Nuclear power involvement | AG1: Nuclear power revenue | AH1: Nuclear power uranium | AI1: Civilian firearms | AJ1: Military equipment | AK1: EU Taxonomy pocket | AL1: Worst 10% avg soc gov score | AM1: Climate Score | AN1: Final Selection | AO1: Carbon Intensity (ISS) | AP1: Temperate score from ISS
A2: 45709 | B2: ALSTOM | C2: FR0010220475 | D2: XPAR | E2: =_xlfn.XLOOKUP(C2,[2]generation_steps!$I$2:$I$500,[2]generation_steps!$L$2:$L$500) -> 0.00066478048 | F2: =_xlfn.XLOOKUP(C2,[2]full_dataframe_final!$C$2:$C$101,[2]full_dataframe_final!$H$2:$H$101,"") -> 0.013739746 | G2: 50202010 | H2: =ISBLANK('Full Universe'!BE36) -> TRUE | I2: =ISBLANK('Full Universe'!BF36) -> TRUE | J2: =ISBLANK('Full Universe'!BG36) -> TRUE | K2: =ISBLANK('Full Universe'!BH36) -> TRUE | L2: =ISBLANK('Full Universe'!BI36) -> TRUE | M2: =ISBLANK('Full Universe'!BJ36) -> TRUE | N2: =ISBLANK('Full Universe'!BK36) -> TRUE | O2: =ISBLANK('Full Universe'!BL36) -> TRUE | ... AJ2: =ISBLANK('Full Universe'!CG36) -> TRUE | AK2: =ISNUMBER(MATCH(C2,[1]Europe!$B$2:$B$15,0)) -> TRUE | AL2: =ISBLANK('Full Universe'!CJ36) -> TRUE | AM2: Green - not applicable | AN2: =ISNUMBER(MATCH(C2,'Selected Companies'!$D$2:$D$101,0)) -> TRUE | AO2: =_xlfn.XLOOKUP(C2,[2]generation_steps!$C$2:$C$18963,[2]generation_steps!$CM$2:$CM$18963) -> 3285.23 | AP2: =_xlfn.XLOOKUP(C2,[2]generation_steps!$C$2:$C$18963,[2]generation_steps!$CN$2:$CN$18963) -> 1.6
A3: 45709 | B3: CASTELLUM AB | C3: SE0000379190 | D3: XSTO | E3: =_xlfn.XLOOKUP(C3,[2]generation_steps!$I$2:$I$500,[2]generation_steps!$L$2:$L$500) -> 0.00043160883 | F3: =_xlfn.XLOOKUP(C3,[2]full_dataframe_final!$C$2:$C$101,[2]full_dataframe_final!$H$2:$H$101,"") -> 0.0035714286 | G3: 35101010 | H3: =ISBLANK('Full Universe'!BE118) -> TRUE | I3: =ISBLANK('Full Universe'!BF118) -> TRUE | J3: =ISBLANK('Full Universe'!BG118) -> TRUE | K3: =ISBLANK('Full Universe'!BH118) -> TRUE | L3: =ISBLANK('Full Universe'!BI118) -> TRUE | M3: =ISBLANK('Full Universe'!BJ118) -> TRUE | N3: =ISBLANK('Full Universe'!BK118) -> TRUE | O3: =ISBLANK('Full Universe'!BL118) -> TRUE | ... AJ3: =ISBLANK('Full Universe'!CG118) -> TRUE | AK3: =ISNUMBER(MATCH(C3,[1]Europe!$B$2:$B$15,0)) -> TRUE | AL3: =ISBLANK('Full Universe'!CJ118) -> TRUE | AM3: Green - not applicable | AN3: =ISNUMBER(MATCH(C3,'Selected Companies'!$D$2:$D$101,0)) -> TRUE | AO3: =_xlfn.XLOOKUP(C3,[2]generation_steps!$C$2:$C$18963,[2]generation_steps!$CM$2:$CM$18963) -> 6.9595815 | AP3: =_xlfn.XLOOKUP(C3,[2]generation_steps!$C$2:$C$18963,[2]generation_steps!$CN$2:$CN$18963) -> 1.4333333
A4: 45709 | B4: DASSAULT SYSTEMES | C4: FR0014003TT8 | D4: XPAR | E4: =_xlfn.XLOOKUP(C4,[2]generation_steps!$I$2:$I$500,[2]generation_steps!$L$2:$L$500) -> 0.0021695415 | F4: =_xlfn.XLOOKUP(C4,[2]full_dataframe_final!$C$2:$C$101,[2]full_dataframe_final!$H$2:$H$101,"") -> 0.0035714286 | G4: 10101015 | H4: =ISBLANK('Full Universe'!BE139) -> TRUE | I4: =ISBLANK('Full Universe'!BF139) -> TRUE | J4: =ISBLANK('Full Universe'!BG139) -> TRUE | K4: =ISBLANK('Full Universe'!BH139) -> TRUE | L4: =ISBLANK('Full Universe'!BI139) -> TRUE | M4: =ISBLANK('Full Universe'!BJ139) -> TRUE | N4: =ISBLANK('Full Universe'!BK139) -> TRUE | O4: =ISBLANK('Full Universe'!BL139) -> TRUE | ... AJ4: =ISBLANK('Full Universe'!CG139) -> TRUE | AK4: =ISNUMBER(MATCH(C4,[1]Europe!$B$2:$B$15,0)) -> TRUE | AL4: =ISBLANK('Full Universe'!CJ139) -> TRUE | AM4: Green - not applicable | AN4: =ISNUMBER(MATCH(C4,'Selected Companies'!$D$2:$D$101,0)) -> TRUE | AO4: =_xlfn.XLOOKUP(C4,[2]generation_steps!$C$2:$C$18963,[2]generation_steps!$CM$2:$CM$18963) -> 10.868427 | AP4: =_xlfn.XLOOKUP(C4,[2]generation_steps!$C$2:$C$18963,[2]generation_steps!$CN$2:$CN$18963) -> 1.4666667
A5: 45709 | B5: INPOST | C5: LU2290522684 | D5: XAMS | E5: =_xlfn.XLOOKUP(C5,[2]generation_steps!$I$2:$I$500,[2]generation_steps!$L$2:$L$500) -> 0.00025556358 | F5: =_xlfn.XLOOKUP(C5,[2]full_dataframe_final!$C$2:$C$101,[2]full_dataframe_final!$H$2:$H$101,"") -> 0.0068292552 | G5: 50206040 | H5: =ISBLANK('Full Universe'!BE243) -> TRUE | I5: =ISBLANK('Full Universe'!BF243) -> TRUE | J5: =ISBLANK('Full Universe'!BG243) -> TRUE | K5: =ISBLANK('Full Universe'!BH243) -> TRUE | L5: =ISBLANK('Full Universe'!BI243) -> TRUE | M5: =ISBLANK('Full Universe'!BJ243) -> TRUE | N5: =ISBLANK('Full Universe'!BK243) -> TRUE | O5: =ISBLANK('Full Universe'!BL243) -> TRUE | ... AJ5: =ISBLANK('Full Universe'!CG243) -> TRUE | AK5: =ISNUMBER(MATCH(C5,[1]Europe!$B$2:$B$15,0)) -> TRUE | AL5: =ISBLANK('Full Universe'!CJ243) -> TRUE | AM5: Green - not applicable | AN5: =ISNUMBER(MATCH(C5,'Selected Companies'!$D$2:$D$101,0)) -> TRUE | AO5: =_xlfn.XLOOKUP(C5,[2]generation_steps!$C$2:$C$18963,[2]generation_steps!$CM$2:$CM$18963) -> 65.872922 | AP5: =_xlfn.XLOOKUP(C5,[2]generation_steps!$C$2:$C$18963,[2]generation_steps!$CN$2:$CN$18963) -> 1.7
A6: 45709 | B6: KINGSPAN GROUP PLC | C6: IE0004927939 | D6: XMSM | E6: =_xlfn.XLOOKUP(C6,[2]generation_steps!$I$2:$I$500,[2]generation_steps!$L$2:$L$500) -> 0.0011122871 | F6: =_xlfn.XLOOKUP(C6,[2]full_dataframe_final!$C$2:$C$101,[2]full_dataframe_final!$H$2:$H$101,"") -> 0.0035714286 | G6: 50101035 | H6: =ISBLANK('Full Universe'!BE267) -> TRUE | I6: =ISBLANK('Full Universe'!BF267) -> TRUE | J6: =ISBLANK('Full Universe'!BG267) -> TRUE | K6: =ISBLANK('Full Universe'!BH267) -> TRUE | L6: =ISBLANK('Full Universe'!BI267) -> TRUE | M6: =ISBLANK('Full Universe'!BJ267) -> TRUE | N6: =ISBLANK('Full Universe'!BK267) -> TRUE | O6: =ISBLANK('Full Universe'!BL267) -> TRUE | ... AJ6: =ISBLANK('Full Universe'!CG267) -> TRUE | AK6: =ISNUMBER(MATCH(C6,[1]Europe!$B$2:$B$15,0)) -> TRUE | AL6: =ISBLANK('Full Universe'!CJ267) -> TRUE | AM6: Green - not applicable | AN6: =ISNUMBER(MATCH(C6,'Selected Companies'!$D$2:$D$101,0)) -> TRUE | AO6: =_xlfn.XLOOKUP(C6,[2]generation_steps!$C$2:$C$18963,[2]generation_steps!$CM$2:$CM$18963) -> 429.69418 | AP6: =_xlfn.XLOOKUP(C6,[2]generation_steps!$C$2:$C$18963,[2]generation_steps!$CN$2:$CN$18963) -> 1.5666667
A7: 45709 | B7: KNORR-BREMSE AG | C7: DE000KBX1006 | D7: XETR | E7: =_xlfn.XLOOKUP(C7,[2]generation_steps!$I$2:$I$500,[2]generation_steps!$L$2:$L$500) -> 0.00050639091 | F7: =_xlfn.XLOOKUP(C7,[2]full_dataframe_final!$C$2:$C$101,[2]full_dataframe_final!$H$2:$H$101,"") -> 0.0035714286 | G7: 50206025 | H7: =ISBLANK('Full Universe'!BE269) -> TRUE | I7: =ISBLANK('Full Universe'!BF269) -> TRUE | J7: =ISBLANK('Full Universe'!BG269) -> TRUE | K7: =ISBLANK('Full Universe'!BH269) -> TRUE | L7: =ISBLANK('Full Universe'!BI269) -> TRUE | M7: =ISBLANK('Full Universe'!BJ269) -> TRUE | N7: =ISBLANK('Full Universe'!BK269) -> TRUE | O7: =ISBLANK('Full Universe'!BL269) -> TRUE | ... AJ7: =ISBLANK('Full Universe'!CG269) -> TRUE | AK7: =ISNUMBER(MATCH(C7,[1]Europe!$B$2:$B$15,0)) -> TRUE | AL7: =ISBLANK('Full Universe'!CJ269) -> TRUE | AM7: Green - not applicable | AN7: =ISNUMBER(MATCH(C7,'Selected Companies'!$D$2:$D$101,0)) -> TRUE | AO7: =_xlfn.XLOOKUP(C7,[2]generation_steps!$C$2:$C$18963,[2]generation_steps!$CM$2:$CM$18963) -> 3428.5625 | AP7: =_xlfn.XLOOKUP(C7,[2]generation_steps!$C$2:$C$18963,[2]generation_steps!$CN$2:$CN$18963) -> 3.0333333
A8: 45709 | B8: METSO CORPORATION | C8: FI0009014575 | D8: XHEL | E8: =_xlfn.XLOOKUP(C8,[2]generation_steps!$I$2:$I$500,[2]generation_steps!$L$2:$L$500) -> 0.00058872335 | F8: =_xlfn.XLOOKUP(C8,[2]full_dataframe_final!$C$2:$C$101,[2]full_dataframe_final!$H$2:$H$101,"") -> 0.012252098 | G8: 50204020 | H8: =ISBLANK('Full Universe'!BE302) -> TRUE | I8: =ISBLANK('Full Universe'!BF302) -> TRUE | J8: =ISBLANK('Full Universe'!BG302) -> TRUE | K8: =ISBLANK('Full Universe'!BH302) -> TRUE | L8: =ISBLANK('Full Universe'!BI302) -> TRUE | M8: =ISBLANK('Full Universe'!BJ302) -> TRUE | N8: =ISBLANK('Full Universe'!BK302) -> TRUE | O8: =ISBLANK('Full Universe'!BL302) -> TRUE | ... AJ8: =ISBLANK('Full Universe'!CG302) -> TRUE | AK8: =ISNUMBER(MATCH(C8,[1]Europe!$B$2:$B$15,0)) -> TRUE | AL8: =ISBLANK('Full Universe'!CJ302) -> TRUE | AM8: Green - not applicable | AN8: =ISNUMBER(MATCH(C8,'Selected Companies'!$D$2:$D$101,0)) -> TRUE | AO8: =_xlfn.XLOOKUP(C8,[2]generation_steps!$C$2:$C$18963,[2]generation_steps!$CM$2:$CM$18963) -> 447.68354 | AP8: =_xlfn.XLOOKUP(C8,[2]generation_steps!$C$2:$C$18963,[2]generation_steps!$CN$2:$CN$18963) -> 1.5333333
A9: 45709 | B9: NORSK HYDRO | C9: NO0005052605 | D9: XOSL | E9: =_xlfn.XLOOKUP(C9,[2]generation_steps!$I$2:$I$500,[2]generation_steps!$L$2:$L$500) -> 0.00056823472 | F9: =_xlfn.XLOOKUP(C9,[2]full_dataframe_final!$C$2:$C$101,[2]full_dataframe_final!$H$2:$H$101,"") -> 0.0035714286 | G9: 55102035 | H9: =ISBLANK('Full Universe'!BE324) -> TRUE | I9: =ISBLANK('Full Universe'!BF324) -> TRUE | J9: =ISBLANK('Full Universe'!BG324) -> TRUE | K9: =ISBLANK('Full Universe'!BH324) -> TRUE | L9: =ISBLANK('Full Universe'!BI324) -> TRUE | M9: =ISBLANK('Full Universe'!BJ324) -> TRUE | N9: =ISBLANK('Full Universe'!BK324) -> TRUE | O9: =ISBLANK('Full Universe'!BL324) -> TRUE | ... AJ9: =ISBLANK('Full Universe'!CG324) -> TRUE | AK9: =ISNUMBER(MATCH(C9,[1]Europe!$B$2:$B$15,0)) -> TRUE | AL9: =ISBLANK('Full Universe'!CJ324) -> TRUE | AM9: Green - not applicable | AN9: =ISNUMBER(MATCH(C9,'Selected Companies'!$D$2:$D$101,0)) -> TRUE | AO9: =_xlfn.XLOOKUP(C9,[2]generation_steps!$C$2:$C$18963,[2]generation_steps!$CM$2:$CM$18963) -> 1406.9401 | AP9: =_xlfn.XLOOKUP(C9,[2]generation_steps!$C$2:$C$18963,[2]generation_steps!$CN$2:$CN$18963) -> 1.5
A10: 45709 | B10: REDEIA CORP | C10: ES0173093024 | D10: XMAD | E10: =_xlfn.XLOOKUP(C10,[2]generation_steps!$I$2:$I$500,[2]generation_steps!$L$2:$L$500) -> 0.00074840834 | F10: =_xlfn.XLOOKUP(C10,[2]full_dataframe_final!$C$2:$C$101,[2]full_dataframe_final!$H$2:$H$101,"") -> 0.010036043 | G10: 65101015 | H10: =ISBLANK('Full Universe'!BE355) -> TRUE | I10: =ISBLANK('Full Universe'!BF355) -> TRUE | J10: =ISBLANK('Full Universe'!BG355) -> TRUE | K10: =ISBLANK('Full Universe'!BH355) -> TRUE | L10: =ISBLANK('Full Universe'!BI355) -> TRUE | M10: =ISBLANK('Full Universe'!BJ355) -> TRUE | N10: =ISBLANK('Full Universe'!BK355) -> TRUE | O10: =ISBLANK('Full Universe'!BL355) -> TRUE | ... AJ10: =ISBLANK('Full Universe'!CG355) -> TRUE | AK10: =ISNUMBER(MATCH(C10,[1]Europe!$B$2:$B$15,0)) -> TRUE | AL10: =ISBLANK('Full Universe'!CJ355) -> TRUE | AM10: Green - not applicable | AN10: =ISNUMBER(MATCH(C10,'Selected Companies'!$D$2:$D$101,0)) -> TRUE | AO10: =_xlfn.XLOOKUP(C10,[2]generation_steps!$C$2:$C$18963,[2]generation_steps!$CM$2:$CM$18963) -> 95.988242 | AP10: =_xlfn.XLOOKUP(C10,[2]generation_steps!$C$2:$C$18963,[2]generation_steps!$CN$2:$CN$18963) -> 1.6333333
A11: 45709 | B11: ROCKWOOL B | C11: DK0063855168 | D11: XCSE | E11: =_xlfn.XLOOKUP(C11,[2]generation_steps!$I$2:$I$500,[2]generation_steps!$L$2:$L$500) -> 0.00036506021 | F11: =_xlfn.XLOOKUP(C11,[2]full_dataframe_final!$C$2:$C$101,[2]full_dataframe_final!$H$2:$H$101,"") -> 0.0035714286 | G11: 50101035 | H11: =ISBLANK('Full Universe'!BE367) -> TRUE | I11: =ISBLANK('Full Universe'!BF367) -> TRUE | J11: =ISBLANK('Full Universe'!BG367) -> TRUE | K11: =ISBLANK('Full Universe'!BH367) -> TRUE | L11: =ISBLANK('Full Universe'!BI367) -> TRUE | M11: =ISBLANK('Full Universe'!BJ367) -> TRUE | N11: =ISBLANK('Full Universe'!BK367) -> TRUE | O11: =ISBLANK('Full Universe'!BL367) -> TRUE | ... AJ11: =ISBLANK('Full Universe'!CG367) -> TRUE | AK11: =ISNUMBER(MATCH(C11,[1]Europe!$B$2:$B$15,0)) -> TRUE | AL11: =ISBLANK('Full Universe'!CJ367) -> TRUE | AM11: Green - not applicable | AN11: =ISNUMBER(MATCH(C11,'Selected Companies'!$D$2:$D$101,0)) -> TRUE | AO11: =_xlfn.XLOOKUP(C11,[2]generation_steps!$C$2:$C$18963,[2]generation_steps!$CM$2:$CM$18963) -> 46.694402 | AP11: =_xlfn.XLOOKUP(C11,[2]generation_steps!$C$2:$C$18963,[2]generation_steps!$CN$2:$CN$18963) -> 1.5
A12: 45709 | B12: SEVERN TRENT | C12: GB00B1FH8J72 | D12: XLON | E12: =_xlfn.XLOOKUP(C12,[2]generation_steps!$I$2:$I$500,[2]generation_steps!$L$2:$L$500) -> 0.00082416423 | F12: =_xlfn.XLOOKUP(C12,[2]full_dataframe_final!$C$2:$C$101,[2]full_dataframe_final!$H$2:$H$101,"") -> 0.014285714 | G12: 65102030 | H12: =ISBLANK('Full Universe'!BE396) -> TRUE | I12: =ISBLANK('Full Universe'!BF396) -> TRUE | J12: =ISBLANK('Full Universe'!BG396) -> TRUE | K12: =ISBLANK('Full Universe'!BH396) -> TRUE | L12: =ISBLANK('Full Universe'!BI396) -> TRUE | M12: =ISBLANK('Full Universe'!BJ396) -> TRUE | N12: =ISBLANK('Full Universe'!BK396) -> TRUE | O12: =ISBLANK('Full Universe'!BL396) -> TRUE | ... AJ12: =ISBLANK('Full Universe'!CG396) -> TRUE | AK12: =ISNUMBER(MATCH(C12,[1]Europe!$B$2:$B$15,0)) -> TRUE | AL12: =ISBLANK('Full Universe'!CJ396) -> TRUE | AM12: Green - not applicable | AN12: =ISNUMBER(MATCH(C12,'Selected Companies'!$D$2:$D$101,0)) -> TRUE | AO12: =_xlfn.XLOOKUP(C12,[2]generation_steps!$C$2:$C$18963,[2]generation_steps!$CM$2:$CM$18963) -> 59.179045 | AP12: =_xlfn.XLOOKUP(C12,[2]generation_steps!$C$2:$C$18963,[2]generation_steps!$CN$2:$CN$18963) -> 1.5
A13: 45709 | B13: TERNA | C13: IT0003242622 | D13: MTAA | E13: =_xlfn.XLOOKUP(C13,[2]generation_steps!$I$2:$I$500,[2]generation_steps!$L$2:$L$500) -> 0.0011336724 | F13: =_xlfn.XLOOKUP(C13,[2]full_dataframe_final!$C$2:$C$101,[2]full_dataframe_final!$H$2:$H$101,"") -> 0.0035714286 | G13: 65101015 | H13: =ISBLANK('Full Universe'!BE457) -> TRUE | I13: =ISBLANK('Full Universe'!BF457) -> TRUE | J13: =ISBLANK('Full Universe'!BG457) -> TRUE | K13: =ISBLANK('Full Universe'!BH457) -> TRUE | L13: =ISBLANK('Full Universe'!BI457) -> TRUE | M13: =ISBLANK('Full Universe'!BJ457) -> TRUE | N13: =ISBLANK('Full Universe'!BK457) -> TRUE | O13: =ISBLANK('Full Universe'!BL457) -> TRUE | ... AJ13: =ISBLANK('Full Universe'!CG457) -> TRUE | AK13: =ISNUMBER(MATCH(C13,[1]Europe!$B$2:$B$15,0)) -> TRUE | AL13: =ISBLANK('Full Universe'!CJ457) -> TRUE | AM13: Green - not applicable | AN13: =ISNUMBER(MATCH(C13,'Selected Companies'!$D$2:$D$101,0)) -> TRUE | AO13: =_xlfn.XLOOKUP(C13,[2]generation_steps!$C$2:$C$18963,[2]generation_steps!$CM$2:$CM$18963) -> 134.74022 | AP13: =_xlfn.XLOOKUP(C13,[2]generation_steps!$C$2:$C$18963,[2]generation_steps!$CN$2:$CN$18963) -> 1.5
A14: 45709 | B14: VESTAS WIND SYSTEMS | C14: DK0061539921 | D14: XCSE | E14: =_xlfn.XLOOKUP(C14,[2]generation_steps!$I$2:$I$500,[2]generation_steps!$L$2:$L$500) -> 0.0011846538 | F14: =_xlfn.XLOOKUP(C14,[2]full_dataframe_final!$C$2:$C$101,[2]full_dataframe_final!$H$2:$H$101,"") -> 0.014285714 | G14: 60102020 | H14: =ISBLANK('Full Universe'!BE483) -> TRUE | I14: =ISBLANK('Full Universe'!BF483) -> TRUE | J14: =ISBLANK('Full Universe'!BG483) -> TRUE | K14: =ISBLANK('Full Universe'!BH483) -> TRUE | L14: =ISBLANK('Full Universe'!BI483) -> TRUE | M14: =ISBLANK('Full Universe'!BJ483) -> TRUE | N14: =ISBLANK('Full Universe'!BK483) -> TRUE | O14: =ISBLANK('Full Universe'!BL483) -> TRUE | ... AJ14: =ISBLANK('Full Universe'!CG483) -> TRUE | AK14: =ISNUMBER(MATCH(C14,[1]Europe!$B$2:$B$15,0)) -> TRUE | AL14: =ISBLANK('Full Universe'!CJ483) -> TRUE | AM14: Green - not applicable | AN14: =ISNUMBER(MATCH(C14,'Selected Companies'!$D$2:$D$101,0)) -> TRUE | AO14: =_xlfn.XLOOKUP(C14,[2]generation_steps!$C$2:$C$18963,[2]generation_steps!$CM$2:$CM$18963) -> 239.55135 | AP14: =_xlfn.XLOOKUP(C14,[2]generation_steps!$C$2:$C$18963,[2]generation_steps!$CN$2:$CN$18963) -> 1.4666667
A15: 45709 | B15: WIENERBERGER AG | C15: AT0000831706 | D15: WBAH | E15: =_xlfn.XLOOKUP(C15,[2]generation_steps!$I$2:$I$500,[2]generation_steps!$L$2:$L$500) -> 0.00032723448 | F15: =_xlfn.XLOOKUP(C15,[2]full_dataframe_final!$C$2:$C$101,[2]full_dataframe_final!$H$2:$H$101,"") -> 0.0035714286 | G15: 50101035 | H15: =ISBLANK('Full Universe'!BE493) -> TRUE | I15: =ISBLANK('Full Universe'!BF493) -> TRUE | J15: =ISBLANK('Full Universe'!BG493) -> TRUE | K15: =ISBLANK('Full Universe'!BH493) -> TRUE | L15: =ISBLANK('Full Universe'!BI493) -> TRUE | M15: =ISBLANK('Full Universe'!BJ493) -> TRUE | N15: =ISBLANK('Full Universe'!BK493) -> TRUE | O15: =ISBLANK('Full Universe'!BL493) -> TRUE | ... AJ15: =ISBLANK('Full Universe'!CG493) -> TRUE | AK15: =ISNUMBER(MATCH(C15,[1]Europe!$B$2:$B$15,0)) -> TRUE | AL15: =ISBLANK('Full Universe'!CJ493) -> TRUE | AM15: Green - not applicable | AN15: =ISNUMBER(MATCH(C15,'Selected Companies'!$D$2:$D$101,0)) -> TRUE | AO15: =_xlfn.XLOOKUP(C15,[2]generation_steps!$C$2:$C$18963,[2]generation_steps!$CM$2:$CM$18963) -> 1738.1272 | AP15: =_xlfn.XLOOKUP(C15,[2]generation_steps!$C$2:$C$18963,[2]generation_steps!$CN$2:$CN$18963) -> 1.5333333
A16: 45709 | B16: 3I GROUP PLC | C16: GB00B1YW4409 | D16: XLON | E16: =_xlfn.XLOOKUP(C16,[2]generation_steps!$I$2:$I$500,[2]generation_steps!$L$2:$L$500) -> 0.0045434353 | F16: =_xlfn.XLOOKUP(C16,[2]full_dataframe_final!$C$2:$C$101,[2]full_dataframe_final!$H$2:$H$101,"") | G16: 30202010 | H16: =ISBLANK('Full Universe'!BE2) -> TRUE | I16: =ISBLANK('Full Universe'!BF2) -> TRUE | J16: =ISBLANK('Full Universe'!BG2) -> TRUE | K16: =ISBLANK('Full Universe'!BH2) -> TRUE | L16: =ISBLANK('Full Universe'!BI2) -> TRUE | M16: =ISBLANK('Full Universe'!BJ2) -> TRUE | N16: =ISBLANK('Full Universe'!BK2) -> TRUE | O16: =ISBLANK('Full Universe'!BL2) -> TRUE | ... AJ16: =ISBLANK('Full Universe'!CG2) -> TRUE | AK16: =ISNUMBER(MATCH(C16,[1]Europe!$B$2:$B$15,0)) -> FALSE | AL16: =ISBLANK('Full Universe'!CJ2) -> TRUE | AM16: 1.9270395 | AN16: =ISNUMBER(MATCH(C16,'Selected Companies'!$D$2:$D$101,0)) -> FALSE | AO16: =_xlfn.XLOOKUP(C16,[2]generation_steps!$C$2:$C$18963,[2]generation_steps!$CM$2:$CM$18963) -> 13.164173 | AP16: =_xlfn.XLOOKUP(C16,[2]generation_steps!$C$2:$C$18963,[2]generation_steps!$CN$2:$CN$18963) -> 1.5333333
A17: 45709 | B17: A2A | C17: IT0001233417 | D17: MTAA | E17: =_xlfn.XLOOKUP(C17,[2]generation_steps!$I$2:$I$500,[2]generation_steps!$L$2:$L$500) -> 0.00031493296 | F17: =_xlfn.XLOOKUP(C17,[2]full_dataframe_final!$C$2:$C$101,[2]full_dataframe_final!$H$2:$H$101,"") | G17: 65101015 | H17: =ISBLANK('Full Universe'!BE3) -> TRUE | I17: =ISBLANK('Full Universe'!BF3) -> TRUE | J17: =ISBLANK('Full Universe'!BG3) -> TRUE | K17: =ISBLANK('Full Universe'!BH3) -> TRUE | L17: =ISBLANK('Full Universe'!BI3) -> TRUE | M17: =ISBLANK('Full Universe'!BJ3) -> TRUE | N17: =ISBLANK('Full Universe'!BK3) -> TRUE | O17: =ISBLANK('Full Universe'!BL3) -> TRUE | ... AJ17: =ISBLANK('Full Universe'!CG3) -> TRUE | AK17: =ISNUMBER(MATCH(C17,[1]Europe!$B$2:$B$15,0)) -> FALSE | AL17: =ISBLANK('Full Universe'!CJ3) -> TRUE | AM17: 2.225 | AN17: =ISNUMBER(MATCH(C17,'Selected Companies'!$D$2:$D$101,0)) -> FALSE | AO17: =_xlfn.XLOOKUP(C17,[2]generation_steps!$C$2:$C$18963,[2]generation_steps!$CM$2:$CM$18963) -> 1181.0697 | AP17: =_xlfn.XLOOKUP(C17,[2]generation_steps!$C$2:$C$18963,[2]generation_steps!$CN$2:$CN$18963) -> 1.5
A18: 45709 | B18: AAK AB | C18: SE0011337708 | D18: XSTO | E18: =_xlfn.XLOOKUP(C18,[2]generation_steps!$I$2:$I$500,[2]generation_steps!$L$2:$L$500) -> 0.00043166138 | F18: =_xlfn.XLOOKUP(C18,[2]full_dataframe_final!$C$2:$C$101,[2]full_dataframe_final!$H$2:$H$101,"") | G18: 45102020 | H18: =ISBLANK('Full Universe'!BE4) -> TRUE | I18: =ISBLANK('Full Universe'!BF4) -> TRUE | J18: =ISBLANK('Full Universe'!BG4) -> TRUE | K18: =ISBLANK('Full Universe'!BH4) -> TRUE | L18: =ISBLANK('Full Universe'!BI4) -> TRUE | M18: =ISBLANK('Full Universe'!BJ4) -> TRUE | N18: =ISBLANK('Full Universe'!BK4) -> TRUE | O18: =ISBLANK('Full Universe'!BL4) -> TRUE | ... AJ18: =ISBLANK('Full Universe'!CG4) -> TRUE | AK18: =ISNUMBER(MATCH(C18,[1]Europe!$B$2:$B$15,0)) -> FALSE | AL18: =ISBLANK('Full Universe'!CJ4) -> TRUE | AM18: 2.5321528 | AN18: =ISNUMBER(MATCH(C18,'Selected Companies'!$D$2:$D$101,0)) -> FALSE | AO18: =_xlfn.XLOOKUP(C18,[2]generation_steps!$C$2:$C$18963,[2]generation_steps!$CM$2:$CM$18963) -> 1223.803 | AP18: =_xlfn.XLOOKUP(C18,[2]generation_steps!$C$2:$C$18963,[2]generation_steps!$CN$2:$CN$18963) -> 1.5
A19: 45709 | B19: AALBERTS NV | C19: NL0000852564 | D19: XAMS | E19: =_xlfn.XLOOKUP(C19,[2]generation_steps!$I$2:$I$500,[2]generation_steps!$L$2:$L$500) -> 0.0002618455 | F19: =_xlfn.XLOOKUP(C19,[2]full_dataframe_final!$C$2:$C$101,[2]full_dataframe_final!$H$2:$H$101,"") | G19: 50202020 | H19: =ISBLANK('Full Universe'!BE5) -> TRUE | I19: =ISBLANK('Full Universe'!BF5) -> TRUE | J19: =ISBLANK('Full Universe'!BG5) -> TRUE | K19: =ISBLANK('Full Universe'!BH5) -> TRUE | L19: =ISBLANK('Full Universe'!BI5) -> TRUE | M19: =ISBLANK('Full Universe'!BJ5) -> TRUE | N19: =ISBLANK('Full Universe'!BK5) -> TRUE | O19: =ISBLANK('Full Universe'!BL5) -> TRUE | ... AJ19: =ISBLANK('Full Universe'!CG5) -> TRUE | AK19: =ISNUMBER(MATCH(C19,[1]Europe!$B$2:$B$15,0)) -> FALSE | AL19: =ISBLANK('Full Universe'!CJ5) -> TRUE | AM19: 3.25 | AN19: =ISNUMBER(MATCH(C19,'Selected Companies'!$D$2:$D$101,0)) -> FALSE | AO19: =_xlfn.XLOOKUP(C19,[2]generation_steps!$C$2:$C$18963,[2]generation_steps!$CM$2:$CM$18963) -> 1619.7555 | AP19: =_xlfn.XLOOKUP(C19,[2]generation_steps!$C$2:$C$18963,[2]generation_steps!$CN$2:$CN$18963) -> 1.5
A20: 45709 | B20: AB INBEV | C20: BE0974293251 | D20: XBRU | E20: =_xlfn.XLOOKUP(C20,[2]generation_steps!$I$2:$I$500,[2]generation_steps!$L$2:$L$500) -> 0.0053561082 | F20: =_xlfn.XLOOKUP(C20,[2]full_dataframe_final!$C$2:$C$101,[2]full_dataframe_final!$H$2:$H$101,"") | G20: 45101010 | H20: =ISBLANK('Full Universe'!BE6) -> TRUE | I20: =ISBLANK('Full Universe'!BF6) -> TRUE | J20: =ISBLANK('Full Universe'!BG6) -> TRUE | K20: =ISBLANK('Full Universe'!BH6) -> TRUE | L20: =ISBLANK('Full Universe'!BI6) -> TRUE | M20: =ISBLANK('Full Universe'!BJ6) -> TRUE | N20: =ISBLANK('Full Universe'!BK6) -> TRUE | O20: =ISBLANK('Full Universe'!BL6) -> TRUE | ... AJ20: =ISBLANK('Full Universe'!CG6) -> TRUE | AK20: =ISNUMBER(MATCH(C20,[1]Europe!$B$2:$B$15,0)) -> FALSE | AL20: =ISBLANK('Full Universe'!CJ6) -> FALSE | AM20: 2.7005395 | AN20: =ISNUMBER(MATCH(C20,'Selected Companies'!$D$2:$D$101,0)) -> FALSE | AO20: =_xlfn.XLOOKUP(C20,[2]generation_steps!$C$2:$C$18963,[2]generation_steps!$CM$2:$CM$18963) -> 128.46807 | AP20: =_xlfn.XLOOKUP(C20,[2]generation_steps!$C$2:$C$18963,[2]generation_steps!$CN$2:$CN$18963) -> 1.5
A21: 45709 | B21: AB SAGAX CLASS B | C21: SE0005127818 | D21: XSTO | E21: =_xlfn.XLOOKUP(C21,[2]generation_steps!$I$2:$I$500,[2]generation_steps!$L$2:$L$500) -> 0.00040208942 | F21: =_xlfn.XLOOKUP(C21,[2]full_dataframe_final!$C$2:$C$101,[2]full_dataframe_final!$H$2:$H$101,"") | G21: 35101010 | H21: =ISBLANK('Full Universe'!BE7) -> TRUE | I21: =ISBLANK('Full Universe'!BF7) -> TRUE | J21: =ISBLANK('Full Universe'!BG7) -> TRUE | K21: =ISBLANK('Full Universe'!BH7) -> TRUE | L21: =ISBLANK('Full Universe'!BI7) -> TRUE | M21: =ISBLANK('Full Universe'!BJ7) -> TRUE | N21: =ISBLANK('Full Universe'!BK7) -> TRUE | O21: =ISBLANK('Full Universe'!BL7) -> TRUE | ... AJ21: =ISBLANK('Full Universe'!CG7) -> TRUE | AK21: =ISNUMBER(MATCH(C21,[1]Europe!$B$2:$B$15,0)) -> FALSE | AL21: =ISBLANK('Full Universe'!CJ7) -> FALSE | AM21: 3.4860513 | AN21: =ISNUMBER(MATCH(C21,'Selected Companies'!$D$2:$D$101,0)) -> FALSE | AO21: =_xlfn.XLOOKUP(C21,[2]generation_steps!$C$2:$C$18963,[2]generation_steps!$CM$2:$CM$18963) -> 3.5372492 | AP21: =_xlfn.XLOOKUP(C21,[2]generation_steps!$C$2:$C$18963,[2]generation_steps!$CN$2:$CN$18963) -> 1.4
A22: 45709 | B22: ABB LTD | C22: CH0012221716 | D22: XSWX | E22: =_xlfn.XLOOKUP(C22,[2]generation_steps!$I$2:$I$500,[2]generation_steps!$L$2:$L$500) -> 0.0068947658 | F22: =_xlfn.XLOOKUP(C22,[2]full_dataframe_final!$C$2:$C$101,[2]full_dataframe_final!$H$2:$H$101,"") | G22: 50202010 | H22: =ISBLANK('Full Universe'!BE8) -> TRUE | I22: =ISBLANK('Full Universe'!BF8) -> TRUE | J22: =ISBLANK('Full Universe'!BG8) -> TRUE | K22: =ISBLANK('Full Universe'!BH8) -> TRUE | L22: =ISBLANK('Full Universe'!BI8) -> TRUE | M22: =ISBLANK('Full Universe'!BJ8) -> TRUE | N22: =ISBLANK('Full Universe'!BK8) -> TRUE | O22: =ISBLANK('Full Universe'!BL8) -> TRUE | ... AJ22: =ISBLANK('Full Universe'!CG8) -> TRUE | AK22: =ISNUMBER(MATCH(C22,[1]Europe!$B$2:$B$15,0)) -> FALSE | AL22: =ISBLANK('Full Universe'!CJ8) -> TRUE | AM22: 1.3245504 | AN22: =ISNUMBER(MATCH(C22,'Selected Companies'!$D$2:$D$101,0)) -> FALSE | AO22: =_xlfn.XLOOKUP(C22,[2]generation_steps!$C$2:$C$18963,[2]generation_steps!$CM$2:$CM$18963) -> 5228.3624 | AP22: =_xlfn.XLOOKUP(C22,[2]generation_steps!$C$2:$C$18963,[2]generation_steps!$CN$2:$CN$18963) -> 1.5
A23: 45709 | B23: ABN AMRO BANK N.V. | C23: NL0011540547 | D23: XAMS | E23: =_xlfn.XLOOKUP(C23,[2]generation_steps!$I$2:$I$500,[2]generation_steps!$L$2:$L$500) -> 0.00094665931 | F23: =_xlfn.XLOOKUP(C23,[2]full_dataframe_final!$C$2:$C$101,[2]full_dataframe_final!$H$2:$H$101,"") | G23: 30101010 | H23: =ISBLANK('Full Universe'!BE9) -> TRUE | I23: =ISBLANK('Full Universe'!BF9) -> TRUE | J23: =ISBLANK('Full Universe'!BG9) -> TRUE | K23: =ISBLANK('Full Universe'!BH9) -> TRUE | L23: =ISBLANK('Full Universe'!BI9) -> TRUE | M23: =ISBLANK('Full Universe'!BJ9) -> TRUE | N23: =ISBLANK('Full Universe'!BK9) -> TRUE | O23: =ISBLANK('Full Universe'!BL9) -> TRUE | ... AJ23: =ISBLANK('Full Universe'!CG9) -> TRUE | AK23: =ISNUMBER(MATCH(C23,[1]Europe!$B$2:$B$15,0)) -> FALSE | AL23: =ISBLANK('Full Universe'!CJ9) -> TRUE | AM23: 3.1866667 | AN23: =ISNUMBER(MATCH(C23,'Selected Companies'!$D$2:$D$101,0)) -> FALSE | AO23: =_xlfn.XLOOKUP(C23,[2]generation_steps!$C$2:$C$18963,[2]generation_steps!$CM$2:$CM$18963) -> 397.99801 | AP23: =_xlfn.XLOOKUP(C23,[2]generation_steps!$C$2:$C$18963,[2]generation_steps!$CN$2:$CN$18963) -> 1.6
A24: 45709 | B24: ABRDN | C24: GB00BF8Q6K64 | D24: XLON | E24: =_xlfn.XLOOKUP(C24,[2]generation_steps!$I$2:$I$500,[2]generation_steps!$L$2:$L$500) -> 0.00029769892 | F24: =_xlfn.XLOOKUP(C24,[2]full_dataframe_final!$C$2:$C$101,[2]full_dataframe_final!$H$2:$H$101,"") | G24: 30202010 | H24: =ISBLANK('Full Universe'!BE10) -> TRUE | I24: =ISBLANK('Full Universe'!BF10) -> TRUE | J24: =ISBLANK('Full Universe'!BG10) -> TRUE | K24: =ISBLANK('Full Universe'!BH10) -> TRUE | L24: =ISBLANK('Full Universe'!BI10) -> TRUE | M24: =ISBLANK('Full Universe'!BJ10) -> TRUE | N24: =ISBLANK('Full Universe'!BK10) -> TRUE | O24: =ISBLANK('Full Universe'!BL10) -> TRUE | ... AJ24: =ISBLANK('Full Universe'!CG10) -> TRUE | AK24: =ISNUMBER(MATCH(C24,[1]Europe!$B$2:$B$15,0)) -> FALSE | AL24: =ISBLANK('Full Universe'!CJ10) -> TRUE | AM24: 3.06 | AN24: =ISNUMBER(MATCH(C24,'Selected Companies'!$D$2:$D$101,0)) -> FALSE | AO24: =_xlfn.XLOOKUP(C24,[2]generation_steps!$C$2:$C$18963,[2]generation_steps!$CM$2:$CM$18963) -> 925.58576 | AP24: =_xlfn.XLOOKUP(C24,[2]generation_steps!$C$2:$C$18963,[2]generation_steps!$CN$2:$CN$18963) -> 1.5333333
A25: 45709 | B25: ACCELLERON INDUSTR. | C25: CH1169360919 | D25: XSWX | E25: =_xlfn.XLOOKUP(C25,[2]generation_steps!$I$2:$I$500,[2]generation_steps!$L$2:$L$500) -> 0.00040576606 | F25: =_xlfn.XLOOKUP(C25,[2]full_dataframe_final!$C$2:$C$101,[2]full_dataframe_final!$H$2:$H$101,"") | G25: 50204030 | H25: =ISBLANK('Full Universe'!BE11) -> TRUE | I25: =ISBLANK('Full Universe'!BF11) -> TRUE | J25: =ISBLANK('Full Universe'!BG11) -> TRUE | K25: =ISBLANK('Full Universe'!BH11) -> TRUE | L25: =ISBLANK('Full Universe'!BI11) -> TRUE | M25: =ISBLANK('Full Universe'!BJ11) -> TRUE | N25: =ISBLANK('Full Universe'!BK11) -> TRUE | O25: =ISBLANK('Full Universe'!BL11) -> TRUE | ... AJ25: =ISBLANK('Full Universe'!CG11) -> TRUE | AK25: =ISNUMBER(MATCH(C25,[1]Europe!$B$2:$B$15,0)) -> FALSE | AL25: =ISBLANK('Full Universe'!CJ11) -> TRUE | AM25: 3.55 | AN25: =ISNUMBER(MATCH(C25,'Selected Companies'!$D$2:$D$101,0)) -> FALSE | AO25: =_xlfn.XLOOKUP(C25,[2]generation_steps!$C$2:$C$18963,[2]generation_steps!$CM$2:$CM$18963) -> 20.223472 | AP25: =_xlfn.XLOOKUP(C25,[2]generation_steps!$C$2:$C$18963,[2]generation_steps!$CN$2:$CN$18963) -> 1.5333333
A26: 45709 | B26: ACCOR | C26: FR0000120404 | D26: XPAR | E26: =_xlfn.XLOOKUP(C26,[2]generation_steps!$I$2:$I$500,[2]generation_steps!$L$2:$L$500) -> 0.00078636814 | F26: =_xlfn.XLOOKUP(C26,[2]full_dataframe_final!$C$2:$C$101,[2]full_dataframe_final!$H$2:$H$101,"") | G26: 40501025 | H26: =ISBLANK('Full Universe'!BE12) -> TRUE | I26: =ISBLANK('Full Universe'!BF12) -> TRUE | J26: =ISBLANK('Full Universe'!BG12) -> TRUE | K26: =ISBLANK('Full Universe'!BH12) -> TRUE | L26: =ISBLANK('Full Universe'!BI12) -> TRUE | M26: =ISBLANK('Full Universe'!BJ12) -> TRUE | N26: =ISBLANK('Full Universe'!BK12) -> TRUE | O26: =ISBLANK('Full Universe'!BL12) -> TRUE | ... AJ26: =ISBLANK('Full Universe'!CG12) -> TRUE | AK26: =ISNUMBER(MATCH(C26,[1]Europe!$B$2:$B$15,0)) -> FALSE | AL26: =ISBLANK('Full Universe'!CJ12) -> TRUE | AM26: 2.3914062 | AN26: =ISNUMBER(MATCH(C26,'Selected Companies'!$D$2:$D$101,0)) -> FALSE | AO26: =_xlfn.XLOOKUP(C26,[2]generation_steps!$C$2:$C$18963,[2]generation_steps!$CM$2:$CM$18963) -> 514.67199 | AP26: =_xlfn.XLOOKUP(C26,[2]generation_steps!$C$2:$C$18963,[2]generation_steps!$CN$2:$CN$18963) -> 2
A27: 45709 | B27: ACKERMANS V.HAAREN | C27: BE0003764785 | D27: XBRU | E27: =_xlfn.XLOOKUP(C27,[2]generation_steps!$I$2:$I$500,[2]generation_steps!$L$2:$L$500) -> 0.00041518649 | F27: =_xlfn.XLOOKUP(C27,[2]full_dataframe_final!$C$2:$C$101,[2]full_dataframe_final!$H$2:$H$101,"") | G27: 30202000 | H27: =ISBLANK('Full Universe'!BE13) -> TRUE | I27: =ISBLANK('Full Universe'!BF13) -> TRUE | J27: =ISBLANK('Full Universe'!BG13) -> TRUE | K27: =ISBLANK('Full Universe'!BH13) -> TRUE | L27: =ISBLANK('Full Universe'!BI13) -> TRUE | M27: =ISBLANK('Full Universe'!BJ13) -> TRUE | N27: =ISBLANK('Full Universe'!BK13) -> TRUE | O27: =ISBLANK('Full Universe'!BL13) -> TRUE | ... AJ27: =ISBLANK('Full Universe'!CG13) -> TRUE | AK27: =ISNUMBER(MATCH(C27,[1]Europe!$B$2:$B$15,0)) -> FALSE | AL27: =ISBLANK('Full Universe'!CJ13) -> FALSE | AM27: 3.07 | AN27: =ISNUMBER(MATCH(C27,'Selected Companies'!$D$2:$D$101,0)) -> FALSE | AO27: =_xlfn.XLOOKUP(C27,[2]generation_steps!$C$2:$C$18963,[2]generation_steps!$CM$2:$CM$18963) -> 130.59557 | AP27: =_xlfn.XLOOKUP(C27,[2]generation_steps!$C$2:$C$18963,[2]generation_steps!$CN$2:$CN$18963) -> 1.6666667
... A49: 45709 | B49: ALM BRAND AS | C49: DK0015250344 | D49: XCSE | E49: =_xlfn.XLOOKUP(C49,[2]generation_steps!$I$2:$I$500,[2]generation_steps!$L$2:$L$500) -> 0.00029831992 | F49: =_xlfn.XLOOKUP(C49,[2]full_dataframe_final!$C$2:$C$101,[2]full_dataframe_final!$H$2:$H$101,"") | G49: 30302010 | H49: =ISBLANK('Full Universe'!BE35) -> TRUE | I49: =ISBLANK('Full Universe'!BF35) -> TRUE | J49: =ISBLANK('Full Universe'!BG35) -> TRUE | K49: =ISBLANK('Full Universe'!BH35) -> TRUE | L49: =ISBLANK('Full Universe'!BI35) -> TRUE | M49: =ISBLANK('Full Universe'!BJ35) -> TRUE | N49: =ISBLANK('Full Universe'!BK35) -> TRUE | O49: =ISBLANK('Full Universe'!BL35) -> TRUE | ... AJ49: =ISBLANK('Full Universe'!CG35) -> TRUE | AK49: =ISNUMBER(MATCH(C49,[1]Europe!$B$2:$B$15,0)) -> FALSE | AL49: =ISBLANK('Full Universe'!CJ35) -> FALSE | AM49: 3.55 | AN49: =ISNUMBER(MATCH(C49,'Selected Companies'!$D$2:$D$101,0)) -> FALSE | AO49: =_xlfn.XLOOKUP(C49,[2]generation_steps!$C$2:$C$18963,[2]generation_steps!$CM$2:$CM$18963) -> 401.80094 | AP49: =_xlfn.XLOOKUP(C49,[2]generation_steps!$C$2:$C$18963,[2]generation_steps!$CN$2:$CN$18963) -> 1.5333333
A50: 45709 | B50: ALTEN | C50: FR0000071946 | D50: XPAR | E50: =_xlfn.XLOOKUP(C50,[2]generation_steps!$I$2:$I$500,[2]generation_steps!$L$2:$L$500) -> 0.00024034754 | F50: =_xlfn.XLOOKUP(C50,[2]full_dataframe_final!$C$2:$C$101,[2]full_dataframe_final!$H$2:$H$101,"") | G50: 10101010 | H50: =ISBLANK('Full Universe'!BE37) -> TRUE | I50: =ISBLANK('Full Universe'!BF37) -> TRUE | J50: =ISBLANK('Full Universe'!BG37) -> TRUE | K50: =ISBLANK('Full Universe'!BH37) -> TRUE | L50: =ISBLANK('Full Universe'!BI37) -> TRUE | M50: =ISBLANK('Full Universe'!BJ37) -> TRUE | N50: =ISBLANK('Full Universe'!BK37) -> TRUE | O50: =ISBLANK('Full Universe'!BL37) -> TRUE | ... AJ50: =ISBLANK('Full Universe'!CG37) -> TRUE | AK50: =ISNUMBER(MATCH(C50,[1]Europe!$B$2:$B$15,0)) -> FALSE | AL50: =ISBLANK('Full Universe'!CJ37) -> TRUE | AM50: 2.1766074 | AN50: =ISNUMBER(MATCH(C50,'Selected Companies'!$D$2:$D$101,0)) -> FALSE | AO50: =_xlfn.XLOOKUP(C50,[2]generation_steps!$C$2:$C$18963,[2]generation_steps!$CM$2:$CM$18963) -> 15.015218 | AP50: =_xlfn.XLOOKUP(C50,[2]generation_steps!$C$2:$C$18963,[2]generation_steps!$CN$2:$CN$18963) -> 1.5
A51: 45709 | B51: AMADEUS IT GROUP | C51: ES0109067019 | D51: XMAD | E51: =_xlfn.XLOOKUP(C51,[2]generation_steps!$I$2:$I$500,[2]generation_steps!$L$2:$L$500) -> 0.0029993329 | F51: =_xlfn.XLOOKUP(C51,[2]full_dataframe_final!$C$2:$C$101,[2]full_dataframe_final!$H$2:$H$101,"") | G51: 10101010 | H51: =ISBLANK('Full Universe'!BE38) -> TRUE | I51: =ISBLANK('Full Universe'!BF38) -> TRUE | J51: =ISBLANK('Full Universe'!BG38) -> TRUE | K51: =ISBLANK('Full Universe'!BH38) -> TRUE | L51: =ISBLANK('Full Universe'!BI38) -> TRUE | M51: =ISBLANK('Full Universe'!BJ38) -> TRUE | N51: =ISBLANK('Full Universe'!BK38) -> TRUE | O51: =ISBLANK('Full Universe'!BL38) -> TRUE | ... AJ51: =ISBLANK('Full Universe'!CG38) -> TRUE | AK51: =ISNUMBER(MATCH(C51,[1]Europe!$B$2:$B$15,0)) -> FALSE | AL51: =ISBLANK('Full Universe'!CJ38) -> TRUE | AM51: 2.1812093 | AN51: =ISNUMBER(MATCH(C51,'Selected Companies'!$D$2:$D$101,0)) -> FALSE | AO51: =_xlfn.XLOOKUP(C51,[2]generation_steps!$C$2:$C$18963,[2]generation_steps!$CM$2:$CM$18963) -> 7.5164737 | AP51: =_xlfn.XLOOKUP(C51,[2]generation_steps!$C$2:$C$18963,[2]generation_steps!$CN$2:$CN$18963) -> 1.7333333
A52: 45709 | B52: AMBU A/S CLASS B | C52: DK0060946788 | D52: XCSE | E52: =_xlfn.XLOOKUP(C52,[2]generation_steps!$I$2:$I$500,[2]generation_steps!$L$2:$L$500) -> 0.00030489636 | F52: =_xlfn.XLOOKUP(C52,[2]full_dataframe_final!$C$2:$C$101,[2]full_dataframe_final!$H$2:$H$101,"") -> 0.00057256794 | G52: 20102010 | H52: =ISBLANK('Full Universe'!BE39) -> TRUE | I52: =ISBLANK('Full Universe'!BF39) -> TRUE | J52: =ISBLANK('Full Universe'!BG39) -> TRUE | K52: =ISBLANK('Full Universe'!BH39) -> TRUE | L52: =ISBLANK('Full Universe'!BI39) -> TRUE | M52: =ISBLANK('Full Universe'!BJ39) -> TRUE | N52: =ISBLANK('Full Universe'!BK39) -> TRUE | O52: =ISBLANK('Full Universe'!BL39) -> TRUE | ... AJ52: =ISBLANK('Full Universe'!CG39) -> TRUE | AK52: =ISNUMBER(MATCH(C52,[1]Europe!$B$2:$B$15,0)) -> FALSE | AL52: =ISBLANK('Full Universe'!CJ39) -> TRUE | AM52: 1.8879955 | AN52: =ISNUMBER(MATCH(C52,'Selected Companies'!$D$2:$D$101,0)) -> TRUE | AO52: =_xlfn.XLOOKUP(C52,[2]generation_steps!$C$2:$C$18963,[2]generation_steps!$CM$2:$CM$18963) -> 110.50637 | AP52: =_xlfn.XLOOKUP(C52,[2]generation_steps!$C$2:$C$18963,[2]generation_steps!$CN$2:$CN$18963) -> 1.6666667
A53: 45709 | B53: AMPLIFON | C53: IT0004056880 | D53: MTAA | E53: =_xlfn.XLOOKUP(C53,[2]generation_steps!$I$2:$I$500,[2]generation_steps!$L$2:$L$500) -> 0.00021991667 | F53: =_xlfn.XLOOKUP(C53,[2]full_dataframe_final!$C$2:$C$101,[2]full_dataframe_final!$H$2:$H$101,"") | G53: 20102015 | H53: =ISBLANK('Full Universe'!BE40) -> TRUE | I53: =ISBLANK('Full Universe'!BF40) -> TRUE | J53: =ISBLANK('Full Universe'!BG40) -> TRUE | K53: =ISBLANK('Full Universe'!BH40) -> TRUE | L53: =ISBLANK('Full Universe'!BI40) -> TRUE | M53: =ISBLANK('Full Universe'!BJ40) -> TRUE | N53: =ISBLANK('Full Universe'!BK40) -> TRUE | O53: =ISBLANK('Full Universe'!BL40) -> TRUE | ... AJ53: =ISBLANK('Full Universe'!CG40) -> TRUE | AK53: =ISNUMBER(MATCH(C53,[1]Europe!$B$2:$B$15,0)) -> FALSE | AL53: =ISBLANK('Full Universe'!CJ40) -> TRUE | AM53: 2.9957682 | AN53: =ISNUMBER(MATCH(C53,'Selected Companies'!$D$2:$D$101,0)) -> FALSE | AO53: =_xlfn.XLOOKUP(C53,[2]generation_steps!$C$2:$C$18963,[2]generation_steps!$CM$2:$CM$18963) -> 16.751855 | AP53: =_xlfn.XLOOKUP(C53,[2]generation_steps!$C$2:$C$18963,[2]generation_steps!$CN$2:$CN$18963) -> 1.5333333
A54: 45709 | B54: AMUNDI | C54: FR0004125920 | D54: XPAR | E54: =_xlfn.XLOOKUP(C54,[2]generation_steps!$I$2:$I$500,[2]generation_steps!$L$2:$L$500) -> 0.00038896731 | F54: =_xlfn.XLOOKUP(C54,[2]full_dataframe_final!$C$2:$C$101,[2]full_dataframe_final!$H$2:$H$101,"") | G54: 30202010 | H54: =ISBLANK('Full Universe'!BE41) -> TRUE | I54: =ISBLANK('Full Universe'!BF41) -> TRUE | J54: =ISBLANK('Full Universe'!BG41) -> TRUE | K54: =ISBLANK('Full Universe'!BH41) -> TRUE | L54: =ISBLANK('Full Universe'!BI41) -> TRUE | M54: =ISBLANK('Full Universe'!BJ41) -> TRUE | N54: =ISBLANK('Full Universe'!BK41) -> TRUE | O54: =ISBLANK('Full Universe'!BL41) -> TRUE | ... AJ54: =ISBLANK('Full Universe'!CG41) -> TRUE | AK54: =ISNUMBER(MATCH(C54,[1]Europe!$B$2:$B$15,0)) -> FALSE | AL54: =ISBLANK('Full Universe'!CJ41) -> TRUE | AM54: 3.01 | AN54: =ISNUMBER(MATCH(C54,'Selected Companies'!$D$2:$D$101,0)) -> FALSE | AO54: =_xlfn.XLOOKUP(C54,[2]generation_steps!$C$2:$C$18963,[2]generation_steps!$CM$2:$CM$18963) -> 36.759526 | AP54: =_xlfn.XLOOKUP(C54,[2]generation_steps!$C$2:$C$18963,[2]generation_steps!$CN$2:$CN$18963) -> 1.5
A55: 45709 | B55: ANDRITZ AG | C55: AT0000730007 | D55: WBAH | E55: =_xlfn.XLOOKUP(C55,[2]generation_steps!$I$2:$I$500,[2]generation_steps!$L$2:$L$500) -> 0.0003220797 | F55: =_xlfn.XLOOKUP(C55,[2]full_dataframe_final!$C$2:$C$101,[2]full_dataframe_final!$H$2:$H$101,"") | G55: 50204000 | H55: =ISBLANK('Full Universe'!BE42) -> TRUE | I55: =ISBLANK('Full Universe'!BF42) -> TRUE | J55: =ISBLANK('Full Universe'!BG42) -> TRUE | K55: =ISBLANK('Full Universe'!BH42) -> TRUE | L55: =ISBLANK('Full Universe'!BI42) -> TRUE | M55: =ISBLANK('Full Universe'!BJ42) -> TRUE | N55: =ISBLANK('Full Universe'!BK42) -> TRUE | O55: =ISBLANK('Full Universe'!BL42) -> TRUE | ... AJ55: =ISBLANK('Full Universe'!CG42) -> TRUE | AK55: =ISNUMBER(MATCH(C55,[1]Europe!$B$2:$B$15,0)) -> FALSE | AL55: =ISBLANK('Full Universe'!CJ42) -> TRUE | AM55: 3.25 | AN55: =ISNUMBER(MATCH(C55,'Selected Companies'!$D$2:$D$101,0)) -> FALSE | AO55: =_xlfn.XLOOKUP(C55,[2]generation_steps!$C$2:$C$18963,[2]generation_steps!$CM$2:$CM$18963) -> 1283.7714 | AP55: =_xlfn.XLOOKUP(C55,[2]generation_steps!$C$2:$C$18963,[2]generation_steps!$CN$2:$CN$18963) -> 1.5
A56: 45709 | B56: ANGLO AMERICAN PLC | C56: GB00B1XZS820 | D56: XLON | E56: =_xlfn.XLOOKUP(C56,[2]generation_steps!$I$2:$I$500,[2]generation_steps!$L$2:$L$500) -> 0.0030702484 | F56: =_xlfn.XLOOKUP(C56,[2]full_dataframe_final!$C$2:$C$101,[2]full_dataframe_final!$H$2:$H$101,"") | G56: 55102000 | H56: =ISBLANK('Full Universe'!BE43) -> TRUE | I56: =ISBLANK('Full Universe'!BF43) -> TRUE | J56: =ISBLANK('Full Universe'!BG43) -> TRUE | K56: =ISBLANK('Full Universe'!BH43) -> TRUE | L56: =ISBLANK('Full Universe'!BI43) -> TRUE | M56: =ISBLANK('Full Universe'!BJ43) -> TRUE | N56: =ISBLANK('Full Universe'!BK43) -> TRUE | O56: =ISBLANK('Full Universe'!BL43) -> TRUE | ... AJ56: =ISBLANK('Full Universe'!CG43) -> TRUE | AK56: =ISNUMBER(MATCH(C56,[1]Europe!$B$2:$B$15,0)) -> FALSE | AL56: =ISBLANK('Full Universe'!CJ43) -> TRUE | AM56: 2.1778911 | AN56: =ISNUMBER(MATCH(C56,'Selected Companies'!$D$2:$D$101,0)) -> FALSE | AO56: =_xlfn.XLOOKUP(C56,[2]generation_steps!$C$2:$C$18963,[2]generation_steps!$CM$2:$CM$18963) -> 2211.0401 | AP56: =_xlfn.XLOOKUP(C56,[2]generation_steps!$C$2:$C$18963,[2]generation_steps!$CN$2:$CN$18963) -> 1.5
A57: 45709 | B57: ANTOFAGASTA PLC | C57: GB0000456144 | D57: XLON | E57: =_xlfn.XLOOKUP(C57,[2]generation_steps!$I$2:$I$500,[2]generation_steps!$L$2:$L$500) -> 0.00068477967 | F57: =_xlfn.XLOOKUP(C57,[2]full_dataframe_final!$C$2:$C$101,[2]full_dataframe_final!$H$2:$H$101,"") | G57: 55102040 | H57: =ISBLANK('Full Universe'!BE44) -> TRUE | I57: =ISBLANK('Full Universe'!BF44) -> TRUE | J57: =ISBLANK('Full Universe'!BG44) -> TRUE | K57: =ISBLANK('Full Universe'!BH44) -> TRUE | L57: =ISBLANK('Full Universe'!BI44) -> TRUE | M57: =ISBLANK('Full Universe'!BJ44) -> TRUE | N57: =ISBLANK('Full Universe'!BK44) -> TRUE | O57: =ISBLANK('Full Universe'!BL44) -> TRUE | ... AJ57: =ISBLANK('Full Universe'!CG44) -> TRUE | AK57: =ISNUMBER(MATCH(C57,[1]Europe!$B$2:$B$15,0)) -> FALSE | AL57: =ISBLANK('Full Universe'!CJ44) -> TRUE | AM57: 2.7045863 | AN57: =ISNUMBER(MATCH(C57,'Selected Companies'!$D$2:$D$101,0)) -> FALSE | AO57: =_xlfn.XLOOKUP(C57,[2]generation_steps!$C$2:$C$18963,[2]generation_steps!$CM$2:$CM$18963) -> 274.99605 | AP57: =_xlfn.XLOOKUP(C57,[2]generation_steps!$C$2:$C$18963,[2]generation_steps!$CN$2:$CN$18963) -> 1.5
A58: 45709 | B58: AP MOELLER - MAERSK | C58: DK0010244508 | D58: XCSE | E58: =_xlfn.XLOOKUP(C58,[2]generation_steps!$I$2:$I$500,[2]generation_steps!$L$2:$L$500) -> 0.00059357665 | F58: =_xlfn.XLOOKUP(C58,[2]full_dataframe_final!$C$2:$C$101,[2]full_dataframe_final!$H$2:$H$101,"") | G58: 50206030 | H58: =ISBLANK('Full Universe'!BE45) -> TRUE | I58: =ISBLANK('Full Universe'!BF45) -> TRUE | J58: =ISBLANK('Full Universe'!BG45) -> TRUE | K58: =ISBLANK('Full Universe'!BH45) -> TRUE | L58: =ISBLANK('Full Universe'!BI45) -> TRUE | M58: =ISBLANK('Full Universe'!BJ45) -> TRUE | N58: =ISBLANK('Full Universe'!BK45) -> TRUE | O58: =ISBLANK('Full Universe'!BL45) -> TRUE | ... AJ58: =ISBLANK('Full Universe'!CG45) -> TRUE | AK58: =ISNUMBER(MATCH(C58,[1]Europe!$B$2:$B$15,0)) -> FALSE | AL58: =ISBLANK('Full Universe'!CJ45) -> TRUE | AM58: 1.7147969 | AN58: =ISNUMBER(MATCH(C58,'Selected Companies'!$D$2:$D$101,0)) -> FALSE | AO58: =_xlfn.XLOOKUP(C58,[2]generation_steps!$C$2:$C$18963,[2]generation_steps!$CM$2:$CM$18963) -> 1897.7701 | AP58: =_xlfn.XLOOKUP(C58,[2]generation_steps!$C$2:$C$18963,[2]generation_steps!$CN$2:$CN$18963) -> 1.5333333
A59: 45709 | B59: ARCADIS | C59: NL0006237562 | D59: XAMS | E59: =_xlfn.XLOOKUP(C59,[2]generation_steps!$I$2:$I$500,[2]generation_steps!$L$2:$L$500) -> 0.00029275027 | F59: =_xlfn.XLOOKUP(C59,[2]full_dataframe_final!$C$2:$C$101,[2]full_dataframe_final!$H$2:$H$101,"") | G59: 50101015 | H59: =ISBLANK('Full Universe'!BE46) -> TRUE | I59: =ISBLANK('Full Universe'!BF46) -> TRUE | J59: =ISBLANK('Full Universe'!BG46) -> TRUE | K59: =ISBLANK('Full Universe'!BH46) -> TRUE | L59: =ISBLANK('Full Universe'!BI46) -> TRUE | M59: =ISBLANK('Full Universe'!BJ46) -> TRUE | N59: =ISBLANK('Full Universe'!BK46) -> TRUE | O59: =ISBLANK('Full Universe'!BL46) -> TRUE | ... AJ59: =ISBLANK('Full Universe'!CG46) -> TRUE | AK59: =ISNUMBER(MATCH(C59,[1]Europe!$B$2:$B$15,0)) -> FALSE | AL59: =ISBLANK('Full Universe'!CJ46) -> TRUE | AM59: 1.4431599 | AN59: =ISNUMBER(MATCH(C59,'Selected Companies'!$D$2:$D$101,0)) -> FALSE | AO59: =_xlfn.XLOOKUP(C59,[2]generation_steps!$C$2:$C$18963,[2]generation_steps!$CM$2:$CM$18963) -> 218.33325 | AP59: =_xlfn.XLOOKUP(C59,[2]generation_steps!$C$2:$C$18963,[2]generation_steps!$CN$2:$CN$18963) -> 1.5
A60: 45709 | B60: ARCELORMITTAL SA | C60: LU1598757687 | D60: XAMS | E60: =_xlfn.XLOOKUP(C60,[2]generation_steps!$I$2:$I$500,[2]generation_steps!$L$2:$L$500) -> 0.0009833998 | F60: =_xlfn.XLOOKUP(C60,[2]full_dataframe_final!$C$2:$C$101,[2]full_dataframe_final!$H$2:$H$101,"") | G60: 55102010 | H60: =ISBLANK('Full Universe'!BE47) -> TRUE | I60: =ISBLANK('Full Universe'!BF47) -> TRUE | J60: =ISBLANK('Full Universe'!BG47) -> TRUE | K60: =ISBLANK('Full Universe'!BH47) -> TRUE | L60: =ISBLANK('Full Universe'!BI47) -> TRUE | M60: =ISBLANK('Full Universe'!BJ47) -> TRUE | N60: =ISBLANK('Full Universe'!BK47) -> TRUE | O60: =ISBLANK('Full Universe'!BL47) -> TRUE | ... AJ60: =ISBLANK('Full Universe'!CG47) -> TRUE | AK60: =ISNUMBER(MATCH(C60,[1]Europe!$B$2:$B$15,0)) -> FALSE | AL60: =ISBLANK('Full Universe'!CJ47) -> TRUE | AM60: 2.365 | AN60: =ISNUMBER(MATCH(C60,'Selected Companies'!$D$2:$D$101,0)) -> FALSE | AO60: =_xlfn.XLOOKUP(C60,[2]generation_steps!$C$2:$C$18963,[2]generation_steps!$CM$2:$CM$18963) -> 5058.8898 | AP60: =_xlfn.XLOOKUP(C60,[2]generation_steps!$C$2:$C$18963,[2]generation_steps!$CN$2:$CN$18963) -> 1.6
A61: 45709 | B61: ARGENX SE | C61: NL0010832176 | D61: XBRU | E61: =_xlfn.XLOOKUP(C61,[2]generation_steps!$I$2:$I$500,[2]generation_steps!$L$2:$L$500) -> 0.0031127051 | F61: =_xlfn.XLOOKUP(C61,[2]full_dataframe_final!$C$2:$C$101,[2]full_dataframe_final!$H$2:$H$101,"") | G61: 20103010 | H61: =ISBLANK('Full Universe'!BE48) -> TRUE | I61: =ISBLANK('Full Universe'!BF48) -> TRUE | J61: =ISBLANK('Full Universe'!BG48) -> TRUE | K61: =ISBLANK('Full Universe'!BH48) -> TRUE | L61: =ISBLANK('Full Universe'!BI48) -> TRUE | M61: =ISBLANK('Full Universe'!BJ48) -> TRUE | N61: =ISBLANK('Full Universe'!BK48) -> TRUE | O61: =ISBLANK('Full Universe'!BL48) -> TRUE | ... AJ61: =ISBLANK('Full Universe'!CG48) -> TRUE | AK61: =ISNUMBER(MATCH(C61,[1]Europe!$B$2:$B$15,0)) -> FALSE | AL61: =ISBLANK('Full Universe'!CJ48) -> TRUE | AM61: 3.55 | AN61: =ISNUMBER(MATCH(C61,'Selected Companies'!$D$2:$D$101,0)) -> FALSE | AO61: =_xlfn.XLOOKUP(C61,[2]generation_steps!$C$2:$C$18963,[2]generation_steps!$CM$2:$CM$18963) -> 22.047143 | AP61: =_xlfn.XLOOKUP(C61,[2]generation_steps!$C$2:$C$18963,[2]generation_steps!$CN$2:$CN$18963) -> 2.6
... A130: 45709 | B130: CARREFOUR | C130: FR0000120172 | D130: XPAR | E130: =_xlfn.XLOOKUP(C130,[2]generation_steps!$I$2:$I$500,[2]generation_steps!$L$2:$L$500) -> 0.00073804402 | F130: =_xlfn.XLOOKUP(C130,[2]full_dataframe_final!$C$2:$C$101,[2]full_dataframe_final!$H$2:$H$101,"") | G130: 45201010 | H130: =ISBLANK('Full Universe'!BE117) -> TRUE | I130: =ISBLANK('Full Universe'!BF117) -> TRUE | J130: =ISBLANK('Full Universe'!BG117) -> TRUE | K130: =ISBLANK('Full Universe'!BH117) -> TRUE | L130: =ISBLANK('Full Universe'!BI117) -> TRUE | M130: =ISBLANK('Full Universe'!BJ117) -> TRUE | N130: =ISBLANK('Full Universe'!BK117) -> TRUE | O130: =ISBLANK('Full Universe'!BL117) -> TRUE | ... AJ130: =ISBLANK('Full Universe'!CG117) -> TRUE | AK130: =ISNUMBER(MATCH(C130,[1]Europe!$B$2:$B$15,0)) -> FALSE | AL130: =ISBLANK('Full Universe'!CJ117) -> TRUE | AM130: 1.5684438 | AN130: =ISNUMBER(MATCH(C130,'Selected Companies'!$D$2:$D$101,0)) -> FALSE | AO130: =_xlfn.XLOOKUP(C130,[2]generation_steps!$C$2:$C$18963,[2]generation_steps!$CM$2:$CM$18963) -> 3009.6822 | AP130: =_xlfn.XLOOKUP(C130,[2]generation_steps!$C$2:$C$18963,[2]generation_steps!$CN$2:$CN$18963) -> 1.5333333
A131: 45709 | B131: CELLNEX TELECOM | C131: ES0105066007 | D131: XMAD | E131: =_xlfn.XLOOKUP(C131,[2]generation_steps!$I$2:$I$500,[2]generation_steps!$L$2:$L$500) -> 0.0019543241 | F131: =_xlfn.XLOOKUP(C131,[2]full_dataframe_final!$C$2:$C$101,[2]full_dataframe_final!$H$2:$H$101,"") | G131: 15102015 | H131: =ISBLANK('Full Universe'!BE119) -> TRUE | I131: =ISBLANK('Full Universe'!BF119) -> TRUE | J131: =ISBLANK('Full Universe'!BG119) -> TRUE | K131: =ISBLANK('Full Universe'!BH119) -> TRUE | L131: =ISBLANK('Full Universe'!BI119) -> TRUE | M131: =ISBLANK('Full Universe'!BJ119) -> TRUE | N131: =ISBLANK('Full Universe'!BK119) -> TRUE | O131: =ISBLANK('Full Universe'!BL119) -> TRUE | ... AJ131: =ISBLANK('Full Universe'!CG119) -> TRUE | AK131: =ISNUMBER(MATCH(C131,[1]Europe!$B$2:$B$15,0)) -> FALSE | AL131: =ISBLANK('Full Universe'!CJ119) -> TRUE | AM131: 2.2269086 | AN131: =ISNUMBER(MATCH(C131,'Selected Companies'!$D$2:$D$101,0)) -> FALSE | AO131: =_xlfn.XLOOKUP(C131,[2]generation_steps!$C$2:$C$18963,[2]generation_steps!$CM$2:$CM$18963) -> 11.162665 | AP131: =_xlfn.XLOOKUP(C131,[2]generation_steps!$C$2:$C$18963,[2]generation_steps!$CN$2:$CN$18963) -> 1.4333333
A132: 45709 | B132: CEMBRA MONEY BANK AG | C132: CH0225173167 | D132: XSWX | E132: =_xlfn.XLOOKUP(C132,[2]generation_steps!$I$2:$I$500,[2]generation_steps!$L$2:$L$500) -> 0.00031248661 | F132: =_xlfn.XLOOKUP(C132,[2]full_dataframe_final!$C$2:$C$101,[2]full_dataframe_final!$H$2:$H$101,"") | G132: 30101010 | H132: =ISBLANK('Full Universe'!BE120) -> TRUE | I132: =ISBLANK('Full Universe'!BF120) -> TRUE | J132: =ISBLANK('Full Universe'!BG120) -> TRUE | K132: =ISBLANK('Full Universe'!BH120) -> TRUE | L132: =ISBLANK('Full Universe'!BI120) -> TRUE | M132: =ISBLANK('Full Universe'!BJ120) -> TRUE | N132: =ISBLANK('Full Universe'!BK120) -> TRUE | O132: =ISBLANK('Full Universe'!BL120) -> TRUE | ... AJ132: =ISBLANK('Full Universe'!CG120) -> TRUE | AK132: =ISNUMBER(MATCH(C132,[1]Europe!$B$2:$B$15,0)) -> FALSE | AL132: =ISBLANK('Full Universe'!CJ120) -> TRUE | AM132: 3.55 | AN132: =ISNUMBER(MATCH(C132,'Selected Companies'!$D$2:$D$101,0)) -> FALSE | AO132: =_xlfn.XLOOKUP(C132,[2]generation_steps!$C$2:$C$18963,[2]generation_steps!$CM$2:$CM$18963) -> 31.511458 | AP132: =_xlfn.XLOOKUP(C132,[2]generation_steps!$C$2:$C$18963,[2]generation_steps!$CN$2:$CN$18963) -> 1.5333333
A133: 45709 | B133: CENTRICA | C133: GB00B033F229 | D133: XLON | E133: =_xlfn.XLOOKUP(C133,[2]generation_steps!$I$2:$I$500,[2]generation_steps!$L$2:$L$500) -> 0.00084331508 | F133: =_xlfn.XLOOKUP(C133,[2]full_dataframe_final!$C$2:$C$101,[2]full_dataframe_final!$H$2:$H$101,"") | G133: 65102000 | H133: =ISBLANK('Full Universe'!BE121) -> TRUE | I133: =ISBLANK('Full Universe'!BF121) -> TRUE | J133: =ISBLANK('Full Universe'!BG121) -> TRUE | K133: =ISBLANK('Full Universe'!BH121) -> TRUE | L133: =ISBLANK('Full Universe'!BI121) -> TRUE | M133: =ISBLANK('Full Universe'!BJ121) -> TRUE | N133: =ISBLANK('Full Universe'!BK121) -> TRUE | O133: =ISBLANK('Full Universe'!BL121) -> TRUE | ... AJ133: =ISBLANK('Full Universe'!CG121) -> TRUE | AK133: =ISNUMBER(MATCH(C133,[1]Europe!$B$2:$B$15,0)) -> FALSE | AL133: =ISBLANK('Full Universe'!CJ121) -> TRUE | AM133: 2.6811188 | AN133: =ISNUMBER(MATCH(C133,'Selected Companies'!$D$2:$D$101,0)) -> FALSE | AO133: =_xlfn.XLOOKUP(C133,[2]generation_steps!$C$2:$C$18963,[2]generation_steps!$CM$2:$CM$18963) -> 1597.0072 | AP133: =_xlfn.XLOOKUP(C133,[2]generation_steps!$C$2:$C$18963,[2]generation_steps!$CN$2:$CN$18963) -> 1.4
A134: 45709 | B134: CIE FIN RICHEMONT | C134: CH0210483332 | D134: XSWX | E134: =_xlfn.XLOOKUP(C134,[2]generation_steps!$I$2:$I$500,[2]generation_steps!$L$2:$L$500) -> 0.00761946 | F134: =_xlfn.XLOOKUP(C134,[2]full_dataframe_final!$C$2:$C$101,[2]full_dataframe_final!$H$2:$H$101,"") | G134: 40204030 | H134: =ISBLANK('Full Universe'!BE122) -> TRUE | I134: =ISBLANK('Full Universe'!BF122) -> TRUE | J134: =ISBLANK('Full Universe'!BG122) -> TRUE | K134: =ISBLANK('Full Universe'!BH122) -> TRUE | L134: =ISBLANK('Full Universe'!BI122) -> TRUE | M134: =ISBLANK('Full Universe'!BJ122) -> TRUE | N134: =ISBLANK('Full Universe'!BK122) -> TRUE | O134: =ISBLANK('Full Universe'!BL122) -> TRUE | ... AJ134: =ISBLANK('Full Universe'!CG122) -> FALSE | AK134: =ISNUMBER(MATCH(C134,[1]Europe!$B$2:$B$15,0)) -> FALSE | AL134: =ISBLANK('Full Universe'!CJ122) -> TRUE | AM134: 3.07 | AN134: =ISNUMBER(MATCH(C134,'Selected Companies'!$D$2:$D$101,0)) -> FALSE | AO134: =_xlfn.XLOOKUP(C134,[2]generation_steps!$C$2:$C$18963,[2]generation_steps!$CM$2:$CM$18963) -> 18.323264 | AP134: =_xlfn.XLOOKUP(C134,[2]generation_steps!$C$2:$C$18963,[2]generation_steps!$CN$2:$CN$18963) -> 1.6333333
A135: 45709 | B135: COCA-COLA HBC AG-CDI | C135: CH0198251305 | D135: XLON | E135: =_xlfn.XLOOKUP(C135,[2]generation_steps!$I$2:$I$500,[2]generation_steps!$L$2:$L$500) -> 0.00082624409 | F135: =_xlfn.XLOOKUP(C135,[2]full_dataframe_final!$C$2:$C$101,[2]full_dataframe_final!$H$2:$H$101,"") -> 0.0015516121 | G135: 45101020 | H135: =ISBLANK('Full Universe'!BE123) -> TRUE | I135: =ISBLANK('Full Universe'!BF123) -> TRUE | J135: =ISBLANK('Full Universe'!BG123) -> TRUE | K135: =ISBLANK('Full Universe'!BH123) -> TRUE | L135: =ISBLANK('Full Universe'!BI123) -> TRUE | M135: =ISBLANK('Full Universe'!BJ123) -> TRUE | N135: =ISBLANK('Full Universe'!BK123) -> TRUE | O135: =ISBLANK('Full Universe'!BL123) -> TRUE | ... AJ135: =ISBLANK('Full Universe'!CG123) -> TRUE | AK135: =ISNUMBER(MATCH(C135,[1]Europe!$B$2:$B$15,0)) -> FALSE | AL135: =ISBLANK('Full Universe'!CJ123) -> TRUE | AM135: 1.3135853 | AN135: =ISNUMBER(MATCH(C135,'Selected Companies'!$D$2:$D$101,0)) -> TRUE | AO135: =_xlfn.XLOOKUP(C135,[2]generation_steps!$C$2:$C$18963,[2]generation_steps!$CM$2:$CM$18963) -> 351.67551 | AP135: =_xlfn.XLOOKUP(C135,[2]generation_steps!$C$2:$C$18963,[2]generation_steps!$CN$2:$CN$18963) -> 1.5
A136: 45709 | B136: COLOPLAST | C136: DK0060448595 | D136: XCSE | E136: =_xlfn.XLOOKUP(C136,[2]generation_steps!$I$2:$I$500,[2]generation_steps!$L$2:$L$500) -> 0.001433355 | F136: =_xlfn.XLOOKUP(C136,[2]full_dataframe_final!$C$2:$C$101,[2]full_dataframe_final!$H$2:$H$101,"") | G136: 20102015 | H136: =ISBLANK('Full Universe'!BE124) -> TRUE | I136: =ISBLANK('Full Universe'!BF124) -> TRUE | J136: =ISBLANK('Full Universe'!BG124) -> TRUE | K136: =ISBLANK('Full Universe'!BH124) -> TRUE | L136: =ISBLANK('Full Universe'!BI124) -> TRUE | M136: =ISBLANK('Full Universe'!BJ124) -> TRUE | N136: =ISBLANK('Full Universe'!BK124) -> TRUE | O136: =ISBLANK('Full Universe'!BL124) -> TRUE | ... AJ136: =ISBLANK('Full Universe'!CG124) -> TRUE | AK136: =ISNUMBER(MATCH(C136,[1]Europe!$B$2:$B$15,0)) -> FALSE | AL136: =ISBLANK('Full Universe'!CJ124) -> TRUE | AM136: 3.07 | AN136: =ISNUMBER(MATCH(C136,'Selected Companies'!$D$2:$D$101,0)) -> FALSE | AO136: =_xlfn.XLOOKUP(C136,[2]generation_steps!$C$2:$C$18963,[2]generation_steps!$CM$2:$CM$18963) -> 70.932589 | AP136: =_xlfn.XLOOKUP(C136,[2]generation_steps!$C$2:$C$18963,[2]generation_steps!$CN$2:$CN$18963) -> 1.5666667
A137: 45709 | B137: COMMERZBANK AG | C137: DE000CBK1001 | D137: XETR | E137: =_xlfn.XLOOKUP(C137,[2]generation_steps!$I$2:$I$500,[2]generation_steps!$L$2:$L$500) -> 0.0020785432 | F137: =_xlfn.XLOOKUP(C137,[2]full_dataframe_final!$C$2:$C$101,[2]full_dataframe_final!$H$2:$H$101,"") -> 0.0039033171 | G137: 30101010 | H137: =ISBLANK('Full Universe'!BE125) -> TRUE | I137: =ISBLANK('Full Universe'!BF125) -> TRUE | J137: =ISBLANK('Full Universe'!BG125) -> TRUE | K137: =ISBLANK('Full Universe'!BH125) -> TRUE | L137: =ISBLANK('Full Universe'!BI125) -> TRUE | M137: =ISBLANK('Full Universe'!BJ125) -> TRUE | N137: =ISBLANK('Full Universe'!BK125) -> TRUE | O137: =ISBLANK('Full Universe'!BL125) -> TRUE | ... AJ137: =ISBLANK('Full Universe'!CG125) -> TRUE | AK137: =ISNUMBER(MATCH(C137,[1]Europe!$B$2:$B$15,0)) -> FALSE | AL137: =ISBLANK('Full Universe'!CJ125) -> TRUE | AM137: 1.5259107 | AN137: =ISNUMBER(MATCH(C137,'Selected Companies'!$D$2:$D$101,0)) -> TRUE | AO137: =_xlfn.XLOOKUP(C137,[2]generation_steps!$C$2:$C$18963,[2]generation_steps!$CM$2:$CM$18963) -> 270.4133 | AP137: =_xlfn.XLOOKUP(C137,[2]generation_steps!$C$2:$C$18963,[2]generation_steps!$CN$2:$CN$18963) -> 1.5
A138: 45709 | B138: COMPASS GROUP PLC | C138: GB00BD6K4575 | D138: XLON | E138: =_xlfn.XLOOKUP(C138,[2]generation_steps!$I$2:$I$500,[2]generation_steps!$L$2:$L$500) -> 0.004905318 | F138: =_xlfn.XLOOKUP(C138,[2]full_dataframe_final!$C$2:$C$101,[2]full_dataframe_final!$H$2:$H$101,"") | G138: 40201060 | H138: =ISBLANK('Full Universe'!BE126) -> TRUE | I138: =ISBLANK('Full Universe'!BF126) -> TRUE | J138: =ISBLANK('Full Universe'!BG126) -> TRUE | K138: =ISBLANK('Full Universe'!BH126) -> TRUE | L138: =ISBLANK('Full Universe'!BI126) -> TRUE | M138: =ISBLANK('Full Universe'!BJ126) -> TRUE | N138: =ISBLANK('Full Universe'!BK126) -> TRUE | O138: =ISBLANK('Full Universe'!BL126) -> TRUE | ... AJ138: =ISBLANK('Full Universe'!CG126) -> TRUE | AK138: =ISNUMBER(MATCH(C138,[1]Europe!$B$2:$B$15,0)) -> FALSE | AL138: =ISBLANK('Full Universe'!CJ126) -> TRUE | AM138: 2.3668825 | AN138: =ISNUMBER(MATCH(C138,'Selected Companies'!$D$2:$D$101,0)) -> FALSE | AO138: =_xlfn.XLOOKUP(C138,[2]generation_steps!$C$2:$C$18963,[2]generation_steps!$CM$2:$CM$18963) -> 194.47422 | AP138: =_xlfn.XLOOKUP(C138,[2]generation_steps!$C$2:$C$18963,[2]generation_steps!$CN$2:$CN$18963) -> 1.4666667
A139: 45709 | B139: CONTINENTAL AG | C139: DE0005439004 | D139: XETR | E139: =_xlfn.XLOOKUP(C139,[2]generation_steps!$I$2:$I$500,[2]generation_steps!$L$2:$L$500) -> 0.00068538323 | F139: =_xlfn.XLOOKUP(C139,[2]full_dataframe_final!$C$2:$C$101,[2]full_dataframe_final!$H$2:$H$101,"") -> 0.0012870881 | G139: 40101025 | H139: =ISBLANK('Full Universe'!BE127) -> TRUE | I139: =ISBLANK('Full Universe'!BF127) -> TRUE | J139: =ISBLANK('Full Universe'!BG127) -> TRUE | K139: =ISBLANK('Full Universe'!BH127) -> TRUE | L139: =ISBLANK('Full Universe'!BI127) -> TRUE | M139: =ISBLANK('Full Universe'!BJ127) -> TRUE | N139: =ISBLANK('Full Universe'!BK127) -> TRUE | O139: =ISBLANK('Full Universe'!BL127) -> TRUE | ... AJ139: =ISBLANK('Full Universe'!CG127) -> TRUE | AK139: =ISNUMBER(MATCH(C139,[1]Europe!$B$2:$B$15,0)) -> FALSE | AL139: =ISBLANK('Full Universe'!CJ127) -> TRUE | AM139: 1.5076888 | AN139: =ISNUMBER(MATCH(C139,'Selected Companies'!$D$2:$D$101,0)) -> TRUE | AO139: =_xlfn.XLOOKUP(C139,[2]generation_steps!$C$2:$C$18963,[2]generation_steps!$CM$2:$CM$18963) -> 4504.9862 | AP139: =_xlfn.XLOOKUP(C139,[2]generation_steps!$C$2:$C$18963,[2]generation_steps!$CN$2:$CN$18963) -> 1.5
A140: 45709 | B140: CONVATEC GROUP PLC | C140: GB00BD3VFW73 | D140: XLON | E140: =_xlfn.XLOOKUP(C140,[2]generation_steps!$I$2:$I$500,[2]generation_steps!$L$2:$L$500) -> 0.00048000255 | F140: =_xlfn.XLOOKUP(C140,[2]full_dataframe_final!$C$2:$C$101,[2]full_dataframe_final!$H$2:$H$101,"") -> 0.00090140162 | G140: 20102015 | H140: =ISBLANK('Full Universe'!BE128) -> TRUE | I140: =ISBLANK('Full Universe'!BF128) -> TRUE | J140: =ISBLANK('Full Universe'!BG128) -> TRUE | K140: =ISBLANK('Full Universe'!BH128) -> TRUE | L140: =ISBLANK('Full Universe'!BI128) -> TRUE | M140: =ISBLANK('Full Universe'!BJ128) -> TRUE | N140: =ISBLANK('Full Universe'!BK128) -> TRUE | O140: =ISBLANK('Full Universe'!BL128) -> TRUE | ... AJ140: =ISBLANK('Full Universe'!CG128) -> TRUE | AK140: =ISNUMBER(MATCH(C140,[1]Europe!$B$2:$B$15,0)) -> FALSE | AL140: =ISBLANK('Full Universe'!CJ128) -> TRUE | AM140: 1.5571159 | AN140: =ISNUMBER(MATCH(C140,'Selected Companies'!$D$2:$D$101,0)) -> TRUE | AO140: =_xlfn.XLOOKUP(C140,[2]generation_steps!$C$2:$C$18963,[2]generation_steps!$CM$2:$CM$18963) -> 68.230877 | AP140: =_xlfn.XLOOKUP(C140,[2]generation_steps!$C$2:$C$18963,[2]generation_steps!$CN$2:$CN$18963) -> 1.6
A141: 45709 | B141: COVESTRO AG | C141: DE000A40KY26 | D141: XETR | E141: =_xlfn.XLOOKUP(C141,[2]generation_steps!$I$2:$I$500,[2]generation_steps!$L$2:$L$500) -> 0.00097498181 | F141: =_xlfn.XLOOKUP(C141,[2]full_dataframe_final!$C$2:$C$101,[2]full_dataframe_final!$H$2:$H$101,"") | G141: 55201020 | H141: =ISBLANK('Full Universe'!BE129) -> TRUE | I141: =ISBLANK('Full Universe'!BF129) -> TRUE | J141: =ISBLANK('Full Universe'!BG129) -> TRUE | K141: =ISBLANK('Full Universe'!BH129) -> TRUE | L141: =ISBLANK('Full Universe'!BI129) -> TRUE | M141: =ISBLANK('Full Universe'!BJ129) -> TRUE | N141: =ISBLANK('Full Universe'!BK129) -> TRUE | O141: =ISBLANK('Full Universe'!BL129) -> TRUE | ... AJ141: =ISBLANK('Full Universe'!CG129) -> TRUE | AK141: =ISNUMBER(MATCH(C141,[1]Europe!$B$2:$B$15,0)) -> FALSE | AL141: =ISBLANK('Full Universe'!CJ129) -> TRUE | AM141: 3.205 | AN141: =ISNUMBER(MATCH(C141,'Selected Companies'!$D$2:$D$101,0)) -> FALSE | AO141: =_xlfn.XLOOKUP(C141,[2]generation_steps!$C$2:$C$18963,[2]generation_steps!$CM$2:$CM$18963) -> 0 | AP141: =_xlfn.XLOOKUP(C141,[2]generation_steps!$C$2:$C$18963,[2]generation_steps!$CN$2:$CN$18963) -> 1.5
A142: 45709 | B142: CRANSWICK PLC | C142: GB0002318888 | D142: XLON | E142: =_xlfn.XLOOKUP(C142,[2]generation_steps!$I$2:$I$500,[2]generation_steps!$L$2:$L$500) -> 0.00030927142 | F142: =_xlfn.XLOOKUP(C142,[2]full_dataframe_final!$C$2:$C$101,[2]full_dataframe_final!$H$2:$H$101,"") | G142: 45102020 | H142: =ISBLANK('Full Universe'!BE130) -> TRUE | I142: =ISBLANK('Full Universe'!BF130) -> TRUE | J142: =ISBLANK('Full Universe'!BG130) -> TRUE | K142: =ISBLANK('Full Universe'!BH130) -> TRUE | L142: =ISBLANK('Full Universe'!BI130) -> TRUE | M142: =ISBLANK('Full Universe'!BJ130) -> TRUE | N142: =ISBLANK('Full Universe'!BK130) -> TRUE | O142: =ISBLANK('Full Universe'!BL130) -> TRUE | ... AJ142: =ISBLANK('Full Universe'!CG130) -> TRUE | AK142: =ISNUMBER(MATCH(C142,[1]Europe!$B$2:$B$15,0)) -> FALSE | AL142: =ISBLANK('Full Universe'!CJ130) -> TRUE | AM142: 1.6981605 | AN142: =ISNUMBER(MATCH(C142,'Selected Companies'!$D$2:$D$101,0)) -> FALSE | AO142: =_xlfn.XLOOKUP(C142,[2]generation_steps!$C$2:$C$18963,[2]generation_steps!$CM$2:$CM$18963) -> 1518.7573 | AP142: =_xlfn.XLOOKUP(C142,[2]generation_steps!$C$2:$C$18963,[2]generation_steps!$CN$2:$CN$18963) -> 1.6
... A150: 45709 | B150: DASSAULT AVIATION | C150: FR0014004L86 | D150: XPAR | E150: =_xlfn.XLOOKUP(C150,[2]generation_steps!$I$2:$I$500,[2]generation_steps!$L$2:$L$500) -> 0.0005883787 | F150: =_xlfn.XLOOKUP(C150,[2]full_dataframe_final!$C$2:$C$101,[2]full_dataframe_final!$H$2:$H$101,"") | G150: 50201010 | H150: =ISBLANK('Full Universe'!BE138) -> TRUE | I150: =ISBLANK('Full Universe'!BF138) -> TRUE | J150: =ISBLANK('Full Universe'!BG138) -> TRUE | K150: =ISBLANK('Full Universe'!BH138) -> FALSE | L150: =ISBLANK('Full Universe'!BI138) -> TRUE | M150: =ISBLANK('Full Universe'!BJ138) -> TRUE | N150: =ISBLANK('Full Universe'!BK138) -> TRUE | O150: =ISBLANK('Full Universe'!BL138) -> TRUE | ... AJ150: =ISBLANK('Full Universe'!CG138) -> TRUE | AK150: =ISNUMBER(MATCH(C150,[1]Europe!$B$2:$B$15,0)) -> FALSE | AL150: =ISBLANK('Full Universe'!CJ138) -> FALSE | AM150: 3.55 | AN150: =ISNUMBER(MATCH(C150,'Selected Companies'!$D$2:$D$101,0)) -> FALSE | AO150: =_xlfn.XLOOKUP(C150,[2]generation_steps!$C$2:$C$18963,[2]generation_steps!$CM$2:$CM$18963) -> 708.90034 | AP150: =_xlfn.XLOOKUP(C150,[2]generation_steps!$C$2:$C$18963,[2]generation_steps!$CN$2:$CN$18963) -> 1.4
A151: 45709 | B151: DCC PLC | C151: IE0002424939 | D151: XLON | E151: =_xlfn.XLOOKUP(C151,[2]generation_steps!$I$2:$I$500,[2]generation_steps!$L$2:$L$500) -> 0.00055454432 | F151: =_xlfn.XLOOKUP(C151,[2]full_dataframe_final!$C$2:$C$101,[2]full_dataframe_final!$H$2:$H$101,"") | G151: 50205010 | H151: =ISBLANK('Full Universe'!BE140) -> TRUE | I151: =ISBLANK('Full Universe'!BF140) -> TRUE | J151: =ISBLANK('Full Universe'!BG140) -> TRUE | K151: =ISBLANK('Full Universe'!BH140) -> TRUE | L151: =ISBLANK('Full Universe'!BI140) -> TRUE | M151: =ISBLANK('Full Universe'!BJ140) -> TRUE | N151: =ISBLANK('Full Universe'!BK140) -> TRUE | O151: =ISBLANK('Full Universe'!BL140) -> TRUE | ... AJ151: =ISBLANK('Full Universe'!CG140) -> TRUE | AK151: =ISNUMBER(MATCH(C151,[1]Europe!$B$2:$B$15,0)) -> FALSE | AL151: =ISBLANK('Full Universe'!CJ140) -> TRUE | AM151: 2.27 | AN151: =ISNUMBER(MATCH(C151,'Selected Companies'!$D$2:$D$101,0)) -> FALSE | AO151: =_xlfn.XLOOKUP(C151,[2]generation_steps!$C$2:$C$18963,[2]generation_steps!$CM$2:$CM$18963) -> 4831.8644 | AP151: =_xlfn.XLOOKUP(C151,[2]generation_steps!$C$2:$C$18963,[2]generation_steps!$CN$2:$CN$18963) -> 1.4666667
A152: 45709 | B152: DELIVERY HERO SE | C152: DE000A2E4K43 | D152: XETR | E152: =_xlfn.XLOOKUP(C152,[2]generation_steps!$I$2:$I$500,[2]generation_steps!$L$2:$L$500) -> 0.0004924734 | F152: =_xlfn.XLOOKUP(C152,[2]full_dataframe_final!$C$2:$C$101,[2]full_dataframe_final!$H$2:$H$101,"") | G152: 40201070 | H152: =ISBLANK('Full Universe'!BE141) -> TRUE | I152: =ISBLANK('Full Universe'!BF141) -> TRUE | J152: =ISBLANK('Full Universe'!BG141) -> TRUE | K152: =ISBLANK('Full Universe'!BH141) -> TRUE | L152: =ISBLANK('Full Universe'!BI141) -> TRUE | M152: =ISBLANK('Full Universe'!BJ141) -> TRUE | N152: =ISBLANK('Full Universe'!BK141) -> TRUE | O152: =ISBLANK('Full Universe'!BL141) -> TRUE | ... AJ152: =ISBLANK('Full Universe'!CG141) -> TRUE | AK152: =ISNUMBER(MATCH(C152,[1]Europe!$B$2:$B$15,0)) -> FALSE | AL152: =ISBLANK('Full Universe'!CJ141) -> FALSE | AM152: 2.3640328 | AN152: =ISNUMBER(MATCH(C152,'Selected Companies'!$D$2:$D$101,0)) -> FALSE | AO152: =_xlfn.XLOOKUP(C152,[2]generation_steps!$C$2:$C$18963,[2]generation_steps!$CM$2:$CM$18963) -> 343.91278 | AP152: =_xlfn.XLOOKUP(C152,[2]generation_steps!$C$2:$C$18963,[2]generation_steps!$CN$2:$CN$18963) -> 4.1
A153: 45709 | B153: DEMANT | C153: DK0060738599 | D153: XCSE | E153: =_xlfn.XLOOKUP(C153,[2]generation_steps!$I$2:$I$500,[2]generation_steps!$L$2:$L$500) -> 0.00026038629 | F153: =_xlfn.XLOOKUP(C153,[2]full_dataframe_final!$C$2:$C$101,[2]full_dataframe_final!$H$2:$H$101,"") | G153: 20102010 | H153: =ISBLANK('Full Universe'!BE142) -> TRUE | I153: =ISBLANK('Full Universe'!BF142) -> TRUE | J153: =ISBLANK('Full Universe'!BG142) -> TRUE | K153: =ISBLANK('Full Universe'!BH142) -> TRUE | L153: =ISBLANK('Full Universe'!BI142) -> TRUE | M153: =ISBLANK('Full Universe'!BJ142) -> TRUE | N153: =ISBLANK('Full Universe'!BK142) -> TRUE | O153: =ISBLANK('Full Universe'!BL142) -> TRUE | ... AJ153: =ISBLANK('Full Universe'!CG142) -> TRUE | AK153: =ISNUMBER(MATCH(C153,[1]Europe!$B$2:$B$15,0)) -> FALSE | AL153: =ISBLANK('Full Universe'!CJ142) -> TRUE | AM153: 2.7099301 | AN153: =ISNUMBER(MATCH(C153,'Selected Companies'!$D$2:$D$101,0)) -> FALSE | AO153: =_xlfn.XLOOKUP(C153,[2]generation_steps!$C$2:$C$18963,[2]generation_steps!$CM$2:$CM$18963) -> 76.206043 | AP153: =_xlfn.XLOOKUP(C153,[2]generation_steps!$C$2:$C$18963,[2]generation_steps!$CN$2:$CN$18963) -> 1.5
A154: 45709 | B154: DEUTSCHE BANK | C154: DE0005140008 | D154: XETR | E154: =_xlfn.XLOOKUP(C154,[2]generation_steps!$I$2:$I$500,[2]generation_steps!$L$2:$L$500) -> 0.0039244658 | F154: =_xlfn.XLOOKUP(C154,[2]full_dataframe_final!$C$2:$C$101,[2]full_dataframe_final!$H$2:$H$101,"") | G154: 30101010 | H154: =ISBLANK('Full Universe'!BE143) -> TRUE | I154: =ISBLANK('Full Universe'!BF143) -> TRUE | J154: =ISBLANK('Full Universe'!BG143) -> TRUE | K154: =ISBLANK('Full Universe'!BH143) -> TRUE | L154: =ISBLANK('Full Universe'!BI143) -> TRUE | M154: =ISBLANK('Full Universe'!BJ143) -> TRUE | N154: =ISBLANK('Full Universe'!BK143) -> TRUE | O154: =ISBLANK('Full Universe'!BL143) -> TRUE | ... AJ154: =ISBLANK('Full Universe'!CG143) -> TRUE | AK154: =ISNUMBER(MATCH(C154,[1]Europe!$B$2:$B$15,0)) -> FALSE | AL154: =ISBLANK('Full Universe'!CJ143) -> TRUE | AM154: 3.07 | AN154: =ISNUMBER(MATCH(C154,'Selected Companies'!$D$2:$D$101,0)) -> FALSE | AO154: =_xlfn.XLOOKUP(C154,[2]generation_steps!$C$2:$C$18963,[2]generation_steps!$CM$2:$CM$18963) -> 245.3754 | AP154: =_xlfn.XLOOKUP(C154,[2]generation_steps!$C$2:$C$18963,[2]generation_steps!$CN$2:$CN$18963) -> 1.5333333
A155: 45709 | B155: DEUTSCHE BOERSE AG | C155: DE0005810055 | D155: XETR | E155: =_xlfn.XLOOKUP(C155,[2]generation_steps!$I$2:$I$500,[2]generation_steps!$L$2:$L$500) -> 0.0049342067 | F155: =_xlfn.XLOOKUP(C155,[2]full_dataframe_final!$C$2:$C$101,[2]full_dataframe_final!$H$2:$H$101,"") -> 0.020973097 | G155: 30202015 | H155: =ISBLANK('Full Universe'!BE144) -> TRUE | I155: =ISBLANK('Full Universe'!BF144) -> TRUE | J155: =ISBLANK('Full Universe'!BG144) -> TRUE | K155: =ISBLANK('Full Universe'!BH144) -> TRUE | L155: =ISBLANK('Full Universe'!BI144) -> TRUE | M155: =ISBLANK('Full Universe'!BJ144) -> TRUE | N155: =ISBLANK('Full Universe'!BK144) -> TRUE | O155: =ISBLANK('Full Universe'!BL144) -> TRUE | ... AJ155: =ISBLANK('Full Universe'!CG144) -> TRUE | AK155: =ISNUMBER(MATCH(C155,[1]Europe!$B$2:$B$15,0)) -> FALSE | AL155: =ISBLANK('Full Universe'!CJ144) -> TRUE | AM155: 2.2395408 | AN155: =ISNUMBER(MATCH(C155,'Selected Companies'!$D$2:$D$101,0)) -> TRUE | AO155: =_xlfn.XLOOKUP(C155,[2]generation_steps!$C$2:$C$18963,[2]generation_steps!$CM$2:$CM$18963) -> 2.7324928 | AP155: =_xlfn.XLOOKUP(C155,[2]generation_steps!$C$2:$C$18963,[2]generation_steps!$CN$2:$CN$18963) -> 1.5333333
A156: 45709 | B156: DEUTSCHE POST | C156: DE0005552004 | D156: XETR | E156: =_xlfn.XLOOKUP(C156,[2]generation_steps!$I$2:$I$500,[2]generation_steps!$L$2:$L$500) -> 0.0035739271 | F156: =_xlfn.XLOOKUP(C156,[2]full_dataframe_final!$C$2:$C$101,[2]full_dataframe_final!$H$2:$H$101,"") | G156: 50206040 | H156: =ISBLANK('Full Universe'!BE145) -> TRUE | I156: =ISBLANK('Full Universe'!BF145) -> TRUE | J156: =ISBLANK('Full Universe'!BG145) -> TRUE | K156: =ISBLANK('Full Universe'!BH145) -> TRUE | L156: =ISBLANK('Full Universe'!BI145) -> TRUE | M156: =ISBLANK('Full Universe'!BJ145) -> TRUE | N156: =ISBLANK('Full Universe'!BK145) -> TRUE | O156: =ISBLANK('Full Universe'!BL145) -> TRUE | ... AJ156: =ISBLANK('Full Universe'!CG145) -> TRUE | AK156: =ISNUMBER(MATCH(C156,[1]Europe!$B$2:$B$15,0)) -> FALSE | AL156: =ISBLANK('Full Universe'!CJ145) -> TRUE | AM156: 2.2203755 | AN156: =ISNUMBER(MATCH(C156,'Selected Companies'!$D$2:$D$101,0)) -> FALSE | AO156: =_xlfn.XLOOKUP(C156,[2]generation_steps!$C$2:$C$18963,[2]generation_steps!$CM$2:$CM$18963) -> 519.50948 | AP156: =_xlfn.XLOOKUP(C156,[2]generation_steps!$C$2:$C$18963,[2]generation_steps!$CN$2:$CN$18963) -> 1.5
A157: 45709 | B157: DEUTSCHE TELEKOM AG | C157: DE0005557508 | D157: XETR | E157: =_xlfn.XLOOKUP(C157,[2]generation_steps!$I$2:$I$500,[2]generation_steps!$L$2:$L$500) -> 0.011441019 | F157: =_xlfn.XLOOKUP(C157,[2]full_dataframe_final!$C$2:$C$101,[2]full_dataframe_final!$H$2:$H$101,"") | G157: 15102015 | H157: =ISBLANK('Full Universe'!BE146) -> TRUE | I157: =ISBLANK('Full Universe'!BF146) -> TRUE | J157: =ISBLANK('Full Universe'!BG146) -> TRUE | K157: =ISBLANK('Full Universe'!BH146) -> TRUE | L157: =ISBLANK('Full Universe'!BI146) -> TRUE | M157: =ISBLANK('Full Universe'!BJ146) -> TRUE | N157: =ISBLANK('Full Universe'!BK146) -> TRUE | O157: =ISBLANK('Full Universe'!BL146) -> TRUE | ... AJ157: =ISBLANK('Full Universe'!CG146) -> TRUE | AK157: =ISNUMBER(MATCH(C157,[1]Europe!$B$2:$B$15,0)) -> FALSE | AL157: =ISBLANK('Full Universe'!CJ146) -> TRUE | AM157: 2.1226731 | AN157: =ISNUMBER(MATCH(C157,'Selected Companies'!$D$2:$D$101,0)) -> FALSE | AO157: =_xlfn.XLOOKUP(C157,[2]generation_steps!$C$2:$C$18963,[2]generation_steps!$CM$2:$CM$18963) -> 37.73704 | AP157: =_xlfn.XLOOKUP(C157,[2]generation_steps!$C$2:$C$18963,[2]generation_steps!$CN$2:$CN$18963) -> 1.4
A158: 45709 | B158: DIAGEO | C158: GB0002374006 | D158: XLON | E158: =_xlfn.XLOOKUP(C158,[2]generation_steps!$I$2:$I$500,[2]generation_steps!$L$2:$L$500) -> 0.0051201917 | F158: =_xlfn.XLOOKUP(C158,[2]full_dataframe_final!$C$2:$C$101,[2]full_dataframe_final!$H$2:$H$101,"") -> 0.025832786 | G158: 45101015 | H158: =ISBLANK('Full Universe'!BE147) -> TRUE | I158: =ISBLANK('Full Universe'!BF147) -> TRUE | J158: =ISBLANK('Full Universe'!BG147) -> TRUE | K158: =ISBLANK('Full Universe'!BH147) -> TRUE | L158: =ISBLANK('Full Universe'!BI147) -> TRUE | M158: =ISBLANK('Full Universe'!BJ147) -> TRUE | N158: =ISBLANK('Full Universe'!BK147) -> TRUE | O158: =ISBLANK('Full Universe'!BL147) -> TRUE | ... AJ158: =ISBLANK('Full Universe'!CG147) -> TRUE | AK158: =ISNUMBER(MATCH(C158,[1]Europe!$B$2:$B$15,0)) -> FALSE | AL158: =ISBLANK('Full Universe'!CJ147) -> TRUE | AM158: 1.5518764 | AN158: =ISNUMBER(MATCH(C158,'Selected Companies'!$D$2:$D$101,0)) -> TRUE | AO158: =_xlfn.XLOOKUP(C158,[2]generation_steps!$C$2:$C$18963,[2]generation_steps!$CM$2:$CM$18963) -> 53.461702 | AP158: =_xlfn.XLOOKUP(C158,[2]generation_steps!$C$2:$C$18963,[2]generation_steps!$CN$2:$CN$18963) -> 1.5333333
A159: 45709 | B159: D'IETEREN GROUP | C159: BE0974259880 | D159: XBRU | E159: =_xlfn.XLOOKUP(C159,[2]generation_steps!$I$2:$I$500,[2]generation_steps!$L$2:$L$500) -> 0.00034720089 | F159: =_xlfn.XLOOKUP(C159,[2]full_dataframe_final!$C$2:$C$101,[2]full_dataframe_final!$H$2:$H$101,"") | G159: 40101010 | H159: =ISBLANK('Full Universe'!BE148) -> TRUE | I159: =ISBLANK('Full Universe'!BF148) -> TRUE | J159: =ISBLANK('Full Universe'!BG148) -> TRUE | K159: =ISBLANK('Full Universe'!BH148) -> TRUE | L159: =ISBLANK('Full Universe'!BI148) -> TRUE | M159: =ISBLANK('Full Universe'!BJ148) -> TRUE | N159: =ISBLANK('Full Universe'!BK148) -> TRUE | O159: =ISBLANK('Full Universe'!BL148) -> TRUE | ... AJ159: =ISBLANK('Full Universe'!CG148) -> TRUE | AK159: =ISNUMBER(MATCH(C159,[1]Europe!$B$2:$B$15,0)) -> FALSE | AL159: =ISBLANK('Full Universe'!CJ148) -> FALSE | AM159: 2.5499138 | AN159: =ISNUMBER(MATCH(C159,'Selected Companies'!$D$2:$D$101,0)) -> FALSE | AO159: =_xlfn.XLOOKUP(C159,[2]generation_steps!$C$2:$C$18963,[2]generation_steps!$CM$2:$CM$18963) -> 101.77506 | AP159: =_xlfn.XLOOKUP(C159,[2]generation_steps!$C$2:$C$18963,[2]generation_steps!$CN$2:$CN$18963) -> 1.7333333
A160: 45709 | B160: DIPLOMA PLC | C160: GB0001826634 | D160: XLON | E160: =_xlfn.XLOOKUP(C160,[2]generation_steps!$I$2:$I$500,[2]generation_steps!$L$2:$L$500) -> 0.00060050305 | F160: =_xlfn.XLOOKUP(C160,[2]full_dataframe_final!$C$2:$C$101,[2]full_dataframe_final!$H$2:$H$101,"") | G160: 50205010 | H160: =ISBLANK('Full Universe'!BE149) -> TRUE | I160: =ISBLANK('Full Universe'!BF149) -> TRUE | J160: =ISBLANK('Full Universe'!BG149) -> TRUE | K160: =ISBLANK('Full Universe'!BH149) -> TRUE | L160: =ISBLANK('Full Universe'!BI149) -> TRUE | M160: =ISBLANK('Full Universe'!BJ149) -> TRUE | N160: =ISBLANK('Full Universe'!BK149) -> TRUE | O160: =ISBLANK('Full Universe'!BL149) -> TRUE | ... AJ160: =ISBLANK('Full Universe'!CG149) -> FALSE | AK160: =ISNUMBER(MATCH(C160,[1]Europe!$B$2:$B$15,0)) -> FALSE | AL160: =ISBLANK('Full Universe'!CJ149) -> FALSE | AM160: 2.2107948 | AN160: =ISNUMBER(MATCH(C160,'Selected Companies'!$D$2:$D$101,0)) -> FALSE | AO160: =_xlfn.XLOOKUP(C160,[2]generation_steps!$C$2:$C$18963,[2]generation_steps!$CM$2:$CM$18963) -> 559.74609 | AP160: =_xlfn.XLOOKUP(C160,[2]generation_steps!$C$2:$C$18963,[2]generation_steps!$CN$2:$CN$18963) -> 1.7333333
A161: 45709 | B161: DIRECT LINE INSURANC | C161: GB00BY9D0Y18 | D161: XLON | E161: =_xlfn.XLOOKUP(C161,[2]generation_steps!$I$2:$I$500,[2]generation_steps!$L$2:$L$500) -> 0.00040639021 | F161: =_xlfn.XLOOKUP(C161,[2]full_dataframe_final!$C$2:$C$101,[2]full_dataframe_final!$H$2:$H$101,"") -> 0.00076316425 | G161: 30302025 | H161: =ISBLANK('Full Universe'!BE150) -> TRUE | I161: =ISBLANK('Full Universe'!BF150) -> TRUE | J161: =ISBLANK('Full Universe'!BG150) -> TRUE | K161: =ISBLANK('Full Universe'!BH150) -> TRUE | L161: =ISBLANK('Full Universe'!BI150) -> TRUE | M161: =ISBLANK('Full Universe'!BJ150) -> TRUE | N161: =ISBLANK('Full Universe'!BK150) -> TRUE | O161: =ISBLANK('Full Universe'!BL150) -> TRUE | ... AJ161: =ISBLANK('Full Universe'!CG150) -> TRUE | AK161: =ISNUMBER(MATCH(C161,[1]Europe!$B$2:$B$15,0)) -> FALSE | AL161: =ISBLANK('Full Universe'!CJ150) -> TRUE | AM161: 2.3663216 | AN161: =ISNUMBER(MATCH(C161,'Selected Companies'!$D$2:$D$101,0)) -> TRUE | AO161: =_xlfn.XLOOKUP(C161,[2]generation_steps!$C$2:$C$18963,[2]generation_steps!$CM$2:$CM$18963) -> 768.96524 | AP161: =_xlfn.XLOOKUP(C161,[2]generation_steps!$C$2:$C$18963,[2]generation_steps!$CN$2:$CN$18963) -> 1.5333333
A162: 45709 | B162: DNB BANK | C162: NO0010161896 | D162: XOSL | E162: =_xlfn.XLOOKUP(C162,[2]generation_steps!$I$2:$I$500,[2]generation_steps!$L$2:$L$500) -> 0.0017198733 | F162: =_xlfn.XLOOKUP(C162,[2]full_dataframe_final!$C$2:$C$101,[2]full_dataframe_final!$H$2:$H$101,"") | G162: 30101010 | H162: =ISBLANK('Full Universe'!BE151) -> TRUE | I162: =ISBLANK('Full Universe'!BF151) -> TRUE | J162: =ISBLANK('Full Universe'!BG151) -> TRUE | K162: =ISBLANK('Full Universe'!BH151) -> TRUE | L162: =ISBLANK('Full Universe'!BI151) -> TRUE | M162: =ISBLANK('Full Universe'!BJ151) -> TRUE | N162: =ISBLANK('Full Universe'!BK151) -> TRUE | O162: =ISBLANK('Full Universe'!BL151) -> TRUE | ... AJ162: =ISBLANK('Full Universe'!CG151) -> TRUE | AK162: =ISNUMBER(MATCH(C162,[1]Europe!$B$2:$B$15,0)) -> FALSE | AL162: =ISBLANK('Full Universe'!CJ151) -> TRUE | AM162: 3.01 | AN162: =ISNUMBER(MATCH(C162,'Selected Companies'!$D$2:$D$101,0)) -> FALSE | AO162: =_xlfn.XLOOKUP(C162,[2]generation_steps!$C$2:$C$18963,[2]generation_steps!$CM$2:$CM$18963) -> 217.70861 | AP162: =_xlfn.XLOOKUP(C162,[2]generation_steps!$C$2:$C$18963,[2]generation_steps!$CN$2:$CN$18963) -> 1.5666667
... A253: 45709 | B253: ING GROEP N.V. | C253: NL0011821202 | D253: XAMS | E253: =_xlfn.XLOOKUP(C253,[2]generation_steps!$I$2:$I$500,[2]generation_steps!$L$2:$L$500) -> 0.005008075 | F253: =_xlfn.XLOOKUP(C253,[2]full_dataframe_final!$C$2:$C$101,[2]full_dataframe_final!$H$2:$H$101,"") | G253: 30101010 | H253: =ISBLANK('Full Universe'!BE242) -> TRUE | I253: =ISBLANK('Full Universe'!BF242) -> TRUE | J253: =ISBLANK('Full Universe'!BG242) -> TRUE | K253: =ISBLANK('Full Universe'!BH242) -> TRUE | L253: =ISBLANK('Full Universe'!BI242) -> TRUE | M253: =ISBLANK('Full Universe'!BJ242) -> TRUE | N253: =ISBLANK('Full Universe'!BK242) -> TRUE | O253: =ISBLANK('Full Universe'!BL242) -> TRUE | ... AJ253: =ISBLANK('Full Universe'!CG242) -> TRUE | AK253: =ISNUMBER(MATCH(C253,[1]Europe!$B$2:$B$15,0)) -> FALSE | AL253: =ISBLANK('Full Universe'!CJ242) -> TRUE | AM253: 3.4866667 | AN253: =ISNUMBER(MATCH(C253,'Selected Companies'!$D$2:$D$101,0)) -> FALSE | AO253: =_xlfn.XLOOKUP(C253,[2]generation_steps!$C$2:$C$18963,[2]generation_steps!$CM$2:$CM$18963) -> 259.21967 | AP253: =_xlfn.XLOOKUP(C253,[2]generation_steps!$C$2:$C$18963,[2]generation_steps!$CN$2:$CN$18963) -> 1.5666667
A254: 45709 | B254: INTERCONTINENTAL HTL | C254: GB00BHJYC057 | D254: XLON | E254: =_xlfn.XLOOKUP(C254,[2]generation_steps!$I$2:$I$500,[2]generation_steps!$L$2:$L$500) -> 0.0013191929 | F254: =_xlfn.XLOOKUP(C254,[2]full_dataframe_final!$C$2:$C$101,[2]full_dataframe_final!$H$2:$H$101,"") | G254: 40501025 | H254: =ISBLANK('Full Universe'!BE244) -> TRUE | I254: =ISBLANK('Full Universe'!BF244) -> TRUE | J254: =ISBLANK('Full Universe'!BG244) -> TRUE | K254: =ISBLANK('Full Universe'!BH244) -> TRUE | L254: =ISBLANK('Full Universe'!BI244) -> TRUE | M254: =ISBLANK('Full Universe'!BJ244) -> TRUE | N254: =ISBLANK('Full Universe'!BK244) -> TRUE | O254: =ISBLANK('Full Universe'!BL244) -> TRUE | ... AJ254: =ISBLANK('Full Universe'!CG244) -> TRUE | AK254: =ISNUMBER(MATCH(C254,[1]Europe!$B$2:$B$15,0)) -> FALSE | AL254: =ISBLANK('Full Universe'!CJ244) -> TRUE | AM254: 1.9613794 | AN254: =ISNUMBER(MATCH(C254,'Selected Companies'!$D$2:$D$101,0)) -> FALSE | AO254: =_xlfn.XLOOKUP(C254,[2]generation_steps!$C$2:$C$18963,[2]generation_steps!$CM$2:$CM$18963) -> 467.08642 | AP254: =_xlfn.XLOOKUP(C254,[2]generation_steps!$C$2:$C$18963,[2]generation_steps!$CN$2:$CN$18963) -> 1.6333333
A255: 45709 | B255: INTERMEDIATE CAPITAL | C255: GB00BYT1DJ19 | D255: XLON | E255: =_xlfn.XLOOKUP(C255,[2]generation_steps!$I$2:$I$500,[2]generation_steps!$L$2:$L$500) -> 0.00059650003 | F255: =_xlfn.XLOOKUP(C255,[2]full_dataframe_final!$C$2:$C$101,[2]full_dataframe_final!$H$2:$H$101,"") -> 0.0011201734 | G255: 30202010 | H255: =ISBLANK('Full Universe'!BE245) -> TRUE | I255: =ISBLANK('Full Universe'!BF245) -> TRUE | J255: =ISBLANK('Full Universe'!BG245) -> TRUE | K255: =ISBLANK('Full Universe'!BH245) -> TRUE | L255: =ISBLANK('Full Universe'!BI245) -> TRUE | M255: =ISBLANK('Full Universe'!BJ245) -> TRUE | N255: =ISBLANK('Full Universe'!BK245) -> TRUE | O255: =ISBLANK('Full Universe'!BL245) -> TRUE | ... AJ255: =ISBLANK('Full Universe'!CG245) -> TRUE | AK255: =ISNUMBER(MATCH(C255,[1]Europe!$B$2:$B$15,0)) -> FALSE | AL255: =ISBLANK('Full Universe'!CJ245) -> TRUE | AM255: 2.3082571 | AN255: =ISNUMBER(MATCH(C255,'Selected Companies'!$D$2:$D$101,0)) -> TRUE | AO255: =_xlfn.XLOOKUP(C255,[2]generation_steps!$C$2:$C$18963,[2]generation_steps!$CM$2:$CM$18963) -> 1231.4285 | AP255: =_xlfn.XLOOKUP(C255,[2]generation_steps!$C$2:$C$18963,[2]generation_steps!$CN$2:$CN$18963) -> 1.5333333
A256: 45709 | B256: INTERPUMP GROUP | C256: IT0001078911 | D256: MTAA | E256: =_xlfn.XLOOKUP(C256,[2]generation_steps!$I$2:$I$500,[2]generation_steps!$L$2:$L$500) -> 0.00022921376 | F256: =_xlfn.XLOOKUP(C256,[2]full_dataframe_final!$C$2:$C$101,[2]full_dataframe_final!$H$2:$H$101,"") | G256: 50204000 | H256: =ISBLANK('Full Universe'!BE246) -> TRUE | I256: =ISBLANK('Full Universe'!BF246) -> TRUE | J256: =ISBLANK('Full Universe'!BG246) -> TRUE | K256: =ISBLANK('Full Universe'!BH246) -> TRUE | L256: =ISBLANK('Full Universe'!BI246) -> TRUE | M256: =ISBLANK('Full Universe'!BJ246) -> TRUE | N256: =ISBLANK('Full Universe'!BK246) -> TRUE | O256: =ISBLANK('Full Universe'!BL246) -> TRUE | ... AJ256: =ISBLANK('Full Universe'!CG246) -> TRUE | AK256: =ISNUMBER(MATCH(C256,[1]Europe!$B$2:$B$15,0)) -> FALSE | AL256: =ISBLANK('Full Universe'!CJ246) -> FALSE | AM256: 3.55 | AN256: =ISNUMBER(MATCH(C256,'Selected Companies'!$D$2:$D$101,0)) -> FALSE | AO256: =_xlfn.XLOOKUP(C256,[2]generation_steps!$C$2:$C$18963,[2]generation_steps!$CM$2:$CM$18963) -> 569.40684 | AP256: =_xlfn.XLOOKUP(C256,[2]generation_steps!$C$2:$C$18963,[2]generation_steps!$CN$2:$CN$18963) -> 1.6333333
A257: 45709 | B257: INTERTEK GROUP | C257: GB0031638363 | D257: XLON | E257: =_xlfn.XLOOKUP(C257,[2]generation_steps!$I$2:$I$500,[2]generation_steps!$L$2:$L$500) -> 0.0008368603 | F257: =_xlfn.XLOOKUP(C257,[2]full_dataframe_final!$C$2:$C$101,[2]full_dataframe_final!$H$2:$H$101,"") | G257: 50205020 | H257: =ISBLANK('Full Universe'!BE247) -> TRUE | I257: =ISBLANK('Full Universe'!BF247) -> TRUE | J257: =ISBLANK('Full Universe'!BG247) -> TRUE | K257: =ISBLANK('Full Universe'!BH247) -> TRUE | L257: =ISBLANK('Full Universe'!BI247) -> TRUE | M257: =ISBLANK('Full Universe'!BJ247) -> TRUE | N257: =ISBLANK('Full Universe'!BK247) -> TRUE | O257: =ISBLANK('Full Universe'!BL247) -> TRUE | ... AJ257: =ISBLANK('Full Universe'!CG247) -> TRUE | AK257: =ISNUMBER(MATCH(C257,[1]Europe!$B$2:$B$15,0)) -> FALSE | AL257: =ISBLANK('Full Universe'!CJ247) -> TRUE | AM257: 2.2132863 | AN257: =ISNUMBER(MATCH(C257,'Selected Companies'!$D$2:$D$101,0)) -> FALSE | AO257: =_xlfn.XLOOKUP(C257,[2]generation_steps!$C$2:$C$18963,[2]generation_steps!$CM$2:$CM$18963) -> 107.74466 | AP257: =_xlfn.XLOOKUP(C257,[2]generation_steps!$C$2:$C$18963,[2]generation_steps!$CN$2:$CN$18963) -> 1.5666667
A258: 45709 | B258: INTESA SANPAOLO | C258: IT0000072618 | D258: MTAA | E258: =_xlfn.XLOOKUP(C258,[2]generation_steps!$I$2:$I$500,[2]generation_steps!$L$2:$L$500) -> 0.0067464831 | F258: =_xlfn.XLOOKUP(C258,[2]full_dataframe_final!$C$2:$C$101,[2]full_dataframe_final!$H$2:$H$101,"") -> 0.012669288 | G258: 30101010 | H258: =ISBLANK('Full Universe'!BE248) -> TRUE | I258: =ISBLANK('Full Universe'!BF248) -> TRUE | J258: =ISBLANK('Full Universe'!BG248) -> TRUE | K258: =ISBLANK('Full Universe'!BH248) -> TRUE | L258: =ISBLANK('Full Universe'!BI248) -> TRUE | M258: =ISBLANK('Full Universe'!BJ248) -> TRUE | N258: =ISBLANK('Full Universe'!BK248) -> TRUE | O258: =ISBLANK('Full Universe'!BL248) -> TRUE | ... AJ258: =ISBLANK('Full Universe'!CG248) -> TRUE | AK258: =ISNUMBER(MATCH(C258,[1]Europe!$B$2:$B$15,0)) -> FALSE | AL258: =ISBLANK('Full Universe'!CJ248) -> TRUE | AM258: 1.8942319 | AN258: =ISNUMBER(MATCH(C258,'Selected Companies'!$D$2:$D$101,0)) -> TRUE | AO258: =_xlfn.XLOOKUP(C258,[2]generation_steps!$C$2:$C$18963,[2]generation_steps!$CM$2:$CM$18963) -> 278.04139 | AP258: =_xlfn.XLOOKUP(C258,[2]generation_steps!$C$2:$C$18963,[2]generation_steps!$CN$2:$CN$18963) -> 1.4666667
A259: 45709 | B259: INTL CONS AIRLINES | C259: ES0177542018 | D259: XLON | E259: =_xlfn.XLOOKUP(C259,[2]generation_steps!$I$2:$I$500,[2]generation_steps!$L$2:$L$500) -> 0.0010178228 | F259: =_xlfn.XLOOKUP(C259,[2]full_dataframe_final!$C$2:$C$101,[2]full_dataframe_final!$H$2:$H$101,"") | G259: 40501010 | H259: =ISBLANK('Full Universe'!BE249) -> TRUE | I259: =ISBLANK('Full Universe'!BF249) -> TRUE | J259: =ISBLANK('Full Universe'!BG249) -> TRUE | K259: =ISBLANK('Full Universe'!BH249) -> TRUE | L259: =ISBLANK('Full Universe'!BI249) -> TRUE | M259: =ISBLANK('Full Universe'!BJ249) -> TRUE | N259: =ISBLANK('Full Universe'!BK249) -> TRUE | O259: =ISBLANK('Full Universe'!BL249) -> TRUE | ... AJ259: =ISBLANK('Full Universe'!CG249) -> TRUE | AK259: =ISNUMBER(MATCH(C259,[1]Europe!$B$2:$B$15,0)) -> FALSE | AL259: =ISBLANK('Full Universe'!CJ249) -> TRUE | AM259: 2.3799502 | AN259: =ISNUMBER(MATCH(C259,'Selected Companies'!$D$2:$D$101,0)) -> FALSE | AO259: =_xlfn.XLOOKUP(C259,[2]generation_steps!$C$2:$C$18963,[2]generation_steps!$CM$2:$CM$18963) -> 1376.2721 | AP259: =_xlfn.XLOOKUP(C259,[2]generation_steps!$C$2:$C$18963,[2]generation_steps!$CN$2:$CN$18963) -> 1.6666667
A260: 45709 | B260: INVESTEC PLC | C260: GB00B17BBQ50 | D260: XLON | E260: =_xlfn.XLOOKUP(C260,[2]generation_steps!$I$2:$I$500,[2]generation_steps!$L$2:$L$500) -> 0.00033088569 | F260: =_xlfn.XLOOKUP(C260,[2]full_dataframe_final!$C$2:$C$101,[2]full_dataframe_final!$H$2:$H$101,"") | G260: 30101010 | H260: =ISBLANK('Full Universe'!BE250) -> TRUE | I260: =ISBLANK('Full Universe'!BF250) -> TRUE | J260: =ISBLANK('Full Universe'!BG250) -> TRUE | K260: =ISBLANK('Full Universe'!BH250) -> TRUE | L260: =ISBLANK('Full Universe'!BI250) -> TRUE | M260: =ISBLANK('Full Universe'!BJ250) -> TRUE | N260: =ISBLANK('Full Universe'!BK250) -> TRUE | O260: =ISBLANK('Full Universe'!BL250) -> TRUE | ... AJ260: =ISBLANK('Full Universe'!CG250) -> TRUE | AK260: =ISNUMBER(MATCH(C260,[1]Europe!$B$2:$B$15,0)) -> FALSE | AL260: =ISBLANK('Full Universe'!CJ250) -> TRUE | AM260: 3.0138107 | AN260: =ISNUMBER(MATCH(C260,'Selected Companies'!$D$2:$D$101,0)) -> FALSE | AO260: =_xlfn.XLOOKUP(C260,[2]generation_steps!$C$2:$C$18963,[2]generation_steps!$CM$2:$CM$18963) -> 172.63177 | AP260: =_xlfn.XLOOKUP(C260,[2]generation_steps!$C$2:$C$18963,[2]generation_steps!$CN$2:$CN$18963) -> 1.6
A261: 45709 | B261: INVESTOR AB CLASS B | C261: SE0015811963 | D261: XSTO | E261: =_xlfn.XLOOKUP(C261,[2]generation_steps!$I$2:$I$500,[2]generation_steps!$L$2:$L$500) -> 0.0044497516 | F261: =_xlfn.XLOOKUP(C261,[2]full_dataframe_final!$C$2:$C$101,[2]full_dataframe_final!$H$2:$H$101,"") | G261: 30202000 | H261: =ISBLANK('Full Universe'!BE251) -> TRUE | I261: =ISBLANK('Full Universe'!BF251) -> TRUE | J261: =ISBLANK('Full Universe'!BG251) -> TRUE | K261: =ISBLANK('Full Universe'!BH251) -> TRUE | L261: =ISBLANK('Full Universe'!BI251) -> TRUE | M261: =ISBLANK('Full Universe'!BJ251) -> TRUE | N261: =ISBLANK('Full Universe'!BK251) -> TRUE | O261: =ISBLANK('Full Universe'!BL251) -> TRUE | ... AJ261: =ISBLANK('Full Universe'!CG251) -> TRUE | AK261: =ISNUMBER(MATCH(C261,[1]Europe!$B$2:$B$15,0)) -> FALSE | AL261: =ISBLANK('Full Universe'!CJ251) -> TRUE | AM261: 3.25 | AN261: =ISNUMBER(MATCH(C261,'Selected Companies'!$D$2:$D$101,0)) -> FALSE | AO261: =_xlfn.XLOOKUP(C261,[2]generation_steps!$C$2:$C$18963,[2]generation_steps!$CM$2:$CM$18963) -> 22.656426 | AP261: =_xlfn.XLOOKUP(C261,[2]generation_steps!$C$2:$C$18963,[2]generation_steps!$CN$2:$CN$18963) -> 1.5
A262: 45709 | B262: INWIT | C262: IT0005090300 | D262: MTAA | E262: =_xlfn.XLOOKUP(C262,[2]generation_steps!$I$2:$I$500,[2]generation_steps!$L$2:$L$500) -> 0.00030864049 | F262: =_xlfn.XLOOKUP(C262,[2]full_dataframe_final!$C$2:$C$101,[2]full_dataframe_final!$H$2:$H$101,"") | G262: 15102015 | H262: =ISBLANK('Full Universe'!BE252) -> TRUE | I262: =ISBLANK('Full Universe'!BF252) -> TRUE | J262: =ISBLANK('Full Universe'!BG252) -> TRUE | K262: =ISBLANK('Full Universe'!BH252) -> TRUE | L262: =ISBLANK('Full Universe'!BI252) -> TRUE | M262: =ISBLANK('Full Universe'!BJ252) -> TRUE | N262: =ISBLANK('Full Universe'!BK252) -> TRUE | O262: =ISBLANK('Full Universe'!BL252) -> TRUE | ... AJ262: =ISBLANK('Full Universe'!CG252) -> TRUE | AK262: =ISNUMBER(MATCH(C262,[1]Europe!$B$2:$B$15,0)) -> FALSE | AL262: =ISBLANK('Full Universe'!CJ252) -> TRUE | AM262: 2.1182566 | AN262: =ISNUMBER(MATCH(C262,'Selected Companies'!$D$2:$D$101,0)) -> FALSE | AO262: =_xlfn.XLOOKUP(C262,[2]generation_steps!$C$2:$C$18963,[2]generation_steps!$CM$2:$CM$18963) -> 15.760893 | AP262: =_xlfn.XLOOKUP(C262,[2]generation_steps!$C$2:$C$18963,[2]generation_steps!$CN$2:$CN$18963) -> 1.4
A263: 45709 | B263: IPSEN | C263: FR0010259150 | D263: XPAR | E263: =_xlfn.XLOOKUP(C263,[2]generation_steps!$I$2:$I$500,[2]generation_steps!$L$2:$L$500) -> 0.0003212991 | F263: =_xlfn.XLOOKUP(C263,[2]full_dataframe_final!$C$2:$C$101,[2]full_dataframe_final!$H$2:$H$101,"") | G263: 20103015 | H263: =ISBLANK('Full Universe'!BE253) -> TRUE | I263: =ISBLANK('Full Universe'!BF253) -> TRUE | J263: =ISBLANK('Full Universe'!BG253) -> TRUE | K263: =ISBLANK('Full Universe'!BH253) -> TRUE | L263: =ISBLANK('Full Universe'!BI253) -> TRUE | M263: =ISBLANK('Full Universe'!BJ253) -> TRUE | N263: =ISBLANK('Full Universe'!BK253) -> TRUE | O263: =ISBLANK('Full Universe'!BL253) -> TRUE | ... AJ263: =ISBLANK('Full Universe'!CG253) -> TRUE | AK263: =ISNUMBER(MATCH(C263,[1]Europe!$B$2:$B$15,0)) -> FALSE | AL263: =ISBLANK('Full Universe'!CJ253) -> TRUE | AM263: 2.4296503 | AN263: =ISNUMBER(MATCH(C263,'Selected Companies'!$D$2:$D$101,0)) -> FALSE | AO263: =_xlfn.XLOOKUP(C263,[2]generation_steps!$C$2:$C$18963,[2]generation_steps!$CM$2:$CM$18963) -> 3.4686767 | AP263: =_xlfn.XLOOKUP(C263,[2]generation_steps!$C$2:$C$18963,[2]generation_steps!$CN$2:$CN$18963) -> 1.4
A264: 45709 | B264: ISS A/S | C264: DK0060542181 | D264: XCSE | E264: =_xlfn.XLOOKUP(C264,[2]generation_steps!$I$2:$I$500,[2]generation_steps!$L$2:$L$500) -> 0.00028199056 | F264: =_xlfn.XLOOKUP(C264,[2]full_dataframe_final!$C$2:$C$101,[2]full_dataframe_final!$H$2:$H$101,"") | G264: 50205040 | H264: =ISBLANK('Full Universe'!BE254) -> TRUE | I264: =ISBLANK('Full Universe'!BF254) -> TRUE | J264: =ISBLANK('Full Universe'!BG254) -> TRUE | K264: =ISBLANK('Full Universe'!BH254) -> TRUE | L264: =ISBLANK('Full Universe'!BI254) -> TRUE | M264: =ISBLANK('Full Universe'!BJ254) -> TRUE | N264: =ISBLANK('Full Universe'!BK254) -> TRUE | O264: =ISBLANK('Full Universe'!BL254) -> TRUE | ... AJ264: =ISBLANK('Full Universe'!CG254) -> TRUE | AK264: =ISNUMBER(MATCH(C264,[1]Europe!$B$2:$B$15,0)) -> FALSE | AL264: =ISBLANK('Full Universe'!CJ254) -> TRUE | AM264: 2.0369653 | AN264: =ISNUMBER(MATCH(C264,'Selected Companies'!$D$2:$D$101,0)) -> FALSE | AO264: =_xlfn.XLOOKUP(C264,[2]generation_steps!$C$2:$C$18963,[2]generation_steps!$CM$2:$CM$18963) -> 291.11447 | AP264: =_xlfn.XLOOKUP(C264,[2]generation_steps!$C$2:$C$18963,[2]generation_steps!$CN$2:$CN$18963) -> 1.5333333
A265: 45709 | B265: ITALGAS | C265: IT0005211237 | D265: MTAA | E265: =_xlfn.XLOOKUP(C265,[2]generation_steps!$I$2:$I$500,[2]generation_steps!$L$2:$L$500) -> 0.00031871449 | F265: =_xlfn.XLOOKUP(C265,[2]full_dataframe_final!$C$2:$C$101,[2]full_dataframe_final!$H$2:$H$101,"") | G265: 65102020 | H265: =ISBLANK('Full Universe'!BE255) -> TRUE | I265: =ISBLANK('Full Universe'!BF255) -> TRUE | J265: =ISBLANK('Full Universe'!BG255) -> TRUE | K265: =ISBLANK('Full Universe'!BH255) -> TRUE | L265: =ISBLANK('Full Universe'!BI255) -> TRUE | M265: =ISBLANK('Full Universe'!BJ255) -> TRUE | N265: =ISBLANK('Full Universe'!BK255) -> TRUE | O265: =ISBLANK('Full Universe'!BL255) -> TRUE | ... AJ265: =ISBLANK('Full Universe'!CG255) -> TRUE | AK265: =ISNUMBER(MATCH(C265,[1]Europe!$B$2:$B$15,0)) -> FALSE | AL265: =ISBLANK('Full Universe'!CJ255) -> TRUE | AM265: 2.0544087 | AN265: =ISNUMBER(MATCH(C265,'Selected Companies'!$D$2:$D$101,0)) -> FALSE | AO265: =_xlfn.XLOOKUP(C265,[2]generation_steps!$C$2:$C$18963,[2]generation_steps!$CM$2:$CM$18963) -> 29.502858 | AP265: =_xlfn.XLOOKUP(C265,[2]generation_steps!$C$2:$C$18963,[2]generation_steps!$CN$2:$CN$18963) -> 1.5666667
... A276: 45709 | B276: KINGFISHER | C276: GB0033195214 | D276: XLON | E276: =_xlfn.XLOOKUP(C276,[2]generation_steps!$I$2:$I$500,[2]generation_steps!$L$2:$L$500) -> 0.00045843633 | F276: =_xlfn.XLOOKUP(C276,[2]full_dataframe_final!$C$2:$C$101,[2]full_dataframe_final!$H$2:$H$101,"") -> 0.0034436087 | G276: 40401025 | H276: =ISBLANK('Full Universe'!BE266) -> TRUE | I276: =ISBLANK('Full Universe'!BF266) -> TRUE | J276: =ISBLANK('Full Universe'!BG266) -> TRUE | K276: =ISBLANK('Full Universe'!BH266) -> TRUE | L276: =ISBLANK('Full Universe'!BI266) -> TRUE | M276: =ISBLANK('Full Universe'!BJ266) -> TRUE | N276: =ISBLANK('Full Universe'!BK266) -> TRUE | O276: =ISBLANK('Full Universe'!BL266) -> TRUE | ... AJ276: =ISBLANK('Full Universe'!CG266) -> TRUE | AK276: =ISNUMBER(MATCH(C276,[1]Europe!$B$2:$B$15,0)) -> FALSE | AL276: =ISBLANK('Full Universe'!CJ266) -> TRUE | AM276: 1.5083996 | AN276: =ISNUMBER(MATCH(C276,'Selected Companies'!$D$2:$D$101,0)) -> TRUE | AO276: =_xlfn.XLOOKUP(C276,[2]generation_steps!$C$2:$C$18963,[2]generation_steps!$CM$2:$CM$18963) -> 2015.699 | AP276: =_xlfn.XLOOKUP(C276,[2]generation_steps!$C$2:$C$18963,[2]generation_steps!$CN$2:$CN$18963) -> 1.6333333
A277: 45709 | B277: KLEPIERRE | C277: FR0000121964 | D277: XPAR | E277: =_xlfn.XLOOKUP(C277,[2]generation_steps!$I$2:$I$500,[2]generation_steps!$L$2:$L$500) -> 0.00063551219 | F277: =_xlfn.XLOOKUP(C277,[2]full_dataframe_final!$C$2:$C$101,[2]full_dataframe_final!$H$2:$H$101,"") | G277: 35102045 | H277: =ISBLANK('Full Universe'!BE268) -> TRUE | I277: =ISBLANK('Full Universe'!BF268) -> TRUE | J277: =ISBLANK('Full Universe'!BG268) -> TRUE | K277: =ISBLANK('Full Universe'!BH268) -> TRUE | L277: =ISBLANK('Full Universe'!BI268) -> TRUE | M277: =ISBLANK('Full Universe'!BJ268) -> TRUE | N277: =ISBLANK('Full Universe'!BK268) -> TRUE | O277: =ISBLANK('Full Universe'!BL268) -> TRUE | ... AJ277: =ISBLANK('Full Universe'!CG268) -> TRUE | AK277: =ISNUMBER(MATCH(C277,[1]Europe!$B$2:$B$15,0)) -> FALSE | AL277: =ISBLANK('Full Universe'!CJ268) -> TRUE | AM277: 2.2473576 | AN277: =ISNUMBER(MATCH(C277,'Selected Companies'!$D$2:$D$101,0)) -> FALSE | AO277: =_xlfn.XLOOKUP(C277,[2]generation_steps!$C$2:$C$18963,[2]generation_steps!$CM$2:$CM$18963) -> 60.686729 | AP277: =_xlfn.XLOOKUP(C277,[2]generation_steps!$C$2:$C$18963,[2]generation_steps!$CN$2:$CN$18963) -> 2.0333333
A278: 45709 | B278: KONE OYJ | C278: FI0009013403 | D278: XHEL | E278: =_xlfn.XLOOKUP(C278,[2]generation_steps!$I$2:$I$500,[2]generation_steps!$L$2:$L$500) -> 0.0019167812 | F278: =_xlfn.XLOOKUP(C278,[2]full_dataframe_final!$C$2:$C$101,[2]full_dataframe_final!$H$2:$H$101,"") -> 0.014398171 | G278: 50204000 | H278: =ISBLANK('Full Universe'!BE270) -> TRUE | I278: =ISBLANK('Full Universe'!BF270) -> TRUE | J278: =ISBLANK('Full Universe'!BG270) -> TRUE | K278: =ISBLANK('Full Universe'!BH270) -> TRUE | L278: =ISBLANK('Full Universe'!BI270) -> TRUE | M278: =ISBLANK('Full Universe'!BJ270) -> TRUE | N278: =ISBLANK('Full Universe'!BK270) -> TRUE | O278: =ISBLANK('Full Universe'!BL270) -> TRUE | ... AJ278: =ISBLANK('Full Universe'!CG270) -> TRUE | AK278: =ISNUMBER(MATCH(C278,[1]Europe!$B$2:$B$15,0)) -> FALSE | AL278: =ISBLANK('Full Universe'!CJ270) -> TRUE | AM278: 1.7376534 | AN278: =ISNUMBER(MATCH(C278,'Selected Companies'!$D$2:$D$101,0)) -> TRUE | AO278: =_xlfn.XLOOKUP(C278,[2]generation_steps!$C$2:$C$18963,[2]generation_steps!$CM$2:$CM$18963) -> 544.71235 | AP278: =_xlfn.XLOOKUP(C278,[2]generation_steps!$C$2:$C$18963,[2]generation_steps!$CN$2:$CN$18963) -> 1.4666667
A279: 45709 | B279: KONECRANES ABP | C279: FI0009005870 | D279: XHEL | E279: =_xlfn.XLOOKUP(C279,[2]generation_steps!$I$2:$I$500,[2]generation_steps!$L$2:$L$500) -> 0.00041886115 | F279: =_xlfn.XLOOKUP(C279,[2]full_dataframe_final!$C$2:$C$101,[2]full_dataframe_final!$H$2:$H$101,"") | G279: 50206015 | H279: =ISBLANK('Full Universe'!BE271) -> TRUE | I279: =ISBLANK('Full Universe'!BF271) -> TRUE | J279: =ISBLANK('Full Universe'!BG271) -> TRUE | K279: =ISBLANK('Full Universe'!BH271) -> TRUE | L279: =ISBLANK('Full Universe'!BI271) -> TRUE | M279: =ISBLANK('Full Universe'!BJ271) -> TRUE | N279: =ISBLANK('Full Universe'!BK271) -> TRUE | O279: =ISBLANK('Full Universe'!BL271) -> TRUE | ... AJ279: =ISBLANK('Full Universe'!CG271) -> TRUE | AK279: =ISNUMBER(MATCH(C279,[1]Europe!$B$2:$B$15,0)) -> FALSE | AL279: =ISBLANK('Full Universe'!CJ271) -> TRUE | AM279: 2.2477098 | AN279: =ISNUMBER(MATCH(C279,'Selected Companies'!$D$2:$D$101,0)) -> FALSE | AO279: =_xlfn.XLOOKUP(C279,[2]generation_steps!$C$2:$C$18963,[2]generation_steps!$CM$2:$CM$18963) -> 1258.4831 | AP279: =_xlfn.XLOOKUP(C279,[2]generation_steps!$C$2:$C$18963,[2]generation_steps!$CN$2:$CN$18963) -> 1.4666667
A280: 45709 | B280: KONGSBERG GRUPPEN | C280: NO0003043309 | D280: XOSL | E280: =_xlfn.XLOOKUP(C280,[2]generation_steps!$I$2:$I$500,[2]generation_steps!$L$2:$L$500) -> 0.0011542896 | F280: =_xlfn.XLOOKUP(C280,[2]full_dataframe_final!$C$2:$C$101,[2]full_dataframe_final!$H$2:$H$101,"") | G280: 50203000 | H280: =ISBLANK('Full Universe'!BE272) -> TRUE | I280: =ISBLANK('Full Universe'!BF272) -> TRUE | J280: =ISBLANK('Full Universe'!BG272) -> TRUE | K280: =ISBLANK('Full Universe'!BH272) -> TRUE | L280: =ISBLANK('Full Universe'!BI272) -> TRUE | M280: =ISBLANK('Full Universe'!BJ272) -> TRUE | N280: =ISBLANK('Full Universe'!BK272) -> TRUE | O280: =ISBLANK('Full Universe'!BL272) -> TRUE | ... AJ280: =ISBLANK('Full Universe'!CG272) -> TRUE | AK280: =ISNUMBER(MATCH(C280,[1]Europe!$B$2:$B$15,0)) -> FALSE | AL280: =ISBLANK('Full Universe'!CJ272) -> TRUE | AM280: 2.3087792 | AN280: =ISNUMBER(MATCH(C280,'Selected Companies'!$D$2:$D$101,0)) -> FALSE | AO280: =_xlfn.XLOOKUP(C280,[2]generation_steps!$C$2:$C$18963,[2]generation_steps!$CM$2:$CM$18963) -> 2352.12 | AP280: =_xlfn.XLOOKUP(C280,[2]generation_steps!$C$2:$C$18963,[2]generation_steps!$CN$2:$CN$18963) -> 1.6
A281: 45709 | B281: KPN KON | C281: NL0000009082 | D281: XAMS | E281: =_xlfn.XLOOKUP(C281,[2]generation_steps!$I$2:$I$500,[2]generation_steps!$L$2:$L$500) -> 0.0015126054 | F281: =_xlfn.XLOOKUP(C281,[2]full_dataframe_final!$C$2:$C$101,[2]full_dataframe_final!$H$2:$H$101,"") | G281: 15102015 | H281: =ISBLANK('Full Universe'!BE273) -> TRUE | I281: =ISBLANK('Full Universe'!BF273) -> TRUE | J281: =ISBLANK('Full Universe'!BG273) -> TRUE | K281: =ISBLANK('Full Universe'!BH273) -> TRUE | L281: =ISBLANK('Full Universe'!BI273) -> TRUE | M281: =ISBLANK('Full Universe'!BJ273) -> TRUE | N281: =ISBLANK('Full Universe'!BK273) -> TRUE | O281: =ISBLANK('Full Universe'!BL273) -> TRUE | ... AJ281: =ISBLANK('Full Universe'!CG273) -> TRUE | AK281: =ISNUMBER(MATCH(C281,[1]Europe!$B$2:$B$15,0)) -> FALSE | AL281: =ISBLANK('Full Universe'!CJ273) -> TRUE | AM281: 2.085405 | AN281: =ISNUMBER(MATCH(C281,'Selected Companies'!$D$2:$D$101,0)) -> FALSE | AO281: =_xlfn.XLOOKUP(C281,[2]generation_steps!$C$2:$C$18963,[2]generation_steps!$CM$2:$CM$18963) -> 38.06481 | AP281: =_xlfn.XLOOKUP(C281,[2]generation_steps!$C$2:$C$18963,[2]generation_steps!$CN$2:$CN$18963) -> 1.4
A282: 45709 | B282: KUEHNE + NAGEL INTL | C282: CH0025238863 | D282: XSWX | E282: =_xlfn.XLOOKUP(C282,[2]generation_steps!$I$2:$I$500,[2]generation_steps!$L$2:$L$500) -> 0.0010446781 | F282: =_xlfn.XLOOKUP(C282,[2]full_dataframe_final!$C$2:$C$101,[2]full_dataframe_final!$H$2:$H$101,"") | G282: 50206030 | H282: =ISBLANK('Full Universe'!BE274) -> TRUE | I282: =ISBLANK('Full Universe'!BF274) -> TRUE | J282: =ISBLANK('Full Universe'!BG274) -> TRUE | K282: =ISBLANK('Full Universe'!BH274) -> TRUE | L282: =ISBLANK('Full Universe'!BI274) -> TRUE | M282: =ISBLANK('Full Universe'!BJ274) -> TRUE | N282: =ISBLANK('Full Universe'!BK274) -> TRUE | O282: =ISBLANK('Full Universe'!BL274) -> TRUE | ... AJ282: =ISBLANK('Full Universe'!CG274) -> TRUE | AK282: =ISNUMBER(MATCH(C282,[1]Europe!$B$2:$B$15,0)) -> FALSE | AL282: =ISBLANK('Full Universe'!CJ274) -> TRUE | AM282: 2.3686126 | AN282: =ISNUMBER(MATCH(C282,'Selected Companies'!$D$2:$D$101,0)) -> FALSE | AO282: =_xlfn.XLOOKUP(C282,[2]generation_steps!$C$2:$C$18963,[2]generation_steps!$CM$2:$CM$18963) -> 371.9699 | AP282: =_xlfn.XLOOKUP(C282,[2]generation_steps!$C$2:$C$18963,[2]generation_steps!$CN$2:$CN$18963) -> 1.4333333
A283: 45709 | B283: LAGERCRANTZ GRP AB B | C283: SE0014990966 | D283: XSTO | E283: =_xlfn.XLOOKUP(C283,[2]generation_steps!$I$2:$I$500,[2]generation_steps!$L$2:$L$500) -> 0.00036022432 | F283: =_xlfn.XLOOKUP(C283,[2]full_dataframe_final!$C$2:$C$101,[2]full_dataframe_final!$H$2:$H$101,"") | G283: 10102015 | H283: =ISBLANK('Full Universe'!BE275) -> TRUE | I283: =ISBLANK('Full Universe'!BF275) -> TRUE | J283: =ISBLANK('Full Universe'!BG275) -> TRUE | K283: =ISBLANK('Full Universe'!BH275) -> TRUE | L283: =ISBLANK('Full Universe'!BI275) -> TRUE | M283: =ISBLANK('Full Universe'!BJ275) -> TRUE | N283: =ISBLANK('Full Universe'!BK275) -> TRUE | O283: =ISBLANK('Full Universe'!BL275) -> TRUE | ... AJ283: =ISBLANK('Full Universe'!CG275) -> TRUE | AK283: =ISNUMBER(MATCH(C283,[1]Europe!$B$2:$B$15,0)) -> FALSE | AL283: =ISBLANK('Full Universe'!CJ275) -> FALSE | AM283: 3.25 | AN283: =ISNUMBER(MATCH(C283,'Selected Companies'!$D$2:$D$101,0)) -> FALSE | AO283: =_xlfn.XLOOKUP(C283,[2]generation_steps!$C$2:$C$18963,[2]generation_steps!$CM$2:$CM$18963) -> 66.648747 | AP283: =_xlfn.XLOOKUP(C283,[2]generation_steps!$C$2:$C$18963,[2]generation_steps!$CN$2:$CN$18963) -> 1.6333333
A284: 45709 | B284: LAND SECURITIES | C284: GB00BYW0PQ60 | D284: XLON | E284: =_xlfn.XLOOKUP(C284,[2]generation_steps!$I$2:$I$500,[2]generation_steps!$L$2:$L$500) -> 0.00046515411 | F284: =_xlfn.XLOOKUP(C284,[2]full_dataframe_final!$C$2:$C$101,[2]full_dataframe_final!$H$2:$H$101,"") -> 0.0034940703 | G284: 35102000 | H284: =ISBLANK('Full Universe'!BE276) -> TRUE | I284: =ISBLANK('Full Universe'!BF276) -> TRUE | J284: =ISBLANK('Full Universe'!BG276) -> TRUE | K284: =ISBLANK('Full Universe'!BH276) -> TRUE | L284: =ISBLANK('Full Universe'!BI276) -> TRUE | M284: =ISBLANK('Full Universe'!BJ276) -> TRUE | N284: =ISBLANK('Full Universe'!BK276) -> TRUE | O284: =ISBLANK('Full Universe'!BL276) -> TRUE | ... AJ284: =ISBLANK('Full Universe'!CG276) -> TRUE | AK284: =ISNUMBER(MATCH(C284,[1]Europe!$B$2:$B$15,0)) -> FALSE | AL284: =ISBLANK('Full Universe'!CJ276) -> TRUE | AM284: 1.3197815 | AN284: =ISNUMBER(MATCH(C284,'Selected Companies'!$D$2:$D$101,0)) -> TRUE | AO284: =_xlfn.XLOOKUP(C284,[2]generation_steps!$C$2:$C$18963,[2]generation_steps!$CM$2:$CM$18963) -> 22.84932 | AP284: =_xlfn.XLOOKUP(C284,[2]generation_steps!$C$2:$C$18963,[2]generation_steps!$CN$2:$CN$18963) -> 1.4666667
A285: 45709 | B285: LATOUR AB INV. - B | C285: SE0010100958 | D285: XSTO | E285: =_xlfn.XLOOKUP(C285,[2]generation_steps!$I$2:$I$500,[2]generation_steps!$L$2:$L$500) -> 0.00034468641 | F285: =_xlfn.XLOOKUP(C285,[2]full_dataframe_final!$C$2:$C$101,[2]full_dataframe_final!$H$2:$H$101,"") | G285: 50203000 | H285: =ISBLANK('Full Universe'!BE277) -> TRUE | I285: =ISBLANK('Full Universe'!BF277) -> TRUE | J285: =ISBLANK('Full Universe'!BG277) -> TRUE | K285: =ISBLANK('Full Universe'!BH277) -> TRUE | L285: =ISBLANK('Full Universe'!BI277) -> TRUE | M285: =ISBLANK('Full Universe'!BJ277) -> TRUE | N285: =ISBLANK('Full Universe'!BK277) -> TRUE | O285: =ISBLANK('Full Universe'!BL277) -> TRUE | ... AJ285: =ISBLANK('Full Universe'!CG277) -> TRUE | AK285: =ISNUMBER(MATCH(C285,[1]Europe!$B$2:$B$15,0)) -> FALSE | AL285: =ISBLANK('Full Universe'!CJ277) -> FALSE | AM285: 2.6669972 | AN285: =ISNUMBER(MATCH(C285,'Selected Companies'!$D$2:$D$101,0)) -> FALSE | AO285: =_xlfn.XLOOKUP(C285,[2]generation_steps!$C$2:$C$18963,[2]generation_steps!$CM$2:$CM$18963) -> 38.521774 | AP285: =_xlfn.XLOOKUP(C285,[2]generation_steps!$C$2:$C$18963,[2]generation_steps!$CN$2:$CN$18963) -> 1.5
A286: 45709 | B286: LEG IMMOBILIEN SE | C286: DE000LEG1110 | D286: XETR | E286: =_xlfn.XLOOKUP(C286,[2]generation_steps!$I$2:$I$500,[2]generation_steps!$L$2:$L$500) -> 0.00053301812 | F286: =_xlfn.XLOOKUP(C286,[2]full_dataframe_final!$C$2:$C$101,[2]full_dataframe_final!$H$2:$H$101,"") | G286: 35101010 | H286: =ISBLANK('Full Universe'!BE278) -> TRUE | I286: =ISBLANK('Full Universe'!BF278) -> TRUE | J286: =ISBLANK('Full Universe'!BG278) -> TRUE | K286: =ISBLANK('Full Universe'!BH278) -> TRUE | L286: =ISBLANK('Full Universe'!BI278) -> TRUE | M286: =ISBLANK('Full Universe'!BJ278) -> TRUE | N286: =ISBLANK('Full Universe'!BK278) -> TRUE | O286: =ISBLANK('Full Universe'!BL278) -> TRUE | ... AJ286: =ISBLANK('Full Universe'!CG278) -> TRUE | AK286: =ISNUMBER(MATCH(C286,[1]Europe!$B$2:$B$15,0)) -> FALSE | AL286: =ISBLANK('Full Universe'!CJ278) -> TRUE | AM286: 3.07 | AN286: =ISNUMBER(MATCH(C286,'Selected Companies'!$D$2:$D$101,0)) -> FALSE | AO286: =_xlfn.XLOOKUP(C286,[2]generation_steps!$C$2:$C$18963,[2]generation_steps!$CM$2:$CM$18963) -> 31.911597 | AP286: =_xlfn.XLOOKUP(C286,[2]generation_steps!$C$2:$C$18963,[2]generation_steps!$CN$2:$CN$18963) -> 1.8333333
A287: 45709 | B287: LEGAL AND GENERAL | C287: GB0005603997 | D287: XLON | E287: =_xlfn.XLOOKUP(C287,[2]generation_steps!$I$2:$I$500,[2]generation_steps!$L$2:$L$500) -> 0.0016184721 | F287: =_xlfn.XLOOKUP(C287,[2]full_dataframe_final!$C$2:$C$101,[2]full_dataframe_final!$H$2:$H$101,"") -> 0.003039345 | G287: 30301010 | H287: =ISBLANK('Full Universe'!BE279) -> TRUE | I287: =ISBLANK('Full Universe'!BF279) -> TRUE | J287: =ISBLANK('Full Universe'!BG279) -> TRUE | K287: =ISBLANK('Full Universe'!BH279) -> TRUE | L287: =ISBLANK('Full Universe'!BI279) -> TRUE | M287: =ISBLANK('Full Universe'!BJ279) -> TRUE | N287: =ISBLANK('Full Universe'!BK279) -> TRUE | O287: =ISBLANK('Full Universe'!BL279) -> TRUE | ... AJ287: =ISBLANK('Full Universe'!CG279) -> TRUE | AK287: =ISNUMBER(MATCH(C287,[1]Europe!$B$2:$B$15,0)) -> FALSE | AL287: =ISBLANK('Full Universe'!CJ279) -> TRUE | AM287: 1.4441752 | AN287: =ISNUMBER(MATCH(C287,'Selected Companies'!$D$2:$D$101,0)) -> TRUE | AO287: =_xlfn.XLOOKUP(C287,[2]generation_steps!$C$2:$C$18963,[2]generation_steps!$CM$2:$CM$18963) -> 3647.589 | AP287: =_xlfn.XLOOKUP(C287,[2]generation_steps!$C$2:$C$18963,[2]generation_steps!$CN$2:$CN$18963) -> 3.1666667
A288: 45709 | B288: LEGRAND | C288: FR0010307819 | D288: XPAR | E288: =_xlfn.XLOOKUP(C288,[2]generation_steps!$I$2:$I$500,[2]generation_steps!$L$2:$L$500) -> 0.0023959053 | F288: =_xlfn.XLOOKUP(C288,[2]full_dataframe_final!$C$2:$C$101,[2]full_dataframe_final!$H$2:$H$101,"") -> 0.017997179 | G288: 50202010 | H288: =ISBLANK('Full Universe'!BE280) -> TRUE | I288: =ISBLANK('Full Universe'!BF280) -> TRUE | J288: =ISBLANK('Full Universe'!BG280) -> TRUE | K288: =ISBLANK('Full Universe'!BH280) -> TRUE | L288: =ISBLANK('Full Universe'!BI280) -> TRUE | M288: =ISBLANK('Full Universe'!BJ280) -> TRUE | N288: =ISBLANK('Full Universe'!BK280) -> TRUE | O288: =ISBLANK('Full Universe'!BL280) -> TRUE | ... AJ288: =ISBLANK('Full Universe'!CG280) -> TRUE | AK288: =ISNUMBER(MATCH(C288,[1]Europe!$B$2:$B$15,0)) -> FALSE | AL288: =ISBLANK('Full Universe'!CJ280) -> TRUE | AM288: 1.3209034 | AN288: =ISNUMBER(MATCH(C288,'Selected Companies'!$D$2:$D$101,0)) -> TRUE | AO288: =_xlfn.XLOOKUP(C288,[2]generation_steps!$C$2:$C$18963,[2]generation_steps!$CM$2:$CM$18963) -> 432.24327 | AP288: =_xlfn.XLOOKUP(C288,[2]generation_steps!$C$2:$C$18963,[2]generation_steps!$CN$2:$CN$18963) -> 1.5
A289: 45709 | B289: LEONARDO | C289: IT0003856405 | D289: MTAA | E289: =_xlfn.XLOOKUP(C289,[2]generation_steps!$I$2:$I$500,[2]generation_steps!$L$2:$L$500) -> 0.0018189859 | F289: =_xlfn.XLOOKUP(C289,[2]full_dataframe_final!$C$2:$C$101,[2]full_dataframe_final!$H$2:$H$101,"") | G289: 50201020 | H289: =ISBLANK('Full Universe'!BE281) -> TRUE | I289: =ISBLANK('Full Universe'!BF281) -> TRUE | J289: =ISBLANK('Full Universe'!BG281) -> TRUE | K289: =ISBLANK('Full Universe'!BH281) -> FALSE | L289: =ISBLANK('Full Universe'!BI281) -> TRUE | M289: =ISBLANK('Full Universe'!BJ281) -> TRUE | N289: =ISBLANK('Full Universe'!BK281) -> TRUE | O289: =ISBLANK('Full Universe'!BL281) -> TRUE | ... AJ289: =ISBLANK('Full Universe'!CG281) -> TRUE | AK289: =ISNUMBER(MATCH(C289,[1]Europe!$B$2:$B$15,0)) -> FALSE | AL289: =ISBLANK('Full Universe'!CJ281) -> TRUE | AM289: 1.8369067 | AN289: =ISNUMBER(MATCH(C289,'Selected Companies'!$D$2:$D$101,0)) -> FALSE | AO289: =_xlfn.XLOOKUP(C289,[2]generation_steps!$C$2:$C$18963,[2]generation_steps!$CM$2:$CM$18963) -> 423.67134 | AP289: =_xlfn.XLOOKUP(C289,[2]generation_steps!$C$2:$C$18963,[2]generation_steps!$CN$2:$CN$18963) -> 1.5
... A309: 45709 | B309: MERLIN PROPERTIES | C309: ES0105025003 | D309: XMAD | E309: =_xlfn.XLOOKUP(C309,[2]generation_steps!$I$2:$I$500,[2]generation_steps!$L$2:$L$500) -> 0.00033646639 | F309: =_xlfn.XLOOKUP(C309,[2]full_dataframe_final!$C$2:$C$101,[2]full_dataframe_final!$H$2:$H$101,"") -> 0.0025274144 | G309: 35102000 | H309: =ISBLANK('Full Universe'!BE301) -> TRUE | I309: =ISBLANK('Full Universe'!BF301) -> TRUE | J309: =ISBLANK('Full Universe'!BG301) -> TRUE | K309: =ISBLANK('Full Universe'!BH301) -> TRUE | L309: =ISBLANK('Full Universe'!BI301) -> TRUE | M309: =ISBLANK('Full Universe'!BJ301) -> TRUE | N309: =ISBLANK('Full Universe'!BK301) -> TRUE | O309: =ISBLANK('Full Universe'!BL301) -> TRUE | ... AJ309: =ISBLANK('Full Universe'!CG301) -> TRUE | AK309: =ISNUMBER(MATCH(C309,[1]Europe!$B$2:$B$15,0)) -> FALSE | AL309: =ISBLANK('Full Universe'!CJ301) -> TRUE | AM309: 2.2425034 | AN309: =ISNUMBER(MATCH(C309,'Selected Companies'!$D$2:$D$101,0)) -> TRUE | AO309: =_xlfn.XLOOKUP(C309,[2]generation_steps!$C$2:$C$18963,[2]generation_steps!$CM$2:$CM$18963) -> 16.106227 | AP309: =_xlfn.XLOOKUP(C309,[2]generation_steps!$C$2:$C$18963,[2]generation_steps!$CN$2:$CN$18963) -> 1.4
A310: 45709 | B310: MICHELIN | C310: FR001400AJ45 | D310: XPAR | E310: =_xlfn.XLOOKUP(C310,[2]generation_steps!$I$2:$I$500,[2]generation_steps!$L$2:$L$500) -> 0.0020846832 | F310: =_xlfn.XLOOKUP(C310,[2]full_dataframe_final!$C$2:$C$101,[2]full_dataframe_final!$H$2:$H$101,"") | G310: 40101015 | H310: =ISBLANK('Full Universe'!BE303) -> TRUE | I310: =ISBLANK('Full Universe'!BF303) -> TRUE | J310: =ISBLANK('Full Universe'!BG303) -> TRUE | K310: =ISBLANK('Full Universe'!BH303) -> TRUE | L310: =ISBLANK('Full Universe'!BI303) -> TRUE | M310: =ISBLANK('Full Universe'!BJ303) -> TRUE | N310: =ISBLANK('Full Universe'!BK303) -> TRUE | O310: =ISBLANK('Full Universe'!BL303) -> TRUE | ... AJ310: =ISBLANK('Full Universe'!CG303) -> TRUE | AK310: =ISNUMBER(MATCH(C310,[1]Europe!$B$2:$B$15,0)) -> FALSE | AL310: =ISBLANK('Full Universe'!CJ303) -> TRUE | AM310: 1.4395075 | AN310: =ISNUMBER(MATCH(C310,'Selected Companies'!$D$2:$D$101,0)) -> FALSE | AO310: =_xlfn.XLOOKUP(C310,[2]generation_steps!$C$2:$C$18963,[2]generation_steps!$CM$2:$CM$18963) -> 4924.2021 | AP310: =_xlfn.XLOOKUP(C310,[2]generation_steps!$C$2:$C$18963,[2]generation_steps!$CN$2:$CN$18963) -> 1.5
A311: 45709 | B311: MONCLER | C311: IT0004965148 | D311: MTAA | E311: =_xlfn.XLOOKUP(C311,[2]generation_steps!$I$2:$I$500,[2]generation_steps!$L$2:$L$500) -> 0.0012354599 | F311: =_xlfn.XLOOKUP(C311,[2]full_dataframe_final!$C$2:$C$101,[2]full_dataframe_final!$H$2:$H$101,"") | G311: 40204020 | H311: =ISBLANK('Full Universe'!BE304) -> TRUE | I311: =ISBLANK('Full Universe'!BF304) -> TRUE | J311: =ISBLANK('Full Universe'!BG304) -> TRUE | K311: =ISBLANK('Full Universe'!BH304) -> TRUE | L311: =ISBLANK('Full Universe'!BI304) -> TRUE | M311: =ISBLANK('Full Universe'!BJ304) -> TRUE | N311: =ISBLANK('Full Universe'!BK304) -> TRUE | O311: =ISBLANK('Full Universe'!BL304) -> TRUE | ... AJ311: =ISBLANK('Full Universe'!CG304) -> TRUE | AK311: =ISNUMBER(MATCH(C311,[1]Europe!$B$2:$B$15,0)) -> FALSE | AL311: =ISBLANK('Full Universe'!CJ304) -> TRUE | AM311: 2.1234782 | AN311: =ISNUMBER(MATCH(C311,'Selected Companies'!$D$2:$D$101,0)) -> FALSE | AO311: =_xlfn.XLOOKUP(C311,[2]generation_steps!$C$2:$C$18963,[2]generation_steps!$CM$2:$CM$18963) -> 15.28079 | AP311: =_xlfn.XLOOKUP(C311,[2]generation_steps!$C$2:$C$18963,[2]generation_steps!$CN$2:$CN$18963) -> 1.5666667
A312: 45709 | B312: MONDI PLC | C312: GB00BMWC6P49 | D312: XLON | E312: =_xlfn.XLOOKUP(C312,[2]generation_steps!$I$2:$I$500,[2]generation_steps!$L$2:$L$500) -> 0.00055449629 | F312: =_xlfn.XLOOKUP(C312,[2]full_dataframe_final!$C$2:$C$101,[2]full_dataframe_final!$H$2:$H$101,"") -> 0.0041651766 | G312: 50203030 | H312: =ISBLANK('Full Universe'!BE305) -> TRUE | I312: =ISBLANK('Full Universe'!BF305) -> TRUE | J312: =ISBLANK('Full Universe'!BG305) -> TRUE | K312: =ISBLANK('Full Universe'!BH305) -> TRUE | L312: =ISBLANK('Full Universe'!BI305) -> TRUE | M312: =ISBLANK('Full Universe'!BJ305) -> TRUE | N312: =ISBLANK('Full Universe'!BK305) -> TRUE | O312: =ISBLANK('Full Universe'!BL305) -> TRUE | ... AJ312: =ISBLANK('Full Universe'!CG305) -> TRUE | AK312: =ISNUMBER(MATCH(C312,[1]Europe!$B$2:$B$15,0)) -> FALSE | AL312: =ISBLANK('Full Universe'!CJ305) -> TRUE | AM312: 1.2669201 | AN312: =ISNUMBER(MATCH(C312,'Selected Companies'!$D$2:$D$101,0)) -> TRUE | AO312: =_xlfn.XLOOKUP(C312,[2]generation_steps!$C$2:$C$18963,[2]generation_steps!$CM$2:$CM$18963) -> 449.49863 | AP312: =_xlfn.XLOOKUP(C312,[2]generation_steps!$C$2:$C$18963,[2]generation_steps!$CN$2:$CN$18963) -> 1.6
A313: 45709 | B313: MOWI | C313: NO0003054108 | D313: XOSL | E313: =_xlfn.XLOOKUP(C313,[2]generation_steps!$I$2:$I$500,[2]generation_steps!$L$2:$L$500) -> 0.00066800809 | F313: =_xlfn.XLOOKUP(C313,[2]full_dataframe_final!$C$2:$C$101,[2]full_dataframe_final!$H$2:$H$101,"") | G313: 45102010 | H313: =ISBLANK('Full Universe'!BE306) -> TRUE | I313: =ISBLANK('Full Universe'!BF306) -> TRUE | J313: =ISBLANK('Full Universe'!BG306) -> TRUE | K313: =ISBLANK('Full Universe'!BH306) -> TRUE | L313: =ISBLANK('Full Universe'!BI306) -> TRUE | M313: =ISBLANK('Full Universe'!BJ306) -> TRUE | N313: =ISBLANK('Full Universe'!BK306) -> TRUE | O313: =ISBLANK('Full Universe'!BL306) -> TRUE | ... AJ313: =ISBLANK('Full Universe'!CG306) -> TRUE | AK313: =ISNUMBER(MATCH(C313,[1]Europe!$B$2:$B$15,0)) -> FALSE | AL313: =ISBLANK('Full Universe'!CJ306) -> TRUE | AM313: 2.221561 | AN313: =ISNUMBER(MATCH(C313,'Selected Companies'!$D$2:$D$101,0)) -> FALSE | AO313: =_xlfn.XLOOKUP(C313,[2]generation_steps!$C$2:$C$18963,[2]generation_steps!$CM$2:$CM$18963) -> 218.88726 | AP313: =_xlfn.XLOOKUP(C313,[2]generation_steps!$C$2:$C$18963,[2]generation_steps!$CN$2:$CN$18963) -> 1.5
A314: 45709 | B314: MTU AERO ENGINES AG | C314: DE000A0D9PT0 | D314: XETR | E314: =_xlfn.XLOOKUP(C314,[2]generation_steps!$I$2:$I$500,[2]generation_steps!$L$2:$L$500) -> 0.0014385089 | F314: =_xlfn.XLOOKUP(C314,[2]full_dataframe_final!$C$2:$C$101,[2]full_dataframe_final!$H$2:$H$101,"") | G314: 50201010 | H314: =ISBLANK('Full Universe'!BE307) -> TRUE | I314: =ISBLANK('Full Universe'!BF307) -> TRUE | J314: =ISBLANK('Full Universe'!BG307) -> TRUE | K314: =ISBLANK('Full Universe'!BH307) -> FALSE | L314: =ISBLANK('Full Universe'!BI307) -> TRUE | M314: =ISBLANK('Full Universe'!BJ307) -> TRUE | N314: =ISBLANK('Full Universe'!BK307) -> TRUE | O314: =ISBLANK('Full Universe'!BL307) -> TRUE | ... AJ314: =ISBLANK('Full Universe'!CG307) -> TRUE | AK314: =ISNUMBER(MATCH(C314,[1]Europe!$B$2:$B$15,0)) -> FALSE | AL314: =ISBLANK('Full Universe'!CJ307) -> TRUE | AM314: 3.07 | AN314: =ISNUMBER(MATCH(C314,'Selected Companies'!$D$2:$D$101,0)) -> FALSE | AO314: =_xlfn.XLOOKUP(C314,[2]generation_steps!$C$2:$C$18963,[2]generation_steps!$CM$2:$CM$18963) -> 740.68014 | AP314: =_xlfn.XLOOKUP(C314,[2]generation_steps!$C$2:$C$18963,[2]generation_steps!$CN$2:$CN$18963) -> 1.4
A315: 45709 | B315: MUNICH RE | C315: DE0008430026 | D315: XETR | E315: =_xlfn.XLOOKUP(C315,[2]generation_steps!$I$2:$I$500,[2]generation_steps!$L$2:$L$500) -> 0.0076281054 | F315: =_xlfn.XLOOKUP(C315,[2]full_dataframe_final!$C$2:$C$101,[2]full_dataframe_final!$H$2:$H$101,"") | G315: 30302020 | H315: =ISBLANK('Full Universe'!BE308) -> TRUE | I315: =ISBLANK('Full Universe'!BF308) -> TRUE | J315: =ISBLANK('Full Universe'!BG308) -> TRUE | K315: =ISBLANK('Full Universe'!BH308) -> TRUE | L315: =ISBLANK('Full Universe'!BI308) -> TRUE | M315: =ISBLANK('Full Universe'!BJ308) -> TRUE | N315: =ISBLANK('Full Universe'!BK308) -> TRUE | O315: =ISBLANK('Full Universe'!BL308) -> TRUE | ... AJ315: =ISBLANK('Full Universe'!CG308) -> TRUE | AK315: =ISNUMBER(MATCH(C315,[1]Europe!$B$2:$B$15,0)) -> FALSE | AL315: =ISBLANK('Full Universe'!CJ308) -> TRUE | AM315: 3.55 | AN315: =ISNUMBER(MATCH(C315,'Selected Companies'!$D$2:$D$101,0)) -> FALSE | AO315: =_xlfn.XLOOKUP(C315,[2]generation_steps!$C$2:$C$18963,[2]generation_steps!$CM$2:$CM$18963) -> 54.849821 | AP315: =_xlfn.XLOOKUP(C315,[2]generation_steps!$C$2:$C$18963,[2]generation_steps!$CN$2:$CN$18963) -> 1.5333333
...

Sheet Full Universe
A1: Rank | B1: Ticker | C1: Company | D1: ISIN Code | E1: MIC | F1: Number of Shares | G1: Price (EUR) | H1: Currency | I1: Mcap in EUR | J1: index | K1: VOL_AV_3M | L1: Free Float | M1: FFMC_CO | N1: Close Prc | O1: FX/Index Ccy | P1: FFMC_WD | Q1: Price_WD | R1: Subsector Code | S1: Supersector Code | T1: itr_scope123_target | U1: itr_scope12_trend | V1: CDP_climate_score | W1: NBR Overall Flag | X1: Tobacco - Production Maximum Percentage of Revenues (%) | Y1: Tobacco - Distribution Maximum Percentage of Revenues (%) | Z1: Biological Weapons - Overall Flag | AA1: Chemical Weapons - Overall Flag | AB1: Nuclear Weapons Outside NPT - Overall Flag | AC1: Nuclear Weapons Inside NPT - Overall Flag | AD1: Cluster Munitions - Overall Flag | AE1: Depleted Uranium - Overall Flag | AF1: Anti-personnel Mines - Overall Flag | AG1: coal_mining_and_power_gen_maximum_percentage_of_revenues-values | AH1: Fossil Fuel - Total Maximum Percentage of Revenues (%) | AI1: power_generation_thermal_maximum_percentage_of_revenues-values | AJ1: shale_oil_and_or_gas_involvement_tie | AK1: arctic_drilling_share_max-values | AL1: deepwater_drilling_involvement | AM1: HydraulicFracturingInvolvement | AN1: CoalMiningExpInvolved | AO1: OilGasExtractExpInvolved | AP1: OtherFFInfraInvolved | AQ1: NuclearPowerInvolvement | AR1: NuclearPowerRevShareMax-values | AS1: NuclearPowerUraniumRevShareMax-values | AT1: CivFARevShareMax-values | AU1: MilitaryEqmtDistMaxRev-values | AV1: Social Rating (Num) | AW1: Governance Rating (Num) | AX1: NACE | AY1: High_Climate_Impact | AZ1: EU_Taxonomy | BA1: Country_Code | BB1: GAFI_Black_List | BC1: GAFI_Grey_List | BD1: Non_Fiscally_Cooperative | BE1: exclude_gafi_black | BF1: exclude_gafi_grey | BG1: exclude_non_fiscal_coop | BH1: exclude_subsector | BI1: exclude_nbr_red | BJ1: exclude_tobacco_prod | BK1: exclude_tobacco_dist | BL1: exclude_biological_weapons | BM1: exclude_chemical_weapons | BN1: exclude_nuclear_weapons_inside_npt | BO1: exclude_nuclear_weapons_outside_npt | BP1: exclude_cluster_munitions | BQ1: exclude_depleted_uranium | BR1: exclude_anti_personnel_mines | BS1: exclude_coal_mining | BT1: exclude_fossil_fuel | BU1: exclude_thermal_power | BV1: exclude_shale_oil_gas | BW1: exclude_arctic_drilling | BX1: exclude_deepwater_drilling | BY1: exclude_hydraulic_fracturing | BZ1: exclude_coal_mining_expansion | CA1: exclude_oil_gas_extraction_expansion | CB1: exclude_other_fossil_fuel_infra | CC1: exclude_nuclear_power | CD1: exclude_nuclear_power_revenue | CE1: exclude_nuclear_uranium | CF1: exclude_civilian_firearms | CG1: exclude_military_equipment | CH1: 29. EU Taxonomy pocket | CI1: SG_Score | CJ1: exclude_sg_bottom_10 | CK1: Excluded | CL1: Exclusion_Reason | CM1: itr_scope123_target_filled | CN1: itr_scope12_trend_filled | CO1: cdp_temperature_score | CP1: bonus_malus | CQ1: climate_score
A2: 1 | B2: III-GB | C2: 3I GROUP PLC | D2: GB00B1YW4409 | E2: XLON | F2: 973396500 | G2: 49.60294 | H2: GBX | I2: 4.8283328e+10 | J2: EU500 | K2: 39423545 | L2: 1 | M2: 4.8283328e+10 | N2: 4130 | O2: 0.01169249 | P2: 4.7005301e+10 | Q2: 48.289984 | R2: 30202010 | S2: 3020 | T2: 1.994079 | U2: 1.5 | V2: D | W2: Green | X2: 0 | Y2: 0 | Z2: Green | AA2: Green | AB2: Green | AC2: Green | AD2: Green | AE2: Green | AF2: Green | AH2: 0.05 | AK2: 0 | AL2: F | AN2: F | AO2: F | AP2: F | AR2: 0 | AS2: 0 | AT2: 0 | AU2: 0 | AV2: 2.406 | AW2: 3.006 | AX2: K | AY2: 0 | AZ2: 0 | BA2: GB | BB2: 0 | BC2: 0 | BD2: 0 | BT2: exclude_fossil_fuel | CH2: =ISNUMBER(MATCH(D2,[1]Europe!$B$2:$B$15,0)) -> FALSE | CI2: 2.706 | CK2: Yes | CL2: exclude_fossil_fuel | CM2: 1.994079 | CN2: 1.5 | CO2: 1.7470395 | CP2: 0.18 | CQ2: 1.9270395
A3: 5 | B3: A2A-IT | C3: A2A | D3: IT0001233417 | E3: MTAA | F3: 3132905277 | G3: 2.145 | H3: EUR | I3: 6.7200818e+09 | J3: EU500;EZ300 | K3: 19527443 | L3: 0.5 | M3: 3.3600409e+09 | N3: 2.08 | O3: 1 | P3: 3.2582215e+09 | Q3: 2.08 | R3: 65101015 | S3: 6510 | T3: 2 | U3: 2.93 | V3: A- | W3: Green | X3: 0 | Y3: 0 | Z3: Green | AA3: Green | AB3: Green | AC3: Green | AD3: Green | AE3: Green | AF3: Green | AG3: 0.0029 | AH3: 0.369 | AI3: 0.0893 | AK3: 0 | AL3: F | AN3: F | AO3: F | AP3: T | AR3: 0 | AS3: 0 | AT3: 0 | AU3: 0 | AV3: 2.448 | AW3: 2.942 | AX3: D | AY3: 1 | AZ3: 0 | BA3: IT | BB3: 0 | BC3: 0 | BD3: 0 | BS3: exclude_coal_mining | BT3: exclude_fossil_fuel | BU3: exclude_thermal_power | CB3: exclude_other_fossil_fuel_infra | CH3: =ISNUMBER(MATCH(D3,[1]Europe!$B$2:$B$15,0)) -> FALSE | CI3: 2.695 | CK3: Yes | CL3: exclude_coal_mining; exclude_fossil_fuel; exclude_thermal_power; exclude_other_fossil_fuel_infra | CM3: 2 | CN3: 2.93 | CO3: 2.465 | CP3: -0.24 | CQ3: 2.225
A4: 7 | B4: AAK-SE | C4: AAK AB | D4: SE0011337708 | E4: XSTO | F4: 259559200 | G4: 27.4255 | H4: SEK | I4: 7.1185408e+09 | J4: EU500 | K4: 10069959 | L4: 0.7 | M4: 4.9829786e+09 | N4: 273.2 | O4: 0.08996851 | P4: 4.465866e+09 | Q4: 24.579397 | R4: 45102020 | S4: 4510 | T4: 1.9643056 | V4: C | W4: Green | X4: 0 | Y4: 0 | Z4: Green | AA4: Green | AB4: Green | AC4: Green | AD4: Green | AE4: Green | AF4: Green | AG4: 0 | AH4: 0 | AI4: 0 | AK4: 0 | AL4: F | AN4: F | AO4: F | AP4: F | AR4: 0 | AS4: 0 | AT4: 0 | AU4: 0 | AV4: 2.42 | AW4: 3.154 | AX4: C | AY4: 1 | AZ4: 0 | BA4: SE | BB4: 0 | BC4: 0 | BD4: 0 | CH4: =ISNUMBER(MATCH(D4,[1]Europe!$B$2:$B$15,0)) -> FALSE | CI4: 2.787 | CK4: No | CM4: 1.9643056 | CN4: 3.1 | CO4: 2.5321528 | CP4: 0 | CQ4: 2.5321528
A5: 8 | B5: AALB-NL | C5: AALBERTS NV | D5: NL0000852564 | E5: XAMS | F5: 110580102 | G5: 36.3 | H5: EUR | I5: 4.0140577e+09 | J5: EU500;EZ300 | K5: 4806266.6 | L5: 0.9 | M5: 3.6126519e+09 | N5: 27.22 | O5: 1 | P5: 2.7089913e+09 | Q5: 27.22 | R5: 50202020 | S5: 5020 | V5: C | W5: Green | X5: 0 | Y5: 0 | Z5: Green | AA5: Green | AB5: Green | AC5: Green | AD5: Green | AE5: Green | AF5: Green | AG5: 0 | AH5: 0.1 | AI5: 0 | AK5: 0 | AL5: F | AN5: F | AO5: F | AP5: F | AQ5: Services | AR5: 0.01 | AS5: 0 | AT5: 0 | AU5: 0 | AV5: 1.998 | AW5: 3.25 | AX5: C | AY5: 1 | AZ5: 0 | BA5: NL | BB5: 0 | BC5: 0 | BD5: 0 | BT5: exclude_fossil_fuel | CC5: exclude_nuclear_power | CH5: =ISNUMBER(MATCH(D5,[1]Europe!$B$2:$B$15,0)) -> FALSE | CI5: 2.624 | CK5: Yes | CL5: exclude_fossil_fuel; exclude_nuclear_power | CM5: 3.4 | CN5: 3.1 | CO5: 3.25 | CP5: 0 | CQ5: 3.25
A6: 9 | B6: ABI-BE | C6: AB INBEV | D6: BE0974293251 | E6: XBRU | F6: 1797198523 | G6: 51.62 | H6: EUR | I6: 9.2771388e+10 | J6: EU500;EZ300 | K6: 98018859 | L6: 0.55 | M6: 5.1024263e+10 | N6: 56.06 | O6: 1 | P6: 5.5413022e+10 | Q6: 56.06 | R6: 45101010 | S6: 4510 | T6: 2.101079 | U6: 2.7 | V6: Score not available | W6: Amber | X6: 0 | Y6: 0 | Z6: Green | AA6: Green | AB6: Green | AC6: Green | AD6: Green | AE6: Green | AF6: Green | AG6: 0 | AH6: 0 | AI6: 0 | AK6: 0 | AL6: F | AN6: F | AO6: F | AP6: F | AR6: 0 | AS6: 0 | AT6: 0 | AU6: 0 | AV6: 1.867 | AW6: 2.352 | AX6: C | AY6: 1 | AZ6: 0 | BA6: BE | BB6: 0 | BC6: 0 | BD6: 0 | CH6: =ISNUMBER(MATCH(D6,[1]Europe!$B$2:$B$15,0)) -> FALSE | CI6: 2.1095 | CJ6: exclude_sg_bottom_10 | CK6: Yes | CL6: exclude_sg_bottom_10 | CM6: 2.101079 | CN6: 2.7 | CO6: 2.4005395 | CP6: 0.3 | CQ6: 2.7005395
A7: 10 | B7: SAGA.B-SE | C7: AB SAGAX CLASS B | D7: SE0005127818 | E7: XSTO | F7: 313943020 | G7: 19.72838 | H7: SEK | I7: 6.1935872e+09 | J7: EU500 | K7: 7671301.9 | L7: 0.7 | M7: 4.335511e+09 | N7: 210.4 | O7: 0.08996851 | P7: 4.1599215e+09 | Q7: 18.929375 | R7: 35101010 | S7: 3510 | T7: 3.2721025 | V7: F | W7: Green | X7: 0 | Y7: 0 | Z7: Green | AA7: Green | AB7: Green | AC7: Green | AD7: Green | AE7: Green | AF7: Green | AG7: 0 | AH7: 0 | AI7: 0 | AK7: 0 | AL7: F | AN7: F | AO7: F | AP7: F | AR7: 0 | AS7: 0 | AT7: 0 | AU7: 0 | AV7: 1.961 | AW7: 2.119 | AX7: L | AY7: 1 | AZ7: 0 | BA7: SE | BB7: 0 | BC7: 0 | BD7: 0 | CH7: =ISNUMBER(MATCH(D7,[1]Europe!$B$2:$B$15,0)) -> FALSE | CI7: 2.04 | CJ7: exclude_sg_bottom_10 | CK7: Yes | CL7: exclude_sg_bottom_10 | CM7: 3.2721025 | CN7: 3.1 | CO7: 3.1860513 | CP7: 0.3 | CQ7: 3.4860513
A8: 11 | B8: ABBN-CH | C8: ABB LTD | D8: CH0012221716 | E8: XSWX | F8: 1860614900 | G8: 55.5674 | H8: CHF | I8: 1.0338953e+11 | J8: EU500 | K8: 1.4023889e+08 | L8: 0.85 | M8: 8.7881103e+10 | N8: 41.77 | O8: 1.079797 | P8: 7.1331608e+10 | Q8: 45.103121 | R8: 50202010 | S8: 5020 | T8: 1.7491009 | U8: 1.5 | V8: A | W8: Amber | X8: 0 | Y8: 0 | Z8: Green | AA8: Green | AB8: Green | AC8: Green | AD8: Green | AE8: Green | AF8: Green | AG8: 0.01 | AH8: 0.15 | AI8: 0 | AK8: 0 | AL8: T | AN8: F | AO8: F | AP8: F | AQ8: Services | AR8: 0.04 | AS8: 0 | AT8: 0 | AU8: 0 | AV8: 2.887 | AW8: 2.502 | AX8: C | AY8: 1 | AZ8: 0 | BA8: CH | BB8: 0 | BC8: 0 | BD8: 0 | BS8: exclude_coal_mining | BT8: exclude_fossil_fuel | BX8: exclude_deepwater_drilling | CC8: exclude_nuclear_power | CH8: =ISNUMBER(MATCH(D8,[1]Europe!$B$2:$B$15,0)) -> FALSE | CI8: 2.6945 | CK8: Yes | CL8: exclude_coal_mining; exclude_fossil_fuel; exclude_deepwater_drilling; exclude_nuclear_power | CM8: 1.7491009 | CN8: 1.5 | CO8: 1.6245504 | CP8: -0.3 | CQ8: 1.3245504
A9: 14 | B9: ABN-NL | C9: ABN AMRO BANK N.V. | D9: NL0011540547 | E9: XAMS | F9: 539163896 | G9: 17.8 | H9: EUR | I9: 9.5971173e+09 | J9: EU500;EZ300 | K9: 48401045 | L9: 1 | M9: 9.5971173e+09 | N9: 18.165 | O9: 1 | P9: 9.7939122e+09 | Q9: 18.165 | R9: 30101010 | S9: 3010 | T9: 3.2733333 | V9: C | W9: Green | X9: 0 | Y9: 0 | Z9: Green | AA9: Green | AB9: Green | AC9: Green | AD9: Green | AE9: Green | AF9: Green | AG9: 0 | AH9: 0 | AI9: 0 | AK9: 0 | AL9: F | AN9: F | AO9: F | AP9: F | AR9: 0 | AS9: 0 | AT9: 0 | AU9: 0 | AV9: 2.394 | AW9: 2.779 | AX9: K | AY9: 0 | AZ9: 0 | BA9: NL | BB9: 0 | BC9: 0 | BD9: 0 | CH9: =ISNUMBER(MATCH(D9,[1]Europe!$B$2:$B$15,0)) -> FALSE | CI9: 2.5865 | CK9: No | CM9: 3.2733333 | CN9: 3.1 | CO9: 3.1866667 | CP9: 0 | CQ9: 3.1866667
A10: 15 | B10: ABDN-GB | C10: ABRDN | D10: GB00BF8Q6K64 | E10: XLON | F10: 1840742800 | G10: 1.908317 | H10: GBX | I10: 3.5127208e+09 | J10: EU500 | K10: 5431165.1 | L10: 1 | M10: 3.5127208e+09 | N10: 143.1 | O10: 0.01169249 | P10: 3.0799222e+09 | Q10: 1.6731953 | R10: 30202010 | S10: 3020 | T10: 3.02 | V10: C | W10: Green | X10: 0 | Y10: 0 | Z10: Green | AA10: Green | AB10: Green | AC10: Green | AD10: Green | AE10: Green | AF10: Green | AG10: 0 | AH10: 0 | AI10: 0 | AK10: 0 | AL10: F | AN10: F | AO10: F | AP10: F | AR10: 0 | AS10: 0 | AT10: 0 | AU10: 0 | AV10: 2.139 | AW10: 3.161 | AX10: K | AY10: 0 | AZ10: 0 | BA10: GB | BB10: 0 | BC10: 0 | BD10: 0 | CH10: =ISNUMBER(MATCH(D10,[1]Europe!$B$2:$B$15,0)) -> FALSE | CI10: 2.65 | CK10: No | CM10: 3.02 | CN10: 3.1 | CO10: 3.06 | CP10: 0 | CQ10: 3.06
A11: 16 | B11: ACLN-CH | C11: ACCELLERON INDUSTR. | D11: CH1169360919 | E11: XSWX | F11: 94500000 | G11: 45.65756 | H11: CHF | I11: 4314639420 | J11: EU500 | K11: 10718443 | L11: 1 | M11: 4314639420 | N11: 41.14 | O11: 1.079797 | P11: 4.1979592e+09 | Q11: 44.422849 | R11: 50204030 | S11: 5020 | V11: F | W11: Green | X11: 0 | Y11: 0 | Z11: Green | AA11: Green | AB11: Green | AC11: Green | AD11: Green | AE11: Green | AF11: Green | AG11: 0 | AH11: 0.43 | AI11: 0 | AK11: 0 | AL11: F | AN11: F | AO11: F | AP11: F | AR11: 0 | AS11: 0 | AT11: 0 | AU11: 0 | AV11: 2.402 | AW11: 3.187 | AX11: C | AY11: 1 | AZ11: 0 | BA11: CH | BB11: 0 | BC11: 0 | BD11: 0 | BT11: exclude_fossil_fuel | CH11: =ISNUMBER(MATCH(D11,[1]Europe!$B$2:$B$15,0)) -> FALSE | CI11: 2.7945 | CK11: Yes | CL11: exclude_fossil_fuel | CM11: 3.4 | CN11: 3.1 | CO11: 3.25 | CP11: 0.3 | CQ11: 3.55
A12: 19 | B12: AC-FR | C12: ACCOR | D12: FR0000120404 | E12: XPAR | F12: 243667720 | G12: 46.43 | H12: EUR | I12: 1.1313492e+10 | J12: EU500;EZ300 | K12: 26555203 | L12: 0.85 | M12: 9.6164684e+09 | N12: 39.28 | O12: 1 | P12: 8.1355778e+09 | Q12: 39.28 | R12: 40501025 | S12: 4050 | T12: 1.7728124 | U12: 3.01 | V12: C | W12: Green | X12: 0 | Y12: 0.01 | Z12: Green | AA12: Green | AB12: Green | AC12: Green | AD12: Green | AE12: Green | AF12: Green | AG12: 0 | AH12: 0 | AI12: 0 | AK12: 0 | AL12: F | AN12: F | AO12: F | AP12: F | AR12: 0 | AS12: 0 | AT12: 0 | AU12: 0 | AV12: 2.754 | AW12: 3.017 | AX12: I | AY12: 0 | AZ12: 0 | BA12: FR | BB12: 0 | BC12: 0 | BD12: 0 | CH12: =ISNUMBER(MATCH(D12,[1]Europe!$B$2:$B$15,0)) -> FALSE | CI12: 2.8855 | CK12: No | CM12: 1.7728124 | CN12: 3.01 | CO12: 2.3914062 | CP12: 0 | CQ12: 2.3914062
A13: 20 | B13: ACKB-BE | C13: ACKERMANS V.HAAREN | D13: BE0003764785 | E13: XBRU | F13: 33157750 | G13: 195.8 | H13: EUR | I13: 6492287450 | J13: EU500;EZ300 | K13: 4586713 | L13: 0.65 | M13: 4.2199868e+09 | N13: 199.3 | O13: 1 | P13: 4.2954207e+09 | Q13: 199.3 | R13: 30202000 | S13: 3020 | T13: 3.4 | V13: B | W13: Green | X13: 0 | Y13: 0 | Z13: Green | AA13: Green | AB13: Green | AC13: Green | AD13: Green | AE13: Green | AF13: Green | AG13: 0 | AH13: 0.5 | AI13: 0 | AK13: 0 | AL13: F | AN13: F | AO13: F | AP13: F | AR13: 0 | AS13: 0 | AT13: 0 | AU13: 0 | AV13: 1.791 | AW13: 1.939 | AX13: F | AY13: 1 | AZ13: 0 | BA13: BE | BB13: 0 | BC13: 0 | BD13: 0 | BT13: exclude_fossil_fuel | CH13: =ISNUMBER(MATCH(D13,[1]Europe!$B$2:$B$15,0)) -> FALSE | CI13: 1.865 | CJ13: exclude_sg_bottom_10 | CK13: Yes | CL13: exclude_fossil_fuel; exclude_sg_bottom_10 | CM13: 3.4 | CN13: 3.1 | CO13: 3.25 | CP13: -0.18 | CQ13: 3.07
A14: 21 | B14: ACS-ES | C14: ACS ACTIVIDADES CONS | D14: ES0167050915 | E14: XMAD | F14: 271664580 | G14: 51.55 | H14: EUR | I14: 14004309099 | J14: EU500;EZ300 | K14: 17744730 | L14: 0.85 | M14: 1.1903663e+10 | N14: 51.35 | O14: 1 | P14: 1.185748e+10 | Q14: 51.35 | R14: 50101010 | S14: 5010 | T14: 3.3115124 | V14: B | W14: Amber | X14: 0 | Y14: 0 | Z14: Green | AA14: Green | AB14: Green | AC14: Green | AD14: Green | AE14: Green | AF14: Green | AH14: 0.05 | AK14: 0 | AL14: F | AN14: F | AO14: F | AP14: F | AQ14: Services | AR14: 0.01 | AS14: 0 | AT14: 0 | AU14: 0 | AV14: 2.375 | AW14: 2.777 | AX14: F | AY14: 1 | AZ14: 0 | BA14: ES | BB14: 0 | BC14: 0 | BD14: 0 | BT14: exclude_fossil_fuel | CC14: exclude_nuclear_power | CH14: =ISNUMBER(MATCH(D14,[1]Europe!$B$2:$B$15,0)) -> FALSE | CI14: 2.576 | CK14: Yes | CL14: exclude_fossil_fuel; exclude_nuclear_power | CM14: 3.3115124 | CN14: 3.1 | CO14: 3.2057562 | CP14: -0.18 | CQ14: 3.0257562
A15: 22 | B15: ADDT.B-SE | C15: ADDTECH AB CLASS B | D15: SE0014781795 | E15: XSTO | F15: 259908230 | G15: 30.30293 | H15: SEK | I15: 7.8759809e+09 | J15: EU500 | K15: 8983765.4 | L15: 1 | M15: 7.8759809e+09 | N15: 304 | O15: 0.08996851 | P15: 7.1086011e+09 | Q15: 27.350427 | R15: 50202010 | S15: 5020 | T15: 1.7347787 | V15: Score not available | W15: Green | X15: 0 | Y15: 0 | Z15: Green | AA15: Green | AB15: Green | AC15: Green | AD15: Green | AE15: Green | AF15: Green | AG15: 0 | AH15: 0 | AI15: 0 | AK15: 0 | AL15: F | AN15: F | AO15: F | AP15: F | AR15: 0 | AS15: 0 | AT15: 0 | AU15: 0.05 | AV15: 1.814 | AW15: 2.231 | AX15: G | AY15: 1 | AZ15: 0 | BA15: SE | BB15: 0 | BC15: 0 | BD15: 0 | CG15: exclude_military_equipment | CH15: =ISNUMBER(MATCH(D15,[1]Europe!$B$2:$B$15,0)) -> FALSE | CI15: 2.0225 | CJ15: exclude_sg_bottom_10 | CK15: Yes | CL15: exclude_military_equipment; exclude_sg_bottom_10 | CM15: 1.7347787 | CN15: 3.1 | CO15: 2.4173893 | CP15: 0.3 | CQ15: 2.7173893
A16: 23 | B16: ADEN-CH | C16: ADECCO GROUP AG | D16: CH0012138605 | E16: XSWX | F16: 168426560 | G16: 24.5832 | H16: CHF | I16: 4.1404638e+09 | J16: EU500 | K16: 25898272 | L16: 0.85 | M16: 3.5193942e+09 | N16: 22.24 | O16: 1.079797 | P16: 3.4380042e+09 | Q16: 24.014685 | R16: 50205025 | S16: 5020 | T16: 1.7457422 | U16: 1.77 | V16: A- | W16: Green | X16: 0 | Y16: 0 | Z16: Green | AA16: Green | AB16: Green | AC16: RED | AD16: Green | AE16: Green | AF16: Green | AG16: 0 | AH16: 0.01 | AI16: 0 | AK16: 0 | AL16: F | AN16: F | AO16: F | AP16: F | AQ16: Services | AR16: 0.01 | AS16: 0 | AT16: 0 | AU16: 0 | AV16: 2.279 | AW16: 3.307 | AX16: N | AY16: 0 | AZ16: 0 | BA16: CH | BB16: 0 | BC16: 0 | BD16: 0 | BN16: exclude_nuclear_weapons_inside_npt | BT16: exclude_fossil_fuel | CC16: exclude_nuclear_power | CH16: =ISNUMBER(MATCH(D16,[1]Europe!$B$2:$B$15,0)) -> FALSE | CI16: 2.793 | CK16: Yes | CL16: exclude_nuclear_weapons_inside_npt; exclude_fossil_fuel; exclude_nuclear_power | CM16: 1.7457422 | CN16: 1.77 | CO16: 1.7578711 | CP16: -0.24 | CQ16: 1.5178711
A17: 24 | B17: ADS-DE | C17: ADIDAS AG | D17: DE000A1EWWW0 | E17: XETR | F17: 180000000 | G17: 245.9 | H17: EUR | I17: 44262000000 | J17: EU500;EZ300 | K17: 95465481 | L17: 1 | M17: 44262000000 | N17: 198.2 | O17: 1 | P17: 35676000000 | Q17: 198.2 | R17: 40204025 | S17: 4020 | T17: 1.7444715 | V17: A | W17: Green | X17: 0 | Y17: 0 | Z17: Green | AA17: Green | AB17: Green | AC17: Green | AD17: Green | AE17: Green | AF17: Green | AG17: 0 | AH17: 0 | AI17: 0 | AK17: 0 | AL17: F | AN17: F | AO17: F | AP17: F | AR17: 0 | AS17: 0 | AT17: 0 | AU17: 0 | AV17: 2.352 | AW17: 2.749 | AX17: C | AY17: 1 | AZ17: 0 | BA17: DE | BB17: 0 | BC17: 0 | BD17: 0 | CH17: =ISNUMBER(MATCH(D17,[1]Europe!$B$2:$B$15,0)) -> FALSE | CI17: 2.5505 | CK17: No | CM17: 1.7444715 | CN17: 3.1 | CO17: 2.4222358 | CP17: -0.3 | CQ17: 2.1222358
A18: 25 | B18: ADM-GB | C18: ADMIRAL GROUP PLC | D18: GB00B02J6398 | E18: XLON | F18: 306304700 | G18: 33.85041 | H18: GBX | I18: 1.036854e+10 | J18: EU500 | K18: 10015140 | L18: 0.7 | M18: 7.2579778e+09 | N18: 3180 | O18: 0.01169249 | P18: 7.9723403e+09 | Q18: 37.182118 | R18: 30302025 | S18: 3030 | T18: 1.998809 | U18: 2.7 | V18: C | W18: Green | X18: 0 | Y18: 0 | Z18: Green | AA18: Green | AB18: Green | AC18: Green | AD18: Green | AE18: Green | AF18: Green | AG18: 0 | AH18: 0 | AI18: 0 | AK18: 0 | AL18: F | AN18: F | AO18: F | AP18: F | AR18: 0 | AS18: 0 | AT18: 0 | AU18: 0 | AV18: 1.88 | AW18: 2.7 | AX18: K | AY18: 0 | AZ18: 0 | BA18: GB | BB18: 0 | BC18: 0 | BD18: 0 | CH18: =ISNUMBER(MATCH(D18,[1]Europe!$B$2:$B$15,0)) -> FALSE | CI18: 2.29 | CK18: No | CM18: 1.998809 | CN18: 2.7 | CO18: 2.3494045 | CP18: 0 | CQ18: 2.3494045
