Workbook

Sheet Sheet1
A1: Where to find the details file:
A2: (4) Folder | Dataiku (Automation)
A3: App | Dataiku (Automation)
B4: Mnemo | C4: Name | D4: Universe | E4: Weighting Method | F4: Capping | G4: Data vendor(s) | H4: Method 2 | I4: Review Aligned on June
B5: AEXEW | C5: AEX Equal Weight | D5: AEX | E5: Equal Weight | F5: 0 | G5: 0 | H5: New Sheet | I5: 1
B6: CACEW | C6: CAC 40 Equal Weight | D6: PX1 | E6: Equal Weight | F6: 0 | G6: 0 | H6: New Sheet | I6: 1
B7: CLEW | C7: CAC Large 60 Equal Weight | D7: CACLG | E7: Equal Weight | F7: 0 | G7: 0 | H7: New Sheet | I7: 1
B8: BNEW | C8: Euronext BeNe 40 Equal Weight | D8: AEX;BEL20 | E8: Equal Weight | F8: 0 | G8: 0 | H8: New Sheet | I8: 1
B9: SBF80 | C9: SBF Top 80 EW | D9: PX4 | E9: Equal Weight | F9: 0 | G9: 0 | H9: New Sheet | I9: Lex
B10: EC1EW | C10: Euronext Core Europe 100 EW | D10: Main Markets France, Germany, Netherland, Belgium, Luxembourg | E10: Equal Weight | F10: 0 | G10: 0 | H10: New Sheet | I10: Wait for Amanda/Edwin
B11: COR3P | C11: Euronext Core Europe 30 EW | D11: Main Markets France, Germany, Netherland, Belgium, Luxembourg | E11: Equal Weight | F11: 0 | G11: 0 | H11: New Sheet | I11: Wait for Amanda/Edwin
B12: EZ40P | C12: Euronext Eurozone 40 EW | D12: EZ300 | E12: Equal Weight | F12: 0 | G12: 0 | H12: New Sheet | I12: 1
B13: EFMEP | C13: Euronext Founding Members Europe 50 EW | D13: EZ300 | E13: Equal Weight | F13: 0 | G13: 0 | H13: New Sheet | I13: 1
B14: FGINP | C14: Euronext Top 30 France Germany Industrials EW | D14: CACT | E14: Equal Weight | F14: 0 | G14: 0 | H14: New Sheet
B15: EZ15P | C15: Euronext Eurozone 150 EW | D15: EZ300 | E15: Equal Weight | F15: 0 | G15: 0 | H15: New Sheet | I15: 1
B16: EZN1P | C16: Euronext Eurozone Next 100 EW | D16: EZ300 | E16: Equal Weight | F16: 0 | G16: 0 | H16: New Sheet | I16: 1
B17: FRECP | C17: Euronext France 20-40 Challengers EW | D17: PX1 | E17: Equal Weight | F17: 0 | G17: 0 | H17: New Sheet | I17: 1
B18: FRN4P | C18: Euronext France Next 40 EW | D18: PX4 | E18: Equal Weight | F18: 0 | G18: 0 | H18: New Sheet | I18: 1
B19: FR20P | C19: Euronext France 20 EW | D19: PX1 | E19: Equal Weight | F19: 0 | G19: 0 | H19: New Sheet | I19: 1
B20: EUS5P | C20: Euronext Transatlantic 50 EW | D20: EZ300;NA500 | E20: Equal Weight | F20: 0 | G20: 0 | H20: New Sheet | I20: 1
B21: ERI5P | C21: Euronext Responsible Investment Euro 50 EW | D21: EZ300 | E21: Equal Weight | F21: 0 | G21: 0 | H21: New Sheet | I21: 1
B22: ELUXP | C22: Euronext Europe Luxury | D22: Fixed Basket | E22: Equal Weight | F22: 0 | G22: 0 | H22: New Sheet | I22: 1
B23: ESVEP | C23: Euronext Souveraineté Européenne | D23: Fixed Basket | E23: Equal Weight | F23: 0 | G23: 0 | H23: New Sheet | I23: 1
B24: BE1P | C24: Euronext Banks Eurozone Select 10 EW | D24: EZ300 | E24: Equal Weight | F24: 0 | G24: 0 | H24: New Sheet | I24: 1
B25: EIAPR | C25: EN Intelligence Artificielle PR | D25: DEUPT;EUSPT | E25: Equal Weight | F25: 0 | G25: 0 | H25: New Sheet
B26: GSFBP | C26: EN Germany Selection Fixed Basket PR | D26: Fixed Basket | E26: Equal Weight | F26: 0 | G26: 0 | H26: New Sheet | I26: Practice Index
B27: EDEFP | C27: Euronext Europe Defense Fixed Basket PR | D27: AS500;EU500;NA500;EZ300 | E27: Equal Weight | F27: 0 | G27: 0 | H27: New Sheet | I27: 1
B28: EZ60P | C28: Euronext Eurozone 60 EW | D28: EZ300 | E28: Equal Weight | F28: 0 | G28: 0 | H28: New Sheet | I28: 1
B29: ETPFB | C29: Euronext Transatlantic Pharmaceuticals Selection Fixed Basket | D29: Fixed Basket | E29: Equal Weight | F29: 0 | G29: 0 | H29: 0 | I29: 1
B30: EES2 | C30: Euronext European Sovereignty 20 EW | D30: Fixed Basket | E30: Equal Weight | F30: 0 | G30: 0 | H30: 0 | I30: Practice Index
B31: ETSEP | C31: Euronext Transatlantic Selection Fixed Basket | D31: Fixed Basket | E31: Equal Weight | F31: 0 | G31: 0 | H31: 0 | I31: Practice Index

Sheet To automate
F1: Total Indices | G1: =COUNTA($A$8:$A$300) -> 187
F2: Done | G2: =COUNTIF($F$8:$F$301,"Done") -> 36
F3: To do: | G3: =COUNTIF($F$8:$F$194,"") -> 90
F4: Moodys: | G4: =COUNTIF($F$8:$F$301,"Moodys") -> 38
F5: Other | G5: =COUNTA($A$8:$A$301)-G1 -> 0
B7: Index | C7: ISIN | D7: Name | E7: Group | F7: Done | G7: Coding Notes | H7: Significant | I7: First Review Effective Date (after close of the ... ) | J7: Cut off Date(s) (after close of the ... ) | K7: Used the following datasets
A8: 21 | B8: AEXEW | C8: QS0011159744 | D8: AEX Equal Weight | E8: CAC/AEX Equal Weight | F8: Done | H8: =ISNUMBER(MATCH(B8,'Old Sheet'!$B$2:$B$305,0)) -> TRUE | I8: Third Friday of March, June, September, December | J8: Penultimate Friday of February, May, August, November | K8: =ISNUMBER(MATCH(B8,$O$9:$O$27,0)) -> FALSE
A9: 21 | B9: CACEW | C9: QS0011159777 | D9: CAC 40 Equal Weight | E9: CAC/AEX Equal Weight | F9: Done | H9: =ISNUMBER(MATCH(B9,'Old Sheet'!$B$2:$B$305,0)) -> TRUE | I9: Third Friday of March, June, September, December | J9: Penultimate Friday of February, May, August, November | K9: =ISNUMBER(MATCH(B9,$O$9:$O$27,0)) -> FALSE
A10: 21 | B10: CLEW | C10: FR0012663292 | D10: CAC Large 60 Equal Weight | E10: CAC/AEX Equal Weight | F10: Done | H10: =ISNUMBER(MATCH(B10,'Old Sheet'!$B$2:$B$305,0)) -> TRUE | I10: Third Friday of March, June, September, December | J10: Penultimate Friday of February, May, August, November | K10: =ISNUMBER(MATCH(B10,$O$9:$O$27,0)) -> FALSE
A11: 28 | B11: BNEW | C11: NL0011376116 | D11: Euronext BeNe 40 Equal Weight | E11: Bene40 Equal Weight | F11: Done | H11: =ISNUMBER(MATCH(B11,'Old Sheet'!$B$2:$B$305,0)) -> TRUE | I11: Third Friday of March, June, September, December | J11: Penultimate Friday of February, May, August, November | K11: =ISNUMBER(MATCH(B11,$O$9:$O$27,0)) -> FALSE
A12: 29 | B12: SBF80 | C12: FR0013017936 | D12: SBF Top 80 EW | E12: SBF 80 | F12: Done | H12: =ISNUMBER(MATCH(B12,'Old Sheet'!$B$2:$B$305,0)) -> TRUE | I12: Third Friday of March, June, September, December | J12: Penultimate Friday of February, May, August, November | K12: =ISNUMBER(MATCH(B12,$O$9:$O$27,0)) -> FALSE
A13: 32 | B13: CAGOV | C13: FR0013232188 | D13: CAC 40 Governance | E13: Cac 40 Governance | F13: Moodys | H13: =ISNUMBER(MATCH(B13,'Old Sheet'!$B$2:$B$305,0)) -> TRUE | I13: Third Friday of March, June, September, December | J13: Penultimate Friday of February, May, August, November | K13: =ISNUMBER(MATCH(B13,$O$9:$O$27,0)) -> FALSE
A14: 33 | B14: EC1EW | C14: NL0012254635 | D14: Euronext Core Europe 100 EW | E14: Core Europe | H14: =ISNUMBER(MATCH(B14,'Old Sheet'!$B$2:$B$305,0)) -> TRUE | I14: Third Friday of March, June, September, December | J14: Penultimate Friday of February, May, August, November | K14: =ISNUMBER(MATCH(B14,$O$9:$O$27,0)) -> FALSE
A15: 33 | B15: COR3P | C15: NL0012483903 | D15: Euronext Core Europe 30 EW | E15: Core Europe | H15: =ISNUMBER(MATCH(B15,'Old Sheet'!$B$2:$B$305,0)) -> TRUE | I15: Third Friday of March, June, September, December | J15: Penultimate Friday of February, May, August, November | K15: =ISNUMBER(MATCH(B15,$O$9:$O$27,0)) -> FALSE
A16: 33 | B16: CEE3P | C16: NL0013026917 | D16: Euronext Core Europe 30 ESG EW | E16: Core Europe | F16: Moodys | H16: =ISNUMBER(MATCH(B16,'Old Sheet'!$B$2:$B$305,0)) -> TRUE | I16: Third Friday of March, June, September, December | J16: Penultimate Friday of February, May, August, November | K16: =ISNUMBER(MATCH(B16,$O$9:$O$27,0)) -> FALSE
A17: 38 | B17: EFGEW | C17: NL0012365035 | D17: Euronext France Germany Leaders 50 EW | E17: France German Leaders 50 EW | H17: =ISNUMBER(MATCH(B17,'Old Sheet'!$B$2:$B$305,0)) -> FALSE | I17: Third Friday of March, June, September, December | J17: Penultimate Friday of February, May, August, November | K17: =ISNUMBER(MATCH(B17,$O$9:$O$27,0)) -> FALSE
A18: 40 | B18: EFGP | C18: NL0012658769 | D18: Euronext France Germany Leaders 50 | E18: France German Leaders 50 | H18: =ISNUMBER(MATCH(B18,'Old Sheet'!$B$2:$B$305,0)) -> TRUE | I18: Third Friday of March, June, September, December | J18: Penultimate Friday of February, May, August, November | K18: =ISNUMBER(MATCH(B18,$O$9:$O$27,0)) -> FALSE
A19: 41 | B19: EZ40P | C19: NL0012731871 | D19: Euronext Eurozone 40 EW | E19: Eurozone 40 EW | H19: =ISNUMBER(MATCH(B19,'Old Sheet'!$B$2:$B$305,0)) -> TRUE | I19: Third Friday of March, June, September, December | J19: Penultimate Friday of February, May, August, November | K19: =ISNUMBER(MATCH(B19,$O$9:$O$27,0)) -> FALSE
A20: 43 | B20: EFMEP | C20: NL0012730451 | D20: Euronext Founding Members Europe 50 EW | E20: Founding Members | H20: =ISNUMBER(MATCH(B20,'Old Sheet'!$B$2:$B$305,0)) -> FALSE | I20: Third Friday of March, June, September, December | J20: Penultimate Friday of February, May, August, November | K20: =ISNUMBER(MATCH(B20,$O$9:$O$27,0)) -> FALSE
A21: 47 | B21: ES1EP | C21: NL0012758627 | D21: Euronext® Europe Sustainable 100 EW | E21: Europe Sustainable 100 | F21: Moodys | H21: =ISNUMBER(MATCH(B21,'Old Sheet'!$B$2:$B$305,0)) -> TRUE | I21: Third Friday of March, June, September, December | J21: Penultimate Friday of February, May, August, November | K21: =ISNUMBER(MATCH(B21,$O$9:$O$27,0)) -> FALSE
A22: 48 | B22: CLE5P | C22: NL0012758585 | D22: Euronext® Eurozone Energy Transition Leaders 50 EW | E22: Eurozone Energy Transition Leaders 50 | F22: Moodys | H22: =ISNUMBER(MATCH(B22,'Old Sheet'!$B$2:$B$305,0)) -> FALSE | I22: Second Friday of January, April, July, October | J22: Penultimate Friday of February, May, August, November | K22: =ISNUMBER(MATCH(B22,$O$9:$O$27,0)) -> FALSE
A23: 49 | B23: ESE4P | C23: NL0012758544 | D23: Euronext® Eurozone ESG Leaders 40 EW | E23: Eurozone ESG Leaders 40 | F23: Moodys | H23: =ISNUMBER(MATCH(B23,'Old Sheet'!$B$2:$B$305,0)) -> TRUE | I23: Third Friday of March, June, September, December | J23: Penultimate Friday of February, May, August, November | K23: =ISNUMBER(MATCH(B23,$O$9:$O$27,0)) -> FALSE
A24: 50 | B24: CLF4P | C24: FR0013317773 | D24: Euronext France Energy Transition Leaders 40 EW | E24: France Energy Transition Leaders 40 | F24: Moodys | H24: =ISNUMBER(MATCH(B24,'Old Sheet'!$B$2:$B$305,0)) -> FALSE | I24: Third Friday of March, June, September, December | J24: Penultimate Friday of February, May, August, November | K24: =ISNUMBER(MATCH(B24,$O$9:$O$27,0)) -> FALSE
A25: 51 | B25: ESF4P | C25: FR0013317732 | D25: Euronext® France ESG Leaders 40 EW | E25: France ESG Leaders 40 | F25: Moodys | H25: =ISNUMBER(MATCH(B25,'Old Sheet'!$B$2:$B$305,0)) -> TRUE | I25: Third Friday of March, June, September, December | J25: Penultimate Friday of February, May, August, November | K25: =ISNUMBER(MATCH(B25,$O$9:$O$27,0)) -> FALSE
A26: 52 | B26: ESG50 | C26: NL0012481741 | D26: Euronext Euro 50 ESG EW | E26: Euronext ESG Euro 50 | F26: Moodys | H26: =ISNUMBER(MATCH(B26,'Old Sheet'!$B$2:$B$305,0)) -> TRUE | I26: Third Friday of March, June, September, December | J26: Penultimate Friday of February, May, August, November | K26: =ISNUMBER(MATCH(B26,$O$9:$O$27,0)) -> FALSE
A27: 56 | B27: EZ15P | C27: NL0012949101 | D27: Euronext Eurozone 150 EW | E27: Eurozone | H27: =ISNUMBER(MATCH(B27,'Old Sheet'!$B$2:$B$305,0)) -> TRUE | I27: Third Friday of March, June, September, December | J27: Penultimate Friday of February, May, August, November | K27: =ISNUMBER(MATCH(B27,$O$9:$O$27,0)) -> FALSE
A28: 56 | B28: EZN1P | C28: NL0012949143 | D28: Euronext Eurozone Next 100 EW | E28: Eurozone | H28: =ISNUMBER(MATCH(B28,'Old Sheet'!$B$2:$B$305,0)) -> TRUE | I28: Third Friday of March, June, September, December | J28: Penultimate Friday of February, May, August, November | K28: =ISNUMBER(MATCH(B28,$O$9:$O$27,0)) -> FALSE
A29: 58 | B29: FRENP | C29: NL0013025471 | D29: Euronext CDP Environment France EW | E29: CDP Environment France | H29: =ISNUMBER(MATCH(B29,'Old Sheet'!$B$2:$B$305,0)) -> TRUE | I29: Third Friday of March, June, September, December | J29: Penultimate Friday of February, May, August, November | K29: =ISNUMBER(MATCH(B29,$O$9:$O$27,0)) -> FALSE
A30: 59 | B30: ESG1P | C30: NL0013025596 | D30: Euronext Eurozone 100 ESG | E30: Eurozone 100 ESG | F30: Moodys | H30: =ISNUMBER(MATCH(B30,'Old Sheet'!$B$2:$B$305,0)) -> TRUE | I30: Third Friday of March, June, September, December | J30: Penultimate Friday of February, May, August, November | K30: =ISNUMBER(MATCH(B30,$O$9:$O$27,0)) -> FALSE
A31: 62 | B31: FRECP | C31: FR0013349057 | D31: Euronext France 20-40 Challengers EW | E31: Euronext France 20-40 Challengers | H31: =ISNUMBER(MATCH(B31,'Old Sheet'!$B$2:$B$305,0)) -> TRUE | I31: Third Friday of March, June, September, December | J31: Penultimate Friday of February, May, August, November | K31: =ISNUMBER(MATCH(B31,$O$9:$O$27,0)) -> FALSE
A32: 63 | B32: FRN4P | C32: FR0013354156 | D32: Euronext France Next 40 EW | E32: France Next 40 | H32: =ISNUMBER(MATCH(B32,'Old Sheet'!$B$2:$B$305,0)) -> TRUE | I32: Third Friday of March, June, September, December | J32: Penultimate Friday of February, May, August, November | K32: =ISNUMBER(MATCH(B32,$O$9:$O$27,0)) -> FALSE
A33: 64 | B33: FR20P | C33: FR0013355948 | D33: Euronext France 20 EW | E33: France 20 | H33: =ISNUMBER(MATCH(B33,'Old Sheet'!$B$2:$B$305,0)) -> TRUE | I33: Third Friday of March, June, September, December | J33: Penultimate Friday of February, May, August, November | K33: =ISNUMBER(MATCH(B33,$O$9:$O$27,0)) -> FALSE
A34: 65 | B34: FREEP | C34: NL0013039258 | D34: Euronext CDP Environment France Ex Oil & Gas EW | E34: CDP Environ. France ex Oil & Gas | H34: =ISNUMBER(MATCH(B34,'Old Sheet'!$B$2:$B$305,0)) -> TRUE | I34: Third Friday of March, June, September, December | J34: Penultimate Friday of February, May, August, November | K34: =ISNUMBER(MATCH(B34,$O$9:$O$27,0)) -> FALSE
A35: 66 | B35: ESF5P | C35: FR0013371416 | D35: SBF Top 50 ESG EW | E35: SBF Top 50 ESG | F35: Moodys | H35: =ISNUMBER(MATCH(B35,'Old Sheet'!$B$2:$B$305,0)) -> TRUE | I35: Third Friday of March, June, September, December | J35: Penultimate Friday of February, May, August, November | K35: =ISNUMBER(MATCH(B35,$O$9:$O$27,0)) -> FALSE
A36: 67 | B36: C6RIP | C36: FR0013376258 | D36: CAC Large 60 Responsible Investment SW | E36: Responsible Investment CAC Large 60 | H36: =ISNUMBER(MATCH(B36,'Old Sheet'!$B$2:$B$305,0)) -> TRUE | I36: Third Friday of March, June, September, December | J36: Penultimate Friday of February, May, August, November | K36: =ISNUMBER(MATCH(B36,$O$9:$O$27,0)) -> FALSE
A37: 68 | B37: F4RIP | C37: FR0013376209 | D37: Euronext France 40 Responsible Investment | E37: Responsible Investment Euronext France 40 | F37: Done | H37: =ISNUMBER(MATCH(B37,'Old Sheet'!$B$2:$B$305,0)) -> TRUE | I37: Third Friday of March, June, September, December | J37: Penultimate Friday of February, May, August, November | K37: =ISNUMBER(MATCH(B37,$O$9:$O$27,0)) -> FALSE
A38: 69 | B38: EUS5P | C38: NL0013216468 | D38: Euronext Transatlantic 50 EW | E38: Transatlantic 50 EW | H38: =ISNUMBER(MATCH(B38,'Old Sheet'!$B$2:$B$305,0)) -> TRUE | I38: Third Friday of March, June, September, December | J38: Penultimate Friday of February, May, August, November | K38: =ISNUMBER(MATCH(B38,$O$9:$O$27,0)) -> FALSE
A39: 70 | B39: ERI5P | C39: NL0013217730 | D39: Euronext Responsible Investment Euro 50 EW | E39: Responsible Investment Euro 50 | H39: =ISNUMBER(MATCH(B39,'Old Sheet'!$B$2:$B$305,0)) -> TRUE | I39: Third Friday of March, June, September, December | J39: Penultimate Friday of February, May, August, November | K39: =ISNUMBER(MATCH(B39,$O$9:$O$27,0)) -> FALSE
A40: 75 | B40: EZENP | C40: NL0013352560 | D40: Euronext CDP Environment Eurozone EW | E40: CDP Environment Eurozone | H40: =ISNUMBER(MATCH(B40,'Old Sheet'!$B$2:$B$305,0)) -> TRUE | I40: Third Friday of March, June, September, December | J40: Penultimate Friday of February, May, August, November | K40: =ISNUMBER(MATCH(B40,$O$9:$O$27,0)) -> FALSE
A41: 76 | B41: WLENP | C41: NL0013352602 | D41: Euronext CDP Environment World EW | E41: CDP Environment World | H41: =ISNUMBER(MATCH(B41,'Old Sheet'!$B$2:$B$305,0)) -> TRUE | I41: Third Friday of March, June, September, December | J41: Penultimate Friday of February, May, August, November | K41: =ISNUMBER(MATCH(B41,$O$9:$O$27,0)) -> FALSE
A42: 79 | B42: WESGP | C42: NL0013940984 | D42: Euronext CDP Environment ESG World EW | E42: Euronext CDP Environment ESG World | F42: Moodys | H42: =ISNUMBER(MATCH(B42,'Old Sheet'!$B$2:$B$305,0)) -> FALSE | I42: Third Friday of March, June, September, December | J42: Penultimate Friday of February, May, August, November | K42: =ISNUMBER(MATCH(B42,$O$9:$O$27,0)) -> FALSE
A43: 80 | B43: ESGTP | C43: NL0013908775 | D43: Euronext Transatlantic ESG Leaders 60 EW | E43: Euronext Transatlantic ESG Leaders 60 | F43: Moodys | H43: =ISNUMBER(MATCH(B43,'Old Sheet'!$B$2:$B$305,0)) -> FALSE | I43: Third Friday of March, June, September, December | J43: Penultimate Friday of February, May, August, November | K43: =ISNUMBER(MATCH(B43,$O$9:$O$27,0)) -> FALSE
A44: 81 | B44: EESGP | C44: NL0013941024 | D44: Euronext CDP Environment ESG Eurozone EW | E44: Euronext CDP Environment ESG Eurozone EW | F44: Moodys | H44: =ISNUMBER(MATCH(B44,'Old Sheet'!$B$2:$B$305,0)) -> TRUE | I44: Third Friday of March, June, September, December | J44: Penultimate Friday of February, May, August, November | K44: =ISNUMBER(MATCH(B44,$O$9:$O$27,0)) -> FALSE
A45: 82 | B45: WATPR | C45: NL0013908825 | D45: Euronext Water and Ocean Europe 40 EW | E45: Euronext Water and Ocean Europe 40 EW | F45: Non-Quarterly | H45: =ISNUMBER(MATCH(B45,'Old Sheet'!$B$2:$B$305,0)) -> FALSE | I45: Third Friday of December | J45: Penultimate Friday of November | K45: =ISNUMBER(MATCH(B45,$O$9:$O$27,0)) -> FALSE
A46: 83 | B46: FESGP | C46: FR0013448131 | D46: Euronext CDP Environment ESG France EW | E46: Euronext CDP Environment ESG France | F46: Moodys | H46: =ISNUMBER(MATCH(B46,'Old Sheet'!$B$2:$B$305,0)) -> FALSE | I46: Third Friday of March, June, September, December | J46: Penultimate Friday of February, May, August, November | K46: =ISNUMBER(MATCH(B46,$O$9:$O$27,0)) -> FALSE
A47: 84 | B47: GRE5P | C47: FR0013457850 | D47: Euronext Green Planet E | E47: Euronext Green Planet | F47: Moodys | H47: =ISNUMBER(MATCH(B47,'Old Sheet'!$B$2:$B$305,0)) -> TRUE | I47: Third Friday of March, June, September, December | J47: Penultimate Friday of February, May, August, November | K47: =ISNUMBER(MATCH(B47,$O$9:$O$27,0)) -> FALSE
A48: 85 | B48: ESGEP | C48: FR0013477007 | D48: Euronext Eurozone ESG Leaders Select 40 EW | E48: Euronext Eurozone ESG Leaders Select 40 | F48: Moodys | H48: =ISNUMBER(MATCH(B48,'Old Sheet'!$B$2:$B$305,0)) -> FALSE | I48: Wednesday after the Third Friday of March, June, September, December | J48: Penultimate Friday of February, May, August, November | K48: =ISNUMBER(MATCH(B48,$O$9:$O$27,0)) -> FALSE
A49: 86 | B49: ESGFP | C49: FR0013476959 | D49: Euronext France ESG Leaders Select 30 EW | E49: Euronext France ESG Leaders Select 30 | F49: Moodys | H49: =ISNUMBER(MATCH(B49,'Old Sheet'!$B$2:$B$305,0)) -> FALSE | I49: Wednesday after the Third Friday of March, June, September, December | J49: Penultimate Friday of February, May, August, November | K49: =ISNUMBER(MATCH(B49,$O$9:$O$27,0)) -> FALSE
A50: 87 | B50: GRF5P | C50: FR0013479763 | D50: Euronext Green Planet France | E50: Euronext Green Planet France | F50: Moodys | H50: =ISNUMBER(MATCH(B50,'Old Sheet'!$B$2:$B$305,0)) -> TRUE | I50: Third Friday of March, June, September, December | J50: Penultimate Friday of February, May, August, November | K50: =ISNUMBER(MATCH(B50,$O$9:$O$27,0)) -> FALSE
A51: 89 | B51: ENESG | C51: FR0013468832 | D51: Euronext Eurozone ESG Large 80 | E51: Euronext Eurozone ESG Large 80 | F51: Moodys | H51: =ISNUMBER(MATCH(B51,'Old Sheet'!$B$2:$B$305,0)) -> TRUE | I51: Third Friday of March, June, September, December | J51: Penultimate Friday of February, May, August, November | K51: =ISNUMBER(MATCH(B51,$O$9:$O$27,0)) -> FALSE
A52: 91 | B52: ECC5P | C52: FR0013533551 | D52: Euronext Core Euro & Global Climate Change EW | E52: Euronext Core Euro & Global Climate Change | F52: Moodys | H52: =ISNUMBER(MATCH(B52,'Old Sheet'!$B$2:$B$305,0)) -> FALSE | I52: Third Friday of March, June, September, December | J52: Penultimate Friday of February, May, August, November | K52: =ISNUMBER(MATCH(B52,$O$9:$O$27,0)) -> FALSE
A53: 92 | B53: OSEXP | C53: NO0010892201 | D53: OSEEXR Index PR | E53: Equity Certificate Indices | F53: Non-Quarterly | H53: =ISNUMBER(MATCH(B53,'Old Sheet'!$B$2:$B$305,0)) -> TRUE | I53: Third Friday of March, September | J53: Penultimate Friday of February, August | K53: =ISNUMBER(MATCH(B53,$O$9:$O$27,0)) -> FALSE
... A61: 105 | B61: EUEPR | C61: NL0015000A61 | D61: Euronext US ESGL 20 EW | E61: US ESGL 20 | F61: Moodys | H61: =ISNUMBER(MATCH(B61,'Old Sheet'!$B$2:$B$305,0)) -> TRUE | I61: Third Friday of March, June, September, December | J61: Penultimate Friday of February, May, August, November | K61: =ISNUMBER(MATCH(B61,$O$9:$O$27,0)) -> FALSE
A62: 106 | B62: BANK | C62: NL0015000AR3 | D62: Euronext Eurozone Banks | E62: Eurozone Banks | H62: =ISNUMBER(MATCH(B62,'Old Sheet'!$B$2:$B$305,0)) -> TRUE | I62: Third Friday of March, June, September, December | J62: Penultimate Friday of February, May, August, November | K62: =ISNUMBER(MATCH(B62,$O$9:$O$27,0)) -> FALSE
A63: 110 | B63: ETE5P | C63: NL0015000BX9 | D63: EN Transatlantic Environment 50 | E63: EN Transatlantic Environment 50 | H63: =ISNUMBER(MATCH(B63,'Old Sheet'!$B$2:$B$305,0)) -> FALSE | I63: Third Friday of March, June, September, December | J63: Penultimate Friday of February, May, August, November | K63: =ISNUMBER(MATCH(B63,$O$9:$O$27,0)) -> FALSE
A64: 111 | B64: FPABP | C64: FR0014003927 | D64: Euronext France PAB 50 | E64: Euronext France PAB 50 | F64: Moodys | H64: =ISNUMBER(MATCH(B64,'Old Sheet'!$B$2:$B$305,0)) -> TRUE | I64: Third Friday of December | J64: Penultimate Friday of November | K64: =ISNUMBER(MATCH(B64,$O$9:$O$27,0)) -> FALSE
A65: 112 | B65: TCEPR | C65: FR0014003BU4 | D65: Euronext Transatlantic Circular Economy 50 EW | E65: Euronext Transatlantic Circular Economy 50 EW | F65: Moodys | H65: =ISNUMBER(MATCH(B65,'Old Sheet'!$B$2:$B$305,0)) -> FALSE | I65: Third Friday of March, June, September, December | J65: Penultimate Friday of February, May, August, November | K65: =ISNUMBER(MATCH(B65,$O$9:$O$27,0)) -> FALSE
A66: 113 | B66: CPABP | C66: FR0014003PU4 | D66: Euronext Core Europe PAB 50 | E66: Euronext Core Europe PAB 50 | F66: Moodys | H66: =ISNUMBER(MATCH(B66,'Old Sheet'!$B$2:$B$305,0)) -> TRUE | I66: Third Friday of December | J66: Penultimate Friday of November | K66: =ISNUMBER(MATCH(B66,$O$9:$O$27,0)) -> FALSE
A67: 114 | B67: GOVEP | C67: FR0014003PO7 | D67: Euronext Eurozone Diversity & Governance 40 EW | E67: Euronext Eurozone Diversity & Governance 40 EW | F67: Moodys | H67: =ISNUMBER(MATCH(B67,'Old Sheet'!$B$2:$B$305,0)) -> FALSE | I67: Third Friday of March, June, September, December | J67: Penultimate Friday of February, May, August, November | K67: =ISNUMBER(MATCH(B67,$O$9:$O$27,0)) -> FALSE
A68: 115 | B68: EPABP | C68: FR0014003PR0 | D68: Euronext Eurozone PAB 50 | E68: Euronext Eurozone PAB 50 | F68: Moodys | H68: =ISNUMBER(MATCH(B68,'Old Sheet'!$B$2:$B$305,0)) -> TRUE | I68: Third Friday of December | J68: Penultimate Friday of November | K68: =ISNUMBER(MATCH(B68,$O$9:$O$27,0)) -> FALSE
A69: 116 | B69: SES5P | C69: NL0015000EF0 | D69: EN Sovereign Economy Selection Eurozone 50 | E69: EN Sovereign Economy Selection EZ50 | F69: Done | H69: =ISNUMBER(MATCH(B69,'Old Sheet'!$B$2:$B$305,0)) -> TRUE | I69: Third Friday of March, June, September, December | J69: Penultimate Friday of February, May, August, November | K69: =ISNUMBER(MATCH(B69,$O$9:$O$27,0)) -> FALSE
A70: 117 | B70: EWCSP | C70: NL0015000E91 | D70: Euronext World Country selection | E70: Euronext World Country selection | H70: =ISNUMBER(MATCH(B70,'Old Sheet'!$B$2:$B$305,0)) -> TRUE | I70: Third Friday of March, June, September, December | J70: Penultimate Friday of February, May, August, November | K70: =ISNUMBER(MATCH(B70,$O$9:$O$27,0)) -> FALSE
A71: 118 | B71: EVEWP | C71: NL0015000ED5 | D71: Euronext ESG World-Select 75 Bund/SV | E71: EN V E ESG World-Select 75 Bund/SV | F71: Moodys | H71: =ISNUMBER(MATCH(B71,'Old Sheet'!$B$2:$B$305,0)) -> FALSE | I71: Last trading-day of June | J71: Penultimate Friday of May | K71: =ISNUMBER(MATCH(B71,$O$9:$O$27,0)) -> FALSE
A72: 119 | B72: EZSFP | C72: FR0014004FP3 | D72: Euronext Eurozone Social Focus | E72: Euronext V E Eurozone Social Focus | F72: Moodys | H72: =ISNUMBER(MATCH(B72,'Old Sheet'!$B$2:$B$305,0)) -> FALSE | I72: Third Friday of March, June, September, December | J72: Penultimate Friday of February, May, August, November | K72: =ISNUMBER(MATCH(B72,$O$9:$O$27,0)) -> FALSE
A73: 120 | B73: ESGCP | C73: FR0014004HI4 | D73: EN EZ ESG Leaders Select 40 | E73: EN EZ ESG Leaders Select 40 | F73: Moodys | H73: =ISNUMBER(MATCH(B73,'Old Sheet'!$B$2:$B$305,0)) -> FALSE | I73: Second Friday of January, April, July, October | J73: Penultimate Friday of February, May, August, November | K73: =ISNUMBER(MATCH(B73,$O$9:$O$27,0)) -> FALSE
A74: 121 | B74: TESGP | C74: FR0014004PQ0 | D74: EN CDP Environment Transatlantic EW | E74: EN CDP Environment Transatlantic EW | F74: Moodys | H74: =ISNUMBER(MATCH(B74,'Old Sheet'!$B$2:$B$305,0)) -> FALSE | I74: Third Friday of March, June, September, December | J74: Penultimate Friday of February, May, August, November | K74: =ISNUMBER(MATCH(B74,$O$9:$O$27,0)) -> FALSE
A75: 122 | B75: CLAMP | C75: FR0014004XR2 | D75: Euronext EZ Scr Clim Amb 40 EW | E75: Euronext EZ Scr Clim Amb 40 EW | H75: =ISNUMBER(MATCH(B75,'Old Sheet'!$B$2:$B$305,0)) -> FALSE | I75: Third Friday of March, June, September, December | J75: Penultimate Friday of February, May, August, November | K75: =ISNUMBER(MATCH(B75,$O$9:$O$27,0)) -> FALSE
A76: 123 | B76: ENDMP | C76: NL0015000I89 | D76: Euronext Developed Market | E76: Euronext Developed Market | H76: =ISNUMBER(MATCH(B76,'Old Sheet'!$B$2:$B$305,0)) -> TRUE | I76: Third Friday of March, June, September, December | J76: Penultimate Friday of February, May, August, November | K76: =ISNUMBER(MATCH(B76,$O$9:$O$27,0)) -> FALSE
A77: 123 | B77: EDMPU | C77: NLIX00000009 | D77: Euronext Developed Market USD | E77: Euronext Developed Market | H77: =ISNUMBER(MATCH(B77,'Old Sheet'!$B$2:$B$305,0)) -> TRUE | I77: Third Friday of March, June, September, December | J77: Penultimate Friday of February, May, August, November | K77: =ISNUMBER(MATCH(B77,$O$9:$O$27,0)) -> FALSE
A78: 124 | B78: ENWP | C78: NL0015000IB0 | D78: Euronext World | E78: Euronext World | F78: Done | H78: =ISNUMBER(MATCH(B78,'Old Sheet'!$B$2:$B$305,0)) -> TRUE | I78: Third Friday of March, June, September, December | J78: Penultimate Friday of February, May, August, November | K78: =ISNUMBER(MATCH(B78,$O$9:$O$27,0)) -> FALSE
A79: 125 | B79: FRSOP | C79: FR0014005D77 | D79: Euronext France Social | E79: Euronext France Social | F79: Moodys | H79: =ISNUMBER(MATCH(B79,'Old Sheet'!$B$2:$B$305,0)) -> TRUE | I79: Second Friday of January, April, July, October | J79: First Friday of January, April, July, October | K79: =ISNUMBER(MATCH(B79,$O$9:$O$27,0)) -> FALSE
A80: 126 | B80: EZCLA | C80: FR0014005IK5 | D80: EN EZ Screened Climate Ambition 35 EW | E80: EN EZ Screened Climate Ambition 35 EW | H80: =ISNUMBER(MATCH(B80,'Old Sheet'!$B$2:$B$305,0)) -> FALSE | I80: Third Friday of March, June, September, December | J80: Penultimate Friday of February, May, August, November | K80: =ISNUMBER(MATCH(B80,$O$9:$O$27,0)) -> FALSE
A81: 127 | B81: USCLE | C81: FR0014005IJ7 | D81: EN US Screened Climate Amb 25 EW EUR | E81: EN US Screened Climate Amb 25 EW EUR | H81: =ISNUMBER(MATCH(B81,'Old Sheet'!$B$2:$B$305,0)) -> FALSE | I81: Third Friday of March, June, September, December | J81: Penultimate Friday of February, May, August, November | K81: =ISNUMBER(MATCH(B81,$O$9:$O$27,0)) -> FALSE
A82: 128 | B82: USCLA | C82: FR0014005GE2 | D82: EN US Screened Climate Ambition 25 EW USD | E82: EN US Screened Climate Ambition 25 EW USD | H82: =ISNUMBER(MATCH(B82,'Old Sheet'!$B$2:$B$305,0)) -> FALSE | I82: Third Friday of March, June, September, December | J82: Penultimate Friday of February, May, August, November | K82: =ISNUMBER(MATCH(B82,$O$9:$O$27,0)) -> FALSE
A83: 131 | B83: GHCPR | C83: FRESG0000009 | D83: Euronext® Global Health Care 50 EW ESG | E83: Euronext® Global Health Care 50 EW ESG | F83: Moodys | H83: =ISNUMBER(MATCH(B83,'Old Sheet'!$B$2:$B$305,0)) -> TRUE | I83: Third Friday of March, June, September, December | J83: Penultimate Friday of February, May, August, November | K83: =ISNUMBER(MATCH(B83,$O$9:$O$27,0)) -> FALSE
A84: 132 | B84: EBSEP | C84: FRESG0000090 | D84: Euronext ESG Biodiversity Screened Eurozone 50 | E84: Euronext ESG Biodiversity Screened Eurozone 50 | H84: =ISNUMBER(MATCH(B84,'Old Sheet'!$B$2:$B$305,0)) -> FALSE | I84: Third Friday of March, June, September, December | J84: Penultimate Friday of February, May, August, November | K84: =ISNUMBER(MATCH(B84,$O$9:$O$27,0)) -> FALSE
A85: 133 | B85: EBSWP | C85: FRESG0000066 | D85: Euronext ESG Biodiversity Screened World | E85: Euronext ESG Biodiversity Screened World | H85: =ISNUMBER(MATCH(B85,'Old Sheet'!$B$2:$B$305,0)) -> FALSE | I85: Third Friday of March, June, September, December | J85: Penultimate Friday of February, May, August, November | K85: =ISNUMBER(MATCH(B85,$O$9:$O$27,0)) -> FALSE
A86: 133 | B86: EBSPW | C86: FRESG0000140 | D86: Euronext ESG Biodiversity Screened World USD | E86: Euronext ESG Biodiversity Screened World | H86: =ISNUMBER(MATCH(B86,'Old Sheet'!$B$2:$B$305,0)) -> FALSE | I86: Third Friday of March, June, September, December | J86: Penultimate Friday of February, May, August, November | K86: =ISNUMBER(MATCH(B86,$O$9:$O$27,0)) -> FALSE
A87: 134 | B87: JPCLE | C87: FRESG0000215 | D87: EN JPN Screened Climate Amb 30 EW EUR | E87: EN JPN Screened Climate Amb 30 EW EUR | H87: =ISNUMBER(MATCH(B87,'Old Sheet'!$B$2:$B$305,0)) -> FALSE | I87: Third Friday of March, June, September, December | J87: Penultimate Friday of February, May, August, November | K87: =ISNUMBER(MATCH(B87,$O$9:$O$27,0)) -> FALSE
A88: 135 | B88: JPCLA | C88: FRESG0000181 | D88: EN JPN Screened Climate Ambition 30 EW | E88: EN JPN Screened Climate Ambition 30 EW | H88: =ISNUMBER(MATCH(B88,'Old Sheet'!$B$2:$B$305,0)) -> FALSE | I88: Third Friday of March, June, September, December | J88: Penultimate Friday of February, May, August, November | K88: =ISNUMBER(MATCH(B88,$O$9:$O$27,0)) -> FALSE
A89: 136 | B89: UC3PE | C89: FRESG0000272 | D89: EN US Screened Climate Amb 35 EW EUR | E89: EN US Screened Climate Amb 35 EW EUR | H89: =ISNUMBER(MATCH(B89,'Old Sheet'!$B$2:$B$305,0)) -> FALSE | I89: Third Friday of March, June, September, December | J89: Penultimate Friday of February, May, August, November | K89: =ISNUMBER(MATCH(B89,$O$9:$O$27,0)) -> FALSE
A90: 137 | B90: USC3P | C90: FRESG0000249 | D90: EN US Screened Climate Ambition 35 EW | E90: EN US Screened Climate Ambition 35 EW | H90: =ISNUMBER(MATCH(B90,'Old Sheet'!$B$2:$B$305,0)) -> FALSE | I90: Third Friday of March, June, September, December | J90: Penultimate Friday of February, May, August, November | K90: =ISNUMBER(MATCH(B90,$O$9:$O$27,0)) -> FALSE
A91: 138 | B91: BIOEP | C91: FRESG0000306 | D91: Euronext Euro Large Cap Biodiversity Leaders 30 | E91: EN Euro Large Cap Biodiversity Leaders 30 | H91: =ISNUMBER(MATCH(B91,'Old Sheet'!$B$2:$B$305,0)) -> FALSE | I91: Third Friday of March, June, September, December | J91: Penultimate Friday of February, May, August, November | K91: =ISNUMBER(MATCH(B91,$O$9:$O$27,0)) -> FALSE
A92: 140 | B92: EBSTP | C92: FRESG0000405 | D92: EN ESG Biodiversity Screened Transatlantic 80 | E92: EN ESG Biodiversity Screened Transatlantic 80 | H92: =ISNUMBER(MATCH(B92,'Old Sheet'!$B$2:$B$305,0)) -> FALSE | I92: Third Friday of March, June, September, December | J92: Penultimate Friday of February, May, August, November | K92: =ISNUMBER(MATCH(B92,$O$9:$O$27,0)) -> FALSE
A93: 142 | B93: OBXEP | C93: NO0012513482 | D93: OBX ESG PR | E93: OBX ESG | F93: Non-Quarterly | H93: =ISNUMBER(MATCH(B93,'Old Sheet'!$B$2:$B$305,0)) -> TRUE | I93: Third Friday of March, September | J93: Penultimate Friday of February, August | K93: =ISNUMBER(MATCH(B93,$O$9:$O$27,0)) -> FALSE
A94: 142 | B94: OEXOP | C94: NO0012513516 | D94: OBX ESG ex Oil and Gas PR | E94: OBX ESG | F94: Non-Quarterly | H94: =ISNUMBER(MATCH(B94,'Old Sheet'!$B$2:$B$305,0)) -> TRUE | I94: Third Friday of March, September | J94: Penultimate Friday of February, August | K94: =ISNUMBER(MATCH(B94,$O$9:$O$27,0)) -> FALSE
A95: 143 | B95: AESGP | C95: NLESG0000014 | D95: AEX ESG | E95: AEX ESG | H95: =ISNUMBER(MATCH(B95,'Old Sheet'!$B$2:$B$305,0)) -> TRUE | I95: Third Friday of March, June, September, December | J95: Penultimate Friday of February, May, August, November | K95: =ISNUMBER(MATCH(B95,$O$9:$O$27,0)) -> FALSE
A96: 144 | B96: EZ6PP | C96: FRESG0000496 | D96: Euronext Eurozone 60 PAB | E96: Euronext Eurozone 60 PAB | F96: Non-Quarterly | H96: =ISNUMBER(MATCH(B96,'Old Sheet'!$B$2:$B$305,0)) -> TRUE | I96: Third Friday of March | J96: Penultimate Friday of February | K96: =ISNUMBER(MATCH(B96,$O$9:$O$27,0)) -> FALSE
A97: 145 | B97: ES4PP | C97: FRESG0000546 | D97: Euronext Eurozone Focus 40 PAB | E97: Euronext Eurozone Focus 40 PAB | F97: Non-Quarterly | H97: =ISNUMBER(MATCH(B97,'Old Sheet'!$B$2:$B$305,0)) -> TRUE | I97: Third Friday of March | J97: Penultimate Friday of February | K97: =ISNUMBER(MATCH(B97,$O$9:$O$27,0)) -> FALSE
A98: 147 | B98: EBLPP | C98: FRESG0000371 | D98: Euronext ESG Eurozone Biodiversity Leaders PAB | E98: Euronext ESG Eurozone Biodiversity Leaders PAB | F98: Moodys | H98: =ISNUMBER(MATCH(B98,'Old Sheet'!$B$2:$B$305,0)) -> TRUE | I98: Third Friday of September | J98: Penultimate Friday of August | K98: =ISNUMBER(MATCH(B98,$O$9:$O$27,0)) -> FALSE
A99: 155 | B99: ENFRP | C99: FRESG0000835 | D99: EN CDP France Environnement | E99: EN CDP France Environnement | F99: Moodys | H99: =ISNUMBER(MATCH(B99,'Old Sheet'!$B$2:$B$305,0)) -> FALSE | I99: Last trading-day of March, June, September, December | J99: Penultimate Friday of February, May, August, November | K99: =ISNUMBER(MATCH(B99,$O$9:$O$27,0)) -> FALSE
A100: 159 | B100: EQGEP | C100: FRESG0000991 | D100: EN Equileap Gender Equality EZ 100 | E100: EN Equileap Gender Equality EZ 100 | H100: =ISNUMBER(MATCH(B100,'Old Sheet'!$B$2:$B$305,0)) -> FALSE | I100: Second Friday of January, April, July, October | J100: First Friday of January, April, July, October | K100: =ISNUMBER(MATCH(B100,$O$9:$O$27,0)) -> FALSE
A101: 160 | B101: EQGFP | C101: FRESG0000900 | D101: EN Equileap Gender Equality France40 | E101: EN Equileap Gender Equality France40 | H101: =ISNUMBER(MATCH(B101,'Old Sheet'!$B$2:$B$305,0)) -> FALSE | I101: Second Friday of January, April, July, October | J101: First Friday of January, April, July, October | K101: =ISNUMBER(MATCH(B101,$O$9:$O$27,0)) -> FALSE
A102: 161 | B102: CSBTP | C102: FRESG0001031 | D102: CAC Transition Climat | E102: CAC SBT 1 5 | H102: =ISNUMBER(MATCH(B102,'Old Sheet'!$B$2:$B$305,0)) -> FALSE | I102: Third Friday of March, June, September, December | J102: Penultimate Friday of February, May, August, November | K102: =ISNUMBER(MATCH(B102,$O$9:$O$27,0)) -> FALSE
A103: 162 | B103: ENTP | C103: NLIX00000926 | D103: EN TRANSATLANTIC | E103: EN TRANSATLANTIC | H103: =ISNUMBER(MATCH(B103,'Old Sheet'!$B$2:$B$305,0)) -> TRUE | I103: Third Friday of March, June, September, December | J103: Penultimate Friday of February, May, August, November | K103: =ISNUMBER(MATCH(B103,$O$9:$O$27,0)) -> FALSE
A104: 165 | B104: ENZTP | C104: NLIX00001015 | D104: EN EZ Transatlantic | E104: EN EZ Transatlantic | H104: =ISNUMBER(MATCH(B104,'Old Sheet'!$B$2:$B$305,0)) -> TRUE | I104: Third Friday of March, June, September, December | J104: Penultimate Friday of February, May, August, November | K104: =ISNUMBER(MATCH(B104,$O$9:$O$27,0)) -> FALSE
A105: 168 | B105: EETPR | C105: FRESG0001163 | D105: Euronext Eurozone ESG Transition | E105: Euronext Eurozone ESG Transition | F105: Non-Quarterly | H105: =ISNUMBER(MATCH(B105,'Old Sheet'!$B$2:$B$305,0)) -> TRUE | I105: Third Friday of March | J105: Penultimate Friday of February | K105: =ISNUMBER(MATCH(B105,$O$9:$O$27,0)) -> FALSE
A106: 169 | B106: ESBTP | C106: FRESG0001304 | D106: Euronext Europe SBT 1.5 | E106: EU SBT 1.5 | H106: =ISNUMBER(MATCH(B106,'Old Sheet'!$B$2:$B$305,0)) -> FALSE | I106: Third Friday of March, June, September, December | J106: Penultimate Friday of February, May, August, November | K106: =ISNUMBER(MATCH(B106,$O$9:$O$27,0)) -> FALSE
A107: 170 | B107: ZSBTP | C107: FRESG0001213 | D107: Euronext Eurozone SBT 1.5 | E107: Euronext Eurozone SBT 1.5 | H107: =ISNUMBER(MATCH(B107,'Old Sheet'!$B$2:$B$305,0)) -> FALSE | I107: Third Friday of March, June, September, December | J107: Penultimate Friday of February, May, August, November | K107: =ISNUMBER(MATCH(B107,$O$9:$O$27,0)) -> FALSE
A108: 171 | B108: EAIWP | C108: FRIX00001845 | D108: Euronext AI World | E108: Euronext AI World | F108: Non-Quarterly | H108: =ISNUMBER(MATCH(B108,'Old Sheet'!$B$2:$B$305,0)) -> TRUE | I108: Third Friday of March | J108: Penultimate Friday of February | K108: =ISNUMBER(MATCH(B108,$O$9:$O$27,0)) -> FALSE
...

Sheet Full sheet Francesco
B3: Index Type | C3: SuperGroup | D3: Group | E3: Inception Date | F3: Delisting Date | G3: Number of effective dates per review | H3: First Review Effective Date (after close of the ... ) | I3: Cut off Date(s) (after close of the ... ) | J3: Review Announcement Date (n. days before eff date) | K3: Review Composition Date (n. days before eff date) | L3: Review Weighting Date (n. days before eff date) | M3: Free float start date (n. days before cutoff) | N3: Universe | O3: Data vendor(s) | P3: Packages | Q3: Comments | R3: Responsible 1 | S3: Method 1 | T3: Responsible 2 | U3: Method 2 | V3: Will be in Agenda Review? | W3: Mnemos in group (price only) | X3: Effective String 1 | Y3: Effective String 2 | Z3: Effective String 3 | AA3: Effective String 4 | AB3: Effective String 5 | AC3: Effective String 6 | AD3: Effective String 7 | AE3: Effective String 8 | AF3: Effective String 9 | AG3: Effective String 10 | AH3: Effective String 11 | AI3: Effective String 12 | AJ3: Effective Date 1 | AK3: Effective Date 2 | AL3: Effective Date 3 | AM3: Effective Date 4 | AN3: Effective Date 5 | AO3: Effective Date 6 | AP3: Effective Date 7 | AQ3: Effective Date 8 | AR3: Effective Date 9 | AS3: Effective Date 10 | AT3: Effective Date 11 | AU3: Effective Date 12 | AV3: Effective Date 13 | AW3: Effective Date 14 | AX3: Effective Date 15 | AY3: Effective Date 16 | AZ3: Effective Date 17 | BA3: Effective Date 18 | BB3: Effective Date 19 | BC3: Effective Date 20 | BD3: Cutoff String 1 | BE3: Cutoff String 2 | BF3: Cutoff String 3 | BG3: Cutoff String 4 | BH3: Cutoff String 5 | BI3: Cutoff String 6 | BJ3: Cutoff String 7 | BK3: Cutoff String 8 | BL3: Cutoff String 9 | BM3: Cutoff String 10 | BN3: Cutoff String 11 | BO3: Cutoff String 12 | BP3: Cutoff Date 1 | BQ3: Cutoff Date 2 | BR3: Cutoff Date 3 | BS3: Cutoff Date 4 | BT3: Cutoff Date 5 | BU3: Cutoff Date 6 | BV3: Cutoff Date 7 | BW3: Cutoff Date 8 | BX3: Cutoff Date 9 | BY3: Cutoff Date 10 | BZ3: Cutoff Date 11 | CA3: Cutoff Date 12 | CB3: Announcement date 1 | CC3: Announcement date 2 | CD3: Announcement date 3 | CE3: Announcement date 4 | CF3: Announcement date 5 | CG3: Announcement date 6 | CH3: Announcement date 7 | CI3: Announcement date 8 | CJ3: Announcement date 9 | CK3: Announcement date 10 | CL3: Announcement date 11 | CM3: Announcement date 12 | CN3: Composition date 1 | CO3: Composition date 2 | CP3: Composition date 3 | CQ3: Composition date 4 | CR3: Composition date 5 | CS3: Composition date 6 | CT3: Composition date 7 | CU3: Composition date 8 | CV3: Composition date 9 | CW3: Composition date 10 | CX3: Composition date 11 | CY3: Composition date 12 | CZ3: Free float date 1 | DA3: Free float date 2 | DB3: Free float date 3 | DC3: Free float date 4 | DD3: Free float date 5 | DE3: Free float date 6 | DF3: Free float date 7 | DG3: Free float date 8 | DH3: Free float date 9 | DI3: Free float date 10 | DJ3: Free float date 11 | DK3: Free float date 12 | DL3: Effective dates in a year | DM3: Cutoff dates in year | DN3: Announcements in year | DO3: Composition dates in year | DP3: Free float start dates | DQ3: Total Dates counter | DR3: Id | DS3: Id stop | DU3: Reason why it's not in dataiku yet | DV3: Dataiku first release | DW3: Year | DX3: Month
B4: Price | C4: 1.5 AEX/CAC | D4: CAC/AEX Equal Weight | E4: 39986 | G4: 1 | H4: Third Friday of March, June, September, December | I4: Penultimate Friday of February, May, August, November | K4: 2 | L4: 3 | P4: NXTG | R4: Lex | S4: New Sheet | T4: Automatic | U4: Dataiku | V4: Yes | W4: AEXEW CACEW CLEW | X4: Third Friday of March | Y4: Third Friday of June | Z4: Third Friday of September | AA4: Third Friday of December | AJ4: 45740 | AK4: 45831 | AL4: 45922 | AM4: 46013 | BD4: Penultimate Friday of February | BE4: Penultimate Friday of May | BF4: Penultimate Friday of August | BG4: Penultimate Friday of November | BP4: 45712 | BQ4: 45803 | BR4: 45894 | BS4: 45985 | CN4: 45736 | CO4: 45827 | CP4: 45918 | CQ4: 46009 | DL4: 4 | DM4: 4 | DN4: 0 | DO4: 4 | DP4: 0 | DQ4: 12 | DR4: 112 | DV4: 44483.638 | DW4: 2021 | DX4: 10
B5: Price | C5: 1.5 AEX/CAC | D5: CAC/AEX Equal Weight | E5: 39986 | G5: 1 | H5: Third Friday of March, June, September, December | I5: Penultimate Friday of February, May, August, November | K5: 2 | L5: 3 | P5: NXTG | R5: Lex | S5: New Sheet | T5: Automatic | U5: Dataiku | V5: No | DL5: 0 | DM5: 0 | DN5: 0 | DO5: 0 | DP5: 0 | DQ5: 0 | DV5: 44483.75 | DW5: 2021 | DX5: 10
B6: Price | C6: 1.5 AEX/CAC | D6: CAC/AEX Equal Weight | E6: 42118 | G6: 1 | H6: Third Friday of March, June, September, December | I6: Penultimate Friday of February, May, August, November | K6: 2 | L6: 3 | P6: NXTG | R6: Lex | S6: New Sheet | T6: Automatic | U6: Dataiku | V6: No | DL6: 0 | DM6: 0 | DN6: 0 | DO6: 0 | DP6: 0 | DQ6: 0 | DV6: 44483.75 | DW6: 2021 | DX6: 10
B7: Price | C7: 1.5 AEX/CAC | D7: Bene40 Equal Weight | E7: 42268 | G7: 1 | H7: Third Friday of March, June, September, December | I7: Penultimate Friday of February, May, August, November | K7: 2 | L7: 3 | P7: NXTG | R7: Lex | S7: New Sheet | T7: Automatic | U7: Dataiku | V7: Yes | W7: BNEW | X7: Third Friday of March | Y7: Third Friday of June | Z7: Third Friday of September | AA7: Third Friday of December | AJ7: 45740 | AK7: 45831 | AL7: 45922 | AM7: 46013 | BD7: Penultimate Friday of February | BE7: Penultimate Friday of May | BF7: Penultimate Friday of August | BG7: Penultimate Friday of November | BP7: 45712 | BQ7: 45803 | BR7: 45894 | BS7: 45985 | CN7: 45736 | CO7: 45827 | CP7: 45918 | CQ7: 46009 | DL7: 4 | DM7: 4 | DN7: 0 | DO7: 4 | DP7: 0 | DQ7: 12 | DR7: 174 | DV7: 45520 | DW7: 2024 | DX7: 8
B8: Price | C8: 2.6 Normal index | D8: SBF 80 | E8: 42345 | G8: 1 | H8: Third Friday of March, June, September, December | I8: Penultimate Friday of February, May, August, November | K8: 2 | L8: 3 | P8: PAR | R8: Lex | S8: New Sheet | T8: Automatic | U8: Dataiku | V8: Yes | W8: SBF80 | X8: Third Friday of March | Y8: Third Friday of June | Z8: Third Friday of September | AA8: Third Friday of December | AJ8: 45740 | AK8: 45831 | AL8: 45922 | AM8: 46013 | BD8: Penultimate Friday of February | BE8: Penultimate Friday of May | BF8: Penultimate Friday of August | BG8: Penultimate Friday of November | BP8: 45712 | BQ8: 45803 | BR8: 45894 | BS8: 45985 | CN8: 45736 | CO8: 45827 | CP8: 45918 | CQ8: 46009 | DL8: 4 | DM8: 4 | DN8: 0 | DO8: 4 | DP8: 0 | DQ8: 12 | DR8: 186 | DV8: 44483.753 | DW8: 2021 | DX8: 10
B9: Price | C9: 2.6 Normal index | D9: Cac 40 Governance | E9: 42787 | G9: 1 | H9: Third Friday of March, June, September, December | I9: Penultimate Friday of February, May, August, November | K9: 2 | L9: 3 | O9: Moody's | P9: NXTG | Q9: Query rates from Vigeo Eiris rates on cut-off date | R9: Lex | S9: New Sheet | T9: Automatic | U9: Dataiku | V9: Yes | W9: CAGOV | X9: Third Friday of March | Y9: Third Friday of June | Z9: Third Friday of September | AA9: Third Friday of December | AJ9: 45740 | AK9: 45831 | AL9: 45922 | AM9: 46013 | BD9: Penultimate Friday of February | BE9: Penultimate Friday of May | BF9: Penultimate Friday of August | BG9: Penultimate Friday of November | BP9: 45712 | BQ9: 45803 | BR9: 45894 | BS9: 45985 | CN9: 45736 | CO9: 45827 | CP9: 45918 | CQ9: 46009 | DL9: 4 | DM9: 4 | DN9: 0 | DO9: 4 | DP9: 0 | DQ9: 12 | DR9: 207 | DV9: 44627.477 | DW9: 2022 | DX9: 3
B10: Price | C10: 1.6 Core | D10: Core Europe | E10: 42831 | G10: 1 | H10: Third Friday of March, June, September, December | I10: Penultimate Friday of February, May, August, November | J10: 6 | K10: 2 | L10: 3 | M10: 20 | P10: NXTG | Q10: Mother index Eurozone 300 can be used as underlying universe (not in rulebook) | R10: Amanda | S10: New Sheet | T10: Edwin | U10: Dataiku | V10: Yes | W10: EC1EW COR3P CEE3P CEE1P | X10: Third Friday of March | Y10: Third Friday of June | Z10: Third Friday of September | AA10: Third Friday of December | AJ10: 45740 | AK10: 45831 | AL10: 45922 | AM10: 46013 | BD10: Penultimate Friday of February | BE10: Penultimate Friday of May | BF10: Penultimate Friday of August | BG10: Penultimate Friday of November | BP10: 45712 | BQ10: 45803 | BR10: 45894 | BS10: 45985 | CB10: 45730 | CC10: 45821 | CD10: 45912 | CE10: 46003 | CN10: 45736 | CO10: 45827 | CP10: 45918 | CQ10: 46009 | CZ10: 45685 | DA10: 45776 | DB10: 45867 | DC10: 45958 | DL10: 4 | DM10: 4 | DN10: 4 | DO10: 4 | DP10: 4 | DQ10: 20 | DR10: 219 | DV10: 44992.583 | DW10: 2023 | DX10: 3
B11: Price | C11: 1.6 Core | D11: Core Europe | E11: 42977 | G11: 1 | H11: Third Friday of March, June, September, December | I11: Penultimate Friday of February, May, August, November | J11: 6 | K11: 2 | L11: 3 | M11: 20 | P11: NXTG | Q11: Mother index Eurozone 300 can be used as underlying universe (not in rulebook) | R11: Amanda | S11: New Sheet | T11: Edwin | U11: Dataiku | V11: No | DL11: 0 | DM11: 0 | DN11: 0 | DO11: 0 | DP11: 0 | DQ11: 0 | DV11: 44992.607 | DW11: 2023 | DX11: 3
B12: Price | C12: 1.6 Core | D12: Core Europe | E12: 43299 | G12: 1 | H12: Third Friday of March, June, September, December | I12: Penultimate Friday of February, May, August, November | J12: 6 | K12: 2 | L12: 3 | M12: 20 | O12: Moody's | P12: NXTG | Q12: Mother index Eurozone 300 can be used as underlying universe (not in rulebook) | R12: Amanda | S12: New Sheet | T12: Edwin | U12: Dataiku | V12: No | DL12: 0 | DM12: 0 | DN12: 0 | DO12: 0 | DP12: 0 | DQ12: 0 | DV12: 45084.603 | DW12: 2023 | DX12: 6
B13: Price | C13: 2.6 Normal index | D13: France German Leaders 50 EW | E13: 42909 | G13: 2 | H13: Third Friday of March, June, September, December | I13: Penultimate Friday of February, May, August, November | K13: 2 | L13: 3 | P13: NXTG | Q13: Mother index Eurozone 300 can be used as underlying (not in rulebook). Review spread over 2 days. | R13: Amanda | S13: New Sheet | T13: Automatic | U13: Dataiku | V13: Yes | W13: EFGEW | X13: Third Friday of March | Y13: Third Friday of June | Z13: Third Friday of September | AA13: Third Friday of December | AJ13: 45740 | AK13: 45741 | AL13: 45831 | AM13: 45832 | AN13: 45922 | AO13: 45923 | AP13: 46013 | AQ13: 46014 | BD13: Penultimate Friday of February | BE13: Penultimate Friday of May | BF13: Penultimate Friday of August | BG13: Penultimate Friday of November | BP13: 45712 | BQ13: 45803 | BR13: 45894 | BS13: 45985 | CN13: 45736 | CO13: 45827 | CP13: 45918 | CQ13: 46009 | DL13: 8 | DM13: 4 | DN13: 0 | DO13: 4 | DP13: 0 | DQ13: 16 | DR13: 255 | DV13: 44483.753 | DW13: 2021 | DX13: 10
B14: Price | C14: 2.6 Normal index | D14: France German Leaders 50 | E14: 43049 | G14: 1 | H14: Third Friday of March, June, September, December | I14: Penultimate Friday of February, May, August, November | K14: 2 | L14: 2 | P14: NXTG | Q14: Mother index Eurozone 300 can be used as underlying (not in rulebook). Review spread over 2 days. | R14: Amanda | S14: New Sheet | T14: Automatic | U14: Dataiku | V14: Yes | W14: EFGP | X14: Third Friday of March | Y14: Third Friday of June | Z14: Third Friday of September | AA14: Third Friday of December | AJ14: 45740 | AK14: 45831 | AL14: 45922 | AM14: 46013 | BD14: Penultimate Friday of February | BE14: Penultimate Friday of May | BF14: Penultimate Friday of August | BG14: Penultimate Friday of November | BP14: 45712 | BQ14: 45803 | BR14: 45894 | BS14: 45985 | CN14: 45736 | CO14: 45827 | CP14: 45918 | CQ14: 46009 | DL14: 4 | DM14: 4 | DN14: 0 | DO14: 4 | DP14: 0 | DQ14: 12 | DR14: 307 | DV14: 44627.447 | DW14: 2022 | DX14: 3
B15: Price | C15: 1.8 Eurozone | D15: Eurozone 40 EW | E15: 43115 | G15: 1 | H15: Third Friday of March, June, September, December | I15: Penultimate Friday of February, May, August, November | K15: 2 | L15: 3 | P15: NXTG | Q15: Underlying universe is mother index Eurozone 300 | R15: Anna | S15: New Sheet | T15: Automatic | U15: Dataiku | V15: Yes | W15: EZ40P | X15: Third Friday of March | Y15: Third Friday of June | Z15: Third Friday of September | AA15: Third Friday of December | AJ15: 45740 | AK15: 45831 | AL15: 45922 | AM15: 46013 | BD15: Penultimate Friday of February | BE15: Penultimate Friday of May | BF15: Penultimate Friday of August | BG15: Penultimate Friday of November | BP15: 45712 | BQ15: 45803 | BR15: 45894 | BS15: 45985 | CN15: 45736 | CO15: 45827 | CP15: 45918 | CQ15: 46009 | DL15: 4 | DM15: 4 | DN15: 0 | DO15: 4 | DP15: 0 | DQ15: 12 | DR15: 319 | DV15: 44483.751 | DW15: 2021 | DX15: 10
B16: Price | C16: 1.8 Eurozone | D16: Eurozone 2 | E16: 43217 | F16: 45699 | G16: 1 | H16: Third Friday of March, June, September, December | I16: Penultimate Friday of February, May, August, November | K16: 2 | L16: 3 | P16: NXTG | Q16: Underlying universe is mother index Eurozone 300 | R16: Anna | S16: New Sheet | T16: Automatic | U16: Dataiku | V16: No | DL16: 0 | DM16: 0 | DN16: 0 | DO16: 0 | DP16: 0 | DQ16: 0 | DV16: 44483.751 | DW16: 2021 | DX16: 10
B17: Price | C17: 2.6 Normal index | D17: Founding Members | E17: 43115 | G17: 1 | H17: Third Friday of March, June, September, December | I17: Penultimate Friday of February, May, August, November | K17: 2 | L17: 3 | P17: NXTG | Q17: Mother index Eurozone 300 can be used as underlying (not in rulebook) | R17: Ginevra | S17: New Sheet | T17: Automatic | U17: Dataiku | V17: Yes | W17: EFMEP | X17: Third Friday of March | Y17: Third Friday of June | Z17: Third Friday of September | AA17: Third Friday of December | AJ17: 45740 | AK17: 45831 | AL17: 45922 | AM17: 46013 | BD17: Penultimate Friday of February | BE17: Penultimate Friday of May | BF17: Penultimate Friday of August | BG17: Penultimate Friday of November | BP17: 45712 | BQ17: 45803 | BR17: 45894 | BS17: 45985 | CN17: 45736 | CO17: 45827 | CP17: 45918 | CQ17: 46009 | DL17: 4 | DM17: 4 | DN17: 0 | DO17: 4 | DP17: 0 | DQ17: 12 | DR17: 331 | DV17: 44483.752 | DW17: 2021 | DX17: 10
B18: Price | C18: 2.6 Normal index | D18: Europe Sustainable 100 | E18: 43154 | G18: 1 | H18: Third Friday of March, June, September, December | I18: Penultimate Friday of February, May, August, November | K18: 2 | L18: 3 | O18: Moody's | P18: NXTG | Q18: Underlying is mother index Europe 500 | R18: Ken | S18: New Sheet | T18: Automatic | U18: Dataiku | V18: Yes | W18: ES1EP | X18: Third Friday of March | Y18: Third Friday of June | Z18: Third Friday of September | AA18: Third Friday of December | AJ18: 45740 | AK18: 45831 | AL18: 45922 | AM18: 46013 | BD18: Penultimate Friday of February | BE18: Penultimate Friday of May | BF18: Penultimate Friday of August | BG18: Penultimate Friday of November | BP18: 45712 | BQ18: 45803 | BR18: 45894 | BS18: 45985 | CN18: 45736 | CO18: 45827 | CP18: 45918 | CQ18: 46009 | DL18: 4 | DM18: 4 | DN18: 0 | DO18: 4 | DP18: 0 | DQ18: 12 | DR18: 355 | DV18: 45061.624 | DW18: 2023 | DX18: 5
B19: Price | C19: 2.6 Normal index | D19: Eurozone Energy Transition Leaders 50 | E19: 43154 | G19: 1 | H19: Second Friday of January, April, July, October | I19: Penultimate Friday of February, May, August, November | K19: 2 | L19: 3 | O19: Moody's | P19: NXTG | Q19: Underlying universe is mother index Eurozone 300 | R19: Anna | S19: New Sheet | T19: Automatic | U19: Dataiku | V19: Yes | W19: CLE5P | X19: Second Friday of January | Y19: Second Friday of April | Z19: Second Friday of July | AA19: Second Friday of October | AJ19: 45670 | AK19: 45761 | AL19: 45852 | AM19: 45943 | BD19: Penultimate Friday of February | BE19: Penultimate Friday of May | BF19: Penultimate Friday of August | BG19: Penultimate Friday of November | BP19: 45712 | BQ19: 45803 | BR19: 45894 | BS19: 45985 | CN19: 45666 | CO19: 45757 | CP19: 45848 | CQ19: 45939 | DL19: 4 | DM19: 4 | DN19: 0 | DO19: 4 | DP19: 0 | DQ19: 12 | DR19: 367 | DV19: 44483.752 | DW19: 2021 | DX19: 10
B20: Price | C20: 2.5 ESG Leaders | D20: Eurozone ESG Leaders 40 | E20: 43154 | G20: 2 | H20: Third Friday of March, June, September, December | I20: Penultimate Friday of February, May, August, November | K20: 2 | L20: 3 | O20: Moody's | P20: NXTG | Q20: Underlying universe is mother index Eurozone 300. Review spread over 2 days. | R20: Lex | S20: New Sheet | T20: Automatic | U20: Dataiku | V20: Yes | W20: ESE4P | X20: Third Friday of March | Y20: Third Friday of June | Z20: Third Friday of September | AA20: Third Friday of December | AJ20: 45740 | AK20: 45741 | AL20: 45831 | AM20: 45832 | AN20: 45922 | AO20: 45923 | AP20: 46013 | AQ20: 46014 | BD20: Penultimate Friday of February | BE20: Penultimate Friday of May | BF20: Penultimate Friday of August | BG20: Penultimate Friday of November | BP20: 45712 | BQ20: 45803 | BR20: 45894 | BS20: 45985 | CN20: 45736 | CO20: 45827 | CP20: 45918 | CQ20: 46009 | DL20: 8 | DM20: 4 | DN20: 0 | DO20: 4 | DP20: 0 | DQ20: 16 | DR20: 379 | DV20: 44483.752 | DW20: 2021 | DX20: 10
B21: Price | C21: 2.6 Normal index | D21: France Energy Transition Leaders 40 | E21: 43154 | G21: 1 | H21: Third Friday of March, June, September, December | I21: Penultimate Friday of February, May, August, November | K21: 2 | L21: 3 | O21: Moody's | P21: NXTG | R21: Anna | S21: New Sheet | T21: Automatic | U21: Dataiku | V21: Yes | W21: CLF4P | X21: Third Friday of March | Y21: Third Friday of June | Z21: Third Friday of September | AA21: Third Friday of December | AJ21: 45740 | AK21: 45831 | AL21: 45922 | AM21: 46013 | BD21: Penultimate Friday of February | BE21: Penultimate Friday of May | BF21: Penultimate Friday of August | BG21: Penultimate Friday of November | BP21: 45712 | BQ21: 45803 | BR21: 45894 | BS21: 45985 | CN21: 45736 | CO21: 45827 | CP21: 45918 | CQ21: 46009 | DL21: 4 | DM21: 4 | DN21: 0 | DO21: 4 | DP21: 0 | DQ21: 12 | DR21: 395 | DV21: 44483.752 | DW21: 2021 | DX21: 10
B22: Price | C22: 2.5 ESG Leaders | D22: France ESG Leaders 40 | E22: 43154 | G22: 1 | H22: Third Friday of March, June, September, December | I22: Penultimate Friday of February, May, August, November | K22: 2 | L22: 3 | O22: Moody's | P22: NXTG | R22: Lex | S22: New Sheet | T22: Automatic | U22: Dataiku | V22: Yes | W22: ESF4P | X22: Third Friday of March | Y22: Third Friday of June | Z22: Third Friday of September | AA22: Third Friday of December | AJ22: 45740 | AK22: 45831 | AL22: 45922 | AM22: 46013 | BD22: Penultimate Friday of February | BE22: Penultimate Friday of May | BF22: Penultimate Friday of August | BG22: Penultimate Friday of November | BP22: 45712 | BQ22: 45803 | BR22: 45894 | BS22: 45985 | CN22: 45736 | CO22: 45827 | CP22: 45918 | CQ22: 46009 | DL22: 4 | DM22: 4 | DN22: 0 | DO22: 4 | DP22: 0 | DQ22: 12 | DR22: 407 | DV22: 44483.752 | DW22: 2021 | DX22: 10
B23: Price | C23: 2.6 Normal index | D23: Euronext ESG Euro 50 | E23: 43193 | G23: 1 | H23: Third Friday of March, June, September, December | I23: Penultimate Friday of February, May, August, November | K23: 2 | L23: 3 | O23: Moody's | P23: NXTG | Q23: Underlying universe is mother index Eurozone 300, Vigeo Eiris is providing the ESG scores | R23: Anna | S23: New Sheet | T23: Automatic | U23: Dataiku | V23: Yes | W23: ESG50 | X23: Third Friday of March | Y23: Third Friday of June | Z23: Third Friday of September | AA23: Third Friday of December | AJ23: 45740 | AK23: 45831 | AL23: 45922 | AM23: 46013 | BD23: Penultimate Friday of February | BE23: Penultimate Friday of May | BF23: Penultimate Friday of August | BG23: Penultimate Friday of November | BP23: 45712 | BQ23: 45803 | BR23: 45894 | BS23: 45985 | CN23: 45736 | CO23: 45827 | CP23: 45918 | CQ23: 46009 | DL23: 4 | DM23: 4 | DN23: 0 | DO23: 4 | DP23: 0 | DQ23: 12 | DR23: 419 | DV23: 44483.75 | DW23: 2021 | DX23: 10
B24: Price | C24: 2.6 Normal index | D24: France Eurozone 60 | E24: 43217 | F24: 45699 | G24: 1 | H24: Third Friday of March, June, September, December | I24: Penultimate Friday of February, May, August, November | K24: 2 | L24: 3 | P24: NXTG | Q24: Underlying universe is mother index Eurozone 300 | R24: Lex | S24: New Sheet | T24: Automatic | U24: Dataiku | V24: No | DL24: 0 | DM24: 0 | DN24: 0 | DO24: 0 | DP24: 0 | DQ24: 0 | DV24: 44483.752 | DW24: 2021 | DX24: 10
B25: Price | C25: 1.8 Eurozone | D25: Eurozone | E25: 43257 | G25: 1 | H25: Third Friday of March, June, September, December | I25: Penultimate Friday of February, May, August, November | K25: 2 | L25: 3 | P25: NXTG | Q25: Underlying universe is mother index Eurozone 300 | R25: Anna | S25: New Sheet | T25: Automatic | U25: Dataiku | V25: Yes | W25: EZ15P EZN1P | X25: Third Friday of March | Y25: Third Friday of June | Z25: Third Friday of September | AA25: Third Friday of December | AJ25: 45740 | AK25: 45831 | AL25: 45922 | AM25: 46013 | BD25: Penultimate Friday of February | BE25: Penultimate Friday of May | BF25: Penultimate Friday of August | BG25: Penultimate Friday of November | BP25: 45712 | BQ25: 45803 | BR25: 45894 | BS25: 45985 | CN25: 45736 | CO25: 45827 | CP25: 45918 | CQ25: 46009 | DL25: 4 | DM25: 4 | DN25: 0 | DO25: 4 | DP25: 0 | DQ25: 12 | DR25: 431 | DV25: 44483.751 | DW25: 2021 | DX25: 10
B26: Price | C26: 1.8 Eurozone | D26: Eurozone | E26: 43257 | G26: 1 | H26: Third Friday of March, June, September, December | I26: Penultimate Friday of February, May, August, November | K26: 2 | L26: 3 | P26: NXTG | Q26: Underlying universe is mother index Eurozone 300 | R26: Anna | S26: New Sheet | T26: Automatic | U26: Dataiku | V26: No | DL26: 0 | DM26: 0 | DN26: 0 | DO26: 0 | DP26: 0 | DQ26: 0 | DV26: 44483.752 | DW26: 2021 | DX26: 10
B27: Price | C27: 1.8 Eurozone | D27: Eurozone | E27: 43264 | F27: 45520 | G27: 1 | H27: Third Friday of March, June, September, December | I27: Penultimate Friday of February, May, August, November | K27: 2 | L27: 3 | P27: NXTG | Q27: Underlying universe is mother index Eurozone 300 | R27: Anna | S27: New Sheet | T27: Automatic | U27: Dataiku | V27: No | DL27: 0 | DM27: 0 | DN27: 0 | DO27: 0 | DP27: 0 | DQ27: 0 | DV27: #N/A | DW27: #N/A | DX27: #N/A
B28: Price | C28: 1.8 Eurozone | D28: Eurozone | E28: 43285 | F28: 45520 | G28: 1 | H28: Third Friday of March, June, September, December | I28: Penultimate Friday of February, May, August, November | K28: 2 | L28: 3 | P28: NXTG | Q28: Underlying universe is mother index Eurozone 300 | R28: Anna | S28: New Sheet | T28: Automatic | U28: Dataiku | V28: No | DL28: 0 | DM28: 0 | DN28: 0 | DO28: 0 | DP28: 0 | DQ28: 0 | DV28: #N/A | DW28: #N/A | DX28: #N/A
B29: Price | C29: 1.8 Eurozone | D29: Eurozone | E29: 43292 | F29: 45699 | G29: 1 | H29: Third Friday of March, June, September, December | I29: Penultimate Friday of February, May, August, November | K29: 2 | L29: 3 | P29: NXTG | Q29: Underlying universe is mother index Eurozone 300 | R29: Anna | S29: New Sheet | T29: Automatic | U29: Dataiku | V29: No | DL29: 0 | DM29: 0 | DN29: 0 | DO29: 0 | DP29: 0 | DQ29: 0 | DV29: 44483.752 | DW29: 2021 | DX29: 10
B30: Price | C30: 2.0 CDP | D30: CDP Environment France | E30: 43271 | G30: 5 | H30: Third Friday of March, June, September, December | I30: Penultimate Friday of February, May, August, November | J30: 6 | K30: 2 | L30: 3 | O30: CDP | P30: NXTG | Q30: CDP provides CDP score; annual review in March. Only Review Announcement at Annual. | R30: Ken | S30: New Sheet | T30: Automatic | U30: Dataiku | V30: Yes | W30: FRENP | X30: Third Friday of March | Y30: Third Friday of June | Z30: Third Friday of September | AA30: Third Friday of December | AJ30: 45740 | AK30: 45741 | AL30: 45742 | AM30: 45743 | AN30: 45744 | AO30: 45831 | AP30: 45832 | AQ30: 45833 | AR30: 45834 | AS30: 45835 | AT30: 45922 | AU30: 45923 | AV30: 45924 | AW30: 45925 | AX30: 45926 | AY30: 46013 | AZ30: 46014 | BA30: 46015 | BB30: 46017 | BC30: 46020 | BD30: Penultimate Friday of February | BE30: Penultimate Friday of May | BF30: Penultimate Friday of August | BG30: Penultimate Friday of November | BP30: 45712 | BQ30: 45803 | BR30: 45894 | BS30: 45985 | CB30: 45730 | CC30: 45821 | CD30: 45912 | CE30: 46003 | CN30: 45736 | CO30: 45827 | CP30: 45918 | CQ30: 46009 | DL30: 20 | DM30: 4 | DN30: 4 | DO30: 4 | DP30: 0 | DQ30: 32 | DR30: 455 | DV30: 44610.309 | DW30: 2022 | DX30: 2
B31: Price | C31: 2.6 Normal index | D31: Eurozone 100 ESG | E31: 43278 | G31: 1 | H31: Third Friday of March, June, September, December | I31: Penultimate Friday of February, May, August, November | K31: 2 | L31: 3 | O31: Moody's | P31: NXTG | Q31: Underlying universe is mother index Eurozone 300, ESG scores provided | R31: Ken | S31: New Sheet | T31: Automatic | U31: Dataiku | V31: Yes | W31: ESG1P | X31: Third Friday of March | Y31: Third Friday of June | Z31: Third Friday of September | AA31: Third Friday of December | AJ31: 45740 | AK31: 45831 | AL31: 45922 | AM31: 46013 | BD31: Penultimate Friday of February | BE31: Penultimate Friday of May | BF31: Penultimate Friday of August | BG31: Penultimate Friday of November | BP31: 45712 | BQ31: 45803 | BR31: 45894 | BS31: 45985 | CN31: 45736 | CO31: 45827 | CP31: 45918 | CQ31: 46009 | DL31: 4 | DM31: 4 | DN31: 0 | DO31: 4 | DP31: 0 | DQ31: 12 | DR31: 487 | DV31: 44687 | DW31: 2022 | DX31: 5
B32: Price | C32: 2.6 Normal index | D32: Euronext France 20-40 Challengers | E32: 43299 | G32: 1 | H32: Third Friday of March, June, September, December | I32: Penultimate Friday of February, May, August, November | K32: 2 | L32: 3 | P32: NXTG | R32: Lex | S32: New Sheet | T32: Automatic | U32: Dataiku | V32: Yes | W32: FRECP | X32: Third Friday of March | Y32: Third Friday of June | Z32: Third Friday of September | AA32: Third Friday of December | AJ32: 45740 | AK32: 45831 | AL32: 45922 | AM32: 46013 | BD32: Penultimate Friday of February | BE32: Penultimate Friday of May | BF32: Penultimate Friday of August | BG32: Penultimate Friday of November | BP32: 45712 | BQ32: 45803 | BR32: 45894 | BS32: 45985 | CN32: 45736 | CO32: 45827 | CP32: 45918 | CQ32: 46009 | DL32: 4 | DM32: 4 | DN32: 0 | DO32: 4 | DP32: 0 | DQ32: 12 | DR32: 515 | DV32: 44483.752 | DW32: 2021 | DX32: 10
B33: Price | C33: 2.6 Normal index | D33: France Next 40 | E33: 43327 | G33: 1 | H33: Third Friday of March, June, September, December | I33: Penultimate Friday of February, May, August, November | K33: 2 | L33: 3 | P33: NXTG | Q33: Selection out of SBF120 | R33: Lex | S33: New Sheet | T33: Automatic | U33: Dataiku | V33: Yes | W33: FRN4P | X33: Third Friday of March | Y33: Third Friday of June | Z33: Third Friday of September | AA33: Third Friday of December | AJ33: 45740 | AK33: 45831 | AL33: 45922 | AM33: 46013 | BD33: Penultimate Friday of February | BE33: Penultimate Friday of May | BF33: Penultimate Friday of August | BG33: Penultimate Friday of November | BP33: 45712 | BQ33: 45803 | BR33: 45894 | BS33: 45985 | CN33: 45736 | CO33: 45827 | CP33: 45918 | CQ33: 46009 | DL33: 4 | DM33: 4 | DN33: 0 | DO33: 4 | DP33: 0 | DQ33: 12 | DR33: 527 | DV33: 44483.753 | DW33: 2021 | DX33: 10
B34: Price | C34: 2.6 Normal index | D34: France 20 | E34: 43334 | G34: 1 | H34: Third Friday of March, June, September, December | I34: Penultimate Friday of February, May, August, November | K34: 2 | L34: 3 | P34: NXTG | Q34: Selection out of CAC40 | R34: Lex | S34: New Sheet | T34: Automatic | U34: Dataiku | V34: Yes | W34: FR20P | X34: Third Friday of March | Y34: Third Friday of June | Z34: Third Friday of September | AA34: Third Friday of December | AJ34: 45740 | AK34: 45831 | AL34: 45922 | AM34: 46013 | BD34: Penultimate Friday of February | BE34: Penultimate Friday of May | BF34: Penultimate Friday of August | BG34: Penultimate Friday of November | BP34: 45712 | BQ34: 45803 | BR34: 45894 | BS34: 45985 | CN34: 45736 | CO34: 45827 | CP34: 45918 | CQ34: 46009 | DL34: 4 | DM34: 4 | DN34: 0 | DO34: 4 | DP34: 0 | DQ34: 12 | DR34: 539 | DV34: 44483.752 | DW34: 2021 | DX34: 10
B35: Price | C35: 2.0 CDP | D35: CDP Environ. France ex Oil & Gas | E35: 43341 | G35: 1 | H35: Third Friday of March, June, September, December | I35: Penultimate Friday of February, May, August, November | J35: 6 | K35: 2 | L35: 3 | O35: CDP | P35: NXTG | Q35: CDP provides CDP score; annual review in March. Only Review Announcement at Annual. | R35: Ken | S35: New Sheet | T35: Automatic | U35: Dataiku | V35: Yes | W35: FREEP | X35: Third Friday of March | Y35: Third Friday of June | Z35: Third Friday of September | AA35: Third Friday of December | AJ35: 45740 | AK35: 45831 | AL35: 45922 | AM35: 46013 | BD35: Penultimate Friday of February | BE35: Penultimate Friday of May | BF35: Penultimate Friday of August | BG35: Penultimate Friday of November | BP35: 45712 | BQ35: 45803 | BR35: 45894 | BS35: 45985 | CB35: 45730 | CC35: 45821 | CD35: 45912 | CE35: 46003 | CN35: 45736 | CO35: 45827 | CP35: 45918 | CQ35: 46009 | DL35: 4 | DM35: 4 | DN35: 4 | DO35: 4 | DP35: 0 | DQ35: 16 | DR35: 551 | DV35: 44610.311 | DW35: 2022 | DX35: 2
B36: Price | C36: 2.6 Normal index | D36: SBF Top 50 ESG | E36: 43390 | G36: 1 | H36: Third Friday of March, June, September, December | I36: Penultimate Friday of February, May, August, November | K36: 2 | L36: 3 | O36: Moody's | P36: NXTG | Q36: Underlying is the SBF120 | R36: Lex | S36: New Sheet | T36: Automatic | U36: Dataiku | V36: Yes | W36: ESF5P | X36: Third Friday of March | Y36: Third Friday of June | Z36: Third Friday of September | AA36: Third Friday of December | AJ36: 45740 | AK36: 45831 | AL36: 45922 | AM36: 46013 | BD36: Penultimate Friday of February | BE36: Penultimate Friday of May | BF36: Penultimate Friday of August | BG36: Penultimate Friday of November | BP36: 45712 | BQ36: 45803 | BR36: 45894 | BS36: 45985 | CN36: 45736 | CO36: 45827 | CP36: 45918 | CQ36: 46009 | DL36: 4 | DM36: 4 | DN36: 0 | DO36: 4 | DP36: 0 | DQ36: 12 | DR36: 567 | DV36: 44483.753 | DW36: 2021 | DX36: 10
B37: Price | C37: 2.2 Responsible Investment | D37: Responsible Investment CAC Large 60 | E37: 43411 | G37: 1 | H37: Third Friday of March, June, September, December | I37: Penultimate Friday of February, May, August, November | K37: 2 | L37: 3 | O37: ISS ESG | P37: NXTG | Q37: Underlying is CAC40 and Large 60 | R37: Anna | S37: New Sheet | T37: Automatic | U37: Dataiku | V37: Yes | W37: C6RIP | X37: Third Friday of March | Y37: Third Friday of June | Z37: Third Friday of September | AA37: Third Friday of December | AJ37: 45740 | AK37: 45831 | AL37: 45922 | AM37: 46013 | BD37: Penultimate Friday of February | BE37: Penultimate Friday of May | BF37: Penultimate Friday of August | BG37: Penultimate Friday of November | BP37: 45712 | BQ37: 45803 | BR37: 45894 | BS37: 45985 | CN37: 45736 | CO37: 45827 | CP37: 45918 | CQ37: 46009 | DL37: 4 | DM37: 4 | DN37: 0 | DO37: 4 | DP37: 0 | DQ37: 12 | DR37: 579 | DV37: 44483.75 | DW37: 2021 | DX37: 10
B38: Price | C38: 2.2 Responsible Investment | D38: Responsible Investment Euronext France 40 | E38: 43411 | G38: 1 | H38: Third Friday of March, June, September, December | I38: Penultimate Friday of February, May, August, November | K38: 2 | L38: 3 | O38: ISS ESG | P38: NXTG | Q38: Underlying is CAC40 and Large 60 | R38: Anna | S38: New Sheet | T38: Automatic | U38: Dataiku | V38: Yes | W38: F4RIP | X38: Third Friday of March | Y38: Third Friday of June | Z38: Third Friday of September | AA38: Third Friday of December | AJ38: 45740 | AK38: 45831 | AL38: 45922 | AM38: 46013 | BD38: Penultimate Friday of February | BE38: Penultimate Friday of May | BF38: Penultimate Friday of August | BG38: Penultimate Friday of November | BP38: 45712 | BQ38: 45803 | BR38: 45894 | BS38: 45985 | CN38: 45736 | CO38: 45827 | CP38: 45918 | CQ38: 46009 | DL38: 4 | DM38: 4 | DN38: 0 | DO38: 4 | DP38: 0 | DQ38: 12 | DR38: 591 | DV38: 44483.75 | DW38: 2021 | DX38: 10
B39: Price | C39: 2.6 Normal index | D39: Transatlantic 50 EW | E39: 43418 | G39: 1 | H39: Third Friday of March, June, September, December | I39: Penultimate Friday of February, May, August, November | K39: 2 | L39: 3 | P39: EUS5P | Q39: Underlying universe is mother index Eurozone 300 + 50 largest FF Mcap US; Composition to be announced on Wednesday on base of Tuesday close | R39: Amanda | S39: New Sheet | T39: Automatic | U39: Dataiku | V39: Yes | W39: EUS5P | X39: Third Friday of March | Y39: Third Friday of June | Z39: Third Friday of September | AA39: Third Friday of December | AJ39: 45740 | AK39: 45831 | AL39: 45922 | AM39: 46013 | BD39: Penultimate Friday of February | BE39: Penultimate Friday of May | BF39: Penultimate Friday of August | BG39: Penultimate Friday of November | BP39: 45712 | BQ39: 45803 | BR39: 45894 | BS39: 45985 | CN39: 45736 | CO39: 45827 | CP39: 45918 | CQ39: 46009 | DL39: 4 | DM39: 4 | DN39: 0 | DO39: 4 | DP39: 0 | DQ39: 12 | DR39: 603 | DV39: 44483.753 | DW39: 2021 | DX39: 10
B40: Price | C40: 2.2 Responsible Investment | D40: Responsible Investment Euro 50 | E40: 43439 | G40: 1 | H40: Third Friday of March, June, September, December | I40: Penultimate Friday of February, May, August, November | K40: 2 | L40: 3 | O40: ISS ESG | P40: NXTG | Q40: Underlying universe is mother index Eurozone 300 | R40: Anna | S40: New Sheet | T40: Automatic | U40: Dataiku | V40: Yes | W40: ERI5P | X40: Third Friday of March | Y40: Third Friday of June | Z40: Third Friday of September | AA40: Third Friday of December | AJ40: 45740 | AK40: 45831 | AL40: 45922 | AM40: 46013 | BD40: Penultimate Friday of February | BE40: Penultimate Friday of May | BF40: Penultimate Friday of August | BG40: Penultimate Friday of November | BP40: 45712 | BQ40: 45803 | BR40: 45894 | BS40: 45985 | CN40: 45736 | CO40: 45827 | CP40: 45918 | CQ40: 46009 | DL40: 4 | DM40: 4 | DN40: 0 | DO40: 4 | DP40: 0 | DQ40: 12 | DR40: 615 | DV40: 44610.31 | DW40: 2022 | DX40: 2
B41: Price | C41: 2.0 CDP | D41: CDP Environment Eurozone | E41: 43518 | G41: 1 | H41: Third Friday of March, June, September, December | I41: Penultimate Friday of February, May, August, November | J41: 6 | K41: 2 | L41: 3 | O41: CDP | P41: NXTG | Q41: Underlying Universe in Mother index Eurozone 300; CDP provides CDP score; annual review in March. Only Review Announcement at Annual. | R41: Ken | S41: New Sheet | T41: Automatic | U41: Dataiku | V41: Yes | W41: EZENP | X41: Third Friday of March | Y41: Third Friday of June | Z41: Third Friday of September | AA41: Third Friday of December | AJ41: 45740 | AK41: 45831 | AL41: 45922 | AM41: 46013 | BD41: Penultimate Friday of February | BE41: Penultimate Friday of May | BF41: Penultimate Friday of August | BG41: Penultimate Friday of November | BP41: 45712 | BQ41: 45803 | BR41: 45894 | BS41: 45985 | CB41: 45730 | CC41: 45821 | CD41: 45912 | CE41: 46003 | CN41: 45736 | CO41: 45827 | CP41: 45918 | CQ41: 46009 | DL41: 4 | DM41: 4 | DN41: 4 | DO41: 4 | DP41: 0 | DQ41: 16 | DR41: 691 | DV41: 44610.311 | DW41: 2022 | DX41: 2
B42: Price | C42: 2.0 CDP | D42: CDP Environment World | E42: 43518 | G42: 1 | H42: Third Friday of March, June, September, December | I42: Penultimate Friday of February, May, August, November | J42: 6 | K42: 2 | L42: 3 | O42: CDP | P42: CUSTOM | Q42: CDP provides CDP score; annual review in March. US index, review composition sent out +1 (Thursday morning instead of Wednesday night). Only Review Announcement at Annual. | R42: Ken | S42: New Sheet | T42: Automatic | U42: Dataiku | V42: Yes | W42: WLENP | X42: Third Friday of March | Y42: Third Friday of June | Z42: Third Friday of September | AA42: Third Friday of December | AJ42: 45740 | AK42: 45831 | AL42: 45922 | AM42: 46013 | BD42: Penultimate Friday of February | BE42: Penultimate Friday of May | BF42: Penultimate Friday of August | BG42: Penultimate Friday of November | BP42: 45712 | BQ42: 45803 | BR42: 45894 | BS42: 45985 | CB42: 45730 | CC42: 45821 | CD42: 45912 | CE42: 46003 | CN42: 45736 | CO42: 45827 | CP42: 45918 | CQ42: 46009 | DL42: 4 | DM42: 4 | DN42: 4 | DO42: 4 | DP42: 0 | DQ42: 16 | DR42: 707 | DV42: 44761.329 | DW42: 2022 | DX42: 7
B43: Price | C43: 2.6 Normal index | D43: Euro 50 Social Governance | E43: 43523 | F43: 45664 | G43: 1 | H43: Third Friday of March, June, September, December | I43: Penultimate Friday of February, May, August, November | K43: 2 | L43: 3 | O43: Moody's | P43: NXTG | Q43: Underlying is Mother Index Eurozone 300 | R43: Amanda | S43: New Sheet | T43: Automatic | U43: Dataiku | V43: No | DL43: 0 | DM43: 0 | DN43: 0 | DO43: 0 | DP43: 0 | DQ43: 0 | DV43: 44483.751 | DW43: 2021 | DX43: 10
B44: Price | C44: 2.0 CDP | D44: Euronext CDP Environment ESG World | E44: 43733 | G44: 1 | H44: Third Friday of March, June, September, December | I44: Penultimate Friday of February, May, August, November | J44: 6 | K44: 2 | L44: 3 | O44: CDP;Moody's | P44: CUSTOM | Q44: CDP provides CDP score; annual review in March. US index, review composition sent out +1 (Thursday morning instead of Wednesday night). Only Review Announcement at Annual. | R44: Ken | S44: New Sheet | T44: Automatic | U44: Dataiku | V44: Yes | W44: WESGP | X44: Third Friday of March | Y44: Third Friday of June | Z44: Third Friday of September | AA44: Third Friday of December | AJ44: 45740 | AK44: 45831 | AL44: 45922 | AM44: 46013 | BD44: Penultimate Friday of February | BE44: Penultimate Friday of May | BF44: Penultimate Friday of August | BG44: Penultimate Friday of November | BP44: 45712 | BQ44: 45803 | BR44: 45894 | BS44: 45985 | CB44: 45730 | CC44: 45821 | CD44: 45912 | CE44: 46003 | CN44: 45736 | CO44: 45827 | CP44: 45918 | CQ44: 46009 | DL44: 4 | DM44: 4 | DN44: 4 | DO44: 4 | DP44: 0 | DQ44: 16 | DR44: 735 | DV44: 44761.34 | DW44: 2022 | DX44: 7
B45: Price | C45: 2.5 ESG Leaders | D45: Euronext Transatlantic ESG Leaders 60 | E45: 43733 | G45: 3 | H45: Third Friday of March, June, September, December | I45: Penultimate Friday of February, May, August, November | K45: 2 | L45: 3 | O45: Moody's | P45: CUSTOM | Q45: 3 day upload! | R45: Martijn | S45: New Sheet | T45: Automatic | U45: Dataiku | V45: Yes | W45: ESGTP | X45: Third Friday of March | Y45: Third Friday of June | Z45: Third Friday of September | AA45: Third Friday of December | AJ45: 45740 | AK45: 45741 | AL45: 45742 | AM45: 45831 | AN45: 45832 | AO45: 45833 | AP45: 45922 | AQ45: 45923 | AR45: 45924 | AS45: 46013 | AT45: 46014 | AU45: 46015 | BD45: Penultimate Friday of February | BE45: Penultimate Friday of May | BF45: Penultimate Friday of August | BG45: Penultimate Friday of November | BP45: 45712 | BQ45: 45803 | BR45: 45894 | BS45: 45985 | CN45: 45736 | CO45: 45827 | CP45: 45918 | CQ45: 46009 | DL45: 12 | DM45: 4 | DN45: 0 | DO45: 4 | DP45: 0 | DQ45: 20 | DR45: 751 | DV45: 44664.601 | DW45: 2022 | DX45: 4
B46: Price | C46: 2.0 CDP | D46: Euronext CDP Environment ESG Eurozone EW | E46: 43740 | G46: 1 | H46: Third Friday of March, June, September, December | I46: Penultimate Friday of February, May, August, November | J46: 6 | K46: 2 | L46: 3 | O46: CDP;Moody's | P46: NXTG | Q46: Underlying Universe in Mother index Eurozone 300; CDP provides CDP score; annual review in March. Only Review Announcement at Annual. | R46: Ken | S46: New Sheet | T46: Automatic | U46: Dataiku | V46: Yes | W46: EESGP | X46: Third Friday of March | Y46: Third Friday of June | Z46: Third Friday of September | AA46: Third Friday of December | AJ46: 45740 | AK46: 45831 | AL46: 45922 | AM46: 46013 | BD46: Penultimate Friday of February | BE46: Penultimate Friday of May | BF46: Penultimate Friday of August | BG46: Penultimate Friday of November | BP46: 45712 | BQ46: 45803 | BR46: 45894 | BS46: 45985 | CB46: 45730 | CC46: 45821 | CD46: 45912 | CE46: 46003 | CN46: 45736 | CO46: 45827 | CP46: 45918 | CQ46: 46009 | DL46: 4 | DM46: 4 | DN46: 4 | DO46: 4 | DP46: 0 | DQ46: 16 | DR46: 771 | DV46: 44610.309 | DW46: 2022 | DX46: 2
B47: Price | C47: 2.6 Normal index | D47: Euronext Water and Ocean Europe 40 EW | E47: 43740 | G47: 1 | H47: Third Friday of December | I47: Penultimate Friday of November | K47: 2 | L47: 3 | O47: ISS ESG | P47: NXTG | Q47: Underlying Universe in Mother index Europe 500 | R47: Martijn | S47: New Sheet | T47: Automatic | U47: Dataiku | V47: Yes | W47: WATPR | X47: Third Friday of December | AJ47: 46013 | BD47: Penultimate Friday of November | BP47: 45985 | CN47: 46009 | DL47: 1 | DM47: 1 | DN47: 0 | DO47: 1 | DP47: 0 | DQ47: 3 | DR47: 787 | DV47: 45219.367 | DW47: 2023 | DX47: 10
B48: Price | C48: 2.0 CDP | D48: Euronext CDP Environment ESG France | E48: 43745 | G48: 1 | H48: Third Friday of March, June, September, December | I48: Penultimate Friday of February, May, August, November | J48: 6 | K48: 2 | L48: 3 | O48: CDP;Moody's | P48: NXTG | Q48: CDP provides CDP score; annual review in March. Only Review Announcement at Annual. | R48: Ken | S48: New Sheet | T48: Automatic | U48: Dataiku | V48: Yes | W48: FESGP | X48: Third Friday of March | Y48: Third Friday of June | Z48: Third Friday of September | AA48: Third Friday of December | AJ48: 45740 | AK48: 45831 | AL48: 45922 | AM48: 46013 | BD48: Penultimate Friday of February | BE48: Penultimate Friday of May | BF48: Penultimate Friday of August | BG48: Penultimate Friday of November | BP48: 45712 | BQ48: 45803 | BR48: 45894 | BS48: 45985 | CB48: 45730 | CC48: 45821 | CD48: 45912 | CE48: 46003 | CN48: 45736 | CO48: 45827 | CP48: 45918 | CQ48: 46009 | DL48: 4 | DM48: 4 | DN48: 4 | DO48: 4 | DP48: 0 | DQ48: 16 | DR48: 790 | DV48: 44722.356 | DW48: 2022 | DX48: 6
B49: Price | C49: 2.6 Normal index | D49: Euronext Green Planet | E49: 43775 | G49: 1 | H49: Third Friday of March, June, September, December | I49: Penultimate Friday of February, May, August, November | K49: 2 | L49: 3 | O49: Moody's | P49: NXTG | Q49: Underlying universe is mother index Eurozone 300 | R49: Ginevra | S49: New Sheet | T49: Automatic | U49: Dataiku | V49: Yes | W49: GRE5P | X49: Third Friday of March | Y49: Third Friday of June | Z49: Third Friday of September | AA49: Third Friday of December | AJ49: 45740 | AK49: 45831 | AL49: 45922 | AM49: 46013 | BD49: Penultimate Friday of February | BE49: Penultimate Friday of May | BF49: Penultimate Friday of August | BG49: Penultimate Friday of November | BP49: 45712 | BQ49: 45803 | BR49: 45894 | BS49: 45985 | CN49: 45736 | CO49: 45827 | CP49: 45918 | CQ49: 46009 | DL49: 4 | DM49: 4 | DN49: 0 | DO49: 4 | DP49: 0 | DQ49: 12 | DR49: 806 | DV49: 44483.751 | DW49: 2021 | DX49: 10
B50: Price | C50: 2.5 ESG Leaders | D50: Euronext Eurozone ESG Leaders Select 40 | E50: 43852 | G50: 1 | H50: Wednesday after the Third Friday of March, June, September, December | I50: Penultimate Friday of February, May, August, November | K50: 5 | L50: 6 | O50: Moody's | P50: NXTG | R50: Amanda | S50: New Sheet | T50: Automatic | U50: Dataiku | V50: Yes | W50: ESGEP | X50: Wednesday after the Third Friday of March | Y50: Wednesday after the Third Friday of June | Z50: Wednesday after the Third Friday of September | AA50: Wednesday after the Third Friday of December | AJ50: 45743 | AK50: 45834 | AL50: 45925 | AM50: 46017 | BD50: Penultimate Friday of February | BE50: Penultimate Friday of May | BF50: Penultimate Friday of August | BG50: Penultimate Friday of November | BP50: 45712 | BQ50: 45803 | BR50: 45894 | BS50: 45985 | CN50: 45736 | CO50: 45827 | CP50: 45918 | CQ50: 46009 | DL50: 4 | DM50: 4 | DN50: 0 | DO50: 4 | DP50: 0 | DQ50: 12 | DR50: 818 | DV50: 44483.752 | DW50: 2021 | DX50: 10
B51: Price | C51: 2.5 ESG Leaders | D51: Euronext France ESG Leaders Select 30 | E51: 43852 | G51: 1 | H51: Wednesday after the Third Friday of March, June, September, December | I51: Penultimate Friday of February, May, August, November | K51: 5 | L51: 6 | O51: Moody's | P51: NXTG | R51: Amanda | S51: New Sheet | T51: Automatic | U51: Dataiku | V51: Yes | W51: ESGFP | X51: Wednesday after the Third Friday of March | Y51: Wednesday after the Third Friday of June | Z51: Wednesday after the Third Friday of September | AA51: Wednesday after the Third Friday of December | AJ51: 45743 | AK51: 45834 | AL51: 45925 | AM51: 46017 | BD51: Penultimate Friday of February | BE51: Penultimate Friday of May | BF51: Penultimate Friday of August | BG51: Penultimate Friday of November | BP51: 45712 | BQ51: 45803 | BR51: 45894 | BS51: 45985 | CN51: 45736 | CO51: 45827 | CP51: 45918 | CQ51: 46009 | DL51: 4 | DM51: 4 | DN51: 0 | DO51: 4 | DP51: 0 | DQ51: 12 | DR51: 830 | DV51: 44627.475 | DW51: 2022 | DX51: 3
B52: Price | C52: 2.6 Normal index | D52: Euronext Green Planet France | E52: 43866 | G52: 1 | H52: Third Friday of March, June, September, December | I52: Penultimate Friday of February, May, August, November | K52: 2 | L52: 3 | O52: Moody's | P52: NXTG | Q52: Underlying universe is mother index Eurozone 300 | R52: Ginevra | S52: New Sheet | T52: Automatic | U52: Dataiku | V52: Yes | W52: GRF5P | X52: Third Friday of March | Y52: Third Friday of June | Z52: Third Friday of September | AA52: Third Friday of December | AJ52: 45740 | AK52: 45831 | AL52: 45922 | AM52: 46013 | BD52: Penultimate Friday of February | BE52: Penultimate Friday of May | BF52: Penultimate Friday of August | BG52: Penultimate Friday of November | BP52: 45712 | BQ52: 45803 | BR52: 45894 | BS52: 45985 | CN52: 45736 | CO52: 45827 | CP52: 45918 | CQ52: 46009 | DL52: 4 | DM52: 4 | DN52: 0 | DO52: 4 | DP52: 0 | DQ52: 12 | DR52: 842 | DV52: 44483.751 | DW52: 2021 | DX52: 10
B53: Price | C53: 2.6 Normal index | D53: Euronext Europe Pioneers 50 ESG EW | E53: 43880 | F53: 45664 | G53: 1 | H53: Third Friday of March, June, September, December | I53: Penultimate Friday of February, May, August, November | K53: 2 | L53: 3 | O53: Moody's | P53: NXTG | Q53: Underlying universe is mother index Eurozone 300 | R53: Anna | S53: New Sheet | T53: Automatic | U53: Dataiku | V53: No | DL53: 0 | DM53: 0 | DN53: 0 | DO53: 0 | DP53: 0 | DQ53: 0 | DV53: 44483.751 | DW53: 2021 | DX53: 10
B54: Price | C54: 1.7 Product linked | D54: Euronext Eurozone ESG Large 80 | E54: 43929 | G54: 1 | H54: Third Friday of March, June, September, December | I54: Penultimate Friday of February, May, August, November | K54: 2 | L54: 2 | O54: Moody's | P54: NXTG | Q54: Annual in March; underlying universe is mother index Eurozone 300 | R54: Ken | S54: New Sheet | T54: Automatic | U54: Dataiku | V54: Yes | W54: ENESG | X54: Third Friday of March | Y54: Third Friday of June | Z54: Third Friday of September | AA54: Third Friday of December | AJ54: 45740 | AK54: 45831 | AL54: 45922 | AM54: 46013 | BD54: Penultimate Friday of February | BE54: Penultimate Friday of May | BF54: Penultimate Friday of August | BG54: Penultimate Friday of November | BP54: 45712 | BQ54: 45803 | BR54: 45894 | BS54: 45985 | CN54: 45736 | CO54: 45827 | CP54: 45918 | CQ54: 46009 | DL54: 4 | DM54: 4 | DN54: 0 | DO54: 4 | DP54: 0 | DQ54: 12 | DR54: 854 | DV54: 45084.584 | DW54: 2023 | DX54: 6
B55: Price | C55: 2.6 Normal index | D55: Euronext Core Euro & Global Climate Change | E55: 44097 | G55: 1 | H55: Third Friday of March, June, September, December | I55: Penultimate Friday of February, May, August, November | K55: 2 | L55: 3 | O55: Moody's | P55: CUSTOM | Q55: Universe Europe 500, Asia 500 and North America 500 | R55: Ginevra | S55: New Sheet | T55: Automatic | U55: Dataiku | V55: Yes | W55: ECC5P | X55: Third Friday of March | Y55: Third Friday of June | Z55: Third Friday of September | AA55: Third Friday of December | AJ55: 45740 | AK55: 45831 | AL55: 45922 | AM55: 46013 | BD55: Penultimate Friday of February | BE55: Penultimate Friday of May | BF55: Penultimate Friday of August | BG55: Penultimate Friday of November | BP55: 45712 | BQ55: 45803 | BR55: 45894 | BS55: 45985 | CN55: 45736 | CO55: 45827 | CP55: 45918 | CQ55: 46009 | DL55: 4 | DM55: 4 | DN55: 0 | DO55: 4 | DP55: 0 | DQ55: 12 | DR55: 886 | DV55: 44988 | DW55: 2023 | DX55: 3
B56: Price | C56: 1. Blue Chip | D56: Equity Certificate Indices | E56: 44165 | G56: 1 | H56: Third Friday of March, September | I56: Penultimate Friday of February, August | K56: 2 | L56: 2 | P56: OSL | R56: Roland | S56: Old Sheet | T56: Automatic | U56: Dataiku | V56: Yes | W56: OSEXP OSEEP | X56: Third Friday of March | Y56: Third Friday of September | AJ56: 45740 | AK56: 45922 | BD56: Penultimate Friday of February | BE56: Penultimate Friday of August | BP56: 45712 | BQ56: 45894 | CN56: 45736 | CO56: 45918 | DL56: 2 | DM56: 2 | DN56: 0 | DO56: 2 | DP56: 0 | DQ56: 6 | DR56: 898 | DV56: 45469 | DW56: 2024 | DX56: 6
B57: Price | C57: 1. Blue Chip | D57: Equity Certificate Indices | E57: 44165 | G57: 1 | H57: Third Friday of March, September | I57: Penultimate Friday of February, August | K57: 2 | L57: 2 | P57: OSL | R57: Roland | S57: Old Sheet | T57: Automatic | U57: Dataiku | V57: No | DL57: 0 | DM57: 0 | DN57: 0 | DO57: 0 | DP57: 0 | DQ57: 0 | DV57: 45469 | DW57: 2024 | DX57: 6
B58: Price | C58: 1. Blue Chip | D58: Investable Sector Indices | E58: 44165 | G58: 1 | H58: Third Friday of March, September | I58: Penultimate Friday of February, August | J58: 8 | K58: 2 | L58: 2 | P58: OSL | R58: Kelly | S58: New Sheet | T58: Roland | U58: Dataiku | V58: Yes | W58: OBOSP OBSFP OBSHP | X58: Third Friday of March | Y58: Third Friday of September | AJ58: 45740 | AK58: 45922 | BD58: Penultimate Friday of February | BE58: Penultimate Friday of August | BP58: 45712 | BQ58: 45894 | CB58: 45728 | CC58: 45910 | CN58: 45736 | CO58: 45918 | DL58: 2 | DM58: 2 | DN58: 2 | DO58: 2 | DP58: 0 | DQ58: 8 | DR58: 904 | DV58: 45344 | DW58: 2024 | DX58: 2
B59: Price | C59: 1. Blue Chip | D59: Oslo Custom Indices | E59: 44165 | G59: 1 | H59: Third Friday of March, September | I59: Penultimate Friday of February, August | K59: 2 | L59: 2 | P59: OSL | R59: Roland | S59: Old Sheet | T59: Automatic | U59: Dataiku | V59: Yes | W59: OSEPX OSEPB | X59: Third Friday of March | Y59: Third Friday of September | AJ59: 45740 | AK59: 45922 | BD59: Penultimate Friday of February | BE59: Penultimate Friday of August | BP59: 45712 | BQ59: 45894 | CN59: 45736 | CO59: 45918 | DL59: 2 | DM59: 2 | DN59: 0 | DO59: 2 | DP59: 0 | DQ59: 6 | DR59: 956 | DV59: 45469 | DW59: 2024 | DX59: 6
B60: Price | C60: 1. Blue Chip | D60: Oslo Custom Indices | E60: 44165 | G60: 1 | H60: Third Friday of March, September | I60: Penultimate Friday of February, August | K60: 2 | L60: 2 | P60: OSL | R60: Roland | S60: Old Sheet | T60: Automatic | U60: Dataiku | V60: No | DL60: 0 | DM60: 0 | DN60: 0 | DO60: 0 | DP60: 0 | DQ60: 0 | DV60: 45469 | DW60: 2024 | DX60: 6
B61: Price | C61: 2.0 CDP | D61: Euronext CDP Water Eurozone | E61: 44202 | G61: 1 | H61: Third Friday of March, June, September, December | I61: Penultimate Friday of February, May, August, November | J61: 6 | K61: 2 | L61: 3 | O61: CDP;Moody's | P61: NXTG | Q61: CDP provides CDP score; annual review in March. Only Review Announcement at Annual. | R61: Ken | S61: New Sheet | T61: Automatic | U61: Dataiku | V61: Yes | W61: EZWTP | X61: Third Friday of March | Y61: Third Friday of June | Z61: Third Friday of September | AA61: Third Friday of December | AJ61: 45740 | AK61: 45831 | AL61: 45922 | AM61: 46013 | BD61: Penultimate Friday of February | BE61: Penultimate Friday of May | BF61: Penultimate Friday of August | BG61: Penultimate Friday of November | BP61: 45712 | BQ61: 45803 | BR61: 45894 | BS61: 45985 | CB61: 45730 | CC61: 45821 | CD61: 45912 | CE61: 46003 | CN61: 45736 | CO61: 45827 | CP61: 45918 | CQ61: 46009 | DL61: 4 | DM61: 4 | DN61: 4 | DO61: 4 | DP61: 0 | DQ61: 16 | DR61: 964 | DV61: 45084.581 | DW61: 2023 | DX61: 6
B62: Price | C62: 1. Blue Chip | D62: CAC 40 ESG | E62: 44277 | G62: 1 | H62: Third Friday of March, June, September, December | I62: Penultimate Friday of February, May, August, November | J62: 7 | K62: 2 | L62: 2 | O62: Moody's | P62: PAR | Q62: Follows CAC 40. Annual in September, Quarterly in other months | R62: Martijn | S62: New Sheet | T62: Automatic | U62: Dataiku | V62: Yes | W62: CESGP | X62: Third Friday of March | Y62: Third Friday of June | Z62: Third Friday of September | AA62: Third Friday of December | AJ62: 45740 | AK62: 45831 | AL62: 45922 | AM62: 46013 | BD62: Penultimate Friday of February | BE62: Penultimate Friday of May | BF62: Penultimate Friday of August | BG62: Penultimate Friday of November | BP62: 45712 | BQ62: 45803 | BR62: 45894 | BS62: 45985 | CB62: 45729 | CC62: 45820 | CD62: 45911 | CE62: 46002 | CN62: 45736 | CO62: 45827 | CP62: 45918 | CQ62: 46009 | DL62: 4 | DM62: 4 | DN62: 4 | DO62: 4 | DP62: 0 | DQ62: 16 | DR62: 1000 | DV62: 45306 | DW62: 2024 | DX62: 1
B63: Price | C63: 2.6 Normal index | D63: Eurozone ESGL 40 | E63: 44286 | G63: 1 | H63: Third Friday of March, June, September, December | I63: Penultimate Friday of February, May, August, November | K63: 2 | L63: 3 | O63: Moody's | P63: NXTG | Q63: Underlying is the Transatlantic ESG Leaders 60 EW | R63: Ginevra | S63: New Sheet | T63: Automatic | U63: Dataiku | V63: Yes | W63: EEEPR | X63: Third Friday of March | Y63: Third Friday of June | Z63: Third Friday of September | AA63: Third Friday of December | AJ63: 45740 | AK63: 45831 | AL63: 45922 | AM63: 46013 | BD63: Penultimate Friday of February | BE63: Penultimate Friday of May | BF63: Penultimate Friday of August | BG63: Penultimate Friday of November | BP63: 45712 | BQ63: 45803 | BR63: 45894 | BS63: 45985 | CN63: 45736 | CO63: 45827 | CP63: 45918 | CQ63: 46009 | DL63: 4 | DM63: 4 | DN63: 0 | DO63: 4 | DP63: 0 | DQ63: 12 | DR63: 1016 | DV63: 44483.751 | DW63: 2021 | DX63: 10
B64: Price | C64: 2.6 Normal index | D64: US ESGL 20 | E64: 44286 | G64: 1 | H64: Third Friday of March, June, September, December | I64: Penultimate Friday of February, May, August, November | K64: 2 | L64: 3 | O64: Moody's | P64: CUSTOM | Q64: Underlying is the Transatlantic ESG Leaders 60 EW | R64: Ginevra | S64: New Sheet | T64: Automatic | U64: Dataiku | V64: Yes | W64: EUEPR | X64: Third Friday of March | Y64: Third Friday of June | Z64: Third Friday of September | AA64: Third Friday of December | AJ64: 45740 | AK64: 45831 | AL64: 45922 | AM64: 46013 | BD64: Penultimate Friday of February | BE64: Penultimate Friday of May | BF64: Penultimate Friday of August | BG64: Penultimate Friday of November | BP64: 45712 | BQ64: 45803 | BR64: 45894 | BS64: 45985 | CN64: 45736 | CO64: 45827 | CP64: 45918 | CQ64: 46009 | DL64: 4 | DM64: 4 | DN64: 0 | DO64: 4 | DP64: 0 | DQ64: 12 | DR64: 1028 | DV64: 44483.753 | DW64: 2021 | DX64: 10
B65: Price | C65: 1.7 Product linked | D65: Eurozone Banks | E65: 44300 | G65: 1 | H65: Third Friday of March, June, September, December | I65: Penultimate Friday of February, May, August, November | J65: 7 | K65: 2 | L65: 2 | P65: NXTG | R65: Alice | S65: New Sheet | T65: Automatic | U65: Dataiku | V65: Yes | W65: BANK | X65: Third Friday of March | Y65: Third Friday of June | Z65: Third Friday of September | AA65: Third Friday of December | AJ65: 45740 | AK65: 45831 | AL65: 45922 | AM65: 46013 | BD65: Penultimate Friday of February | BE65: Penultimate Friday of May | BF65: Penultimate Friday of August | BG65: Penultimate Friday of November | BP65: 45712 | BQ65: 45803 | BR65: 45894 | BS65: 45985 | CB65: 45729 | CC65: 45820 | CD65: 45911 | CE65: 46002 | CN65: 45736 | CO65: 45827 | CP65: 45918 | CQ65: 46009 | DL65: 4 | DM65: 4 | DN65: 4 | DO65: 4 | DP65: 0 | DQ65: 16 | DR65: 1040 | DV65: 45622 | DW65: 2024 | DX65: 11
B66: Price | C66: 2.6 Normal index | D66: EN Transatlantic Environment 50 | E66: 44321 | G66: 1 | H66: Third Friday of March, June, September, December | I66: Penultimate Friday of February, May, August, November | K66: 2 | L66: 3 | N66: EZ300;NA500 | O66: Moody's | P66: CUSTOM | Q66: Underlying is the EZ300 and NA500 | R66: Amanda | S66: New Sheet | T66: Automatic | U66: Dataiku | V66: Yes | W66: ETE5P | X66: Third Friday of March | Y66: Third Friday of June | Z66: Third Friday of September | AA66: Third Friday of December | AJ66: 45740 | AK66: 45831 | AL66: 45922 | AM66: 46013 | BD66: Penultimate Friday of February | BE66: Penultimate Friday of May | BF66: Penultimate Friday of August | BG66: Penultimate Friday of November | BP66: 45712 | BQ66: 45803 | BR66: 45894 | BS66: 45985 | CN66: 45736 | CO66: 45827 | CP66: 45918 | CQ66: 46009 | DL66: 4 | DM66: 4 | DN66: 0 | DO66: 4 | DP66: 0 | DQ66: 12 | DR66: 1104 | DV66: 44610.312 | DW66: 2022 | DX66: 2
B67: Price | C67: 1.3 PAB | D67: Euronext France PAB 50 | E67: 44321 | G67: 1 | H67: Third Friday of December | I67: Penultimate Friday of November | J67: 6 | K67: 2 | L67: 3 | O67: Moody's | P67: NXTG | Q67: Underlying is the SBF 120 Index, only Annual review | R67: Ginevra | S67: New Sheet | T67: Automatic | U67: Dataiku | V67: Yes | W67: FPABP | X67: Third Friday of December | AJ67: 46013 | BD67: Penultimate Friday of November | BP67: 45985 | CB67: 46003 | CN67: 46009 | DL67: 1 | DM67: 1 | DN67: 1 | DO67: 1 | DP67: 0 | DQ67: 4 | DR67: 1116 | DV67: 45236.558 | DW67: 2023 | DX67: 11
B68: Price | C68: 2.6 Normal index | D68: Euronext Transatlantic Circular Economy 50 EW | E68: 44328 | G68: 1 | H68: Third Friday of March, June, September, December | I68: Penultimate Friday of February, May, August, November | J68: 7 | K68: 2 | L68: 3 | N68: EU500;NA500 | O68: Moody's | P68: CUSTOM | Q68: Underlying is the NA500 and EU500 | R68: Amanda | S68: New Sheet | T68: Automatic | U68: Dataiku | V68: Yes | W68: TCEPR | X68: Third Friday of March | Y68: Third Friday of June | Z68: Third Friday of September | AA68: Third Friday of December | AJ68: 45740 | AK68: 45831 | AL68: 45922 | AM68: 46013 | BD68: Penultimate Friday of February | BE68: Penultimate Friday of May | BF68: Penultimate Friday of August | BG68: Penultimate Friday of November | BP68: 45712 | BQ68: 45803 | BR68: 45894 | BS68: 45985 | CB68: 45729 | CC68: 45820 | CD68: 45911 | CE68: 46002 | CN68: 45736 | CO68: 45827 | CP68: 45918 | CQ68: 46009 | DL68: 4 | DM68: 4 | DN68: 4 | DO68: 4 | DP68: 0 | DQ68: 16 | DR68: 1120 | DV68: 44900.647 | DW68: 2022 | DX68: 12
B69: Price | C69: 1.3 PAB | D69: Euronext Core Europe PAB 50 | E69: 44349 | G69: 1 | H69: Third Friday of December | I69: Penultimate Friday of November | J69: 6 | K69: 2 | L69: 3 | O69: Moody's | P69: NXTG | Q69: Annual review in March, no quarterly | R69: Ginevra | S69: New Sheet | T69: Automatic | U69: Dataiku | V69: Yes | W69: CPABP | X69: Third Friday of December | AJ69: 46013 | BD69: Penultimate Friday of November | BP69: 45985 | CB69: 46003 | CN69: 46009 | DL69: 1 | DM69: 1 | DN69: 1 | DO69: 1 | DP69: 0 | DQ69: 4 | DR69: 1136 | DV69: 45236.627 | DW69: 2023 | DX69: 11
B70: Price | C70: 2.6 Normal index | D70: Euronext Eurozone Diversity & Governance 40 EW | E70: 44349 | G70: 1 | H70: Third Friday of March, June, September, December | I70: Penultimate Friday of February, May, August, November | K70: 2 | L70: 3 | O70: Moody's | P70: NXTG | Q70: Underlying is EZ300 | R70: Anna | S70: New Sheet | T70: Automatic | U70: Dataiku | V70: Yes | W70: GOVEP | X70: Third Friday of March | Y70: Third Friday of June | Z70: Third Friday of September | AA70: Third Friday of December | AJ70: 45740 | AK70: 45831 | AL70: 45922 | AM70: 46013 | BD70: Penultimate Friday of February | BE70: Penultimate Friday of May | BF70: Penultimate Friday of August | BG70: Penultimate Friday of November | BP70: 45712 | BQ70: 45803 | BR70: 45894 | BS70: 45985 | CN70: 45736 | CO70: 45827 | CP70: 45918 | CQ70: 46009 | DL70: 4 | DM70: 4 | DN70: 0 | DO70: 4 | DP70: 0 | DQ70: 12 | DR70: 1140 | DV70: 44992.414 | DW70: 2023 | DX70: 3
B71: Price | C71: 1.3 PAB | D71: Euronext Eurozone PAB 50 | E71: 44349 | G71: 1 | H71: Third Friday of December | I71: Penultimate Friday of November | J71: 6 | K71: 2 | L71: 3 | O71: Moody's | P71: NXTG | Q71: Annual review in March, no quarterly | R71: Ginevra | S71: New Sheet | T71: Automatic | U71: Dataiku | V71: Yes | W71: EPABP | X71: Third Friday of December | AJ71: 46013 | BD71: Penultimate Friday of November | BP71: 45985 | CB71: 46003 | CN71: 46009 | DL71: 1 | DM71: 1 | DN71: 1 | DO71: 1 | DP71: 0 | DQ71: 4 | DR71: 1152 | DV71: 45236.56 | DW71: 2023 | DX71: 11
B72: Price | C72: 2.6 Normal index | D72: EN Sovereign Economy Selection EZ50 | E72: 44356 | G72: 1 | H72: Third Friday of March, June, September, December | I72: Penultimate Friday of February, May, August, November | K72: 2 | L72: 2 | N72: EZ300 | P72: NXTG | Q72: Underlying is EZ300 | R72: Anna | S72: New Sheet | T72: Automatic | U72: Dataiku | V72: Yes | W72: SES5P | X72: Third Friday of March | Y72: Third Friday of June | Z72: Third Friday of September | AA72: Third Friday of December | AJ72: 45740 | AK72: 45831 | AL72: 45922 | AM72: 46013 | BD72: Penultimate Friday of February | BE72: Penultimate Friday of May | BF72: Penultimate Friday of August | BG72: Penultimate Friday of November | BP72: 45712 | BQ72: 45803 | BR72: 45894 | BS72: 45985 | CN72: 45736 | CO72: 45827 | CP72: 45918 | CQ72: 46009 | DL72: 4 | DM72: 4 | DN72: 0 | DO72: 4 | DP72: 0 | DQ72: 12 | DR72: 1156 | DV72: 44698.595 | DW72: 2022 | DX72: 5
B73: Price | C73: 1.2 World | D73: Euronext World Country selection | E73: 44377 | G73: 1 | H73: Third Friday of March, June, September, December | I73: Penultimate Friday of February, May, August, November | K73: 2 | L73: 3 | P73: ENXG | Q73: Underlying is EU500 NA500, AS500 + main listings USA, CAN, UK, CH, JP, AUS | R73: Alice | S73: New Sheet | T73: Automatic | U73: Dataiku | V73: Yes | W73: EWCSP | X73: Third Friday of March | Y73: Third Friday of June | Z73: Third Friday of September | AA73: Third Friday of December | AJ73: 45740 | AK73: 45831 | AL73: 45922 | AM73: 46013 | BD73: Penultimate Friday of February | BE73: Penultimate Friday of May | BF73: Penultimate Friday of August | BG73: Penultimate Friday of November | BP73: 45712 | BQ73: 45803 | BR73: 45894 | BS73: 45985 | CN73: 45736 | CO73: 45827 | CP73: 45918 | CQ73: 46009 | DL73: 4 | DM73: 4 | DN73: 0 | DO73: 4 | DP73: 0 | DQ73: 12 | DR73: 1168 | DV73: 44627.474 | DW73: 2022 | DX73: 3
B74: Price | C74: 1.21 World | D74: EN V E ESG World-Select 75 Bund/SV | E74: 44386 | G74: 1 | H74: Last trading-day of June | I74: Penultimate Friday of May | J74: 6 | K74: 2 | L74: 3 | O74: Moody's | P74: ENXG | Q74: Underlying is EU500/NA500/AS500 + JP, AUS, UK, SW, CA, USA // Only Annual in May | R74: Martijn | S74: New Sheet | T74: Automatic | U74: Dataiku | V74: Yes | W74: EVEWP | X74: Last trading-day of June | AJ74: 45839 | BD74: Penultimate Friday of May | BP74: 45803 | CB74: 45831 | CN74: 45835 | DL74: 1 | DM74: 1 | DN74: 1 | DO74: 1 | DP74: 0 | DQ74: 4 | DR74: 1180 | DV74: 45028.332 | DW74: 2023 | DX74: 4
B75: Price | C75: 2.6 Normal index | D75: Euronext V E Eurozone Social Focus | E75: 44391 | G75: 1 | H75: Third Friday of March, June, September, December | I75: Penultimate Friday of February, May, August, November | K75: 2 | L75: 3 | O75: Moody's | P75: NXTG | Q75: Underlying is EZ300 | R75: Ginevra | S75: New Sheet | T75: Automatic | U75: Dataiku | V75: Yes | W75: EZSFP | X75: Third Friday of March | Y75: Third Friday of June | Z75: Third Friday of September | AA75: Third Friday of December | AJ75: 45740 | AK75: 45831 | AL75: 45922 | AM75: 46013 | BD75: Penultimate Friday of February | BE75: Penultimate Friday of May | BF75: Penultimate Friday of August | BG75: Penultimate Friday of November | BP75: 45712 | BQ75: 45803 | BR75: 45894 | BS75: 45985 | CN75: 45736 | CO75: 45827 | CP75: 45918 | CQ75: 46009 | DL75: 4 | DM75: 4 | DN75: 0 | DO75: 4 | DP75: 0 | DQ75: 12 | DR75: 1184 | DV75: 44992.617 | DW75: 2023 | DX75: 3
B76: Price | C76: 2.5 ESG Leaders | D76: EN EZ ESG Leaders Select 40 | E76: 44393 | G76: 1 | H76: Second Friday of January, April, July, October | I76: Penultimate Friday of February, May, August, November | K76: 2 | L76: 2 | O76: Moody's | P76: NXTG | Q76: Underlying is EZ300, alternative effective date | R76: Amanda | S76: New Sheet | T76: Automatic | U76: Dataiku | V76: Yes | W76: ESGCP | X76: Second Friday of January | Y76: Second Friday of April | Z76: Second Friday of July | AA76: Second Friday of October | AJ76: 45670 | AK76: 45761 | AL76: 45852 | AM76: 45943 | BD76: Penultimate Friday of February | BE76: Penultimate Friday of May | BF76: Penultimate Friday of August | BG76: Penultimate Friday of November | BP76: 45712 | BQ76: 45803 | BR76: 45894 | BS76: 45985 | CN76: 45666 | CO76: 45757 | CP76: 45848 | CQ76: 45939 | DL76: 4 | DM76: 4 | DN76: 0 | DO76: 4 | DP76: 0 | DQ76: 12 | DR76: 1196 | DV76: 44610.311 | DW76: 2022 | DX76: 2
B77: Price | C77: 2.0 CDP | D77: EN CDP Environment Transatlantic EW | E77: 44405 | G77: 1 | H77: Third Friday of March, June, September, December | I77: Penultimate Friday of February, May, August, November | J77: 6 | K77: 2 | L77: 3 | O77: CDP;Moody's | P77: CUSTOM | Q77: CDP provides CDP score; annual review in March. US index, review composition sent out +1 (Thursday morning instead of Wednesday night). Only Review Announcement at Annual. | R77: Ken | S77: New Sheet | T77: Automatic | U77: Dataiku | V77: Yes | W77: TESGP | X77: Third Friday of March | Y77: Third Friday of June | Z77: Third Friday of September | AA77: Third Friday of December | AJ77: 45740 | AK77: 45831 | AL77: 45922 | AM77: 46013 | BD77: Penultimate Friday of February | BE77: Penultimate Friday of May | BF77: Penultimate Friday of August | BG77: Penultimate Friday of November | BP77: 45712 | BQ77: 45803 | BR77: 45894 | BS77: 45985 | CB77: 45730 | CC77: 45821 | CD77: 45912 | CE77: 46003 | CN77: 45736 | CO77: 45827 | CP77: 45918 | CQ77: 46009 | DL77: 4 | DM77: 4 | DN77: 4 | DO77: 4 | DP77: 0 | DQ77: 16 | DR77: 1208 | DV77: 44761.347 | DW77: 2022 | DX77: 7
B78: Price | C78: 2.3 Screened Climate | D78: Euronext EZ Scr Clim Amb 40 EW | E78: 44426 | G78: 1 | H78: Third Friday of March, June, September, December | I78: Penultimate Friday of February, May, August, November | K78: 2 | L78: 3 | O78: ISS ESG | P78: NXTG | Q78: Underlying is EZ300 | R78: Coen | S78: New Sheet | T78: Automatic | U78: Dataiku | V78: Yes | W78: CLAMP | X78: Third Friday of March | Y78: Third Friday of June | Z78: Third Friday of September | AA78: Third Friday of December | AJ78: 45740 | AK78: 45831 | AL78: 45922 | AM78: 46013 | BD78: Penultimate Friday of February | BE78: Penultimate Friday of May | BF78: Penultimate Friday of August | BG78: Penultimate Friday of November | BP78: 45712 | BQ78: 45803 | BR78: 45894 | BS78: 45985 | CN78: 45736 | CO78: 45827 | CP78: 45918 | CQ78: 46009 | DL78: 4 | DM78: 4 | DN78: 0 | DO78: 4 | DP78: 0 | DQ78: 12 | DR78: 1224 | DV78: 44992.618 | DW78: 2023 | DX78: 3
B79: Price | C79: 1.2 World | D79: Euronext Developed Market | E79: 44433 | G79: 1 | H79: Third Friday of March, June, September, December | I79: Penultimate Friday of February, May, August, November | K79: 2 | L79: 3 | P79: ENDM | Q79: Benchmark index / Mother index. | R79: Alice | S79: New Sheet | T79: Automatic | U79: Dataiku | V79: Yes | W79: ENDMP EDMPU | X79: Third Friday of March | Y79: Third Friday of June | Z79: Third Friday of September | AA79: Third Friday of December | AJ79: 45740 | AK79: 45831 | AL79: 45922 | AM79: 46013 | BD79: Penultimate Friday of February | BE79: Penultimate Friday of May | BF79: Penultimate Friday of August | BG79: Penultimate Friday of November | BP79: 45712 | BQ79: 45803 | BR79: 45894 | BS79: 45985 | CN79: 45736 | CO79: 45827 | CP79: 45918 | CQ79: 46009 | DL79: 4 | DM79: 4 | DN79: 0 | DO79: 4 | DP79: 0 | DQ79: 12 | DR79: 1236 | DV79: 44627.472 | DW79: 2022 | DX79: 3
B80: Price | C80: 1.2 World | D80: Euronext Developed Market | E80: 44525 | G80: 1 | H80: Third Friday of March, June, September, December | I80: Penultimate Friday of February, May, August, November | K80: 2 | L80: 3 | P80: ENDM | Q80: Benchmark index / Mother index. | R80: Alice | S80: New Sheet | T80: Automatic | U80: Dataiku | V80: No | DL80: 0 | DM80: 0 | DN80: 0 | DO80: 0 | DP80: 0 | DQ80: 0 | DV80: 44627.472 | DW80: 2022 | DX80: 3
B81: Price | C81: 1.2 World | D81: Euronext World | E81: 44433 | G81: 1 | H81: Third Friday of March, June, September, December | I81: Penultimate Friday of February, May, August, November | K81: 2 | L81: 3 | P81: ENWP | Q81: Benchmark index / Mother index. | R81: Alice | S81: New Sheet | T81: Automatic | U81: Dataiku | V81: Yes | W81: ENWP | X81: Third Friday of March | Y81: Third Friday of June | Z81: Third Friday of September | AA81: Third Friday of December | AJ81: 45740 | AK81: 45831 | AL81: 45922 | AM81: 46013 | BD81: Penultimate Friday of February | BE81: Penultimate Friday of May | BF81: Penultimate Friday of August | BG81: Penultimate Friday of November | BP81: 45712 | BQ81: 45803 | BR81: 45894 | BS81: 45985 | CN81: 45736 | CO81: 45827 | CP81: 45918 | CQ81: 46009 | DL81: 4 | DM81: 4 | DN81: 0 | DO81: 4 | DP81: 0 | DQ81: 12 | DR81: 1248 | DV81: 44629.431 | DW81: 2022 | DX81: 3
B82: Price | C82: 2.6 Normal index | D82: Euronext France Social | E82: 44461 | G82: 1 | H82: Second Friday of January, April, July, October | I82: First Friday of January, April, July, October | K82: 2 | L82: 2 | O82: Moody's | P82: NXTG | Q82: Underlying is SBF 120, alternative effective schedule | R82: Ken | S82: New Sheet | T82: Automatic | U82: Dataiku | V82: Yes | W82: FRSOP | X82: Second Friday of January | Y82: Second Friday of April | Z82: Second Friday of July | AA82: Second Friday of October | AJ82: 45670 | AK82: 45761 | AL82: 45852 | AM82: 45943 | BD82: First Friday of January | BE82: First Friday of April | BF82: First Friday of July | BG82: First Friday of October | BP82: 45663 | BQ82: 45754 | BR82: 45845 | BS82: 45936 | CN82: 45666 | CO82: 45757 | CP82: 45848 | CQ82: 45939 | DL82: 4 | DM82: 4 | DN82: 0 | DO82: 4 | DP82: 0 | DQ82: 12 | DR82: 1260 | DV82: 45198.44 | DW82: 2023 | DX82: 9
B83: Price | C83: 2.3 Screened Climate | D83: EN EZ Screened Climate Ambition 35 EW | E83: 44470 | G83: 1 | H83: Third Friday of March, June, September, December | I83: Penultimate Friday of February, May, August, November | K83: 2 | L83: 3 | O83: ISS ESG | P83: NXTG | Q83: Underlying is EZ300 | R83: Coen | S83: New Sheet | T83: Automatic | U83: Dataiku | V83: Yes | W83: EZCLA | X83: Third Friday of March | Y83: Third Friday of June | Z83: Third Friday of September | AA83: Third Friday of December | AJ83: 45740 | AK83: 45831 | AL83: 45922 | AM83: 46013 | BD83: Penultimate Friday of February | BE83: Penultimate Friday of May | BF83: Penultimate Friday of August | BG83: Penultimate Friday of November | BP83: 45712 | BQ83: 45803 | BR83: 45894 | BS83: 45985 | CN83: 45736 | CO83: 45827 | CP83: 45918 | CQ83: 46009 | DL83: 4 | DM83: 4 | DN83: 0 | DO83: 4 | DP83: 0 | DQ83: 12 | DR83: 1272 | DV83: 44865.597 | DW83: 2022 | DX83: 10
B84: Price | C84: 2.3 Screened Climate | D84: EN US Screened Climate Amb 25 EW EUR | E84: 44470 | G84: 1 | H84: Third Friday of March, June, September, December | I84: Penultimate Friday of February, May, August, November | K84: 2 | L84: 3 | O84: ISS ESG | P84: CUSTOM | Q84: Underlying is NA500, EUR version | R84: Coen | S84: New Sheet | T84: Automatic | U84: Dataiku | V84: Yes | W84: USCLE | X84: Third Friday of March | Y84: Third Friday of June | Z84: Third Friday of September | AA84: Third Friday of December | AJ84: 45740 | AK84: 45831 | AL84: 45922 | AM84: 46013 | BD84: Penultimate Friday of February | BE84: Penultimate Friday of May | BF84: Penultimate Friday of August | BG84: Penultimate Friday of November | BP84: 45712 | BQ84: 45803 | BR84: 45894 | BS84: 45985 | CN84: 45736 | CO84: 45827 | CP84: 45918 | CQ84: 46009 | DL84: 4 | DM84: 4 | DN84: 0 | DO84: 4 | DP84: 0 | DQ84: 12 | DR84: 1284 | DV84: 44865.603 | DW84: 2022 | DX84: 10
B85: Price | C85: 2.3 Screened Climate | D85: EN US Screened Climate Ambition 25 EW USD | E85: 44470 | G85: 1 | H85: Third Friday of March, June, September, December | I85: Penultimate Friday of February, May, August, November | K85: 2 | L85: 3 | O85: ISS ESG | P85: CUSTOM | Q85: Underlying is NA500, USD version | R85: Coen | S85: New Sheet | T85: Automatic | U85: Dataiku | V85: Yes | W85: USCLA | X85: Third Friday of March | Y85: Third Friday of June | Z85: Third Friday of September | AA85: Third Friday of December | AJ85: 45740 | AK85: 45831 | AL85: 45922 | AM85: 46013 | BD85: Penultimate Friday of February | BE85: Penultimate Friday of May | BF85: Penultimate Friday of August | BG85: Penultimate Friday of November | BP85: 45712 | BQ85: 45803 | BR85: 45894 | BS85: 45985 | CN85: 45736 | CO85: 45827 | CP85: 45918 | CQ85: 46009 | DL85: 4 | DM85: 4 | DN85: 0 | DO85: 4 | DP85: 0 | DQ85: 12 | DR85: 1296 | DV85: 44865.601 | DW85: 2022 | DX85: 10
B86: Price | C86: 2.6 Normal index | D86: Euronext® Global Health Care 50 EW ESG | E86: 44497 | G86: 1 | H86: Third Friday of March, June, September, December | I86: Penultimate Friday of February, May, August, November | K86: 2 | L86: 3 | O86: Moody's | P86: CUSTOM | Q86: Underlying Euronext Developed Market | R86: Amanda | S86: New Sheet | T86: Automatic | U86: Dataiku | V86: Yes | W86: GHCPR | X86: Third Friday of March | Y86: Third Friday of June | Z86: Third Friday of September | AA86: Third Friday of December | AJ86: 45740 | AK86: 45831 | AL86: 45922 | AM86: 46013 | BD86: Penultimate Friday of February | BE86: Penultimate Friday of May | BF86: Penultimate Friday of August | BG86: Penultimate Friday of November | BP86: 45712 | BQ86: 45803 | BR86: 45894 | BS86: 45985 | CN86: 45736 | CO86: 45827 | CP86: 45918 | CQ86: 46009 | DL86: 4 | DM86: 4 | DN86: 0 | DO86: 4 | DP86: 0 | DQ86: 12 | DR86: 1336 | DV86: 44610.31 | DW86: 2022 | DX86: 2
B87: Price | C87: 2.1 Biodiversity | D87: Euronext ESG Biodiversity Screened Eurozone 50 | E87: 44518 | G87: 1 | H87: Third Friday of March, June, September, December | I87: Penultimate Friday of February, May, August, November | K87: 2 | L87: 2 | N87: EZ300 | O87: Iceberg;Sustainalytics | P87: NXTG | Q87: Sustainalytics data used, underlying Euronext EZ300 | R87: Kelly | S87: New Sheet | T87: Automatic | U87: Dataiku | V87: Yes | W87: EBSEP | X87: Third Friday of March | Y87: Third Friday of June | Z87: Third Friday of September | AA87: Third Friday of December | AJ87: 45740 | AK87: 45831 | AL87: 45922 | AM87: 46013 | BD87: Penultimate Friday of February | BE87: Penultimate Friday of May | BF87: Penultimate Friday of August | BG87: Penultimate Friday of November | BP87: 45712 | BQ87: 45803 | BR87: 45894 | BS87: 45985 | CN87: 45736 | CO87: 45827 | CP87: 45918 | CQ87: 46009 | DL87: 4 | DM87: 4 | DN87: 0 | DO87: 4 | DP87: 0 | DQ87: 12 | DR87: 1348 | DV87: 44910.443 | DW87: 2022 | DX87: 12
B88: Price | C88: 2.1 Biodiversity | D88: Euronext ESG Biodiversity Screened World | E88: 44518 | G88: 1 | H88: Third Friday of March, June, September, December | I88: Penultimate Friday of February, May, August, November | J88: 6 | K88: 2 | L88: 3 | N88: ENWP | O88: Iceberg;Sustainalytics | P88: CUSTOM | Q88: Sustainalytics data used, underlying Euronext World | R88: Kelly | S88: New Sheet | T88: Automatic | U88: Dataiku | V88: Yes | W88: EBSWP EBSPW | X88: Third Friday of March | Y88: Third Friday of June | Z88: Third Friday of September | AA88: Third Friday of December | AJ88: 45740 | AK88: 45831 | AL88: 45922 | AM88: 46013 | BD88: Penultimate Friday of February | BE88: Penultimate Friday of May | BF88: Penultimate Friday of August | BG88: Penultimate Friday of November | BP88: 45712 | BQ88: 45803 | BR88: 45894 | BS88: 45985 | CB88: 45730 | CC88: 45821 | CD88: 45912 | CE88: 46003 | CN88: 45736 | CO88: 45827 | CP88: 45918 | CQ88: 46009 | DL88: 4 | DM88: 4 | DN88: 4 | DO88: 4 | DP88: 0 | DQ88: 16 | DR88: 1360 | DV88: 44910.441 | DW88: 2022 | DX88: 12
B89: Price | C89: 2.1 Biodiversity | D89: Euronext ESG Biodiversity Screened World | E89: 44533 | G89: 1 | H89: Third Friday of March, June, September, December | I89: Penultimate Friday of February, May, August, November | J89: 6 | K89: 2 | L89: 3 | N89: ENWP | O89: Iceberg;Sustainalytics | P89: CUSTOM | Q89: Sustainalytics data used, underlying Euronext World | R89: Kelly | S89: New Sheet | T89: Automatic | U89: Dataiku | V89: No | DL89: 0 | DM89: 0 | DN89: 0 | DO89: 0 | DP89: 0 | DQ89: 0 | DV89: 44910.441 | DW89: 2022 | DX89: 12
B90: Price | C90: 2.3 Screened Climate | D90: EN JPN Screened Climate Amb 30 EW EUR | E90: 44566 | G90: 1 | H90: Third Friday of March, June, September, December | I90: Penultimate Friday of February, May, August, November | K90: 2 | L90: 3 | O90: ISS ESG | P90: NXTG | Q90: Underlying AS500, ISS-ESG Oekom Trust Carbon data used | R90: Coen | S90: New Sheet | T90: Automatic | U90: Dataiku | V90: Yes | W90: JPCLE | X90: Third Friday of March | Y90: Third Friday of June | Z90: Third Friday of September | AA90: Third Friday of December | AJ90: 45740 | AK90: 45831 | AL90: 45922 | AM90: 46013 | BD90: Penultimate Friday of February | BE90: Penultimate Friday of May | BF90: Penultimate Friday of August | BG90: Penultimate Friday of November | BP90: 45712 | BQ90: 45803 | BR90: 45894 | BS90: 45985 | CN90: 45736 | CO90: 45827 | CP90: 45918 | CQ90: 46009 | DL90: 4 | DM90: 4 | DN90: 0 | DO90: 4 | DP90: 0 | DQ90: 12 | DR90: 1376 | DV90: 44865.606 | DW90: 2022 | DX90: 10
B91: Price | C91: 2.3 Screened Climate | D91: EN JPN Screened Climate Ambition 30 EW | E91: 44566 | G91: 1 | H91: Third Friday of March, June, September, December | I91: Penultimate Friday of February, May, August, November | K91: 2 | L91: 3 | O91: ISS ESG | P91: NXTG | Q91: Underlying AS500, ISS-ESG Oekom Trust Carbon data used | R91: Coen | S91: New Sheet | T91: Automatic | U91: Dataiku | V91: Yes | W91: JPCLA | X91: Third Friday of March | Y91: Third Friday of June | Z91: Third Friday of September | AA91: Third Friday of December | AJ91: 45740 | AK91: 45831 | AL91: 45922 | AM91: 46013 | BD91: Penultimate Friday of February | BE91: Penultimate Friday of May | BF91: Penultimate Friday of August | BG91: Penultimate Friday of November | BP91: 45712 | BQ91: 45803 | BR91: 45894 | BS91: 45985 | CN91: 45736 | CO91: 45827 | CP91: 45918 | CQ91: 46009 | DL91: 4 | DM91: 4 | DN91: 0 | DO91: 4 | DP91: 0 | DQ91: 12 | DR91: 1388 | DV91: 44865.605 | DW91: 2022 | DX91: 10
B92: Price | C92: 2.3 Screened Climate | D92: EN US Screened Climate Amb 35 EW EUR | E92: 44566 | G92: 1 | H92: Third Friday of March, June, September, December | I92: Penultimate Friday of February, May, August, November | K92: 2 | L92: 3 | O92: ISS ESG | P92: CUSTOM | Q92: Underlying NA500, ISS-ESG Oekom Trust Carbon data used | R92: Coen | S92: New Sheet | T92: Automatic | U92: Dataiku | V92: Yes | W92: UC3PE | X92: Third Friday of March | Y92: Third Friday of June | Z92: Third Friday of September | AA92: Third Friday of December | AJ92: 45740 | AK92: 45831 | AL92: 45922 | AM92: 46013 | BD92: Penultimate Friday of February | BE92: Penultimate Friday of May | BF92: Penultimate Friday of August | BG92: Penultimate Friday of November | BP92: 45712 | BQ92: 45803 | BR92: 45894 | BS92: 45985 | CN92: 45736 | CO92: 45827 | CP92: 45918 | CQ92: 46009 | DL92: 4 | DM92: 4 | DN92: 0 | DO92: 4 | DP92: 0 | DQ92: 12 | DR92: 1400 | DV92: 44865.609 | DW92: 2022 | DX92: 10
B93: Price | C93: 2.3 Screened Climate | D93: EN US Screened Climate Ambition 35 EW | E93: 44566 | G93: 1 | H93: Third Friday of March, June, September, December | I93: Penultimate Friday of February, May, August, November | K93: 2 | L93: 3 | O93: ISS ESG | P93: CUSTOM | Q93: Underlying NA500, ISS-ESG Oekom Trust Carbon data used | R93: Coen | S93: New Sheet | T93: Automatic | U93: Dataiku | V93: Yes | W93: USC3P | X93: Third Friday of March | Y93: Third Friday of June | Z93: Third Friday of September | AA93: Third Friday of December | AJ93: 45740 | AK93: 45831 | AL93: 45922 | AM93: 46013 | BD93: Penultimate Friday of February | BE93: Penultimate Friday of May | BF93: Penultimate Friday of August | BG93: Penultimate Friday of November | BP93: 45712 | BQ93: 45803 | BR93: 45894 | BS93: 45985 | CN93: 45736 | CO93: 45827 | CP93: 45918 | CQ93: 46009 | DL93: 4 | DM93: 4 | DN93: 0 | DO93: 4 | DP93: 0 | DQ93: 12 | DR93: 1412 | DV93: 44865.608 | DW93: 2022 | DX93: 10
B94: Price | C94: 2.1 Biodiversity | D94: EN Euro Large Cap Biodiversity Leaders 30 | E94: 44583 | G94: 1 | H94: Third Friday of March, June, September, December | I94: Penultimate Friday of February, May, August, November | K94: 2 | L94: 2 | N94: EZ300 | O94: Carbon4 Finance;Sustainalytics | P94: NXTG | Q94: Underlying EZ300, Sustainanalytics data used | R94: Kelly | S94: New Sheet | T94: Automatic | U94: Dataiku | V94: Yes | W94: BIOEP | X94: Third Friday of March | Y94: Third Friday of June | Z94: Third Friday of September | AA94: Third Friday of December | AJ94: 45740 | AK94: 45831 | AL94: 45922 | AM94: 46013 | BD94: Penultimate Friday of February | BE94: Penultimate Friday of May | BF94: Penultimate Friday of August | BG94: Penultimate Friday of November | BP94: 45712 | BQ94: 45803 | BR94: 45894 | BS94: 45985 | CN94: 45736 | CO94: 45827 | CP94: 45918 | CQ94: 46009 | DL94: 4 | DM94: 4 | DN94: 0 | DO94: 4 | DP94: 0 | DQ94: 12 | DR94: 1424 | DV94: 45334 | DW94: 2024 | DX94: 2
B95: Price | C95: 2.1 Biodiversity | D95: EN ESG Biodiversity Screened Transatlantic 80 | E95: 44622 | G95: 1 | H95: Third Friday of March, June, September, December | I95: Penultimate Friday of February, May, August, November | K95: 2 | L95: 3 | O95: Iceberg;Sustainalytics | P95: CUSTOM | Q95: Underlying is Euronext World Index, Sustainalytics & Iceberg data needed | R95: Kelly | S95: New Sheet | T95: Automatic | U95: Dataiku | V95: Yes | W95: EBSTP | X95: Third Friday of March | Y95: Third Friday of June | Z95: Third Friday of September | AA95: Third Friday of December | AJ95: 45740 | AK95: 45831 | AL95: 45922 | AM95: 46013 | BD95: Penultimate Friday of February | BE95: Penultimate Friday of May | BF95: Penultimate Friday of August | BG95: Penultimate Friday of November | BP95: 45712 | BQ95: 45803 | BR95: 45894 | BS95: 45985 | CN95: 45736 | CO95: 45827 | CP95: 45918 | CQ95: 46009 | DL95: 4 | DM95: 4 | DN95: 0 | DO95: 4 | DP95: 0 | DQ95: 12 | DR95: 1448 | DV95: 44910.455 | DW95: 2022 | DX95: 12
B96: Price | C96: 1. Blue Chip | D96: OBX ESG | E96: 44687 | G96: 1 | H96: Third Friday of March, September | I96: Penultimate Friday of February, August | J96: 8 | K96: 2 | L96: 2 | O96: Sustainalytics | P96: OSL | Q96: Semi-annual review, March and September | R96: Ken | S96: New Sheet | T96: Automatic | U96: Dataiku | V96: Yes | W96: OBXEP OEXOP | X96: Third Friday of March | Y96: Third Friday of September | AJ96: 45740 | AK96: 45922 | BD96: Penultimate Friday of February | BE96: Penultimate Friday of August | BP96: 45712 | BQ96: 45894 | CB96: 45728 | CC96: 45910 | CN96: 45736 | CO96: 45918 | DL96: 2 | DM96: 2 | DN96: 2 | DO96: 2 | DP96: 0 | DQ96: 8 | DR96: 1463 | DV96: 45531 | DW96: 2024 | DX96: 8
B97: Price | C97: 1. Blue Chip | D97: OBX ESG | E97: 44687 | G97: 1 | H97: Third Friday of March, September | I97: Penultimate Friday of February, August | J97: 8 | K97: 2 | L97: 2 | O97: Sustainalytics | P97: OSL | Q97: Semi-annual review, March and September | R97: Ken | S97: New Sheet | T97: Automatic | U97: Dataiku | V97: No | DL97: 0 | DM97: 0 | DN97: 0 | DO97: 0 | DP97: 0 | DQ97: 0 | DV97: 45531 | DW97: 2024 | DX97: 8
B98: Price | C98: 1. Blue Chip | D98: AEX ESG | E98: 44693 | G98: 1 | H98: Third Friday of March, June, September, December | I98: Penultimate Friday of February, May, August, November | J98: 9 | K98: 2 | L98: 2 | O98: Sustainalytics | P98: AMS | Q98: Annual Review in March | R98: Ginevra | S98: New Sheet | T98: Automatic | U98: Dataiku | V98: Yes | W98: AESGP | X98: Third Friday of March | Y98: Third Friday of June | Z98: Third Friday of September | AA98: Third Friday of December | AJ98: 45740 | AK98: 45831 | AL98: 45922 | AM98: 46013 | BD98: Penultimate Friday of February | BE98: Penultimate Friday of May | BF98: Penultimate Friday of August | BG98: Penultimate Friday of November | BP98: 45712 | BQ98: 45803 | BR98: 45894 | BS98: 45985 | CB98: 45727 | CC98: 45818 | CD98: 45909 | CE98: 46000 | CN98: 45736 | CO98: 45827 | CP98: 45918 | CQ98: 46009 | DL98: 4 | DM98: 4 | DN98: 4 | DO98: 4 | DP98: 0 | DQ98: 16 | DR98: 1471 | DV98: 45344 | DW98: 2024 | DX98: 2
B99: Price | C99: 1.3 PAB | D99: Euronext Eurozone 60 PAB | E99: 44699 | G99: 1 | H99: Third Friday of March | I99: Penultimate Friday of February | K99: 2 | L99: 3 | O99: ISS ESG | P99: NXTG | Q99: Only Annual in March | R99: Ginevra | S99: New Sheet | T99: Automatic | U99: Dataiku | V99: Yes | W99: EZ6PP | X99: Third Friday of March | AJ99: 45740 | BD99: Penultimate Friday of February | BP99: 45712 | CN99: 45736 | DL99: 1 | DM99: 1 | DN99: 0 | DO99: 1 | DP99: 0 | DQ99: 3 | DR99: 1487 | DV99: 45400 | DW99: 2024 | DX99: 4
B100: Price | C100: 1.3 PAB | D100: Euronext Eurozone Focus 40 PAB | E100: 44699 | G100: 1 | H100: Third Friday of March | I100: Penultimate Friday of February | K100: 2 | L100: 3 | O100: ISS ESG | P100: NXTG | Q100: Only Annual in March | R100: Ginevra | S100: New Sheet | T100: Automatic | U100: Dataiku | V100: Yes | W100: ES4PP | X100: Third Friday of March | AJ100: 45740 | BD100: Penultimate Friday of February | BP100: 45712 | CN100: 45736 | DL100: 1 | DM100: 1 | DN100: 0 | DO100: 1 | DP100: 0 | DQ100: 3 | DR100: 1490 | DV100: 45400 | DW100: 2024 | DX100: 4
B101: Price | C101: 1.3 PAB | D101: Euronext Switzerland 20 PAB | E101: 44699 | F101: 45699 | G101: 1 | H101: Third Friday of March | I101: Penultimate Friday of February | K101: 2 | L101: 3 | O101: ISS ESG | P101: NXTG | Q101: Only Annual in March | R101: Ginevra | S101: New Sheet | T101: Automatic | U101: Dataiku | V101: No | DL101: 0 | DM101: 0 | DN101: 0 | DO101: 0 | DP101: 0 | DQ101: 0 | DV101: 45400 | DW101: 2024 | DX101: 4
B102: Price | C102: 2.1 Biodiversity | D102: Euronext ESG Eurozone Biodiversity Leaders PAB | E102: 44739 | G102: 1 | H102: Third Friday of September | I102: Penultimate Friday of August | J102: 6 | K102: 2 | L102: 3 | O102: Iceberg;Moody's | P102: NXTG | Q102: Also Review Weighting Announcement Date | R102: Ginevra | S102: New Sheet | T102: Automatic | U102: Dataiku | V102: Yes | W102: EBLPP | X102: Third Friday of September | AJ102: 45922 | BD102: Penultimate Friday of August | BP102: 45894 | CB102: 45912 | CN102: 45918 | DL102: 1 | DM102: 1 | DN102: 1 | DO102: 1 | DP102: 0 | DQ102: 4 | DR102: 1493 | DV102: 45169.536 | DW102: 2023 | DX102: 8
...

Sheet AUM
AA2: 9.9652665e+09 | AB2: 3.0051983e+10 | AC2: 1.5548497e+10 | AD2: 6.3977345e+10 | AE2: 2.8613287e+11 | AF2: 2.7967554e+10 | AG2: 4.0807806e+11
C3: ESG Yes/No | D3: (Multiple Items) | G3: ESG Yes/No | H3: (Multiple Items) | K3: ESG Yes/No | L3: Yes | Q3: Blue-Chip | R3: Yes | T3: Blue-Chip | U3: Yes | AA3: TRUE | AB3: TRUE | AC3: TRUE | AD3: TRUE | AE3: TRUE | AF3: TRUE | AG3: TRUE
C5: Indices | D5: Total AUM per Index | E5: Classification | G5: Family Index | H5: Total AUM per Family Index | I5: Classification | K5: Row Labels | L5: Sum of Total | Q5: Family Index | R5: Total AUM per Family Index | T5: Family Index | U5: Total AUM per Family Index
C6: CAC 40 | D6: 1.789033e+11 | E6: =IF(D6>=500000000000,"Critical",IF(AND(D6>=50000000000,D6<500000000000),"Significant",IF(AND(D6>=45000000000,D6<50000000000),"Almost Significant",IF(D6<45000000000,"Non Significant",0)))) -> Significant | G6: CAC | H6: 2.1352225e+11 | I6: =IF(H6>=500000000000,"Critical",IF(AND(H6>=50000000000,H6<500000000000),"Significant",IF(AND(H6>=45000000000,H6<50000000000),"Almost Significant",IF(H6<45000000000,"Non Significant",0)))) -> Significant | K6: CTB | L6: 5262516339 | N6: ESG | O6: Sum of Total | Q6: CAC | R6: 1.9661952e+11 | T6: CAC 40 | U6: 1.789033e+11
C7: AEX-Index | D7: 1.3539561e+11 | E7: =IF(D7>=500000000000,"Critical",IF(AND(D7>=50000000000,D7<500000000000),"Significant",IF(AND(D7>=45000000000,D7<50000000000),"Almost Significant",IF(D7<45000000000,"Non Significant",0)))) -> Significant | G7: AEX | H7: 1.3664278e+11 | I7: =IF(H7>=500000000000,"Critical",IF(AND(H7>=50000000000,H7<500000000000),"Significant",IF(AND(H7>=45000000000,H7<50000000000),"Almost Significant",IF(H7<45000000000,"Non Significant",0)))) -> Significant | K7: ESG Other | L7: 1.2799828e+10 | N7: No | O7: 3.8825257e+11 | Q7: AEX | R7: 1.3607295e+11 | T7: AEX-Index | U7: 1.3539561e+11
C8: CAC 40 NR | D8: 1.3337071e+10 | E8: =IF(D8>=500000000000,"Critical",IF(AND(D8>=50000000000,D8<500000000000),"Significant",IF(AND(D8>=45000000000,D8<50000000000),"Almost Significant",IF(D8<45000000000,"Non Significant",0)))) -> Non Significant | G8: Oslo Børs Benchmark and Mutual Fund | H8: 2.1312566e+10 | I8: =IF(H8>=500000000000,"Critical",IF(AND(H8>=50000000000,H8<500000000000),"Significant",IF(AND(H8>=45000000000,H8<50000000000),"Almost Significant",IF(H8<45000000000,"Non Significant",0)))) -> Non Significant | K8: PAB | L8: 1.7631462e+09 | N8: Yes | O8: 1.9825491e+10 | Q8: CAC 40 ESG | R8: 1781588879 | T8: CAC 40 NR | U8: 1.3337071e+10
C9: Oslo Børs Mutual Fund Index_GI | D9: 1.2522008e+10 | E9: =IF(D9>=500000000000,"Critical",IF(AND(D9>=50000000000,D9<500000000000),"Significant",IF(AND(D9>=45000000000,D9<50000000000),"Almost Significant",IF(D9<45000000000,"Non Significant",0)))) -> Non Significant | G9: Euronext V.E ESG World-Select 75 Bund SV | H9: 5262516339 | I9: =IF(H9>=500000000000,"Critical",IF(AND(H9>=50000000000,H9<500000000000),"Significant",IF(AND(H9>=45000000000,H9<50000000000),"Almost Significant",IF(H9<45000000000,"Non Significant",0)))) -> Non Significant | K9: (blank) | L9: 0 | N9: (blank) | O9: 0 | Q9: PSI | R9: 6.0827938e+08 | T9: CAC 40 GR | U9: 4.379145e+09
C10: Oslo Børs Benchmark Index_GI | D10: 8.7905575e+09 | E10: =IF(D10>=500000000000,"Critical",IF(AND(D10>=50000000000,D10<500000000000),"Significant",IF(AND(D10>=45000000000,D10<50000000000),"Almost Significant",IF(D10<45000000000,"Non Significant",0)))) -> Non Significant | G10: Euronext Single Stock Decrement | H10: 4.9314225e+09 | I10: =IF(H10>=500000000000,"Critical",IF(AND(H10>=50000000000,H10<500000000000),"Significant",IF(AND(H10>=45000000000,H10<50000000000),"Almost Significant",IF(H10<45000000000,"Non Significant",0)))) -> Non Significant | K10: Grand Total | L10: 1.9825491e+10 | N10: Grand Total | O10: 4.0807806e+11 | Q10: OBX | R10: 5.9796738e+08 | T10: CAC 40 ESG NR | U10: 1114756668
C11: CAC All-Tradable NR | D11: 6.0207381e+09 | E11: =IF(D11>=500000000000,"Critical",IF(AND(D11>=50000000000,D11<500000000000),"Significant",IF(AND(D11>=45000000000,D11<50000000000),"Almost Significant",IF(D11<45000000000,"Non Significant",0)))) -> Non Significant | G11: CAC-EWE | H11: 4.1987155e+09 | I11: =IF(H11>=500000000000,"Critical",IF(AND(H11>=50000000000,H11<500000000000),"Significant",IF(AND(H11>=45000000000,H11<50000000000),"Almost Significant",IF(H11<45000000000,"Non Significant",0)))) -> Non Significant | Q11: BEL | R11: 3.6912727e+08 | T11: AEX NR | U11: 6.7734585e+08
C12: SBF 120 NR | D12: 5.9485787e+09 | E12: =IF(D12>=500000000000,"Critical",IF(AND(D12>=50000000000,D12<500000000000),"Significant",IF(AND(D12>=45000000000,D12<50000000000),"Almost Significant",IF(D12<45000000000,"Non Significant",0)))) -> Non Significant | G12: SBF TOP 80 EW | H12: 2738000000 | I12: =IF(H12>=500000000000,"Critical",IF(AND(H12>=50000000000,H12<500000000000),"Significant",IF(AND(H12>=45000000000,H12<50000000000),"Almost Significant",IF(H12<45000000000,"Non Significant",0)))) -> Non Significant | Q12: MIB ESG | R12: 72633454 | T12: OBX Total Return Index | U12: 5.9796738e+08
C13: Euronext V.E ESG World-Select 75 Bund/SV | D13: 5262516339 | E13: =IF(D13>=500000000000,"Critical",IF(AND(D13>=50000000000,D13<500000000000),"Significant",IF(AND(D13>=45000000000,D13<50000000000),"Almost Significant",IF(D13<45000000000,"Non Significant",0)))) -> Non Significant | G13: Euronext Climate Objective 50 Euro EW | H13: 1.7950542e+09 | I13: =IF(H13>=500000000000,"Critical",IF(AND(H13>=50000000000,H13<500000000000),"Significant",IF(AND(H13>=45000000000,H13<50000000000),"Almost Significant",IF(H13<45000000000,"Non Significant",0)))) -> Non Significant | Q13: Total | R13: 3.3612206e+11 | T13: CAC 40 ESG GR | U13: 329732605
C14: CAC 40 GR | D14: 4.379145e+09 | E14: =IF(D14>=500000000000,"Critical",IF(AND(D14>=50000000000,D14<500000000000),"Significant",IF(AND(D14>=45000000000,D14<50000000000),"Almost Significant",IF(D14<45000000000,"Non Significant",0)))) -> Non Significant | G14: CAC 40 ESG | H14: 1781588879 | I14: =IF(H14>=500000000000,"Critical",IF(AND(H14>=50000000000,H14<500000000000),"Significant",IF(AND(H14>=45000000000,H14<50000000000),"Almost Significant",IF(H14<45000000000,"Non Significant",0)))) -> Non Significant | T14: PSI | U14: 3.0632123e+08
C15: CAC Large 60 EW ER | D15: 2.9146715e+09 | E15: =IF(D15>=500000000000,"Critical",IF(AND(D15>=50000000000,D15<500000000000),"Significant",IF(AND(D15>=45000000000,D15<50000000000),"Almost Significant",IF(D15<45000000000,"Non Significant",0)))) -> Non Significant | G15: SBF Top 50 ESG EW | H15: 1.4316726e+09 | I15: =IF(H15>=500000000000,"Critical",IF(AND(H15>=50000000000,H15<500000000000),"Significant",IF(AND(H15>=45000000000,H15<50000000000),"Almost Significant",IF(H15<45000000000,"Non Significant",0)))) -> Non Significant | T15: PSI GR | U15: 3.0195814e+08
C16: SBF Top 80 EW Decrement 50 Points | D16: 2738000000 | E16: =IF(D16>=500000000000,"Critical",IF(AND(D16>=50000000000,D16<500000000000),"Significant",IF(AND(D16>=45000000000,D16<50000000000),"Almost Significant",IF(D16<45000000000,"Non Significant",0)))) -> Non Significant | G16: Low Carbon 100 Europe PAB | H16: 1386268710 | I16: =IF(H16>=500000000000,"Critical",IF(AND(H16>=50000000000,H16<500000000000),"Significant",IF(AND(H16>=45000000000,H16<50000000000),"Almost Significant",IF(H16<45000000000,"Non Significant",0)))) -> Non Significant | T16: BEL 20 NR | U16: 254158873
C17: CAC Mid & Small NR | D17: 2.0033838e+09 | E17: =IF(D17>=500000000000,"Critical",IF(AND(D17>=50000000000,D17<500000000000),"Significant",IF(AND(D17>=45000000000,D17<50000000000),"Almost Significant",IF(D17<45000000000,"Non Significant",0)))) -> Non Significant | G17: Euronext Euro 50 ESG EW | H17: 9.659314e+08 | I17: =IF(H17>=500000000000,"Critical",IF(AND(H17>=50000000000,H17<500000000000),"Significant",IF(AND(H17>=45000000000,H17<50000000000),"Almost Significant",IF(H17<45000000000,"Non Significant",0)))) -> Non Significant | T17: CAC 40 ESG Decrement 5% | U17: 200000000
C18: CAC Small NR | D18: 1.8612056e+09 | E18: =IF(D18>=500000000000,"Critical",IF(AND(D18>=50000000000,D18<500000000000),"Significant",IF(AND(D18>=45000000000,D18<50000000000),"Almost Significant",IF(D18<45000000000,"Non Significant",0)))) -> Non Significant | G18: OBX | H18: 9.3849104e+08 | I18: =IF(H18>=500000000000,"Critical",IF(AND(H18>=50000000000,H18<500000000000),"Significant",IF(AND(H18>=45000000000,H18<50000000000),"Almost Significant",IF(H18<45000000000,"Non Significant",0)))) -> Non Significant | K18: ESG Yes/No | L18: (Multiple Items) | T18: CAC 40 ESG | U18: 137099606
C19: EN Climate Objective 50 Euro EW D5% | D19: 1.7950542e+09 | E19: =IF(D19>=500000000000,"Critical",IF(AND(D19>=50000000000,D19<500000000000),"Significant",IF(AND(D19>=45000000000,D19<50000000000),"Almost Significant",IF(D19<45000000000,"Non Significant",0)))) -> Non Significant | G19: LeverageShort indices | H19: 857356749 | I19: =IF(H19>=500000000000,"Critical",IF(AND(H19>=50000000000,H19<500000000000),"Significant",IF(AND(H19>=45000000000,H19<50000000000),"Almost Significant",IF(H19<45000000000,"Non Significant",0)))) -> Non Significant | T19: BEL 20 | U19: 1.149684e+08
C20: Euronext G BNP 010622 Decrement 3.85 | D20: 1392500000 | E20: =IF(D20>=500000000000,"Critical",IF(AND(D20>=50000000000,D20<500000000000),"Significant",IF(AND(D20>=45000000000,D20<50000000000),"Almost Significant",IF(D20<45000000000,"Non Significant",0)))) -> Non Significant | G20: Euronext CDP Environment Eurozone | H20: 6.208362e+08 | I20: =IF(H20>=500000000000,"Critical",IF(AND(H20>=50000000000,H20<500000000000),"Significant",IF(AND(H20>=45000000000,H20<50000000000),"Almost Significant",IF(H20<45000000000,"Non Significant",0)))) -> Non Significant | K20: Administrator | L20: Sum of Total | T20: MIB ESG NR | U20: 72633454
C21: Low Carbon 100 Europe PAB Index NR | D21: 1386268710 | E21: =IF(D21>=500000000000,"Critical",IF(AND(D21>=50000000000,D21<500000000000),"Significant",IF(AND(D21>=45000000000,D21<50000000000),"Almost Significant",IF(D21<45000000000,"Non Significant",0)))) -> Non Significant | G21: Oslo Børs Equity Certificate | H21: 6.1796737e+08 | I21: =IF(H21>=500000000000,"Critical",IF(AND(H21>=50000000000,H21<500000000000),"Significant",IF(AND(H21>=45000000000,H21<50000000000),"Almost Significant",IF(H21<45000000000,"Non Significant",0)))) -> Non Significant | K21: Euronext Amsterdam | L21: 1.3735412e+11 | T21: Total | U21: 3.3612206e+11
C22: CAC Large 60 Equal Weight GR | D22: 1284044000 | E22: =IF(D22>=500000000000,"Critical",IF(AND(D22>=50000000000,D22<500000000000),"Significant",IF(AND(D22>=45000000000,D22<50000000000),"Almost Significant",IF(D22<45000000000,"Non Significant",0)))) -> Non Significant | G22: PSI | H22: 6.0827938e+08 | I22: =IF(H22>=500000000000,"Critical",IF(AND(H22>=50000000000,H22<500000000000),"Significant",IF(AND(H22>=45000000000,H22<50000000000),"Almost Significant",IF(H22<45000000000,"Non Significant",0)))) -> Non Significant | K22: Euronext Brussels | L22: 3.7237361e+08
C23: CAC 40 ESG NR | D23: 1114756668 | E23: =IF(D23>=500000000000,"Critical",IF(AND(D23>=50000000000,D23<500000000000),"Significant",IF(AND(D23>=45000000000,D23<50000000000),"Almost Significant",IF(D23<45000000000,"Non Significant",0)))) -> Non Significant | G23: Euronext Water and Ocean Europe | H23: 4.89331e+08 | I23: =IF(H23>=500000000000,"Critical",IF(AND(H23>=50000000000,H23<500000000000),"Significant",IF(AND(H23>=45000000000,H23<50000000000),"Almost Significant",IF(H23<45000000000,"Non Significant",0)))) -> Non Significant | K23: Euronext Dublin | L23: 0
C24: SBF Top 50 ESG EW Decrement 50 Points | D24: 9.1507256e+08 | E24: =IF(D24>=500000000000,"Critical",IF(AND(D24>=50000000000,D24<500000000000),"Significant",IF(AND(D24>=45000000000,D24<50000000000),"Almost Significant",IF(D24<45000000000,"Non Significant",0)))) -> Non Significant | G24: Euronext Core Euro and Global Climate | H24: 4.6919642e+08 | I24: =IF(H24>=500000000000,"Critical",IF(AND(H24>=50000000000,H24<500000000000),"Significant",IF(AND(H24>=45000000000,H24<50000000000),"Almost Significant",IF(H24<45000000000,"Non Significant",0)))) -> Non Significant | K24: Euronext Lisbon | L24: 6.0827938e+08
C25: Euronext Euro 50 ESG EW Decrement 50 Points | D25: 7.259314e+08 | E25: =IF(D25>=500000000000,"Critical",IF(AND(D25>=50000000000,D25<500000000000),"Significant",IF(AND(D25>=45000000000,D25<50000000000),"Almost Significant",IF(D25<45000000000,"Non Significant",0)))) -> Non Significant | G25: Euronext Transatlantic ESG Leaders | H25: 4.6105458e+08 | I25: =IF(H25>=500000000000,"Critical",IF(AND(H25>=50000000000,H25<500000000000),"Significant",IF(AND(H25>=45000000000,H25<50000000000),"Almost Significant",IF(H25<45000000000,"Non Significant",0)))) -> Non Significant | K25: Euronext Paris | L25: 2.4687426e+11
C26: CAC Mid 60 NR | D26: 684657431 | E26: =IF(D26>=500000000000,"Critical",IF(AND(D26>=50000000000,D26<500000000000),"Significant",IF(AND(D26>=45000000000,D26<50000000000),"Almost Significant",IF(D26<45000000000,"Non Significant",0)))) -> Non Significant | G26: Euronext Climate Orientation Priority 50 EW | H26: 4.3824298e+08 | I26: =IF(H26>=500000000000,"Critical",IF(AND(H26>=50000000000,H26<500000000000),"Significant",IF(AND(H26>=45000000000,H26<50000000000),"Almost Significant",IF(H26<45000000000,"Non Significant",0)))) -> Non Significant | K26: Oslo Børs | L26: 2.2869024e+10
C27: AEX NR | D27: 6.7734585e+08 | E27: =IF(D27>=500000000000,"Critical",IF(AND(D27>=50000000000,D27<500000000000),"Significant",IF(AND(D27>=45000000000,D27<50000000000),"Almost Significant",IF(D27<45000000000,"Non Significant",0)))) -> Non Significant | G27: Euronext Eurozone ESG Leaders 40 EW | H27: 431759000 | I27: =IF(H27>=500000000000,"Critical",IF(AND(H27>=50000000000,H27<500000000000),"Significant",IF(AND(H27>=45000000000,H27<50000000000),"Almost Significant",IF(H27<45000000000,"Non Significant",0)))) -> Non Significant | K27: Grand Total | L27: 4.0807806e+11
C28: Oslo Børs Equity Certificate Index | D28: 6.1796737e+08 | E28: =IF(D28>=500000000000,"Critical",IF(AND(D28>=50000000000,D28<500000000000),"Significant",IF(AND(D28>=45000000000,D28<50000000000),"Almost Significant",IF(D28<45000000000,"Non Significant",0)))) -> Non Significant | G28: Euronext CDP France Environment EW | H28: 3.9479946e+08 | I28: =IF(H28>=500000000000,"Critical",IF(AND(H28>=50000000000,H28<500000000000),"Significant",IF(AND(H28>=45000000000,H28<50000000000),"Almost Significant",IF(H28<45000000000,"Non Significant",0)))) -> Non Significant
C29: Euronext G Credit Agricole 010621 PR 0.9 | D29: 600000000 | E29: =IF(D29>=500000000000,"Critical",IF(AND(D29>=50000000000,D29<500000000000),"Significant",IF(AND(D29>=45000000000,D29<50000000000),"Almost Significant",IF(D29<45000000000,"Non Significant",0)))) -> Non Significant | G29: Euronext Core Europe EW | H29: 3.8942145e+08 | I29: =IF(H29>=500000000000,"Critical",IF(AND(H29>=50000000000,H29<500000000000),"Significant",IF(AND(H29>=45000000000,H29<50000000000),"Almost Significant",IF(H29<45000000000,"Non Significant",0)))) -> Non Significant
C30: OBX Total Return Index | D30: 5.9796738e+08 | E30: =IF(D30>=500000000000,"Critical",IF(AND(D30>=50000000000,D30<500000000000),"Significant",IF(AND(D30>=45000000000,D30<50000000000),"Almost Significant",IF(D30<45000000000,"Non Significant",0)))) -> Non Significant | G30: BEL | H30: 3.6912727e+08 | I30: =IF(H30>=500000000000,"Critical",IF(AND(H30>=50000000000,H30<500000000000),"Significant",IF(AND(H30>=45000000000,H30<50000000000),"Almost Significant",IF(H30<45000000000,"Non Significant",0)))) -> Non Significant
C31: SBF Top 50 ESG EW | D31: 516600000 | E31: =IF(D31>=500000000000,"Critical",IF(AND(D31>=50000000000,D31<500000000000),"Significant",IF(AND(D31>=45000000000,D31<50000000000),"Almost Significant",IF(D31<45000000000,"Non Significant",0)))) -> Non Significant | G31: Euronext France Social | H31: 3.488684e+08 | I31: =IF(H31>=500000000000,"Critical",IF(AND(H31>=50000000000,H31<500000000000),"Significant",IF(AND(H31>=45000000000,H31<50000000000),"Almost Significant",IF(H31<45000000000,"Non Significant",0)))) -> Non Significant
C32: AEX All-Tradable Alternative Weight NR | D32: 515734000 | E32: =IF(D32>=500000000000,"Critical",IF(AND(D32>=50000000000,D32<500000000000),"Significant",IF(AND(D32>=45000000000,D32<50000000000),"Almost Significant",IF(D32<45000000000,"Non Significant",0)))) -> Non Significant | G32: Euronext CDP France Environnement | H32: 3.3720842e+08 | I32: =IF(H32>=500000000000,"Critical",IF(AND(H32>=50000000000,H32<500000000000),"Significant",IF(AND(H32>=45000000000,H32<50000000000),"Almost Significant",IF(H32<45000000000,"Non Significant",0)))) -> Non Significant
C33: Euronext Core Euro & Global Climate Change EW Decrement 5% | D33: 4.6919642e+08 | E33: =IF(D33>=500000000000,"Critical",IF(AND(D33>=50000000000,D33<500000000000),"Significant",IF(AND(D33>=45000000000,D33<50000000000),"Almost Significant",IF(D33<45000000000,"Non Significant",0)))) -> Non Significant | G33: Euronext World Sustainability and Climate Screened | H33: 304810000 | I33: =IF(H33>=500000000000,"Critical",IF(AND(H33>=50000000000,H33<500000000000),"Significant",IF(AND(H33>=45000000000,H33<50000000000),"Almost Significant",IF(H33<45000000000,"Non Significant",0)))) -> Non Significant
C34: Euronext Transatlantic ESG Leaders 60 EW Decrement 5% | D34: 4.6105458e+08 | E34: =IF(D34>=500000000000,"Critical",IF(AND(D34>=50000000000,D34<500000000000),"Significant",IF(AND(D34>=45000000000,D34<50000000000),"Almost Significant",IF(D34<45000000000,"Non Significant",0)))) -> Non Significant | G34: CAC Large 60 Responsible Investment | H34: 2.8565036e+08 | I34: =IF(H34>=500000000000,"Critical",IF(AND(H34>=50000000000,H34<500000000000),"Significant",IF(AND(H34>=45000000000,H34<50000000000),"Almost Significant",IF(H34<45000000000,"Non Significant",0)))) -> Non Significant
C35: Euronext Water and Ocean Europe 40 EW Decrement 5% | D35: 4.57831e+08 | E35: =IF(D35>=500000000000,"Critical",IF(AND(D35>=50000000000,D35<500000000000),"Significant",IF(AND(D35>=45000000000,D35<50000000000),"Almost Significant",IF(D35<45000000000,"Non Significant",0)))) -> Non Significant | G35: Euronext Europe Sustainable 100 EW | H35: 2.686438e+08 | I35: =IF(H35>=500000000000,"Critical",IF(AND(H35>=50000000000,H35<500000000000),"Significant",IF(AND(H35>=45000000000,H35<50000000000),"Almost Significant",IF(H35<45000000000,"Non Significant",0)))) -> Non Significant
C36: Euronext CDP Environment Eurozone EW D5% | D36: 4.4829187e+08 | E36: =IF(D36>=500000000000,"Critical",IF(AND(D36>=50000000000,D36<500000000000),"Significant",IF(AND(D36>=45000000000,D36<50000000000),"Almost Significant",IF(D36<45000000000,"Non Significant",0)))) -> Non Significant | G36: Euronext Transatlantic Environment 50 | H36: 260000000 | I36: =IF(H36>=500000000000,"Critical",IF(AND(H36>=50000000000,H36<500000000000),"Significant",IF(AND(H36>=45000000000,H36<50000000000),"Almost Significant",IF(H36<45000000000,"Non Significant",0)))) -> Non Significant
C37: EN Climate Orientation Priority 50 EW | D37: 4.218835e+08 | E37: =IF(D37>=500000000000,"Critical",IF(AND(D37>=50000000000,D37<500000000000),"Significant",IF(AND(D37>=45000000000,D37<50000000000),"Almost Significant",IF(D37<45000000000,"Non Significant",0)))) -> Non Significant | G37: Euronext Transatlantic Sustainability and Climate Screened 60 | H37: 240000000 | I37: =IF(H37>=500000000000,"Critical",IF(AND(H37>=50000000000,H37<500000000000),"Significant",IF(AND(H37>=45000000000,H37<50000000000),"Almost Significant",IF(H37<45000000000,"Non Significant",0)))) -> Non Significant
C38: EN CDP Environment France EW Decrement 5% | D38: 3.9479946e+08 | E38: =IF(D38>=500000000000,"Critical",IF(AND(D38>=50000000000,D38<500000000000),"Significant",IF(AND(D38>=45000000000,D38<50000000000),"Almost Significant",IF(D38<45000000000,"Non Significant",0)))) -> Non Significant | G38: Euronext ESG Leaders Select 40 EW | H38: 227950381 | I38: =IF(H38>=500000000000,"Critical",IF(AND(H38>=50000000000,H38<500000000000),"Significant",IF(AND(H38>=45000000000,H38<50000000000),"Almost Significant",IF(H38<45000000000,"Non Significant",0)))) -> Non Significant
C39: Euronext Core Europe 30 EW Decrement 5% NR | D39: 3.8832145e+08 | E39: =IF(D39>=500000000000,"Critical",IF(AND(D39>=50000000000,D39<500000000000),"Significant",IF(AND(D39>=45000000000,D39<50000000000),"Almost Significant",IF(D39<45000000000,"Non Significant",0)))) -> Non Significant | G39: Euronext France Energy Transition Leaders 40 EW | H39: 2.0312457e+08 | I39: =IF(H39>=500000000000,"Critical",IF(AND(H39>=50000000000,H39<500000000000),"Significant",IF(AND(H39>=45000000000,H39<50000000000),"Almost Significant",IF(H39<45000000000,"Non Significant",0)))) -> Non Significant
... C208: Euronext MTS EGB 15-25 Year GR | D208: 0 | E208: =IF(D208>=500000000000,"Critical",IF(AND(D208>=50000000000,D208<500000000000),"Significant",IF(AND(D208>=45000000000,D208<50000000000),"Almost Significant",IF(D208<45000000000,"Non Significant",0)))) -> Non Significant | G208: Euronext Eurozone 80 EW | H208: 0 | I208: =IF(H208>=500000000000,"Critical",IF(AND(H208>=50000000000,H208<500000000000),"Significant",IF(AND(H208>=45000000000,H208<50000000000),"Almost Significant",IF(H208<45000000000,"Non Significant",0)))) -> Non Significant
C209: Euronext Global Health Care 50 EW ESG ER | D209: 0 | E209: =IF(D209>=500000000000,"Critical",IF(AND(D209>=50000000000,D209<500000000000),"Significant",IF(AND(D209>=45000000000,D209<50000000000),"Almost Significant",IF(D209<45000000000,"Non Significant",0)))) -> Non Significant | G209: Euronext Canada Total Market | H209: 0
C210: Euronext MTS EGB Italy 3-5 Year GR | D210: 0 | E210: =IF(D210>=500000000000,"Critical",IF(AND(D210>=50000000000,D210<500000000000),"Significant",IF(AND(D210>=45000000000,D210<50000000000),"Almost Significant",IF(D210<45000000000,"Non Significant",0)))) -> Non Significant | G210: Euronext ESG Biodiversity Screened Transatlantic 80 | H210: 0
C211: Euronext Global Sustainability and Climate Screened DR | D211: 0 | E211: =IF(D211>=500000000000,"Critical",IF(AND(D211>=50000000000,D211<500000000000),"Significant",IF(AND(D211>=45000000000,D211<50000000000),"Almost Significant",IF(D211<45000000000,"Non Significant",0)))) -> Non Significant | G211: Euronext Developed Asia Total Market | H211: 0
C212: Euronext PAB Transatlantic 60 GR | D212: 0 | E212: =IF(D212>=500000000000,"Critical",IF(AND(D212>=50000000000,D212<500000000000),"Significant",IF(AND(D212>=45000000000,D212<50000000000),"Almost Significant",IF(D212<45000000000,"Non Significant",0)))) -> Non Significant | G212: Euronext Europe Luxury | H212: 0
C213: Euronext Japan | D213: 0 | E213: =IF(D213>=500000000000,"Critical",IF(AND(D213>=50000000000,D213<500000000000),"Significant",IF(AND(D213>=45000000000,D213<50000000000),"Almost Significant",IF(D213<45000000000,"Non Significant",0)))) -> Non Significant | G213: Euronext Developed Eurozone Total Market | H213: 0
C214: Euronext G Orange 060624 D 0.74 | D214: 0 | E214: =IF(D214>=500000000000,"Critical",IF(AND(D214>=50000000000,D214<500000000000),"Significant",IF(AND(D214>=45000000000,D214<50000000000),"Almost Significant",IF(D214<45000000000,"Non Significant",0)))) -> Non Significant | G214: Euronext Eurozone Sectorial | H214: 0
C215: Euronext Japan GR | D215: 0 | E215: =IF(D215>=500000000000,"Critical",IF(AND(D215>=50000000000,D215<500000000000),"Significant",IF(AND(D215>=45000000000,D215<50000000000),"Almost Significant",IF(D215<45000000000,"Non Significant",0)))) -> Non Significant | G215: Euronext Developed Pacific Total Market | H215: 0
C216: Euronext G Stellantis 030524 PR 1.55 | D216: 0 | E216: =IF(D216>=500000000000,"Critical",IF(AND(D216>=50000000000,D216<500000000000),"Significant",IF(AND(D216>=45000000000,D216<50000000000),"Almost Significant",IF(D216<45000000000,"Non Significant",0)))) -> Non Significant | G216: Euronext FAS IAS | H216: 0
C217: Euronext Japan NR | D217: 0 | E217: =IF(D217>=500000000000,"Critical",IF(AND(D217>=50000000000,D217<500000000000),"Significant",IF(AND(D217>=45000000000,D217<50000000000),"Almost Significant",IF(D217<45000000000,"Non Significant",0)))) -> Non Significant | G217: Euronext Core Europe 30 ESG EW | H217: 0
C218: Euronext Transatlantic Health Care NR | D218: 0 | E218: =IF(D218>=500000000000,"Critical",IF(AND(D218>=50000000000,D218<500000000000),"Significant",IF(AND(D218>=45000000000,D218<50000000000),"Almost Significant",IF(D218<45000000000,"Non Significant",0)))) -> Non Significant | G218: Euronext France Investissement 40 | H218: 0
C219: Euronext Developed Asia Pacific NR | D219: 0 | E219: =IF(D219>=500000000000,"Critical",IF(AND(D219>=50000000000,D219<500000000000),"Significant",IF(AND(D219>=45000000000,D219<50000000000),"Almost Significant",IF(D219<45000000000,"Non Significant",0)))) -> Non Significant | G219: Euronext Eurozone Small Cap | H219: 0
C220: Euronext UK Total Market | D220: 0 | E220: =IF(D220>=500000000000,"Critical",IF(AND(D220>=50000000000,D220<500000000000),"Significant",IF(AND(D220>=45000000000,D220<50000000000),"Almost Significant",IF(D220<45000000000,"Non Significant",0)))) -> Non Significant | G220: Euronext French Employment 40 EW | H220: 0
... C241: Euronext Switzerland NR | D241: 0 | E241: =IF(D241>=500000000000,"Critical",IF(AND(D241>=50000000000,D241<500000000000),"Significant",IF(AND(D241>=45000000000,D241<50000000000),"Almost Significant",IF(D241<45000000000,"Non Significant",0)))) -> Non Significant | G241: Total | H241: 4.0807806e+11
C242: Euronext G Societe Generale 310523 GR 1.35 | D242: 0 | E242: =IF(D242>=500000000000,"Critical",IF(AND(D242>=50000000000,D242<500000000000),"Significant",IF(AND(D242>=45000000000,D242<50000000000),"Almost Significant",IF(D242<45000000000,"Non Significant",0)))) -> Non Significant
C243: Euronext UK | D243: 0 | E243: =IF(D243>=500000000000,"Critical",IF(AND(D243>=50000000000,D243<500000000000),"Significant",IF(AND(D243>=45000000000,D243<50000000000),"Almost Significant",IF(D243<45000000000,"Non Significant",0)))) -> Non Significant
C244: Euronext G URW 270223 PR 3 50 | D244: 0 | E244: =IF(D244>=500000000000,"Critical",IF(AND(D244>=50000000000,D244<500000000000),"Significant",IF(AND(D244>=45000000000,D244<50000000000),"Almost Significant",IF(D244<45000000000,"Non Significant",0)))) -> Non Significant
C245: Euronext UK GR | D245: 0 | E245: =IF(D245>=500000000000,"Critical",IF(AND(D245>=50000000000,D245<500000000000),"Significant",IF(AND(D245>=45000000000,D245<50000000000),"Almost Significant",IF(D245<45000000000,"Non Significant",0)))) -> Non Significant
C246: Euronext Transatlantic Financials GR | D246: 0 | E246: =IF(D246>=500000000000,"Critical",IF(AND(D246>=50000000000,D246<500000000000),"Significant",IF(AND(D246>=45000000000,D246<50000000000),"Almost Significant",IF(D246<45000000000,"Non Significant",0)))) -> Non Significant
C247: Euronext UK NR | D247: 0 | E247: =IF(D247>=500000000000,"Critical",IF(AND(D247>=50000000000,D247<500000000000),"Significant",IF(AND(D247>=45000000000,D247<50000000000),"Almost Significant",IF(D247<45000000000,"Non Significant",0)))) -> Non Significant
C248: Euronext Transatlantic Industrials PR | D248: 0 | E248: =IF(D248>=500000000000,"Critical",IF(AND(D248>=50000000000,D248<500000000000),"Significant",IF(AND(D248>=45000000000,D248<50000000000),"Almost Significant",IF(D248<45000000000,"Non Significant",0)))) -> Non Significant
C249: Euronext USA | D249: 0 | E249: =IF(D249>=500000000000,"Critical",IF(AND(D249>=50000000000,D249<500000000000),"Significant",IF(AND(D249>=45000000000,D249<50000000000),"Almost Significant",IF(D249<45000000000,"Non Significant",0)))) -> Non Significant
C250: Euronext Transatlantic Utilities NR | D250: 0 | E250: =IF(D250>=500000000000,"Critical",IF(AND(D250>=50000000000,D250<500000000000),"Significant",IF(AND(D250>=45000000000,D250<50000000000),"Almost Significant",IF(D250<45000000000,"Non Significant",0)))) -> Non Significant
C251: Euronext USA GR | D251: 0 | E251: =IF(D251>=500000000000,"Critical",IF(AND(D251>=50000000000,D251<500000000000),"Significant",IF(AND(D251>=45000000000,D251<50000000000),"Almost Significant",IF(D251<45000000000,"Non Significant",0)))) -> Non Significant
C252: Euronext US Consumer Tech Energy GR | D252: 0 | E252: =IF(D252>=500000000000,"Critical",IF(AND(D252>=50000000000,D252<500000000000),"Significant",IF(AND(D252>=45000000000,D252<50000000000),"Almost Significant",IF(D252<45000000000,"Non Significant",0)))) -> Non Significant
C253: Euronext USA NR | D253: 0 | E253: =IF(D253>=500000000000,"Critical",IF(AND(D253>=50000000000,D253<500000000000),"Significant",IF(AND(D253>=45000000000,D253<50000000000),"Almost Significant",IF(D253<45000000000,"Non Significant",0)))) -> Non Significant
C254: Euronext World Invest In France 40 GR | D254: 0 | E254: =IF(D254>=500000000000,"Critical",IF(AND(D254>=50000000000,D254<500000000000),"Significant",IF(AND(D254>=45000000000,D254<50000000000),"Almost Significant",IF(D254<45000000000,"Non Significant",0)))) -> Non Significant
C255: CAC 40 Gross Return Decrement 5% | E255: =IF(D255>=500000000000,"Critical",IF(AND(D255>=50000000000,D255<500000000000),"Significant",IF(AND(D255>=45000000000,D255<50000000000),"Almost Significant",IF(D255<45000000000,"Non Significant",0)))) -> Non Significant
C256: Euronext Invest In France | D256: 0 | E256: =IF(D256>=500000000000,"Critical",IF(AND(D256>=50000000000,D256<500000000000),"Significant",IF(AND(D256>=45000000000,D256<50000000000),"Almost Significant",IF(D256<45000000000,"Non Significant",0)))) -> Non Significant
C257: Euronext Developed Europe NR | D257: 0 | E257: =IF(D257>=500000000000,"Critical",IF(AND(D257>=50000000000,D257<500000000000),"Significant",IF(AND(D257>=45000000000,D257<50000000000),"Almost Significant",IF(D257<45000000000,"Non Significant",0)))) -> Non Significant
C258: Euronext Invest In France 40 D 5% | D258: 0 | E258: =IF(D258>=500000000000,"Critical",IF(AND(D258>=50000000000,D258<500000000000),"Significant",IF(AND(D258>=45000000000,D258<50000000000),"Almost Significant",IF(D258<45000000000,"Non Significant",0)))) -> Non Significant
C259: Euronext G BNP 310523 Decrement 4.00 Index | E259: =IF(D259>=500000000000,"Critical",IF(AND(D259>=50000000000,D259<500000000000),"Significant",IF(AND(D259>=45000000000,D259<50000000000),"Almost Significant",IF(D259<45000000000,"Non Significant",0)))) -> Non Significant
C260: Euronext Invest In France Low Volatility Decrement 3% | D260: 0 | E260: =IF(D260>=500000000000,"Critical",IF(AND(D260>=50000000000,D260<500000000000),"Significant",IF(AND(D260>=45000000000,D260<50000000000),"Almost Significant",IF(D260<45000000000,"Non Significant",0)))) -> Non Significant
C261: Euronext Developed Eurozone | D261: 0 | E261: =IF(D261>=500000000000,"Critical",IF(AND(D261>=50000000000,D261<500000000000),"Significant",IF(AND(D261>=45000000000,D261<50000000000),"Almost Significant",IF(D261<45000000000,"Non Significant",0)))) -> Non Significant
C262: Euronext Japan Total Market GR | D262: 0 | E262: =IF(D262>=500000000000,"Critical",IF(AND(D262>=50000000000,D262<500000000000),"Significant",IF(AND(D262>=45000000000,D262<50000000000),"Almost Significant",IF(D262<45000000000,"Non Significant",0)))) -> Non Significant
C263: Euronext Developed Eurozone GR | D263: 0 | E263: =IF(D263>=500000000000,"Critical",IF(AND(D263>=50000000000,D263<500000000000),"Significant",IF(AND(D263>=45000000000,D263<50000000000),"Almost Significant",IF(D263<45000000000,"Non Significant",0)))) -> Non Significant
C264: Euronext MTS EGB 1-3 Year GR | D264: 0 | E264: =IF(D264>=500000000000,"Critical",IF(AND(D264>=50000000000,D264<500000000000),"Significant",IF(AND(D264>=45000000000,D264<50000000000),"Almost Significant",IF(D264<45000000000,"Non Significant",0)))) -> Non Significant
C265: Euronext G Scor 230524 Decrement 1.80 Index | E265: =IF(D265>=500000000000,"Critical",IF(AND(D265>=50000000000,D265<500000000000),"Significant",IF(AND(D265>=45000000000,D265<50000000000),"Almost Significant",IF(D265<45000000000,"Non Significant",0)))) -> Non Significant
C266: Euronext MTS EGB 3-5 Year GR | D266: 0 | E266: =IF(D266>=500000000000,"Critical",IF(AND(D266>=50000000000,D266<500000000000),"Significant",IF(AND(D266>=45000000000,D266<50000000000),"Almost Significant",IF(D266<45000000000,"Non Significant",0)))) -> Non Significant
C267: Euronext Developed Eurozone NR | D267: 0 | E267: =IF(D267>=500000000000,"Critical",IF(AND(D267>=50000000000,D267<500000000000),"Significant",IF(AND(D267>=45000000000,D267<50000000000),"Almost Significant",IF(D267<45000000000,"Non Significant",0)))) -> Non Significant
C268: Euronext MTS EGB Belgium GR | D268: 0 | E268: =IF(D268>=500000000000,"Critical",IF(AND(D268>=50000000000,D268<500000000000),"Significant",IF(AND(D268>=45000000000,D268<50000000000),"Almost Significant",IF(D268<45000000000,"Non Significant",0)))) -> Non Significant
C269: Euronext Developed North America | D269: 0 | E269: =IF(D269>=500000000000,"Critical",IF(AND(D269>=50000000000,D269<500000000000),"Significant",IF(AND(D269>=45000000000,D269<50000000000),"Almost Significant",IF(D269<45000000000,"Non Significant",0)))) -> Non Significant
C270: Euronext MTS EGB Germany GR | D270: 0 | E270: =IF(D270>=500000000000,"Critical",IF(AND(D270>=50000000000,D270<500000000000),"Significant",IF(AND(D270>=45000000000,D270<50000000000),"Almost Significant",IF(D270<45000000000,"Non Significant",0)))) -> Non Significant
C271: Euronext Developed North America GR | D271: 0 | E271: =IF(D271>=500000000000,"Critical",IF(AND(D271>=50000000000,D271<500000000000),"Significant",IF(AND(D271>=45000000000,D271<50000000000),"Almost Significant",IF(D271<45000000000,"Non Significant",0)))) -> Non Significant
C272: Euronext MTS EGB Italy 15-25 Year GR | D272: 0 | E272: =IF(D272>=500000000000,"Critical",IF(AND(D272>=50000000000,D272<500000000000),"Significant",IF(AND(D272>=45000000000,D272<50000000000),"Almost Significant",IF(D272<45000000000,"Non Significant",0)))) -> Non Significant
C273: Euronext Developed North America NR | D273: 0 | E273: =IF(D273>=500000000000,"Critical",IF(AND(D273>=50000000000,D273<500000000000),"Significant",IF(AND(D273>=45000000000,D273<50000000000),"Almost Significant",IF(D273<45000000000,"Non Significant",0)))) -> Non Significant
C274: Euronext MTS EGB Italy 7-10 Year GR | D274: 0 | E274: =IF(D274>=500000000000,"Critical",IF(AND(D274>=50000000000,D274<500000000000),"Significant",IF(AND(D274>=45000000000,D274<50000000000),"Almost Significant",IF(D274<45000000000,"Non Significant",0)))) -> Non Significant
C275: Euronext Developed Pacific | D275: 0 | E275: =IF(D275>=500000000000,"Critical",IF(AND(D275>=50000000000,D275<500000000000),"Significant",IF(AND(D275>=45000000000,D275<50000000000),"Almost Significant",IF(D275<45000000000,"Non Significant",0)))) -> Non Significant
C276: Euronext MTS EGB The Netherlands GR | D276: 0 | E276: =IF(D276>=500000000000,"Critical",IF(AND(D276>=50000000000,D276<500000000000),"Significant",IF(AND(D276>=45000000000,D276<50000000000),"Almost Significant",IF(D276<45000000000,"Non Significant",0)))) -> Non Significant
C277: Euronext Aerospace and Defense | D277: 0 | E277: =IF(D277>=500000000000,"Critical",IF(AND(D277>=50000000000,D277<500000000000),"Significant",IF(AND(D277>=45000000000,D277<50000000000),"Almost Significant",IF(D277<45000000000,"Non Significant",0)))) -> Non Significant
... C1206: OSEBX_STB Index | D1206: 0 | E1206: =IF(D1206>=500000000000,"Critical",IF(AND(D1206>=50000000000,D1206<500000000000),"Significant",IF(AND(D1206>=45000000000,D1206<50000000000),"Almost Significant",IF(D1206<45000000000,"Non Significant",0)))) -> Non Significant
C1207: Euronext Growth All-Share Index NR | D1207: 0 | E1207: =IF(D1207>=500000000000,"Critical",IF(AND(D1207>=50000000000,D1207<500000000000),"Significant",IF(AND(D1207>=45000000000,D1207<50000000000),"Almost Significant",IF(D1207<45000000000,"Non Significant",0)))) -> Non Significant | G1207: Previous Q
C1208: OSEBXG Index | D1208: 0 | F1208: =GETPIVOTDATA("Total",$C$5)/G1208-1 -> -0.02673511 | G1208: 4.1928776e+11
C1209: Euronext Growth Bpifrance Innovation Index | D1209: 0
C1210: Euronext Growth Bpifrance Innovation Index GR | D1210: 0
C1211: OSEEXR Index PR | D1211: 0
C1212: Euronext Green Planet E Decrement 5% GR | D1212: 0
C1213: OSEFX Mutual Fund_PR | D1213: 0
C1214: Euronext Green Planet E GR | D1214: 0
C1215: OSEMX Mid Cap_PR | D1215: 0
C1216: Euronext Green Planet E NR | D1216: 0
C1217: OSESX Small Cap_PR | D1217: 0
C1218: Euronext Green Planet E | D1218: 0
...

Sheet Index 14-01
A1: #Symbol | B1: System Date | C1: Change | D1: IsinCode | E1: Country | F1: Mnemo | G1: Name | H1: MIC | I1: Divisor | J1: t-1 IV | K1: t0 IV | L1: t0 IV unround | M1: Mkt Cap | N1: Nr of components | O1: Curr | P1: FX | Q1: ISIN Underlying Price Index | R1: ISIN Gross Return version | S1: ISIN Net Return version | T1: Effect Gross Total Return | U1: Effect Net Total Return | V1: Stocks Effect Index | W1: Dividend Currency Type | X1: Calculation Type | Y1: Index Type | Z1: Return Method | AA1: Return Value | AB1: Number Of Days | AC1: Yearly Days | AD1: Dead Flag | AE1: x | AF1: x
A2: QS0011260732 | B2: 45671 | D2: QS0011260732 | E2: FR | F2: EEMHN | G2: ESI Excellence Europe Hedged w multip NR | H2: XPAR | I2: 1 | J2: 0 | K2: 0 | L2: 0 | M2: 0 | N2: 1 | O2: EUR | P2: 1 | W2: ECB | X2: EU Price | Y2: Indices | AD2: 0 | AE2: =ISNUMBER(MATCH(G2,AUM!$C$6:$C$1451,0)) -> FALSE | AF2: =ISNUMBER(MATCH(G2,AUM!$G$6:$G$240,0)) -> FALSE
A3: QS0011260UNH | B3: 45671 | D3: QS0011260UNH | E3: NL | F3: EEUNH | G3: ESI UNHEDGED RETURN | H3: XAMS | I3: 2466.84 | J3: 0.87 | K3: 0.87 | L3: 0.865727 | M3: 2135.61 | N3: 1 | O3: EUR | P3: 1 | W3: ECB | X3: EU Price | Y3: Indices | AD3: 0 | AE3: =ISNUMBER(MATCH(G3,AUM!$C$6:$C$1451,0)) -> FALSE | AF3: =ISNUMBER(MATCH(G3,AUM!$G$6:$G$240,0)) -> FALSE
A4: QS0011260SEK | B4: 45671 | D4: QS0011260SEK | E4: NL | F4: EESEK | G4: ESI SEK FWD RETURN | H4: XAMS | I4: 0.1005786 | J4: 0 | K4: 0 | L4: 0 | M4: 0 | N4: 1 | O4: EUR | P4: 1 | W4: ECB | X4: EU Price | Y4: Indices | AD4: 0 | AE4: =ISNUMBER(MATCH(G4,AUM!$C$6:$C$1451,0)) -> FALSE | AF4: =ISNUMBER(MATCH(G4,AUM!$G$6:$G$240,0)) -> FALSE
A5: QS0011260NOK | B5: 45671 | D5: QS0011260NOK | E5: NL | F5: EENOK | G5: ESI NOK FWD RETURN | H5: XAMS | I5: 0.10207058 | J5: 0 | K5: 0 | L5: 0 | M5: 0 | N5: 1 | O5: EUR | P5: 1 | W5: ECB | X5: EU Price | Y5: Indices | AD5: 0 | AE5: =ISNUMBER(MATCH(G5,AUM!$C$6:$C$1451,0)) -> FALSE | AF5: =ISNUMBER(MATCH(G5,AUM!$G$6:$G$240,0)) -> FALSE
A6: QS0011260HDG | B6: 45671 | D6: QS0011260HDG | E6: NL | F6: EEHDG | G6: ESI HEDGED RETURN | H6: XAMS | I6: 1 | J6: 0.01 | K6: 0.01 | L6: 0.01 | M6: -1.2588579 | N6: 3 | O6: EUR | P6: 1 | W6: ECB | X6: EU Price | Y6: Indices | AD6: 1 | AE6: =ISNUMBER(MATCH(G6,AUM!$C$6:$C$1451,0)) -> FALSE | AF6: =ISNUMBER(MATCH(G6,AUM!$G$6:$G$240,0)) -> FALSE
A7: QS0011260GBP | B7: 45671 | D7: QS0011260GBP | E7: NL | F7: EEGBP | G7: ESI GBP FWD RETURN | H7: XAMS | I7: 1.1838144 | J7: 0 | K7: 0 | L7: 0 | M7: 0 | N7: 1 | O7: EUR | P7: 1 | W7: ECB | X7: EU Price | Y7: Indices | AD7: 0 | AE7: =ISNUMBER(MATCH(G7,AUM!$C$6:$C$1451,0)) -> FALSE | AF7: =ISNUMBER(MATCH(G7,AUM!$G$6:$G$240,0)) -> FALSE
A8: QS0011260FWD | B8: 45671 | D8: QS0011260FWD | E8: NL | F8: EEFWD | G8: ESI TOTAL FWD RETURN | H8: XAMS | I8: 1 | J8: 2.12 | K8: 2.12 | L8: 2.1245849 | M8: 2.1245849 | N8: 6 | O8: EUR | P8: 1 | W8: ECB | X8: EU Price | Y8: Indices | AD8: 0 | AE8: =ISNUMBER(MATCH(G8,AUM!$C$6:$C$1451,0)) -> FALSE | AF8: =ISNUMBER(MATCH(G8,AUM!$G$6:$G$240,0)) -> FALSE
A9: QS0011260DKK | B9: 45671 | D9: QS0011260DKK | E9: NL | F9: EEDKK | G9: ESI DKK FWD RETURN | H9: XAMS | I9: 0.13442516 | J9: 1 | K9: 1 | L9: 0.9971561 | M9: 0.13404287 | N9: 1 | O9: EUR | P9: 1 | W9: ECB | X9: EU Price | Y9: Indices | AD9: 0 | AE9: =ISNUMBER(MATCH(G9,AUM!$C$6:$C$1451,0)) -> FALSE | AF9: =ISNUMBER(MATCH(G9,AUM!$G$6:$G$240,0)) -> FALSE
A10: QS0011260CHF | B10: 45671 | D10: QS0011260CHF | E10: NL | F10: EECHF | G10: ESI CHF FWD RETURN | H10: XAMS | I10: 0.94590376 | J10: 1.13 | K10: 1.13 | L10: 1.1274288 | M10: 1.0664392 | N10: 1 | O10: EUR | P10: 1 | W10: ECB | X10: EU Price | Y10: Indices | AD10: 0 | AE10: =ISNUMBER(MATCH(G10,AUM!$C$6:$C$1451,0)) -> FALSE | AF10: =ISNUMBER(MATCH(G10,AUM!$G$6:$G$240,0)) -> FALSE
A11: QS0011256250 | B11: 45671 | D11: QS0011256250 | E11: NL | F11: ENVBG | G11: Euronext Sustainable Benelux 20 GR Index | H11: XAMS | J11: 3129.48 | K11: 3108.62 | L11: 3108.6223 | Q11: QS0011256235 | T11: 0 | W11: ECB | X11: TR1 | Y11: Indices | AD11: 0 | AE11: =ISNUMBER(MATCH(G11,AUM!$C$6:$C$1451,0)) -> FALSE | AF11: =ISNUMBER(MATCH(G11,AUM!$G$6:$G$240,0)) -> FALSE
A12: QS0011256243 | B12: 45671 | D12: QS0011256243 | E12: NL | F12: ENVBN | G12: Euronext Sustainable Benelux 20 NR Index | H12: XAMS | J12: 2878.5 | K12: 2859.32 | L12: 2859.3197 | Q12: QS0011256235 | U12: 0 | W12: ECB | X12: TR1 | Y12: Indices | AD12: 0 | AE12: =ISNUMBER(MATCH(G12,AUM!$C$6:$C$1451,0)) -> FALSE | AF12: =ISNUMBER(MATCH(G12,AUM!$G$6:$G$240,0)) -> FALSE
A13: QS0011256235 | B13: 45671 | D13: QS0011256235 | E13: NL | F13: ENVB | G13: Euronext Sustainable Benelux 20 Index | H13: XAMS | I13: 885.96256 | J13: 1978.85 | K13: 1965.66 | L13: 1965.6574 | M13: 1741498.9 | N13: 20 | O13: EUR | P13: 1 | R13: QS0011256250 | S13: QS0011256243 | W13: ECB | X13: EU Price | Y13: Indices | AD13: 0 | AE13: =ISNUMBER(MATCH(G13,AUM!$C$6:$C$1451,0)) -> FALSE | AF13: =ISNUMBER(MATCH(G13,AUM!$G$6:$G$240,0)) -> FALSE
A14: QS0011256227 | B14: 45671 | D14: QS0011256227 | E14: NL | F14: ENVOG | G14: Euronext Sustainable Euro 120 GR Index | H14: XAMS | J14: 2963.91 | K14: 2960.33 | L14: 2960.3255 | Q14: QS0011256201 | T14: 0.15146555 | V14: FR0000121485 | W14: ECB | X14: TR1 | Y14: Indices | AD14: 0 | AE14: =ISNUMBER(MATCH(G14,AUM!$C$6:$C$1451,0)) -> FALSE | AF14: =ISNUMBER(MATCH(G14,AUM!$G$6:$G$240,0)) -> FALSE
A15: QS0011256219 | B15: 45671 | D15: QS0011256219 | E15: NL | F15: ENVON | G15: Euronext Sustainable Euro 120 NR Index | H15: XAMS | J15: 2621.13 | K15: 2617.96 | L15: 2617.9622 | Q15: QS0011256201 | U15: 0.11359917 | V15: FR0000121485 | W15: ECB | X15: TR1 | Y15: Indices | AD15: 0 | AE15: =ISNUMBER(MATCH(G15,AUM!$C$6:$C$1451,0)) -> FALSE | AF15: =ISNUMBER(MATCH(G15,AUM!$G$6:$G$240,0)) -> FALSE
A16: QS0011256201 | B16: 45671 | D16: QS0011256201 | E16: NL | F16: ENVEO | G16: Euronext Sustainable Euro 120 Index | H16: XAMS | I16: 818.39782 | J16: 1813.68 | K16: 1811.49 | L16: 1811.4899 | M16: 1482519.4 | N16: 120 | O16: EUR | P16: 1 | R16: QS0011256227 | S16: QS0011256219 | W16: ECB | X16: EU Price | Y16: Indices | AD16: 0 | AE16: =ISNUMBER(MATCH(G16,AUM!$C$6:$C$1451,0)) -> FALSE | AF16: =ISNUMBER(MATCH(G16,AUM!$G$6:$G$240,0)) -> FALSE
A17: QS0011256169 | B17: 45671 | D17: QS0011256169 | E17: NL | F17: ENVU | G17: Euronext Sustainable US 50 | H17: XAMS | I17: 840.55091 | J17: 3710.64 | K17: 3772.6 | L17: 3772.5987 | M17: 3171061.2 | N17: 50 | O17: USD | P17: 1 | R17: QS0011256193 | S17: QS0011256185 | W17: WM | X17: EU Price | Y17: Indices | AD17: 0 | AE17: =ISNUMBER(MATCH(G17,AUM!$C$6:$C$1451,0)) -> FALSE | AF17: =ISNUMBER(MATCH(G17,AUM!$G$6:$G$240,0)) -> FALSE
A18: QS0011250956 | B18: 45671 | D18: QS0011250956 | E18: NL | F18: ENVUG | G18: Euronext Sustainable UK 20 GR Index | H18: XAMS | J18: 1853.04 | K18: 1851.06 | L18: 1851.0607 | Q18: QS0011250931 | T18: 0 | W18: ECB | X18: TR1 | Y18: Indices | AD18: 0 | AE18: =ISNUMBER(MATCH(G18,AUM!$C$6:$C$1451,0)) -> FALSE | AF18: =ISNUMBER(MATCH(G18,AUM!$G$6:$G$240,0)) -> FALSE
A19: QS0011250949 | B19: 45671 | D19: QS0011250949 | E19: NL | F19: ENVUN | G19: Euronext Sustainable UK 20 NR Index | H19: XAMS | J19: 1828.23 | K19: 1826.28 | L19: 1826.2754 | Q19: QS0011250931 | U19: 0 | W19: ECB | X19: TR1 | Y19: Indices | AD19: 0 | AE19: =ISNUMBER(MATCH(G19,AUM!$C$6:$C$1451,0)) -> FALSE | AF19: =ISNUMBER(MATCH(G19,AUM!$G$6:$G$240,0)) -> FALSE
A20: QS0011250931 | B20: 45671 | D20: QS0011250931 | E20: NL | F20: ENVUK | G20: Euronext Sustainable UK 20 Index | H20: XAMS | I20: 76177.382 | J20: 1129.85 | K20: 1128.64 | L20: 1128.6423 | M20: 85977016 | N20: 20 | O20: GBX | P20: 1 | R20: QS0011250956 | S20: QS0011250949 | W20: ECB | X20: EU Price | Y20: Indices | AD20: 0 | AE20: =ISNUMBER(MATCH(G20,AUM!$C$6:$C$1451,0)) -> FALSE | AF20: =ISNUMBER(MATCH(G20,AUM!$G$6:$G$240,0)) -> FALSE
A21: QS0011250923 | B21: 45671 | D21: QS0011250923 | E21: NL | F21: ENVFG | G21: Euronext Sustainable France 20 GR Index | H21: XAMS | J21: 2311.32 | K21: 2310.18 | L21: 2310.1771 | Q21: QS0011250907 | T21: 0.63958281 | V21: FR0000121485 | W21: ECB | X21: TR1 | Y21: Indices | AD21: 0 | AE21: =ISNUMBER(MATCH(G21,AUM!$C$6:$C$1451,0)) -> FALSE | AF21: =ISNUMBER(MATCH(G21,AUM!$G$6:$G$240,0)) -> FALSE
A22: QS0011250915 | B22: 45671 | D22: QS0011250915 | E22: NL | F22: ENVFN | G22: Euronext Sustainable France 20 NR Index | H22: XAMS | J22: 2008.67 | K22: 2007.68 | L22: 2007.6791 | Q22: QS0011250907 | U22: 0.47968711 | V22: FR0000121485 | W22: ECB | X22: TR1 | Y22: Indices | AD22: 0 | AE22: =ISNUMBER(MATCH(G22,AUM!$C$6:$C$1451,0)) -> FALSE | AF22: =ISNUMBER(MATCH(G22,AUM!$G$6:$G$240,0)) -> FALSE
A23: QS0011250907 | B23: 45671 | D23: QS0011250907 | E23: NL | F23: ENVF | G23: Euronext Sustainable France 20 Index | H23: XAMS | I23: 808.36272 | J23: 1412.44 | K23: 1411.74 | L23: 1411.7411 | M23: 1141198.9 | N23: 20 | O23: EUR | P23: 1 | R23: QS0011250923 | S23: QS0011250915 | W23: ECB | X23: EU Price | Y23: Indices | AD23: 0 | AE23: =ISNUMBER(MATCH(G23,AUM!$C$6:$C$1451,0)) -> FALSE | AF23: =ISNUMBER(MATCH(G23,AUM!$G$6:$G$240,0)) -> FALSE
A24: QS0011250899 | B24: 45671 | D24: QS0011250899 | E24: NL | F24: ENVEG | G24: Euronext Sustainable Europe 120 GR Index | H24: XAMS | J24: 2870.81 | K24: 2866.98 | L24: 2866.9834 | Q24: QS0011250873 | T24: 0.14553765 | V24: FR0000121485 | W24: ECB | X24: TR1 | Y24: Indices | AD24: 0 | AE24: =ISNUMBER(MATCH(G24,AUM!$C$6:$C$1451,0)) -> FALSE | AF24: =ISNUMBER(MATCH(G24,AUM!$G$6:$G$240,0)) -> FALSE
A25: QS0011250881 | B25: 45671 | D25: QS0011250881 | E25: NL | F25: ENVEN | G25: Euronext Sustainable Europe 120 NR Index | H25: XAMS | J25: 2578.26 | K25: 2574.83 | L25: 2574.8263 | Q25: QS0011250873 | U25: 0.10915324 | V25: FR0000121485 | W25: ECB | X25: TR1 | Y25: Indices | AD25: 0 | AE25: =ISNUMBER(MATCH(G25,AUM!$C$6:$C$1451,0)) -> FALSE | AF25: =ISNUMBER(MATCH(G25,AUM!$G$6:$G$240,0)) -> FALSE
A26: QS0011250873 | B26: 45671 | D26: QS0011250873 | E26: NL | F26: ENVEU | G26: Euronext Sustainable Europe 120 Index | H26: XAMS | I26: 865.11828 | J26: 1749.93 | K26: 1747.6 | L26: 1747.5981 | M26: 1511879.1 | N26: 120 | O26: EUR | P26: 1 | R26: QS0011250899 | S26: QS0011250881 | W26: ECB | X26: EU Price | Y26: Indices | AD26: 0 | AE26: =ISNUMBER(MATCH(G26,AUM!$C$6:$C$1451,0)) -> FALSE | AF26: =ISNUMBER(MATCH(G26,AUM!$G$6:$G$240,0)) -> FALSE
A27: QS0011250840 | B27: 45671 | D27: QS0011250840 | E27: NL | F27: ENVW | G27: Euronext Sustainable World 120 | H27: XAMS | I27: 859.73031 | J27: 1790.37 | K27: 1791.66 | L27: 1791.6607 | M27: 1540345 | N27: 120 | O27: USD | P27: 1 | R27: QS0011250865 | S27: QS0011250857 | W27: WM | X27: EU Price | Y27: Indices | AD27: 0 | AE27: =ISNUMBER(MATCH(G27,AUM!$C$6:$C$1451,0)) -> FALSE | AF27: =ISNUMBER(MATCH(G27,AUM!$G$6:$G$240,0)) -> FALSE
A28: QS0011249503 | B28: 45671 | D28: QS0011249503 | E28: PT | F28: PTOGP | G28: PSI Energy | H28: XLIS | I28: 8178088 | J28: 1376.28 | K28: 1390.31 | L28: 1390.3061 | M28: 1.1370046e+10 | N28: 1 | O28: EUR | P28: 1 | R28: QS0011249495 | W28: ECB | X28: EU Price | Y28: Indices | AD28: 0 | AE28: =ISNUMBER(MATCH(G28,AUM!$C$6:$C$1451,0)) -> TRUE | AF28: =ISNUMBER(MATCH(G28,AUM!$G$6:$G$240,0)) -> FALSE
A29: QS0011249495 | B29: 45671 | D29: QS0011249495 | E29: PT | F29: PTOG | G29: PSI Energy GR | H29: XLIS | J29: 2188.93 | K29: 2211.24 | L29: 2211.2416 | Q29: QS0011249503 | T29: 0 | W29: ECB | X29: TR1 | Y29: Indices | AD29: 0 | AE29: =ISNUMBER(MATCH(G29,AUM!$C$6:$C$1451,0)) -> TRUE | AF29: =ISNUMBER(MATCH(G29,AUM!$G$6:$G$240,0)) -> FALSE
A30: QS0011249487 | B30: 45671 | D30: QS0011249487 | E30: PT | F30: PTHCP | G30: PSI Health Care | H30: XLIS | I30: 0.00055892857 | J30: 1789.14 | K30: 1789.14 | L30: 1789.1374 | M30: 1 | N30: 1 | O30: EUR | P30: 1 | R30: QS0011249479 | W30: ECB | X30: EU Price | Y30: Indices | AD30: 0 | AE30: =ISNUMBER(MATCH(G30,AUM!$C$6:$C$1451,0)) -> FALSE | AF30: =ISNUMBER(MATCH(G30,AUM!$G$6:$G$240,0)) -> FALSE
A31: QS0011249479 | B31: 45671 | D31: QS0011249479 | E31: PT | F31: PTHC | G31: PSI Health Care GR | H31: XLIS | J31: 0 | K31: 0 | L31: 0 | Q31: QS0011249487 | T31: 0 | W31: ECB | X31: TR1 | Y31: Indices | AD31: 0 | AE31: =ISNUMBER(MATCH(G31,AUM!$C$6:$C$1451,0)) -> FALSE | AF31: =ISNUMBER(MATCH(G31,AUM!$G$6:$G$240,0)) -> FALSE
A32: QS0011249248 | B32: 45671 | D32: QS0011249248 | E32: BE | F32: BEOGP | G32: BEL Energy | H32: XBRU | I32: 87468830 | J32: 1516.63 | K32: 1534.94 | L32: 1534.9358 | M32: 1.3425904e+11 | N32: 2 | O32: EUR | P32: 1 | S32: QS0011249230 | W32: ECB | X32: EU Price | Y32: Indices | AD32: 0 | AE32: =ISNUMBER(MATCH(G32,AUM!$C$6:$C$1451,0)) -> TRUE | AF32: =ISNUMBER(MATCH(G32,AUM!$G$6:$G$240,0)) -> FALSE
A33: QS0011249230 | B33: 45671 | D33: QS0011249230 | E33: BE | F33: BEOG | G33: BEL Energy NR | H33: XBRU | J33: 2476.3 | K33: 2506.19 | L33: 2506.1859 | Q33: QS0011249248 | U33: 0 | W33: ECB | X33: TR1 | Y33: Indices | AD33: 0 | AE33: =ISNUMBER(MATCH(G33,AUM!$C$6:$C$1451,0)) -> TRUE | AF33: =ISNUMBER(MATCH(G33,AUM!$G$6:$G$240,0)) -> FALSE
A34: QS0011227186 | B34: 45671 | D34: QS0011227186 | E34: FR | F34: ALASG | G34: Euronext Growth All-Share Index GR | H34: XPAR | J34: 1056.56 | K34: 1053.81 | L34: 1053.8137 | Q34: QS0011040902 | T34: 0.04601584 | V34: NO0010360019 | W34: ECB | X34: TR1 | Y34: Indices | AD34: 0 | AE34: =ISNUMBER(MATCH(G34,AUM!$C$6:$C$1451,0)) -> TRUE | AF34: =ISNUMBER(MATCH(G34,AUM!$G$6:$G$240,0)) -> FALSE
A35: QS0011227178 | B35: 45671 | D35: QS0011227178 | E35: FR | F35: ALASN | G35: Euronext Growth All-Share Index NR | H35: XPAR | J35: 1014.02 | K35: 1011.39 | L35: 1011.3879 | Q35: QS0011040902 | U35: 0.03451188 | V35: NO0010360019 | W35: ECB | X35: TR1 | Y35: Indices | AD35: 0 | AE35: =ISNUMBER(MATCH(G35,AUM!$C$6:$C$1451,0)) -> TRUE | AF35: =ISNUMBER(MATCH(G35,AUM!$G$6:$G$240,0)) -> FALSE
A36: QS0011225420 | B36: 45671 | D36: QS0011225420 | E36: NL | F36: NLCSG | G36: AEX Consumer Staples GR | H36: XAMS | J36: 4710.89 | K36: 4693.72 | L36: 4693.7166 | Q36: QS0011016563 | T36: 0 | W36: ECB | X36: TR1 | Y36: Indices | AD36: 0 | AE36: =ISNUMBER(MATCH(G36,AUM!$C$6:$C$1451,0)) -> TRUE | AF36: =ISNUMBER(MATCH(G36,AUM!$G$6:$G$240,0)) -> FALSE
A37: QS0011225404 | B37: 45671 | D37: QS0011225404 | E37: NL | F37: NLCGG | G37: AEX Consumer Discretionary GR | H37: XAMS | J37: 6717.85 | K37: 6645.98 | L37: 6645.9835 | Q37: QS0011016530 | T37: 0 | W37: ECB | X37: TR1 | Y37: Indices | AD37: 0 | AE37: =ISNUMBER(MATCH(G37,AUM!$C$6:$C$1451,0)) -> TRUE | AF37: =ISNUMBER(MATCH(G37,AUM!$G$6:$G$240,0)) -> FALSE
A38: QS0011225396 | B38: 45671 | D38: QS0011225396 | E38: NL | F38: NLBMG | G38: AEX Basic Materials GR | H38: XAMS | J38: 1931.82 | K38: 1928.01 | L38: 1928.0054 | Q38: QS0011016480 | T38: 0 | W38: ECB | X38: TR1 | Y38: Indices | AD38: 0 | AE38: =ISNUMBER(MATCH(G38,AUM!$C$6:$C$1451,0)) -> TRUE | AF38: =ISNUMBER(MATCH(G38,AUM!$G$6:$G$240,0)) -> FALSE
A39: QS0011225370 | B39: 45671 | D39: QS0011225370 | E39: BE | F39: BELCP | G39: BEL Continuous Stocks Index | H39: XBRU | I39: 17924556 | J39: 35843.09 | K39: 35879.78 | L39: 35879.782 | M39: 6.4312915e+11 | N39: 107 | O39: EUR | P39: 1 | S39: BE0389552978 | W39: ECB | X39: EU Price | Y39: Indices | AD39: 0 | AE39: =ISNUMBER(MATCH(G39,AUM!$C$6:$C$1451,0)) -> TRUE | AF39: =ISNUMBER(MATCH(G39,AUM!$G$6:$G$240,0)) -> FALSE
A40: QS0011225222 | B40: 45671 | D40: QS0011225222 | E40: BE | F40: BECGP | G40: BEL Consumer Discretionary | H40: XBRU | I40: 1420723.9 | J40: 7054.38 | K40: 7025.69 | L40: 7025.6914 | M40: 9.9815675e+09 | N40: 6 | O40: EUR | P40: 1 | S40: QS0011016761 | W40: ECB | X40: EU Price | Y40: Indices | AD40: 0 | AE40: =ISNUMBER(MATCH(G40,AUM!$C$6:$C$1451,0)) -> TRUE | AF40: =ISNUMBER(MATCH(G40,AUM!$G$6:$G$240,0)) -> FALSE
A41: QS0011225214 | B41: 45671 | D41: QS0011225214 | E41: BE | F41: BEINP | G41: BEL Industrials | H41: XBRU | I41: 32460555 | J41: 1750.91 | K41: 1746.38 | L41: 1746.3828 | M41: 5.6688557e+10 | N41: 16 | O41: EUR | P41: 1 | S41: QS0011016738 | W41: ECB | X41: EU Price | Y41: Indices | AD41: 0 | AE41: =ISNUMBER(MATCH(G41,AUM!$C$6:$C$1451,0)) -> TRUE | AF41: =ISNUMBER(MATCH(G41,AUM!$G$6:$G$240,0)) -> FALSE
A42: QS0011225206 | B42: 45671 | D42: QS0011225206 | E42: BE | F42: BEHCP | G42: BEL Health Care | H42: XBRU | I42: 16090744 | J42: 5458.86 | K42: 5404.49 | L42: 5404.4914 | M42: 8.6962288e+10 | N42: 14 | O42: EUR | P42: 1 | S42: QS0011016795 | W42: ECB | X42: EU Price | Y42: Indices | AD42: 0 | AE42: =ISNUMBER(MATCH(G42,AUM!$C$6:$C$1451,0)) -> TRUE | AF42: =ISNUMBER(MATCH(G42,AUM!$G$6:$G$240,0)) -> FALSE
A43: QS0011225198 | B43: 45671 | D43: QS0011225198 | E43: BE | F43: BETEP | G43: BEL Telecommunications | H43: XBRU | I43: 11082414 | J43: 285.08 | K43: 283.83 | L43: 283.82927 | M43: 3.1455135e+09 | N43: 4 | O43: EUR | P43: 1 | S43: QS0011016860 | W43: ECB | X43: EU Price | Y43: Indices | AD43: 0 | AE43: =ISNUMBER(MATCH(G43,AUM!$C$6:$C$1451,0)) -> TRUE | AF43: =ISNUMBER(MATCH(G43,AUM!$G$6:$G$240,0)) -> FALSE
A44: QS0011225180 | B44: 45671 | D44: QS0011225180 | E44: BE | F44: BEFIP | G44: BEL Financials | H44: XBRU | I44: 1.4540386e+08 | J44: 896.63 | K44: 901.03 | L44: 901.02809 | M44: 1.3101296e+11 | N44: 15 | O44: EUR | P44: 1 | S44: QS0011016902 | W44: ECB | X44: EU Price | Y44: Indices | AD44: 0 | AE44: =ISNUMBER(MATCH(G44,AUM!$C$6:$C$1451,0)) -> TRUE | AF44: =ISNUMBER(MATCH(G44,AUM!$G$6:$G$240,0)) -> FALSE
A45: QS0011225172 | B45: 45671 | D45: QS0011225172 | E45: BE | F45: BETP | G45: BEL Technology | H45: XBRU | I45: 2997809.8 | J45: 1291.23 | K45: 1284.29 | L45: 1284.2926 | M45: 3.8500649e+09 | N45: 6 | O45: EUR | P45: 1 | S45: QS0011016936 | W45: ECB | X45: EU Price | Y45: Indices | AD45: 0 | AE45: =ISNUMBER(MATCH(G45,AUM!$C$6:$C$1451,0)) -> TRUE | AF45: =ISNUMBER(MATCH(G45,AUM!$G$6:$G$240,0)) -> FALSE
A46: QS0011225164 | B46: 45671 | D46: QS0011225164 | E46: BE | F46: BEUTP | G46: BEL Utilities | H46: XBRU | I46: 49765388 | J46: 862.92 | K46: 869.66 | L46: 869.66336 | M46: 4.3279134e+10 | N46: 3 | O46: EUR | P46: 1 | S46: QS0011019005 | W46: ECB | X46: EU Price | Y46: Indices | AD46: 0 | AE46: =ISNUMBER(MATCH(G46,AUM!$C$6:$C$1451,0)) -> TRUE | AF46: =ISNUMBER(MATCH(G46,AUM!$G$6:$G$240,0)) -> FALSE
A47: QS0011225156 | B47: 45671 | D47: QS0011225156 | E47: BE | F47: BECSP | G47: BEL Consumer Staples | H47: XBRU | I47: 49145708 | J47: 2598.73 | K47: 2584.33 | L47: 2584.3304 | M47: 127008747270 | N47: 13 | O47: EUR | P47: 1 | S47: QS0011016829 | W47: ECB | X47: EU Price | Y47: Indices | AD47: 0 | AE47: =ISNUMBER(MATCH(G47,AUM!$C$6:$C$1451,0)) -> TRUE | AF47: =ISNUMBER(MATCH(G47,AUM!$G$6:$G$240,0)) -> FALSE
A48: QS0011225065 | B48: 45671 | D48: QS0011225065 | E48: PT | F48: PTTEP | G48: PSI Technology | H48: XLIS | I48: 361417.18 | J48: 689.41 | K48: 691.95 | L48: 691.9467 | M48: 2.5008143e+08 | N48: 2 | O48: EUR | P48: 1 | R48: QS0011016688 | W48: ECB | X48: EU Price | Y48: Indices | AD48: 0 | AE48: =ISNUMBER(MATCH(G48,AUM!$C$6:$C$1451,0)) -> TRUE | AF48: =ISNUMBER(MATCH(G48,AUM!$G$6:$G$240,0)) -> FALSE
A49: QS0011225057 | B49: 45671 | D49: QS0011225057 | E49: PT | F49: PTFIP | G49: PSI Financials | H49: XLIS | I49: 47303899 | J49: 153.81 | K49: 153.81 | L49: 153.81293 | M49: 7.2759515e+09 | N49: 2 | O49: EUR | P49: 1 | R49: QS0011016662 | W49: ECB | X49: EU Price | Y49: Indices | AD49: 0 | AE49: =ISNUMBER(MATCH(G49,AUM!$C$6:$C$1451,0)) -> TRUE | AF49: =ISNUMBER(MATCH(G49,AUM!$G$6:$G$240,0)) -> FALSE
A50: QS0011225040 | B50: 45671 | D50: QS0011225040 | E50: PT | F50: PTUTP | G50: PSI Utilities | H50: XLIS | I50: 25186964 | J50: 926.55 | K50: 940.5 | L50: 940.49988 | M50: 2.3688337e+10 | N50: 3 | O50: EUR | P50: 1 | R50: QS0011016647 | W50: ECB | X50: EU Price | Y50: Indices | AD50: 0 | AE50: =ISNUMBER(MATCH(G50,AUM!$C$6:$C$1451,0)) -> TRUE | AF50: =ISNUMBER(MATCH(G50,AUM!$G$6:$G$240,0)) -> FALSE
A51: QS0011225032 | B51: 45671 | D51: QS0011225032 | E51: PT | F51: PTTLP | G51: PSI Telecommunications | H51: XLIS | I51: 26837335 | J51: 96.75 | K51: 96.27 | L51: 96.267252 | M51: 2.5835565e+09 | N51: 4 | O51: EUR | P51: 1 | R51: QS0011016621 | W51: ECB | X51: EU Price | Y51: Indices | AD51: 0 | AE51: =ISNUMBER(MATCH(G51,AUM!$C$6:$C$1451,0)) -> TRUE | AF51: =ISNUMBER(MATCH(G51,AUM!$G$6:$G$240,0)) -> FALSE
A52: QS0011225024 | B52: 45671 | D52: QS0011225024 | E52: PT | F52: PTCSP | G52: PSI Consumer Staples | H52: XLIS | I52: 6783548.7 | J52: 1964.89 | K52: 1967.42 | L52: 1967.424 | M52: 1.3346116e+10 | N52: 2 | O52: EUR | P52: 1 | R52: QS0011016597 | W52: ECB | X52: EU Price | Y52: Indices | AD52: 0 | AE52: =ISNUMBER(MATCH(G52,AUM!$C$6:$C$1451,0)) -> TRUE | AF52: =ISNUMBER(MATCH(G52,AUM!$G$6:$G$240,0)) -> FALSE
A53: QS0011225016 | B53: 45671 | D53: QS0011225016 | E53: PT | F53: PTCGP | G53: PSI Consumer Discretionary | H53: XLIS | I53: 202875.85 | J53: 5068.71 | K53: 5069.85 | L53: 5069.8485 | M53: 1.0285498e+09 | N53: 10 | O53: EUR | P53: 1 | R53: QS0011016571 | W53: ECB | X53: EU Price | Y53: Indices | AD53: 0 | AE53: =ISNUMBER(MATCH(G53,AUM!$C$6:$C$1451,0)) -> TRUE | AF53: =ISNUMBER(MATCH(G53,AUM!$G$6:$G$240,0)) -> FALSE
A54: QS0011225008 | B54: 45671 | D54: QS0011225008 | E54: PT | F54: PTINP | G54: PSI Industrials | H54: XLIS | I54: 6552562.9 | J54: 432.26 | K54: 431.69 | L54: 431.68554 | M54: 2.8286467e+09 | N54: 5 | O54: EUR | P54: 1 | R54: QS0011016522 | W54: ECB | X54: EU Price | Y54: Indices | AD54: 0 | AE54: =ISNUMBER(MATCH(G54,AUM!$C$6:$C$1451,0)) -> TRUE | AF54: =ISNUMBER(MATCH(G54,AUM!$G$6:$G$240,0)) -> FALSE
A55: QS0011224993 | B55: 45671 | D55: QS0011224993 | E55: PT | F55: PTBMP | G55: PSI Basic Materials | H55: XLIS | I55: 2039158.2 | J55: 2381.24 | K55: 2394.32 | L55: 2394.3171 | M55: 4.8823914e+09 | N55: 4 | O55: EUR | P55: 1 | R55: QS0011016514 | W55: ECB | X55: EU Price | Y55: Indices | AD55: 0 | AE55: =ISNUMBER(MATCH(G55,AUM!$C$6:$C$1451,0)) -> TRUE | AF55: =ISNUMBER(MATCH(G55,AUM!$G$6:$G$240,0)) -> FALSE
A56: QS0011224977 | B56: 45671 | D56: QS0011224977 | E56: NL | F56: AAXG | G56: AEX All-Share Index GR | H56: XAMS | J56: 4664.03 | K56: 4627.62 | L56: 4627.6196 | Q56: NL0000249100 | T56: 0 | W56: ECB | X56: TR1 | Y56: Indices | AD56: 0 | AE56: =ISNUMBER(MATCH(G56,AUM!$C$6:$C$1451,0)) -> TRUE | AF56: =ISNUMBER(MATCH(G56,AUM!$G$6:$G$240,0)) -> FALSE
A57: QS0011224944 | B57: 45671 | D57: QS0011224944 | E57: NL | F57: NLTLG | G57: AEX Telecommunications GR | H57: XAMS | J57: 3422.46 | K57: 3451.65 | L57: 3451.6485 | Q57: QS0011016589 | T57: 0 | W57: ECB | X57: TR1 | Y57: Indices | AD57: 0 | AE57: =ISNUMBER(MATCH(G57,AUM!$C$6:$C$1451,0)) -> TRUE | AF57: =ISNUMBER(MATCH(G57,AUM!$G$6:$G$240,0)) -> FALSE
A58: QS0011224936 | B58: 45671 | D58: QS0011224936 | E58: NL | F58: NLTCG | G58: AEX Technology GR | H58: XAMS | J58: 12924.56 | K58: 12693.48 | L58: 12693.478 | Q58: QS0011016613 | T58: 0 | W58: ECB | X58: TR1 | Y58: Indices | AD58: 0 | AE58: =ISNUMBER(MATCH(G58,AUM!$C$6:$C$1451,0)) -> TRUE | AF58: =ISNUMBER(MATCH(G58,AUM!$G$6:$G$240,0)) -> FALSE
A59: QS0011224910 | B59: 45671 | D59: QS0011224910 | E59: BE | F59: BEBMP | G59: BEL Basic Materials | H59: XBRU | I59: 25077366 | J59: 1075.55 | K59: 1072.13 | L59: 1072.1283 | M59: 2.6886154e+10 | N59: 13 | O59: EUR | P59: 1 | S59: QS0011016696 | W59: ECB | X59: EU Price | Y59: Indices | AD59: 0 | AE59: =ISNUMBER(MATCH(G59,AUM!$C$6:$C$1451,0)) -> TRUE | AF59: =ISNUMBER(MATCH(G59,AUM!$G$6:$G$240,0)) -> FALSE
A60: QS0011224829 | B60: 45671 | D60: QS0011224829 | E60: NL | F60: NLOGG | G60: AEX Energy GR | H60: XAMS | J60: 2952.91 | K60: 2989.9 | L60: 2989.8978 | Q60: QS0011016472 | T60: 0 | W60: ECB | X60: TR1 | Y60: Indices | AD60: 0 | AE60: =ISNUMBER(MATCH(G60,AUM!$C$6:$C$1451,0)) -> TRUE | AF60: =ISNUMBER(MATCH(G60,AUM!$G$6:$G$240,0)) -> FALSE
A61: QS0011224662 | B61: 45671 | D61: QS0011224662 | E61: NL | F61: NLING | G61: AEX Industrials GR | H61: XAMS | J61: 3917.56 | K61: 3812.96 | L61: 3812.9621 | Q61: QS0011016506 | T61: 0 | W61: ECB | X61: TR1 | Y61: Indices | AD61: 0 | AE61: =ISNUMBER(MATCH(G61,AUM!$C$6:$C$1451,0)) -> TRUE | AF61: =ISNUMBER(MATCH(G61,AUM!$G$6:$G$240,0)) -> FALSE
A62: QS0011224589 | B62: 45671 | D62: QS0011224589 | E62: NL | F62: NLHCG | G62: AEX Health Care GR | H62: XAMS | J62: 1978.37 | K62: 1952.59 | L62: 1952.5924 | Q62: QS0011016555 | T62: 0 | W62: ECB | X62: TR1 | Y62: Indices | AD62: 0 | AE62: =ISNUMBER(MATCH(G62,AUM!$C$6:$C$1451,0)) -> TRUE | AF62: =ISNUMBER(MATCH(G62,AUM!$G$6:$G$240,0)) -> FALSE
A63: QS0011224571 | B63: 45671 | D63: QS0011224571 | E63: FR | F63: FRINN | G63: CAC Industrials NR | H63: XPAR | J63: 4575.24 | K63: 4541.07 | L63: 4541.0679 | Q63: QS0011017652 | U63: 0 | W63: ECB | X63: TR1 | Y63: Indices | AD63: 0 | AE63: =ISNUMBER(MATCH(G63,AUM!$C$6:$C$1451,0)) -> TRUE | AF63: =ISNUMBER(MATCH(G63,AUM!$G$6:$G$240,0)) -> FALSE
A64: QS0011224522 | B64: 45671 | D64: QS0011224522 | E64: NL | F64: NLFNG | G64: AEX Financials GR | H64: XAMS | J64: 1532.89 | K64: 1540.75 | L64: 1540.7545 | Q64: QS0011016605 | T64: 0 | W64: ECB | X64: TR1 | Y64: Indices | AD64: 0 | AE64: =ISNUMBER(MATCH(G64,AUM!$C$6:$C$1451,0)) -> TRUE | AF64: =ISNUMBER(MATCH(G64,AUM!$G$6:$G$240,0)) -> FALSE
A65: QS0011224498 | B65: 45671 | D65: QS0011224498 | E65: FR | F65: FRHCN | G65: CAC Health Care NR | H65: XPAR | J65: 3221.97 | K65: 3211.62 | L65: 3211.6154 | Q65: QS0011017702 | U65: 0 | W65: ECB | X65: TR1 | Y65: Indices | AD65: 0 | AE65: =ISNUMBER(MATCH(G65,AUM!$C$6:$C$1451,0)) -> TRUE | AF65: =ISNUMBER(MATCH(G65,AUM!$G$6:$G$240,0)) -> FALSE
A66: QS0011224373 | B66: 45671 | D66: QS0011224373 | E66: FR | F66: FRFNN | G66: CAC Financials NR | H66: XPAR | J66: 1882.46 | K66: 1879.22 | L66: 1879.2163 | Q66: QS0011017801 | U66: 0 | W66: ECB | X66: TR1 | Y66: Indices | AD66: 0 | AE66: =ISNUMBER(MATCH(G66,AUM!$C$6:$C$1451,0)) -> TRUE | AF66: =ISNUMBER(MATCH(G66,AUM!$G$6:$G$240,0)) -> FALSE
A67: QS0011224308 | B67: 45671 | D67: QS0011224308 | E67: PT | F67: BVL | G67: PSI All-Share Index | H67: XLIS | I67: 46481742 | J67: 1436.25 | K67: 1446.88 | L67: 1446.8837 | M67: 6.7253677e+10 | N67: 33 | O67: EUR | P67: 1 | R67: PTING1000005 | W67: ECB | X67: EU Price | Y67: Indices | AD67: 0 | AE67: =ISNUMBER(MATCH(G67,AUM!$C$6:$C$1451,0)) -> TRUE | AF67: =ISNUMBER(MATCH(G67,AUM!$G$6:$G$240,0)) -> FALSE
A68: QS0011224290 | B68: 45671 | D68: QS0011224290 | E68: FR | F68: FRCSN | G68: CAC Consumer Staples NR | H68: XPAR | J68: 1369.61 | K68: 1366.96 | L68: 1366.9598 | Q68: QS0011017736 | U68: 0 | W68: ECB | X68: TR1 | Y68: Indices | AD68: 0 | AE68: =ISNUMBER(MATCH(G68,AUM!$C$6:$C$1451,0)) -> TRUE | AF68: =ISNUMBER(MATCH(G68,AUM!$G$6:$G$240,0)) -> FALSE
A69: QS0011224274 | B69: 45671 | D69: QS0011224274 | E69: FR | F69: N150G | G69: Next 150 Index GR | H69: XPAR | J69: 6499.55 | K69: 6467.38 | L69: 6467.3769 | Q69: FR0003502087 | T69: 0 | W69: ECB | X69: TR1 | Y69: Indices | AD69: 0 | AE69: =ISNUMBER(MATCH(G69,AUM!$C$6:$C$1451,0)) -> TRUE | AF69: =ISNUMBER(MATCH(G69,AUM!$G$6:$G$240,0)) -> FALSE
A70: QS0011224258 | B70: 45671 | D70: QS0011224258 | E70: FR | F70: N100G | G70: Euronext 100 Index GR | H70: XPAR | J70: 3155.55 | K70: 3141.12 | L70: 3141.1229 | Q70: FR0003502079 | T70: 0.10151015 | V70: FR0000121485 | W70: ECB | X70: TR1 | Y70: Indices | AD70: 0 | AE70: =ISNUMBER(MATCH(G70,AUM!$C$6:$C$1451,0)) -> TRUE | AF70: =ISNUMBER(MATCH(G70,AUM!$G$6:$G$240,0)) -> FALSE
A71: QS0011224233 | B71: 45671 | D71: QS0011224233 | E71: FR | F71: CN20G | G71: CAC Next 20 GR | H71: XPAR | J71: 20109.63 | K71: 20059.25 | L71: 20059.248 | Q71: QS0010989109 | T71: 0 | W71: ECB | X71: TR1 | Y71: Indices | AD71: 0 | AE71: =ISNUMBER(MATCH(G71,AUM!$C$6:$C$1451,0)) -> TRUE | AF71: =ISNUMBER(MATCH(G71,AUM!$G$6:$G$240,0)) -> FALSE
A72: QS0011224217 | B72: 45671 | D72: QS0011224217 | E72: FR | F72: PAXNR | G72: CAC All-Share Index NR | H72: XPAR | J72: 14848.31 | K72: 14810.03 | L72: 14810.031 | Q72: QS0010989141 | U72: 0.5543662 | V72: FR0000121485 | W72: ECB | X72: TR1 | Y72: Indices | AD72: 0 | AE72: =ISNUMBER(MATCH(G72,AUM!$C$6:$C$1451,0)) -> TRUE | AF72: =ISNUMBER(MATCH(G72,AUM!$G$6:$G$240,0)) -> FALSE
A73: QS0011224092 | B73: 45671 | D73: QS0011224092 | E73: FR | F73: CN20N | G73: CAC Next 20 NR | H73: XPAR | J73: 17382.53 | K73: 17338.98 | L73: 17338.98 | Q73: QS0010989109 | U73: 0 | W73: ECB | X73: TR1 | Y73: Indices | AD73: 0 | AE73: =ISNUMBER(MATCH(G73,AUM!$C$6:$C$1451,0)) -> TRUE | AF73: =ISNUMBER(MATCH(G73,AUM!$G$6:$G$240,0)) -> FALSE
A74: QS0011224084 | B74: 45671 | D74: QS0011224084 | E74: FR | F74: FRUTN | G74: CAC Utilities NR | H74: XPAR | J74: 1369.18 | K74: 1374.98 | L74: 1374.9773 | Q74: QS0011017785 | U74: 0 | W74: ECB | X74: TR1 | Y74: Indices | AD74: 0 | AE74: =ISNUMBER(MATCH(G74,AUM!$C$6:$C$1451,0)) -> TRUE | AF74: =ISNUMBER(MATCH(G74,AUM!$G$6:$G$240,0)) -> FALSE
A75: QS0011223995 | B75: 45671 | D75: QS0011223995 | E75: FR | F75: FRCGN | G75: CAC Consumer Discretionary NR | H75: XPAR | J75: 6676.36 | K75: 6665.5 | L75: 6665.4999 | Q75: QS0011017686 | U75: 0.86239736 | V75: FR0000121485 | W75: ECB | X75: TR1 | Y75: Indices | AD75: 0 | AE75: =ISNUMBER(MATCH(G75,AUM!$C$6:$C$1451,0)) -> TRUE | AF75: =ISNUMBER(MATCH(G75,AUM!$G$6:$G$240,0)) -> FALSE
A76: QS0011223979 | B76: 45671 | D76: QS0011223979 | E76: FR | F76: FRBMN | G76: CAC Basic Materials NR | H76: XPAR | J76: 3674.01 | K76: 3686.21 | L76: 3686.2129 | Q76: QS0011017637 | U76: 0 | W76: ECB | X76: TR1 | Y76: Indices | AD76: 0 | AE76: =ISNUMBER(MATCH(G76,AUM!$C$6:$C$1451,0)) -> TRUE | AF76: =ISNUMBER(MATCH(G76,AUM!$G$6:$G$240,0)) -> FALSE
A77: QS0011223920 | B77: 45671 | D77: QS0011223920 | E77: FR | F77: FRTEN | G77: CAC Telecommunications NR | H77: XPAR | J77: 1553.49 | K77: 1567.82 | L77: 1567.8209 | Q77: QS0011017769 | U77: 0 | W77: ECB | X77: TR1 | Y77: Indices | AD77: 0 | AE77: =ISNUMBER(MATCH(G77,AUM!$C$6:$C$1451,0)) -> TRUE | AF77: =ISNUMBER(MATCH(G77,AUM!$G$6:$G$240,0)) -> FALSE
A78: QS0011223896 | B78: 45671 | D78: QS0011223896 | E78: FR | F78: FRTCN | G78: CAC Technology NR | H78: XPAR | J78: 1836.74 | K78: 1823.59 | L78: 1823.586 | Q78: QS0011017827 | U78: 0 | W78: ECB | X78: TR1 | Y78: Indices | AD78: 0 | AE78: =ISNUMBER(MATCH(G78,AUM!$C$6:$C$1451,0)) -> TRUE | AF78: =ISNUMBER(MATCH(G78,AUM!$G$6:$G$240,0)) -> FALSE
A79: QS0011223698 | B79: 45671 | D79: QS0011223698 | E79: FR | F79: FROGN | G79: CAC Energy NR | H79: XPAR | J79: 2132.7 | K79: 2156.15 | L79: 2156.1531 | Q79: QS0011017603 | U79: 0 | W79: ECB | X79: TR1 | Y79: Indices | AD79: 0 | AE79: =ISNUMBER(MATCH(G79,AUM!$C$6:$C$1451,0)) -> TRUE | AF79: =ISNUMBER(MATCH(G79,AUM!$G$6:$G$240,0)) -> FALSE
A80: QS0011213756 | B80: 45671 | D80: QS0011213756 | E80: FR | F80: CMSG | G80: CAC Mid & Small GR | H80: XPAR | J80: 25534.33 | K80: 25457.56 | L80: 25457.556 | Q80: QS0010989133 | T80: 0 | W80: ECB | X80: TR1 | Y80: Indices | AD80: 0 | AE80: =ISNUMBER(MATCH(G80,AUM!$C$6:$C$1451,0)) -> TRUE | AF80: =ISNUMBER(MATCH(G80,AUM!$G$6:$G$240,0)) -> FALSE
A81: QS0011213731 | B81: 45671 | D81: QS0011213731 | E81: FR | F81: CMSN | G81: CAC Mid & Small NR | H81: XPAR | J81: 21553.08 | K81: 21488.27 | L81: 21488.273 | Q81: QS0010989133 | U81: 0 | W81: ECB | X81: TR1 | Y81: Indices | AD81: 0 | AE81: =ISNUMBER(MATCH(G81,AUM!$C$6:$C$1451,0)) -> TRUE | AF81: =ISNUMBER(MATCH(G81,AUM!$G$6:$G$240,0)) -> FALSE
A82: QS0011213723 | B82: 45671 | D82: QS0011213723 | E82: FR | F82: CACSR | G82: CAC Small GR | H82: XPAR | J82: 18590.07 | K82: 18352.43 | L82: 18352.435 | Q82: QS0010989125 | T82: 0 | W82: ECB | X82: TR1 | Y82: Indices | AD82: 0 | AE82: =ISNUMBER(MATCH(G82,AUM!$C$6:$C$1451,0)) -> TRUE | AF82: =ISNUMBER(MATCH(G82,AUM!$G$6:$G$240,0)) -> FALSE
A83: QS0011213707 | B83: 45671 | D83: QS0011213707 | E83: FR | F83: CACSN | G83: CAC Small NR | H83: XPAR | J83: 16226.15 | K83: 16018.73 | L83: 16018.731 | Q83: QS0010989125 | U83: 0 | W83: ECB | X83: TR1 | Y83: Indices | AD83: 0 | AE83: =ISNUMBER(MATCH(G83,AUM!$C$6:$C$1451,0)) -> TRUE | AF83: =ISNUMBER(MATCH(G83,AUM!$G$6:$G$240,0)) -> FALSE
A84: QS0011213699 | B84: 45671 | D84: QS0011213699 | E84: FR | F84: CAR | G84: CAC Large 60 GR | H84: XPAR | J84: 14713.46 | K84: 14669.49 | L84: 14669.491 | Q84: QS0011213657 | T84: 0.66929727 | V84: FR0000121485 | W84: ECB | X84: TR1 | Y84: Indices | AD84: 0 | AE84: =ISNUMBER(MATCH(G84,AUM!$C$6:$C$1451,0)) -> TRUE | AF84: =ISNUMBER(MATCH(G84,AUM!$G$6:$G$240,0)) -> FALSE
A85: QS0011213681 | B85: 45671 | D85: QS0011213681 | E85: FR | F85: CACLN | G85: CAC Large 60 NR | H85: XPAR | J85: 12947.53 | K85: 12908.84 | L85: 12908.836 | Q85: QS0011213657 | U85: 0.50197295 | V85: FR0000121485 | W85: ECB | X85: TR1 | Y85: Indices | AD85: 0 | AE85: =ISNUMBER(MATCH(G85,AUM!$C$6:$C$1451,0)) -> TRUE | AF85: =ISNUMBER(MATCH(G85,AUM!$G$6:$G$240,0)) -> FALSE
A86: QS0011213657 | B86: 45671 | D86: QS0011213657 | E86: FR | F86: CACLG | G86: CAC Large 60 | H86: XPAR | I86: 2.2128423e+08 | J86: 7995.88 | K86: 7971.98 | L86: 7971.9783 | M86: 1.7640731e+12 | N86: 60 | O86: EUR | P86: 1 | R86: QS0011213699 | S86: QS0011213681 | W86: ECB | X86: EU Price | Y86: Indices | AD86: 0 | AE86: =ISNUMBER(MATCH(G86,AUM!$C$6:$C$1451,0)) -> TRUE | AF86: =ISNUMBER(MATCH(G86,AUM!$G$6:$G$240,0)) -> FALSE
A87: QS0011211248 | B87: 45671 | D87: QS0011211248 | E87: BE | F87: BELSG | G87: BEL Small GR | H87: XBRU | J87: 15152.09 | K87: 14982.27 | L87: 14982.268 | Q87: BE0389857146 | T87: 0 | W87: ECB | X87: TR1 | Y87: Indices | AD87: 0 | AE87: =ISNUMBER(MATCH(G87,AUM!$C$6:$C$1451,0)) -> TRUE | AF87: =ISNUMBER(MATCH(G87,AUM!$G$6:$G$240,0)) -> FALSE
A88: QS0011211230 | B88: 45671 | D88: QS0011211230 | E88: BE | F88: BELMG | G88: BEL Mid GR | H88: XBRU | J88: 10881.27 | K88: 10843.33 | L88: 10843.335 | Q88: BE0389856130 | T88: 0 | W88: ECB | X88: TR1 | Y88: Indices | AD88: 0 | AE88: =ISNUMBER(MATCH(G88,AUM!$C$6:$C$1451,0)) -> TRUE | AF88: =ISNUMBER(MATCH(G88,AUM!$G$6:$G$240,0)) -> FALSE
A89: QS0011211222 | B89: 45671 | D89: QS0011211222 | E89: NL | F89: AEXEG | G89: AEX Equal Weight GR | H89: XAMS | J89: 5743.73 | K89: 5712.86 | L89: 5712.8594 | Q89: QS0011159744 | T89: 0 | W89: ECB | X89: TR1 | Y89: Indices | AD89: 0 | AE89: =ISNUMBER(MATCH(G89,AUM!$C$6:$C$1451,0)) -> TRUE | AF89: =ISNUMBER(MATCH(G89,AUM!$G$6:$G$240,0)) -> FALSE
A90: QS0011211214 | B90: 45671 | D90: QS0011211214 | E90: FR | F90: CACEG | G90: CAC 40 Equal Weight GR | H90: XPAR | J90: 4122.98 | K90: 4108.91 | L90: 4108.906 | Q90: QS0011159777 | T90: 0.52304218 | V90: FR0000121485 | W90: ECB | X90: TR1 | Y90: Indices | AD90: 0 | AE90: =ISNUMBER(MATCH(G90,AUM!$C$6:$C$1451,0)) -> TRUE | AF90: =ISNUMBER(MATCH(G90,AUM!$G$6:$G$240,0)) -> FALSE
A91: QS0011211206 | B91: 45671 | D91: QS0011211206 | E91: NL | F91: AEXEN | G91: AEX Equal Weight NR | H91: XAMS | J91: 5295.12 | K91: 5266.66 | L91: 5266.6641 | Q91: QS0011159744 | U91: 0 | W91: ECB | X91: TR1 | Y91: Indices | AD91: 0 | AE91: =ISNUMBER(MATCH(G91,AUM!$C$6:$C$1451,0)) -> TRUE | AF91: =ISNUMBER(MATCH(G91,AUM!$G$6:$G$240,0)) -> FALSE
A92: QS0011211198 | B92: 45671 | D92: QS0011211198 | E92: FR | F92: CACEN | G92: CAC 40 Equal Weight NR | H92: XPAR | J92: 3636.5 | K92: 3624.08 | L92: 3624.0827 | Q92: QS0011159777 | U92: 0.39228164 | V92: FR0000121485 | W92: ECB | X92: TR1 | Y92: Indices | AD92: 0 | AE92: =ISNUMBER(MATCH(G92,AUM!$C$6:$C$1451,0)) -> TRUE | AF92: =ISNUMBER(MATCH(G92,AUM!$G$6:$G$240,0)) -> FALSE
A93: QS0011211180 | B93: 45671 | D93: QS0011211180 | E93: PT | F93: PSINR | G93: PSI NR | H93: XLIS | J93: 14785.89 | K93: 14857.87 | L93: 14857.872 | Q93: PTING0200002 | U93: 0 | W93: ECB | X93: TR1 | Y93: Indices | AD93: 0 | AE93: =ISNUMBER(MATCH(G93,AUM!$C$6:$C$1451,0)) -> TRUE | AF93: =ISNUMBER(MATCH(G93,AUM!$G$6:$G$240,0)) -> FALSE
A94: QS0011211172 | B94: 45671 | D94: QS0011211172 | E94: NL | F94: ASCXN | G94: AScX NR | H94: XAMS | J94: 2208 | K94: 2184.07 | L94: 2184.0713 | Q94: NL0000249142 | U94: 0 | W94: ECB | X94: TR1 | Y94: Indices | AD94: 0 | AE94: =ISNUMBER(MATCH(G94,AUM!$C$6:$C$1451,0)) -> TRUE | AF94: =ISNUMBER(MATCH(G94,AUM!$G$6:$G$240,0)) -> FALSE
A95: QS0011211164 | B95: 45671 | D95: QS0011211164 | E95: NL | F95: AMXNR | G95: AMX NR | H95: XAMS | J95: 2494.27 | K95: 2465.34 | L95: 2465.3358 | Q95: NL0000249274 | U95: 0 | W95: ECB | X95: TR1 | Y95: Indices | AD95: 0 | AE95: =ISNUMBER(MATCH(G95,AUM!$C$6:$C$1451,0)) -> TRUE | AF95: =ISNUMBER(MATCH(G95,AUM!$G$6:$G$240,0)) -> FALSE
A96: QS0011211156 | B96: 45671 | D96: QS0011211156 | E96: NL | F96: AEXNR | G96: AEX NR | H96: XAMS | J96: 3006.41 | K96: 2989.45 | L96: 2989.4506 | Q96: NL0000000107 | U96: 0 | W96: ECB | X96: TR1 | Y96: Indices | AD96: 0 | AE96: =ISNUMBER(MATCH(G96,AUM!$C$6:$C$1451,0)) -> TRUE | AF96: =ISNUMBER(MATCH(G96,AUM!$G$6:$G$240,0)) -> FALSE
A97: QS0011204995 | B97: 45671 | D97: QS0011204995 | E97: NL | F97: ASCXG | G97: AScX GR | H97: XAMS | J97: 2428.16 | K97: 2401.85 | L97: 2401.8463 | Q97: NL0000249142 | T97: 0 | W97: ECB | X97: TR1 | Y97: Indices | AD97: 0 | AE97: =ISNUMBER(MATCH(G97,AUM!$C$6:$C$1451,0)) -> TRUE | AF97: =ISNUMBER(MATCH(G97,AUM!$G$6:$G$240,0)) -> FALSE
A98: QS0011204763 | B98: 45671 | D98: QS0011204763 | E98: NL | F98: AMXGR | G98: AMX GR | H98: XAMS | J98: 2901.43 | K98: 2867.77 | L98: 2867.7715 | Q98: NL0000249274 | T98: 0 | W98: ECB | X98: TR1 | Y98: Indices | AD98: 0 | AE98: =ISNUMBER(MATCH(G98,AUM!$C$6:$C$1451,0)) -> TRUE | AF98: =ISNUMBER(MATCH(G98,AUM!$G$6:$G$240,0)) -> FALSE
A99: QS00112PSINR | B99: 45671 | D99: QS0011211180 | E99: PT | F99: PREUN | G99: PSI NET RT | H99: XLIS | J99: 14785.89 | K99: 14857.87 | L99: 14857.872 | Q99: PTING0200002 | U99: 0 | W99: ECB | X99: TR1 | Y99: Indices | AD99: 0 | AE99: =ISNUMBER(MATCH(G99,AUM!$C$6:$C$1451,0)) -> FALSE | AF99: =ISNUMBER(MATCH(G99,AUM!$G$6:$G$240,0)) -> FALSE
A100: QS00112AMXNR | B100: 45671 | D100: QS0011211164 | E100: NL | F100: MREUN | G100: AMX NET RT | H100: XAMS | J100: 2495.25 | K100: 2466.31 | L100: 2466.3083 | Q100: NL0000249274 | U100: 0 | W100: ECB | X100: TR1 | Y100: Indices | AD100: 0 | AE100: =ISNUMBER(MATCH(G100,AUM!$C$6:$C$1451,0)) -> FALSE | AF100: =ISNUMBER(MATCH(G100,AUM!$G$6:$G$240,0)) -> FALSE
...

Sheet Old Sheet
A1: Index | B1: Mnemo | C1: Type | D1: Moody's | E1: To do: | F1: x | H1: Frequency | I1: Review
A2: =_xlfn.XLOOKUP(B2,'Index 14-01'!$F$2:$F$1248,'Index 14-01'!$G$2:$G$1248) -> EN FR 40 Responsible Investment | B2: F4RIP | C2: Normal | D2: =ISNUMBER(MATCH(B2,$J$1:$J$52,0)) -> FALSE | E2: 1 | F2: Check | J2: FRSOP
A3: =_xlfn.XLOOKUP(B3,'Index 14-01'!$F$2:$F$1248,'Index 14-01'!$G$2:$G$1248) -> EN Sovereign Economy Selection EZ50 | B3: SES5P | C3: Normal | D3: =ISNUMBER(MATCH(B3,$J$1:$J$52,0)) -> FALSE | E3: 1 | F3: Check | J3: CAGOV
A4: =_xlfn.XLOOKUP(B4,'Index 14-01'!$F$2:$F$1248,'Index 14-01'!$G$2:$G$1248) -> Euronext France Developpement 40 | B4: FRD4P | C4: Normal | D4: =ISNUMBER(MATCH(B4,$J$1:$J$52,0)) -> FALSE | E4: 1 | F4: Check | J4: ESG1P
A5: =_xlfn.XLOOKUP(B5,'Index 14-01'!$F$2:$F$1248,'Index 14-01'!$G$2:$G$1248) -> Euronext France Investissement 40 | B5: FRI4P | C5: Normal | D5: =ISNUMBER(MATCH(B5,$J$1:$J$52,0)) -> FALSE | E5: 1 | F5: Check | J5: WESGP
A6: EN Global Industry Champions 30 | B6: GICP | C6: Normal | D6: =ISNUMBER(MATCH(B6,$J$1:$J$52,0)) -> FALSE | E6: 1 | F6: Check | J6: EESGP
A7: =_xlfn.XLOOKUP(B7,'Index 14-01'!$F$2:$F$1248,'Index 14-01'!$G$2:$G$1248) -> AEX All-Share Index | B7: AAX | C7: AEX | D7: =ISNUMBER(MATCH(B7,$J$1:$J$52,0)) -> FALSE | E7: 0 | J7: FESGP
A8: =_xlfn.XLOOKUP(B8,'Index 14-01'!$F$2:$F$1248,'Index 14-01'!$G$2:$G$1248) -> AEX All-Tradable | B8: AEXAT | C8: AEX | D8: =ISNUMBER(MATCH(B8,$J$1:$J$52,0)) -> FALSE | E8: 0 | J8: ENFRP
A9: =_xlfn.XLOOKUP(B9,'Index 14-01'!$F$2:$F$1248,'Index 14-01'!$G$2:$G$1248) -> AEX All-Tradable Alternative Weighting | B9: AETAW | C9: AEX | D9: =ISNUMBER(MATCH(B9,$J$1:$J$52,0)) -> FALSE | E9: 0 | J9: CESGP
A10: =_xlfn.XLOOKUP(B10,'Index 14-01'!$F$2:$F$1248,'Index 14-01'!$G$2:$G$1248) -> AEX Basic Materials | B10: NLBM | C10: AEX | D10: =ISNUMBER(MATCH(B10,$J$1:$J$52,0)) -> FALSE | E10: 0 | J10: MESGP
A11: =_xlfn.XLOOKUP(B11,'Index 14-01'!$F$2:$F$1248,'Index 14-01'!$G$2:$G$1248) -> AEX Consumer Discretionary | B11: NLCG | C11: AEX | D11: =ISNUMBER(MATCH(B11,$J$1:$J$52,0)) -> FALSE | E11: 0 | J11: LC100
A12: =_xlfn.XLOOKUP(B12,'Index 14-01'!$F$2:$F$1248,'Index 14-01'!$G$2:$G$1248) -> AEX Consumer Staples | B12: NLCS | C12: AEX | D12: =ISNUMBER(MATCH(B12,$J$1:$J$52,0)) -> FALSE | E12: 0 | J12: LC3WP
A13: =_xlfn.XLOOKUP(B13,'Index 14-01'!$F$2:$F$1248,'Index 14-01'!$G$2:$G$1248) -> AEX Dividend Index | B13: AEXDI | C13: AEX | D13: =ISNUMBER(MATCH(B13,$J$1:$J$52,0)) -> FALSE | E13: 0 | J13: LC1EP
