Workbook

Sheet Selected Companies
A1: Rank | B1: Ticker | C1: Company | D1: ISIN Code | E1: MIC | F1: Number of Shares | G1: Price (EUR) | H1: Currency | I1: Mcap in EUR | J1: index | K1: VOL_AV_3M | L1: Free Float | M1: FFMC_CO | N1: Close Prc | O1: FX/Index Ccy | P1: FFMC_WD | Q1: Subsector Code | R1: Supersector Code | S1: itr_scope123_target | T1: itr_scope12_trend | U1: CDP_climate_score | V1: NBR Overall Flag | W1: Tobacco - Production Maximum Percentage of Revenues (%) | X1: Tobacco - Distribution Maximum Percentage of Revenues (%) | Y1: Biological Weapons - Overall Flag | Z1: Chemical Weapons - Overall Flag | AA1: Nuclear Weapons Outside NPT - Overall Flag | AB1: Nuclear Weapons Inside NPT - Overall Flag | AC1: Cluster Munitions - Overall Flag | AD1: Depleted Uranium - Overall Flag | AE1: Anti-personnel Mines - Overall Flag | AF1: coal_mining_and_power_gen_maximum_percentage_of_revenues-values | AG1: Fossil Fuel - Total Maximum Percentage of Revenues (%) | AH1: power_generation_thermal_maximum_percentage_of_revenues-values | AI1: shale_oil_and_or_gas_involvement_tie | AJ1: arctic_drilling_share_max-values | AK1: deepwater_drilling_involvement | AL1: HydraulicFracturingInvolvement | AM1: CoalMiningExpInvolved | AN1: OilGasExtractExpInvolved | AO1: OtherFFInfraInvolved | AP1: NuclearPowerInvolvement | AQ1: NuclearPowerRevShareMax-values | AR1: NuclearPowerUraniumRevShareMax-values | AS1: CivFARevShareMax-values | AT1: MilitaryEqmtDistMaxRev-values | AU1: Social Rating (Num) | AV1: Governance Rating (Num) | AW1: Carbon Intensity (ISS) | AX1: ScoreTemperatureISS | AY1: NACE | AZ1: High_Climate_Impact | BA1: EU_Taxonomy | BB1: Country_Code | BC1: GAFI_Black_List | BD1: GAFI_Grey_List | BE1: Non_Fiscally_Cooperative | BF1: exclude_gafi_black | BG1: exclude_gafi_grey | BH1: exclude_non_fiscal_coop | BI1: exclude_subsector | BJ1: exclude_nbr_red | BK1: exclude_tobacco_prod | BL1: exclude_tobacco_dist | BM1: exclude_biological_weapons | BN1: exclude_chemical_weapons | BO1: exclude_nuclear_weapons_inside_npt | BP1: exclude_nuclear_weapons_outside_npt | BQ1: exclude_cluster_munitions | BR1: exclude_depleted_uranium | BS1: exclude_anti_personnel_mines | BT1: exclude_coal_mining | BU1: exclude_fossil_fuel | BV1: exclude_thermal_power | BW1: exclude_shale_oil_gas | BX1: exclude_arctic_drilling | BY1: exclude_deepwater_drilling | BZ1: exclude_hydraulic_fracturing | CA1: exclude_coal_mining_expansion | CB1: exclude_oil_gas_extraction_expansion | CC1: exclude_other_fossil_fuel_infra | CD1: exclude_nuclear_power | CE1: exclude_nuclear_power_revenue | CF1: exclude_nuclear_uranium | CG1: exclude_civilian_firearms | CH1: exclude_military_equipment | CI1: SG_Score | CJ1: exclude_sg_bottom_10 | CK1: Excluded | CL1: Exclusion_Reason | CM1: itr_scope123_target_filled | CN1: itr_scope12_trend_filled | CO1: cdp_temperature_score | CP1: bonus_malus | CQ1: climate_score | CR1: Median_Carbon_Intensity_Supersector | CS1: PAB_Flag | CT1: Liquidity_Cap | CU1: Liquidity_Floor
A2: 66 | B2: ALO-FR | C2: ALSTOM | D2: FR0010220475 | E2: XPAR | F2: 461510538 | G2: 20.09 | H2: EUR | I2: 9.2717467e+09 | J2: EU500 | K2: 23095735 | L2: 0.75 | M2: 6.95381e+09 | N2: 19.33 | O2: 1 | P2: 6.690749e+09 | Q2: 50202010 | R2: 5020 | S2: 1.9980521 | T2: 3.1 | U2: A | V2: Green | W2: 0 | X2: 0 | Y2: Green | Z2: Green | AA2: Green | AB2: Green | AC2: Green | AD2: Green | AE2: Green | AF2: 0 | AG2: 0 | AH2: 0 | AJ2: 0 | AK2: F | AM2: F | AN2: F | AO2: F | AQ2: 0 | AR2: 0 | AS2: 0 | AT2: 0 | AU2: 2.795 | AV2: 3.363 | AW2: 3285.23 | AX2: 1.5 | AY2: C | AZ2: 1 | BA2: 1 | BB2: FR | BC2: 0 | BD2: 0 | BE2: 0 | CI2: 3.079 | CK2: No | CM2: 1.9980521 | CN2: 3.1 | CO2: 2.5490261 | CP2: -0.3 | CQ2: 2.2490261 | CR2: 350.98887 | CS2: 0 | CT2: 0.017960925 | CU2: 0
A3: 249 | B3: CAST-SE | C3: CASTELLUM AB | D3: SE0000379190 | E3: XSTO | F3: 492601440 | G3: 10.55657 | H3: SEK | I3: 5.2001816e+09 | J3: EU500 | K3: 15217501 | L3: 0.9 | M3: 4.6801634e+09 | N3: 108.65 | O3: 0.09077334 | P3: 4.3724639e+09 | Q3: 35101010 | R3: 3510 | S3: 1.9835888 | U3: A | V3: Green | W3: 0 | X3: 0 | Y3: Green | Z3: Green | AA3: Green | AB3: Green | AC3: Green | AD3: Green | AE3: Green | AF3: 0 | AG3: 0 | AH3: 0 | AJ3: 0 | AK3: F | AM3: F | AN3: F | AO3: F | AQ3: 0 | AR3: 0 | AS3: 0 | AT3: 0 | AU3: 2.359 | AV3: 2.663 | AW3: 6.9595815 | AX3: 1.5 | AY3: L | AZ3: 1 | BA3: 1 | BB3: SE | BC3: 0 | BD3: 0 | BE3: 0 | CI3: 2.511 | CK3: No | CM3: 1.9835888 | CN3: 3.1 | CO3: 2.5417944 | CP3: -0.3 | CQ3: 2.2417944 | CR3: 23.753721 | CS3: 0 | CT3: 0.011830799 | CU3: 0
A4: 360 | B4: DSY-FR | C4: DASSAULT SYSTEMES | D4: FR0014003TT8 | E4: XPAR | F4: 1338435363 | G4: 39.72 | H4: EUR | I4: 5.3162653e+10 | J4: EU500 | K4: 57311403 | L4: 0.5 | M4: 2.6581326e+10 | N4: 32.87 | O4: 1 | P4: 2.1997185e+10 | Q4: 10101015 | R4: 1010 | S4: 1.9943237 | U4: B | V4: Green | W4: 0 | X4: 0 | Y4: Green | Z4: Green | AA4: Green | AB4: Green | AC4: Green | AD4: Green | AE4: Green | AF4: 0 | AG4: 0 | AH4: 0 | AJ4: 0 | AK4: F | AM4: F | AN4: F | AO4: F | AQ4: 0 | AR4: 0 | AS4: 0 | AT4: 0 | AU4: 2.636 | AV4: 3.304 | AW4: 10.868427 | AX4: 1.5 | AY4: J | AZ4: 0 | BA4: 1 | BB4: FR | BC4: 0 | BD4: 0 | BE4: 0 | CI4: 2.97 | CK4: No | CM4: 1.9943237 | CN4: 3.1 | CO4: 2.5471619 | CP4: -0.18 | CQ4: 2.3671619 | CR4: 33.625121 | CS4: 0 | CT4: 0.0450848 | CU4: 0
A5: 633 | B5: INPST-NL | C5: INPOST | D5: LU2290522684 | E5: XAMS | F5: 500000000 | G5: 17.46 | H5: EUR | I5: 8730000000 | J5: EU500 | K5: 7745434.2 | L5: 0.4 | M5: 3492000000 | N5: 13.32 | O5: 1 | P5: 2664000000 | Q5: 50206040 | R5: 5020 | S5: 3.3134401 | U5: A | V5: Green | W5: 0 | X5: 0 | Y5: Green | Z5: Green | AA5: Green | AB5: Green | AC5: Green | AD5: Green | AE5: Green | AF5: 0 | AG5: 0 | AH5: 0 | AJ5: 0 | AK5: F | AM5: F | AN5: F | AO5: F | AQ5: 0 | AR5: 0 | AS5: 0 | AT5: 0 | AU5: 2.05 | AV5: 3.117 | AW5: 65.872922 | AX5: 1.5 | AY5: H | AZ5: 1 | BA5: 1 | BB5: LU | BC5: 0 | BD5: 0 | BE5: 0 | CI5: 2.5835 | CK5: No | CM5: 3.3134401 | CN5: 3.1 | CO5: 3.2067201 | CP5: -0.3 | CQ5: 2.9067201 | CR5: 350.98887 | CS5: 0 | CT5: 0.0060635502 | CU5: 0
A6: 724 | B6: KRX-IE | C6: KINGSPAN GROUP PLC | D6: IE0004927939 | E6: XMSM | F6: 181964859 | G6: 75.5 | H6: EUR | I6: 1.3738347e+10 | J6: EU500 | K6: 27712784 | L6: 0.85 | M6: 1.1677595e+10 | N6: 72.6 | O6: 1 | P6: 1.1229051e+10 | Q6: 50101035 | R6: 5010 | S6: 1.9783312 | T6: 3.1 | U6: A | V6: Green | W6: 0 | X6: 0 | Y6: Green | Z6: Green | AA6: Green | AB6: Green | AC6: Green | AD6: Green | AE6: Green | AF6: 0 | AG6: 0 | AH6: 0 | AJ6: 0 | AK6: F | AM6: F | AN6: F | AO6: F | AQ6: 0 | AR6: 0 | AS6: 0 | AT6: 0 | AU6: 2.108 | AV6: 2.617 | AW6: 429.69418 | AX6: 1.5 | AY6: C | AZ6: 1 | BA6: 1 | BB6: IE | BC6: 0 | BD6: 0 | BE6: 0 | CI6: 2.3625 | CK6: No | CM6: 1.9783312 | CN6: 3.1 | CO6: 2.5391656 | CP6: -0.3 | CQ6: 2.2391656 | CR6: 644.98569 | CS6: 0 | CT6: 0.021857226 | CU6: 0
A7: 730 | B7: KBX-DE | C7: KNORR-BREMSE AG | D7: DE000KBX1006 | E7: XETR | F7: 161200000 | G7: 82.2 | H7: EUR | I7: 13250640000 | J7: EU500 | K7: 9423306.8 | L7: 0.4 | M7: 5300256000 | N7: 78.55 | O7: 1 | P7: 5064904000 | Q7: 50206025 | R7: 5020 | S7: 1.9989892 | U7: A- | V7: Green | W7: 0 | X7: 0 | Y7: Green | Z7: Green | AA7: Green | AB7: Green | AC7: Green | AD7: Green | AE7: Green | AF7: 0 | AG7: 0 | AH7: 0 | AJ7: 0 | AK7: F | AM7: F | AN7: F | AO7: F | AQ7: 0 | AR7: 0 | AS7: 0 | AT7: 0 | AU7: 2.78 | AV7: 2.888 | AW7: 3428.5625 | AX7: 1.5 | AY7: C | AZ7: 1 | BA7: 1 | BB7: DE | BC7: 0 | BD7: 0 | BE7: 0 | CI7: 2.834 | CK7: No | CM7: 1.9989892 | CN7: 3.1 | CO7: 2.5494946 | CP7: -0.24 | CQ7: 2.3094946 | CR7: 350.98887 | CS7: 0 | CT7: 0.0075512973 | CU7: 0
A8: 837 | B8: METSO-FI | C8: METSO CORPORATION | D8: FI0009014575 | E8: XHEL | F8: 828972400 | G8: 10.98 | H8: EUR | I8: 9102116952 | J8: EU500 | K8: 13202646 | L8: 0.85 | M8: 7.7367994e+09 | N8: 8.5 | O8: 1 | P8: 5989325590 | Q8: 50204020 | R8: 5020 | S8: 1.9935451 | U8: B | V8: Green | W8: 0 | X8: 0 | Y8: Green | Z8: Green | AA8: Green | AB8: Green | AC8: Green | AD8: Green | AE8: Green | AF8: 0 | AG8: 0 | AH8: 0 | AJ8: 0 | AK8: F | AM8: F | AN8: F | AO8: F | AQ8: 0 | AR8: 0 | AS8: 0 | AT8: 0 | AU8: 2.559 | AV8: 2.673 | AW8: 447.68354 | AX8: 1.5 | AY8: C | AZ8: 1 | BA8: 1 | BB8: FI | BC8: 0 | BD8: 0 | BE8: 0 | CI8: 2.616 | CK8: No | CM8: 1.9935451 | CN8: 3.1 | CO8: 2.5467726 | CP8: -0.18 | CQ8: 2.3667726 | CR8: 350.98887 | CS8: 0 | CT8: 0.010474106 | CU8: 0
A9: 941 | B9: NHY-NO | C9: NORSK HYDRO | D9: NO0005052605 | E9: XOSL | F9: 2009015998 | G9: 5.713564 | H9: NOK | I9: 1.1478641e+10 | J9: EU500 | K9: 22699024 | L9: 0.65 | M9: 7.461117e+09 | N9: 54.06 | O9: 0.08324454 | P9: 5.8766327e+09 | Q9: 55102035 | R9: 5510 | S9: 2.728329 | T9: 1.5 | U9: C | V9: Green | W9: 0 | X9: 0 | Y9: Green | Z9: Green | AA9: Green | AB9: Green | AC9: Green | AD9: Green | AE9: Green | AF9: 0 | AG9: 0 | AH9: 0 | AJ9: 0 | AK9: F | AM9: F | AN9: F | AO9: F | AQ9: 0 | AR9: 0 | AS9: 0 | AT9: 0 | AU9: 2.861 | AV9: 3.723 | AW9: 1406.9401 | AX9: 6 | AY9: C | AZ9: 1 | BA9: 1 | BB9: NO | BC9: 0 | BD9: 0 | BE9: 0 | CI9: 3.292 | CK9: No | CM9: 2.728329 | CN9: 1.5 | CO9: 2.1141645 | CP9: 0 | CQ9: 2.1141645 | CR9: 1318.4572 | CS9: 0 | CT9: 0.017585624 | CU9: 0
A10: 1062 | B10: RED-ES | C10: REDEIA CORP | D10: ES0173093024 | E10: XMAD | F10: 541080000 | G10: 16.83 | H10: EUR | I10: 9106376400 | J10: EU500 | K10: 15311685 | L10: 0.75 | M10: 6829782300 | N10: 18.67 | O10: 1 | P10: 7576472700 | Q10: 65101015 | R10: 6510 | S10: 1.5959603 | U10: A | V10: Green | W10: 0 | X10: 0 | Y10: Green | Z10: Green | AA10: Green | AB10: Green | AC10: Green | AD10: Green | AE10: Green | AF10: 0 | AG10: 0 | AH10: 0 | AJ10: 0 | AK10: F | AM10: F | AN10: F | AO10: F | AQ10: 0 | AR10: 0 | AS10: 0 | AT10: 0 | AU10: 2.938 | AV10: 2.874 | AW10: 95.988242 | AX10: 3.6 | AY10: D | AZ10: 1 | BA10: 1 | BB10: ES | BC10: 0 | BD10: 0 | BE10: 0 | CI10: 2.906 | CK10: No | CM10: 1.5959603 | CN10: 3.1 | CO10: 2.3479802 | CP10: -0.3 | CQ10: 2.0479802 | CR10: 1003.2865 | CS10: 0 | CT10: 0.012207495 | CU10: 0
A11: 1089 | B11: ROCK.B-DK | C11: ROCKWOOL B | D11: DK0063855168 | E11: XCSE | F11: 11754106 | G11: 375.3242 | H11: DKK | I11: 4.4116004e+09 | J11: EU500 | K11: 13834313 | L11: 0.85 | M11: 3.7498604e+09 | N11: 273.4 | O11: 0.13393335 | P11: 3.6584386e+08 | Q11: 50101035 | R11: 5010 | S11: 1.8363484 | T11: 3.1 | U11: B | V11: Green | W11: 0 | X11: 0 | Y11: Green | Z11: Green | AA11: Green | AB11: Green | AC11: Green | AD11: Green | AE11: Green | AF11: 0 | AG11: 0 | AH11: 0 | AJ11: 0 | AK11: F | AM11: F | AN11: F | AO11: F | AQ11: 0 | AR11: 0 | AS11: 0 | AT11: 0 | AU11: 2.152 | AV11: 2.604 | AW11: 46.694402 | AX11: 5.7 | AY11: C | AZ11: 1 | BA11: 1 | BB11: DK | BC11: 0 | BD11: 0 | BE11: 0 | CI11: 2.378 | CK11: No | CM11: 1.8363484 | CN11: 3.1 | CO11: 2.4681742 | CP11: -0.18 | CQ11: 2.2881742 | CR11: 644.98569 | CS11: 0 | CT11: 0.010410682 | CU11: 0
A12: 1159 | B12: SVT-GB | C12: SEVERN TRENT | D12: GB00B1FH8J72 | E12: XLON | F12: 300209100 | G12: 29.42568 | H12: GBX | I12: 8.8338569e+09 | J12: EU500 | K12: 14800849 | L12: 0.9 | M12: 7.9504712e+09 | N12: 2622 | O12: 0.01160026 | P12: 8.218012e+09 | Q12: 65102030 | R12: 6510 | S12: 1.7824348 | T12: 1.5 | U12: A- | V12: Green | W12: 0 | X12: 0 | Y12: Green | Z12: Green | AA12: Green | AB12: Green | AC12: Green | AD12: Green | AE12: Green | AF12: 0 | AG12: 0 | AH12: 0 | AJ12: 0 | AK12: F | AM12: F | AN12: F | AO12: F | AQ12: 0 | AR12: 0 | AS12: 0 | AT12: 0 | AU12: 2.826 | AV12: 3.137 | AW12: 59.179045 | AX12: 4.7 | AY12: E | AZ12: 1 | BA12: 1 | BB12: GB | BC12: 0 | BD12: 0 | BE12: 0 | CI12: 2.9815 | CK12: No | CM12: 1.7824348 | CN12: 1.5 | CO12: 1.6412174 | CP12: -0.24 | CQ12: 1.4012174 | CR12: 1003.2865 | CS12: 1 | CT12: 0.01188565 | CU12: 0
A13: 1321 | B13: TRN-IT | C13: TERNA | D13: IT0003242622 | E13: MTAA | F13: 2009992000 | G13: 7.826 | H13: EUR | I13: 15730197392 | J13: EU500 | K13: 30108575 | L13: 0.7 | M13: 1.1011138e+10 | N13: 8.194 | O13: 1 | P13: 1.1528912e+10 | Q13: 65101015 | R13: 6510 | S13: 1.7449211 | U13: A- | V13: Green | W13: 0 | X13: 0 | Y13: Green | Z13: Green | AA13: Green | AB13: Green | AC13: Green | AD13: Green | AE13: Green | AF13: 0 | AG13: 0 | AH13: 0 | AJ13: 0 | AK13: F | AM13: F | AN13: F | AO13: F | AQ13: 0 | AR13: 0 | AS13: 0 | AT13: 0 | AU13: 2.853 | AV13: 3.169 | AW13: 134.74022 | AX13: 5.8 | AY13: D | AZ13: 1 | BA13: 1 | BB13: IT | BC13: 0 | BD13: 0 | BE13: 0 | CI13: 3.011 | CK13: No | CM13: 1.7449211 | CN13: 3.1 | CO13: 2.4224605 | CP13: -0.24 | CQ13: 2.1824605 | CR13: 1003.2865 | CS13: 0 | CT13: 0.023682713 | CU13: 0
A14: 1421 | B14: VWS-DK | C14: VESTAS WIND SYSTEMS | D14: DK0061539921 | E14: XCSE | F14: 1009867250 | G14: 13.13903 | H14: DKK | I14: 1.3268676e+10 | J14: EU500 | K14: 50667588 | L14: 1 | M14: 1.3268676e+10 | N14: 89.9 | O14: 0.13393335 | P14: 1.2159416e+10 | Q14: 60102020 | R14: 6010 | S14: 1.9940728 | T14: 3.1 | U14: D | V14: Green | W14: 0 | X14: 0 | Y14: Green | Z14: Green | AA14: Green | AB14: Green | AC14: Green | AD14: Green | AE14: Green | AF14: 0 | AG14: 0 | AH14: 0 | AJ14: 0 | AK14: F | AM14: F | AN14: F | AO14: F | AQ14: 0 | AR14: 0 | AS14: 0 | AT14: 0 | AU14: 2.304 | AV14: 3.223 | AW14: 239.55135 | AX14: 1.5 | AY14: C | AZ14: 1 | BA14: 1 | BB14: DK | BC14: 0 | BD14: 0 | BE14: 0 | CI14: 2.7635 | CK14: No | CM14: 1.9940728 | CN14: 3.1 | CO14: 2.5470364 | CP14: 0.18 | CQ14: 2.7270364 | CR14: 2017.1154 | CS14: 0 | CT14: 0.039162201 | CU14: 0
A15: 1458 | B15: WIE-AT | C15: WIENERBERGER AG | D15: AT0000831706 | E15: WBAH | F15: 111732346 | G15: 29.66 | H15: EUR | I15: 3.3139814e+09 | J15: EU500 | K15: 6821360.8 | L15: 1 | M15: 3.3139814e+09 | N15: 29.62 | O15: 1 | P15: 3.3095121e+09 | Q15: 50101035 | R15: 5010 | U15: B | V15: Green | W15: 0 | X15: 0 | Y15: Green | Z15: Green | AA15: Green | AB15: Green | AC15: Green | AD15: Green | AE15: Green | AF15: 0 | AG15: 0 | AH15: 0 | AJ15: 0 | AK15: F | AM15: F | AN15: F | AO15: F | AQ15: 0 | AR15: 0 | AS15: 0 | AT15: 0 | AU15: 2.441 | AV15: 3.471 | AW15: 1738.1272 | AX15: 6 | AY15: C | AZ15: 1 | BA15: 1 | BB15: AT | BC15: 0 | BD15: 0 | BE15: 0 | CI15: 2.956 | CK15: No | CM15: 3.4592708 | CN15: 3.1 | CO15: 3.2796354 | CP15: -0.18 | CQ15: 3.0996354 | CR15: 644.98569 | CS15: 0 | CT15: 0.0054321567 | CU15: 0
A16: 1107 | B16: SGE-GB | C16: SAGE GROUP PLC/THE | D16: GB00B8C3BL03 | E16: XLON | F16: 995756840 | G16: 15.69208 | H16: GBX | I16: 1.5625496e+10 | J16: EU500 | K16: 29289351 | L16: 1 | M16: 1.5625496e+10 | N16: 1159 | O16: 0.01160026 | P16: 1.3387653e+10 | Q16: 10101015 | R16: 1010 | S16: 1.7465783 | T16: 1.5 | U16: A | V16: Green | W16: 0 | X16: 0 | Y16: Green | Z16: Green | AA16: Green | AB16: Green | AC16: Green | AD16: Green | AE16: Green | AF16: 0 | AG16: 0 | AH16: 0 | AJ16: 0 | AK16: F | AM16: F | AN16: F | AO16: F | AQ16: 0 | AR16: 0 | AS16: 0 | AT16: 0 | AU16: 2.41 | AV16: 3.306 | AW16: 14.625099 | AX16: 1.5 | AY16: J | AZ16: 0 | BA16: 0 | BB16: GB | BC16: 0 | BD16: 0 | BE16: 0 | CI16: 2.858 | CK16: No | CM16: 1.7465783 | CN16: 1.5 | CO16: 1.6232892 | CP16: -0.3 | CQ16: 1.3232892 | CR16: 33.625121 | CS16: 1 | CT16: 0.01006564 | CU16: 0
A17: 937 | B17: 4307-JP | C17: NOMURA RESEARCH | D17: JP3762800005 | E17: XTKS | F17: 581241500 | G17: 33.46018 | H17: JPY | I17: 1.9448445e+10 | J17: AS500 | K17: 40113347 | L17: 0.75 | M17: 1.4586334e+10 | N17: 5344 | O17: 0.00613973 | P17: 1.4303213e+10 | Q17: 10101010 | R17: 1010 | S17: 1.7260685 | T17: 1.5 | U17: A- | V17: Green | W17: 0 | X17: 0 | Y17: Green | Z17: Green | AA17: Green | AB17: Green | AC17: Green | AD17: Green | AE17: Green | AF17: 0 | AG17: 0 | AH17: 0 | AJ17: 0 | AK17: F | AM17: F | AN17: F | AO17: F | AQ17: 0 | AR17: 0 | AS17: 0 | AT17: 0 | AU17: 2.499 | AV17: 2.79 | AW17: 15.943331 | AX17: 1.5 | AY17: J | AZ17: 0 | BA17: 0 | BB17: JP | BC17: 0 | BD17: 0 | BE17: 0 | CI17: 2.6445 | CK17: No | CM17: 1.7260685 | CN17: 1.5 | CO17: 1.6130342 | CP17: -0.24 | CQ17: 1.3730342 | CR17: 33.625121 | CS17: 1 | CT17: 0.013400297 | CU17: 0
A18: 601 | B18: HPQ-US | C18: HP INC | D18: US40434L1052 | E18: XNYS | F18: 937797700 | G18: 33.12291 | H18: USD | I18: 3.1062589e+10 | J18: NA500 | K18: 2.280715e+08 | L18: 1 | M18: 3.1062589e+10 | N18: 24.04 | O18: 0.8797009 | P18: 1.9832555e+10 | Q18: 10102030 | R18: 1010 | S18: 1.7487901 | T18: 1.5 | U18: A- | V18: Green | W18: 0 | X18: 0 | Y18: Green | Z18: Green | AA18: Green | AB18: Green | AC18: Green | AD18: Green | AE18: Green | AF18: 0 | AG18: 0 | AH18: 0 | AJ18: 0 | AK18: F | AM18: F | AN18: F | AO18: F | AQ18: 0 | AR18: 0 | AS18: 0 | AT18: 0 | AU18: 2.769 | AV18: 3.447 | AW18: 682.01872 | AX18: 1.5 | AY18: C | AZ18: 1 | BA18: 0 | BB18: US | BC18: 0 | BD18: 0 | BE18: 0 | CI18: 3.108 | CK18: No | CM18: 1.7487901 | CN18: 1.5 | CO18: 1.6243951 | CP18: -0.24 | CQ18: 1.3843951 | CR18: 33.625121 | CS18: 1 | CT18: 0.070315925 | CU18: 0
A19: 508 | B19: 4901-JP | C19: FUJIFILM HOLDING | D19: JP3814000000 | E19: XTKS | F19: 1243877200 | G19: 19.2946 | H19: JPY | I19: 2.4000113e+10 | J19: AS500 | K19: 66540190 | L19: 1 | M19: 2.4000113e+10 | N19: 2648.5 | O19: 0.00613973 | P19: 2.022678e+10 | Q19: 10102035 | R19: 1010 | S19: 1.9017283 | T19: 1.5 | U19: A | V19: Green | W19: 0 | X19: 0 | Y19: Green | Z19: Green | AA19: Green | AB19: Green | AC19: Green | AD19: Green | AE19: Green | AF19: 0 | AG19: 0 | AH19: 0 | AJ19: 0 | AK19: F | AM19: F | AN19: F | AO19: F | AQ19: 0 | AR19: 0 | AS19: 0 | AT19: 0 | AU19: 2.134 | AV19: 2.707 | AW19: 131.18339 | AX19: 1.5 | AY19: C | AZ19: 1 | BA19: 0 | BB19: JP | BC19: 0 | BD19: 0 | BE19: 0 | CI19: 2.4205 | CK19: No | CM19: 1.9017283 | CN19: 1.5 | CO19: 1.7008642 | CP19: -0.3 | CQ19: 1.4008642 | CR19: 33.625121 | CS19: 1 | CT19: 0.021894189 | CU19: 0
A20: 1150 | B20: 6724-JP | C20: SEIKO EPSON | D20: JP3414750004 | E20: XTKS | F20: 384945340 | G20: 15.70364 | H20: JPY | I20: 6.045043e+09 | J20: AS500 | K20: 19629946 | L20: 0.85 | M20: 5.1382866e+09 | N20: 1909.5 | O20: 0.00613973 | P20: 3.8360736e+09 | Q20: 10102030 | R20: 1010 | S20: 1.9541852 | T20: 1.5 | U20: A | V20: Green | W20: 0 | X20: 0 | Y20: Green | Z20: Green | AA20: Green | AB20: Green | AC20: Green | AD20: Green | AE20: Green | AF20: 0 | AG20: 0 | AH20: 0 | AJ20: 0 | AK20: F | AM20: F | AN20: F | AO20: F | AQ20: 0 | AR20: 0 | AS20: 0 | AT20: 0 | AU20: 2.224 | AV20: 2.302 | AW20: 412.03624 | AX20: 1.5 | AY20: C | AZ20: 1 | BA20: 0 | BB20: JP | BC20: 0 | BD20: 0 | BE20: 0 | CI20: 2.263 | CK20: No | CM20: 1.9541852 | CN20: 1.5 | CO20: 1.7270926 | CP20: -0.3 | CQ20: 1.4270926 | CR20: 33.625121 | CS20: 1 | CT20: 0.0062554189 | CU20: 0
A21: 1070 | B21: 6723-JP | C21: RENESAS ELECTRON | D21: JP3164720009 | E21: XTKS | F21: 1870614900 | G21: 17.54549 | H21: JPY | I21: 3.2820855e+10 | J21: AS500 | K21: 1.3825327e+08 | L21: 1 | M21: 3.2820855e+10 | N21: 1660.5 | O21: 0.00613973 | P21: 1.9070959e+10 | Q21: 10102010 | R21: 1010 | S21: 1.9518801 | T21: 1.5 | U21: A- | V21: Green | W21: 0 | X21: 0 | Y21: Green | Z21: Green | AA21: Green | AB21: Green | AC21: Green | AD21: Green | AE21: Green | AF21: 0 | AG21: 0 | AH21: 0 | AJ21: 0 | AK21: F | AM21: F | AN21: F | AO21: F | AQ21: 0 | AR21: 0 | AS21: 0 | AT21: 0 | AU21: 2.474 | AV21: 3.258 | AW21: 73.555304 | AX21: 1.5 | AY21: C | AZ21: 1 | BA21: 0 | BB21: JP | BC21: 0 | BD21: 0 | BE21: 0 | CI21: 2.866 | CK21: No | CM21: 1.9518801 | CN21: 1.5 | CO21: 1.72594 | CP21: -0.24 | CQ21: 1.48594 | CR21: 33.625121 | CS21: 1 | CT21: 0.043297705 | CU21: 0
A22: 1068 | B22: REN-NL | C22: RELX | D22: GB00B2B0DG97 | E22: XAMS | F22: 1907070957 | G22: 47.26 | H22: EUR | I22: 9.0128173e+10 | J22: EU500 | K22: 34161920 | L22: 1 | M22: 9.0128173e+10 | N22: 43.84 | O22: 1 | P22: 8.3605991e+10 | Q22: 10101010 | R22: 1010 | S22: 1.9831747 | T22: 1.5 | U22: B | V22: Green | W22: 0 | X22: 0 | Y22: Green | Z22: Green | AA22: Green | AB22: Green | AC22: Green | AD22: Green | AE22: Green | AF22: 0 | AG22: 0 | AH22: 0 | AJ22: 0 | AK22: F | AM22: F | AN22: F | AO22: F | AQ22: 0 | AR22: 0 | AS22: 0 | AT22: 0 | AU22: 2.474 | AV22: 3.295 | AW22: 5.158333 | AX22: 1.5 | AY22: M | AZ22: 0 | BA22: 0 | BB22: GB | BC22: 0 | BD22: 0 | BE22: 0 | CI22: 2.8845 | CK22: No | CM22: 1.9831747 | CN22: 1.5 | CO22: 1.7415873 | CP22: -0.18 | CQ22: 1.5615873 | CR22: 33.625121 | CS22: 1 | CT22: 0.018234911 | CU22: 0
A23: 892 | B23: 6701-JP | C23: NEC CORP | D23: JP3733000008 | E23: XTKS | F23: 272849850 | G23: 96.66486 | H23: JPY | I23: 2.6374993e+10 | J23: AS500 | K23: 84508284 | L23: 1 | M23: 2.6374993e+10 | N23: 2963 | O23: 0.00613973 | P23: 4.9636899e+09 | Q23: 10102030 | R23: 1010 | S23: 1.740965 | T23: 2.08 | U23: A | V23: Green | W23: 0 | X23: 0 | Y23: Green | Z23: Green | AA23: Green | AB23: Green | AC23: Green | AD23: Green | AE23: Green | AF23: 0 | AG23: 0 | AH23: 0 | AJ23: 0 | AK23: F | AM23: F | AN23: F | AO23: F | AQ23: 0 | AR23: 0 | AS23: 0 | AT23: 0 | AU23: 2.478 | AV23: 2.811 | AW23: 110.91259 | AX23: 1.5 | AY23: J | AZ23: 0 | BA23: 0 | BB23: JP | BC23: 0 | BD23: 0 | BE23: 0 | CI23: 2.6445 | CK23: No | CM23: 1.740965 | CN23: 2.08 | CO23: 1.9104825 | CP23: -0.3 | CQ23: 1.6104825 | CR23: 33.625121 | CS23: 1 | CT23: 0.025826634 | CU23: 0
A24: 235 | B24: 7751-JP | C24: CANON INC | D24: JP3242800005 | E24: XTKS | F24: 1333763400 | G24: 32.78867 | H24: JPY | I24: 4.3732328e+10 | J24: AS500 | K24: 87704081 | L24: 0.7 | M24: 3.061263e+10 | N24: 4247 | O24: 0.00613973 | P24: 2.4344921e+10 | Q24: 10102035 | R24: 1010 | S24: 1.9387809 | T24: 1.77 | U24: A- | V24: Green | W24: 0 | X24: 0 | Y24: Green | Z24: Green | AA24: Green | AB24: Green | AC24: Green | AD24: Green | AE24: Green | AF24: 0 | AG24: 0 | AH24: 0 | AJ24: 0 | AK24: F | AM24: F | AN24: F | AO24: F | AQ24: 0 | AR24: 0 | AS24: 0 | AT24: 0 | AU24: 2.406 | AV24: 2.765 | AW24: 264.55706 | AX24: 1.5 | AY24: C | AZ24: 1 | BA24: 0 | BB24: JP | BC24: 0 | BD24: 0 | BE24: 0 | CI24: 2.5855 | CK24: No | CM24: 1.9387809 | CN24: 1.77 | CO24: 1.8543904 | CP24: -0.24 | CQ24: 1.6143904 | CR24: 33.625121 | CS24: 1 | CT24: 0.028636736 | CU24: 0
A25: 1140 | B25: 9719-JP | C25: SCSK CORP | D25: JP3400400002 | E25: XTKS | F25: 312875180 | G25: 24.06549 | H25: JPY | I25: 7.5294945e+09 | J25: AS500 | K25: 18693970 | L25: 0.5 | M25: 3.7647473e+09 | N25: 3603 | O25: 0.00613973 | P25: 3.4606259e+09 | Q25: 10101010 | R25: 1010 | S25: 1.9702873 | T25: 2.39 | U25: A | V25: Green | W25: 0 | X25: 0 | Y25: Green | Z25: Green | AA25: Green | AB25: Green | AC25: Green | AD25: Green | AE25: Green | AF25: 0 | AG25: 0 | AH25: 0 | AJ25: 0 | AK25: F | AM25: F | AN25: F | AO25: F | AQ25: 0 | AR25: 0 | AS25: 0 | AT25: 0 | AU25: 2.194 | AV25: 1.978 | AW25: 140.99185 | AX25: 1.5 | AY25: J | AZ25: 0 | BA25: 0 | BB25: JP | BC25: 0 | BD25: 0 | BE25: 0 | CI25: 2.086 | CK25: No | CM25: 1.9702873 | CN25: 2.39 | CO25: 2.1801436 | CP25: -0.3 | CQ25: 1.8801436 | CR25: 33.625121 | CS25: 0 | CT25: 0.0059387621 | CU25: 0
A26: 1449 | B26: WDC-US | C26: WESTERN DIGITAL CORP | D26: US9581021055 | E26: XNGS | F26: 347823900 | G26: 65.71497 | H26: USD | I26: 2.2857237e+10 | J26: NA500 | K26: 3.9794983e+08 | L26: 1 | M26: 2.2857237e+10 | N26: 35.82 | O26: 0.8797009 | P26: 1.0960239e+10 | Q26: 10102030 | R26: 1010 | S26: 1.9618808 | T26: 1.5 | U26: D | V26: Green | W26: 0 | X26: 0 | Y26: Green | Z26: Green | AA26: Green | AB26: Green | AC26: Green | AD26: Green | AE26: Green | AF26: 0 | AG26: 0 | AH26: 0 | AJ26: 0 | AK26: F | AM26: F | AN26: F | AO26: F | AQ26: 0 | AR26: 0 | AS26: 0 | AT26: 0 | AU26: 2.396 | AV26: 3.106 | AW26: 903.69973 | AX26: 1.5 | AY26: C | AZ26: 1 | BA26: 0 | BB26: US | BC26: 0 | BD26: 0 | BE26: 0 | CI26: 2.751 | CK26: No | CM26: 1.9618808 | CN26: 1.5 | CO26: 1.7309404 | CP26: 0.18 | CQ26: 1.9109404 | CR26: 33.625121 | CS26: 1 | CT26: 0.1 | CU26: 0
A27: 296 | B27: CTSH-US | C27: COGNIZANT TECHN SOL | D27: US1924461023 | E27: XNGS | F27: 494615500 | G27: 81.17648 | H27: USD | I27: 4.0151145e+10 | J27: NA500 | K27: 2.3407602e+08 | L27: 1 | M27: 4.0151145e+10 | N27: 70.81 | O27: 0.8797009 | P27: 3.0810401e+10 | Q27: 10101010 | R27: 1010 | S27: 1.7317486 | T27: 1.77 | U27: D | V27: Green | W27: 0 | X27: 0 | Y27: Green | Z27: Green | AA27: Green | AB27: Green | AC27: Green | AD27: Green | AE27: Green | AF27: 0 | AG27: 0 | AH27: 0 | AJ27: 0 | AK27: F | AM27: F | AN27: F | AO27: F | AQ27: 0 | AR27: 0 | AS27: 0 | AT27: 0 | AU27: 2.665 | AV27: 2.895 | AW27: 19.647787 | AX27: 1.5 | AY27: J | AZ27: 0 | BA27: 0 | BB27: US | BC27: 0 | BD27: 0 | BE27: 0 | CI27: 2.78 | CK27: No | CM27: 1.7317486 | CN27: 1.77 | CO27: 1.7508743 | CP27: 0.18 | CQ27: 1.9308743 | CR27: 33.625121 | CS27: 1 | CT27: 0.073165921 | CU27: 0
... A30: 1141 | B30: STX-US | C30: SEAGATE TECHNOLOGY | D30: IE00BKVD2N49 | E30: XNGS | F30: 211707400 | G30: 96.46102 | H30: USD | I30: 2.0421512e+10 | J30: NA500 | K30: 2.8058437e+08 | L30: 1 | M30: 2.0421512e+10 | N30: 72.67 | O30: 0.8797009 | P30: 1.3534002e+10 | Q30: 10102030 | R30: 1010 | S30: 1.9820846 | T30: 2.08 | U30: C | V30: Green | W30: 0 | X30: 0 | Y30: Green | Z30: Green | AA30: Green | AB30: Green | AC30: Green | AD30: Green | AE30: Green | AF30: 0 | AG30: 0 | AH30: 0 | AJ30: 0 | AK30: F | AM30: F | AN30: F | AO30: F | AQ30: 0 | AR30: 0 | AS30: 0 | AT30: 0 | AU30: 2.452 | AV30: 3.387 | AW30: 329.02082 | AX30: 1.8 | AY30: C | AZ30: 1 | BA30: 0 | BB30: IE | BC30: 0 | BD30: 0 | BE30: 0 | CI30: 2.9195 | CK30: No | CM30: 1.9820846 | CN30: 2.08 | CO30: 2.0310423 | CP30: 0 | CQ30: 2.0310423 | CR30: 33.625121 | CS30: 0 | CT30: 0.085468126 | CU30: 0
A31: 792 | B31: 4689-JP | C31: LY CORPORATION | D31: JP3933800009 | E31: XTKS | F31: 7152421400 | G31: 3.143927 | H31: JPY | I31: 2.2486691e+10 | J31: AS500 | K31: 31542508 | L31: 0.4 | M31: 8.9946763e+09 | N31: 517 | O31: 0.00613973 | P31: 9.081402e+09 | Q31: 10101020 | R31: 1010 | S31: 1.6174571 | U31: A | V31: Green | W31: 0 | X31: 0 | Y31: Green | Z31: Green | AA31: Green | AB31: Green | AC31: Green | AD31: Green | AE31: Green | AF31: 0 | AG31: 0 | AH31: 0 | AJ31: 0 | AK31: F | AM31: F | AN31: F | AO31: F | AQ31: 0 | AR31: 0 | AS31: 0 | AT31: 0 | AU31: 2.329 | AV31: 2.558 | AW31: 95.668827 | AX31: 1.5 | AY31: J | AZ31: 0 | BA31: 0 | BB31: JP | BC31: 0 | BD31: 0 | BE31: 0 | CI31: 2.4435 | CK31: No | CM31: 1.6174571 | CN31: 3.1 | CO31: 2.3587286 | CP31: -0.3 | CQ31: 2.0587286 | CR31: 33.625121 | CS31: 0 | CT31: 0.010330239 | CU31: 0
A32: 949 | B32: 9613-JP | C32: NTT DATA GROUP CORP | D32: JP3165700000 | E32: XTKS | F32: 1402500000 | G32: 19.04519 | H32: JPY | I32: 26710878975 | J32: AS500 | K32: 56462596 | L32: 0.4 | M32: 10684351590 | N32: 2510.5 | O32: 0.00613973 | P32: 8.6471374e+09 | Q32: 10101010 | R32: 1010 | S32: 1.7373531 | T32: 3.01 | U32: A | V32: Green | W32: 0 | X32: 0 | Y32: Green | Z32: Green | AA32: Green | AB32: Green | AC32: Green | AD32: Green | AE32: Green | AF32: 0 | AG32: 0 | AH32: 0 | AJ32: 0 | AK32: F | AM32: F | AN32: F | AO32: F | AQ32: 0 | AR32: 0 | AS32: 0 | AT32: 0 | AU32: 2.477 | AV32: 2.581 | AW32: 56.885476 | AX32: 1.5 | AY32: J | AZ32: 0 | BA32: 0 | BB32: JP | BC32: 0 | BD32: 0 | BE32: 0 | CI32: 2.529 | CK32: No | CM32: 1.7373531 | CN32: 3.01 | CO32: 2.3736766 | CP32: -0.3 | CQ32: 2.0736766 | CR32: 33.625121 | CS32: 0 | CT32: 0.017764783 | CU32: 0
A33: 1139 | B33: 7735-JP | C33: SCREEN HOLDINGS | D33: JP3494600004 | E33: XTKS | F33: 101589730 | G33: 75.08075 | H33: JPY | I33: 7.6274331e+09 | J33: AS500 | K33: 1.179789e+08 | L33: 1 | M33: 7.6274331e+09 | N33: 9487 | O33: 0.00613973 | P33: 5.9173598e+09 | Q33: 10102020 | R33: 1010 | S33: 1.9963885 | T33: 2.7 | U33: A- | V33: Green | W33: 0 | X33: 0 | Y33: Green | Z33: Green | AA33: Green | AB33: Green | AC33: Green | AD33: Green | AE33: Green | AF33: 0 | AG33: 0 | AH33: 0 | AJ33: 0 | AK33: F | AM33: F | AN33: F | AO33: F | AQ33: 0 | AR33: 0 | AS33: 0 | AT33: 0 | AU33: 1.963 | AV33: 2.131 | AW33: 393.19901 | AX33: 1.5 | AY33: C | AZ33: 1 | BA33: 0 | BB33: JP | BC33: 0 | BD33: 0 | BE33: 0 | CI33: 2.047 | CK33: No | CM33: 1.9963885 | CN33: 2.7 | CO33: 2.3481942 | CP33: -0.24 | CQ33: 2.1081942 | CR33: 33.625121 | CS33: 0 | CT33: 0.035958917 | CU33: 0
A34: 1335 | B34: 3626-JP | C34: TIS INC | D34: JP3104890003 | E34: XTKS | F34: 236233410 | G34: 24.52595 | H34: JPY | I34: 5.7938488e+09 | J34: AS500 | K34: 20044155 | L34: 1 | M34: 5.7938488e+09 | N34: 3983 | O34: 0.00613973 | P34: 5.7769805e+09 | Q34: 10101010 | R34: 1010 | S34: 1.7256042 | T34: 3.1 | U34: A | V34: Green | W34: 0 | X34: 0 | Y34: Green | Z34: Green | AA34: Green | AB34: Green | AC34: Green | AD34: Green | AE34: Green | AF34: 0 | AG34: 0 | AH34: 0 | AJ34: 0 | AK34: F | AM34: F | AN34: F | AO34: F | AQ34: 0 | AR34: 0 | AS34: 0 | AT34: 0 | AU34: 2.126 | AV34: 2.229 | AW34: 87.580417 | AX34: 1.5 | AY34: J | AZ34: 0 | BA34: 0 | BB34: JP | BC34: 0 | BD34: 0 | BE34: 0 | CI34: 2.1775 | CK34: No | CM34: 1.7256042 | CN34: 3.1 | CO34: 2.4128021 | CP34: -0.3 | CQ34: 2.1128021 | CR34: 33.625121 | CS34: 0 | CT34: 0.0065650838 | CU34: 0
A35: 118 | B35: ASM-NL | C35: ASM INTERNATIONAL | D35: NL0000334118 | E35: XAMS | F35: 49328548 | G35: 569.8 | H35: EUR | I35: 2.8107407e+10 | J35: EU500 | K35: 78679459 | L35: 0.95 | M35: 2.6702036e+10 | N35: 385.6 | O35: 1 | P35: 1.8070034e+10 | Q35: 10102020 | R35: 1010 | S35: 1.7486641 | T35: 3.1 | U35: A | V35: Green | W35: 0 | X35: 0 | Y35: Green | Z35: Green | AA35: Green | AB35: Green | AC35: Green | AD35: Green | AE35: Green | AF35: 0 | AG35: 0 | AH35: 0 | AJ35: 0 | AK35: F | AM35: F | AN35: F | AO35: F | AQ35: 0 | AR35: 0 | AS35: 0 | AT35: 0 | AU35: 2.446 | AV35: 3.219 | AW35: 51.61805 | AX35: 1.5 | AY35: C | AZ35: 1 | BA35: 0 | BB35: NL | BC35: 0 | BD35: 0 | BE35: 0 | CI35: 2.8325 | CK35: No | CM35: 1.7486641 | CN35: 3.1 | CO35: 2.4243321 | CP35: -0.3 | CQ35: 2.1243321 | CR35: 33.625121 | CS35: 0 | CT35: 0.02532995 | CU35: 0
A36: 766 | B36: 992-HK | C36: LENOVO GROUP LIMITED | D36: HK0992009065 | E36: XHKG | F36: 12404659000 | G36: 1.674363 | H36: HKD | I36: 2.0769902e+10 | J36: AS500 | K36: 1.0995044e+08 | L36: 0.65 | M36: 1.3500436e+10 | N36: 8.27 | O36: 0.11342884 | P36: 7.5635762e+09 | Q36: 10102030 | R36: 1010 | S36: 1.749664 | U36: A | V36: Green | W36: 0 | X36: 0 | Y36: Green | Z36: Green | AA36: Green | AB36: Green | AC36: Green | AD36: Green | AE36: Green | AF36: 0 | AG36: 0 | AH36: 0 | AJ36: 0 | AK36: F | AM36: F | AN36: F | AO36: F | AQ36: 0 | AR36: 0 | AS36: 0 | AT36: 0 | AU36: 2.412 | AV36: 2.657 | AW36: 871.05588 | AX36: 1.5 | AY36: C | AZ36: 1 | BA36: 0 | BB36: HK | BC36: 0 | BD36: 0 | BE36: 0 | CI36: 2.5345 | CK36: No | CM36: 1.749664 | CN36: 3.1 | CO36: 2.424832 | CP36: -0.3 | CQ36: 2.124832 | CR36: 33.625121 | CS36: 0 | CT36: 0.03370763 | CU36: 0
A37: 779 | B37: LOGN-CH | C37: LOGITECH INTL SA | D37: CH0025751329 | E37: XSWX | F37: 168994140 | G37: 99.48116 | H37: CHF | I37: 1.6811733e+10 | J37: EU500 | K37: 53427463 | L37: 0.9 | M37: 1.513056e+10 | N37: 60.7 | O37: 1.0763104 | P37: 9.936659e+09 | Q37: 10102030 | R37: 1010 | S37: 1.7497523 | U37: A | V37: Green | W37: 0 | X37: 0 | Y37: Green | Z37: Green | AA37: Green | AB37: Green | AC37: Green | AD37: Green | AE37: Green | AF37: 0 | AG37: 0 | AH37: 0 | AJ37: 0 | AK37: F | AM37: F | AN37: F | AO37: F | AQ37: 0 | AR37: 0 | AS37: 0 | AT37: 0 | AU37: 2.565 | AV37: 3.4 | AW37: 140.57785 | AX37: 1.5 | AY37: C | AZ37: 1 | BA37: 0 | BB37: CH | BC37: 0 | BD37: 0 | BE37: 0 | CI37: 2.9825 | CK37: No | CM37: 1.7497523 | CN37: 3.1 | CO37: 2.4248762 | CP37: -0.3 | CQ37: 2.1248762 | CR37: 33.625121 | CS37: 0 | CT37: 0.016977423 | CU37: 0
A38: 1497 | B38: ZS-US | C38: ZSCALER INC. | D38: US98980G1022 | E38: XNGS | F38: 153438630 | G38: 189.9187 | H38: USD | I38: 2.9140865e+10 | J38: NA500 | K38: 3.4970744e+08 | L38: 0.6 | M38: 1.7484519e+10 | N38: 199.44 | O38: 0.8797009 | P38: 1.6152259e+10 | Q38: 10101015 | R38: 1010 | S38: 1.5594323 | U38: B | V38: Green | W38: 0 | X38: 0 | Y38: Green | Z38: Green | AA38: Green | AB38: Green | AC38: Green | AD38: Green | AE38: Green | AF38: 0 | AG38: 0 | AH38: 0 | AJ38: 0 | AK38: F | AM38: F | AN38: F | AO38: F | AQ38: 0 | AR38: 0 | AS38: 0 | AT38: 0 | AU38: 2.422 | AV38: 2.761 | AW38: 0.81633985 | AX38: 1.5 | AY38: J | AZ38: 0 | BA38: 0 | BB38: US | BC38: 0 | BD38: 0 | BE38: 0 | CI38: 2.5915 | CK38: No | CM38: 1.5594323 | CN38: 3.1 | CO38: 2.3297161 | CP38: -0.18 | CQ38: 2.1497161 | CR38: 33.625121 | CS38: 0 | CT38: 0.1 | CU38: 0
A39: 100 | B39: AMAT-US | C39: APPLIED MATERIALS | D39: US0382221051 | E39: XNGS | F39: 812440860 | G39: 164.4955 | H39: USD | I39: 1.3364287e+11 | J39: NA500 | K39: 1.120737e+09 | L39: 1 | M39: 1.3364287e+11 | N39: 144.53 | O39: 0.8797009 | P39: 1.0329631e+11 | Q39: 10102020 | R39: 1010 | S39: 1.9971232 | T39: 2.7 | U39: B | V39: Green | W39: 0 | X39: 0 | Y39: Green | Z39: Green | AA39: Green | AB39: Green | AC39: Green | AD39: Green | AE39: Green | AF39: 0 | AG39: 0 | AH39: 0 | AJ39: 0 | AK39: F | AM39: F | AN39: F | AO39: F | AQ39: 0 | AR39: 0 | AS39: 0 | AT39: 0 | AU39: 2.522 | AV39: 3.158 | AW39: 202.72372 | AX39: 1.5 | AY39: C | AZ39: 1 | BA39: 0 | BB39: US | BC39: 0 | BD39: 0 | BE39: 0 | CI39: 2.84 | CK39: No | CM39: 1.9971232 | CN39: 2.7 | CO39: 2.3485616 | CP39: -0.18 | CQ39: 2.1685616 | CR39: 33.625121 | CS39: 0 | CT39: 0.1 | CU39: 0
A40: 228 | B40: CDNS-US | C40: CADENCE DESIGN SYST. | D40: US1273871087 | E40: XNGS | F40: 274108000 | G40: 247.0971 | H40: USD | I40: 6.7731292e+10 | J40: NA500 | K40: 4.9305628e+08 | L40: 1 | M40: 6.7731292e+10 | N40: 260.56 | O40: 0.8797009 | P40: 6.2829629e+10 | Q40: 10101015 | R40: 1010 | S40: 1.7199766 | T40: 3.1 | U40: A- | V40: Green | W40: 0 | X40: 0 | Y40: Green | Z40: Green | AA40: Green | AB40: Green | AC40: Green | AD40: Green | AE40: Green | AF40: 0 | AG40: 0 | AH40: 0 | AJ40: 0 | AK40: F | AM40: F | AN40: F | AO40: F | AQ40: 0 | AR40: 0 | AS40: 0 | AT40: 0 | AU40: 2.182 | AV40: 3.348 | AW40: 4.827636 | AX40: 1.5 | AY40: J | AZ40: 0 | BA40: 0 | BB40: US | BC40: 0 | BD40: 0 | BE40: 0 | CI40: 2.765 | CK40: No | CM40: 1.7199766 | CN40: 3.1 | CO40: 2.4099883 | CP40: -0.24 | CQ40: 2.1699883 | CR40: 33.625121 | CS40: 0 | CT40: 0.1 | CU40: 0
A41: 70 | B41: AMS-ES | C41: AMADEUS IT GROUP | D41: ES0109067019 | E41: XMAD | F41: 450499200 | G41: 69.46 | H41: EUR | I41: 31291674432 | J41: EU500 | K41: 42461320 | L41: 1 | M41: 31291674432 | N41: 66.52 | O41: 1 | P41: 29967206784 | Q41: 10101010 | R41: 1010 | S41: 1.7124186 | T41: 3.01 | U41: B | V41: Green | W41: 0 | X41: 0 | Y41: Green | Z41: Green | AA41: Green | AB41: Green | AC41: Green | AD41: Green | AE41: Green | AF41: 0 | AG41: 0 | AH41: 0 | AJ41: 0 | AK41: F | AM41: F | AN41: F | AO41: F | AQ41: 0 | AR41: 0 | AS41: 0 | AT41: 0 | AU41: 2.506 | AV41: 3.136 | AW41: 7.5164737 | AX41: 1.5 | AY41: N | AZ41: 0 | BA41: 0 | BB41: ES | BC41: 0 | BD41: 0 | BE41: 0 | CI41: 2.821 | CK41: No | CM41: 1.7124186 | CN41: 3.01 | CO41: 2.3612093 | CP41: -0.18 | CQ41: 2.1812093 | CR41: 33.625121 | CS41: 0 | CT41: 0.015600968 | CU41: 0
A42: 578 | B42: HEXA.B-SE | C42: HEXAGON AB-B | D42: SE0015961909 | E42: XSTO | F42: 2595227800 | G42: 11.41081 | H42: SEK | I42: 2.9613651e+10 | J42: EU500 | K42: 42986586 | L42: 0.8 | M42: 2.3690921e+10 | N42: 89.96 | O42: 0.09077334 | P42: 1.6954041e+10 | Q42: 10101015 | R42: 1010 | S42: 1.7041863 | U42: B | V42: Green | W42: 0 | X42: 0 | Y42: Green | Z42: Green | AA42: Green | AB42: Green | AC42: Green | AD42: Green | AE42: Green | AF42: 0 | AG42: 0 | AH42: 0 | AJ42: 0 | AK42: F | AM42: F | AN42: F | AO42: F | AQ42: 0 | AR42: 0 | AS42: 0 | AT42: 0 | AU42: 1.968 | AV42: 2.952 | AW42: 89.153148 | AX42: 1.5 | AY42: C | AZ42: 1 | BA42: 0 | BB42: SE | BC42: 0 | BD42: 0 | BE42: 0 | CI42: 2.46 | CK42: No | CM42: 1.7041863 | CN42: 3.1 | CO42: 2.4020931 | CP42: -0.18 | CQ42: 2.2220931 | CR42: 33.625121 | CS42: 0 | CT42: 0.014515485 | CU42: 0
A43: 1080 | B43: 7752-JP | C43: RICOH CO LTD | D43: JP3973400009 | E43: XTKS | F43: 569733150 | G43: 9.858345 | H43: JPY | I43: 5.616626e+09 | J43: AS500 | K43: 19260711 | L43: 0.8 | M43: 4.4933008e+09 | N43: 1454 | O43: 0.00613973 | P43: 4.0688826e+09 | Q43: 10102035 | R43: 1010 | S43: 1.9452581 | T43: 3.1 | U43: A | V43: Green | W43: 0 | X43: 0 | Y43: Green | Z43: Green | AA43: Green | AB43: Green | AC43: Green | AD43: Green | AE43: Green | AF43: 0 | AG43: 0 | AH43: 0 | AJ43: 0 | AK43: F | AM43: F | AN43: F | AO43: F | AQ43: 0 | AR43: 0 | AS43: 0 | AT43: 0 | AU43: 2.537 | AV43: 2.915 | AW43: 273.68009 | AX43: 1.5 | AY43: C | AZ43: 1 | BA43: 0 | BB43: JP | BC43: 0 | BD43: 0 | BE43: 0 | CI43: 2.726 | CK43: No | CM43: 1.9452581 | CN43: 3.1 | CO43: 2.5226291 | CP43: -0.3 | CQ43: 2.2226291 | CR43: 33.625121 | CS43: 0 | CT43: 0.0061668872 | CU43: 0
A44: 1090 | B44: 6963-JP | C44: ROHM CO LTD | D44: JP3982800009 | E44: XTKS | F44: 403760000 | G44: 10.4659 | H44: JPY | I44: 4225711784 | J44: AS500 | K44: 35664535 | L44: 0.9 | M44: 3.8031406e+09 | N44: 1283 | O44: 0.00613973 | P44: 2.8624752e+09 | Q44: 10102010 | R44: 1010 | S44: 1.9567041 | T44: 3.1 | U44: A | V44: Green | W44: 0 | X44: 0 | Y44: Green | Z44: Green | AA44: Green | AB44: Green | AC44: Green | AD44: Green | AE44: Green | AF44: 0 | AG44: 0 | AH44: 0 | AJ44: 0 | AK44: F | AM44: F | AN44: F | AO44: F | AQ44: 0 | AR44: 0 | AS44: 0 | AT44: 0 | AU44: 2.252 | AV44: 2.288 | AW44: 218.44367 | AX44: 2.2 | AY44: C | AZ44: 1 | BA44: 0 | BB44: JP | BC44: 0 | BD44: 0 | BE44: 0 | CI44: 2.27 | CK44: No | CM44: 1.9567041 | CN44: 3.1 | CO44: 2.528352 | CP44: -0.3 | CQ44: 2.228352 | CR44: 33.625121 | CS44: 0 | CT44: 0.010972794 | CU44: 0
A45: 971 | B45: ORCL-US | C45: ORACLE CORP | D45: US68389X1054 | E45: XNYS | F45: 2796956000 | G45: 160.5069 | H45: USD | I45: 4.4893074e+11 | J45: NA500 | K45: 1.8014585e+09 | L45: 0.6 | M45: 2.6935844e+11 | N45: 134.64 | O45: 0.8797009 | P45: 1.987678e+11 | Q45: 10101015 | R45: 1010 | S45: 2.3866667 | T45: 2.08 | U45: C | V45: Green | W45: 0 | X45: 0 | Y45: Green | Z45: Green | AA45: Green | AB45: Green | AC45: Green | AD45: Green | AE45: Green | AF45: 0 | AG45: 0 | AH45: 0 | AJ45: 0 | AK45: F | AM45: F | AN45: F | AO45: F | AQ45: 0 | AR45: 0 | AS45: 0 | AT45: 0 | AU45: 2.479 | AV45: 2.953 | AW45: 2.7096844 | AX45: 1.5 | AY45: J | AZ45: 0 | BA45: 0 | BB45: US | BC45: 0 | BD45: 0 | BE45: 0 | CI45: 2.716 | CK45: No | CM45: 2.3866667 | CN45: 2.08 | CO45: 2.2333333 | CP45: 0 | CQ45: 2.2333333 | CR45: 33.625121 | CS45: 0 | CT45: 0.1 | CU45: 0
A46: 649 | B46: INTU-US | C46: INTUIT INC. | D46: US4612021034 | E46: XNGS | F46: 279916780 | G46: 540.8608 | H46: USD | I46: 1.5139601e+11 | J46: NA500 | K46: 1.0168728e+09 | L46: 1 | M46: 1.5139601e+11 | N46: 593.55 | O46: 0.8797009 | P46: 1.4615756e+11 | Q46: 10101015 | R46: 1010 | S46: 1.7411493 | U46: B | V46: Green | W46: 0 | X46: 0 | Y46: Green | Z46: Green | AA46: Green | AB46: Green | AC46: Green | AD46: Green | AE46: Green | AF46: 0 | AG46: 0 | AH46: 0 | AJ46: 0 | AK46: F | AM46: F | AN46: F | AO46: F | AQ46: 0 | AR46: 0 | AS46: 0 | AT46: 0 | AU46: 1.986 | AV46: 2.837 | AW46: 3.6457484 | AX46: 1.5 | AY46: J | AZ46: 0 | BA46: 0 | BB46: US | BC46: 0 | BD46: 0 | BE46: 0 | CI46: 2.4115 | CK46: No | CM46: 1.7411493 | CN46: 3.1 | CO46: 2.4205747 | CP46: -0.18 | CQ46: 2.2405747 | CR46: 33.625121 | CS46: 0 | CT46: 0.1 | CU46: 0
A47: 1050 | B47: 4755-JP | C47: RAKUTEN GROUP INC | D47: JP3967200001 | E47: XTKS | F47: 2155002000 | G47: 6.283376 | H47: JPY | I47: 1.3540688e+10 | J47: AS500 | K47: 1.4699366e+08 | L47: 0.7 | M47: 9.4784815e+09 | N47: 771.5 | O47: 0.00613973 | P47: 7.145472e+09 | Q47: 10101020 | R47: 1010 | S47: 1.9860258 | U47: A | V47: Green | W47: 0 | X47: 0 | Y47: Green | Z47: Green | AA47: Green | AB47: Green | AC47: Green | AD47: Green | AE47: Green | AF47: 0 | AG47: 0 | AH47: 0 | AJ47: 0 | AK47: F | AM47: F | AN47: F | AO47: F | AQ47: 0 | AR47: 0 | AS47: 0 | AT47: 0 | AU47: 1.86 | AV47: 2.359 | AW47: 313.11089 | AX47: 1.5 | AY47: G | AZ47: 1 | BA47: 0 | BB47: JP | BC47: 0 | BD47: 0 | BE47: 0 | CI47: 2.1095 | CK47: No | CM47: 1.9860258 | CN47: 3.1 | CO47: 2.5430129 | CP47: -0.3 | CQ47: 2.2430129 | CR47: 33.625121 | CS47: 0 | CT47: 0.044780658 | CU47: 0
A48: 1124 | B48: SAP-DE | C48: SAP | D48: DE0007164600 | E48: XETR | F48: 1228504300 | G48: 273.6 | H48: EUR | I48: 336118776480 | J48: EU500 | K48: 3.6855448e+08 | L48: 0.95 | M48: 319312837656 | N48: 228.8 | O48: 1 | P48: 267027694648 | Q48: 10101015 | R48: 1010 | S48: 1.7474068 | T48: 3.1 | U48: B | V48: Green | W48: 0 | X48: 0 | Y48: Green | Z48: Green | AA48: Green | AB48: Green | AC48: Green | AD48: Green | AE48: Green | AF48: 0 | AG48: 0 | AH48: 0 | AJ48: 0 | AK48: F | AM48: F | AN48: F | AO48: F | AQ48: 0 | AR48: 0 | AS48: 0 | AT48: 0 | AU48: 2.961 | AV48: 3.121 | AW48: 59.213927 | AX48: 1.5 | AY48: J | AZ48: 0 | BA48: 0 | BB48: DE | BC48: 0 | BD48: 0 | BE48: 0 | CI48: 3.041 | CK48: No | CM48: 1.7474068 | CN48: 3.1 | CO48: 2.4237034 | CP48: -0.18 | CQ48: 2.2437034 | CR48: 33.625121 | CS48: 0 | CT48: 0.1 | CU48: 0
A49: 990 | B49: PANW-US | C49: PALO ALTO NETWORKS | D49: US6974351057 | E49: XNGS | F49: 662100000 | G49: 182.7164 | H49: USD | I49: 120976528440 | J49: NA500 | K49: 1.0602036e+09 | L49: 1 | M49: 120976528440 | N49: 169.98 | O49: 0.8797009 | P49: 9.9004845e+10 | Q49: 10101015 | R49: 1010 | S49: 1.7475101 | U49: B | V49: Green | W49: 0 | X49: 0 | Y49: Green | Z49: Green | AA49: Green | AB49: Green | AC49: Green | AD49: Green | AE49: Green | AF49: 0 | AG49: 0 | AH49: 0 | AJ49: 0 | AK49: F | AM49: F | AN49: F | AO49: F | AQ49: 0 | AR49: 0 | AS49: 0 | AT49: 0 | AU49: 2.452 | AV49: 3.018 | AW49: 10.682149 | AX49: 1.5 | AY49: J | AZ49: 0 | BA49: 0 | BB49: US | BC49: 0 | BD49: 0 | BE49: 0 | CI49: 2.735 | CK49: No | CM49: 1.7475101 | CN49: 3.1 | CO49: 2.4237551 | CP49: -0.18 | CQ49: 2.2437551 | CR49: 33.625121 | CS49: 0 | CT49: 0.1 | CU49: 0
A50: 1110 | B50: CRM-US | C50: SALESFORCE INC | D50: US79466L3024 | E50: XNYS | F50: 957000000 | G50: 296.3175 | H50: USD | I50: 283575847500 | J50: NA500 | K50: 2.1443866e+09 | L50: 1 | M50: 283575847500 | N50: 254.55 | O50: 0.8797009 | P50: 2.1429897e+11 | Q50: 10101015 | R50: 1010 | S50: 1.9635314 | T50: 3.01 | U50: A- | V50: Green | W50: 0 | X50: 0 | Y50: Green | Z50: Green | AA50: Green | AB50: Green | AC50: Green | AD50: Green | AE50: Green | AF50: 0 | AG50: 0 | AH50: 0 | AJ50: 0 | AK50: F | AM50: F | AN50: F | AO50: F | AQ50: 0 | AR50: 0 | AS50: 0 | AT50: 0 | AU50: 2.548 | AV50: 3.241 | AW50: 7.1464193 | AX50: 1.5 | AY50: J | AZ50: 0 | BA50: 0 | BB50: US | BC50: 0 | BD50: 0 | BE50: 0 | CI50: 2.8945 | CK50: No | CM50: 1.9635314 | CN50: 3.01 | CO50: 2.4867657 | CP50: -0.24 | CQ50: 2.2467657 | CR50: 33.625121 | CS50: 0 | CT50: 0.1 | CU50: 0
A51: 611 | B51: 4062-JP | C51: IBIDEN CO LTD | D51: JP3148800000 | E51: XTKS | F51: 140860570 | G51: 24.49397 | H51: JPY | I51: 3.4502346e+09 | J51: AS500 | K51: 62689257 | L51: 1 | M51: 3.4502346e+09 | N51: 3622 | O51: 0.00613973 | P51: 3.1324717e+09 | Q51: 10102015 | R51: 1010 | S51: 3.0254821 | T51: 1.5 | U51: C | V51: Green | W51: 0 | X51: 0 | Y51: Green | Z51: Green | AA51: Green | AB51: Green | AC51: Green | AD51: Green | AE51: Green | AF51: 0 | AG51: 0 | AH51: 0 | AJ51: 0 | AK51: F | AM51: F | AN51: F | AO51: F | AQ51: 0 | AR51: 0 | AS51: 0 | AT51: 0 | AU51: 2.158 | AV51: 2.207 | AW51: 134.91089 | AX51: 2.3 | AY51: C | AZ51: 1 | BA51: 0 | BB51: JP | BC51: 0 | BD51: 0 | BE51: 0 | CI51: 2.1825 | CK51: No | CM51: 3.0254821 | CN51: 1.5 | CO51: 2.262741 | CP51: 0 | CQ51: 2.262741 | CR51: 33.625121 | CS51: 0 | CT51: 0.019106002 | CU51: 0
A52: 319 | B52: GLW-US | C52: CORNING INC | D52: US2193501051 | E52: XNYS | F52: 856564000 | G52: 49.24916 | H52: USD | I52: 4.2185057e+10 | J52: NA500 | K52: 2.3260225e+08 | L52: 0.9 | M52: 3.7966552e+10 | N52: 41.61 | O52: 0.8797009 | P52: 2.8218575e+10 | Q52: 10102015 | R52: 1010 | S52: 1.8088943 | T52: 3.1 | U52: B | V52: Green | W52: 0 | X52: 0 | Y52: Green | Z52: Green | AA52: Green | AB52: Green | AC52: Green | AD52: Green | AE52: Green | AF52: 0 | AG52: 0 | AH52: 0 | AJ52: 0 | AK52: F | AM52: F | AN52: F | AO52: F | AQ52: 0 | AR52: 0 | AS52: 0 | AT52: 0 | AU52: 2.047 | AV52: 3.5 | AW52: 263.91739 | AX52: 2.4 | AY52: C | AZ52: 1 | BA52: 0 | BB52: US | BC52: 0 | BD52: 0 | BE52: 0 | CI52: 2.7735 | CK52: No | CM52: 1.8088943 | CN52: 3.1 | CO52: 2.4544471 | CP52: -0.18 | CQ52: 2.2744471 | CR52: 33.625121 | CS52: 0 | CT52: 0.072476213 | CU52: 0
A53: 1318 | B53: TEMN-CH | C53: TEMENOS AG | D53: CH0012453913 | E53: XSWX | F53: 75171080 | G53: 79.58706 | H53: CHF | I53: 5.9826453e+09 | J53: EU500 | K53: 18044773 | L53: 0.8 | M53: 4.7861162e+09 | N53: 62.8 | O53: 1.0763104 | P53: 4.0647886e+09 | Q53: 10101015 | R53: 1010 | S53: 1.9728064 | U53: A- | V53: Green | W53: 0 | X53: 0 | Y53: Green | Z53: Green | AA53: Green | AB53: Green | AC53: Green | AD53: Green | AE53: Green | AF53: 0 | AG53: 0 | AH53: 0 | AJ53: 0 | AK53: F | AM53: F | AN53: F | AO53: F | AQ53: 0 | AR53: 0 | AS53: 0 | AT53: 0 | AU53: 2.785 | AV53: 3.222 | AW53: 9.1031755 | AX53: 1.5 | AY53: J | AZ53: 0 | BA53: 0 | BB53: CH | BC53: 0 | BD53: 0 | BE53: 0 | CI53: 3.0035 | CK53: No | CM53: 1.9728064 | CN53: 3.1 | CO53: 2.5364032 | CP53: -0.24 | CQ53: 2.2964032 | CR53: 33.625121 | CS53: 0 | CT53: 0.0058017145 | CU53: 0
A54: 1189 | B54: Z74-SG | C54: SINGAPORE TELECO | D54: SG1T75931496 | E54: XSES | F54: 16514635000 | G54: 2.347542 | H54: SGD | I54: 3.8768799e+10 | J54: AS500 | K54: 46392176 | L54: 0.5 | M54: 1.93844e+10 | N54: 3.5 | O54: 0.6687174 | P54: 1.9326342e+10 | Q54: 15102015 | R54: 1510 | S54: 1.7226152 | T54: 1.5 | U54: A | V54: Amber | W54: 0 | X54: 0 | Y54: Green | Z54: Green | AA54: Green | AB54: Green | AC54: Green | AD54: Green | AE54: Green | AF54: 0 | AG54: 0 | AH54: 0 | AJ54: 0 | AK54: F | AM54: F | AN54: F | AO54: F | AQ54: 0 | AR54: 0 | AS54: 0 | AT54: 0 | AU54: 2.211 | AV54: 2.535 | AW54: 81.270384 | AX54: 1.5 | AY54: J | AZ54: 0 | BA54: 0 | BB54: SG | BC54: 0 | BD54: 0 | BE54: 0 | CI54: 2.373 | CK54: No | CM54: 1.7226152 | CN54: 1.5 | CO54: 1.6113076 | CP54: -0.3 | CQ54: 1.3113076 | CR54: 57.373552 | CS54: 1 | CT54: 0.015763772 | CU54: 0
A55: 1310 | B55: TEF-ES | C55: TELEFONICA | D55: ES0178430E18 | E55: XMAD | F55: 5670161600 | G55: 4.174 | H55: EUR | I55: 2.3667255e+10 | J55: EU500 | K55: 53268601 | L55: 0.7 | M55: 1.6567078e+10 | N55: 4.121 | O55: 1 | P55: 1.6356715e+10 | Q55: 15102015 | R55: 1510 | S55: 1.7233601 | T55: 1.5 | U55: A | V55: Green | W55: 0 | X55: 0 | Y55: Green | Z55: Green | AA55: Green | AB55: Green | AC55: Green | AD55: Green | AE55: Green | AF55: 0 | AG55: 0 | AH55: 0 | AJ55: 0 | AK55: F | AM55: F | AN55: F | AO55: F | AQ55: 0 | AR55: 0 | AS55: 0 | AT55: 0 | AU55: 3.103 | AV55: 2.885 | AW55: 29.717956 | AX55: 1.5 | AY55: J | AZ55: 0 | BA55: 0 | BB55: ES | BC55: 0 | BD55: 0 | BE55: 0 | CI55: 2.994 | CK55: No | CM55: 1.7233601 | CN55: 1.5 | CO55: 1.61168 | CP55: -0.3 | CQ55: 1.31168 | CR55: 57.373552 | CS55: 1 | CT55: 0.017543031 | CU55: 0
A56: 1427 | B56: VOD-GB | C56: VODAFONE GROUP | D56: GB00BH4HKS39 | E56: XLON | F56: 25081295000 | G56: 0.8003203 | H56: GBX | I56: 2.007307e+10 | J56: EU500 | K56: 51438057 | L56: 0.8 | M56: 1.6058456e+10 | N56: 68.42 | O56: 0.01160026 | P56: 1.5925414e+10 | Q56: 15102015 | R56: 1510 | S56: 1.7280905 | T56: 1.5 | U56: A | V56: Green | W56: 0 | X56: 0 | Y56: Green | Z56: Green | AA56: Green | AB56: Green | AC56: Green | AD56: Green | AE56: Green | AF56: 0 | AG56: 0 | AH56: 0 | AJ56: 0 | AK56: F | AM56: F | AN56: F | AO56: F | AQ56: 0 | AR56: 0 | AS56: 0 | AT56: 0 | AU56: 2.765 | AV56: 3.141 | AW56: 71.848871 | AX56: 1.5 | AY56: J | AZ56: 0 | BA56: 0 | BB56: GB | BC56: 0 | BD56: 0 | BE56: 0 | CI56: 2.953 | CK56: No | CM56: 1.7280905 | CN56: 1.5 | CO56: 1.6140453 | CP56: -0.3 | CQ56: 1.3140453 | CR56: 57.373552 | CS56: 1 | CT56: 0.016952668 | CU56: 0
A57: 279 | B57: CSCO-US | C57: CISCO SYSTEMS INC | D57: US17275R1023 | E57: XNGS | F57: 3978292500 | G57: 61.1956 | H57: USD | I57: 243453996513 | J57: NA500 | K57: 1.1473082e+09 | L57: 1 | M57: 243453996513 | N57: 57.41 | O57: 0.8797009 | P57: 2.0091821e+11 | Q57: 15101010 | R57: 1510 | S57: 1.7478036 | T57: 1.5 | U57: A | V57: Green | W57: 0 | X57: 0 | Y57: Green | Z57: Green | AA57: Green | AB57: Green | AC57: Green | AD57: Green | AE57: Green | AF57: 0 | AG57: 0 | AH57: 0 | AJ57: 0 | AK57: F | AM57: F | AN57: F | AO57: F | AQ57: 0 | AR57: 0 | AS57: 0 | AT57: 0 | AU57: 2.497 | AV57: 3.614 | AW57: 109.92281 | AX57: 1.5 | AY57: C | AZ57: 1 | BA57: 0 | BB57: US | BC57: 0 | BD57: 0 | BE57: 0 | CI57: 3.0555 | CK57: No | CM57: 1.7478036 | CN57: 1.5 | CO57: 1.6239018 | CP57: -0.3 | CQ57: 1.3239018 | CR57: 57.373552 | CS57: 1 | CT57: 0.1 | CU57: 0
A58: 1316 | B58: TLS-AU | C58: TELSTRA GROUP LTD | D58: AU000000TLS2 | E58: XASX | F58: 11554428000 | G58: 2.530488 | H58: AUD | I58: 2.9238341e+10 | J58: AS500 | K58: 47128629 | L58: 1 | M58: 2.9238341e+10 | N58: 4.43 | O58: 0.55671538 | P58: 2.8496098e+10 | Q58: 15102015 | R58: 1510 | S58: 1.6552297 | T58: 1.5 | U58: A- | V58: Green | W58: 0 | X58: 0 | Y58: Green | Z58: Green | AA58: Green | AB58: Green | AC58: Green | AD58: Green | AE58: Green | AF58: 0 | AG58: 0 | AH58: 0 | AJ58: 0 | AK58: F | AM58: F | AN58: F | AO58: F | AQ58: 0 | AR58: 0 | AS58: 0 | AT58: 0 | AU58: 2.853 | AV58: 2.761 | AW58: 58.406855 | AX58: 1.7 | AY58: J | AZ58: 0 | BA58: 0 | BB58: AU | BC58: 0 | BD58: 0 | BE58: 0 | CI58: 2.807 | CK58: No | CM58: 1.6552297 | CN58: 1.5 | CO58: 1.5776148 | CP58: -0.24 | CQ58: 1.3376148 | CR58: 57.373552 | CS58: 1 | CT58: 0.016860635 | CU58: 0
A59: 177 | B59: BCE-CA | C59: BCE INC | D59: CA05534B7604 | E59: XTSE | F59: 912283100 | G59: 22.96334 | H59: CAD | I59: 2.0949067e+10 | J59: NA500 | K59: 1.0147172e+08 | L59: 1 | M59: 2.0949067e+10 | N59: 30.03 | O59: 0.63445738 | P59: 1.7381507e+10 | Q59: 15102015 | R59: 1510 | S59: 1.9418812 | T59: 1.5 | U59: B | V59: Green | W59: 0 | X59: 0 | Y59: Green | Z59: Green | AA59: Green | AB59: Green | AC59: Green | AD59: Green | AE59: Green | AF59: 0 | AG59: 0 | AH59: 0 | AJ59: 0 | AK59: F | AM59: F | AN59: F | AO59: F | AQ59: 0 | AR59: 0 | AS59: 0 | AT59: 0 | AU59: 2.637 | AV59: 3.166 | AW59: 33.693755 | AX59: 1.5 | AY59: J | AZ59: 0 | BA59: 0 | BB59: CA | BC59: 0 | BD59: 0 | BE59: 0 | CI59: 2.9015 | CK59: No | CM59: 1.9418812 | CN59: 1.5 | CO59: 1.7209406 | CP59: -0.18 | CQ59: 1.5409406 | CR59: 57.373552 | CS59: 1 | CT59: 0.032101859 | CU59: 0
A60: 1317 | B60: T-CA | C60: TELUS CORP | D60: CA87971M1032 | E60: XTSE | F60: 1514000000 | G60: 14.943 | H60: CAD | I60: 22623702000 | J60: NA500 | K60: 61757603 | L60: 1 | M60: 22623702000 | N60: 20.55 | O60: 0.63445738 | P60: 1.9739682e+10 | Q60: 15102015 | R60: 1510 | S60: 1.9784268 | T60: 1.5 | U60: B | V60: Green | W60: 0 | X60: 0 | Y60: Green | Z60: Green | AA60: Green | AB60: Green | AC60: Green | AD60: Green | AE60: Green | AF60: 0 | AG60: 0 | AH60: 0 | AJ60: 0 | AK60: F | AM60: F | AN60: F | AO60: F | AQ60: 0 | AR60: 0 | AS60: 0 | AT60: 0 | AU60: 2.554 | AV60: 3.2 | AW60: 113.55179 | AX60: 1.5 | AY60: J | AZ60: 0 | BA60: 0 | BB60: CA | BC60: 0 | BD60: 0 | BE60: 0 | CI60: 2.877 | CK60: No | CM60: 1.9784268 | CN60: 1.5 | CO60: 1.7392134 | CP60: -0.18 | CQ60: 1.5592134 | CR60: 57.373552 | CS60: 1 | CT60: 0.020412884 | CU60: 0
A61: 919 | B61: 9432-JP | C61: NIPPON TELEGRAPH | D61: JP3735400008 | E61: XTKS | F61: 90550310000 | G61: 0.9420268 | H61: JPY | I61: 8.5300819e+10 | J61: AS500 | K61: 1.4034842e+08 | L61: 0.6 | M61: 5.1180491e+10 | N61: 147.1 | O61: 0.00613973 | P61: 4.906854e+10 | Q61: 15102015 | R61: 1510 | S61: 1.9389411 | T61: 2.39 | U61: A | V61: Green | W61: 0 | X61: 0 | Y61: Green | Z61: Green | AA61: Green | AB61: Green | AC61: Green | AD61: Green | AE61: Green | AF61: 0 | AG61: 0 | AH61: 0 | AJ61: 0 | AK61: F | AM61: F | AN61: F | AO61: F | AQ61: 0 | AR61: 0 | AS61: 0 | AT61: 0 | AU61: 2.064 | AV61: 1.841 | AW61: 8.0179981 | AX61: 1.5 | AY61: J | AZ61: 0 | BA61: 0 | BB61: JP | BC61: 0 | BD61: 0 | BE61: 0 | CI61: 1.9525 | CK61: No | CM61: 1.9389411 | CN61: 2.39 | CO61: 2.1644706 | CP61: -0.3 | CQ61: 1.8644706 | CR61: 57.373552 | CS61: 0 | CT61: 0.046791723 | CU61: 0
A62: 973 | B62: ORA-FR | C62: ORANGE | D62: FR0000133308 | E62: XPAR | F62: 2660056599 | G62: 11.075 | H62: EUR | I62: 2.9460127e+10 | J62: EU500 | K62: 71522746 | L62: 0.65 | M62: 1.9149082e+10 | N62: 12.3 | O62: 1 | P62: 2.1267153e+10 | Q62: 15102015 | R62: 1510 | S62: 1.7104133 | T62: 2.39 | U62: B | V62: Green | W62: 0 | X62: 0 | Y62: Green | Z62: Green | AA62: Green | AB62: Green | AC62: Green | AD62: Green | AE62: Green | AF62: 0 | AG62: 0 | AH62: 0 | AJ62: 0 | AK62: F | AM62: F | AN62: F | AO62: F | AQ62: 0 | AR62: 0 | AS62: 0 | AT62: 0 | AU62: 2.716 | AV62: 2.747 | AW62: 98.199417 | AX62: 1.5 | AY62: J | AZ62: 0 | BA62: 0 | BB62: FR | BC62: 0 | BD62: 0 | BE62: 0 | CI62: 2.7315 | CK62: No | CM62: 1.7104133 | CN62: 2.39 | CO62: 2.0502067 | CP62: -0.18 | CQ62: 1.8702067 | CR62: 57.373552 | CS62: 0 | CT62: 0.023488336 | CU62: 0
A63: 1312 | B63: TEL-NO | C63: TELENOR | D63: NO0010063308 | E63: XOSL | F63: 1368349989 | G63: 12.14261 | H63: NOK | I63: 1.661534e+10 | J63: EU500 | K63: 14604406 | L63: 0.45 | M63: 7.4769031e+09 | N63: 145.3 | O63: 0.08324454 | P63: 7.4478527e+09 | Q63: 15102015 | R63: 1510 | S63: 1.6924228 | T63: 2.7 | U63: A- | V63: Green | W63: 0 | X63: 0 | Y63: Green | Z63: Green | AA63: Green | AB63: Green | AC63: Green | AD63: Green | AE63: Green | AF63: 0 | AG63: 0 | AH63: 0 | AJ63: 0 | AK63: F | AM63: F | AN63: F | AO63: F | AQ63: 0 | AR63: 0 | AS63: 0 | AT63: 0 | AU63: 2.337 | AV63: 2.934 | AW63: 117.06157 | AX63: 1.9 | AY63: J | AZ63: 0 | BA63: 0 | BB63: NO | BC63: 0 | BD63: 0 | BE63: 0 | CI63: 2.6355 | CK63: No | CM63: 1.6924228 | CN63: 2.7 | CO63: 2.1962114 | CP63: -0.24 | CQ63: 1.9562114 | CR63: 57.373552 | CS63: 0 | CT63: 0.0050927666 | CU63: 0
A64: 222 | B64: BT.A-GB | C64: BT GROUP PLC | D64: GB0030913577 | E64: XLON | F64: 9956837000 | G64: 1.820668 | H64: GBX | I64: 1.8128095e+10 | J64: EU500 | K64: 22456254 | L64: 0.4 | M64: 7.2512378e+09 | N64: 165.45 | O64: 0.01160026 | P64: 7.6439156e+09 | Q64: 15102015 | R64: 1510 | S64: 2.3119389 | T64: 2.39 | U64: A | V64: Green | W64: 0 | X64: 0 | Y64: Green | Z64: Green | AA64: Green | AB64: Green | AC64: Green | AD64: Green | AE64: Green | AF64: 0 | AG64: 0 | AH64: 0 | AJ64: 0 | AK64: F | AM64: F | AN64: F | AO64: F | AQ64: 0 | AR64: 0 | AS64: 0 | AT64: 0 | AU64: 2.762 | AV64: 2.562 | AW64: 72.169243 | AX64: 1.5 | AY64: J | AZ64: 0 | BA64: 0 | BB64: GB | BC64: 0 | BD64: 0 | BE64: 0 | CI64: 2.662 | CK64: No | CM64: 2.3119389 | CN64: 2.39 | CO64: 2.3509695 | CP64: -0.3 | CQ64: 2.0509695 | CR64: 57.373552 | CS64: 0 | CT64: 0.0074670495 | CU64: 0
A65: 740 | B65: KPN-NL | C65: KPN KON | D65: NL0000009082 | E65: XAMS | F65: 3888930422 | G65: 3.507 | H65: EUR | I65: 1.3638479e+10 | J65: EU500 | K65: 26549992 | L65: 1 | M65: 1.3638479e+10 | N65: 3.969 | O65: 1 | P65: 1.5435165e+10 | Q65: 15102015 | R65: 1510 | S65: 1.67081 | U65: A | V65: Green | W65: 0 | X65: 0 | Y65: Green | Z65: Green | AA65: Green | AB65: Green | AC65: Green | AD65: Green | AE65: Green | AF65: 0 | AG65: 0 | AH65: 0 | AJ65: 0 | AK65: F | AM65: F | AN65: F | AO65: F | AQ65: 0 | AR65: 0 | AS65: 0 | AT65: 0 | AU65: 2.401 | AV65: 3.075 | AW65: 38.06481 | AX65: 1.5 | AY65: J | AZ65: 0 | BA65: 0 | BB65: NL | BC65: 0 | BD65: 0 | BE65: 0 | CI65: 2.738 | CK65: No | CM65: 1.67081 | CN65: 3.1 | CO65: 2.385405 | CP65: -0.3 | CQ65: 2.085405 | CR65: 57.373552 | CS65: 0 | CT65: 0.0094394183 | CU65: 0
A66: 947 | B66: NSIS.B-DK | C66: NOVONESIS | D66: DK0060336014 | E66: XCSE | F66: 414555050 | G66: 53.64455 | H66: DKK | I66: 2.2238619e+10 | J66: EU500 | K66: 28551145 | L66: 0.85 | M66: 1.8902826e+10 | N66: 403.8 | O66: 0.13393335 | P66: 1.9057072e+10 | Q66: 20103010 | R66: 2010 | S66: 1.704606 | T66: 1.5 | U66: A | V66: Green | W66: 0 | X66: 0 | Y66: Green | Z66: Green | AA66: Green | AB66: Green | AC66: Green | AD66: Green | AE66: Green | AF66: 0 | AG66: 0 | AH66: 0 | AJ66: 0 | AK66: F | AM66: F | AN66: F | AO66: F | AQ66: 0 | AR66: 0 | AS66: 0 | AT66: 0 | AU66: 2.575 | AV66: 2.876 | AW66: 55.121386 | AX66: 1.5 | AY66: C | AZ66: 1 | BA66: 0 | BB66: DK | BC66: 0 | BD66: 0 | BE66: 0 | CI66: 2.7255 | CK66: No | CM66: 1.704606 | CN66: 1.5 | CO66: 1.602303 | CP66: -0.3 | CQ66: 1.302303 | CR66: 50.951644 | CS66: 1 | CT66: 0.010385741 | CU66: 0
A67: 550 | B67: GSK-GB | C67: GSK PLC | D67: GB00BN7SWP63 | E67: XLON | F67: 4145945300 | G67: 17.2758 | H67: GBX | I67: 7.1624522e+10 | J67: EU500 | K67: 94231735 | L67: 1 | M67: 7.1624522e+10 | N67: 1322.5 | O67: 0.01160026 | P67: 6.3604372e+10 | Q67: 20103015 | R67: 2010 | S67: 1.7306923 | T67: 1.5 | U67: A | V67: Green | W67: 0 | X67: 0 | Y67: Green | Z67: Green | AA67: Green | AB67: Green | AC67: Green | AD67: Green | AE67: Green | AF67: 0 | AG67: 0 | AH67: 0 | AJ67: 0 | AK67: F | AM67: F | AN67: F | AO67: F | AQ67: 0 | AR67: 0 | AS67: 0 | AT67: 0 | AU67: 3.198 | AV67: 2.788 | AW67: 108.37267 | AX67: 1.5 | AY67: C | AZ67: 1 | BA67: 0 | BB67: GB | BC67: 0 | BD67: 0 | BE67: 0 | CI67: 2.993 | CK67: No | CM67: 1.7306923 | CN67: 1.5 | CO67: 1.6153462 | CP67: -0.3 | CQ67: 1.3153462 | CR67: 50.951644 | CS67: 1 | CT67: 0.034345231 | CU67: 0
A68: 945 | B68: NOVN-CH | C68: NOVARTIS | D68: CH0012005267 | E68: XSWX | F68: 2189930400 | G68: 104.3617 | H68: CHF | I68: 2.2854486e+11 | J68: EU500 | K68: 3.4805244e+08 | L68: 0.95 | M68: 2.1711762e+11 | N68: 88.74 | O68: 1.0763104 | P68: 1.9870596e+11 | Q68: 20103015 | R68: 2010 | S68: 1.7351436 | T68: 1.5 | U68: A | V68: Green | W68: 0 | X68: 0 | Y68: Green | Z68: Green | AA68: Green | AB68: Green | AC68: Green | AD68: Green | AE68: Green | AF68: 0 | AG68: 0 | AH68: 0 | AJ68: 0 | AK68: F | AM68: F | AN68: F | AO68: F | AQ68: 0 | AR68: 0 | AS68: 0 | AT68: 0 | AU68: 2.978 | AV68: 2.973 | AW68: 23.29442 | AX68: 1.5 | AY68: C | AZ68: 1 | BA68: 0 | BB68: CH | BC68: 0 | BD68: 0 | BE68: 0 | CI68: 2.9755 | CK68: No | CM68: 1.7351436 | CN68: 1.5 | CO68: 1.6175718 | CP68: -0.3 | CQ68: 1.3175718 | CR68: 50.951644 | CS68: 1 | CT68: 0.1 | CU68: 0
A69: 125 | B69: AZN-GB | C69: ASTRAZENECA | D69: GB0009895292 | E69: XLON | F69: 1550581200 | G69: 141.5431 | H69: GBX | I69: 2.1947407e+11 | J69: EU500 | K69: 1.7576966e+08 | L69: 1 | M69: 2.1947407e+11 | N69: 10320 | O69: 0.01160026 | P69: 1.8562734e+11 | Q69: 20103015 | R69: 2010 | S69: 1.7400925 | T69: 1.5 | U69: A | V69: Green | W69: 0 | X69: 0 | Y69: Green | Z69: Green | AA69: Green | AB69: Green | AC69: Green | AD69: Green | AE69: Green | AF69: 0 | AG69: 0 | AH69: 0 | AJ69: 0 | AK69: F | AM69: F | AN69: F | AO69: F | AQ69: 0 | AR69: 0 | AS69: 0 | AT69: 0 | AU69: 2.777 | AV69: 2.399 | AW69: 31.970898 | AX69: 1.5 | AY69: C | AZ69: 1 | BA69: 0 | BB69: GB | BC69: 0 | BD69: 0 | BE69: 0 | CI69: 2.588 | CK69: No | CM69: 1.7400925 | CN69: 1.5 | CO69: 1.6200463 | CP69: -0.3 | CQ69: 1.3200463 | CR69: 50.951644 | CS69: 1 | CT69: 0.070462665 | CU69: 0
A70: 1119 | B70: SAN-FR | C70: SANOFI | D70: FR0000120578 | E70: XPAR | F70: 1263122721 | G70: 104.12 | H70: EUR | I70: 1.3151634e+11 | J70: EU500 | K70: 1.5479623e+08 | L70: 0.95 | M70: 1.2494052e+11 | N70: 91.88 | O70: 1 | P70: 1.1025293e+11 | Q70: 20103015 | R70: 2010 | S70: 1.7231997 | T70: 1.5 | U70: A- | V70: Green | W70: 0 | X70: 0 | Y70: Green | Z70: Green | AA70: Green | AB70: Green | AC70: Green | AD70: Green | AE70: Green | AF70: 0 | AG70: 0 | AH70: 0 | AJ70: 0 | AK70: F | AM70: F | AN70: F | AO70: F | AQ70: 0 | AR70: 0 | AS70: 0 | AT70: 0 | AU70: 2.98 | AV70: 2.774 | AW70: 34.157891 | AX70: 1.5 | AY70: C | AZ70: 1 | BA70: 0 | BB70: FR | BC70: 0 | BD70: 0 | BE70: 0 | CI70: 2.877 | CK70: No | CM70: 1.7231997 | CN70: 1.5 | CO70: 1.6115998 | CP70: -0.24 | CQ70: 1.3715998 | CR70: 50.951644 | CS70: 1 | CT70: 0.05697061 | CU70: 0
A71: 969 | B71: 4528-JP | C71: ONO PHARMA | D71: JP3197600004 | E71: XTKS | F71: 498692800 | G71: 9.963868 | H71: JPY | I71: 4.9689092e+09 | J71: AS500 | K71: 23621771 | L71: 0.95 | M71: 4.7204638e+09 | N71: 1665 | O71: 0.00613973 | P71: 4.8430641e+09 | Q71: 20103015 | R71: 2010 | S71: 1.8594983 | T71: 1.5 | U71: A | V71: Green | W71: 0 | X71: 0 | Y71: Green | Z71: Green | AA71: Green | AB71: Green | AC71: Green | AD71: Green | AE71: Green | AF71: 0 | AG71: 0 | AH71: 0 | AJ71: 0 | AK71: F | AM71: F | AN71: F | AO71: F | AQ71: 0 | AR71: 0 | AS71: 0 | AT71: 0 | AU71: 2.448 | AV71: 2.524 | AW71: 5.9555095 | AX71: 1.5 | AY71: C | AZ71: 1 | BA71: 0 | BB71: JP | BC71: 0 | BD71: 0 | BE71: 0 | CI71: 2.486 | CK71: No | CM71: 1.8594983 | CN71: 1.5 | CO71: 1.6797491 | CP71: -0.3 | CQ71: 1.3797491 | CR71: 50.951644 | CS71: 1 | CT71: 0.0075491575 | CU71: 0
A72: 203 | B72: BSX-US | C72: BOSTON SCIENTIFIC | D72: US1011371077 | E72: XNYS | F72: 1475778100 | G72: 99.94261 | H72: USD | I72: 1.4749312e+11 | J72: NA500 | K72: 5.0618698e+08 | L72: 1 | M72: 1.4749312e+11 | N72: 94.27 | O72: 0.8797009 | P72: 1.223854e+11 | Q72: 20102010 | R72: 2010 | S72: 1.7381151 | T72: 1.5 | U72: B | V72: Green | W72: 0 | X72: 0 | Y72: Green | Z72: Green | AA72: Green | AB72: Green | AC72: Green | AD72: Green | AE72: Green | AF72: 0 | AG72: 0 | AH72: 0 | AJ72: 0 | AK72: F | AM72: F | AN72: F | AO72: F | AQ72: 0 | AR72: 0 | AS72: 0 | AT72: 0 | AU72: 2.771 | AV72: 3.399 | AW72: 16.44373 | AX72: 1.5 | AY72: C | AZ72: 1 | BA72: 0 | BB72: US | BC72: 0 | BD72: 0 | BE72: 0 | CI72: 3.085 | CK72: No | CM72: 1.7381151 | CN72: 1.5 | CO72: 1.6190576 | CP72: -0.18 | CQ72: 1.4390576 | CR72: 50.951644 | CS72: 1 | CT72: 0.1 | CU72: 0
A73: 81 | B73: AMGN-US | C73: AMGEN INC | D73: US0311621009 | E73: XNGS | F73: 537204960 | G73: 289.8231 | H73: USD | I73: 1.5569441e+11 | J73: NA500 | K73: 9.8449836e+08 | L73: 1 | M73: 1.5569441e+11 | N73: 293.92 | O73: 0.8797009 | P73: 1.3890062e+11 | Q73: 20103015 | R73: 2010 | S73: 1.9753941 | T73: 1.5 | U73: A- | V73: Amber | W73: 0 | X73: 0 | Y73: Green | Z73: Green | AA73: Green | AB73: Green | AC73: Green | AD73: Green | AE73: Green | AF73: 0 | AG73: 0 | AH73: 0 | AJ73: 0 | AK73: F | AM73: F | AN73: F | AO73: F | AQ73: 0 | AR73: 0 | AS73: 0 | AT73: 0 | AU73: 2.67 | AV73: 2.789 | AW73: 7.764408 | AX73: 1.5 | AY73: M | AZ73: 0 | BA73: 0 | BB73: US | BC73: 0 | BD73: 0 | BE73: 0 | CI73: 2.7295 | CK73: No | CM73: 1.9753941 | CN73: 1.5 | CO73: 1.737697 | CP73: -0.24 | CQ73: 1.497697 | CR73: 50.951644 | CS73: 1 | CT73: 0.1 | CU73: 0
A74: 348 | B74: 4568-JP | C74: DAIICHI SANKYO | D74: JP3475350009 | E74: XTKS | F74: 1908322100 | G74: 21.92946 | H74: JPY | I74: 4.1848473e+10 | J74: AS500 | K74: 1.3486816e+08 | L74: 1 | M74: 4.1848473e+10 | N74: 3174 | O74: 0.00613973 | P74: 3.7188433e+10 | Q74: 20103015 | R74: 2010 | S74: 1.9767065 | T74: 1.5 | U74: A- | V74: Green | W74: 0 | X74: 0 | Y74: Green | Z74: Green | AA74: Green | AB74: Green | AC74: Green | AD74: Green | AE74: Green | AF74: 0 | AG74: 0 | AH74: 0 | AJ74: 0 | AK74: F | AM74: F | AN74: F | AO74: F | AQ74: 0 | AR74: 0 | AS74: 0 | AT74: 0 | AU74: 2.548 | AV74: 2.52 | AW74: 69.488295 | AX74: 1.5 | AY74: C | AZ74: 1 | BA74: 0 | BB74: JP | BC74: 0 | BD74: 0 | BE74: 0 | CI74: 2.534 | CK74: No | CM74: 1.9767065 | CN74: 1.5 | CO74: 1.7383532 | CP74: -0.24 | CQ74: 1.4983532 | CR74: 50.951644 | CS74: 1 | CT74: 0.044012817 | CU74: 0
A75: 686 | B75: JNJ-US | C75: JOHNSON & JOHNSON | D75: US4781601046 | E75: XNYS | F75: 2407616700 | G75: 155.2367 | H75: USD | I75: 3.7375047e+11 | J75: NA500 | K75: 1.2491959e+09 | L75: 1 | M75: 3.7375047e+11 | N75: 154.36 | O75: 0.8797009 | P75: 3.2693179e+11 | Q75: 20103015 | R75: 2010 | S75: 1.9817262 | T75: 1.5 | U75: A- | V75: Amber | W75: 0 | X75: 0 | Y75: Green | Z75: Green | AA75: Green | AB75: Green | AC75: Green | AD75: Green | AE75: Green | AF75: 0 | AG75: 0 | AH75: 0 | AJ75: 0 | AK75: F | AM75: F | AN75: F | AO75: F | AQ75: 0 | AR75: 0 | AS75: 0 | AT75: 0 | AU75: 2.836 | AV75: 3.508 | AW75: 40.004259 | AX75: 1.5 | AY75: C | AZ75: 1 | BA75: 0 | BB75: US | BC75: 0 | BD75: 0 | BE75: 0 | CI75: 3.172 | CK75: No | CM75: 1.9817262 | CN75: 1.5 | CO75: 1.7408631 | CP75: -0.24 | CQ75: 1.5008631 | CR75: 50.951644 | CS75: 1 | CT75: 0.1 | CU75: 0
A76: 1387 | B76: UCB-BE | C76: UCB | D76: BE0003739530 | E76: XBRU | F76: 194505658 | G76: 181.8 | H76: EUR | I76: 3.5361129e+10 | J76: EU500 | K76: 36834331 | L76: 0.65 | M76: 2.2984734e+10 | N76: 139.1 | O76: 1 | P76: 1.7586229e+10 | Q76: 20103015 | R76: 2010 | S76: 1.7415642 | T76: 1.77 | U76: A- | V76: Green | W76: 0 | X76: 0 | Y76: Green | Z76: Green | AA76: Green | AB76: Green | AC76: Green | AD76: Green | AE76: Green | AF76: 0 | AG76: 0 | AH76: 0 | AJ76: 0 | AK76: F | AM76: F | AN76: F | AO76: F | AQ76: 0 | AR76: 0 | AS76: 0 | AT76: 0 | AU76: 2.661 | AV76: 2.861 | AW76: 48.111746 | AX76: 1.5 | AY76: M | AZ76: 0 | BA76: 0 | BB76: BE | BC76: 0 | BD76: 0 | BE76: 0 | CI76: 2.761 | CK76: No | CM76: 1.7415642 | CN76: 1.77 | CO76: 1.7557821 | CP76: -0.24 | CQ76: 1.5157821 | CR76: 50.951644 | CS76: 1 | CT76: 0.012730197 | CU76: 0
A77: 419 | B77: 4523-JP | C77: EISAI CO LTD | D77: JP3160400002 | E77: XTKS | F77: 291649140 | G77: 27.36546 | H77: JPY | I77: 7.9811129e+09 | J77: AS500 | K77: 39953319 | L77: 1 | M77: 7.9811129e+09 | N77: 3696 | O77: 0.00613973 | P77: 6.6182312e+09 | Q77: 20103015 | R77: 2010 | S77: 1.8628057 | T77: 1.77 | U77: A | V77: Green | W77: 0 | X77: 0 | Y77: Green | Z77: Green | AA77: Green | AB77: Green | AC77: Green | AD77: Green | AE77: Green | AF77: 0 | AG77: 0 | AH77: 0 | AJ77: 0 | AK77: F | AM77: F | AN77: F | AO77: F | AQ77: 0 | AR77: 0 | AS77: 0 | AT77: 0 | AU77: 2.677 | AV77: 2.747 | AW77: 42.997321 | AX77: 1.5 | AY77: C | AZ77: 1 | BA77: 0 | BB77: JP | BC77: 0 | BD77: 0 | BE77: 0 | CI77: 2.712 | CK77: No | CM77: 1.8628057 | CN77: 1.77 | CO77: 1.8164029 | CP77: -0.3 | CQ77: 1.5164029 | CR77: 50.951644 | CS77: 1 | CT77: 0.012618192 | CU77: 0
... A95: 1293 | B95: 4502-JP | C95: TAKEDA PHARMACEU | D95: JP3463000004 | E95: XTKS | F95: 1590949600 | G95: 26.97535 | H95: JPY | I95: 4.2916422e+10 | J95: AS500 | K95: 92320968 | L95: 1 | M95: 4.2916422e+10 | N95: 4065 | O95: 0.00613973 | P95: 3.9706924e+10 | Q95: 20103015 | R95: 2010 | S95: 1.7301341 | T95: 3.01 | U95: A | V95: Green | W95: 0 | X95: 0 | Y95: Green | Z95: Green | AA95: Green | AB95: Green | AC95: Green | AD95: Green | AE95: Green | AF95: 0 | AG95: 0 | AH95: 0 | AJ95: 0 | AK95: F | AM95: F | AN95: F | AO95: F | AQ95: 0 | AR95: 0 | AS95: 0 | AT95: 0 | AU95: 2.799 | AV95: 2.407 | AW95: 52.749168 | AX95: 1.5 | AY95: C | AZ95: 1 | BA95: 0 | BB95: JP | BC95: 0 | BD95: 0 | BE95: 0 | CI95: 2.603 | CK95: No | CM95: 1.7301341 | CN95: 3.01 | CO95: 2.3700671 | CP95: -0.3 | CQ95: 2.0700671 | CR95: 50.951644 | CS95: 0 | CT95: 0.031489234 | CU95: 0
A96: 964 | B96: 7733-JP | C96: OLYMPUS CORP | D96: JP3201200007 | E96: XTKS | F96: 1139116300 | G96: 13.10396 | H96: JPY | I96: 1.4926934e+10 | J96: AS500 | K96: 50059871 | L96: 1 | M96: 1.4926934e+10 | N96: 1783 | O96: 0.00613973 | P96: 1.2470064e+10 | Q96: 20102010 | R96: 2010 | S96: 1.7347256 | U96: A | V96: Green | W96: 0 | X96: 0 | Y96: Green | Z96: Green | AA96: Green | AB96: Green | AC96: Green | AD96: Green | AE96: Green | AF96: 0 | AG96: 0 | AH96: 0 | AJ96: 0 | AK96: F | AM96: F | AN96: F | AO96: F | AQ96: 0 | AR96: 0 | AS96: 0 | AT96: 0 | AU96: 2.634 | AV96: 3.029 | AW96: 28.19889 | AX96: 1.5 | AY96: C | AZ96: 1 | BA96: 0 | BB96: JP | BC96: 0 | BD96: 0 | BE96: 0 | CI96: 2.8315 | CK96: No | CM96: 1.7347256 | CN96: 3.1 | CO96: 2.4173628 | CP96: -0.3 | CQ96: 2.1173628 | CR96: 50.951644 | CS96: 0 | CT96: 0.016209145 | CU96: 0
A97: 978 | B97: ORNBV-FI | C97: ORION OYJ CLASS B | D97: FI0009014377 | E97: XHEL | F97: 108382010 | G97: 52.44 | H97: EUR | I97: 5.6835526e+09 | J97: EU500 | K97: 9590018.6 | L97: 1 | M97: 5.6835526e+09 | N97: 49.2 | O97: 1 | P97: 5332394892 | Q97: 20103015 | R97: 2010 | S97: 1.970758 | T97: 2.7 | U97: B | V97: Green | W97: 0 | X97: 0 | Y97: Green | Z97: Green | AA97: Green | AB97: Green | AC97: Green | AD97: Green | AE97: Green | AF97: 0 | AG97: 0 | AH97: 0 | AJ97: 0 | AK97: F | AM97: F | AN97: F | AO97: F | AQ97: 0 | AR97: 0 | AS97: 0 | AT97: 0 | AU97: 2.469 | AV97: 2.826 | AW97: 75.524879 | AX97: 1.5 | AY97: C | AZ97: 1 | BA97: 0 | BB97: FI | BC97: 0 | BD97: 0 | BE97: 0 | CI97: 2.6475 | CK97: No | CM97: 1.970758 | CN97: 2.7 | CO97: 2.335379 | CP97: -0.18 | CQ97: 2.155379 | CR97: 50.951644 | CS97: 0 | CT97: 0.0033863744 | CU97: 0
A98: 422 | B98: ELV-US | C98: ELEVANCE HEALTH | D98: US0367521038 | E98: XNYS | F98: 227351870 | G98: 368.3405 | H98: USD | I98: 8.3742901e+10 | J98: NA500 | K98: 6.4458268e+08 | L98: 1 | M98: 8.3742901e+10 | N98: 441.17 | O98: 0.8797009 | P98: 8.8234726e+10 | Q98: 20101020 | R98: 2010 | S98: 1.9949848 | T98: 2.7 | U98: B | V98: Green | W98: 0 | X98: 0 | Y98: Green | Z98: Green | AA98: Green | AB98: Green | AC98: Green | AD98: Green | AE98: Green | AF98: 0 | AG98: 0 | AH98: 0 | AJ98: 0 | AK98: F | AM98: F | AN98: F | AO98: F | AQ98: 0 | AR98: 0 | AS98: 0 | AT98: 0 | AU98: 2.547 | AV98: 3.242 | AW98: 56.788846 | AX98: 1.5 | AY98: K | AZ98: 0 | BA98: 0 | BB98: US | BC98: 0 | BD98: 0 | BE98: 0 | CI98: 2.8945 | CK98: No | CM98: 1.9949848 | CN98: 2.7 | CO98: 2.3474924 | CP98: -0.18 | CQ98: 2.1674924 | CR98: 50.951644 | CS98: 0 | CT98: 0.1 | CU98: 0
A99: 1330 | B99: TMO-US | C99: THERMO FISHER SCIENT | D99: US8835561023 | E99: XNYS | F99: 377261170 | G99: 509.3735 | H99: USD | I99: 1.9216684e+11 | J99: NA500 | K99: 1.0675202e+09 | L99: 1 | M99: 1.9216684e+11 | N99: 449.33 | O99: 0.8797009 | P99: 1.4912229e+11 | Q99: 20102010 | R99: 2010 | S99: 1.7384965 | T99: 3.1 | U99: A- | V99: Green | W99: 0 | X99: 0 | Y99: Green | Z99: Green | AA99: Green | AB99: Green | AC99: Green | AD99: Green | AE99: Green | AF99: 0 | AG99: 0 | AH99: 0 | AJ99: 0 | AK99: F | AM99: F | AN99: F | AO99: F | AQ99: 0 | AR99: 0 | AS99: 0 | AT99: 0 | AU99: 2.583 | AV99: 3.555 | AW99: 54.125693 | AX99: 1.5 | AY99: C | AZ99: 1 | BA99: 0 | BB99: US | BC99: 0 | BD99: 0 | BE99: 0 | CI99: 3.069 | CK99: No | CM99: 1.7384965 | CN99: 3.1 | CO99: 2.4192482 | CP99: -0.24 | CQ99: 2.1792482 | CR99: 50.951644 | CS99: 0 | CT99: 0.1 | CU99: 0
A100: 303 | B100: CBK-DE | C100: COMMERZBANK AG | D100: DE000CBK1001 | E100: XETR | F100: 1184669100 | G100: 19.525 | H100: EUR | I100: 2.3130664e+10 | J100: EU500 | K100: 92864872 | L100: 0.8 | M100: 18504531342 | N100: 21.95 | O100: 1 | P100: 20802789396 | Q100: 30101010 | R100: 3010 | S100: 1.9118214 | T100: 1.5 | U100: B | V100: Green | W100: 0 | X100: 0 | Y100: Green | Z100: Green | AA100: Green | AB100: Green | AC100: Green | AD100: Green | AE100: Green | AF100: 0 | AG100: 0 | AH100: 0 | AJ100: 0 | AK100: F | AM100: F | AN100: F | AO100: F | AQ100: 0 | AR100: 0 | AS100: 0 | AT100: 0 | AU100: 2.389 | AV100: 2.794 | AW100: 270.4133 | AX100: 1.5 | AY100: K | AZ100: 0 | BA100: 0 | BB100: DE | BC100: 0 | BD100: 0 | BE100: 0 | CI100: 2.5915 | CK100: No | CM100: 1.9118214 | CN100: 1.5 | CO100: 1.7059107 | CP100: -0.18 | CQ100: 1.5259107 | CR100: 276.86158 | CS100: 1 | CT100: 0.029846616 | CU100: 0
A101: 44 | B101: A5G-IE | C101: AIB GROUP PLC | D101: IE00BF0L3536 | E101: XMSM | F101: 2328438575 | G101: 6.34 | H101: EUR | I101: 1.4762301e+10 | J101: EU500 | K101: 28502146 | L101: 0.9 | M101: 1.3286071e+10 | N101: 5.64 | O101: 1 | P101: 1.1819154e+10 | Q101: 30101010 | R101: 3010 | S101: 1.9993471 | T101: 1.5 | U101: B | V101: Green | W101: 0 | X101: 0 | Y101: Green | Z101: Green | AA101: Green | AB101: Green | AC101: Green | AD101: Green | AE101: Green | AF101: 0 | AG101: 0 | AH101: 0 | AJ101: 0 | AK101: F | AM101: F | AN101: F | AO101: F | AQ101: 0 | AR101: 0 | AS101: 0 | AT101: 0 | AU101: 2.486 | AV101: 3.169 | AW101: 92.827047 | AX101: 1.5 | AY101: K | AZ101: 0 | BA101: 0 | BB101: IE | BC101: 0 | BD101: 0 | BE101: 0 | CI101: 2.8275 | CK101: No | CM101: 1.9993471 | CN101: 1.5 | CO101: 1.7496735 | CP101: -0.18 | CQ101: 1.5696735 | CR101: 276.86158 | CS101: 1 | CT101: 0.0096796505 | CU101: 0
A102: 646 | B102: ISP-IT | C102: INTESA SANPAOLO | D102: IT0000072618 | E102: MTAA | F102: 17803670501 | G102: 4.5205 | H102: EUR | I102: 8.0481492e+10 | J102: EU500 | K102: 2.6021288e+08 | L102: 0.9 | M102: 7.2433343e+10 | N102: 4.2335 | O102: 1 | P102: 6.7834655e+10 | Q102: 30101010 | R102: 3010 | S102: 1.9984639 | T102: 2.39 | U102: A | V102: Green | W102: 0 | X102: 0 | Y102: Green | Z102: Green | AA102: Green | AB102: Green | AC102: Green | AD102: Green | AE102: Green | AF102: 0 | AG102: 0 | AH102: 0 | AJ102: 0 | AK102: F | AM102: F | AN102: F | AO102: F | AQ102: 0 | AR102: 0 | AS102: 0 | AT102: 0 | AU102: 2.444 | AV102: 3.077 | AW102: 278.04139 | AX102: 1.5 | AY102: K | AZ102: 0 | BA102: 0 | BB102: IT | BC102: 0 | BD102: 0 | BE102: 0 | CI102: 2.7605 | CK102: No | CM102: 1.9984639 | CN102: 2.39 | CO102: 2.1942319 | CP102: -0.3 | CQ102: 1.8942319 | CR102: 276.86158 | CS102: 0 | CT102: 0.084543667 | CU102: 0
A103: 700 | B103: KBC-BE | C103: KBC | D103: BE0003565737 | E103: XBRU | F103: 417544151 | G103: 81.3 | H103: EUR | I103: 3.3946339e+10 | J103: EU500 | K103: 34500356 | L103: 0.55 | M103: 1.8670487e+10 | N103: 78.6 | O103: 1 | P103: 1.8050434e+10 | Q103: 30101010 | R103: 3010 | S103: 2.8933333 | T103: 1.5 | U103: A | V103: Green | W103: 0 | X103: 0 | Y103: Green | Z103: Green | AA103: Green | AB103: Green | AC103: Green | AD103: Green | AE103: Green | AF103: 0 | AG103: 0 | AH103: 0 | AJ103: 0 | AK103: F | AM103: F | AN103: F | AO103: F | AQ103: 0 | AR103: 0 | AS103: 0 | AT103: 0 | AU103: 2.378 | AV103: 2.879 | AW103: 1695.9453 | AX103: 1.5 | AY103: K | AZ103: 0 | BA103: 0 | BB103: BE | BC103: 0 | BD103: 0 | BE103: 0 | CI103: 2.6285 | CK103: No | CM103: 2.8933333 | CN103: 1.5 | CO103: 2.1966667 | CP103: -0.3 | CQ103: 1.8966667 | CR103: 276.86158 | CS103: 0 | CT103: 0.012074347 | CU103: 0
A104: 1205 | B104: GLE-FR | C104: SOCIETE GENERALE | D104: FR0000130809 | E104: XPAR | F104: 800316777 | G104: 37.835 | H104: EUR | I104: 3.0279985e+10 | J104: EU500 | K104: 97163082 | L104: 0.9 | M104: 2.7251987e+10 | N104: 38.38 | O104: 1 | P104: 2.7644542e+10 | Q104: 30101010 | R104: 3010 | S104: 2.8933333 | T104: 1.5 | U104: A- | V104: Green | W104: 0 | X104: 0 | Y104: Green | Z104: Green | AA104: Green | AB104: Green | AC104: Green | AD104: Green | AE104: Green | AF104: 0 | AG104: 0 | AH104: 0 | AJ104: 0 | AK104: F | AM104: F | AN104: F | AO104: F | AQ104: 0 | AR104: 0 | AS104: 0 | AT104: 0 | AU104: 2.452 | AV104: 3.187 | AW104: 353.81948 | AX104: 1.5 | AY104: K | AZ104: 0 | BA104: 0 | BB104: FR | BC104: 0 | BD104: 0 | BE104: 0 | CI104: 2.8195 | CK104: No | CM104: 2.8933333 | CN104: 1.5 | CO104: 2.1966667 | CP104: -0.24 | CQ104: 1.9566667 | CR104: 276.86158 | CS104: 0 | CT104: 0.031789627 | CU104: 0
A105: 157 | B105: SAN-ES | C105: BANCO SANTANDER CENT | D105: ES0113900J37 | E105: XMAD | F105: 15152492000 | G105: 5.884 | H105: EUR | I105: 89157262928 | J105: EU500 | K105: 1.4922939e+08 | L105: 1 | M105: 89157262928 | N105: 5.798 | O105: 1 | P105: 87854148616 | Q105: 30101010 | R105: 3010 | S105: 3.1466667 | T105: 1.5 | U105: A | V105: Green | W105: 0 | X105: 0 | Y105: Green | Z105: Green | AA105: Green | AB105: Green | AC105: Green | AD105: Green | AE105: Green | AF105: 0 | AG105: 0 | AH105: 0 | AJ105: 0 | AK105: F | AM105: F | AN105: F | AO105: F | AQ105: 0 | AR105: 0 | AS105: 0 | AT105: 0 | AU105: 2.398 | AV105: 3.146 | AW105: 67.170916 | AX105: 1.5 | AY105: K | AZ105: 0 | BA105: 0 | BB105: ES | BC105: 0 | BD105: 0 | BE105: 0 | CI105: 2.772 | CK105: No | CM105: 3.1466667 | CN105: 1.5 | CO105: 2.3233333 | CP105: -0.3 | CQ105: 2.0233333 | CR105: 276.86158 | CS105: 0 | CT105: 0.053160951 | CU105: 0
A106: 330 | B106: ACA-FR | C106: CREDIT AGRICOLE | D106: FR0000045072 | E106: XPAR | F106: 3025902350 | G106: 15.64 | H106: EUR | I106: 47325112754 | J106: EU500 | K106: 92791252 | L106: 0.3 | M106: 1.4197534e+10 | N106: 15.755 | O106: 1 | P106: 1.4301927e+10 | Q106: 30101010 | R106: 3010 | S106: 3.2733333 | T106: 1.5 | U106: A- | V106: Green | W106: 0 | X106: 0 | Y106: Green | Z106: Green | AA106: Green | AB106: Green | AC106: Green | AD106: Green | AE106: Green | AF106: 0 | AG106: 0 | AH106: 0 | AJ106: 0 | AK106: F | AM106: F | AN106: F | AO106: F | AQ106: 0 | AR106: 0 | AS106: 0 | AT106: 0 | AU106: 2.184 | AV106: 2.841 | AW106: 175.90883 | AX106: 1.5 | AY106: K | AZ106: 0 | BA106: 0 | BB106: FR | BC106: 0 | BD106: 0 | BE106: 0 | CI106: 2.5125 | CK106: No | CM106: 3.2733333 | CN106: 1.5 | CO106: 2.3866667 | CP106: -0.24 | CQ106: 2.1466667 | CR106: 276.86158 | CS106: 0 | CT106: 0.029203545 | CU106: 0
A107: 886 | B107: NAB-AU | C107: NAT AUSTRALIA BANK | D107: AU000000NAB4 | E107: XASX | F107: 3070194000 | G107: 21.39024 | H107: AUD | I107: 6.5672187e+10 | J107: AS500 | K107: 84911053 | L107: 1 | M107: 6.5672187e+10 | N107: 33.55 | O107: 0.55671538 | P107: 5.7344473e+10 | Q107: 30101010 | R107: 3010 | S107: 3.4 | T107: 1.5 | U107: A | V107: Green | W107: 0 | X107: 0 | Y107: Green | Z107: Green | AA107: Green | AB107: Green | AC107: Green | AD107: Green | AE107: Green | AF107: 0 | AG107: 0 | AH107: 0 | AJ107: 0 | AK107: F | AM107: F | AN107: F | AO107: F | AQ107: 0 | AR107: 0 | AS107: 0 | AT107: 0 | AU107: 2.328 | AV107: 2.652 | AW107: 204.57932 | AX107: 1.5 | AY107: K | AZ107: 0 | BA107: 0 | BB107: AU | BC107: 0 | BD107: 0 | BE107: 0 | CI107: 2.49 | CK107: No | CM107: 3.4 | CN107: 1.5 | CO107: 2.45 | CP107: -0.3 | CQ107: 2.15 | CR107: 276.86158 | CS107: 0 | CT107: 0.030951059 | CU107: 0
A108: 198 | B108: BNP-FR | C108: BNP PARIBAS ACT.A | D108: FR0000131104 | E108: XPAR | F108: 1130810671 | G108: 71.12 | H108: EUR | I108: 8.0423255e+10 | J108: EU500 | K108: 1.8149903e+08 | L108: 0.95 | M108: 7.6402092e+10 | N108: 68.5 | O108: 1 | P108: 7.3587504e+10 | Q108: 30101010 | R108: 3010 | S108: 3.3054606 | T108: 1.5 | U108: A- | V108: Green | W108: 0 | X108: 0 | Y108: Green | Z108: Green | AA108: Green | AB108: Green | AC108: Green | AD108: Green | AE108: Green | AF108: 0 | AG108: 0 | AH108: 0 | AJ108: 0 | AK108: F | AM108: F | AN108: F | AO108: F | AQ108: 0 | AR108: 0 | AS108: 0 | AT108: 0 | AU108: 2.325 | AV108: 3.296 | AW108: 281.86734 | AX108: 1.5 | AY108: K | AZ108: 0 | BA108: 0 | BB108: FR | BC108: 0 | BD108: 0 | BE108: 0 | CI108: 2.8105 | CK108: No | CM108: 3.3054606 | CN108: 1.5 | CO108: 2.4027303 | CP108: -0.24 | CQ108: 2.1627303 | CR108: 276.86158 | CS108: 0 | CT108: 0.061479042 | CU108: 0
... A114: 864 | B114: 8411-JP | C114: MIZUHO FINANCIAL GRP | D114: JP3885780001 | E114: XTKS | F114: 2539250000 | G114: 27.19279 | H114: JPY | I114: 6.9049292e+10 | J114: AS500 | K114: 2.5628821e+08 | L114: 1 | M114: 6.9049292e+10 | N114: 3292 | O114: 0.00613973 | P114: 5.1323299e+10 | Q114: 30101010 | R114: 3010 | S114: 3.4 | T114: 1.5 | U114: B | V114: Green | W114: 0 | X114: 0 | Y114: Green | Z114: Green | AA114: Green | AB114: Green | AC114: Green | AD114: Green | AE114: Green | AF114: 0 | AG114: 0 | AH114: 0 | AJ114: 0 | AK114: F | AM114: F | AN114: F | AO114: F | AQ114: 0 | AR114: 0 | AS114: 0 | AT114: 0 | AU114: 2.101 | AV114: 2.45 | AW114: 210.02409 | AX114: 1.5 | AY114: K | AZ114: 0 | BA114: 0 | BB114: JP | BC114: 0 | BD114: 0 | BE114: 0 | CI114: 2.2755 | CK114: No | CM114: 3.4 | CN114: 1.5 | CO114: 2.45 | CP114: -0.18 | CQ114: 2.27 | CR114: 276.86158 | CS114: 0 | CT114: 0.081789043 | CU114: 0
A115: 891 | B115: NWG-GB | C115: NATWEST GROUP | D115: GB00BM8PJY71 | E115: XLON | F115: 8058562000 | G115: 5.462005 | H115: GBX | I115: 4.4015906e+10 | J115: EU500 | K115: 81343299 | L115: 0.9 | M115: 3.9614315e+10 | N115: 446.1 | O115: 0.01160026 | P115: 3.7531853e+10 | Q115: 30101010 | R115: 3010 | S115: 1.9993422 | U115: A- | V115: Green | W115: 0 | X115: 0 | Y115: Green | Z115: Green | AA115: Green | AB115: Green | AC115: Green | AD115: Green | AE115: Green | AF115: 0 | AG115: 0 | AH115: 0 | AJ115: 0 | AK115: F | AM115: F | AN115: F | AO115: F | AQ115: 0 | AR115: 0 | AS115: 0 | AT115: 0 | AU115: 2.414 | AV115: 2.734 | AW115: 119.28351 | AX115: 1.5 | AY115: K | AZ115: 0 | BA115: 0 | BB115: GB | BC115: 0 | BD115: 0 | BE115: 0 | CI115: 2.574 | CK115: No | CM115: 1.9993422 | CN115: 3.1 | CO115: 2.5496711 | CP115: -0.24 | CQ115: 2.3096711 | CR115: 276.86158 | CS115: 0 | CT115: 0.027988163 | CU115: 0
A116: 161 | B116: BIRG-IE | C116: BANK OF IRELAND GP | D116: IE00BD1RP616 | E116: XMSM | F116: 1003409101 | G116: 10.44 | H116: EUR | I116: 1.0475591e+10 | J116: EU500 | K116: 17800026 | L116: 1 | M116: 1.0475591e+10 | N116: 10.1 | O116: 1 | P116: 1.0134432e+10 | Q116: 30101010 | R116: 3010 | S116: 1.9796332 | U116: C | V116: Green | W116: 0 | X116: 0 | Y116: Green | Z116: Green | AA116: Green | AB116: Green | AC116: Green | AD116: Green | AE116: Green | AF116: 0 | AG116: 0 | AH116: 0 | AJ116: 0 | AK116: F | AM116: F | AN116: F | AO116: F | AQ116: 0 | AR116: 0 | AS116: 0 | AT116: 0 | AU116: 2.317 | AV116: 2.543 | AW116: 547.5107 | AX116: 1.5 | AY116: K | AZ116: 0 | BA116: 0 | BB116: IE | BC116: 0 | BD116: 0 | BE116: 0 | CI116: 2.43 | CK116: No | CM116: 1.9796332 | CN116: 3.1 | CO116: 2.5398166 | CP116: 0 | CQ116: 2.5398166 | CR116: 276.86158 | CS116: 0 | CT116: 0.006308084 | CU116: 0
A117: 1230 | B117: STAN-GB | C117: STANDARD CHARTERED | D117: GB0004082847 | E117: XLON | F117: 2414227500 | G117: 14.3018 | H117: GBX | I117: 3.4527799e+10 | J117: EU500 | K117: 49461387 | L117: 0.8 | M117: 2.7622239e+10 | N117: 989.4 | O117: 0.01160026 | P117: 2.2167045e+10 | Q117: 30101010 | R117: 3010 | S117: 3.4 | T117: 1.77 | U117: C | V117: Green | W117: 0 | X117: 0 | Y117: Green | Z117: Green | AA117: Green | AB117: Green | AC117: Green | AD117: Green | AE117: Green | AF117: 0 | AG117: 0 | AH117: 0 | AJ117: 0 | AK117: F | AM117: F | AN117: F | AO117: F | AQ117: 0 | AR117: 0 | AS117: 0 | AT117: 0 | AU117: 2.151 | AV117: 3.052 | AW117: 304.67613 | AX117: 1.5 | AY117: K | AZ117: 0 | BA117: 0 | BB117: GB | BC117: 0 | BD117: 0 | BE117: 0 | CI117: 2.6015 | CK117: No | CM117: 3.4 | CN117: 1.77 | CO117: 2.585 | CP117: 0 | CQ117: 2.585 | CR117: 276.86158 | CS117: 0 | CT117: 0.016955889 | CU117: 0
A118: 602 | B118: HSBA-GB | C118: HSBC HOLDINGS PLC | D118: GB0005405286 | E118: XLON | F118: 17822174000 | G118: 10.70882 | H118: GBX | I118: 1.9085445e+11 | J118: EU500 | K118: 1.6004577e+08 | L118: 0.9 | M118: 1.7176901e+11 | N118: 770.9 | O118: 0.01160026 | P118: 1.4343956e+11 | Q118: 30101010 | R118: 3010 | S118: 3.2733333 | T118: 1.5 | U118: Score not available | V118: Green | W118: 0 | X118: 0 | Y118: Green | Z118: Green | AA118: Green | AB118: Green | AC118: Green | AD118: Green | AE118: Green | AF118: 0 | AG118: 0 | AH118: 0 | AJ118: 0 | AK118: F | AM118: F | AN118: F | AO118: F | AQ118: 0 | AR118: 0 | AS118: 0 | AT118: 0 | AU118: 2.267 | AV118: 2.675 | AW118: 144.53784 | AX118: 1.5 | AY118: K | AZ118: 0 | BA118: 0 | BB118: GB | BC118: 0 | BD118: 0 | BE118: 0 | CI118: 2.471 | CK118: No | CM118: 3.2733333 | CN118: 1.5 | CO118: 2.3866667 | CP118: 0.3 | CQ118: 2.6866667 | CR118: 276.86158 | CS118: 0 | CT118: 0.061715576 | CU118: 0
A119: 1197 | B119: 8316-JP | C119: SMFG | D119: JP3890350006 | E119: XTKS | F119: 3884445600 | G119: 24.84572 | H119: JPY | I119: 9.6511848e+10 | J119: AS500 | K119: 3.3293004e+08 | L119: 1 | M119: 9.6511848e+10 | N119: 3120 | O119: 0.00613973 | P119: 7.4410275e+10 | Q119: 30101010 | R119: 3010 | S119: 3.4 | T119: 2.39 | U119: B | V119: Green | W119: 0 | X119: 0 | Y119: Green | Z119: Green | AA119: Green | AB119: Green | AC119: Green | AD119: Green | AE119: Green | AF119: 0 | AG119: 0 | AH119: 0 | AJ119: 0 | AK119: F | AM119: F | AN119: F | AO119: F | AQ119: 0 | AR119: 0 | AS119: 0 | AT119: 0 | AU119: 2.172 | AV119: 3.245 | AW119: 169.76147 | AX119: 1.5 | AY119: K | AZ119: 0 | BA119: 0 | BB119: JP | BC119: 0 | BD119: 0 | BE119: 0 | CI119: 2.7085 | CK119: No | CM119: 3.4 | CN119: 2.39 | CO119: 2.895 | CP119: -0.18 | CQ119: 2.715 | CR119: 276.86158 | CS119: 0 | CT119: 0.1 | CU119: 0
A120: 1015 | B120: PNC-US | C120: PNC FINANCIAL SERV. | D120: US6934751057 | E120: XNYS | F120: 395937000 | G120: 179.8661 | H120: USD | I120: 7.1215644e+10 | J120: NA500 | K120: 3.8150667e+08 | L120: 1 | M120: 7.1215644e+10 | N120: 155.32 | O120: 0.8797009 | P120: 5.4098909e+10 | Q120: 30101010 | R120: 3010 | S120: 3.4 | T120: 1.5 | U120: Score not available | V120: Green | W120: 0 | X120: 0 | Y120: Green | Z120: Green | AA120: Green | AB120: Green | AC120: Green | AD120: Green | AE120: Green | AF120: 0 | AG120: 0 | AH120: 0 | AJ120: 0 | AK120: F | AM120: F | AN120: F | AO120: F | AQ120: 0 | AR120: 0 | AS120: 0 | AT120: 0 | AU120: 1.89 | AV120: 3.318 | AW120: 232.51642 | AX120: 1.5 | AY120: K | AZ120: 0 | BA120: 0 | BB120: US | BC120: 0 | BD120: 0 | BE120: 0 | CI120: 2.604 | CK120: No | CM120: 3.4 | CN120: 1.5 | CO120: 2.45 | CP120: 0.3 | CQ120: 2.75 | CR120: 276.86158 | CS120: 0 | CT120: 0.1 | CU120: 0
A121: 1384 | B121: USB-US | C121: U.S. BANCORP | D121: US9029733048 | E121: XNYS | F121: 1559887500 | G121: 43.87374 | H121: USD | I121: 6.8438099e+10 | J121: NA500 | K121: 3.7962126e+08 | L121: 1 | M121: 6.8438099e+10 | N121: 38.2 | O121: 0.8797009 | P121: 5.2419356e+10 | Q121: 30101010 | R121: 3010 | S121: 3.4 | T121: 1.5 | U121: Score not available | V121: Green | W121: 0 | X121: 0 | Y121: Green | Z121: Green | AA121: Green | AB121: Green | AC121: Green | AD121: Green | AE121: Green | AF121: 0 | AG121: 0 | AH121: 0 | AJ121: 0 | AK121: F | AM121: F | AN121: F | AO121: F | AQ121: 0 | AR121: 0 | AS121: 0 | AT121: 0 | AU121: 1.821 | AV121: 3.191 | AW121: 427.2542 | AX121: 1.5 | AY121: K | AZ121: 0 | BA121: 0 | BB121: US | BC121: 0 | BD121: 0 | BE121: 0 | CI121: 2.506 | CK121: No | CM121: 3.4 | CN121: 1.5 | CO121: 2.45 | CP121: 0.3 | CQ121: 2.75 | CR121: 276.86158 | CS121: 0 | CT121: 0.1 | CU121: 0
A122: 163 | B122: BNS-CA | C122: BANK OF NOVA SCOTIA | D122: CA0641491075 | E122: XTSE | F122: 1229569600 | G122: 48.41156 | H122: CAD | I122: 5.9525382e+10 | J122: NA500 | K122: 2.223689e+08 | L122: 1 | M122: 5.9525382e+10 | N122: 65.01 | O122: 0.63445738 | P122: 5.0714919e+10 | Q122: 30101010 | R122: 3010 | S122: 3.4 | T122: 1.5 | U122: Score not available | V122: Green | W122: 0 | X122: 0 | Y122: Green | Z122: Green | AA122: Green | AB122: Green | AC122: Green | AD122: Green | AE122: Green | AF122: 0 | AG122: 0 | AH122: 0 | AJ122: 0 | AK122: F | AM122: F | AN122: F | AO122: F | AQ122: 0 | AR122: 0 | AS122: 0 | AT122: 0 | AU122: 2.088 | AV122: 3.487 | AW122: 351.27129 | AX122: 1.5 | AY122: K | AZ122: 0 | BA122: 0 | BB122: CA | BC122: 0 | BD122: 0 | BE122: 0 | CI122: 2.7875 | CK122: No | CM122: 3.4 | CN122: 1.5 | CO122: 2.45 | CP122: 0.3 | CQ122: 2.75 | CR122: 276.86158 | CS122: 0 | CT122: 0.071555134 | CU122: 0
A123: 812 | B123: 8252-JP | C123: MARUI GROUP | D123: JP3870400003 | E123: XTKS | F123: 208660420 | G123: 16.54143 | H123: JPY | I123: 3.4515417e+09 | J123: AS500 | K123: 9264504.3 | L123: 0.9 | M123: 3.1063876e+09 | N123: 2802 | O123: 0.00613973 | P123: 3.230725e+09 | Q123: 30201020 | R123: 3020 | S123: 1.7194201 | T123: 1.5 | U123: A | V123: Green | W123: 0 | X123: 0 | Y123: Green | Z123: Green | AA123: Green | AB123: Green | AC123: Green | AD123: Green | AE123: Green | AF123: 0 | AG123: 0 | AH123: 0 | AJ123: 0 | AK123: F | AM123: F | AN123: F | AO123: F | AQ123: 0 | AR123: 0 | AS123: 0 | AT123: 0 | AU123: 2.267 | AV123: 2.189 | AW123: 40.072971 | AX123: 1.5 | AY123: G | AZ123: 1 | BA123: 0 | BB123: JP | BC123: 0 | BD123: 0 | BE123: 0 | CI123: 2.228 | CK123: No | CM123: 1.7194201 | CN123: 1.5 | CO123: 1.60971 | CP123: -0.3 | CQ123: 1.30971 | CR123: 51.827488 | CS123: 1 | CT123: 0.0030879614 | CU123: 0
A124: 1104 | B124: SPGI-US | C124: S&P GLOBAL | D124: US78409V1044 | E124: XNYS | F124: 307800000 | G124: 510.1865 | H124: USD | I124: 157035404700 | J124: NA500 | K124: 6.3304865e+08 | L124: 1 | M124: 157035404700 | N124: 471.59 | O124: 0.8797009 | P124: 1.2769334e+11 | Q124: 30201030 | R124: 3020 | S124: 1.734895 | T124: 1.5 | U124: A- | V124: Green | W124: 0 | X124: 0 | Y124: Green | Z124: Green | AA124: Green | AB124: Green | AC124: Green | AD124: Green | AE124: Green | AF124: 0 | AG124: 0 | AH124: 0 | AJ124: 0 | AK124: F | AM124: F | AN124: F | AO124: F | AQ124: 0 | AR124: 0 | AS124: 0 | AT124: 0 | AU124: 2.223 | AV124: 3.265 | AW124: 2.9521274 | AX124: 1.5 | AY124: J | AZ124: 0 | BA124: 0 | BB124: US | BC124: 0 | BD124: 0 | BE124: 0 | CI124: 2.744 | CK124: No | CM124: 1.734895 | CN124: 1.5 | CO124: 1.6174475 | CP124: -0.24 | CQ124: 1.3774475 | CR124: 51.827488 | CS124: 1 | CT124: 0.1 | CU124: 0
...

Sheet Sheet1
A1: x | C1: x | E1: x | O1: x | P1: z
A2: AT0000730007 | B2: =_xlfn.XLOOKUP(A2,[1]Universe_World!$D$10:$D$1496,[1]Universe_World!$CK$10:$CK$1496) -> 1283.7714 | C2: AT0000730007 | D2: =_xlfn.XLOOKUP(C2,'Full Universe'!$D$3:$D$1499,'Full Universe'!$AW$3:$AW$1499) -> 1283.7714 | E2: =D2=B2 -> TRUE | J2: {=_xlfn.UNIQUE([1]!Universe_World[CI_Median])} -> 33.989273 | L2: {=_xlfn.UNIQUE('Full Universe'!$CR$2:$CR$1500)} -> 51.827488 | O2: GB00B1YW4409 | P2: 13.164173
A3: AU000000ALQ6 | B3: =_xlfn.XLOOKUP(A3,[1]Universe_World!$D$10:$D$1496,[1]Universe_World!$CK$10:$CK$1496) -> 242.61356 | C3: AU000000ALQ6 | D3: =_xlfn.XLOOKUP(C3,'Full Universe'!$D$3:$D$1499,'Full Universe'!$AW$3:$AW$1499) -> 242.61356 | E3: =D3=B3 -> TRUE | J3: 23.753721 | L3: 350.98887 | O3: US88579Y1010 | P3: 180.06968
A4: AU000000AZJ1 | B4: =_xlfn.XLOOKUP(A4,[1]Universe_World!$D$10:$D$1496,[1]Universe_World!$CK$10:$CK$1496) -> 289.30166 | C4: AU000000AZJ1 | D4: =_xlfn.XLOOKUP(C4,'Full Universe'!$D$3:$D$1499,'Full Universe'!$AW$3:$AW$1499) -> 289.30166 | E4: =D4=B4 -> TRUE | J4: 360.49567 | L4: 276.86158 | O4: JP3352000008 | P4: 1487.4985
A5: AU000000BXB1 | B5: =_xlfn.XLOOKUP(A5,[1]Universe_World!$D$10:$D$1496,[1]Universe_World!$CK$10:$CK$1496) -> 97.156371 | C5: AU000000BXB1 | D5: =_xlfn.XLOOKUP(C5,'Full Universe'!$D$3:$D$1499,'Full Universe'!$AW$3:$AW$1499) -> 97.156371 | E5: =D5=B5 -> TRUE | J5: 653.70388 | L5: 285.13539 | O5: NZATME0002S8 | P5: 474.06286
A6: AU000000QUB5 | B6: =_xlfn.XLOOKUP(A6,[1]Universe_World!$D$10:$D$1496,[1]Universe_World!$CK$10:$CK$1496) -> 432.54202 | C6: AU000000QUB5 | D6: =_xlfn.XLOOKUP(C6,'Full Universe'!$D$3:$D$1499,'Full Universe'!$AW$3:$AW$1499) -> 432.54202 | E6: =D6=B6 -> TRUE | J6: 52.62914 | L6: 1003.2865 | O6: IT0001233417 | P6: 1181.0697
A7: AU000000SEK6 | B7: =_xlfn.XLOOKUP(A7,[1]Universe_World!$D$10:$D$1496,[1]Universe_World!$CK$10:$CK$1496) -> 2.9351716 | C7: AU000000SEK6 | D7: =_xlfn.XLOOKUP(C7,'Full Universe'!$D$3:$D$1499,'Full Universe'!$AW$3:$AW$1499) -> 2.9351716 | E7: =D7=B7 -> TRUE | J7: 89.792933 | L7: 33.625121 | O7: KYG2953R1149 | P7: 556.19064
A8: AU000000TCL6 | B8: =_xlfn.XLOOKUP(A8,[1]Universe_World!$D$10:$D$1496,[1]Universe_World!$CK$10:$CK$1496) -> 10.558773 | C8: AU000000TCL6 | D8: =_xlfn.XLOOKUP(C8,'Full Universe'!$D$3:$D$1499,'Full Universe'!$AW$3:$AW$1499) -> 10.558773 | E8: =D8=B8 -> TRUE | J8: 1003.2865 | L8: 23.753721 | O8: SE0011337708 | P8: 1223.803
A9: AU0000013559 | B9: =_xlfn.XLOOKUP(A9,[1]Universe_World!$D$10:$D$1496,[1]Universe_World!$CK$10:$CK$1496) -> 381.31394 | C9: AU0000013559 | D9: =_xlfn.XLOOKUP(C9,'Full Universe'!$D$3:$D$1499,'Full Universe'!$AW$3:$AW$1499) -> 381.31394 | E9: =D9=B9 -> TRUE | J9: 414.93168 | L9: 50.951644 | O9: NL0000852564 | P9: 1619.7555
A10: AU0000364754 | B10: =_xlfn.XLOOKUP(A10,[1]Universe_World!$D$10:$D$1496,[1]Universe_World!$CK$10:$CK$1496) -> 368.92549 | C10: AU0000364754 | D10: =_xlfn.XLOOKUP(C10,'Full Universe'!$D$3:$D$1499,'Full Universe'!$AW$3:$AW$1499) -> 368.92549 | E10: =D10=B10 -> TRUE | J10: 324.26126 | L10: 201.88986 | O10: BE0974293251 | P10: 128.46807
A11: BMG507361001 | B11: =_xlfn.XLOOKUP(A11,[1]Universe_World!$D$10:$D$1496,[1]Universe_World!$CK$10:$CK$1496) -> 317.06417 | C11: BMG507361001 | D11: =_xlfn.XLOOKUP(C11,'Full Universe'!$D$3:$D$1499,'Full Universe'!$AW$3:$AW$1499) -> 317.06417 | E11: =D11=B11 -> TRUE | J11: 205.31107 | L11: 644.98569 | O11: SE0005127818 | P11: 3.5372492
A12: CA1363751027 | B12: =_xlfn.XLOOKUP(A12,[1]Universe_World!$D$10:$D$1496,[1]Universe_World!$CK$10:$CK$1496) -> 83.529122 | C12: CA1363751027 | D12: =_xlfn.XLOOKUP(C12,'Full Universe'!$D$3:$D$1499,'Full Universe'!$AW$3:$AW$1499) -> 83.529122 | E12: =D12=B12 -> TRUE | J12: 64.495465 | L12: 89.792933 | O12: CH0012221716 | P12: 5228.3624
A13: CA13646K1084 | B13: =_xlfn.XLOOKUP(A13,[1]Universe_World!$D$10:$D$1496,[1]Universe_World!$CK$10:$CK$1496) -> 81.465005 | C13: CA13646K1084 | D13: =_xlfn.XLOOKUP(C13,'Full Universe'!$D$3:$D$1499,'Full Universe'!$AW$3:$AW$1499) -> 81.465005 | E13: =D13=B13 -> TRUE | J13: 57.961718 | L13: 324.26126 | O13: US0028241000 | P13: 61.330192
A14: CH0012138605 | B14: =_xlfn.XLOOKUP(A14,[1]Universe_World!$D$10:$D$1496,[1]Universe_World!$CK$10:$CK$1496) -> 73.669675 | C14: CH0012138605 | D14: =_xlfn.XLOOKUP(C14,'Full Universe'!$D$3:$D$1499,'Full Universe'!$AW$3:$AW$1499) -> 73.669675 | E14: =D14=B14 -> TRUE | J14: 52.456211 | L14: 414.93168 | O14: US00287Y1091 | P14: 24.281901
... A21: CH0435377954 | B21: =_xlfn.XLOOKUP(A21,[1]Universe_World!$D$10:$D$1496,[1]Universe_World!$CK$10:$CK$1496) -> 184.57838 | C21: CH0435377954 | D21: =_xlfn.XLOOKUP(C21,'Full Universe'!$D$3:$D$1499,'Full Universe'!$AW$3:$AW$1499) -> 184.57838 | E21: =D21=B21 -> TRUE | J21: 687.12183 | L21: 64.495465 | O21: ES0167050915 | P21: 515.72006
A22: CH1169360919 | B22: =_xlfn.XLOOKUP(A22,[1]Universe_World!$D$10:$D$1496,[1]Universe_World!$CK$10:$CK$1496) -> 20.223472 | C22: CH1169360919 | D22: =_xlfn.XLOOKUP(C22,'Full Universe'!$D$3:$D$1499,'Full Universe'!$AW$3:$AW$1499) -> 20.223472 | E22: =D22=B22 -> TRUE | O22: SE0014781795 | P22: 135.06604
A23: CH1256740924 | B23: =_xlfn.XLOOKUP(A23,[1]Universe_World!$D$10:$D$1496,[1]Universe_World!$CK$10:$CK$1496) -> 48.003583 | C23: CH1256740924 | D23: =_xlfn.XLOOKUP(C23,'Full Universe'!$D$3:$D$1499,'Full Universe'!$AW$3:$AW$1499) -> 48.003583 | E23: =D23=B23 -> TRUE | O23: CH0012138605 | P23: 73.669675
A24: DE0005552004 | B24: =_xlfn.XLOOKUP(A24,[1]Universe_World!$D$10:$D$1496,[1]Universe_World!$CK$10:$CK$1496) -> 519.50948 | C24: DE0005552004 | D24: =_xlfn.XLOOKUP(C24,'Full Universe'!$D$3:$D$1499,'Full Universe'!$AW$3:$AW$1499) -> 519.50948 | E24: =D24=B24 -> TRUE | O24: DE000A1EWWW0 | P24: 156.19655
A25: DE0006602006 | B25: =_xlfn.XLOOKUP(A25,[1]Universe_World!$D$10:$D$1496,[1]Universe_World!$CK$10:$CK$1496) -> 4346.5658 | C25: DE0006602006 | D25: =_xlfn.XLOOKUP(C25,'Full Universe'!$D$3:$D$1499,'Full Universe'!$AW$3:$AW$1499) -> 4346.5658 | E25: =D25=B25 -> TRUE | O25: GB00B02J6398 | P25: 0.37512065
A26: DE0007010803 | B26: =_xlfn.XLOOKUP(A26,[1]Universe_World!$D$10:$D$1496,[1]Universe_World!$CK$10:$CK$1496) -> 162.61099 | C26: DE0007010803 | D26: =_xlfn.XLOOKUP(C26,'Full Universe'!$D$3:$D$1499,'Full Universe'!$AW$3:$AW$1499) -> 162.61099 | E26: =D26=B26 -> TRUE | O26: US00724F1012 | P26: 2.4645519
A27: DE0007030009 | B27: =_xlfn.XLOOKUP(A27,[1]Universe_World!$D$10:$D$1496,[1]Universe_World!$CK$10:$CK$1496) -> 586.35118 | C27: DE0007030009 | D27: =_xlfn.XLOOKUP(C27,'Full Universe'!$D$3:$D$1499,'Full Universe'!$AW$3:$AW$1499) -> 586.35118 | E27: =D27=B27 -> TRUE | O27: FR0010340141 | P27: 1046.2147
A28: DE0007236101 | B28: =_xlfn.XLOOKUP(A28,[1]Universe_World!$D$10:$D$1496,[1]Universe_World!$CK$10:$CK$1496) -> 3012.5164 | C28: DE0007236101 | D28: =_xlfn.XLOOKUP(C28,'Full Universe'!$D$3:$D$1499,'Full Universe'!$AW$3:$AW$1499) -> 3012.5164 | E28: =D28=B28 -> TRUE | O28: JP3047160001 | P28: 6.8662207
A29: DE0007500001 | B29: =_xlfn.XLOOKUP(A29,[1]Universe_World!$D$10:$D$1496,[1]Universe_World!$CK$10:$CK$1496) -> 55273.618 | C29: DE0007500001 | D29: =_xlfn.XLOOKUP(C29,'Full Universe'!$D$3:$D$1499,'Full Universe'!$AW$3:$AW$1499) -> 55273.618 | E29: =D29=B29 -> TRUE | O29: US0079031078 | P29: 99.328746
A30: DE000A0D9PT0 | B30: =_xlfn.XLOOKUP(A30,[1]Universe_World!$D$10:$D$1496,[1]Universe_World!$CK$10:$CK$1496) -> 740.68014 | C30: DE000A0D9PT0 | D30: =_xlfn.XLOOKUP(C30,'Full Universe'!$D$3:$D$1499,'Full Universe'!$AW$3:$AW$1499) -> 740.68014 | E30: =D30=B30 -> TRUE | O30: JP3122400009 | P30: 39.208876
A31: DE000DTR0CK8 | B31: =_xlfn.XLOOKUP(A31,[1]Universe_World!$D$10:$D$1496,[1]Universe_World!$CK$10:$CK$1496) -> 2250.9008 | C31: DE000DTR0CK8 | D31: =_xlfn.XLOOKUP(C31,'Full Universe'!$D$3:$D$1499,'Full Universe'!$AW$3:$AW$1499) -> 2250.9008 | E31: =D31=B31 -> TRUE | O31: NL0012969182 | P31: 8.867792
A32: DE000KBX1006 | B32: =_xlfn.XLOOKUP(A32,[1]Universe_World!$D$10:$D$1496,[1]Universe_World!$CK$10:$CK$1496) -> 3428.5625 | C32: DE000KBX1006 | D32: =_xlfn.XLOOKUP(C32,'Full Universe'!$D$3:$D$1499,'Full Universe'!$AW$3:$AW$1499) -> 3428.5625 | E32: =D32=B32 -> TRUE | O32: BE0003851681 | P32: 9.2750313
A33: DK0010244508 | B33: =_xlfn.XLOOKUP(A33,[1]Universe_World!$D$10:$D$1496,[1]Universe_World!$CK$10:$CK$1496) -> 1897.7701 | C33: DK0010244508 | D33: =_xlfn.XLOOKUP(C33,'Full Universe'!$D$3:$D$1499,'Full Universe'!$AW$3:$AW$1499) -> 1897.7701 | E33: =D33=B33 -> TRUE | O33: BMG0112X1056 | P33: 205.29609
... A260: US98419M1009 | B260: =_xlfn.XLOOKUP(A260,[1]Universe_World!$D$10:$D$1496,[1]Universe_World!$CK$10:$CK$1496) -> 2529.1874 | C260: US98419M1009 | D260: =_xlfn.XLOOKUP(C260,'Full Universe'!$D$3:$D$1499,'Full Universe'!$AW$3:$AW$1499) -> 2529.1874 | E260: =D260=B260 -> TRUE | O260: JP3566800003 | P260: 28.355979
O261: GB00B033F229 | P261: 1597.0072
O262: CA12532H1047 | P262: 72.26846
O263: US8085131055 | P263: 27.088612
O264: US16119P1084 | P264: 172.22133
O265: AU000000CHC0 | P265: 126.20468
O266: IL0010824113 | P266: 24.460998
O267: US16411R2085 | P267: 1348.5978
O268: US1667641005 | P268: 4003.7103
O269: JP3511800009 | P269: 604.46634
O270: US1696561059 | P270: 1.4991416
O271: CH0044328745 | P271: 253.49704
O272: JP3526600006 | P272: 3644.7207
... O623: GB00B61TVQ02 | P623: 1978.3548
O624: AU000000IPL1
O625: ES0148396007 | P625: 173.64204
O626: SE0000107203 | P626: 122.49929
O627: SE0001515552 | P627: 43.021619
O628: DE0006231004 | P628: 71.572118
O629: GB00BMJ6DW54 | P629: 40.268022
O630: NZIFTE0003S3 | P630: 3.7244343
O631: NL0011821202 | P631: 259.21967
O632: US45687V1061 | P632: 6985.4994
O633: JP3294460005 | P633: 3883.1042
O634: LU2290522684 | P634: 65.872922
O635: US45784P1012 | P635: 34.361927
O636: AU000000IAG3 | P636: 480.67716
... O1500: CH0011075394 | P1500: 45.306543

Sheet Full Universe
A1: Rank | B1: Ticker | C1: Company | D1: ISIN Code | E1: MIC | F1: Number of Shares | G1: Price (EUR) | H1: Currency | I1: Mcap in EUR | J1: index | K1: VOL_AV_3M | L1: Free Float | M1: FFMC_CO | N1: Close Prc | O1: FX/Index Ccy | P1: FFMC_WD | Q1: Subsector Code | R1: Supersector Code | S1: itr_scope123_target | T1: itr_scope12_trend | U1: CDP_climate_score | V1: NBR Overall Flag | W1: Tobacco - Production Maximum Percentage of Revenues (%) | X1: Tobacco - Distribution Maximum Percentage of Revenues (%) | Y1: Biological Weapons - Overall Flag | Z1: Chemical Weapons - Overall Flag | AA1: Nuclear Weapons Outside NPT - Overall Flag | AB1: Nuclear Weapons Inside NPT - Overall Flag | AC1: Cluster Munitions - Overall Flag | AD1: Depleted Uranium - Overall Flag | AE1: Anti-personnel Mines - Overall Flag | AF1: coal_mining_and_power_gen_maximum_percentage_of_revenues-values | AG1: Fossil Fuel - Total Maximum Percentage of Revenues (%) | AH1: power_generation_thermal_maximum_percentage_of_revenues-values | AI1: shale_oil_and_or_gas_involvement_tie | AJ1: arctic_drilling_share_max-values | AK1: deepwater_drilling_involvement | AL1: HydraulicFracturingInvolvement | AM1: CoalMiningExpInvolved | AN1: OilGasExtractExpInvolved | AO1: OtherFFInfraInvolved | AP1: NuclearPowerInvolvement | AQ1: NuclearPowerRevShareMax-values | AR1: NuclearPowerUraniumRevShareMax-values | AS1: CivFARevShareMax-values | AT1: MilitaryEqmtDistMaxRev-values | AU1: Social Rating (Num) | AV1: Governance Rating (Num) | AW1: Carbon Intensity (ISS) | AX1: ScoreTemperatureISS | AY1: NACE | AZ1: High_Climate_Impact | BA1: EU_Taxonomy | BB1: Country_Code | BC1: GAFI_Black_List | BD1: GAFI_Grey_List | BE1: Non_Fiscally_Cooperative | BF1: exclude_gafi_black | BG1: exclude_gafi_grey | BH1: exclude_non_fiscal_coop | BI1: exclude_subsector | BJ1: exclude_nbr_red | BK1: exclude_tobacco_prod | BL1: exclude_tobacco_dist | BM1: exclude_biological_weapons | BN1: exclude_chemical_weapons | BO1: exclude_nuclear_weapons_inside_npt | BP1: exclude_nuclear_weapons_outside_npt | BQ1: exclude_cluster_munitions | BR1: exclude_depleted_uranium | BS1: exclude_anti_personnel_mines | BT1: exclude_coal_mining | BU1: exclude_fossil_fuel | BV1: exclude_thermal_power | BW1: exclude_shale_oil_gas | BX1: exclude_arctic_drilling | BY1: exclude_deepwater_drilling | BZ1: exclude_hydraulic_fracturing | CA1: exclude_coal_mining_expansion | CB1: exclude_oil_gas_extraction_expansion | CC1: exclude_other_fossil_fuel_infra | CD1: exclude_nuclear_power | CE1: exclude_nuclear_power_revenue | CF1: exclude_nuclear_uranium | CG1: exclude_civilian_firearms | CH1: exclude_military_equipment | CI1: SG_Score | CJ1: exclude_sg_bottom_10 | CK1: Excluded | CL1: Exclusion_Reason | CM1: itr_scope123_target_filled | CN1: itr_scope12_trend_filled | CO1: cdp_temperature_score | CP1: bonus_malus | CQ1: climate_score | CR1: Median_Carbon_Intensity_Supersector
A2: 1 | B2: III-GB | C2: 3I GROUP PLC | D2: GB00B1YW4409 | E2: XLON | F2: 973396500 | G2: 49.60294 | H2: GBX | I2: 4.8283328e+10 | J2: EU500 | K2: 39423545 | L2: 1 | M2: 4.8283328e+10 | N2: 3904 | O2: 0.01160026 | P2: 4.4082611e+10 | Q2: 30202010 | R2: 3020 | S2: 1.994079 | T2: 1.5 | U2: D | V2: Green | W2: 0 | X2: 0 | Y2: Green | Z2: Green | AA2: Green | AB2: Green | AC2: Green | AD2: Green | AE2: Green | AG2: 0.05 | AJ2: 0 | AK2: F | AM2: F | AN2: F | AO2: F | AQ2: 0 | AR2: 0 | AS2: 0 | AT2: 0 | AU2: 2.406 | AV2: 3.006 | AW2: 13.164173 | AX2: 1.5 | AY2: K | AZ2: 0 | BA2: 0 | BB2: GB | BC2: 0 | BD2: 0 | BE2: 0 | BU2: exclude_fossil_fuel | CI2: 2.706 | CK2: Yes | CL2: exclude_fossil_fuel | CM2: 1.994079 | CN2: 1.5 | CO2: 1.7470395 | CP2: 0.18 | CQ2: 1.9270395 | CR2: 51.827488
A3: 2 | B3: MMM-US | C3: 3M CO | D3: US88579Y1010 | E3: XNYS | F3: 542900000 | G3: 138.6705 | H3: USD | I3: 75284214450 | J3: NA500 | K3: 4.6977667e+08 | L3: 1 | M3: 75284214450 | N3: 136.01 | O3: 0.8797009 | P3: 6.4956964e+10 | Q3: 50203000 | R3: 5020 | U3: D | V3: Green | W3: 0 | X3: 0 | Y3: Green | Z3: Green | AA3: Green | AB3: Green | AC3: Green | AD3: Green | AE3: Green | AF3: 0 | AG3: 0.05 | AH3: 0 | AI3: Services | AJ3: 0 | AK3: F | AL3: Services | AM3: F | AN3: F | AO3: F | AP3: Services | AQ3: 0.01 | AR3: 0 | AS3: 0 | AT3: 0 | AU3: 2.564 | AV3: 3.384 | AW3: 180.06968 | AX3: 2.1 | AY3: C | AZ3: 1 | BA3: 0 | BB3: US | BC3: 0 | BD3: 0 | BE3: 0 | BU3: exclude_fossil_fuel | BW3: exclude_shale_oil_gas | BZ3: exclude_hydraulic_fracturing | CD3: exclude_nuclear_power | CI3: 2.974 | CK3: Yes | CL3: exclude_fossil_fuel; exclude_shale_oil_gas; exclude_hydraulic_fracturing; exclude_nuclear_power | CM3: 3.4592708 | CN3: 3.1 | CO3: 3.2796354 | CP3: 0.18 | CQ3: 3.4596354 | CR3: 350.98887
A4: 3 | B4: 8341-JP | C4: 77 BANK LTD. | D4: JP3352000008 | E4: XTKS | F4: 76655750 | G4: 29.43114 | H4: JPY | I4: 2.2560661e+09 | J4: AS500 | K4: 5232903.1 | L4: 1 | M4: 2.2560661e+09 | N4: 3934 | O4: 0.00613973 | P4: 1.8515198e+09 | Q4: 30101010 | R4: 3010 | S4: 3.4 | U4: C | V4: Green | W4: 0 | X4: 0 | Y4: Green | Z4: Green | AA4: Green | AB4: Green | AC4: Green | AD4: Green | AE4: Green | AF4: 0 | AG4: 0 | AH4: 0 | AJ4: 0 | AK4: F | AM4: F | AN4: F | AO4: F | AQ4: 0 | AR4: 0 | AS4: 0 | AT4: 0 | AU4: 1.73 | AV4: 1.698 | AW4: 1487.4985 | AX4: 2.9 | AY4: K | AZ4: 0 | BA4: 0 | BB4: JP | BC4: 0 | BD4: 0 | BE4: 0 | CI4: 1.714 | CJ4: exclude_sg_bottom_10 | CK4: Yes | CL4: exclude_sg_bottom_10 | CM4: 3.4 | CN4: 3.1 | CO4: 3.25 | CP4: 0 | CQ4: 3.25 | CR4: 276.86158
A5: 4 | B5: A2M-AU | C5: A2 MILK CO LTD | D5: NZATME0002S8 | E5: XASX | F5: 724019100 | G5: 4.737804 | H5: AUD | I5: 3.4302606e+09 | J5: AS500 | K5: 8193130.8 | L5: 0.9 | M5: 3.0872345e+09 | N5: 8.06 | O5: 0.55671538 | P5: 2.9238884e+09 | Q5: 45102020 | R5: 4510 | S5: 3.4 | U5: F | V5: Green | W5: 0 | X5: 0 | Y5: Green | Z5: Green | AA5: Green | AB5: Green | AC5: Green | AD5: Green | AE5: Green | AF5: 0 | AG5: 0 | AH5: 0 | AJ5: 0 | AK5: F | AM5: F | AN5: F | AO5: F | AQ5: 0 | AR5: 0 | AS5: 0 | AT5: 0 | AU5: 2.013 | AV5: 3.066 | AW5: 474.06286 | AX5: 1.5 | AY5: A | AZ5: 1 | BA5: 0 | BB5: NZ | BC5: 0 | BD5: 0 | BE5: 0 | CI5: 2.5395 | CK5: No | CM5: 3.4 | CN5: 3.1 | CO5: 3.25 | CP5: 0.3 | CQ5: 3.55 | CR5: 285.13539
A6: 5 | B6: A2A-IT | C6: A2A | D6: IT0001233417 | E6: MTAA | F6: 3132905277 | G6: 2.145 | H6: EUR | I6: 6.7200818e+09 | J6: EU500 | K6: 19527443 | L6: 0.5 | M6: 3.3600409e+09 | N6: 2.036 | O6: 1 | P6: 3.1892976e+09 | Q6: 65101015 | R6: 6510 | S6: 2 | T6: 2.93 | U6: A- | V6: Green | W6: 0 | X6: 0 | Y6: Green | Z6: Green | AA6: Green | AB6: Green | AC6: Green | AD6: Green | AE6: Green | AF6: 0.0029 | AG6: 0.369 | AH6: 0.0893 | AJ6: 0 | AK6: F | AM6: F | AN6: F | AO6: T | AQ6: 0 | AR6: 0 | AS6: 0 | AT6: 0 | AU6: 2.448 | AV6: 2.942 | AW6: 1181.0697 | AX6: 2.3 | AY6: D | AZ6: 1 | BA6: 0 | BB6: IT | BC6: 0 | BD6: 0 | BE6: 0 | BT6: exclude_coal_mining | BU6: exclude_fossil_fuel | BV6: exclude_thermal_power | CC6: exclude_other_fossil_fuel_infra | CI6: 2.695 | CK6: Yes | CL6: exclude_coal_mining; exclude_fossil_fuel; exclude_thermal_power; exclude_other_fossil_fuel_infra | CM6: 2 | CN6: 2.93 | CO6: 2.465 | CP6: -0.24 | CQ6: 2.225 | CR6: 1003.2865
A7: 6 | B7: 2018-HK | C7: AAC TECHNOLOGIES | D7: KYG2953R1149 | E7: XHKG | F7: 1198500000 | G7: 6.155748 | H7: HKD | I7: 7377663978 | J7: AS500 | K7: 32843617 | L7: 0.7 | M7: 5.1643648e+09 | N7: 36.65 | O7: 0.11342884 | P7: 3.4876552e+09 | Q7: 10102015 | R7: 1010 | S7: 3.4 | U7: C | V7: Green | W7: 0 | X7: 0 | Y7: Green | Z7: Green | AA7: Green | AB7: Green | AC7: Green | AD7: Green | AE7: Green | AF7: 0 | AG7: 0 | AH7: 0 | AJ7: 0 | AK7: F | AM7: F | AN7: F | AO7: F | AQ7: 0 | AR7: 0 | AS7: 0 | AT7: 0 | AU7: 1.906 | AV7: 2.317 | AW7: 556.19064 | AX7: 6 | AY7: C | AZ7: 1 | BA7: 0 | BB7: KY | BC7: 0 | BD7: 0 | BE7: 0 | CI7: 2.1115 | CK7: No | CM7: 3.4 | CN7: 3.1 | CO7: 3.25 | CP7: 0 | CQ7: 3.25 | CR7: 33.625121
A8: 7 | B8: AAK-SE | C8: AAK AB | D8: SE0011337708 | E8: XSTO | F8: 259559200 | G8: 27.4255 | H8: SEK | I8: 7.1185408e+09 | J8: EU500 | K8: 10069959 | L8: 0.7 | M8: 4.9829786e+09 | N8: 268 | O8: 0.09077334 | P8: 4.420054e+09 | Q8: 45102020 | R8: 4510 | S8: 1.9643056 | U8: C | V8: Green | W8: 0 | X8: 0 | Y8: Green | Z8: Green | AA8: Green | AB8: Green | AC8: Green | AD8: Green | AE8: Green | AF8: 0 | AG8: 0 | AH8: 0 | AJ8: 0 | AK8: F | AM8: F | AN8: F | AO8: F | AQ8: 0 | AR8: 0 | AS8: 0 | AT8: 0 | AU8: 2.42 | AV8: 3.154 | AW8: 1223.803 | AX8: 1.5 | AY8: C | AZ8: 1 | BA8: 0 | BB8: SE | BC8: 0 | BD8: 0 | BE8: 0 | CI8: 2.787 | CK8: No | CM8: 1.9643056 | CN8: 3.1 | CO8: 2.5321528 | CP8: 0 | CQ8: 2.5321528 | CR8: 285.13539
A9: 8 | B9: AALB-NL | C9: AALBERTS NV | D9: NL0000852564 | E9: XAMS | F9: 110580102 | G9: 36.3 | H9: EUR | I9: 4.0140577e+09 | J9: EU500 | K9: 4806266.6 | L9: 0.9 | M9: 3.6126519e+09 | N9: 26.96 | O9: 1 | P9: 2.6831156e+09 | Q9: 50202020 | R9: 5020 | U9: C | V9: Green | W9: 0 | X9: 0 | Y9: Green | Z9: Green | AA9: Green | AB9: Green | AC9: Green | AD9: Green | AE9: Green | AF9: 0 | AG9: 0.1 | AH9: 0 | AJ9: 0 | AK9: F | AM9: F | AN9: F | AO9: F | AP9: Services | AQ9: 0.01 | AR9: 0 | AS9: 0 | AT9: 0 | AU9: 1.998 | AV9: 3.25 | AW9: 1619.7555 | AX9: 1.7 | AY9: C | AZ9: 1 | BA9: 0 | BB9: NL | BC9: 0 | BD9: 0 | BE9: 0 | BU9: exclude_fossil_fuel | CD9: exclude_nuclear_power | CI9: 2.624 | CK9: Yes | CL9: exclude_fossil_fuel; exclude_nuclear_power | CM9: 3.4592708 | CN9: 3.1 | CO9: 3.2796354 | CP9: 0 | CQ9: 3.2796354 | CR9: 350.98887
A10: 9 | B10: ABI-BE | C10: AB INBEV | D10: BE0974293251 | E10: XBRU | F10: 1797198523 | G10: 51.62 | H10: EUR | I10: 9.2771388e+10 | J10: EU500 | K10: 98018859 | L10: 0.55 | M10: 5.1024263e+10 | N10: 55.4 | O10: 1 | P10: 5.4760639e+10 | Q10: 45101010 | R10: 4510 | S10: 2.101079 | T10: 2.7 | U10: Score not available | V10: Amber | W10: 0 | X10: 0 | Y10: Green | Z10: Green | AA10: Green | AB10: Green | AC10: Green | AD10: Green | AE10: Green | AF10: 0 | AG10: 0 | AH10: 0 | AJ10: 0 | AK10: F | AM10: F | AN10: F | AO10: F | AQ10: 0 | AR10: 0 | AS10: 0 | AT10: 0 | AU10: 1.867 | AV10: 2.352 | AW10: 128.46807 | AX10: 1.8 | AY10: C | AZ10: 1 | BA10: 0 | BB10: BE | BC10: 0 | BD10: 0 | BE10: 0 | CI10: 2.1095 | CK10: No | CM10: 2.101079 | CN10: 2.7 | CO10: 2.4005395 | CP10: 0.3 | CQ10: 2.7005395 | CR10: 285.13539
A11: 10 | B11: SAGA.B-SE | C11: AB SAGAX CLASS B | D11: SE0005127818 | E11: XSTO | F11: 313943020 | G11: 19.72838 | H11: SEK | I11: 6.1935872e+09 | J11: EU500 | K11: 7671301.9 | L11: 0.7 | M11: 4.335511e+09 | N11: 201.4 | O11: 0.09077334 | P11: 4.0175996e+09 | Q11: 35101010 | R11: 3510 | S11: 3.2721025 | U11: F | V11: Green | W11: 0 | X11: 0 | Y11: Green | Z11: Green | AA11: Green | AB11: Green | AC11: Green | AD11: Green | AE11: Green | AF11: 0 | AG11: 0 | AH11: 0 | AJ11: 0 | AK11: F | AM11: F | AN11: F | AO11: F | AQ11: 0 | AR11: 0 | AS11: 0 | AT11: 0 | AU11: 1.961 | AV11: 2.119 | AW11: 3.5372492 | AX11: 1.5 | AY11: L | AZ11: 1 | BA11: 0 | BB11: SE | BC11: 0 | BD11: 0 | BE11: 0 | CI11: 2.04 | CK11: No | CM11: 3.2721025 | CN11: 3.1 | CO11: 3.1860513 | CP11: 0.3 | CQ11: 3.4860513 | CR11: 23.753721
A12: 11 | B12: ABBN-CH | C12: ABB LTD | D12: CH0012221716 | E12: XSWX | F12: 1860614900 | G12: 55.5674 | H12: CHF | I12: 1.0338953e+11 | J12: EU500 | K12: 1.4023889e+08 | L12: 0.85 | M12: 8.7881103e+10 | N12: 41.37 | O12: 1.0763104 | P12: 7.0420399e+10 | Q12: 50202010 | R12: 5020 | S12: 1.7491009 | T12: 1.5 | U12: A | V12: Amber | W12: 0 | X12: 0 | Y12: Green | Z12: Green | AA12: Green | AB12: Green | AC12: Green | AD12: Green | AE12: Green | AF12: 0.01 | AG12: 0.15 | AH12: 0 | AJ12: 0 | AK12: T | AM12: F | AN12: F | AO12: F | AP12: Services | AQ12: 0.04 | AR12: 0 | AS12: 0 | AT12: 0 | AU12: 2.887 | AV12: 2.502 | AW12: 5228.3624 | AX12: 1.5 | AY12: C | AZ12: 1 | BA12: 0 | BB12: CH | BC12: 0 | BD12: 0 | BE12: 0 | BT12: exclude_coal_mining | BU12: exclude_fossil_fuel | BY12: exclude_deepwater_drilling | CD12: exclude_nuclear_power | CI12: 2.6945 | CK12: Yes | CL12: exclude_coal_mining; exclude_fossil_fuel; exclude_deepwater_drilling; exclude_nuclear_power | CM12: 1.7491009 | CN12: 1.5 | CO12: 1.6245504 | CP12: -0.3 | CQ12: 1.3245504 | CR12: 350.98887
A13: 12 | B13: ABT-US | C13: ABBOTT LABORATORIES | D13: US0028241000 | E13: XNYS | F13: 1734323400 | G13: 129.0483 | H13: USD | I13: 2.2381149e+11 | J13: NA500 | K13: 6.6899105e+08 | L13: 1 | M13: 2.2381149e+11 | N13: 127.96 | O13: 0.8797009 | P13: 1.9522676e+11 | Q13: 20102010 | R13: 2010 | S13: 1.9835941 | T13: 2.08 | U13: B | V13: Green | W13: 0 | X13: 0 | Y13: Green | Z13: Green | AA13: Green | AB13: Green | AC13: Green | AD13: Green | AE13: Green | AF13: 0 | AG13: 0 | AH13: 0 | AJ13: 0 | AK13: F | AM13: F | AN13: F | AO13: F | AQ13: 0 | AR13: 0 | AS13: 0 | AT13: 0 | AU13: 2.693 | AV13: 3.678 | AW13: 61.330192 | AX13: 1.5 | AY13: C | AZ13: 1 | BA13: 0 | BB13: US | BC13: 0 | BD13: 0 | BE13: 0 | CI13: 3.1855 | CK13: No | CM13: 1.9835941 | CN13: 2.08 | CO13: 2.0317971 | CP13: -0.18 | CQ13: 1.8517971 | CR13: 50.951644
A14: 13 | B14: ABBV-US | C14: ABBVIE INC. | D14: US00287Y1091 | E14: XNYS | F14: 1765354900 | G14: 193.2855 | H14: USD | I14: 3.412175e+11 | J14: NA500 | K14: 1.0309011e+09 | L14: 1 | M14: 3.412175e+11 | N14: 179.1 | O14: 0.8797009 | P14: 2.7813949e+11 | Q14: 20103015 | R14: 2010 | S14: 1.969737 | T14: 2.08 | U14: B | V14: Green | W14: 0 | X14: 0 | Y14: Green | Z14: Green | AA14: Green | AB14: Green | AC14: Green | AD14: Green | AE14: Green | AF14: 0 | AG14: 0 | AH14: 0 | AJ14: 0 | AK14: F | AM14: F | AN14: F | AO14: F | AQ14: 0 | AR14: 0 | AS14: 0 | AT14: 0 | AU14: 2.616 | AV14: 2.953 | AW14: 24.281901 | AX14: 1.5 | AY14: C | AZ14: 1 | BA14: 0 | BB14: US | BC14: 0 | BD14: 0 | BE14: 0 | CI14: 2.7845 | CK14: No | CM14: 1.969737 | CN14: 2.08 | CO14: 2.0248685 | CP14: -0.18 | CQ14: 1.8448685 | CR14: 50.951644
A15: 14 | B15: ABN-NL | C15: ABN AMRO BANK N.V. | D15: NL0011540547 | E15: XAMS | F15: 539163896 | G15: 17.8 | H15: EUR | I15: 9.5971173e+09 | J15: EU500 | K15: 48401045 | L15: 1 | M15: 9.5971173e+09 | N15: 17.56 | O15: 1 | P15: 9.467718e+09 | Q15: 30101010 | R15: 3010 | S15: 3.2733333 | U15: C | V15: Green | W15: 0 | X15: 0 | Y15: Green | Z15: Green | AA15: Green | AB15: Green | AC15: Green | AD15: Green | AE15: Green | AF15: 0 | AG15: 0 | AH15: 0 | AJ15: 0 | AK15: F | AM15: F | AN15: F | AO15: F | AQ15: 0 | AR15: 0 | AS15: 0 | AT15: 0 | AU15: 2.394 | AV15: 2.779 | AW15: 397.99801 | AX15: 1.5 | AY15: K | AZ15: 0 | BA15: 0 | BB15: NL | BC15: 0 | BD15: 0 | BE15: 0 | CI15: 2.5865 | CK15: No | CM15: 3.2733333 | CN15: 3.1 | CO15: 3.1866667 | CP15: 0 | CQ15: 3.1866667 | CR15: 276.86158
A16: 15 | B16: ABDN-GB | C16: ABRDN | D16: GB00BF8Q6K64 | E16: XLON | F16: 1840742800 | G16: 1.908317 | H16: GBX | I16: 3.5127208e+09 | J16: EU500 | K16: 5431165.1 | L16: 1 | M16: 3.5127208e+09 | N16: 138.9 | O16: 0.01160026 | P16: 2.9659449e+09 | Q16: 30202010 | R16: 3020 | S16: 3.02 | U16: C | V16: Green | W16: 0 | X16: 0 | Y16: Green | Z16: Green | AA16: Green | AB16: Green | AC16: Green | AD16: Green | AE16: Green | AF16: 0 | AG16: 0 | AH16: 0 | AJ16: 0 | AK16: F | AM16: F | AN16: F | AO16: F | AQ16: 0 | AR16: 0 | AS16: 0 | AT16: 0 | AU16: 2.139 | AV16: 3.161 | AW16: 925.58576 | AX16: 1.5 | AY16: K | AZ16: 0 | BA16: 0 | BB16: GB | BC16: 0 | BD16: 0 | BE16: 0 | CI16: 2.65 | CK16: No | CM16: 3.02 | CN16: 3.1 | CO16: 3.06 | CP16: 0 | CQ16: 3.06 | CR16: 51.827488
A17: 16 | B17: ACLN-CH | C17: ACCELLERON INDUSTR. | D17: CH1169360919 | E17: XSWX | F17: 94500000 | G17: 45.65756 | H17: CHF | I17: 4314639420 | J17: EU500 | K17: 10718443 | L17: 1 | M17: 4314639420 | N17: 39.74 | O17: 1.0763104 | P17: 4.0420084e+09 | Q17: 50204030 | R17: 5020 | U17: F | V17: Green | W17: 0 | X17: 0 | Y17: Green | Z17: Green | AA17: Green | AB17: Green | AC17: Green | AD17: Green | AE17: Green | AF17: 0 | AG17: 0.43 | AH17: 0 | AJ17: 0 | AK17: F | AM17: F | AN17: F | AO17: F | AQ17: 0 | AR17: 0 | AS17: 0 | AT17: 0 | AU17: 2.402 | AV17: 3.187 | AW17: 20.223472 | AX17: 1.5 | AY17: C | AZ17: 1 | BA17: 0 | BB17: CH | BC17: 0 | BD17: 0 | BE17: 0 | BU17: exclude_fossil_fuel | CI17: 2.7945 | CK17: Yes | CL17: exclude_fossil_fuel | CM17: 3.4592708 | CN17: 3.1 | CO17: 3.2796354 | CP17: 0.3 | CQ17: 3.5796354 | CR17: 350.98887
A18: 17 | B18: ACN-US | C18: ACCENTURE PLC-A | D18: IE00B4BNMY34 | E18: XNYS | F18: 625479900 | G18: 348.4075 | H18: USD | I18: 2.1792189e+11 | J18: NA500 | K18: 9.1298424e+08 | L18: 1 | M18: 2.1792189e+11 | N18: 289.79 | O18: 0.8797009 | P18: 1.5945267e+11 | Q18: 50205020 | R18: 5020 | S18: 1.73905 | T18: 1.5 | U18: A- | V18: Amber | W18: 0 | X18: 0 | Y18: Green | Z18: Green | AA18: Green | AB18: Green | AC18: Green | AD18: Green | AE18: Green | AF18: 0 | AG18: 0 | AH18: 0 | AJ18: 0 | AK18: F | AM18: F | AN18: F | AO18: F | AQ18: 0 | AR18: 0 | AS18: 0 | AT18: 0 | AU18: 2.543 | AV18: 2.915 | AW18: 2.7933113 | AX18: 1.5 | AY18: J | AZ18: 0 | BA18: 0 | BB18: IE | BC18: 0 | BD18: 0 | BE18: 0 | CI18: 2.729 | CK18: No | CM18: 1.73905 | CN18: 1.5 | CO18: 1.619525 | CP18: -0.24 | CQ18: 1.379525 | CR18: 350.98887
A19: 18 | B19: AC-FR | C19: ACCOR | D19: FR0000120404 | E19: XPAR | F19: 243667720 | G19: 46.43 | H19: EUR | I19: 1.1313492e+10 | J19: EU500 | K19: 26555203 | L19: 0.85 | M19: 9.6164684e+09 | N19: 38.58 | O19: 1 | P19: 7.9905955e+09 | Q19: 40501025 | R19: 4050 | S19: 1.7728124 | T19: 3.01 | U19: C | V19: Green | W19: 0 | X19: 0.01 | Y19: Green | Z19: Green | AA19: Green | AB19: Green | AC19: Green | AD19: Green | AE19: Green | AF19: 0 | AG19: 0 | AH19: 0 | AJ19: 0 | AK19: F | AM19: F | AN19: F | AO19: F | AQ19: 0 | AR19: 0 | AS19: 0 | AT19: 0 | AU19: 2.754 | AV19: 3.017 | AW19: 514.67199 | AX19: 6 | AY19: I | AZ19: 0 | BA19: 0 | BB19: FR | BC19: 0 | BD19: 0 | BE19: 0 | CI19: 2.8855 | CK19: No | CM19: 1.7728124 | CN19: 3.01 | CO19: 2.3914062 | CP19: 0 | CQ19: 2.3914062 | CR19: 201.88986
A20: 19 | B20: ACKB-BE | C20: ACKERMANS V.HAAREN | D20: BE0003764785 | E20: XBRU | F20: 33157750 | G20: 195.8 | H20: EUR | I20: 6492287450 | J20: EU500 | K20: 4586713 | L20: 0.65 | M20: 4.2199868e+09 | N20: 196.7 | O20: 1 | P20: 4.2393841e+09 | Q20: 50101015 | R20: 5010 | S20: 3.4 | U20: B | V20: Green | W20: 0 | X20: 0 | Y20: Green | Z20: Green | AA20: Green | AB20: Green | AC20: Green | AD20: Green | AE20: Green | AF20: 0 | AG20: 0.5 | AH20: 0 | AJ20: 0 | AK20: F | AM20: F | AN20: F | AO20: F | AQ20: 0 | AR20: 0 | AS20: 0 | AT20: 0 | AU20: 1.791 | AV20: 1.939 | AW20: 130.59557 | AX20: 6 | AY20: F | AZ20: 1 | BA20: 0 | BB20: BE | BC20: 0 | BD20: 0 | BE20: 0 | BU20: exclude_fossil_fuel | CI20: 1.865 | CJ20: exclude_sg_bottom_10 | CK20: Yes | CL20: exclude_fossil_fuel; exclude_sg_bottom_10 | CM20: 3.4 | CN20: 3.1 | CO20: 3.25 | CP20: -0.18 | CQ20: 3.07 | CR20: 644.98569
A21: 20 | B21: ACS-ES | C21: ACS ACTIVIDADES CONS | D21: ES0167050915 | E21: XMAD | F21: 271664580 | G21: 51.55 | H21: EUR | I21: 14004309099 | J21: EU500 | K21: 17744730 | L21: 0.85 | M21: 1.1903663e+10 | N21: 50.35 | O21: 1 | P21: 1.1626565e+10 | Q21: 50101010 | R21: 5010 | S21: 3.3115124 | U21: B | V21: Amber | W21: 0 | X21: 0 | Y21: Green | Z21: Green | AA21: Green | AB21: Green | AC21: Green | AD21: Green | AE21: Green | AG21: 0.05 | AJ21: 0 | AK21: F | AM21: F | AN21: F | AO21: F | AP21: Services | AQ21: 0.01 | AR21: 0 | AS21: 0 | AT21: 0 | AU21: 2.375 | AV21: 2.777 | AW21: 515.72006 | AX21: 1.5 | AY21: F | AZ21: 1 | BA21: 0 | BB21: ES | BC21: 0 | BD21: 0 | BE21: 0 | BU21: exclude_fossil_fuel | CD21: exclude_nuclear_power | CI21: 2.576 | CK21: Yes | CL21: exclude_fossil_fuel; exclude_nuclear_power | CM21: 3.3115124 | CN21: 3.1 | CO21: 3.2057562 | CP21: -0.18 | CQ21: 3.0257562 | CR21: 644.98569
A22: 21 | B22: ADDT.B-SE | C22: ADDTECH AB CLASS B | D22: SE0014781795 | E22: XSTO | F22: 259908230 | G22: 30.30293 | H22: SEK | I22: 7.8759809e+09 | J22: EU500 | K22: 8983765.4 | L22: 1 | M22: 7.8759809e+09 | N22: 293.4 | O22: 0.09077334 | P22: 6.9221094e+09 | Q22: 50202010 | R22: 5020 | S22: 1.7347787 | U22: Score not available | V22: Green | W22: 0 | X22: 0 | Y22: Green | Z22: Green | AA22: Green | AB22: Green | AC22: Green | AD22: Green | AE22: Green | AF22: 0 | AG22: 0 | AH22: 0 | AJ22: 0 | AK22: F | AM22: F | AN22: F | AO22: F | AQ22: 0 | AR22: 0 | AS22: 0 | AT22: 0.05 | AU22: 1.814 | AV22: 2.231 | AW22: 135.06604 | AX22: 1.5 | AY22: G | AZ22: 1 | BA22: 0 | BB22: SE | BC22: 0 | BD22: 0 | BE22: 0 | CH22: exclude_military_equipment | CI22: 2.0225 | CK22: Yes | CL22: exclude_military_equipment | CM22: 1.7347787 | CN22: 3.1 | CO22: 2.4173893 | CP22: 0.3 | CQ22: 2.7173893 | CR22: 350.98887
A23: 22 | B23: ADEN-CH | C23: ADECCO GROUP AG | D23: CH0012138605 | E23: XSWX | F23: 168426560 | G23: 24.5832 | H23: CHF | I23: 4.1404638e+09 | J23: EU500 | K23: 25898272 | L23: 0.85 | M23: 3.5193942e+09 | N23: 22 | O23: 1.0763104 | P23: 3.3899222e+09 | Q23: 50205025 | R23: 5020 | S23: 1.7457422 | T23: 1.77 | U23: A- | V23: Green | W23: 0 | X23: 0 | Y23: Green | Z23: Green | AA23: Green | AB23: RED | AC23: Green | AD23: Green | AE23: Green | AF23: 0 | AG23: 0.01 | AH23: 0 | AJ23: 0 | AK23: F | AM23: F | AN23: F | AO23: F | AP23: Services | AQ23: 0.01 | AR23: 0 | AS23: 0 | AT23: 0 | AU23: 2.279 | AV23: 3.307 | AW23: 73.669675 | AX23: 1.5 | AY23: N | AZ23: 0 | BA23: 0 | BB23: CH | BC23: 0 | BD23: 0 | BE23: 0 | BO23: exclude_nuclear_weapons_inside_npt | BU23: exclude_fossil_fuel | CD23: exclude_nuclear_power | CI23: 2.793 | CK23: Yes | CL23: exclude_nuclear_weapons_inside_npt; exclude_fossil_fuel; exclude_nuclear_power | CM23: 1.7457422 | CN23: 1.77 | CO23: 1.7578711 | CP23: -0.24 | CQ23: 1.5178711 | CR23: 350.98887
A24: 23 | B24: ADS-DE | C24: ADIDAS AG | D24: DE000A1EWWW0 | E24: XETR | F24: 180000000 | G24: 245.9 | H24: EUR | I24: 44262000000 | J24: EU500 | K24: 95465481 | L24: 1 | M24: 44262000000 | N24: 202.3 | O24: 1 | P24: 36414000000 | Q24: 40204025 | R24: 4020 | S24: 1.7444715 | U24: A | V24: Green | W24: 0 | X24: 0 | Y24: Green | Z24: Green | AA24: Green | AB24: Green | AC24: Green | AD24: Green | AE24: Green | AF24: 0 | AG24: 0 | AH24: 0 | AJ24: 0 | AK24: F | AM24: F | AN24: F | AO24: F | AQ24: 0 | AR24: 0 | AS24: 0 | AT24: 0 | AU24: 2.352 | AV24: 2.749 | AW24: 156.19655 | AX24: 1.5 | AY24: C | AZ24: 1 | BA24: 0 | BB24: DE | BC24: 0 | BD24: 0 | BE24: 0 | CI24: 2.5505 | CK24: No | CM24: 1.7444715 | CN24: 3.1 | CO24: 2.4222358 | CP24: -0.3 | CQ24: 2.1222358 | CR24: 89.792933
A25: 24 | B25: ADM-GB | C25: ADMIRAL GROUP PLC | D25: GB00B02J6398 | E25: XLON | F25: 306304700 | G25: 33.85041 | H25: GBX | I25: 1.036854e+10 | J25: EU500 | K25: 10015140 | L25: 0.7 | M25: 7.2579778e+09 | N25: 3130 | O25: 0.01160026 | P25: 7.7850922e+09 | Q25: 30302025 | R25: 3030 | S25: 1.998809 | T25: 2.7 | U25: C | V25: Green | W25: 0 | X25: 0 | Y25: Green | Z25: Green | AA25: Green | AB25: Green | AC25: Green | AD25: Green | AE25: Green | AF25: 0 | AG25: 0 | AH25: 0 | AJ25: 0 | AK25: F | AM25: F | AN25: F | AO25: F | AQ25: 0 | AR25: 0 | AS25: 0 | AT25: 0 | AU25: 1.88 | AV25: 2.7 | AW25: 0.37512065 | AX25: 1.5 | AY25: K | AZ25: 0 | BA25: 0 | BB25: GB | BC25: 0 | BD25: 0 | BE25: 0 | CI25: 2.29 | CK25: No | CM25: 1.998809 | CN25: 2.7 | CO25: 2.3494045 | CP25: 0 | CQ25: 2.3494045 | CR25: 324.26126
A26: 25 | B26: ADBE-US | C26: ADOBE INC | D26: US00724F1012 | E26: XNGS | F26: 435309140 | G26: 424.9833 | H26: USD | I26: 1.8499911e+11 | J26: NA500 | K26: 1.7556593e+09 | L26: 1 | M26: 1.8499911e+11 | N26: 350.91 | O26: 0.8797009 | P26: 1.3437812e+11 | Q26: 10101015 | R26: 1010 | S26: 1.7351096 | T26: 2.7 | U26: D | V26: Green | W26: 0 | X26: 0 | Y26: Green | Z26: Green | AA26: Green | AB26: Green | AC26: Green | AD26: Green | AE26: Green | AF26: 0 | AG26: 0 | AH26: 0 | AJ26: 0 | AK26: F | AM26: F | AN26: F | AO26: F | AQ26: 0 | AR26: 0 | AS26: 0 | AT26: 0 | AU26: 2.872 | AV26: 3.215 | AW26: 2.4645519 | AX26: 1.5 | AY26: J | AZ26: 0 | BA26: 0 | BB26: US | BC26: 0 | BD26: 0 | BE26: 0 | CI26: 3.0435 | CK26: No | CM26: 1.7351096 | CN26: 2.7 | CO26: 2.2175548 | CP26: 0.18 | CQ26: 2.3975548 | CR26: 33.625121
A27: 26 | B27: ADP-FR | C27: ADP | D27: FR0010340141 | E27: XPAR | F27: 98960602 | G27: 102.7 | H27: EUR | I27: 1.0163254e+10 | J27: EU500 | K27: 10050109 | L27: 0.3 | M27: 3.0489761e+09 | N27: 98.85 | O27: 1 | P27: 2.9346767e+09 | Q27: 50206060 | R27: 5020 | S27: 1.7486175 | U27: A | V27: Green | W27: 0 | X27: 0.05 | Y27: Green | Z27: Green | AA27: Green | AB27: Green | AC27: Green | AD27: Green | AE27: Green | AF27: 0 | AG27: 0 | AH27: 0 | AJ27: 0 | AK27: F | AM27: F | AN27: F | AO27: F | AQ27: 0 | AR27: 0 | AS27: 0 | AT27: 0 | AU27: 2.229 | AV27: 3.082 | AW27: 1046.2147 | AX27: 1.6 | AY27: H | AZ27: 1 | BA27: 0 | BB27: FR | BC27: 0 | BD27: 0 | BE27: 0 | CI27: 2.6555 | CK27: No | CM27: 1.7486175 | CN27: 3.1 | CO27: 2.4243087 | CP27: -0.3 | CQ27: 2.1243087 | CR27: 350.98887
A28: 27 | B28: 3269-JP | C28: ADVANCE RESIDENCE IN | D28: JP3047160001 | E28: XTKS | F28: 2866000 | G28: 917.7247 | H28: JPY | I28: 2.630199e+09 | J28: AS500 | K28: 5051251.1 | L28: 1 | M28: 2.630199e+09 | N28: 148100 | O28: 0.00613973 | P28: 2.6060366e+09 | Q28: 35102040 | R28: 3510 | S28: 3.0916319 | U28: A | V28: Green | W28: 0 | X28: 0 | Y28: Green | Z28: Green | AA28: Green | AB28: Green | AC28: Green | AD28: Green | AE28: Green | AF28: 0 | AG28: 0 | AH28: 0 | AJ28: 0 | AK28: F | AM28: F | AN28: F | AO28: F | AQ28: 0 | AR28: 0 | AS28: 0 | AT28: 0 | AU28: Not Collected | AV28: Not Collected | AW28: 6.8662207 | AX28: 0 | AY28: L | AZ28: 1 | BA28: 0 | BB28: JP | BC28: 0 | BD28: 0 | BE28: 0 | CK28: No | CM28: 3.0916319 | CN28: 3.1 | CO28: 3.0958159 | CP28: -0.3 | CQ28: 2.7958159 | CR28: 23.753721
A29: 28 | B29: AMD-US | C29: ADVANCED MICRO DEV. | D29: US0079031078 | E29: XNGS | F29: 1620477900 | G29: 106.0163 | H29: USD | I29: 1.7179707e+11 | J29: NA500 | K29: 4.5505962e+09 | L29: 1 | M29: 1.7179707e+11 | N29: 94.5 | O29: 0.8797009 | P29: 1.3471314e+11 | Q29: 10102010 | R29: 1010 | S29: 3.3943824 | U29: B | V29: Green | W29: 0 | X29: 0 | Y29: Green | Z29: Green | AA29: Green | AB29: Green | AC29: Green | AD29: Green | AE29: Green | AF29: 0 | AG29: 0 | AH29: 0 | AJ29: 0 | AK29: F | AM29: F | AN29: F | AO29: F | AQ29: 0 | AR29: 0 | AS29: 0 | AT29: 0 | AU29: 2.578 | AV29: 3.658 | AW29: 99.328746 | AX29: 1.5 | AY29: C | AZ29: 1 | BA29: 0 | BB29: US | BC29: 0 | BD29: 0 | BE29: 0 | CI29: 3.118 | CK29: No | CM29: 3.3943824 | CN29: 3.1 | CO29: 3.2471912 | CP29: -0.18 | CQ29: 3.0671912 | CR29: 33.625121
A30: 29 | B30: 6857-JP | C30: ADVANTEST CORP | D30: JP3122400009 | E30: XTKS | F30: 766141240 | G30: 61.58668 | H30: JPY | I30: 4.7184095e+10 | J30: AS500 | K30: 9.2335989e+08 | L30: 1 | M30: 4.7184095e+10 | N30: 5909 | O30: 0.00613973 | P30: 2.7795347e+10 | Q30: 10102020 | R30: 1010 | S30: 1.9966534 | T30: 3.1 | U30: B | V30: Green | W30: 0 | X30: 0 | Y30: Green | Z30: Green | AA30: Green | AB30: Green | AC30: Green | AD30: Green | AE30: Green | AF30: 0 | AG30: 0 | AH30: 0 | AJ30: 0 | AK30: F | AM30: F | AN30: F | AO30: F | AQ30: 0 | AR30: 0 | AS30: 0 | AT30: 0 | AU30: 2.049 | AV30: 1.978 | AW30: 39.208876 | AX30: 1.5 | AY30: C | AZ30: 1 | BA30: 0 | BB30: JP | BC30: 0 | BD30: 0 | BE30: 0 | CI30: 2.0135 | CK30: No | CM30: 1.9966534 | CN30: 3.1 | CO30: 2.5483267 | CP30: -0.18 | CQ30: 2.3683267 | CR30: 33.625121
A31: 30 | B31: ADYEN-NL | C31: ADYEN | D31: NL0012969182 | E31: XAMS | F31: 31485187 | G31: 1787 | H31: EUR | I31: 56264029169 | J31: EU500 | K31: 1.0768117e+08 | L31: 0.95 | M31: 5.3450828e+10 | N31: 1419.8 | O31: 1 | P31: 4.2467535e+10 | Q31: 50205015 | R31: 5020 | S31: 3.4 | U31: F | V31: Green | W31: 0 | X31: 0 | Y31: Green | Z31: Green | AA31: Green | AB31: Green | AC31: Green | AD31: Green | AE31: Green | AF31: 0 | AG31: 0 | AH31: 0 | AJ31: 0 | AK31: F | AM31: F | AN31: F | AO31: F | AQ31: 0 | AR31: 0 | AS31: 0 | AT31: 0 | AU31: 1.867 | AV31: 2.238 | AW31: 8.867792 | AX31: 2.2 | AY31: K | AZ31: 0 | BA31: 0 | BB31: NL | BC31: 0 | BD31: 0 | BE31: 0 | CI31: 2.0525 | CK31: No | CM31: 3.4 | CN31: 3.1 | CO31: 3.25 | CP31: 0.3 | CQ31: 3.55 | CR31: 350.98887
A32: 31 | B32: AED-BE | C32: AEDIFICA | D32: BE0003851681 | E32: XBRU | F32: 47550119 | G32: 61.3 | H32: EUR | I32: 2.9148223e+09 | J32: EU500 | K32: 3337881.7 | L32: 1 | M32: 2.9148223e+09 | N32: 64.1 | O32: 1 | P32: 3.0479626e+09 | Q32: 35102010 | R32: 3510 | S32: 2.9403972 | U32: D | V32: Green | W32: 0 | X32: 0 | Y32: Green | Z32: Green | AA32: Green | AB32: Green | AC32: Green | AD32: Green | AE32: Green | AF32: 0 | AG32: 0 | AH32: 0 | AJ32: 0 | AK32: F | AM32: F | AN32: F | AO32: F | AQ32: 0 | AR32: 0 | AS32: 0 | AT32: 0 | AU32: 2.182 | AV32: 2.199 | AW32: 9.2750313 | AX32: 1.5 | AY32: L | AZ32: 1 | BA32: 0 | BB32: BE | BC32: 0 | BD32: 0 | BE32: 0 | CI32: 2.1905 | CK32: No | CM32: 2.9403972 | CN32: 3.1 | CO32: 3.0201986 | CP32: 0.18 | CQ32: 3.2001986 | CR32: 23.753721
A33: 32 | B33: AGN-NL | C33: AEGON | D33: BMG0112X1056 | E33: XAMS | F33: 1652797432 | G33: 5.832 | H33: EUR | I33: 9.6391146e+09 | J33: EU500 | K33: 27259477 | L33: 0.8 | M33: 7.7112917e+09 | N33: 5.372 | O33: 1 | P33: 7.1030622e+09 | Q33: 30301010 | R33: 3030 | S33: 3.4 | U33: D | V33: Green | W33: 0 | X33: 0 | Y33: Green | Z33: Green | AA33: Green | AB33: Green | AC33: Green | AD33: Green | AE33: Green | AF33: 0 | AG33: 0 | AH33: 0 | AJ33: 0 | AK33: F | AM33: F | AN33: F | AO33: F | AQ33: 0 | AR33: 0 | AS33: 0 | AT33: 0 | AU33: 2.142 | AV33: 3.156 | AW33: 205.29609 | AX33: 1.5 | AY33: K | AZ33: 0 | BA33: 0 | BB33: BM | BC33: 0 | BD33: 0 | BE33: 0 | CI33: 2.649 | CK33: No | CM33: 3.4 | CN33: 3.1 | CO33: 3.25 | CP33: 0.18 | CQ33: 3.43 | CR33: 324.26126
A34: 33 | B34: AENA-ES | C34: AENA SME | D34: ES0105046009 | E34: XMAD | F34: 150000000 | G34: 211.4 | H34: EUR | I34: 31710000000 | J34: EU500 | K34: 27930489 | L34: 0.5 | M34: 15855000000 | N34: 212 | O34: 1 | P34: 15900000000 | Q34: 50206060 | R34: 5020 | S34: 1.7467491 | U34: A- | V34: Green | W34: 0 | X34: 0.05 | Y34: Green | Z34: Green | AA34: Green | AB34: Green | AC34: Green | AD34: Green | AE34: Green | AF34: 0 | AG34: 0 | AH34: 0 | AJ34: 0 | AK34: F | AM34: F | AN34: F | AO34: F | AQ34: 0 | AR34: 0 | AS34: 0 | AT34: 0 | AU34: 2.876 | AV34: 3.212 | AW34: 129.80711 | AX34: 1.5 | AY34: H | AZ34: 1 | BA34: 0 | BB34: ES | BC34: 0 | BD34: 0 | BE34: 0 | CI34: 3.044 | CK34: No | CM34: 1.7467491 | CN34: 3.1 | CO34: 2.4233745 | CP34: -0.24 | CQ34: 2.1833745 | CR34: 350.98887
A35: 34 | B35: 8267-JP | C35: AEON CO LTD | D35: JP3388200002 | E35: XTKS | F35: 871924560 | G35: 23.31724 | H35: JPY | I35: 2.0330874e+10 | J35: AS500 | K35: 41076025 | L35: 1 | M35: 2.0330874e+10 | N35: 3929 | O35: 0.00613973 | P35: 2.1033435e+10 | Q35: 45201010 | R35: 4520 | S35: 1.8587394 | T35: 2.7 | U35: A | V35: Green | W35: 0 | X35: 0.05 | Y35: Green | Z35: Green | AA35: Green | AB35: Green | AC35: Green | AD35: Green | AE35: Green | AF35: 0 | AG35: 0 | AH35: 0 | AJ35: 0 | AK35: F | AM35: F | AN35: F | AO35: F | AQ35: 0 | AR35: 0 | AS35: 0 | AT35: 0 | AU35: 1.821 | AV35: 1.801 | AW35: 190.21829 | AX35: 1.5 | AY35: G | AZ35: 1 | BA35: 0 | BB35: JP | BC35: 0 | BD35: 0 | BE35: 0 | CI35: 1.811 | CJ35: exclude_sg_bottom_10 | CK35: Yes | CL35: exclude_sg_bottom_10 | CM35: 1.8587394 | CN35: 2.7 | CO35: 2.2793697 | CP35: -0.3 | CQ35: 1.9793697 | CR35: 414.93168
A36: 35 | B36: AER-US | C36: AERCAP HOLDINGS NV | D36: NL0000687663 | E36: XNYS | F36: 202493160 | G36: 97.24534 | H36: USD | I36: 1.9691516e+10 | J36: NA500 | K36: 97640596 | L36: 1 | M36: 1.9691516e+10 | N36: 95.75 | O36: 0.8797009 | P36: 1.7056274e+10 | Q36: 50206050 | R36: 5020 | S36: 3.4 | U36: D- | V36: Green | W36: 0 | X36: 0 | Y36: Green | Z36: Green | AA36: Green | AB36: Green | AC36: Green | AD36: Green | AE36: Green | AF36: 0 | AG36: 0 | AH36: 0 | AJ36: 0 | AK36: F | AM36: F | AN36: F | AO36: F | AQ36: 0 | AR36: 0 | AS36: 0 | AT36: 0 | AU36: 1.81 | AV36: 2.672 | AW36: 772.65119 | AX36: 1.5 | AY36: K | AZ36: 0 | BA36: 0 | BB36: NL | BC36: 0 | BD36: 0 | BE36: 0 | CI36: 2.241 | CK36: No | CM36: 3.4 | CN36: 3.1 | CO36: 3.25 | CP36: 0.24 | CQ36: 3.49 | CR36: 350.98887
A37: 36 | B37: AFRM-US | C37: AFFIRM HLDNG CLASS A | D37: US00827B1061 | E37: XNGS | F37: 277254760 | G37: 65.56672 | H37: USD | I37: 1.8178685e+10 | J37: NA500 | K37: 4.4687727e+08 | L37: 1 | M37: 1.8178685e+10 | N37: 40.78 | O37: 0.8797009 | P37: 9.9462935e+09 | Q37: 50205015 | R37: 5020 | S37: 3.4 | U37: F | V37: Green | W37: 0 | X37: 0 | Y37: Green | Z37: Green | AA37: Green | AB37: Green | AC37: Green | AD37: Green | AE37: Green | AF37: 0 | AG37: 0 | AH37: 0 | AJ37: 0 | AK37: F | AM37: F | AN37: F | AO37: F | AQ37: 0 | AR37: 0 | AS37: 0 | AT37: 0 | AU37: 1.916 | AV37: 3.17 | AW37: 40.510005 | AX37: 1.5 | AY37: K | AZ37: 0 | BA37: 0 | BB37: US | BC37: 0 | BD37: 0 | BE37: 0 | CI37: 2.543 | CK37: No | CM37: 3.4 | CN37: 3.1 | CO37: 3.25 | CP37: 0.3 | CQ37: 3.55 | CR37: 350.98887
A38: 37 | B38: AFL-US | C38: AFLAC INCORPORATED | D38: US0010551028 | E38: XNYS | F38: 555528440 | G38: 97.71401 | H38: USD | I38: 5.4282912e+10 | J38: NA500 | K38: 1.9706253e+08 | L38: 0.9 | M38: 4.885462e+10 | N38: 108.51 | O38: 0.8797009 | P38: 4.7725843e+10 | Q38: 30301010 | R38: 3030 | S38: 3.4 | T38: 1.5 | U38: C | V38: Green | W38: 0 | X38: 0 | Y38: Green | Z38: Green | AA38: Green | AB38: Green | AC38: Green | AD38: Green | AE38: Green | AF38: 0 | AG38: 0 | AH38: 0 | AJ38: 0 | AK38: F | AM38: F | AN38: F | AO38: F | AQ38: 0 | AR38: 0 | AS38: 0 | AT38: 0 | AU38: 1.885 | AV38: 2.718 | AW38: 194.35545 | AX38: 1.5 | AY38: K | AZ38: 0 | BA38: 0 | BB38: US | BC38: 0 | BD38: 0 | BE38: 0 | CI38: 2.3015 | CK38: No | CM38: 3.4 | CN38: 1.5 | CO38: 2.45 | CP38: 0 | CQ38: 2.45 | CR38: 324.26126
A39: 38 | B39: AGS-BE | C39: AGEAS | D39: BE0974264930 | E39: XBRU | F39: 187971187 | G39: 51 | H39: EUR | I39: 9586530537 | J39: EU500 | K39: 17348500 | L39: 0.8 | M39: 7.6692244e+09 | N39: 53 | O39: 1 | P39: 7.9699783e+09 | Q39: 30301010 | R39: 3030 | S39: 3.4 | T39: 2.39 | U39: B | V39: Green | W39: 0 | X39: 0 | Y39: Green | Z39: Green | AA39: Green | AB39: Green | AC39: Green | AD39: Green | AE39: Green | AF39: 0 | AG39: 0 | AH39: 0 | AJ39: 0 | AK39: F | AM39: F | AN39: F | AO39: F | AQ39: 0 | AR39: 0 | AS39: 0 | AT39: 0 | AU39: 2.058 | AV39: 3.091 | AW39: 431.53002 | AX39: 1.5 | AY39: K | AZ39: 0 | BA39: 0 | BB39: BE | BC39: 0 | BD39: 0 | BE39: 0 | CI39: 2.5745 | CK39: No | CM39: 3.4 | CN39: 2.39 | CO39: 2.895 | CP39: -0.18 | CQ39: 2.715 | CR39: 324.26126
A40: 39 | B40: A-US | C40: AGILENT TECHNOLOGIES | D40: US00846U1016 | E40: XNYS | F40: 285289580 | G40: 129.4787 | H40: USD | I40: 3.6938924e+10 | J40: NA500 | K40: 2.2697034e+08 | L40: 1 | M40: 3.6938924e+10 | N40: 105.19 | O40: 0.8797009 | P40: 2.6399482e+10 | Q40: 20102010 | R40: 2010 | S40: 1.7389865 | T40: 1.5 | U40: C | V40: Green | W40: 0 | X40: 0 | Y40: Green | Z40: Green | AA40: Green | AB40: Green | AC40: Green | AD40: Green | AE40: Green | AF40: 0 | AG40: 0 | AH40: 0 | AJ40: 0 | AK40: F | AM40: F | AN40: F | AO40: F | AQ40: 0 | AR40: 0 | AS40: 0 | AT40: 0 | AU40: 2.312 | AV40: 3.606 | AW40: 27.531726 | AX40: 1.5 | AY40: C | AZ40: 1 | BA40: 0 | BB40: US | BC40: 0 | BD40: 0 | BE40: 0 | CI40: 2.959 | CK40: No | CM40: 1.7389865 | CN40: 1.5 | CO40: 1.6194932 | CP40: 0 | CQ40: 1.6194932 | CR40: 50.951644
A41: 40 | B41: AGL-AU | C41: AGL ENERGY LTD | D41: AU000000AGL7 | E41: XASX | F41: 672747250 | G41: 6.439024 | H41: AUD | I41: 4.3318357e+09 | J41: AS500 | K41: 11949123 | L41: 1 | M41: 4.3318357e+09 | N41: 10.32 | O41: 0.55671538 | P41: 3.8651366e+09 | Q41: 65102000 | R41: 6510 | S41: 3.4 | T41: 2 | U41: C | V41: Green | W41: 0 | X41: 0 | Y41: Green | Z41: Green | AA41: Green | AB41: Green | AC41: Green | AD41: Green | AE41: Green | AF41: 0.6384 | AG41: 0.845 | AH41: 0.6504 | AJ41: 0 | AK41: F | AM41: F | AN41: F | AO41: F | AQ41: 0 | AR41: 0 | AS41: 0 | AT41: 0 | AU41: 2.786 | AV41: 3.269 | AW41: 9435.221 | AX41: 4.6 | AY41: D | AZ41: 1 | BA41: 0 | BB41: AU | BC41: 0 | BD41: 0 | BE41: 0 | BT41: exclude_coal_mining | BU41: exclude_fossil_fuel | BV41: exclude_thermal_power | CI41: 3.0275 | CK41: Yes | CL41: exclude_coal_mining; exclude_fossil_fuel; exclude_thermal_power | CM41: 3.4 | CN41: 2 | CO41: 2.7 | CP41: 0 | CQ41: 2.7 | CR41: 1003.2865
A42: 41 | B42: AEM-CA | C42: AGNICO EAGLE MINES | D42: CA0084741085 | E42: XTSE | F42: 502936920 | G42: 92.10251 | H42: CAD | I42: 4.6321753e+10 | J42: NA500 | K42: 78266196 | L42: 1 | M42: 4.6321753e+10 | N42: 164.26 | O42: 0.63445738 | P42: 5.2414059e+10 | Q42: 55103025 | R42: 5510 | S42: 2.8010721 | T42: 3.1 | U42: C | V42: Green | W42: 0 | X42: 0 | Y42: Green | Z42: Green | AA42: Green | AB42: Green | AC42: Green | AD42: Green | AE42: Green | AF42: 0 | AG42: 0 | AH42: 0 | AJ42: 0 | AK42: F | AM42: F | AN42: F | AO42: F | AQ42: 0 | AR42: 0 | AS42: 0 | AT42: 0 | AU42: 2.326 | AV42: 2.609 | AW42: 127.90586 | AX42: 3.4 | AY42: B | AZ42: 1 | BA42: 0 | BB42: CA | BC42: 0 | BD42: 0 | BE42: 0 | CI42: 2.4675 | CK42: No | CM42: 2.8010721 | CN42: 3.1 | CO42: 2.9505361 | CP42: 0 | CQ42: 2.9505361 | CR42: 1318.4572
A43: 42 | B43: AD-NL | C43: AHOLD DEL | D43: NL0011794037 | E43: XAMS | F43: 920493634 | G43: 33.63 | H43: EUR | I43: 3.0956201e+10 | J43: EU500 | K43: 71894765 | L43: 1 | M43: 3.0956201e+10 | N43: 33.85 | O43: 1 | P43: 3.115871e+10 | Q43: 45201010 | R43: 4520 | S43: 1.9797276 | T43: 1.5 | U43: A- | V43: Green | W43: 0 | X43: 0.05 | Y43: Green | Z43: Green | AA43: Green | AB43: Green | AC43: Green | AD43: Green | AE43: Green | AF43: 0 | AG43: 0.013 | AH43: 0 | AJ43: 0 | AK43: F | AM43: F | AN43: F | AO43: F | AQ43: 0 | AR43: 0 | AS43: 0 | AT43: 0 | AU43: 2.339 | AV43: 2.823 | AW43: 1458.5003 | AX43: 1.8 | AY43: G | AZ43: 1 | BA43: 0 | BB43: NL | BC43: 0 | BD43: 0 | BE43: 0 | BU43: exclude_fossil_fuel | CI43: 2.581 | CK43: Yes | CL43: exclude_fossil_fuel | CM43: 1.9797276 | CN43: 1.5 | CO43: 1.7398638 | CP43: -0.24 | CQ43: 1.4998638 | CR43: 414.93168
A44: 43 | B44: 1299-HK | C44: AIA | D44: HK0000069689 | E44: XHKG | F44: 10694194000 | G44: 7.140667 | H44: HKD | I44: 7.6363678e+10 | J44: AS500 | K44: 2.2426901e+08 | L44: 1 | M44: 7.6363678e+10 | N44: 52.2 | O44: 0.11342884 | P44: 6.3320167e+10 | Q44: 30301010 | R44: 3030 | S44: 1.997281 | T44: 2.39 | U44: C | V44: Green | W44: 0 | X44: 0 | Y44: Green | Z44: Green | AA44: Green | AB44: Green | AC44: Green | AD44: Green | AE44: Green | AF44: 0 | AG44: 0 | AH44: 0 | AJ44: 0 | AK44: F | AM44: F | AN44: F | AO44: F | AQ44: 0 | AR44: 0 | AS44: 0 | AT44: 0 | AU44: 2.216 | AV44: 2.327 | AW44: 79.17447 | AX44: 1.5 | AY44: K | AZ44: 0 | BA44: 0 | BB44: HK | BC44: 0 | BD44: 0 | BE44: 0 | CI44: 2.2715 | CK44: No | CM44: 1.997281 | CN44: 2.39 | CO44: 2.1936405 | CP44: 0 | CQ44: 2.1936405 | CR44: 324.26126
A45: 44 | B45: A5G-IE | C45: AIB GROUP PLC | D45: IE00BF0L3536 | E45: XMSM | F45: 2328438575 | G45: 6.34 | H45: EUR | I45: 1.4762301e+10 | J45: EU500 | K45: 28502146 | L45: 0.9 | M45: 1.3286071e+10 | N45: 5.64 | O45: 1 | P45: 1.1819154e+10 | Q45: 30101010 | R45: 3010 | S45: 1.9993471 | T45: 1.5 | U45: B | V45: Green | W45: 0 | X45: 0 | Y45: Green | Z45: Green | AA45: Green | AB45: Green | AC45: Green | AD45: Green | AE45: Green | AF45: 0 | AG45: 0 | AH45: 0 | AJ45: 0 | AK45: F | AM45: F | AN45: F | AO45: F | AQ45: 0 | AR45: 0 | AS45: 0 | AT45: 0 | AU45: 2.486 | AV45: 3.169 | AW45: 92.827047 | AX45: 1.5 | AY45: K | AZ45: 0 | BA45: 0 | BB45: IE | BC45: 0 | BD45: 0 | BE45: 0 | CI45: 2.8275 | CK45: No | CM45: 1.9993471 | CN45: 1.5 | CO45: 1.7496735 | CP45: -0.18 | CQ45: 1.5696735 | CR45: 276.86158
A46: 45 | B46: AI-FR | C46: AIR LIQUIDE | D46: FR0000120073 | E46: XPAR | F46: 578264258 | G46: 178.4 | H46: EUR | I46: 1.0316234e+11 | J46: EU500 | K46: 1.1615652e+08 | L46: 1 | M46: 1.0316234e+11 | N46: 170.6 | O46: 1 | P46: 9.8651882e+10 | Q46: 55201020 | R46: 5520 | S46: 1.8514317 | T46: 3.1 | U46: B | V46: Green | W46: 0 | X46: 0 | Y46: Green | Z46: Green | AA46: Green | AB46: Green | AC46: Green | AD46: Green | AE46: Green | AF46: 0 | AG46: 0.082 | AH46: 0.032 | AI46: Services | AJ46: 0 | AK46: F | AL46: Services | AM46: F | AN46: F | AO46: F | AQ46: 0 | AR46: 0 | AS46: 0 | AT46: 0 | AU46: 2.251 | AV46: 3.322 | AW46: 513.2325 | AX46: 1.8 | AY46: C | AZ46: 1 | BA46: 0 | BB46: FR | BC46: 0 | BD46: 0 | BE46: 0 | BU46: exclude_fossil_fuel | BV46: exclude_thermal_power | BW46: exclude_shale_oil_gas | BZ46: exclude_hydraulic_fracturing | CI46: 2.7865 | CK46: Yes | CL46: exclude_fossil_fuel; exclude_thermal_power; exclude_shale_oil_gas; exclude_hydraulic_fracturing | CM46: 1.8514317 | CN46: 3.1 | CO46: 2.4757158 | CP46: -0.18 | CQ46: 2.2957158 | CR46: 648.3039
A47: 46 | B47: APD-US | C47: AIR PROD & CHEMICALS | D47: US0091581068 | E47: XNYS | F47: 222475660 | G47: 296.4037 | H47: USD | I47: 6.5942609e+10 | J47: NA500 | K47: 4.4648262e+08 | L47: 1 | M47: 6.5942609e+10 | N47: 272.58 | O47: 0.8797009 | P47: 5.3347187e+10 | Q47: 55201020 | R47: 5520 | S47: 2.4415899 | T47: 1.5 | U47: B | V47: Green | W47: 0 | X47: 0 | Y47: Green | Z47: Green | AA47: Green | AB47: Green | AC47: Green | AD47: Green | AE47: Green | AF47: 0 | AG47: 0.05 | AH47: 0.01 | AI47: Services | AJ47: 0 | AK47: F | AL47: Services | AM47: F | AN47: F | AO47: F | AQ47: 0 | AR47: 0 | AS47: 0 | AT47: 0 | AU47: 2.495 | AV47: 3.412 | AW47: 496.47195 | AX47: 2.4 | AY47: C | AZ47: 1 | BA47: 0 | BB47: US | BC47: 0 | BD47: 0 | BE47: 0 | BU47: exclude_fossil_fuel | BV47: exclude_thermal_power | BW47: exclude_shale_oil_gas | BZ47: exclude_hydraulic_fracturing | CI47: 2.9535 | CK47: Yes | CL47: exclude_fossil_fuel; exclude_thermal_power; exclude_shale_oil_gas; exclude_hydraulic_fracturing | CM47: 2.4415899 | CN47: 1.5 | CO47: 1.9707949 | CP47: -0.18 | CQ47: 1.7907949 | CR47: 648.3039
A48: 47 | B48: 4088-JP | C48: AIR WATER INC | D48: JP3160670000 | E48: XTKS | F48: 229755050 | G48: 12.05513 | H48: JPY | I48: 2.769727e+09 | J48: AS500 | K48: 5969574.4 | L48: 1 | M48: 2.769727e+09 | N48: 1828.5 | O48: 0.00613973 | P48: 2.5793442e+09 | Q48: 55201020 | R48: 5520 | S48: 2.646081 | T48: 2.39 | U48: A- | V48: Green | W48: 0 | X48: 0 | Y48: Green | Z48: Green | AA48: Green | AB48: Green | AC48: Green | AD48: Green | AE48: Green | AF48: 0 | AG48: 0.065 | AH48: 0 | AJ48: 0 | AK48: F | AM48: F | AN48: F | AO48: F | AQ48: 0 | AR48: 0 | AS48: 0 | AT48: 0 | AU48: 1.66 | AV48: 1.276 | AW48: 1065.0111 | AX48: 1.5 | AY48: C | AZ48: 1 | BA48: 0 | BB48: JP | BC48: 0 | BD48: 0 | BE48: 0 | BU48: exclude_fossil_fuel | CI48: 1.468 | CJ48: exclude_sg_bottom_10 | CK48: Yes | CL48: exclude_fossil_fuel; exclude_sg_bottom_10 | CM48: 2.646081 | CN48: 2.39 | CO48: 2.5180405 | CP48: -0.24 | CQ48: 2.2780405 | CR48: 648.3039
A49: 48 | B49: ABNB-US | C49: AIRBNB INC. CLASS A | D49: US0090661010 | E49: XNGS | F49: 432876650 | G49: 139.7131 | H49: USD | I49: 6.0478539e+10 | J49: NA500 | K49: 6.4468088e+08 | L49: 1 | M49: 6.0478539e+10 | N49: 113.22 | O49: 0.8797009 | P49: 4.31144e+10 | Q49: 40501015 | R49: 4050 | U49: B | V49: Green | W49: 0 | X49: 0 | Y49: Green | Z49: Green | AA49: Green | AB49: Green | AC49: Green | AD49: Green | AE49: Green | AF49: 0 | AG49: 0 | AH49: 0 | AJ49: 0 | AK49: F | AM49: F | AN49: F | AO49: F | AQ49: 0 | AR49: 0 | AS49: 0 | AT49: 0 | AU49: 1.655 | AV49: 2.596 | AW49: 4.3570114 | AX49: 1.5 | AY49: J | AZ49: 0 | BA49: 0 | BB49: US | BC49: 0 | BD49: 0 | BE49: 0 | CI49: 2.1255 | CK49: No | CM49: 3.4592708 | CN49: 3.1 | CO49: 3.2796354 | CP49: -0.18 | CQ49: 3.0996354 | CR49: 201.88986
A50: 49 | B50: AIR-FR | C50: AIRBUS | D50: NL0000235190 | E50: XPAR | F50: 792283683 | G50: 160 | H50: EUR | I50: 126765389280 | J50: EU500 | K50: 1.8302255e+08 | L50: 0.75 | M50: 95074041960 | N50: 139.26 | O50: 1 | P50: 8.2750069e+10 | Q50: 50201010 | R50: 5020 | S50: 1.999128 | T50: 1.5 | U50: B | V50: Green | W50: 0 | X50: 0 | Y50: Green | Z50: Green | AA50: Green | AB50: RED | AC50: Green | AD50: Green | AE50: Green | AF50: 0 | AG50: 0 | AH50: 0 | AJ50: 0 | AK50: F | AM50: F | AN50: F | AO50: F | AQ50: 0 | AR50: 0 | AS50: 0 | AT50: 0 | AU50: 2.316 | AV50: 2.985 | AW50: 3831.542 | AX50: 1.5 | AY50: C | AZ50: 1 | BA50: 0 | BB50: NL | BC50: 0 | BD50: 0 | BE50: 0 | BI50: exclude_subsector_50201010.0 | BO50: exclude_nuclear_weapons_inside_npt | CI50: 2.6505 | CK50: Yes | CL50: exclude_subsector_50201010.0; exclude_nuclear_weapons_inside_npt | CM50: 1.999128 | CN50: 1.5 | CO50: 1.749564 | CP50: -0.18 | CQ50: 1.569564 | CR50: 350.98887
A51: 50 | B51: 7259-JP | C51: AISIN CORP | D51: JP3102000001 | E51: XTKS | F51: 809023900 | G51: 11.19176 | H51: JPY | I51: 9.0544013e+09 | J51: AS500 | K51: 27390180 | L51: 0.75 | M51: 6.790801e+09 | N51: 1432 | O51: 0.00613973 | P51: 5.3347602e+09 | Q51: 40101025 | R51: 4010 | S51: 1.9346644 | T51: 3.01 | U51: A | V51: Green | W51: 0 | X51: 0 | Y51: Green | Z51: Green | AA51: Green | AB51: Green | AC51: Green | AD51: Green | AE51: Green | AF51: 0 | AG51: 0 | AH51: 0 | AJ51: 0 | AK51: F | AM51: F | AN51: F | AO51: F | AQ51: 0 | AR51: 0 | AS51: 0 | AT51: 0 | AU51: 2.103 | AV51: 2.423 | AW51: 890.0835 | AX51: 1.5 | AY51: C | AZ51: 1 | BA51: 0 | BB51: JP | BC51: 0 | BD51: 0 | BE51: 0 | CI51: 2.263 | CK51: No | CM51: 1.9346644 | CN51: 3.01 | CO51: 2.4723322 | CP51: -0.3 | CQ51: 2.1723322 | CR51: 1319.6522
A52: 51 | B52: 2802-JP | C52: AJINOMOTO COMPANY | D52: JP3119600009 | E52: XTKS | F52: 508314760 | G52: 37.81537 | H52: JPY | I52: 1.9222111e+10 | J52: AS500 | K52: 45779553 | L52: 0.9 | M52: 1.72999e+10 | N52: 2898.5 | O52: 0.00613973 | P52: 8.1413759e+09 | Q52: 45102020 | R52: 4510 | S52: 1.7171817 | T52: 1.77 | U52: A | V52: Green | W52: 0 | X52: 0 | Y52: Green | Z52: Green | AA52: Green | AB52: Green | AC52: Green | AD52: Green | AE52: Green | AF52: 0 | AG52: 0 | AH52: 0 | AJ52: 0 | AK52: F | AM52: F | AN52: F | AO52: F | AQ52: 0 | AR52: 0 | AS52: 0 | AT52: 0 | AU52: 1.97 | AV52: 2.817 | AW52: 311.94705 | AX52: 1.5 | AY52: C | AZ52: 1 | BA52: 0 | BB52: JP | BC52: 0 | BD52: 0 | BE52: 0 | CI52: 2.3935 | CK52: No | CM52: 1.7171817 | CN52: 1.77 | CO52: 1.7435908 | CP52: -0.3 | CQ52: 1.4435908 | CR52: 285.13539
A53: 52 | B53: AKRBP-NO | C53: AKER BP | D53: NO0010345853 | E53: XOSL | F53: 632022210 | G53: 20.48421 | H53: NOK | I53: 1.2946476e+10 | J53: EU500 | K53: 23734562 | L53: 0.5 | M53: 6.4732378e+09 | N53: 217.7 | O53: 0.08324454 | P53: 5.7268595e+09 | Q53: 60101010 | R53: 6010 | S53: 3.3956337 | T53: 3.1 | U53: B | V53: Green | W53: 0 | X53: 0 | Y53: Green | Z53: Green | AA53: Green | AB53: Green | AC53: Green | AD53: Green | AE53: Green | AF53: 0 | AG53: 0.993 | AH53: 0 | AJ53: 0 | AK53: T | AL53: Production | AM53: F | AN53: T | AO53: F | AQ53: 0 | AR53: 0 | AS53: 0 | AT53: 0 | AU53: 2.739 | AV53: 3.107 | AW53: 3284.7473 | AX53: 6 | AY53: B | AZ53: 1 | BA53: 0 | BB53: NO | BC53: 0 | BD53: 0 | BE53: 0 | BU53: exclude_fossil_fuel | BY53: exclude_deepwater_drilling | BZ53: exclude_hydraulic_fracturing | CB53: exclude_oil_gas_extraction_expansion | CI53: 2.923 | CK53: Yes | CL53: exclude_fossil_fuel; exclude_deepwater_drilling; exclude_hydraulic_fracturing; exclude_oil_gas_extraction_expansion | CM53: 3.3956337 | CN53: 3.1 | CO53: 3.2478168 | CP53: -0.18 | CQ53: 3.0678168 | CR53: 2017.1154
A54: 53 | B54: 9926-HK | C54: AKESO INC. | D54: KYG0146B1032 | E54: XHKG | F54: 897575200 | G54: 8.488776 | H54: HKD | I54: 7.6193148e+09 | J54: AS500 | K54: 63184371 | L54: 0.95 | M54: 7.2383491e+09 | N54: 86.95 | O54: 0.11342884 | P54: 8.409836e+09 | Q54: 20103010 | R54: 2010 | S54: 3.4 | U54: F | V54: Green | W54: 0 | X54: 0 | Y54: Green | Z54: Green | AA54: Green | AB54: Green | AC54: Green | AD54: Green | AE54: Green | AF54: 0 | AG54: 0 | AH54: 0 | AJ54: 0 | AK54: F | AM54: F | AN54: F | AO54: F | AQ54: 0 | AR54: 0 | AS54: 0 | AT54: 0 | AU54: Not Collected | AV54: Not Collected | AW54: 44.197151 | AX54: 2.5 | AY54: M | AZ54: 0 | BA54: 0 | BB54: KY | BC54: 0 | BD54: 0 | BE54: 0 | CK54: No | CM54: 3.4 | CN54: 3.1 | CO54: 3.25 | CP54: 0.3 | CQ54: 3.55 | CR54: 50.951644
A55: 54 | B55: AKZA-NL | C55: AKZO NOBEL | D55: NL0013267909 | E55: XAMS | F55: 170784638 | G55: 58.06 | H55: EUR | I55: 9.9157561e+09 | J55: EU500 | K55: 27577279 | L55: 1 | M55: 9.9157561e+09 | N55: 51.44 | O55: 1 | P55: 8.7851618e+09 | Q55: 55201020 | R55: 5520 | S55: 1.9918618 | U55: C | V55: Green | W55: 0 | X55: 0 | Y55: Green | Z55: Green | AA55: Green | AB55: Green | AC55: Green | AD55: Green | AE55: Green | AF55: 0 | AG55: 0.05 | AH55: 0 | AJ55: 0 | AK55: F | AM55: F | AN55: F | AO55: F | AQ55: 0 | AR55: 0 | AS55: 0 | AT55: 0 | AU55: 2.356 | AV55: 3.603 | AW55: 713.70505 | AX55: 1.5 | AY55: C | AZ55: 1 | BA55: 0 | BB55: NL | BC55: 0 | BD55: 0 | BE55: 0 | BU55: exclude_fossil_fuel | CI55: 2.9795 | CK55: Yes | CL55: exclude_fossil_fuel | CM55: 1.9918618 | CN55: 3.1 | CO55: 2.5459309 | CP55: 0 | CQ55: 2.5459309 | CR55: 648.3039
A56: 55 | B56: ALC-CH | C56: ALCON | D56: CH0432492467 | E56: XSWX | F56: 499700000 | G56: 86.38146 | H56: CHF | I56: 43164815562 | J56: EU500 | K56: 63266428 | L56: 1 | M56: 43164815562 | N56: 74.12 | O56: 1.0763104 | P56: 3.9864131e+10 | Q56: 20102015 | R56: 2010 | S56: 3.4 | U56: F | V56: Green | W56: 0 | X56: 0 | Y56: Green | Z56: Green | AA56: Green | AB56: Green | AC56: Green | AD56: Green | AE56: Green | AF56: 0 | AG56: 0 | AH56: 0 | AJ56: 0 | AK56: F | AM56: F | AN56: F | AO56: F | AQ56: 0 | AR56: 0 | AS56: 0 | AT56: 0 | AU56: 2.813 | AV56: 3.153 | AW56: 98.409565 | AX56: 1.6 | AY56: C | AZ56: 1 | BA56: 0 | BB56: CH | BC56: 0 | BD56: 0 | BE56: 0 | CI56: 2.983 | CK56: No | CM56: 3.4 | CN56: 3.1 | CO56: 3.25 | CP56: 0.3 | CQ56: 3.55 | CR56: 50.951644
A57: 56 | B57: ALFA-SE | C57: ALFA LAVAL | D57: SE0000695876 | E57: XSTO | F57: 413326320 | G57: 42.19931 | H57: SEK | I57: 1.7442086e+10 | J57: EU500 | K57: 23907875 | L57: 0.7 | M57: 1.220946e+10 | N57: 390.9 | O57: 0.09077334 | P57: 1.0266327e+10 | Q57: 50202020 | R57: 5020 | S57: 1.7498168 | U57: B | V57: Green | W57: 0 | X57: 0 | Y57: Green | Z57: Green | AA57: Green | AB57: Green | AC57: Green | AD57: Green | AE57: Green | AF57: 0.01 | AG57: 0.2 | AH57: 0 | AJ57: 0 | AK57: F | AM57: F | AN57: F | AO57: F | AP57: Services | AQ57: 0.01 | AR57: 0 | AS57: 0 | AT57: 0 | AU57: 2.324 | AV57: 3.292 | AW57: 2712.3522 | AX57: 1.5 | AY57: C | AZ57: 1 | BA57: 0 | BB57: SE | BC57: 0 | BD57: 0 | BE57: 0 | BT57: exclude_coal_mining | BU57: exclude_fossil_fuel | CD57: exclude_nuclear_power | CI57: 2.808 | CK57: Yes | CL57: exclude_coal_mining; exclude_fossil_fuel; exclude_nuclear_power | CM57: 1.7498168 | CN57: 3.1 | CO57: 2.4249084 | CP57: -0.18 | CQ57: 2.2449084 | CR57: 350.98887
A58: 57 | B58: 2784-JP | C58: ALFRESA HOLDINGS | D58: JP3126340003 | E58: XTKS | F58: 202840000 | G58: 12.61152 | H58: JPY | I58: 2.5581207e+09 | J58: AS500 | K58: 6246761.4 | L58: 0.9 | M58: 2.3023086e+09 | N58: 2086 | O58: 0.00613973 | P58: 2.3380817e+09 | Q58: 20103015 | R58: 2010 | S58: 3.4 | U58: D | V58: Green | W58: 0 | X58: 0 | Y58: Green | Z58: Green | AA58: Green | AB58: Green | AC58: Green | AD58: Green | AE58: Green | AF58: 0 | AG58: 0 | AH58: 0 | AJ58: 0 | AK58: F | AM58: F | AN58: F | AO58: F | AQ58: 0 | AR58: 0 | AS58: 0 | AT58: 0 | AU58: 1.971 | AV58: 1.703 | AW58: 2013.1858 | AX58: 1.5 | AY58: G | AZ58: 1 | BA58: 0 | BB58: JP | BC58: 0 | BD58: 0 | BE58: 0 | CI58: 1.837 | CJ58: exclude_sg_bottom_10 | CK58: Yes | CL58: exclude_sg_bottom_10 | CM58: 3.4 | CN58: 3.1 | CO58: 3.25 | CP58: 0.18 | CQ58: 3.43 | CR58: 50.951644
A59: 58 | B59: ATD-CA | C59: ALIMEN COUCHE-TARD A | D59: CA01626P1484 | E59: XTSE | F59: 948064400 | G59: 47.3139 | H59: CAD | I59: 4.4856624e+10 | J59: NA500 | K59: 66702231 | L59: 0.8 | M59: 3.5885299e+10 | N59: 70.37 | O59: 0.63445738 | P59: 3.3862407e+10 | Q59: 40401030 | R59: 4040 | U59: D | V59: Green | W59: 0 | X59: 0.1 | Y59: Green | Z59: Green | AA59: Green | AB59: Green | AC59: Green | AD59: Green | AE59: Green | AF59: 0 | AG59: 0.747 | AH59: 0 | AJ59: 0 | AK59: F | AM59: F | AN59: F | AO59: F | AQ59: 0 | AR59: 0 | AS59: 0 | AT59: 0 | AU59: 1.586 | AV59: 3 | AW59: 2835.0357 | AX59: 1.6 | AY59: G | AZ59: 1 | BA59: 0 | BB59: CA | BC59: 0 | BD59: 0 | BE59: 0 | BL59: exclude_tobacco_distribution | BU59: exclude_fossil_fuel | CI59: 2.293 | CK59: Yes | CL59: exclude_tobacco_distribution; exclude_fossil_fuel | CM59: 3.4592708 | CN59: 3.1 | CO59: 3.2796354 | CP59: 0.18 | CQ59: 3.4596354 | CR59: 205.31107
A60: 59 | B60: ALV-DE | C60: ALLIANZ SE | D60: DE0008404005 | E60: XETR | F60: 386166700 | G60: 320.2 | H60: EUR | I60: 123650577340 | J60: EU500 | K60: 1.9255735e+08 | L60: 1 | M60: 123650577340 | N60: 337.7 | O60: 1 | P60: 130408494590 | Q60: 30302010 | R60: 3030 | U60: Score not available | V60: Green | W60: 0 | X60: 0 | Y60: Green | Z60: Green | AA60: Green | AB60: Green | AC60: Green | AD60: Green | AE60: Green | AF60: 0 | AG60: 0 | AH60: 0 | AJ60: 0 | AK60: F | AM60: F | AN60: F | AO60: F | AQ60: 0 | AR60: 0 | AS60: 0 | AT60: 0 | AU60: 2.419 | AV60: 2.812 | AW60: 473.80562 | AX60: 1.5 | AY60: K | AZ60: 0 | BA60: 0 | BB60: DE | BC60: 0 | BD60: 0 | BE60: 0 | CI60: 2.6155 | CK60: No | CM60: 3.4592708 | CN60: 3.1 | CO60: 3.2796354 | CP60: 0.3 | CQ60: 3.5796354 | CR60: 324.26126
A61: 60 | B61: ALLN-CH | C61: ALLREAL HOLDING | D61: CH0008837566 | E61: XSWX | F61: 16592821 | G61: 184.1614 | H61: CHF | I61: 3.0557571e+09 | J61: EU500 | K61: 5547061.9 | L61: 0.95 | M61: 2.9029693e+09 | N61: 182 | O61: 1.0763104 | P61: 3.0878256e+09 | Q61: 35101010 | R61: 3510 | S61: 3.2733333 | U61: B | V61: Green | W61: 0 | X61: 0 | Y61: Green | Z61: Green | AA61: Green | AB61: Green | AC61: Green | AD61: Green | AE61: Green | AF61: 0 | AG61: 0 | AH61: 0 | AJ61: 0 | AK61: F | AM61: F | AN61: F | AO61: F | AQ61: 0 | AR61: 0 | AS61: 0 | AT61: 0 | AU61: 1.81 | AV61: 2.576 | AW61: 22.95269 | AX61: 1.5 | AY61: L | AZ61: 1 | BA61: 0 | BB61: CH | BC61: 0 | BD61: 0 | BE61: 0 | CI61: 2.193 | CK61: No | CM61: 3.2733333 | CN61: 3.1 | CO61: 3.1866667 | CP61: -0.18 | CQ61: 3.0066667 | CR61: 23.753721
A62: 61 | B62: ALL-US | C62: ALLSTATE CORPORATION | D62: US0200021014 | E62: XNYS | F62: 264803470 | G62: 177.5801 | H62: USD | I62: 4.7023827e+10 | J62: NA500 | K62: 3.1458174e+08 | L62: 1 | M62: 4.7023827e+10 | N62: 195.5 | O62: 0.8797009 | P62: 4.5541305e+10 | Q62: 30302025 | R62: 3030 | S62: 3.4 | T62: 1.5 | U62: B | V62: Green | W62: 0 | X62: 0 | Y62: Green | Z62: Green | AA62: Green | AB62: Green | AC62: Green | AD62: Green | AE62: Green | AF62: 0 | AG62: 0 | AH62: 0 | AJ62: 0 | AK62: F | AM62: F | AN62: F | AO62: F | AQ62: 0 | AR62: 0 | AS62: 0 | AT62: 0 | AU62: 1.968 | AV62: 3.163 | AW62: 719.01295 | AX62: 1.5 | AY62: K | AZ62: 0 | BA62: 0 | BB62: US | BC62: 0 | BD62: 0 | BE62: 0 | CI62: 2.5655 | CK62: No | CM62: 3.4 | CN62: 1.5 | CO62: 2.45 | CP62: -0.18 | CQ62: 2.27 | CR62: 324.26126
A63: 62 | B63: ALMB-DK | C63: ALM BRAND AS | D63: DK0015250344 | E63: XCSE | F63: 1541140000 | G63: 2.088411 | H63: DKK | I63: 3.2185337e+09 | J63: EU500 | K63: 3702059 | L63: 1 | M63: 3.2185337e+09 | N63: 14.7 | O63: 0.13393335 | P63: 3.0342276e+09 | Q63: 30302010 | R63: 3030 | S63: 3.4 | U63: F | V63: Green | W63: 0 | X63: 0 | Y63: Green | Z63: Green | AA63: Green | AB63: Green | AC63: Green | AD63: Green | AE63: Green | AF63: 0 | AG63: 0 | AH63: 0 | AJ63: 0 | AK63: F | AM63: F | AN63: F | AO63: F | AQ63: 0 | AR63: 0 | AS63: 0 | AT63: 0 | AU63: 1.819 | AV63: 1.83 | AW63: 401.80094 | AX63: 1.5 | AY63: K | AZ63: 0 | BA63: 0 | BB63: DK | BC63: 0 | BD63: 0 | BE63: 0 | CI63: 1.8245 | CJ63: exclude_sg_bottom_10 | CK63: Yes | CL63: exclude_sg_bottom_10 | CM63: 3.4 | CN63: 3.1 | CO63: 3.25 | CP63: 0.3 | CQ63: 3.55 | CR63: 324.26126
A64: 63 | B64: ALNY-US | C64: ALNYLAM PHARMA | D64: US02043Q1076 | E64: XNGS | F64: 129457150 | G64: 239.6844 | H64: USD | I64: 3.1028859e+10 | J64: NA500 | K64: 1.6096057e+08 | L64: 1 | M64: 3.1028859e+10 | N64: 240.01 | O64: 0.8797009 | P64: 2.7333196e+10 | Q64: 20103010 | R64: 2010 | S64: 3.4 | U64: F | V64: Green | W64: 0 | X64: 0 | Y64: Green | Z64: Green | AA64: Green | AB64: Green | AC64: Green | AD64: Green | AE64: Green | AF64: 0 | AG64: 0 | AH64: 0 | AJ64: 0 | AK64: F | AM64: F | AN64: F | AO64: F | AQ64: 0 | AR64: 0 | AS64: 0 | AT64: 0 | AU64: 2.28 | AV64: 3.085 | AW64: 24.322167 | AX64: 1.5 | AY64: M | AZ64: 0 | BA64: 0 | BB64: US | BC64: 0 | BD64: 0 | BE64: 0 | CI64: 2.6825 | CK64: No | CM64: 3.4 | CN64: 3.1 | CO64: 3.25 | CP64: 0.3 | CQ64: 3.55 | CR64: 50.951644
A65: 64 | B65: GOOGL-US | C65: ALPHABET CLASS A | D65: US02079K3059 | E65: XNGS | F65: 5833000000 | G65: 171.8412 | H65: USD | I65: 1002349719600 | J65: NA500 | K65: 5.1514293e+09 | L65: 1 | M65: 1002349719600 | N65: 159.07 | O65: 0.8797009 | P65: 8.1623515e+11 | Q65: 10101020 | R65: 1010 | S65: 1.5814827 | U65: B | V65: RED | W65: 0 | X65: 0 | Y65: Green | Z65: Green | AA65: Green | AB65: Green | AC65: Green | AD65: Green | AE65: Green | AF65: 0 | AG65: 0 | AH65: 0 | AJ65: 0 | AK65: F | AM65: F | AN65: F | AO65: F | AQ65: 0 | AR65: 0 | AS65: 0 | AT65: 0 | AU65: 2.346 | AV65: 2.505 | AW65: 8.7508666 | AX65: 1.5 | AY65: J | AZ65: 0 | BA65: 0 | BB65: US | BC65: 0 | BD65: 0 | BE65: 0 | BJ65: exclude_nbr_red_flag | CI65: 2.4255 | CK65: Yes | CL65: exclude_nbr_red_flag | CM65: 1.5814827 | CN65: 3.1 | CO65: 2.3407413 | CP65: -0.18 | CQ65: 2.1607413 | CR65: 33.625121
A66: 65 | B66: ALQ-AU | C66: ALS LTD | D66: AU000000ALQ6 | E66: XASX | F66: 484874200 | G66: 10.32927 | H66: AUD | I66: 5.0083965e+09 | J66: AS500 | K66: 6314817.6 | L66: 1 | M66: 5.0083965e+09 | N66: 15.14 | O66: 0.55671538 | P66: 4.086845e+09 | Q66: 50205020 | R66: 5020 | S66: 3.4 | U66: F | V66: Green | W66: 0 | X66: 0 | Y66: Green | Z66: Green | AA66: Green | AB66: Green | AC66: Green | AD66: Green | AE66: Green | AF66: 0.05 | AG66: 0.05 | AH66: 0 | AJ66: 0 | AK66: F | AM66: F | AN66: F | AO66: F | AP66: Services | AQ66: 0.01 | AR66: 0 | AS66: 0 | AT66: 0 | AU66: 2.343 | AV66: 3.58 | AW66: 242.61356 | AX66: 1.8 | AY66: M | AZ66: 0 | BA66: 0 | BB66: AU | BC66: 0 | BD66: 0 | BE66: 0 | BT66: exclude_coal_mining | BU66: exclude_fossil_fuel | CD66: exclude_nuclear_power | CI66: 2.9615 | CK66: Yes | CL66: exclude_coal_mining; exclude_fossil_fuel; exclude_nuclear_power | CM66: 3.4 | CN66: 3.1 | CO66: 3.25 | CP66: 0.3 | CQ66: 3.55 | CR66: 350.98887
A67: 66 | B67: ALO-FR | C67: ALSTOM | D67: FR0010220475 | E67: XPAR | F67: 461510538 | G67: 20.09 | H67: EUR | I67: 9.2717467e+09 | J67: EU500 | K67: 23095735 | L67: 0.75 | M67: 6.95381e+09 | N67: 19.33 | O67: 1 | P67: 6.690749e+09 | Q67: 50202010 | R67: 5020 | S67: 1.9980521 | T67: 3.1 | U67: A | V67: Green | W67: 0 | X67: 0 | Y67: Green | Z67: Green | AA67: Green | AB67: Green | AC67: Green | AD67: Green | AE67: Green | AF67: 0 | AG67: 0 | AH67: 0 | AJ67: 0 | AK67: F | AM67: F | AN67: F | AO67: F | AQ67: 0 | AR67: 0 | AS67: 0 | AT67: 0 | AU67: 2.795 | AV67: 3.363 | AW67: 3285.23 | AX67: 1.5 | AY67: C | AZ67: 1 | BA67: 1 | BB67: FR | BC67: 0 | BD67: 0 | BE67: 0 | CI67: 3.079 | CK67: No | CM67: 1.9980521 | CN67: 3.1 | CO67: 2.5490261 | CP67: -0.3 | CQ67: 2.2490261 | CR67: 350.98887
A68: 67 | B68: ATE-FR | C68: ALTEN | D68: FR0000071946 | E68: XPAR | F68: 35266866 | G68: 97.15 | H68: EUR | I68: 3.426176e+09 | J68: EU500 | K68: 3080266.8 | L68: 0.85 | M68: 2.9122496e+09 | N68: 80.85 | O68: 1 | P68: 2.4236272e+09 | Q68: 10101010 | R68: 1010 | S68: 1.7332147 | U68: A- | V68: Green | W68: 0 | X68: 0 | Y68: Green | Z68: Green | AA68: Green | AB68: RED | AC68: Green | AD68: Green | AE68: Green | AF68: 0 | AG68: 0.05 | AH68: 0 | AJ68: 0 | AK68: F | AM68: F | AN68: F | AO68: F | AP68: Services | AQ68: 0.05 | AR68: 0 | AS68: 0 | AT68: 0 | AU68: 2.313 | AV68: 2.73 | AW68: 15.015218 | AX68: 1.5 | AY68: M | AZ68: 0 | BA68: 0 | BB68: FR | BC68: 0 | BD68: 0 | BE68: 0 | BO68: exclude_nuclear_weapons_inside_npt | BU68: exclude_fossil_fuel | CD68: exclude_nuclear_power | CE68: exclude_nuclear_power_revenue | CI68: 2.5215 | CK68: Yes | CL68: exclude_nuclear_weapons_inside_npt; exclude_fossil_fuel; exclude_nuclear_power; exclude_nuclear_power_revenue | CM68: 1.7332147 | CN68: 3.1 | CO68: 2.4166074 | CP68: -0.24 | CQ68: 2.1766074 | CR68: 33.625121
A69: 68 | B69: MO-US | C69: ALTRIA GROUP INC | D69: US02209S1033 | E69: XNYS | F69: 1694813000 | G69: 52.65423 | H69: USD | I69: 8.9239074e+10 | J69: NA500 | K69: 3.9309259e+08 | L69: 1 | M69: 8.9239074e+10 | N69: 57.13 | O69: 0.8797009 | P69: 8.5176746e+10 | Q69: 45103010 | R69: 4510 | S69: 1.7376786 | T69: 1.5 | U69: B | V69: Green | W69: 1 | X69: 0 | Y69: Green | Z69: Green | AA69: Green | AB69: Green | AC69: Green | AD69: Green | AE69: Green | AF69: 0 | AG69: 0 | AH69: 0 | AJ69: 0 | AK69: F | AM69: F | AN69: F | AO69: F | AQ69: 0 | AR69: 0 | AS69: 0 | AT69: 0 | AU69: 1.69 | AV69: 3.341 | AW69: 21.475925 | AX69: 1.5 | AY69: C | AZ69: 1 | BA69: 0 | BB69: US | BC69: 0 | BD69: 0 | BE69: 0 | BI69: exclude_subsector_45103010.0 | BK69: exclude_tobacco_production | CI69: 2.5155 | CK69: Yes | CL69: exclude_subsector_45103010.0; exclude_tobacco_production | CM69: 1.7376786 | CN69: 1.5 | CO69: 1.6188393 | CP69: -0.18 | CQ69: 1.4388393 | CR69: 285.13539
A70: 69 | B70: 6113-JP | C70: AMADA CO LTD | D70: JP3122800000 | E70: XTKS | F70: 341115200 | G70: 9.282769 | H70: JPY | I70: 3.1664936e+09 | J70: AS500 | K70: 11921837 | L70: 0.95 | M70: 3.0081689e+09 | N70: 1317.5 | O70: 0.00613973 | P70: 2.6213474e+09 | Q70: 50204050 | R70: 5020 | S70: 1.9962257 | T70: 3.01 | U70: B | V70: Green | W70: 0 | X70: 0 | Y70: Green | Z70: Green | AA70: Green | AB70: Green | AC70: Green | AD70: Green | AE70: Green | AF70: 0 | AG70: 0 | AH70: 0 | AJ70: 0 | AK70: F | AM70: F | AN70: F | AO70: F | AQ70: 0 | AR70: 0 | AS70: 0 | AT70: 0 | AU70: 1.7 | AV70: 1.483 | AW70: 689.32639 | AX70: 1.5 | AY70: C | AZ70: 1 | BA70: 0 | BB70: JP | BC70: 0 | BD70: 0 | BE70: 0 | CI70: 1.5915 | CJ70: exclude_sg_bottom_10 | CK70: Yes | CL70: exclude_sg_bottom_10 | CM70: 1.9962257 | CN70: 3.01 | CO70: 2.5031129 | CP70: -0.18 | CQ70: 2.3231129 | CR70: 350.98887
A71: 70 | B71: AMS-ES | C71: AMADEUS IT GROUP | D71: ES0109067019 | E71: XMAD | F71: 450499200 | G71: 69.46 | H71: EUR | I71: 31291674432 | J71: EU500 | K71: 42461320 | L71: 1 | M71: 31291674432 | N71: 66.52 | O71: 1 | P71: 29967206784 | Q71: 10101010 | R71: 1010 | S71: 1.7124186 | T71: 3.01 | U71: B | V71: Green | W71: 0 | X71: 0 | Y71: Green | Z71: Green | AA71: Green | AB71: Green | AC71: Green | AD71: Green | AE71: Green | AF71: 0 | AG71: 0 | AH71: 0 | AJ71: 0 | AK71: F | AM71: F | AN71: F | AO71: F | AQ71: 0 | AR71: 0 | AS71: 0 | AT71: 0 | AU71: 2.506 | AV71: 3.136 | AW71: 7.5164737 | AX71: 1.5 | AY71: N | AZ71: 0 | BA71: 0 | BB71: ES | BC71: 0 | BD71: 0 | BE71: 0 | CI71: 2.821 | CK71: No | CM71: 1.7124186 | CN71: 3.01 | CO71: 2.3612093 | CP71: -0.18 | CQ71: 2.1812093 | CR71: 33.625121
A72: 71 | B72: AMZN-US | C72: AMAZON | D72: US0231351067 | E72: XNGS | F72: 10597729500 | G72: 207.1545 | H72: USD | I72: 2.1953674e+12 | J72: NA500 | K72: 7.6793799e+09 | L72: 0.9 | M72: 1.9758306e+12 | N72: 182.12 | O72: 0.8797009 | P72: 1.5280868e+12 | Q72: 40401010 | R72: 4040 | S72: 3.4 | U72: C | V72: RED | W72: 0 | X72: 0 | Y72: Green | Z72: Green | AA72: Green | AB72: Green | AC72: Green | AD72: Green | AE72: Green | AF72: 0 | AG72: 0 | AH72: 0 | AJ72: 0 | AK72: F | AM72: F | AN72: F | AO72: F | AQ72: 0 | AR72: 0 | AS72: 0 | AT72: 0.01 | AU72: 2.039 | AV72: 2.407 | AW72: 43.473184 | AX72: 4.6 | AY72: G | AZ72: 1 | BA72: 0 | BB72: US | BC72: 0 | BD72: 0 | BE72: 0 | BJ72: exclude_nbr_red_flag | CI72: 2.223 | CK72: Yes | CL72: exclude_nbr_red_flag | CM72: 3.4 | CN72: 3.1 | CO72: 3.25 | CP72: 0 | CQ72: 3.25 | CR72: 205.31107
A73: 72 | B73: AMBU.B-DK | C73: AMBU A/S CLASS B | D73: DK0060946788 | E73: XCSE | F73: 234974400 | G73: 18.71929 | H73: DKK | I73: 4.3985539e+09 | J73: EU500 | K73: 7606684.2 | L73: 0.85 | M73: 3.7387708e+09 | N73: 118.5 | O73: 0.13393335 | P73: 3.1699073e+09 | Q73: 20102010 | R73: 2010 | S73: 1.9159909 | T73: 1.5 | U73: D | V73: Green | W73: 0 | X73: 0 | Y73: Green | Z73: Green | AA73: Green | AB73: Green | AC73: Green | AD73: Green | AE73: Green | AF73: 0 | AG73: 0 | AH73: 0 | AJ73: 0 | AK73: F | AM73: F | AN73: F | AO73: F | AQ73: 0 | AR73: 0 | AS73: 0 | AT73: 0 | AU73: 2.627 | AV73: 2.753 | AW73: 110.50637 | AX73: 1.5 | AY73: C | AZ73: 1 | BA73: 0 | BB73: DK | BC73: 0 | BD73: 0 | BE73: 0 | CI73: 2.69 | CK73: No | CM73: 1.9159909 | CN73: 1.5 | CO73: 1.7079955 | CP73: 0.18 | CQ73: 1.8879955 | CR73: 50.951644
A74: 73 | B74: AEE-US | C74: AMEREN CORPORATION | D74: US0236081024 | E74: XNYS | F74: 269906250 | G74: 94.25156 | H74: USD | I74: 2.5439085e+10 | J74: NA500 | K74: 1.3407599e+08 | L74: 1 | M74: 2.5439085e+10 | N74: 99.01 | O74: 0.8797009 | P74: 2.3508615e+10 | Q74: 65102000 | R74: 6510 | U74: Score not available | V74: Green | W74: 0 | X74: 0 | Y74: Green | Z74: Green | AA74: Green | AB74: Green | AC74: Green | AD74: Green | AE74: Green | AF74: 0.2509 | AG74: 0.398 | AH74: 0.256 | AJ74: 0 | AK74: F | AM74: F | AN74: F | AO74: F | AP74: Production | AQ74: 0.116 | AR74: 0 | AS74: 0 | AT74: 0 | AU74: 2.194 | AV74: 2.866 | AW74: 1362.4322 | AX74: 3.9 | AY74: D | AZ74: 1 | BA74: 0 | BB74: US | BC74: 0 | BD74: 0 | BE74: 0 | BT74: exclude_coal_mining | BU74: exclude_fossil_fuel | BV74: exclude_thermal_power | CD74: exclude_nuclear_power | CE74: exclude_nuclear_power_revenue | CI74: 2.53 | CK74: Yes | CL74: exclude_coal_mining; exclude_fossil_fuel; exclude_thermal_power; exclude_nuclear_power; exclude_nuclear_power_revenue | CM74: 3.4592708 | CN74: 3.1 | CO74: 3.2796354 | CP74: 0.3 | CQ74: 3.5796354 | CR74: 1003.2865
A75: 74 | B75: AEP-US | C75: AMERICAN ELECT. PWR. | D75: US0255371017 | E75: XNGS | F75: 533210500 | G75: 100.7461 | H75: USD | I75: 5.3718878e+10 | J75: NA500 | K75: 2.7243376e+08 | L75: 1 | M75: 5.3718878e+10 | N75: 106.58 | O75: 0.8797009 | P75: 4.9993028e+10 | Q75: 65101015 | R75: 6510 | U75: F | V75: Green | W75: 0 | X75: 0 | Y75: Green | Z75: Green | AA75: Green | AB75: Green | AC75: Green | AD75: Green | AE75: Green | AF75: 0.1436 | AG75: 0.227 | AH75: 0.2268 | AJ75: 0 | AK75: F | AM75: F | AN75: F | AO75: F | AP75: Production | AQ75: 0.093 | AR75: 0 | AS75: 0 | AT75: 0 | AU75: 2.566 | AV75: 3.171 | AW75: 1089.2123 | AX75: 6 | AY75: D | AZ75: 1 | BA75: 0 | BB75: US | BC75: 0 | BD75: 0 | BE75: 0 | BT75: exclude_coal_mining | BU75: exclude_fossil_fuel | BV75: exclude_thermal_power | CD75: exclude_nuclear_power | CE75: exclude_nuclear_power_revenue | CI75: 2.8685 | CK75: Yes | CL75: exclude_coal_mining; exclude_fossil_fuel; exclude_thermal_power; exclude_nuclear_power; exclude_nuclear_power_revenue | CM75: 3.4592708 | CN75: 3.1 | CO75: 3.2796354 | CP75: 0.3 | CQ75: 3.5796354 | CR75: 1003.2865
A76: 75 | B76: AXP-US | C76: AMERICAN EXPRESS | D76: US0258161092 | E76: XNYS | F76: 702532100 | G76: 282.5442 | H76: USD | I76: 1.9849637e+11 | J76: NA500 | K76: 7.1582478e+08 | L76: 0.8 | M76: 1.587971e+11 | N76: 255.38 | O76: 0.8797009 | P76: 1.2626357e+11 | Q76: 50205015 | R76: 5020 | S76: 1.7468648 | U76: B | V76: Green | W76: 0 | X76: 0 | Y76: Green | Z76: Green | AA76: Green | AB76: Green | AC76: Green | AD76: Green | AE76: Green | AF76: 0 | AG76: 0 | AH76: 0 | AJ76: 0 | AK76: F | AM76: F | AN76: F | AO76: F | AQ76: 0 | AR76: 0 | AS76: 0 | AT76: 0 | AU76: 1.837 | AV76: 3.49 | AW76: 14.847079 | AX76: 1.5 | AY76: K | AZ76: 0 | BA76: 0 | BB76: US | BC76: 0 | BD76: 0 | BE76: 0 | CI76: 2.6635 | CK76: No | CM76: 1.7468648 | CN76: 3.1 | CO76: 2.4234324 | CP76: -0.18 | CQ76: 2.2434324 | CR76: 350.98887
A77: 76 | B77: AIG-US | C77: AMERICAN INTERN. | D77: US0268747849 | E77: XNYS | F77: 593332950 | G77: 73.3142 | H77: USD | I77: 4.3499731e+10 | J77: NA500 | K77: 2.9130708e+08 | L77: 1 | M77: 4.3499731e+10 | N77: 81.5 | O77: 0.8797009 | P77: 4.2539376e+10 | Q77: 30302010 | R77: 3030 | S77: 3.4 | U77: C | V77: Green | W77: 0 | X77: 0 | Y77: Green | Z77: Green | AA77: Green | AB77: Green | AC77: Green | AD77: Green | AE77: Green | AF77: 0 | AG77: 0 | AH77: 0 | AJ77: 0 | AK77: F | AM77: F | AN77: F | AO77: F | AQ77: 0 | AR77: 0 | AS77: 0 | AT77: 0 | AU77: 1.839 | AV77: 3.136 | AW77: 350.09829 | AX77: 1.5 | AY77: K | AZ77: 0 | BA77: 0 | BB77: US | BC77: 0 | BD77: 0 | BE77: 0 | CI77: 2.4875 | CK77: No | CM77: 3.4 | CN77: 3.1 | CO77: 3.25 | CP77: 0 | CQ77: 3.25 | CR77: 324.26126
A78: 77 | B78: AMT-US | C78: AMERICAN TOWER CORP | D78: US03027X1000 | E78: XNYS | F78: 467289400 | G78: 183.2138 | H78: USD | I78: 8.5613867e+10 | J78: NA500 | K78: 4.2363648e+08 | L78: 1 | M78: 8.5613867e+10 | N78: 217.79 | O78: 0.8797009 | P78: 8.9528004e+10 | Q78: 35102025 | R78: 3510 | U78: D | V78: Green | W78: 0 | X78: 0 | Y78: Green | Z78: Green | AA78: Green | AB78: Green | AC78: Green | AD78: Green | AE78: Green | AF78: 0 | AG78: 0 | AH78: 0 | AJ78: 0 | AK78: F | AM78: F | AN78: F | AO78: F | AQ78: 0 | AR78: 0 | AS78: 0 | AT78: 0 | AU78: 2.11 | AV78: 3.64 | AW78: 38.664667 | AX78: 2.9 | AY78: L | AZ78: 1 | BA78: 0 | BB78: US | BC78: 0 | BD78: 0 | BE78: 0 | CI78: 2.875 | CK78: No | CM78: 3.4592708 | CN78: 3.1 | CO78: 3.2796354 | CP78: 0.18 | CQ78: 3.4596354 | CR78: 23.753721
A79: 78 | B79: AWK-US | C79: AMERICAN WATER WORKS | D79: US0304201033 | E79: XNYS | F79: 194947310 | G79: 126.9058 | H79: USD | I79: 2.4739944e+10 | J79: NA500 | K79: 1.5427474e+08 | L79: 1 | M79: 2.4739944e+10 | N79: 148.83 | O79: 0.8797009 | P79: 2.5523649e+10 | Q79: 65102030 | R79: 6510 | S79: 3.4 | T79: 1.77 | U79: B | V79: Green | W79: 0 | X79: 0 | Y79: Green | Z79: Green | AA79: Green | AB79: Green | AC79: Green | AD79: Green | AE79: Green | AF79: 0 | AG79: 0 | AH79: 0 | AJ79: 0 | AK79: F | AM79: F | AN79: F | AO79: F | AQ79: 0 | AR79: 0 | AS79: 0 | AT79: 0 | AU79: 2.515 | AV79: 2.892 | AW79: 144.72815 | AX79: 2.4 | AY79: E | AZ79: 1 | BA79: 0 | BB79: US | BC79: 0 | BD79: 0 | BE79: 0 | CI79: 2.7035 | CK79: No | CM79: 3.4 | CN79: 1.77 | CO79: 2.585 | CP79: -0.18 | CQ79: 2.405 | CR79: 1003.2865
A80: 79 | B80: AMP-US | C80: AMERIPRISE FINANCIAL | D80: US03076C1062 | E80: XNYS | F80: 96118500 | G80: 507.3936 | H80: USD | I80: 4.8769912e+10 | J80: NA500 | K80: 2.7600854e+08 | L80: 1 | M80: 4.8769912e+10 | N80: 474.45 | O80: 0.8797009 | P80: 4.0117372e+10 | Q80: 30202010 | R80: 3020 | S80: 3.0985171 | T80: 1.5 | U80: C | V80: Green | W80: 0 | X80: 0 | Y80: Green | Z80: Green | AA80: Green | AB80: Green | AC80: Green | AD80: Green | AE80: Green | AF80: 0 | AG80: 0 | AH80: 0 | AJ80: 0 | AK80: F | AM80: F | AN80: F | AO80: F | AQ80: 0 | AR80: 0 | AS80: 0 | AT80: 0 | AU80: 1.814 | AV80: 2.992 | AW80: 424.13839 | AX80: 1.5 | AY80: K | AZ80: 0 | BA80: 0 | BB80: US | BC80: 0 | BD80: 0 | BE80: 0 | CI80: 2.403 | CK80: No | CM80: 3.0985171 | CN80: 1.5 | CO80: 2.2992585 | CP80: 0 | CQ80: 2.2992585 | CR80: 51.827488
A81: 80 | B81: AME-US | C81: AMETEK INC. | D81: US0311001004 | E81: XNYS | F81: 230659380 | G81: 178.087 | H81: USD | I81: 4.1077437e+10 | J81: NA500 | K81: 2.1306063e+08 | L81: 1 | M81: 4.1077437e+10 | N81: 161.36 | O81: 0.8797009 | P81: 3.2741762e+10 | Q81: 50202025 | R81: 5020 | S81: 3.4 | U81: Score not available | V81: Green | W81: 0 | X81: 0 | Y81: Green | Z81: Green | AA81: Green | AB81: Green | AC81: Green | AD81: Green | AE81: Green | AF81: 0 | AG81: 0.05 | AH81: 0 | AI81: Services | AJ81: 0 | AK81: F | AL81: Services | AM81: F | AN81: F | AO81: F | AP81: Services | AQ81: 0.01 | AR81: 0 | AS81: 0 | AT81: 0 | AU81: 1.929 | AV81: 3.13 | AW81: 563.3972 | AX81: 1.5 | AY81: C | AZ81: 1 | BA81: 0 | BB81: US | BC81: 0 | BD81: 0 | BE81: 0 | BU81: exclude_fossil_fuel | BW81: exclude_shale_oil_gas | BZ81: exclude_hydraulic_fracturing | CD81: exclude_nuclear_power | CI81: 2.5295 | CK81: Yes | CL81: exclude_fossil_fuel; exclude_shale_oil_gas; exclude_hydraulic_fracturing; exclude_nuclear_power | CM81: 3.4 | CN81: 3.1 | CO81: 3.25 | CP81: 0.3 | CQ81: 3.55 | CR81: 350.98887
A82: 81 | B82: AMGN-US | C82: AMGEN INC | D82: US0311621009 | E82: XNGS | F82: 537204960 | G82: 289.8231 | H82: USD | I82: 1.5569441e+11 | J82: NA500 | K82: 9.8449836e+08 | L82: 1 | M82: 1.5569441e+11 | N82: 293.92 | O82: 0.8797009 | P82: 1.3890062e+11 | Q82: 20103015 | R82: 2010 | S82: 1.9753941 | T82: 1.5 | U82: A- | V82: Amber | W82: 0 | X82: 0 | Y82: Green | Z82: Green | AA82: Green | AB82: Green | AC82: Green | AD82: Green | AE82: Green | AF82: 0 | AG82: 0 | AH82: 0 | AJ82: 0 | AK82: F | AM82: F | AN82: F | AO82: F | AQ82: 0 | AR82: 0 | AS82: 0 | AT82: 0 | AU82: 2.67 | AV82: 2.789 | AW82: 7.764408 | AX82: 1.5 | AY82: M | AZ82: 0 | BA82: 0 | BB82: US | BC82: 0 | BD82: 0 | BE82: 0 | CI82: 2.7295 | CK82: No | CM82: 1.9753941 | CN82: 1.5 | CO82: 1.737697 | CP82: -0.24 | CQ82: 1.497697 | CR82: 50.951644
A83: 82 | B83: AMP-AU | C83: AMP LTD | D83: AU000000AMP6 | E83: XASX | F83: 2531739700 | G83: 0.8445121 | H83: AUD | I83: 2.1380848e+09 | J83: AS500 | K83: 6999350.9 | L83: 0.95 | M83: 2.0311806e+09 | N83: 1.1 | O83: 0.55671538 | P83: 1.4728841e+09 | Q83: 30202010 | R83: 3020 | S83: 3.4 | T83: 1.5 | U83: Score not available | V83: Green | W83: 0 | X83: 0 | Y83: Green | Z83: Green | AA83: Green | AB83: Green | AC83: Green | AD83: Green | AE83: Green | AF83: 0 | AG83: 0 | AH83: 0 | AJ83: 0 | AK83: F | AM83: F | AN83: F | AO83: F | AQ83: 0 | AR83: 0 | AS83: 0 | AT83: 0 | AU83: 1.944 | AV83: 2.497 | AW83: 7.7130171 | AX83: 1.5 | AY83: K | AZ83: 0 | BA83: 0 | BB83: AU | BC83: 0 | BD83: 0 | BE83: 0 | CI83: 2.2205 | CK83: No | CM83: 3.4 | CN83: 1.5 | CO83: 2.45 | CP83: 0.3 | CQ83: 2.75 | CR83: 51.827488
A84: 83 | B84: APH-US | C84: AMPHENOL COR CLASS A | D84: US0320951017 | E84: XNYS | F84: 1211081000 | G84: 64.63893 | H84: USD | I84: 7.828298e+10 | J84: NA500 | K84: 4.7105668e+08 | L84: 1 | M84: 7.828298e+10 | N84: 65.46 | O84: 0.8797009 | P84: 6.9740367e+10 | Q84: 10102015 | R84: 1010 | S84: 3.4 | U84: B | V84: Green | W84: 0 | X84: 0 | Y84: Green | Z84: Green | AA84: Green | AB84: Amber | AC84: Green | AD84: Green | AE84: Green | AF84: 0 | AG84: 0 | AH84: 0 | AJ84: 0 | AK84: F | AM84: F | AN84: F | AO84: F | AQ84: 0 | AR84: 0 | AS84: 0 | AT84: 0 | AU84: 2.3 | AV84: 2.743 | AW84: 31.071969 | AX84: 1.5 | AY84: C | AZ84: 1 | BA84: 0 | BB84: US | BC84: 0 | BD84: 0 | BE84: 0 | BO84: exclude_nuclear_weapons_inside_npt | CI84: 2.5215 | CK84: Yes | CL84: exclude_nuclear_weapons_inside_npt | CM84: 3.4 | CN84: 3.1 | CO84: 3.25 | CP84: -0.18 | CQ84: 3.07 | CR84: 33.625121
A85: 84 | B85: AMP-IT | C85: AMPLIFON | D85: IT0004056880 | E85: MTAA | F85: 226388620 | G85: 25.22 | H85: EUR | I85: 5.709521e+09 | J85: EU500 | K85: 16355032 | L85: 0.6 | M85: 3.4257126e+09 | N85: 17.56 | O85: 1 | P85: 2.3852305e+09 | Q85: 20102015 | R85: 2010 | S85: 3.2515364 | U85: B | V85: Green | W85: 0 | X85: 0 | Y85: Green | Z85: Green | AA85: Green | AB85: Green | AC85: Green | AD85: Green | AE85: Green | AF85: 0 | AG85: 0 | AH85: 0 | AJ85: 0 | AK85: F | AM85: F | AN85: F | AO85: F | AQ85: 0 | AR85: 0 | AS85: 0 | AT85: 0 | AU85: 2.434 | AV85: 2.496 | AW85: 16.751855 | AX85: 1.5 | AY85: G | AZ85: 1 | BA85: 0 | BB85: IT | BC85: 0 | BD85: 0 | BE85: 0 | CI85: 2.465 | CK85: No | CM85: 3.2515364 | CN85: 3.1 | CO85: 3.1757682 | CP85: -0.18 | CQ85: 2.9957682 | CR85: 50.951644
A86: 85 | B86: ALD-AU | C86: AMPOL LTD | D86: AU0000088338 | E86: XASX | F86: 238302100 | G86: 17.09146 | H86: AUD | I86: 4.0729308e+09 | J86: AS500 | K86: 26185929 | L86: 1 | M86: 4.0729308e+09 | N86: 21.3 | O86: 0.55671538 | P86: 2.8257953e+09 | Q86: 60101020 | R86: 6010 | S86: 3.4 | U86: F | V86: Green | W86: 0 | X86: 0.01 | Y86: Green | Z86: Green | AA86: Green | AB86: Green | AC86: Green | AD86: Green | AE86: Green | AF86: 0 | AG86: 1 | AH86: 0 | AJ86: 0 | AK86: F | AM86: F | AN86: F | AO86: T | AQ86: 0 | AR86: 0 | AS86: 0 | AT86: 0 | AU86: 2.16 | AV86: 2.546 | AW86: 7155.5644 | AX86: 1.8 | AY86: C | AZ86: 1 | BA86: 0 | BB86: AU | BC86: 0 | BD86: 0 | BE86: 0 | BU86: exclude_fossil_fuel | CC86: exclude_other_fossil_fuel_infra | CI86: 2.353 | CK86: Yes | CL86: exclude_fossil_fuel; exclude_other_fossil_fuel_infra | CM86: 3.4 | CN86: 3.1 | CO86: 3.25 | CP86: 0.3 | CQ86: 3.55 | CR86: 2017.1154
A87: 86 | B87: AMUN-FR | C87: AMUNDI | D87: FR0004125920 | E87: XPAR | F87: 205419262 | G87: 68.8 | H87: EUR | I87: 1.4132845e+10 | J87: EU500 | K87: 10120376 | L87: 0.3 | M87: 4.2398536e+09 | N87: 63.7 | O87: 1 | P87: 3.9255621e+09 | Q87: 30202010 | R87: 3020 | U87: A- | V87: Green | W87: 0 | X87: 0 | Y87: Green | Z87: Green | AA87: Green | AB87: Green | AC87: Green | AD87: Green | AE87: Green | AF87: 0 | AG87: 0 | AH87: 0 | AJ87: 0 | AK87: F | AM87: F | AN87: F | AO87: F | AQ87: 0 | AR87: 0 | AS87: 0 | AT87: 0 | AU87: 2.225 | AV87: 2.465 | AW87: 36.759526 | AX87: 1.5 | AY87: K | AZ87: 0 | BA87: 0 | BB87: FR | BC87: 0 | BD87: 0 | BE87: 0 | CI87: 2.345 | CK87: No | CM87: 3.4592708 | CN87: 3.1 | CO87: 3.2796354 | CP87: -0.24 | CQ87: 3.0396354 | CR87: 51.827488
A88: 87 | B88: 9202-JP | C88: ANA HOLDINGS INC | D88: JP3429800000 | E88: XTKS | F88: 484293550 | G88: 18.68705 | H88: JPY | I88: 9.0500178e+09 | J88: AS500 | K88: 27773239 | L88: 1 | M88: 9.0500178e+09 | N88: 2655 | O88: 0.00613973 | P88: 7.894461e+09 | Q88: 40501010 | R88: 4050 | S88: 1.8012116 | T88: 2.7 | U88: A | V88: Green | W88: 0 | X88: 0.05 | Y88: Green | Z88: Green | AA88: Green | AB88: Green | AC88: Green | AD88: Green | AE88: Green | AF88: 0 | AG88: 0 | AH88: 0 | AJ88: 0 | AK88: F | AM88: F | AN88: F | AO88: F | AQ88: 0 | AR88: 0 | AS88: 0 | AT88: 0 | AU88: 1.95 | AV88: 2.074 | AW88: 557.54326 | AX88: 1.9 | AY88: H | AZ88: 1 | BA88: 0 | BB88: JP | BC88: 0 | BD88: 0 | BE88: 0 | CI88: 2.012 | CK88: No | CM88: 1.8012116 | CN88: 2.7 | CO88: 2.2506058 | CP88: -0.3 | CQ88: 1.9506058 | CR88: 201.88986
A89: 88 | B89: ADI-US | C89: ANALOG DEVICES INC | D89: US0326541051 | E89: XNGS | F89: 495976470 | G89: 228.5127 | H89: USD | I89: 1.1333692e+11 | J89: NA500 | K89: 7.3756664e+08 | L89: 1 | M89: 1.1333692e+11 | N89: 178.6 | O89: 0.8797009 | P89: 7.7925135e+10 | Q89: 10102010 | R89: 1010 | S89: 1.9810447 | T89: 3.1 | U89: Score not available | V89: Green | W89: 0 | X89: 0 | Y89: Green | Z89: Green | AA89: Green | AB89: Green | AC89: Green | AD89: Green | AE89: Green | AF89: 0 | AG89: 0 | AH89: 0 | AJ89: 0 | AK89: F | AM89: F | AN89: F | AO89: F | AQ89: 0 | AR89: 0 | AS89: 0 | AT89: 0 | AU89: 2.32 | AV89: 3.476 | AW89: 31.856598 | AX89: 1.5 | AY89: C | AZ89: 1 | BA89: 0 | BB89: US | BC89: 0 | BD89: 0 | BE89: 0 | CI89: 2.898 | CK89: No | CM89: 1.9810447 | CN89: 3.1 | CO89: 2.5405224 | CP89: 0.3 | CQ89: 2.8405224 | CR89: 33.625121
A90: 89 | B90: ANDR-AT | C90: ANDRITZ AG | D90: AT0000730007 | E90: WBAH | F90: 104000000 | G90: 56.75 | H90: EUR | I90: 5902000000 | J90: EU500 | K90: 5651248.1 | L90: 0.6 | M90: 3541200000 | N90: 52.75 | O90: 1 | P90: 3291600000 | Q90: 50204000 | R90: 5020 | U90: C | V90: Green | W90: 0 | X90: 0 | Y90: Green | Z90: Green | AA90: Green | AB90: Green | AC90: Green | AD90: Green | AE90: Green | AF90: 0.01 | AG90: 0.01 | AH90: 0 | AJ90: 0 | AK90: F | AM90: F | AN90: F | AO90: F | AP90: Services | AQ90: 0.01 | AR90: 0 | AS90: 0 | AT90: 0 | AU90: 2.137 | AV90: 2.943 | AW90: 1283.7714 | AX90: 1.5 | AY90: C | AZ90: 1 | BA90: 0 | BB90: AT | BC90: 0 | BD90: 0 | BE90: 0 | BT90: exclude_coal_mining | BU90: exclude_fossil_fuel | CD90: exclude_nuclear_power | CI90: 2.54 | CK90: Yes | CL90: exclude_coal_mining; exclude_fossil_fuel; exclude_nuclear_power | CM90: 3.4592708 | CN90: 3.1 | CO90: 3.2796354 | CP90: 0 | CQ90: 3.2796354 | CR90: 350.98887
A91: 90 | B91: AAL-GB | C91: ANGLO AMERICAN PLC | D91: GB00B1XZS820 | E91: XLON | F91: 1337577900 | G91: 29.49821 | H91: GBX | I91: 3.9456154e+10 | J91: EU500 | K91: 50815466 | L91: 1 | M91: 3.9456154e+10 | N91: 1986.8 | O91: 0.01160026 | P91: 3.0827688e+10 | Q91: 55102000 | R91: 5510 | S91: 1.7357823 | T91: 3.1 | U91: A- | V91: Green | W91: 0 | X91: 0 | Y91: Green | Z91: Green | AA91: Green | AB91: Green | AC91: Green | AD91: Green | AE91: Green | AF91: 0.128 | AG91: 0.15 | AH91: 0.01 | AJ91: 0 | AK91: F | AM91: F | AN91: F | AO91: F | AQ91: 0 | AR91: 0 | AS91: 0 | AT91: 0 | AU91: 2.957 | AV91: 3.128 | AW91: 2211.0401 | AX91: 4.9 | AY91: B | AZ91: 1 | BA91: 0 | BB91: GB | BC91: 0 | BD91: 0 | BE91: 0 | BT91: exclude_coal_mining | BU91: exclude_fossil_fuel | BV91: exclude_thermal_power | CI91: 3.0425 | CK91: Yes | CL91: exclude_coal_mining; exclude_fossil_fuel; exclude_thermal_power | CM91: 1.7357823 | CN91: 3.1 | CO91: 2.4178911 | CP91: -0.24 | CQ91: 2.1778911 | CR91: 1318.4572
A92: 91 | B92: ANN-AU | C92: ANSELL LTD | D92: AU000000ANN9 | E92: XASX | F92: 145944890 | G92: 21.76829 | H92: AUD | I92: 3.1769707e+09 | J92: AS500 | K92: 6749392.4 | L92: 0.9 | M92: 2.8592736e+09 | N92: 29.03 | O92: 0.55671538 | P92: 2.1228126e+09 | Q92: 20102015 | R92: 2010 | S92: 3.4 | T92: 2.39 | U92: D | V92: Green | W92: 0 | X92: 0 | Y92: Green | Z92: Green | AA92: Green | AB92: Green | AC92: Green | AD92: Green | AE92: Green | AF92: 0 | AG92: 0 | AH92: 0 | AJ92: 0 | AK92: F | AM92: F | AN92: F | AO92: F | AQ92: 0 | AR92: 0 | AS92: 0 | AT92: 0 | AU92: 2.458 | AV92: 3.191 | AW92: 613.72642 | AX92: 2.5 | AY92: C | AZ92: 1 | BA92: 0 | BB92: AU | BC92: 0 | BD92: 0 | BE92: 0 | CI92: 2.8245 | CK92: No | CM92: 3.4 | CN92: 2.39 | CO92: 2.895 | CP92: 0.18 | CQ92: 3.075 | CR92: 50.951644
A93: 92 | B93: ANSS-US | C93: ANSYS INC. | D93: US03662Q1058 | E93: XNGS | F93: 87651780 | G93: 319.6652 | H93: USD | I93: 2.8019224e+10 | J93: NA500 | K93: 1.6320955e+08 | L93: 1 | M93: 2.8019224e+10 | N93: 302.1 | O93: 0.8797009 | P93: 2.329413e+10 | Q93: 10101015 | R93: 1010 | S93: 3.4 | T93: 3.01 | U93: C | V93: Green | W93: 0 | X93: 0 | Y93: Green | Z93: Green | AA93: Green | AB93: Green | AC93: Green | AD93: Green | AE93: Green | AF93: 0 | AG93: 0.1 | AH93: 0 | AI93: Services | AJ93: 0 | AK93: T | AL93: Services | AM93: F | AN93: F | AO93: F | AP93: Services | AQ93: 0.01 | AR93: 0 | AS93: 0 | AT93: 0 | AU93: 2.402 | AV93: 3.19 | AW93: 12.991508 | AX93: 1.9 | AY93: J | AZ93: 0 | BA93: 0 | BB93: US | BC93: 0 | BD93: 0 | BE93: 0 | BU93: exclude_fossil_fuel | BW93: exclude_shale_oil_gas | BY93: exclude_deepwater_drilling | BZ93: exclude_hydraulic_fracturing | CD93: exclude_nuclear_power | CI93: 2.796 | CK93: Yes | CL93: exclude_fossil_fuel; exclude_shale_oil_gas; exclude_deepwater_drilling; exclude_hydraulic_fracturing; exclude_nuclear_power | CM93: 3.4 | CN93: 3.01 | CO93: 3.205 | CP93: 0 | CQ93: 3.205 | CR93: 33.625121
A94: 93 | B94: ANTO-GB | C94: ANTOFAGASTA PLC | D94: GB0000456144 | E94: XLON | F94: 985856700 | G94: 22.00277 | H94: GBX | I94: 2.1691578e+10 | J94: EU500 | K94: 15462568 | L94: 0.4 | M94: 8.6766313e+09 | N94: 1518 | O94: 0.01160026 | P94: 6.944057e+09 | Q94: 55102040 | R94: 5510 | S94: 2.6691726 | T94: 3.1 | U94: B | V94: Green | W94: 0 | X94: 0 | Y94: Green | Z94: Green | AA94: Green | AB94: Green | AC94: Green | AD94: Green | AE94: Green | AF94: 0 | AG94: 0 | AH94: 0 | AJ94: 0 | AK94: F | AM94: F | AN94: F | AO94: F | AQ94: 0 | AR94: 0 | AS94: 0 | AT94: 0 | AU94: 2.331 | AV94: 3.169 | AW94: 274.99605 | AX94: 6 | AY94: B | AZ94: 1 | BA94: 0 | BB94: GB | BC94: 0 | BD94: 0 | BE94: 0 | CI94: 2.75 | CK94: No | CM94: 2.6691726 | CN94: 3.1 | CO94: 2.8845863 | CP94: -0.18 | CQ94: 2.7045863 | CR94: 1318.4572
A95: 94 | B95: ANZ-AU | C95: ANZ GROUP HOLDINGS | D95: AU000000ANZ3 | E95: XASX | F95: 2975404800 | G95: 17.55488 | H95: AUD | I95: 5.2232874e+10 | J95: AS500 | K95: 85427652 | L95: 1 | M95: 5.2232874e+10 | N95: 27.42 | O95: 0.55671538 | P95: 4.5419958e+10 | Q95: 30101010 | R95: 3010 | S95: 3.4 | T95: 1.5 | U95: Score not available | V95: Green | W95: 0 | X95: 0 | Y95: Green | Z95: Green | AA95: Green | AB95: Green | AC95: Green | AD95: Green | AE95: Green | AF95: 0 | AG95: 0 | AH95: 0 | AJ95: 0 | AK95: F | AM95: F | AN95: F | AO95: F | AQ95: 0 | AR95: 0 | AS95: 0 | AT95: 0 | AU95: 2.441 | AV95: 2.82 | AW95: 198.88213 | AX95: 1.5 | AY95: K | AZ95: 0 | BA95: 0 | BB95: AU | BC95: 0 | BD95: 0 | BE95: 0 | CI95: 2.6305 | CK95: No | CM95: 3.4 | CN95: 1.5 | CO95: 2.45 | CP95: 0.3 | CQ95: 2.75 | CR95: 276.86158
A96: 95 | B96: AON-US | C96: AON PLC CLASS A | D96: IE00BLP1HW54 | E96: XNYS | F96: 216001100 | G96: 372.6064 | H96: USD | I96: 8.0483392e+10 | J96: NA500 | K96: 3.6328232e+08 | L96: 1 | M96: 8.0483392e+10 | N96: 384.34 | O96: 0.8797009 | P96: 7.3030889e+10 | Q96: 30302015 | R96: 3030 | S96: 1.9726029 | U96: D | V96: Green | W96: 0 | X96: 0 | Y96: Green | Z96: Green | AA96: Green | AB96: Green | AC96: Green | AD96: Green | AE96: Green | AF96: 0 | AG96: 0 | AH96: 0 | AJ96: 0 | AK96: F | AM96: F | AN96: F | AO96: F | AQ96: 0 | AR96: 0 | AS96: 0 | AT96: 0 | AU96: 1.739 | AV96: 2.806 | AW96: 110.17375 | AX96: 1.5 | AY96: K | AZ96: 0 | BA96: 0 | BB96: IE | BC96: 0 | BD96: 0 | BE96: 0 | CI96: 2.2725 | CK96: No | CM96: 1.9726029 | CN96: 3.1 | CO96: 2.5363014 | CP96: 0.18 | CQ96: 2.7163014 | CR96: 324.26126
A97: 96 | B97: MAERSK.B-DK | C97: AP MOELLER - MAERSK | D97: DK0010244508 | E97: XCSE | F97: 6072390 | G97: 1655.448 | H97: DKK | I97: 1.0052526e+10 | J97: EU500 | K97: 39712798 | L97: 0.7 | M97: 7.0367681e+09 | N97: 10585 | O97: 0.13393335 | P97: 6.0261133e+09 | Q97: 50206030 | R97: 5020 | S97: 1.6395939 | T97: 2.39 | U97: A | V97: Green | W97: 0 | X97: 0 | Y97: Green | Z97: Green | AA97: Green | AB97: Green | AC97: Green | AD97: Green | AE97: Green | AF97: 0 | AG97: 0.05 | AH97: 0 | AJ97: 0 | AK97: F | AM97: F | AN97: F | AO97: F | AQ97: 0 | AR97: 0 | AS97: 0 | AT97: 0 | AU97: 1.985 | AV97: 2.657 | AW97: 1897.7701 | AX97: 2 | AY97: H | AZ97: 1 | BA97: 0 | BB97: DK | BC97: 0 | BD97: 0 | BE97: 0 | BU97: exclude_fossil_fuel | CI97: 2.321 | CK97: Yes | CL97: exclude_fossil_fuel | CM97: 1.6395939 | CN97: 2.39 | CO97: 2.0147969 | CP97: -0.3 | CQ97: 1.7147969 | CR97: 350.98887
A98: 97 | B98: APA-AU | C98: APA GROUP | D98: AU000000APA1 | E98: XASX | F98: 1294951700 | G98: 4.030488 | H98: AUD | I98: 5.2192873e+09 | J98: AS500 | K98: 16995725 | L98: 1 | M98: 5.2192873e+09 | N98: 8.03 | O98: 0.55671538 | P98: 5.7889838e+09 | Q98: 60101035 | R98: 6010 | S98: 3.4 | U98: F | V98: Green | W98: 0 | X98: 0 | Y98: Green | Z98: Green | AA98: Green | AB98: Green | AC98: Green | AD98: Green | AE98: Green | AF98: 0 | AG98: 0.707 | AH98: 0.0854 | AJ98: 0 | AK98: F | AM98: F | AN98: F | AO98: T | AQ98: 0 | AR98: 0 | AS98: 0 | AT98: 0 | AU98: 2.229 | AV98: 2.79 | AW98: 876.46748 | AX98: 6 | AY98: D | AZ98: 1 | BA98: 0 | BB98: AU | BC98: 0 | BD98: 0 | BE98: 0 | BU98: exclude_fossil_fuel | BV98: exclude_thermal_power | CC98: exclude_other_fossil_fuel_infra | CI98: 2.5095 | CK98: Yes | CL98: exclude_fossil_fuel; exclude_thermal_power; exclude_other_fossil_fuel_infra | CM98: 3.4 | CN98: 3.1 | CO98: 3.25 | CP98: 0.3 | CQ98: 3.55 | CR98: 2017.1154
A99: 98 | B99: APO-US | C99: APOLLO GLOBAL MNGMNT | D99: US03769M1062 | E99: XNYS | F99: 565816470 | G99: 143.9981 | H99: USD | I99: 8.1476497e+10 | J99: NA500 | K99: 8.7427234e+08 | L99: 0.7 | M99: 5.7033548e+10 | N99: 125.52 | O99: 0.8797009 | P99: 4.3734241e+10 | Q99: 30202010 | R99: 3020 | S99: 3.4 | U99: F | V99: Green | W99: 0 | X99: 0.01 | Y99: Green | Z99: Green | AA99: Green | AB99: Green | AC99: Green | AD99: Green | AE99: Green | AF99: 0 | AG99: 0 | AH99: 0 | AJ99: 0 | AK99: F | AM99: F | AN99: F | AO99: F | AQ99: 0 | AR99: 0 | AS99: 0 | AT99: 0 | AU99: 1.67 | AV99: 2.615 | AW99: 109.38674 | AX99: 1.5 | AY99: K | AZ99: 0 | BA99: 0 | BB99: US | BC99: 0 | BD99: 0 | BE99: 0 | CI99: 2.1425 | CK99: No | CM99: 3.4 | CN99: 3.1 | CO99: 3.25 | CP99: 0.3 | CQ99: 3.55 | CR99: 51.827488
A100: 99 | B100: AAPL-US | C100: APPLE | D100: US0378331005 | E100: XNGS | F100: 15022073000 | G100: 234.8637 | H100: USD | I100: 3.5281396e+12 | J100: NA500 | K100: 1.1618463e+10 | L100: 1 | M100: 3.5281396e+12 | N100: 202.52 | O100: 0.8797009 | P100: 2.6762879e+12 | Q100: 10102030 | R100: 1010 | S100: 1.9987623 | U100: Score not available | V100: Amber | W100: 0 | X100: 0 | Y100: Green | Z100: Green | AA100: Green | AB100: Green | AC100: Green | AD100: Green | AE100: Green | AF100: 0 | AG100: 0 | AH100: 0 | AJ100: 0 | AK100: F | AM100: F | AN100: F | AO100: F | AQ100: 0 | AR100: 0 | AS100: 0 | AT100: 0 | AU100: 2.519 | AV100: 2.686 | AW100: 5.997061 | AX100: 1.5 | AY100: C | AZ100: 1 | BA100: 0 | BB100: US | BC100: 0 | BD100: 0 | BE100: 0 | CI100: 2.6025 | CK100: No | CM100: 1.9987623 | CN100: 3.1 | CO100: 2.5493812 | CP100: 0.3 | CQ100: 2.8493812 | CR100: 33.625121
...

Sheet Target Calculation
A1: ICB_Supersector_Code | B1: Eligible_Count | C1: Proportion | D1: Raw_Target | E1: Rounded_Target | F1: Initial_Selected | G1: Final_Selected | H1: Companies_Removed
A2: 1010 | B2: 131 | C2: 0.13381001 | D2: 38.269663 | E2: 39 | F2: 39 | G2: 38 | H2: 1
A3: 1510 | B3: 38 | C3: 0.038815117 | D3: 11.101124 | E3: 12 | F3: 12 | G3: 12 | H3: 0
A4: 2010 | B4: 116 | C4: 0.11848825 | D4: 33.88764 | E4: 34 | F4: 34 | G4: 34 | H4: 0
A5: 3010 | B5: 82 | C5: 0.083758938 | D5: 23.955056 | E5: 24 | F5: 24 | G5: 23 | H5: 1
A6: 3020 | B6: 71 | C6: 0.072522983 | D6: 20.741573 | E6: 21 | F6: 21 | G6: 20 | H6: 1
A7: 3030 | B7: 64 | C7: 0.065372829 | D7: 18.696629 | E7: 19 | F7: 19 | G7: 18 | H7: 1
A8: 3510 | B8: 79 | C8: 0.080694586 | D8: 23.078652 | E8: 24 | F8: 24 | G8: 23 | H8: 1
A9: 4010 | B9: 20 | C9: 0.020429009 | D9: 5.8426966 | E9: 6 | F9: 6 | G9: 6 | H9: 0
A10: 4020 | B10: 57 | C10: 0.058222676 | D10: 16.651685 | E10: 17 | F10: 17 | G10: 17 | H10: 0
A11: 4030 | B11: 14 | C11: 0.014300306 | D11: 4.0898876 | E11: 5 | F11: 5 | G11: 5 | H11: 0
A12: 4040 | B12: 26 | C12: 0.026557712 | D12: 7.5955056 | E12: 8 | F12: 8 | G12: 8 | H12: 0
A13: 4050 | B13: 36 | C13: 0.036772217 | D13: 10.516854 | E13: 11 | F13: 11 | G13: 10 | H13: 1
... A20: 6510 | B20: 6 | C20: 0.0061287028 | D20: 1.752809 | E20: 2 | F20: 2 | G20: 2 | H20: 0

Sheet Eligible Companies
A1: Rank | B1: Ticker | C1: Company | D1: ISIN Code | E1: MIC | F1: Number of Shares | G1: Price (EUR) | H1: Currency | I1: Mcap in EUR | J1: index | K1: VOL_AV_3M | L1: Free Float | M1: FFMC_CO | N1: Close Prc | O1: FX/Index Ccy | P1: FFMC_WD | Q1: Subsector Code | R1: Supersector Code | S1: itr_scope123_target | T1: itr_scope12_trend | U1: CDP_climate_score | V1: NBR Overall Flag | W1: Tobacco - Production Maximum Percentage of Revenues (%) | X1: Tobacco - Distribution Maximum Percentage of Revenues (%) | Y1: Biological Weapons - Overall Flag | Z1: Chemical Weapons - Overall Flag | AA1: Nuclear Weapons Outside NPT - Overall Flag | AB1: Nuclear Weapons Inside NPT - Overall Flag | AC1: Cluster Munitions - Overall Flag | AD1: Depleted Uranium - Overall Flag | AE1: Anti-personnel Mines - Overall Flag | AF1: coal_mining_and_power_gen_maximum_percentage_of_revenues-values | AG1: Fossil Fuel - Total Maximum Percentage of Revenues (%) | AH1: power_generation_thermal_maximum_percentage_of_revenues-values | AI1: shale_oil_and_or_gas_involvement_tie | AJ1: arctic_drilling_share_max-values | AK1: deepwater_drilling_involvement | AL1: HydraulicFracturingInvolvement | AM1: CoalMiningExpInvolved | AN1: OilGasExtractExpInvolved | AO1: OtherFFInfraInvolved | AP1: NuclearPowerInvolvement | AQ1: NuclearPowerRevShareMax-values | AR1: NuclearPowerUraniumRevShareMax-values | AS1: CivFARevShareMax-values | AT1: MilitaryEqmtDistMaxRev-values | AU1: Social Rating (Num) | AV1: Governance Rating (Num) | AW1: Carbon Intensity (ISS) | AX1: ScoreTemperatureISS | AY1: NACE | AZ1: High_Climate_Impact | BA1: EU_Taxonomy | BB1: Country_Code | BC1: GAFI_Black_List | BD1: GAFI_Grey_List | BE1: Non_Fiscally_Cooperative | BF1: exclude_gafi_black | BG1: exclude_gafi_grey | BH1: exclude_non_fiscal_coop | BI1: exclude_subsector | BJ1: exclude_nbr_red | BK1: exclude_tobacco_prod | BL1: exclude_tobacco_dist | BM1: exclude_biological_weapons | BN1: exclude_chemical_weapons | BO1: exclude_nuclear_weapons_inside_npt | BP1: exclude_nuclear_weapons_outside_npt | BQ1: exclude_cluster_munitions | BR1: exclude_depleted_uranium | BS1: exclude_anti_personnel_mines | BT1: exclude_coal_mining | BU1: exclude_fossil_fuel | BV1: exclude_thermal_power | BW1: exclude_shale_oil_gas | BX1: exclude_arctic_drilling | BY1: exclude_deepwater_drilling | BZ1: exclude_hydraulic_fracturing | CA1: exclude_coal_mining_expansion | CB1: exclude_oil_gas_extraction_expansion | CC1: exclude_other_fossil_fuel_infra | CD1: exclude_nuclear_power | CE1: exclude_nuclear_power_revenue | CF1: exclude_nuclear_uranium | CG1: exclude_civilian_firearms | CH1: exclude_military_equipment | CI1: SG_Score | CJ1: exclude_sg_bottom_10 | CK1: Excluded | CL1: Exclusion_Reason | CM1: itr_scope123_target_filled | CN1: itr_scope12_trend_filled | CO1: cdp_temperature_score | CP1: bonus_malus | CQ1: climate_score | CR1: Median_Carbon_Intensity_Supersector
A2: 4 | B2: A2M-AU | C2: A2 MILK CO LTD | D2: NZATME0002S8 | E2: XASX | F2: 724019100 | G2: 4.737804 | H2: AUD | I2: 3.4302606e+09 | J2: AS500 | K2: 8193130.8 | L2: 0.9 | M2: 3.0872345e+09 | N2: 8.06 | O2: 0.55671538 | P2: 2.9238884e+09 | Q2: 45102020 | R2: 4510 | S2: 3.4 | U2: F | V2: Green | W2: 0 | X2: 0 | Y2: Green | Z2: Green | AA2: Green | AB2: Green | AC2: Green | AD2: Green | AE2: Green | AF2: 0 | AG2: 0 | AH2: 0 | AJ2: 0 | AK2: F | AM2: F | AN2: F | AO2: F | AQ2: 0 | AR2: 0 | AS2: 0 | AT2: 0 | AU2: 2.013 | AV2: 3.066 | AW2: 474.06286 | AX2: 1.5 | AY2: A | AZ2: 1 | BA2: 0 | BB2: NZ | BC2: 0 | BD2: 0 | BE2: 0 | CI2: 2.5395 | CK2: No | CM2: 3.4 | CN2: 3.1 | CO2: 3.25 | CP2: 0.3 | CQ2: 3.55 | CR2: 285.13539
A3: 6 | B3: 2018-HK | C3: AAC TECHNOLOGIES | D3: KYG2953R1149 | E3: XHKG | F3: 1198500000 | G3: 6.155748 | H3: HKD | I3: 7377663978 | J3: AS500 | K3: 32843617 | L3: 0.7 | M3: 5.1643648e+09 | N3: 36.65 | O3: 0.11342884 | P3: 3.4876552e+09 | Q3: 10102015 | R3: 1010 | S3: 3.4 | U3: C | V3: Green | W3: 0 | X3: 0 | Y3: Green | Z3: Green | AA3: Green | AB3: Green | AC3: Green | AD3: Green | AE3: Green | AF3: 0 | AG3: 0 | AH3: 0 | AJ3: 0 | AK3: F | AM3: F | AN3: F | AO3: F | AQ3: 0 | AR3: 0 | AS3: 0 | AT3: 0 | AU3: 1.906 | AV3: 2.317 | AW3: 556.19064 | AX3: 6 | AY3: C | AZ3: 1 | BA3: 0 | BB3: KY | BC3: 0 | BD3: 0 | BE3: 0 | CI3: 2.1115 | CK3: No | CM3: 3.4 | CN3: 3.1 | CO3: 3.25 | CP3: 0 | CQ3: 3.25 | CR3: 33.625121
A4: 7 | B4: AAK-SE | C4: AAK AB | D4: SE0011337708 | E4: XSTO | F4: 259559200 | G4: 27.4255 | H4: SEK | I4: 7.1185408e+09 | J4: EU500 | K4: 10069959 | L4: 0.7 | M4: 4.9829786e+09 | N4: 268 | O4: 0.09077334 | P4: 4.420054e+09 | Q4: 45102020 | R4: 4510 | S4: 1.9643056 | U4: C | V4: Green | W4: 0 | X4: 0 | Y4: Green | Z4: Green | AA4: Green | AB4: Green | AC4: Green | AD4: Green | AE4: Green | AF4: 0 | AG4: 0 | AH4: 0 | AJ4: 0 | AK4: F | AM4: F | AN4: F | AO4: F | AQ4: 0 | AR4: 0 | AS4: 0 | AT4: 0 | AU4: 2.42 | AV4: 3.154 | AW4: 1223.803 | AX4: 1.5 | AY4: C | AZ4: 1 | BA4: 0 | BB4: SE | BC4: 0 | BD4: 0 | BE4: 0 | CI4: 2.787 | CK4: No | CM4: 1.9643056 | CN4: 3.1 | CO4: 2.5321528 | CP4: 0 | CQ4: 2.5321528 | CR4: 285.13539
A5: 9 | B5: ABI-BE | C5: AB INBEV | D5: BE0974293251 | E5: XBRU | F5: 1797198523 | G5: 51.62 | H5: EUR | I5: 9.2771388e+10 | J5: EU500 | K5: 98018859 | L5: 0.55 | M5: 5.1024263e+10 | N5: 55.4 | O5: 1 | P5: 5.4760639e+10 | Q5: 45101010 | R5: 4510 | S5: 2.101079 | T5: 2.7 | U5: Score not available | V5: Amber | W5: 0 | X5: 0 | Y5: Green | Z5: Green | AA5: Green | AB5: Green | AC5: Green | AD5: Green | AE5: Green | AF5: 0 | AG5: 0 | AH5: 0 | AJ5: 0 | AK5: F | AM5: F | AN5: F | AO5: F | AQ5: 0 | AR5: 0 | AS5: 0 | AT5: 0 | AU5: 1.867 | AV5: 2.352 | AW5: 128.46807 | AX5: 1.8 | AY5: C | AZ5: 1 | BA5: 0 | BB5: BE | BC5: 0 | BD5: 0 | BE5: 0 | CI5: 2.1095 | CK5: No | CM5: 2.101079 | CN5: 2.7 | CO5: 2.4005395 | CP5: 0.3 | CQ5: 2.7005395 | CR5: 285.13539
A6: 10 | B6: SAGA.B-SE | C6: AB SAGAX CLASS B | D6: SE0005127818 | E6: XSTO | F6: 313943020 | G6: 19.72838 | H6: SEK | I6: 6.1935872e+09 | J6: EU500 | K6: 7671301.9 | L6: 0.7 | M6: 4.335511e+09 | N6: 201.4 | O6: 0.09077334 | P6: 4.0175996e+09 | Q6: 35101010 | R6: 3510 | S6: 3.2721025 | U6: F | V6: Green | W6: 0 | X6: 0 | Y6: Green | Z6: Green | AA6: Green | AB6: Green | AC6: Green | AD6: Green | AE6: Green | AF6: 0 | AG6: 0 | AH6: 0 | AJ6: 0 | AK6: F | AM6: F | AN6: F | AO6: F | AQ6: 0 | AR6: 0 | AS6: 0 | AT6: 0 | AU6: 1.961 | AV6: 2.119 | AW6: 3.5372492 | AX6: 1.5 | AY6: L | AZ6: 1 | BA6: 0 | BB6: SE | BC6: 0 | BD6: 0 | BE6: 0 | CI6: 2.04 | CK6: No | CM6: 3.2721025 | CN6: 3.1 | CO6: 3.1860513 | CP6: 0.3 | CQ6: 3.4860513 | CR6: 23.753721
A7: 12 | B7: ABT-US | C7: ABBOTT LABORATORIES | D7: US0028241000 | E7: XNYS | F7: 1734323400 | G7: 129.0483 | H7: USD | I7: 2.2381149e+11 | J7: NA500 | K7: 6.6899105e+08 | L7: 1 | M7: 2.2381149e+11 | N7: 127.96 | O7: 0.8797009 | P7: 1.9522676e+11 | Q7: 20102010 | R7: 2010 | S7: 1.9835941 | T7: 2.08 | U7: B | V7: Green | W7: 0 | X7: 0 | Y7: Green | Z7: Green | AA7: Green | AB7: Green | AC7: Green | AD7: Green | AE7: Green | AF7: 0 | AG7: 0 | AH7: 0 | AJ7: 0 | AK7: F | AM7: F | AN7: F | AO7: F | AQ7: 0 | AR7: 0 | AS7: 0 | AT7: 0 | AU7: 2.693 | AV7: 3.678 | AW7: 61.330192 | AX7: 1.5 | AY7: C | AZ7: 1 | BA7: 0 | BB7: US | BC7: 0 | BD7: 0 | BE7: 0 | CI7: 3.1855 | CK7: No | CM7: 1.9835941 | CN7: 2.08 | CO7: 2.0317971 | CP7: -0.18 | CQ7: 1.8517971 | CR7: 50.951644
A8: 13 | B8: ABBV-US | C8: ABBVIE INC. | D8: US00287Y1091 | E8: XNYS | F8: 1765354900 | G8: 193.2855 | H8: USD | I8: 3.412175e+11 | J8: NA500 | K8: 1.0309011e+09 | L8: 1 | M8: 3.412175e+11 | N8: 179.1 | O8: 0.8797009 | P8: 2.7813949e+11 | Q8: 20103015 | R8: 2010 | S8: 1.969737 | T8: 2.08 | U8: B | V8: Green | W8: 0 | X8: 0 | Y8: Green | Z8: Green | AA8: Green | AB8: Green | AC8: Green | AD8: Green | AE8: Green | AF8: 0 | AG8: 0 | AH8: 0 | AJ8: 0 | AK8: F | AM8: F | AN8: F | AO8: F | AQ8: 0 | AR8: 0 | AS8: 0 | AT8: 0 | AU8: 2.616 | AV8: 2.953 | AW8: 24.281901 | AX8: 1.5 | AY8: C | AZ8: 1 | BA8: 0 | BB8: US | BC8: 0 | BD8: 0 | BE8: 0 | CI8: 2.7845 | CK8: No | CM8: 1.969737 | CN8: 2.08 | CO8: 2.0248685 | CP8: -0.18 | CQ8: 1.8448685 | CR8: 50.951644
A9: 14 | B9: ABN-NL | C9: ABN AMRO BANK N.V. | D9: NL0011540547 | E9: XAMS | F9: 539163896 | G9: 17.8 | H9: EUR | I9: 9.5971173e+09 | J9: EU500 | K9: 48401045 | L9: 1 | M9: 9.5971173e+09 | N9: 17.56 | O9: 1 | P9: 9.467718e+09 | Q9: 30101010 | R9: 3010 | S9: 3.2733333 | U9: C | V9: Green | W9: 0 | X9: 0 | Y9: Green | Z9: Green | AA9: Green | AB9: Green | AC9: Green | AD9: Green | AE9: Green | AF9: 0 | AG9: 0 | AH9: 0 | AJ9: 0 | AK9: F | AM9: F | AN9: F | AO9: F | AQ9: 0 | AR9: 0 | AS9: 0 | AT9: 0 | AU9: 2.394 | AV9: 2.779 | AW9: 397.99801 | AX9: 1.5 | AY9: K | AZ9: 0 | BA9: 0 | BB9: NL | BC9: 0 | BD9: 0 | BE9: 0 | CI9: 2.5865 | CK9: No | CM9: 3.2733333 | CN9: 3.1 | CO9: 3.1866667 | CP9: 0 | CQ9: 3.1866667 | CR9: 276.86158
A10: 15 | B10: ABDN-GB | C10: ABRDN | D10: GB00BF8Q6K64 | E10: XLON | F10: 1840742800 | G10: 1.908317 | H10: GBX | I10: 3.5127208e+09 | J10: EU500 | K10: 5431165.1 | L10: 1 | M10: 3.5127208e+09 | N10: 138.9 | O10: 0.01160026 | P10: 2.9659449e+09 | Q10: 30202010 | R10: 3020 | S10: 3.02 | U10: C | V10: Green | W10: 0 | X10: 0 | Y10: Green | Z10: Green | AA10: Green | AB10: Green | AC10: Green | AD10: Green | AE10: Green | AF10: 0 | AG10: 0 | AH10: 0 | AJ10: 0 | AK10: F | AM10: F | AN10: F | AO10: F | AQ10: 0 | AR10: 0 | AS10: 0 | AT10: 0 | AU10: 2.139 | AV10: 3.161 | AW10: 925.58576 | AX10: 1.5 | AY10: K | AZ10: 0 | BA10: 0 | BB10: GB | BC10: 0 | BD10: 0 | BE10: 0 | CI10: 2.65 | CK10: No | CM10: 3.02 | CN10: 3.1 | CO10: 3.06 | CP10: 0 | CQ10: 3.06 | CR10: 51.827488
A11: 17 | B11: ACN-US | C11: ACCENTURE PLC-A | D11: IE00B4BNMY34 | E11: XNYS | F11: 625479900 | G11: 348.4075 | H11: USD | I11: 2.1792189e+11 | J11: NA500 | K11: 9.1298424e+08 | L11: 1 | M11: 2.1792189e+11 | N11: 289.79 | O11: 0.8797009 | P11: 1.5945267e+11 | Q11: 50205020 | R11: 5020 | S11: 1.73905 | T11: 1.5 | U11: A- | V11: Amber | W11: 0 | X11: 0 | Y11: Green | Z11: Green | AA11: Green | AB11: Green | AC11: Green | AD11: Green | AE11: Green | AF11: 0 | AG11: 0 | AH11: 0 | AJ11: 0 | AK11: F | AM11: F | AN11: F | AO11: F | AQ11: 0 | AR11: 0 | AS11: 0 | AT11: 0 | AU11: 2.543 | AV11: 2.915 | AW11: 2.7933113 | AX11: 1.5 | AY11: J | AZ11: 0 | BA11: 0 | BB11: IE | BC11: 0 | BD11: 0 | BE11: 0 | CI11: 2.729 | CK11: No | CM11: 1.73905 | CN11: 1.5 | CO11: 1.619525 | CP11: -0.24 | CQ11: 1.379525 | CR11: 350.98887
A12: 18 | B12: AC-FR | C12: ACCOR | D12: FR0000120404 | E12: XPAR | F12: 243667720 | G12: 46.43 | H12: EUR | I12: 1.1313492e+10 | J12: EU500 | K12: 26555203 | L12: 0.85 | M12: 9.6164684e+09 | N12: 38.58 | O12: 1 | P12: 7.9905955e+09 | Q12: 40501025 | R12: 4050 | S12: 1.7728124 | T12: 3.01 | U12: C | V12: Green | W12: 0 | X12: 0.01 | Y12: Green | Z12: Green | AA12: Green | AB12: Green | AC12: Green | AD12: Green | AE12: Green | AF12: 0 | AG12: 0 | AH12: 0 | AJ12: 0 | AK12: F | AM12: F | AN12: F | AO12: F | AQ12: 0 | AR12: 0 | AS12: 0 | AT12: 0 | AU12: 2.754 | AV12: 3.017 | AW12: 514.67199 | AX12: 6 | AY12: I | AZ12: 0 | BA12: 0 | BB12: FR | BC12: 0 | BD12: 0 | BE12: 0 | CI12: 2.8855 | CK12: No | CM12: 1.7728124 | CN12: 3.01 | CO12: 2.3914062 | CP12: 0 | CQ12: 2.3914062 | CR12: 201.88986
A13: 23 | B13: ADS-DE | C13: ADIDAS AG | D13: DE000A1EWWW0 | E13: XETR | F13: 180000000 | G13: 245.9 | H13: EUR | I13: 44262000000 | J13: EU500 | K13: 95465481 | L13: 1 | M13: 44262000000 | N13: 202.3 | O13: 1 | P13: 36414000000 | Q13: 40204025 | R13: 4020 | S13: 1.7444715 | U13: A | V13: Green | W13: 0 | X13: 0 | Y13: Green | Z13: Green | AA13: Green | AB13: Green | AC13: Green | AD13: Green | AE13: Green | AF13: 0 | AG13: 0 | AH13: 0 | AJ13: 0 | AK13: F | AM13: F | AN13: F | AO13: F | AQ13: 0 | AR13: 0 | AS13: 0 | AT13: 0 | AU13: 2.352 | AV13: 2.749 | AW13: 156.19655 | AX13: 1.5 | AY13: C | AZ13: 1 | BA13: 0 | BB13: DE | BC13: 0 | BD13: 0 | BE13: 0 | CI13: 2.5505 | CK13: No | CM13: 1.7444715 | CN13: 3.1 | CO13: 2.4222358 | CP13: -0.3 | CQ13: 2.1222358 | CR13: 89.792933
A14: 24 | B14: ADM-GB | C14: ADMIRAL GROUP PLC | D14: GB00B02J6398 | E14: XLON | F14: 306304700 | G14: 33.85041 | H14: GBX | I14: 1.036854e+10 | J14: EU500 | K14: 10015140 | L14: 0.7 | M14: 7.2579778e+09 | N14: 3130 | O14: 0.01160026 | P14: 7.7850922e+09 | Q14: 30302025 | R14: 3030 | S14: 1.998809 | T14: 2.7 | U14: C | V14: Green | W14: 0 | X14: 0 | Y14: Green | Z14: Green | AA14: Green | AB14: Green | AC14: Green | AD14: Green | AE14: Green | AF14: 0 | AG14: 0 | AH14: 0 | AJ14: 0 | AK14: F | AM14: F | AN14: F | AO14: F | AQ14: 0 | AR14: 0 | AS14: 0 | AT14: 0 | AU14: 1.88 | AV14: 2.7 | AW14: 0.37512065 | AX14: 1.5 | AY14: K | AZ14: 0 | BA14: 0 | BB14: GB | BC14: 0 | BD14: 0 | BE14: 0 | CI14: 2.29 | CK14: No | CM14: 1.998809 | CN14: 2.7 | CO14: 2.3494045 | CP14: 0 | CQ14: 2.3494045 | CR14: 324.26126
