Workbook

Sheet Index Composition
A1: Company | B1: ISIN Code | C1: MIC | D1: Number of Shares | E1: Free Float | F1: Capping Factor | G1: Effective Date of Review | H1: Currency
A2: ALPHABET CLASS A | B2: US02079K3059 | C2: XNGS | D2: 973106 | E2: 1 | F2: 1 | G2: 22-Sep-25 | H2: USD
A3: AMAZON | B3: US0231351067 | C3: XNGS | D3: 1044244 | E3: 1 | F3: 1 | G3: 22-Sep-25 | H3: USD
A4: APPLE | B4: US0378331005 | C4: XNGS | D4: 1026266 | E4: 1 | F4: 1 | G4: 22-Sep-25 | H4: USD
A5: BANK OF AMERICA | B5: US0605051046 | C5: XNYS | D5: 4824423 | E5: 1 | F5: 1 | G5: 22-Sep-25 | H5: USD
A6: BROADCOM INC. | B6: US11135F1012 | C6: XNGS | D6: 678903 | E6: 1 | F6: 1 | G6: 22-Sep-25 | H6: USD
A7: CISCO SYSTEMS INC | B7: US17275R1023 | C7: XNGS | D7: 3651655 | E7: 1 | F7: 1 | G7: 22-Sep-25 | H7: USD
A8: COCA-COLA CO | B8: US1912161007 | C8: XNYS | D8: 3689693 | E8: 1 | F8: 1 | G8: 22-Sep-25 | H8: USD
A9: ELI LILLY AND CO | B9: US5324571083 | C9: XNYS | D9: 319605 | E9: 1 | F9: 1 | G9: 22-Sep-25 | H9: USD
A10: GE AEROSPACE | B10: US3696043013 | C10: XNYS | D10: 834233 | E10: 1 | F10: 1 | G10: 22-Sep-25 | H10: USD
A11: HOME DEPOT INC | B11: US4370761029 | C11: XNYS | D11: 579915 | E11: 1 | F11: 1 | G11: 22-Sep-25 | H11: USD
A12: JOHNSON & JOHNSON | B12: US4781601046 | C12: XNYS | D12: 1385046 | E12: 1 | F12: 1 | G12: 22-Sep-25 | H12: USD
A13: JP MORGAN CHASE & CO | B13: US46625H1005 | C13: XNYS | D13: 790469 | E13: 1 | F13: 1 | G13: 22-Sep-25 | H13: USD
... A26: WALMART INC | B26: US9311421039 | C26: XNYS | D26: 2363230 | E26: 1 | F26: 1 | G26: 22-Sep-25 | H26: USD

Sheet Inclusion
A1: Company | B1: ISIN Code | C1: MIC
A2: ALPHABET CLASS A | B2: US02079K3059 | C2: XNGS
A3: AMAZON | B3: US0231351067 | C3: XNGS
A4: TESLA INC | B4: US88160R1014 | C4: XNGS

Sheet Exclusion
A1: Company | B1: ISIN code | C1: MIC
A2: ABBVIE INC. | B2: US00287Y1091 | C2: XNYS
A3: IBM CORP | B3: US4592001014 | C3: XNYS
A4: NVIDIA CORP | B4: US67066G1040 | C4: XNGS

Sheet Full Universe
A1: Rank | B1: Company | C1: Ticker | D1: ISIN | E1: Currency (Local) | F1: Price (EUR) | G1: NOSH | H1: Exchange Name (VND) | I1: Sec Market Value (EUR) | J1: 20 days aver. turn EUR | K1: 6 month aver. turnover EUR | L1: 3 month average turnover EUR | M1: 3 months aver. Turnover USD | N1: 12 month aver. turnover EUR | O1: MIC | P1: Free Float | Q1: #Symbol | R1: FX/Index Ccy | S1: ClimateCuAlignIEANZTgt2050-values | T1: ESG Performance Score | U1: Reported Emissions - Emissions Trust Metric | V1: NBR Overall Flag | W1: Anti-personnel Mines - Overall Flag | X1: Biological Weapons - Overall Flag | Y1: Chemical Weapons - Overall Flag | Z1: Cluster Munitions - Overall Flag | AA1: Depleted Uranium - Overall Flag | AB1: Incendiary Weapons - Overall Flag | AC1: Nuclear Weapons Outside NPT - Overall Flag | AD1: White Phosphorous Weapons - Overall Flag | AE1: Thermal Coal Mining - Maximum Percentage of Revenues (%) | AF1: Power Generation - Thermal Maximum Percentage of Revenues (%) | AG1: Shale Oil and/or Gas - Involvement tie | AH1: Trust Metric Numeric | AI1: Coal Mining Numeric | AJ1: Thermal Power Numeric | AK1: Carbon Budget Rank | AL1: exclusion_1_TrustMetric | AM1: exclusion_2_NBROverallFlag | AN1: exclusion_3_APMines | AO1: exclusion_4_BiologicalWeapons | AP1: exclusion_5_ChemicalWeapons | AQ1: exclusion_6_ClusterMunitions | AR1: exclusion_7_DepletedUranium | AS1: exclusion_8_IncendiaryWeapons | AT1: exclusion_9_NuclearWeaponsNonNPT | AU1: exclusion_10_WhitePhosphorus | AV1: exclusion_11_CoalMining | AW1: exclusion_12_ThermalPower | AX1: exclusion_13_ShaleOilGas | AY1: exclusion_14_CarbonBudget | AZ1: Exclusion Summary | BA1: Excluded | BB1: ESG Performance Rank
A2: 1 | B2: 3M CO | C2: MMM-US | D2: US88579Y1010 | E2: USD | F2: 135.4497 | G2: 532629700 | H2: NYSE | I2: 72144.55 | J2: 4.0894509e+08 | K2: 4.9663707e+08 | L2: 4.4055249e+08 | M2: 5.1103236e+08 | N2: 4.7372284e+08 | O2: XNYS | P2: 1 | Q2: MMM.N | R2: 0.84373945 | S2: 2.06 | T2: 62.06 | U2: 0.99 | V2: Green | W2: Green | X2: Green | Y2: Green | Z2: Green | AA2: Green | AB2: Green | AC2: Green | AD2: Green | AE2: 0 | AF2: 0 | AG2: Services | AH2: 0.99 | AI2: 0 | AJ2: 0 | AK2: 233 | AZ2: Included | BA2: No | BB2: 34
A3: 2 | B3: ABBOTT LABORATORIES | C3: ABT-US | D3: US0028241000 | E3: USD | F3: 113.1507 | G3: 1740459000 | H3: NYSE | I3: 196934.2 | J3: 6.1682532e+08 | K3: 7.9636219e+08 | L3: 7.2641161e+08 | M3: 8.421529e+08 | N3: 6.9617688e+08 | O3: XNYS | P3: 1 | Q3: ABT.N | R3: 0.84373945 | S3: 2.02 | T3: 59.53 | U3: 1 | V3: Green | W3: Green | X3: Green | Y3: Green | Z3: Green | AA3: Green | AB3: Green | AC3: Green | AD3: Green | AE3: 0 | AF3: 0 | AH3: 1 | AI3: 0 | AJ3: 0 | AK3: 228 | AZ3: Included | BA3: No | BB3: 54
A4: 3 | B4: ABBVIE INC. | C4: ABBV-US | D4: US00287Y1091 | E4: USD | F4: 179.7235 | G4: 1766558200 | H4: NYSE | I4: 317492.1 | J4: 8.0936205e+08 | K4: 1.1783614e+09 | L4: 9.342367e+08 | M4: 1.0832805e+09 | N4: 1.0849966e+09 | O4: XNYS | P4: 1 | Q4: ABBV.N | R4: 0.84373945 | S4: 7.07 | T4: 59.51 | U4: 0.95 | V4: Green | W4: Green | X4: Green | Y4: Green | Z4: Green | AA4: Green | AB4: Green | AC4: Green | AD4: Green | AE4: 0 | AF4: 0 | AH4: 0.95 | AI4: 0 | AJ4: 0 | AK4: 435 | AY4: exclude_CarbonBudget | AZ4: CarbonBudget | BA4: Yes
A5: 4 | B5: ACCENTURE PLC-A | C5: ACN-US | D5: IE00B4BNMY34 | E5: USD | F5: 221.2152 | G5: 622852700 | H5: NYSE | I5: 137784.5 | J5: 1.0767012e+09 | K5: 9.8915591e+08 | L5: 9.5671143e+08 | M5: 1.1087687e+09 | N5: 9.152817e+08 | O5: XNYS | P5: 1 | Q5: ACN.N | R5: 0.84373945 | S5: 0.69 | T5: 63.16 | U5: 0.99 | V5: Amber | W5: Green | X5: Green | Y5: Green | Z5: Green | AA5: Green | AB5: Green | AC5: Green | AD5: Green | AE5: 0 | AF5: 0 | AH5: 0.99 | AI5: 0 | AJ5: 0 | AK5: 62 | AZ5: Included | BA5: No | BB5: 29
A6: 5 | B6: ADOBE INC | C6: ADBE-US | D6: US00724F1012 | E6: USD | F6: 309.0032 | G6: 424200000 | H6: NASDAQ | I6: 131079.2 | J6: 1.1209776e+09 | K6: 1.2945546e+09 | L6: 1.2387585e+09 | M6: 1.4359691e+09 | N6: 1.4229173e+09 | O6: XNGS | P6: 1 | Q6: ADBE.O | R6: 0.84373945 | S6: 0.62 | T6: 69.03 | U6: 0.92 | V6: Green | W6: Green | X6: Green | Y6: Green | Z6: Green | AA6: Green | AB6: Green | AC6: Green | AD6: Green | AE6: 0 | AF6: 0 | AH6: 0.92 | AI6: 0 | AJ6: 0 | AK6: 52 | AZ6: Included | BA6: No | BB6: 8
A7: 6 | B7: ADVANCED MICRO DEV. | C7: AMD-US | D7: US0079031078 | E7: USD | F7: 143.1644 | G7: 1622843800 | H7: NASDAQ | I7: 232333.4 | J7: 1.0180694e+10 | K7: 5.5215137e+09 | L7: 7.308069e+09 | M7: 8.4823675e+09 | N7: 5.1385126e+09 | O7: XNGS | P7: 1 | Q7: AMD.O | R7: 0.84373945 | S7: 7.58 | T7: 63.93 | U7: 0.93 | V7: Green | W7: Green | X7: Green | Y7: Green | Z7: Green | AA7: Green | AB7: Green | AC7: Green | AD7: Green | AE7: 0 | AF7: 0 | AH7: 0.93 | AI7: 0 | AJ7: 0 | AK7: 443 | AY7: exclude_CarbonBudget | AZ7: CarbonBudget | BA7: Yes
A8: 7 | B8: AERCAP HOLDINGS NV | C8: AER-US | D8: NL0000687663 | E8: USD | F8: 101.9287 | G8: 176566560 | H8: NYSE | I8: 17997.19 | J8: 1.4667501e+08 | K8: 1.4845408e+08 | L8: 1.2816052e+08 | M8: 1.484442e+08 | N8: 1.2325096e+08 | O8: XNYS | P8: 1 | Q8: AER.N | R8: 0.84373945 | S8: 0.19 | T8: 42.09 | U8: 0.5 | V8: Green | W8: Green | X8: Green | Y8: Green | Z8: Green | AA8: Green | AB8: Green | AC8: Green | AD8: Green | AE8: 0 | AF8: 0 | AH8: 0.5 | AI8: 0 | AJ8: 0 | AK8: 3 | AL8: exclude_TrustMetric | AZ8: TrustMetric | BA8: Yes
A9: 8 | B9: AFFIRM HLDNG CLASS A | C9: AFRM-US | D9: US00827B1061 | E9: USD | F9: 67.83581 | G9: 281825620 | H9: NASDAQ | I9: 19117.87 | J9: 3.7984228e+08 | K9: 3.4939164e+08 | L9: 3.1330658e+08 | M9: 3.6334448e+08 | N9: 4.0808896e+08 | O9: XNGS | P9: 1 | Q9: AFRM.O | R9: 0.84373945 | S9: 3.03 | T9: 36.1 | U9: 0.5 | V9: Green | W9: Green | X9: Green | Y9: Green | Z9: Green | AA9: Green | AB9: Green | AC9: Green | AD9: Green | AE9: 0 | AF9: 0 | AH9: 0.5 | AI9: 0 | AJ9: 0 | AK9: 356 | AL9: exclude_TrustMetric | AZ9: TrustMetric | BA9: Yes
A10: 9 | B10: AFLAC INCORPORATED | C10: AFL-US | D10: US0010551028 | E10: USD | F10: 92.55846 | G10: 534831500 | H10: NYSE | I10: 49503.18 | J10: 2.3656445e+08 | K10: 2.1079298e+08 | L10: 2.1836058e+08 | M10: 2.5326599e+08 | N10: 2.0951413e+08 | O10: XNYS | P10: 0.9 | Q10: AFL.N | R10: 0.84373945 | S10: 0.81 | T10: 47.44 | U10: 0.95 | V10: Green | W10: Green | X10: Green | Y10: Green | Z10: Green | AA10: Green | AB10: Green | AC10: Green | AD10: Green | AE10: 0 | AF10: 0 | AH10: 0.95 | AI10: 0 | AJ10: 0 | AK10: 80 | AZ10: Included | BA10: No | BB10: 197
A11: 10 | B11: AGILENT TECHNOLOGIES | C11: A-US | D11: US00846U1016 | E11: USD | F11: 103.7976 | G11: 284064730 | H11: NYSE | I11: 29485.23 | J11: 1.1335849e+08 | K11: 2.0771335e+08 | L11: 1.7971705e+08 | M11: 2.0790079e+08 | N11: 2.1068761e+08 | O11: XNYS | P11: 1 | Q11: A.N | R11: 0.84373945 | S11: 0.58 | T11: 54.94 | U11: 0.98 | V11: Green | W11: Green | X11: Green | Y11: Green | Z11: Green | AA11: Green | AB11: Green | AC11: Green | AD11: Green | AE11: 0 | AF11: 0 | AH11: 0.98 | AI11: 0 | AJ11: 0 | AK11: 45 | AZ11: Included | BA11: No | BB11: 108
A12: 12 | B12: AIR PROD & CHEMICALS | C12: APD-US | D12: US0091581068 | E12: USD | F12: 255.419 | G12: 222553630 | H12: NYSE | I12: 56844.43 | J12: 2.19176e+08 | K12: 2.9626585e+08 | L12: 2.6904217e+08 | M12: 3.1152427e+08 | N12: 3.583009e+08 | O12: XNYS | P12: 1 | Q12: APD.N | R12: 0.84373945 | S12: 2.75 | T12: 58.25 | U12: 0.99 | V12: Green | W12: Green | X12: Green | Y12: Green | Z12: Green | AA12: Green | AB12: Green | AC12: Green | AD12: Green | AE12: 0 | AF12: 0.01 | AG12: Services | AH12: 0.99 | AI12: 0 | AJ12: 0.01 | AK12: 328 | AZ12: Included | BA12: No | BB12: 68
A13: 13 | B13: AIRBNB INC. CLASS A | C13: ABNB-US | D13: US0090661010 | E13: USD | F13: 110.8722 | G13: 429079560 | H13: NASDAQ | I13: 47572.98 | J13: 6.8107911e+08 | K13: 6.0294661e+08 | L13: 5.4679516e+08 | M13: 6.3286068e+08 | N13: 5.9084316e+08 | O13: XNGS | P13: 1 | Q13: ABNB.O | R13: 0.84373945 | S13: 0.62 | T13: 34.92 | U13: 0.84 | V13: Green | W13: Green | X13: Green | Y13: Green | Z13: Green | AA13: Green | AB13: Green | AC13: Green | AD13: Green | AE13: 0 | AF13: 0 | AH13: 0.84 | AI13: 0 | AJ13: 0 | AK13: 52 | AZ13: Included | BA13: No | BB13: 290
A14: 15 | B14: ALLSTATE CORPORATION | C14: ALL-US | D14: US0200021014 | E14: USD | F14: 175.3883 | G14: 263505340 | H14: NYSE | I14: 46215.75 | J14: 2.3016961e+08 | K14: 3.0072871e+08 | L14: 2.7287305e+08 | M14: 3.1614098e+08 | N14: 2.9194916e+08 | O14: XNYS | P14: 1 | Q14: ALL.N | R14: 0.84373945 | S14: 0.48 | T14: 52.89 | U14: 0.99 | V14: Green | W14: Green | X14: Green | Y14: Green | Z14: Green | AA14: Green | AB14: Green | AC14: Green | AD14: Green | AE14: 0 | AF14: 0 | AH14: 0.99 | AI14: 0 | AJ14: 0 | AK14: 26 | AZ14: Included | BA14: No | BB14: 139
A15: 16 | B15: ALNYLAM PHARMA | C15: ALNY-US | D15: US02043Q1076 | E15: USD | F15: 387.7624 | G15: 131079010 | H15: NASDAQ | I15: 50827.52 | J15: 4.7851202e+08 | K15: 2.7916715e+08 | L15: 3.2744825e+08 | M15: 3.7957111e+08 | N15: 2.3400888e+08 | O15: XNGS | P15: 1 | Q15: ALNY.O | R15: 0.84373945 | S15: 6.53 | T15: 56 | U15: 0.71 | V15: Green | W15: Green | X15: Green | Y15: Green | Z15: Green | AA15: Green | AB15: Green | AC15: Green | AD15: Green | AE15: 0 | AF15: 0 | AH15: 0.71 | AI15: 0 | AJ15: 0 | AK15: 433 | AY15: exclude_CarbonBudget | AZ15: CarbonBudget | BA15: Yes
A16: 17 | B16: ALPHABET CLASS A | C16: GOOGL-US | D16: US02079K3059 | E16: USD | F16: 175.8747 | G16: 5817000000 | H16: NASDAQ | I16: 1023063 | J16: 4.9248801e+09 | K16: 5.8717197e+09 | L16: 5.9033678e+09 | M16: 6.8459395e+09 | N16: 5.1699677e+09 | O16: XNGS | P16: 1 | Q16: GOOGL.O | R16: 0.84373945 | S16: 0.65 | T16: 57.27 | U16: 0.84 | V16: Amber | W16: Green | X16: Green | Y16: Green | Z16: Green | AA16: Green | AB16: Green | AC16: Green | AD16: Green | AE16: 0 | AF16: 0 | AH16: 0.84 | AI16: 0 | AJ16: 0 | AK16: 58 | AZ16: Included | BA16: No | BB16: 79
A17: 18 | B17: ALTRIA GROUP INC | C17: MO-US | D17: US02209S1033 | E17: USD | F17: 57.74876 | G17: 1679891000 | H17: NYSE | I17: 97011.62 | J17: 4.328411e+08 | K17: 5.0524081e+08 | L17: 4.5528886e+08 | M17: 5.2787621e+08 | N17: 4.4449354e+08 | O17: XNYS | P17: 1 | Q17: MO.N | R17: 0.84373945 | S17: 0.79 | T17: 43.06 | U17: 0.99 | V17: Green | W17: Green | X17: Green | Y17: Green | Z17: Green | AA17: Green | AB17: Green | AC17: Green | AD17: Green | AE17: 0 | AF17: 0 | AH17: 0.99 | AI17: 0 | AJ17: 0 | AK17: 77 | AZ17: Included | BA17: No | BB17: 242
A18: 19 | B18: AMAZON | C18: AMZN-US | D18: US0231351067 | E18: USD | F18: 195.2893 | G18: 10664912000 | H18: NASDAQ | I18: 2082743 | J18: 7.9772001e+09 | K18: 8.5104795e+09 | L18: 7.9912963e+09 | M18: 9.2643579e+09 | N18: 7.8246173e+09 | O18: XNGS | P18: 0.9 | Q18: AMZN.O | R18: 0.84373945 | S18: 1.36 | T18: 43.66 | U18: 0.93 | V18: Amber | W18: Green | X18: Green | Y18: Green | Z18: Green | AA18: Green | AB18: Green | AC18: Green | AD18: Green | AE18: 0 | AF18: 0 | AH18: 0.93 | AI18: 0 | AJ18: 0 | AK18: 145 | AZ18: Included | BA18: No | BB18: 232
A19: 20 | B19: AMCOR PLC | C19: AMCR-US | D19: JE00BJ1F3079 | E19: USD | F19: 7.433009 | G19: 2305359900 | H19: NYSE | I19: 17135.76 | J19: 2.3413273e+08 | K19: 2.6565502e+08 | L19: 2.0831158e+08 | M19: 2.4131198e+08 | N19: 1.9659698e+08 | O19: XNYS | P19: 1 | Q19: AMCR.N | R19: 0.84373945 | S19: 1.44 | T19: 58.26 | U19: 0.99 | V19: Green | W19: Green | X19: Green | Y19: Green | Z19: Green | AA19: Green | AB19: Green | AC19: Green | AD19: Green | AE19: 0 | AF19: 0 | AH19: 0.99 | AI19: 0 | AJ19: 0 | AK19: 154 | AZ19: Included | BA19: No | BB19: 67
A20: 21 | B20: AMEREN CORPORATION | C20: AEE-US | D20: US0236081024 | E20: USD | F20: 87.0029 | G20: 270409900 | H20: NYSE | I20: 23526.45 | J20: 1.2245225e+08 | K20: 1.5137013e+08 | L20: 1.3361704e+08 | M20: 1.548029e+08 | N20: 1.3799348e+08 | O20: XNYS | P20: 1 | Q20: AEE.N | R20: 0.84373945 | S20: 2.65 | T20: 34.93 | U20: 0.93 | V20: Green | W20: Green | X20: Green | Y20: Green | Z20: Green | AA20: Green | AB20: Green | AC20: Green | AD20: Green | AE20: 0 | AF20: 0.2326 | AH20: 0.93 | AI20: 0 | AJ20: 0.2326 | AK20: 316 | AW20: exclude_ThermalPower | AZ20: ThermalPower | BA20: Yes
A21: 22 | B21: AMERICAN ELECT. PWR. | C21: AEP-US | D21: US0255371017 | E21: USD | F21: 97.30329 | G21: 534794740 | H21: NASDAQ | I21: 52037.29 | J21: 3.0197537e+08 | K21: 3.4255525e+08 | L21: 2.7478319e+08 | M21: 3.1851057e+08 | N21: 3.0528238e+08 | O21: XNGS | P21: 1 | Q21: AEP.O | R21: 0.84373945 | S21: 2.37 | T21: 43 | U21: 0.73 | V21: Green | W21: Green | X21: Green | Y21: Green | Z21: Green | AA21: Green | AB21: Green | AC21: Green | AD21: Green | AE21: 0 | AF21: 0.2509 | AH21: 0.73 | AI21: 0 | AJ21: 0.2509 | AK21: 276 | AW21: exclude_ThermalPower | AZ21: ThermalPower | BA21: Yes
A22: 23 | B22: AMERICAN EXPRESS | C22: AXP-US | D22: US0258161092 | E22: USD | F22: 272.3673 | G22: 695882200 | H22: NYSE | I22: 189535.6 | J22: 6.1478665e+08 | K22: 7.6537691e+08 | L22: 6.8852872e+08 | M22: 7.9844639e+08 | N22: 7.2732359e+08 | O22: XNYS | P22: 0.8 | Q22: AXP.N | R22: 0.84373945 | S22: 0.71 | T22: 48.25 | U22: 0.86 | V22: Green | W22: Green | X22: Green | Y22: Green | Z22: Green | AA22: Green | AB22: Green | AC22: Green | AD22: Green | AE22: 0 | AF22: 0 | AH22: 0.86 | AI22: 0 | AJ22: 0 | AK22: 64 | AZ22: Included | BA22: No | BB22: 192
A23: 24 | B23: AMERICAN INTERN. | C23: AIG-US | D23: US0268747849 | E23: USD | F23: 71.15549 | G23: 554003850 | H23: NYSE | I23: 39420.41 | J23: 2.6003803e+08 | K23: 3.3994544e+08 | L23: 2.9556747e+08 | M23: 3.4259511e+08 | N23: 3.1062969e+08 | O23: XNYS | P23: 1 | Q23: AIG.N | R23: 0.84373945 | S23: 1.04 | T23: 41.74 | U23: 0.76 | V23: Green | W23: Green | X23: Green | Y23: Green | Z23: Green | AA23: Green | AB23: Green | AC23: Green | AD23: Green | AE23: 0 | AF23: 0 | AH23: 0.76 | AI23: 0 | AJ23: 0 | AK23: 111 | AZ23: Included | BA23: No | BB23: 252
A24: 25 | B24: AMERICAN TOWER CORP | C24: AMT-US | D24: US03027X1000 | E24: USD | F24: 180.8158 | G24: 468251220 | H24: NYSE | I24: 84667.24 | J24: 3.9275888e+08 | K24: 5.158913e+08 | L24: 3.9996884e+08 | M24: 4.6319874e+08 | N24: 4.7697854e+08 | O24: XNYS | P24: 1 | Q24: AMT.N | R24: 0.84373945 | S24: 4 | T24: 51.93 | U24: 0.5 | V24: Green | W24: Green | X24: Green | Y24: Green | Z24: Green | AA24: Green | AB24: Green | AC24: Green | AD24: Green | AE24: 0 | AF24: 0 | AH24: 0.5 | AI24: 0 | AJ24: 0 | AK24: 401 | AL24: exclude_TrustMetric | AY24: exclude_CarbonBudget | AZ24: TrustMetric; CarbonBudget | BA24: Yes
A25: 26 | B25: AMERICAN WATER WORKS | C25: AWK-US | D25: US0304201033 | E25: USD | F25: 124.7653 | G25: 202140820 | H25: NYSE | I25: 25220.16 | J25: 2.0283616e+08 | K25: 1.8588778e+08 | L25: 1.5908726e+08 | M25: 1.8429776e+08 | N25: 1.6540337e+08 | O25: XNYS | P25: 1 | Q25: AWK.N | R25: 0.84373945 | S25: 2.16 | T25: 69.08 | U25: 0.96 | V25: Green | W25: Green | X25: Green | Y25: Green | Z25: Green | AA25: Green | AB25: Green | AC25: Green | AD25: Green | AE25: 0 | AF25: 0 | AH25: 0.96 | AI25: 0 | AJ25: 0 | AK25: 247 | AZ25: Included | BA25: No | BB25: 7
A26: 27 | B26: AMERIPRISE FINANCIAL | C26: AMP-US | D26: US03076C1062 | E26: USD | F26: 441.1333 | G26: 94271570 | H26: NYSE | I26: 41586.33 | J26: 1.6819253e+08 | K26: 2.1774123e+08 | L26: 2.0042298e+08 | M26: 2.3224784e+08 | N26: 2.2542364e+08 | O26: XNYS | P26: 1 | Q26: AMP.N | R26: 0.84373945 | S26: 2.6 | T26: 51.83 | U26: 0.74 | V26: Green | W26: Green | X26: Green | Y26: Green | Z26: Green | AA26: Green | AB26: Green | AC26: Green | AD26: Green | AE26: 0 | AF26: 0 | AH26: 0.74 | AI26: 0 | AJ26: 0 | AK26: 308 | AZ26: Included | BA26: No | BB26: 157
A27: 28 | B27: AMETEK INC. | C27: AME-US | D27: US0311001004 | E27: USD | F27: 159.5409 | G27: 230953960 | H27: NYSE | I27: 36846.6 | J27: 1.9023048e+08 | K27: 2.1611398e+08 | L27: 2.1095942e+08 | M27: 2.443305e+08 | N27: 2.1001555e+08 | O27: XNYS | P27: 1 | Q27: AME.N | R27: 0.84373945 | S27: 2.18 | T27: 35.76 | U27: 0.66 | V27: Green | W27: Green | X27: Green | Y27: Green | Z27: Green | AA27: Green | AB27: Green | AC27: Green | AD27: Green | AE27: 0 | AF27: 0 | AG27: Services | AH27: 0.66 | AI27: 0 | AJ27: 0 | AK27: 251 | AZ27: Included | BA27: No | BB27: 288
A28: 29 | B28: AMGEN INC | C28: AMGN-US | D28: US0311621009 | E28: USD | F28: 250.6571 | G28: 538361900 | H28: NASDAQ | I28: 134944.2 | J28: 5.4594013e+08 | K28: 7.2116114e+08 | L28: 5.9994509e+08 | M28: 6.9446391e+08 | N28: 7.6237189e+08 | O28: XNGS | P28: 1 | Q28: AMGN.O | R28: 0.84373945 | S28: 1.06 | T28: 60.78 | U28: 0.99 | V28: Amber | W28: Green | X28: Green | Y28: Green | Z28: Green | AA28: Green | AB28: Green | AC28: Green | AD28: Green | AE28: 0 | AF28: 0 | AH28: 0.99 | AI28: 0 | AJ28: 0 | AK28: 113 | AZ28: Included | BA28: No | BB28: 43
A29: 30 | B29: AMPHENOL COR CLASS A | C29: APH-US | D29: US0320951017 | E29: USD | F29: 93.32651 | G29: 1220921100 | H29: NYSE | I29: 113944.3 | J29: 6.8199416e+08 | K29: 6.456871e+08 | L29: 7.4146339e+08 | M29: 8.5991509e+08 | N29: 5.4344609e+08 | O29: XNYS | P29: 1 | Q29: APH.N | R29: 0.84373945 | S29: 1.2 | T29: 47.59 | U29: 0.67 | V29: Green | W29: Green | X29: Green | Y29: Green | Z29: Green | AA29: Green | AB29: Green | AC29: Green | AD29: Green | AE29: 0 | AF29: 0 | AH29: 0.67 | AI29: 0 | AJ29: 0 | AK29: 126 | AZ29: Included | BA29: No | BB29: 196
A30: 31 | B30: AMRIZE | C30: AMRZ-US | D30: CH1430134226 | E30: USD | F30: 43.7276 | G30: 552735960 | H30: NYSE | I30: 24169.82 | J30: 1.2421026e+08 | K30: 1.4078713e+08 | L30: 1.4078713e+08 | M30: 1.6396716e+08 | N30: 1.4078713e+08 | O30: XNYS | P30: 0.95 | Q30: AMRZ.S | R30: 1.0711799 | U30: Not Collected | V30: Green | W30: Green | X30: Green | Y30: Green | Z30: Green | AA30: Green | AB30: Green | AC30: Green | AD30: Green | AE30: 0 | AF30: 0 | AI30: 0 | AJ30: 0 | AK30: 454 | AL30: exclude_TrustMetric | AY30: exclude_CarbonBudget | AZ30: TrustMetric; CarbonBudget | BA30: Yes
A31: 32 | B31: ANALOG DEVICES INC | C31: ADI-US | D31: US0326541051 | E31: USD | F31: 215.2244 | G31: 491955440 | H31: NASDAQ | I31: 105880.8 | J31: 7.8648679e+08 | K31: 7.6823978e+08 | L31: 7.3965538e+08 | M31: 8.5692957e+08 | N31: 7.1141108e+08 | O31: XNGS | P31: 1 | Q31: ADI.O | R31: 0.84373945 | S31: 0.29 | T31: 54.21 | U31: 0.94 | V31: Green | W31: Green | X31: Green | Y31: Green | Z31: Green | AA31: Green | AB31: Green | AC31: Green | AD31: Green | AE31: 0 | AF31: 0 | AH31: 0.94 | AI31: 0 | AJ31: 0 | AK31: 6 | AZ31: Included | BA31: No | BB31: 118
A32: 33 | B32: ANGLOGOLD ASHANTI | C32: AU-US | D32: GB00BRXH2664 | E32: USD | F32: 46.60352 | G32: 503527040 | H32: NYSE | I32: 23466.13 | J32: 1.2527038e+08 | K32: 1.2487429e+08 | L32: 1.4007955e+08 | M32: 1.62562e+08 | N32: 97503699 | O32: XNYS | P32: 1 | Q32: AU.N | R32: 0.84373945 | S32: 0.98 | T32: 49.63 | U32: 0.98 | V32: Amber | W32: Green | X32: Green | Y32: Green | Z32: Green | AA32: Green | AB32: Green | AC32: Green | AD32: Green | AE32: 0 | AF32: 0 | AH32: 0.98 | AI32: 0 | AJ32: 0 | AK32: 105 | AZ32: Included | BA32: No | BB32: 177
A33: 34 | B33: AON PLC CLASS A | C33: AON-US | D33: IE00BLP1HW54 | E33: USD | F33: 320.1058 | G33: 215626600 | H33: NYSE | I33: 69023.33 | J33: 4.2284411e+08 | K33: 4.5989012e+08 | L33: 4.2189028e+08 | M33: 4.8925184e+08 | N33: 3.9723105e+08 | O33: XNYS | P33: 1 | Q33: AON.N | R33: 0.84373945 | S33: 0.47 | T33: 38.22 | U33: 0.62 | V33: Green | W33: Green | X33: Green | Y33: Green | Z33: Green | AA33: Green | AB33: Green | AC33: Green | AD33: Green | AE33: 0 | AF33: 0 | AH33: 0.62 | AI33: 0 | AJ33: 0 | AK33: 24 | AZ33: Included | BA33: No | BB33: 279
A34: 35 | B34: APOLLO GLOBAL MNGMNT | C34: APO-US | D34: US03769M1062 | E34: USD | F34: 114.5247 | G34: 572026730 | H34: NYSE | I34: 65511.17 | J34: 4.2196472e+08 | K34: 4.4437613e+08 | L34: 3.5284316e+08 | M34: 4.0916264e+08 | N34: 5.3542697e+08 | O34: XNYS | P34: 0.7 | Q34: APO.N | R34: 0.84373945 | S34: 4.39 | T34: 45.46 | U34: 0.75 | V34: Green | W34: Green | X34: Green | Y34: Green | Z34: Green | AA34: Green | AB34: Green | AC34: Green | AD34: Green | AE34: 0 | AF34: 0 | AH34: 0.75 | AI34: 0 | AJ34: 0 | AK34: 414 | AY34: exclude_CarbonBudget | AZ34: CarbonBudget | BA34: Yes
A35: 36 | B35: APPLE | C35: AAPL-US | D35: US0378331005 | E35: USD | F35: 194.3676 | G35: 14840390000 | H35: NASDAQ | I35: 2884492 | J35: 1.1742442e+10 | K35: 1.0834249e+10 | L35: 1.0078044e+10 | M35: 1.1681697e+10 | N35: 1.0788743e+10 | O35: XNGS | P35: 1 | Q35: AAPL.O | R35: 0.84373945 | S35: 0.42 | T35: 64.95 | U35: 0.93 | V35: Amber | W35: Green | X35: Green | Y35: Green | Z35: Green | AA35: Green | AB35: Green | AC35: Green | AD35: Green | AE35: 0 | AF35: 0 | AH35: 0.93 | AI35: 0 | AJ35: 0 | AK35: 18 | AZ35: Included | BA35: No | BB35: 25
A36: 37 | B36: APPLIED MATERIALS | C36: AMAT-US | D36: US0382221051 | E36: USD | F36: 138.667 | G36: 796642460 | H36: NASDAQ | I36: 110468 | J36: 1.30406e+09 | K36: 1.1013615e+09 | L36: 1.1110164e+09 | M36: 1.2883422e+09 | N36: 1.1167945e+09 | O36: XNGS | P36: 1 | Q36: AMAT.O | R36: 0.84373945 | S36: 1.06 | T36: 58.08 | U36: 0.99 | V36: Green | W36: Green | X36: Green | Y36: Green | Z36: Green | AA36: Green | AB36: Green | AC36: Green | AD36: Green | AE36: 0 | AF36: 0 | AH36: 0.99 | AI36: 0 | AJ36: 0 | AK36: 113 | AZ36: Included | BA36: No | BB36: 70
A37: 38 | B37: APPLOVIN CORP CLSS A | C37: APP-US | D37: US03831W1080 | E37: USD | F37: 376.9244 | G37: 307636380 | H37: NASDAQ | I37: 115955.6 | J37: 2.5656797e+09 | K37: 2.212126e+09 | L37: 1.8714938e+09 | M37: 2.1680133e+09 | N37: 1.8150301e+09 | O37: XNGS | P37: 0.75 | Q37: APP.O | R37: 0.84373945 | S37: 2.53 | T37: 40.67 | U37: Not Applicable | V37: Green | W37: Green | X37: Green | Y37: Green | Z37: Green | AA37: Green | AB37: Green | AC37: Green | AD37: Green | AE37: 0 | AF37: 0 | AI37: 0 | AJ37: 0 | AK37: 299 | AZ37: Included | BA37: No | BB37: 258
A38: 39 | B38: ARCH CAPITAL GROUP | C38: ACGL-US | D38: BMG0450A1053 | E38: USD | F38: 79.71497 | G38: 373220300 | H38: NASDAQ | I38: 29751.24 | J38: 1.5319338e+08 | K38: 1.5430351e+08 | L38: 1.6897503e+08 | M38: 1.9614616e+08 | N38: 1.6335796e+08 | O38: XNGS | P38: 1 | Q38: ACGL.O | R38: 0.84373945 | S38: 3 | T38: 49.52 | U38: 0.66 | V38: Green | W38: Green | X38: Green | Y38: Green | Z38: Green | AA38: Green | AB38: Green | AC38: Green | AD38: Green | AE38: 0 | AF38: 0 | AH38: 0.66 | AI38: 0 | AJ38: 0 | AK38: 352 | AZ38: Included | BA38: No | BB38: 179
A39: 40 | B39: ARCHER-DANIELS-MID. | C39: ADM-US | D39: US0394831020 | E39: USD | F39: 53.69517 | G39: 480464480 | H39: NYSE | I39: 25798.62 | J39: 1.9756694e+08 | K39: 1.8162581e+08 | L39: 1.684143e+08 | M39: 1.9536449e+08 | N39: 1.6836819e+08 | O39: XNYS | P39: 1 | Q39: ADM.N | R39: 0.84373945 | S39: 2.7 | T39: 52.37 | U39: 0.94 | V39: Green | W39: Green | X39: Green | Y39: Green | Z39: Green | AA39: Green | AB39: Green | AC39: Green | AD39: Green | AE39: 0 | AF39: 0 | AH39: 0.94 | AI39: 0 | AJ39: 0 | AK39: 326 | AZ39: Included | BA39: No | BB39: 147
A40: 41 | B40: ARES MANAGEMENT CORP | C40: ARES-US | D40: US03990B1017 | E40: USD | F40: 154.523 | G40: 215934700 | H40: NYSE | I40: 33366.87 | J40: 2.0952462e+08 | K40: 2.5273597e+08 | L40: 2.1508802e+08 | M40: 2.4926242e+08 | N40: 2.1781916e+08 | O40: XNYS | P40: 0.9 | Q40: ARES.N | R40: 0.84373945 | S40: 2.51 | T40: 27.77 | U40: 0.57 | V40: Green | W40: Green | X40: Green | Y40: Green | Z40: Green | AA40: Green | AB40: Green | AC40: Green | AD40: Green | AE40: 0 | AF40: 0 | AH40: 0.57 | AI40: 0 | AJ40: 0 | AK40: 296 | AL40: exclude_TrustMetric | AZ40: TrustMetric | BA40: Yes
A41: 42 | B41: ARISTA NETWORKS INC. | C41: ANET-US | D41: US0404132054 | E41: USD | F41: 113.7139 | G41: 1256865400 | H41: NYSE | I41: 142923.1 | J41: 1.1211668e+09 | K41: 8.8543703e+08 | L41: 9.0588774e+08 | M41: 1.0498665e+09 | N41: 8.2316797e+08 | O41: XNYS | P41: 0.8 | Q41: ANET.N | R41: 0.84373945 | S41: 3.32 | T41: 51.8 | U41: 0.75 | V41: Green | W41: Green | X41: Green | Y41: Green | Z41: Green | AA41: Green | AB41: Green | AC41: Green | AD41: Green | AE41: 0 | AF41: 0 | AH41: 0.75 | AI41: 0 | AJ41: 0 | AK41: 372 | AY41: exclude_CarbonBudget | AZ41: CarbonBudget | BA41: Yes
A42: 43 | B42: ARTHUR J. GALLAGHER | C42: AJG-US | D42: US3635761097 | E42: USD | F42: 258.7216 | G42: 256400000 | H42: NYSE | I42: 66336.23 | J42: 3.7693273e+08 | K42: 4.2205694e+08 | L42: 3.9251187e+08 | M42: 4.5469438e+08 | N42: 4.1495323e+08 | O42: XNYS | P42: 1 | Q42: AJG.N | R42: 0.84373945 | S42: 2.55 | T42: 39.24 | U42: 0.66 | V42: Green | W42: Green | X42: Green | Y42: Green | Z42: Green | AA42: Green | AB42: Green | AC42: Green | AD42: Green | AE42: 0 | AF42: 0 | AH42: 0.66 | AI42: 0 | AJ42: 0 | AK42: 302 | AZ42: Included | BA42: No | BB42: 269
A43: 44 | B43: ASTERA LABS INC. | C43: ALAB-US | D43: US04626A1034 | E43: USD | F43: 152.8333 | G43: 166219150 | H43: NASDAQ | I43: 25403.81 | J43: 9.5277062e+08 | K43: 4.2060413e+08 | L43: 5.6550116e+08 | M43: 6.5633733e+08 | N43: 4.1664339e+08 | O43: XNGS | P43: 0.8 | Q43: ALAB.O | R43: 0.84373945 | T43: 15.83 | U43: Not Applicable | V43: Green | W43: Green | X43: Green | Y43: Green | Z43: Green | AA43: Green | AB43: Green | AC43: Green | AD43: Green | AE43: 0 | AF43: 0 | AI43: 0 | AJ43: 0 | AK43: 454 | AY43: exclude_CarbonBudget | AZ43: CarbonBudget | BA43: Yes
A44: 45 | B44: AT&T INC | C44: T-US | D44: US00206R1023 | E44: USD | F44: 24.55197 | G44: 7150385300 | H44: NYSE | I44: 175556.1 | J44: 7.0749309e+08 | K44: 8.9919713e+08 | L44: 7.6097185e+08 | M44: 8.8225193e+08 | N44: 8.2864248e+08 | O44: XNYS | P44: 1 | Q44: T.N | R44: 0.84373945 | S44: 2.48 | T44: 62.1 | U44: 0.98 | V44: Green | W44: Green | X44: Green | Y44: Green | Z44: Green | AA44: Green | AB44: Green | AC44: Green | AD44: Green | AE44: 0 | AF44: 0 | AH44: 0.98 | AI44: 0 | AJ44: 0 | AK44: 291 | AZ44: Included | BA44: No | BB44: 33
A45: 46 | B45: ATLASSIAN CORP | C45: TEAM-US | D45: US0494681010 | E45: USD | F45: 145.7501 | G45: 166284670 | H45: NASDAQ | I45: 24236.01 | J45: 4.9363342e+08 | K45: 4.5309886e+08 | L45: 4.0865843e+08 | M45: 4.7360828e+08 | N45: 4.4698159e+08 | O45: XNGS | P45: 1 | Q45: TEAM.O | R45: 0.84373945 | S45: 0.55 | T45: 61.07 | U45: 0.86 | V45: Green | W45: Green | X45: Green | Y45: Green | Z45: Green | AA45: Green | AB45: Green | AC45: Green | AD45: Green | AE45: 0 | AF45: 0 | AH45: 0.86 | AI45: 0 | AJ45: 0 | AK45: 37 | AZ45: Included | BA45: No | BB45: 39
A46: 47 | B46: ATMOS ENERGY CORP. | C46: ATO-US | D46: US0495601058 | E46: USD | F46: 143.5484 | G46: 160523570 | H46: NYSE | I46: 23042.9 | J46: 1.4202965e+08 | K46: 1.36473e+08 | L46: 1.1647785e+08 | M46: 1.3479756e+08 | N46: 1.2363312e+08 | O46: XNYS | P46: 1 | Q46: ATO.N | R46: 0.84373945 | S46: 3.46 | T46: 50.24 | U46: 0.91 | V46: Green | W46: Green | X46: Green | Y46: Green | Z46: Green | AA46: Green | AB46: Green | AC46: Green | AD46: Green | AE46: 0 | AF46: 0 | AH46: 0.91 | AI46: 0 | AJ46: 0 | AK46: 381 | AY46: exclude_CarbonBudget | AZ46: CarbonBudget | BA46: Yes
A47: 48 | B47: AUTODESK INC | C47: ADSK-US | D47: US0527691069 | E47: USD | F47: 247.6788 | G47: 213944530 | H47: NASDAQ | I47: 52989.52 | J47: 3.380718e+08 | K47: 4.1120825e+08 | L47: 4.0485391e+08 | M47: 4.69139e+08 | N47: 3.9985913e+08 | O47: XNGS | P47: 1 | Q47: ADSK.O | R47: 0.84373945 | S47: 2.47 | T47: 60.39 | U47: 0.91 | V47: Green | W47: Green | X47: Green | Y47: Green | Z47: Green | AA47: Green | AB47: Green | AC47: Green | AD47: Green | AE47: 0 | AF47: 0 | AH47: 0.91 | AI47: 0 | AJ47: 0 | AK47: 290 | AZ47: Included | BA47: No | BB47: 46
A48: 49 | B48: AUTOM. DATA PROCESSI | C48: ADP-US | D48: US0530151036 | E48: USD | F48: 262.8008 | G48: 405043150 | H48: NASDAQ | I48: 106445.7 | J48: 3.7148242e+08 | K48: 4.7709362e+08 | L48: 4.2288049e+08 | M48: 4.8969548e+08 | N48: 4.6326217e+08 | O48: XNGS | P48: 1 | Q48: ADP.O | R48: 0.84373945 | S48: 1.86 | T48: 59.95 | U48: 0.89 | V48: Green | W48: Green | X48: Green | Y48: Green | Z48: Green | AA48: Green | AB48: Green | AC48: Green | AD48: Green | AE48: 0 | AF48: 0 | AH48: 0.89 | AI48: 0 | AJ48: 0 | AK48: 204 | AZ48: Included | BA48: No | BB48: 50
A49: 50 | B49: AUTOZONE INC. | C49: AZO-US | D49: US0533321024 | E49: USD | F49: 3507.945 | G49: 16728714 | H49: NYSE | I49: 58683.41 | J49: 3.7242886e+08 | K49: 4.558286e+08 | L49: 4.3998979e+08 | M49: 5.0947557e+08 | N49: 4.1103382e+08 | O49: XNYS | P49: 1 | Q49: AZO.N | R49: 0.84373945 | S49: 3.77 | T49: 48.34 | U49: 0.85 | V49: Green | W49: Green | X49: Green | Y49: Green | Z49: Green | AA49: Green | AB49: Green | AC49: Green | AD49: Green | AE49: 0 | AF49: 0 | AH49: 0.85 | AI49: 0 | AJ49: 0 | AK49: 393 | AY49: exclude_CarbonBudget | AZ49: CarbonBudget | BA49: Yes
A50: 51 | B50: AVALONBAY COMMUNIT. | C50: AVB-US | D50: US0534841012 | E50: USD | F50: 165.233 | G50: 142383030 | H50: NYSE | I50: 23526.37 | J50: 1.64576e+08 | K50: 1.5703006e+08 | L50: 1.5721474e+08 | M50: 1.8203563e+08 | N50: 1.4917388e+08 | O50: XNYS | P50: 1 | Q50: AVB.N | R50: 0.84373945 | S50: 1.18 | T50: 59.07 | U50: 0.97 | V50: Green | W50: Green | X50: Green | Y50: Green | Z50: Green | AA50: Green | AB50: Green | AC50: Green | AD50: Green | AE50: 0 | AF50: 0 | AH50: 0.97 | AI50: 0 | AJ50: 0 | AK50: 124 | AZ50: Included | BA50: No | BB50: 56
A51: 52 | B51: AXON ENTERPRISE INC | C51: AXON-US | D51: US05464C1018 | E51: USD | F51: 653.9 | G51: 78504440 | H51: NASDAQ | I51: 51334.05 | J51: 5.5503554e+08 | K51: 4.138862e+08 | L51: 4.2893868e+08 | M51: 4.9756909e+08 | N51: 4.0602453e+08 | O51: XNGS | P51: 0.95 | Q51: AXON.O | R51: 0.84373945 | S51: 3.15 | T51: 28.33 | U51: Not Applicable | V51: Green | W51: Green | X51: Green | Y51: Green | Z51: Green | AA51: Green | AB51: Green | AC51: Green | AD51: Green | AE51: 0 | AF51: 0 | AI51: 0 | AJ51: 0 | AK51: 361 | AZ51: Included | BA51: No | BB51: 307
A52: 53 | B52: BAKER HUGHES COMPANY | C52: BKR-US | D52: US05722G1004 | E52: USD | F52: 38.19764 | G52: 985879150 | H52: NASDAQ | I52: 37658.26 | J52: 1.808189e+08 | K52: 2.808513e+08 | L52: 2.539178e+08 | M52: 2.9445838e+08 | N52: 2.6882273e+08 | O52: XNGS | P52: 1 | Q52: BKR.O | R52: 0.84373945 | S52: 6.68 | T52: 40.21 | U52: 0.93 | V52: Amber | W52: Green | X52: Green | Y52: Green | Z52: Green | AA52: Green | AB52: Green | AC52: Green | AD52: Green | AE52: 0 | AF52: 0 | AG52: Services | AH52: 0.93 | AI52: 0 | AJ52: 0 | AK52: 434 | AY52: exclude_CarbonBudget | AZ52: CarbonBudget | BA52: Yes
A53: 54 | B53: BANK NY MELLON | C53: BK-US | D53: US0640581007 | E53: USD | F53: 87.5064 | G53: 705240840 | H53: NYSE | I53: 61713.09 | J53: 2.8362823e+08 | K53: 3.3194394e+08 | L53: 3.2749875e+08 | M53: 3.7987025e+08 | N53: 3.0725332e+08 | O53: XNYS | P53: 1 | Q53: BK.N | R53: 0.84373945 | S53: 0.31 | T53: 55.08 | U53: 0.97 | V53: Green | W53: Green | X53: Green | Y53: Green | Z53: Green | AA53: Green | AB53: Green | AC53: Green | AD53: Green | AE53: 0 | AF53: 0 | AH53: 0.97 | AI53: 0 | AJ53: 0 | AK53: 8 | AZ53: Included | BA53: No | BB53: 103
A54: 55 | B54: BANK OF AMERICA | C54: BAC-US | D54: US0605051046 | E54: USD | F54: 42.22564 | G54: 7406947300 | H54: NYSE | I54: 312763.1 | J54: 1.3268499e+09 | K54: 1.6718114e+09 | L54: 1.5432748e+09 | M54: 1.7896074e+09 | N54: 1.5611002e+09 | O54: XNYS | P54: 0.9 | Q54: BAC.N | R54: 0.84373945 | S54: 1.8 | T54: 45.4 | U54: 0.96 | V54: Amber | W54: Green | X54: Green | Y54: Green | Z54: Green | AA54: Green | AB54: Green | AC54: Green | AD54: Green | AE54: 0 | AF54: 0 | AH54: 0.96 | AI54: 0 | AJ54: 0 | AK54: 197 | AZ54: Included | BA54: No | BB54: 217
A55: 60 | B55: BECTON DICKINSON | C55: BDX-US | D55: US0758871091 | E55: USD | F55: 170.3874 | G55: 286627470 | H55: NYSE | I55: 48837.71 | J55: 4.4073686e+08 | K55: 4.6617e+08 | L55: 4.3152312e+08 | M55: 5.0025943e+08 | N55: 4.2120206e+08 | O55: XNYS | P55: 1 | Q55: BDX.N | R55: 0.84373945 | S55: 3.63 | T55: 63.83 | U55: 0.74 | V55: Green | W55: Green | X55: Green | Y55: Green | Z55: Green | AA55: Green | AB55: Green | AC55: Green | AD55: Green | AE55: 0 | AF55: 0 | AH55: 0.74 | AI55: 0 | AJ55: 0 | AK55: 390 | AY55: exclude_CarbonBudget | AZ55: CarbonBudget | BA55: Yes
A56: 61 | B56: BERKSHIRE HATHAWAY B | C56: BRK.B-US | D56: US0846707026 | E56: USD | F56: 417.3067 | G56: 1342836700 | H56: NYSE | I56: 560374.6 | J56: 1.9906743e+09 | K56: 2.2905143e+09 | L56: 1.9568762e+09 | M56: 2.2671648e+09 | N56: 1.9944468e+09 | O56: XNYS | P56: 1 | Q56: BRKb.N | R56: 0.84373945 | S56: 7.31 | T56: 22.33 | U56: Not Applicable | V56: Amber | W56: Green | X56: Green | Y56: Green | Z56: Green | AA56: Amber | AB56: Green | AC56: Green | AD56: Green | AE56: 0.005 | AF56: 0.0204 | AI56: 0.005 | AJ56: 0.0204 | AK56: 438 | AV56: exclude_CoalMining | AY56: exclude_CarbonBudget | AZ56: CoalMining; CarbonBudget | BA56: Yes
A57: 62 | B57: BIOGEN INC | C57: BIIB-US | D57: US09062X1037 | E57: USD | F57: 118.8855 | G57: 146614600 | H57: NASDAQ | I57: 17430.35 | J57: 1.6312913e+08 | K57: 1.8405767e+08 | L57: 1.6061933e+08 | M57: 1.8590203e+08 | N57: 1.9986822e+08 | O57: XNGS | P57: 1 | Q57: BIIB.O | R57: 0.84373945 | S57: 1.54 | T57: 56.39 | U57: 0.99 | V57: Green | W57: Green | X57: Green | Y57: Green | Z57: Green | AA57: Green | AB57: Green | AC57: Green | AD57: Green | AE57: 0 | AF57: 0 | AH57: 0.99 | AI57: 0 | AJ57: 0 | AK57: 163 | AZ57: Included | BA57: No | BB57: 89
A58: 63 | B58: BLACKROCK INC. | C58: BLK-US | D58: US09290D1019 | E58: USD | F58: 979.8345 | G58: 154853330 | H58: NYSE | I58: 151730.6 | J58: 4.7365516e+08 | K58: 6.431035e+08 | L58: 5.417679e+08 | M58: 6.2806011e+08 | N58: 6.2908999e+08 | O58: XNYS | P58: 0.95 | Q58: BLK.N | R58: 0.84373945 | S58: 0.52 | T58: 52.19 | U58: 0.87 | V58: Amber | W58: Green | X58: Green | Y58: Green | Z58: Green | AA58: Green | AB58: Green | AC58: Green | AD58: Green | AE58: 0 | AF58: 0 | AH58: 0.87 | AI58: 0 | AJ58: 0 | AK58: 33 | AZ58: Included | BA58: No | BB58: 150
A59: 64 | B59: BLACKSTONE INC | C59: BX-US | D59: US09260D1072 | E59: USD | F59: 145.5026 | G59: 737091700 | H59: NYSE | I59: 107248.8 | J59: 5.6897468e+08 | K59: 5.8404849e+08 | L59: 5.0692762e+08 | M59: 5.8852327e+08 | N59: 5.5427664e+08 | O59: XNYS | P59: 1 | Q59: BX.N | R59: 0.84373945 | S59: 1.64 | T59: 29.18 | U59: 0.87 | V59: Amber | W59: Green | X59: Green | Y59: Green | Z59: Green | AA59: Green | AB59: Green | AC59: Green | AD59: Green | AE59: 0 | AF59: 0 | AH59: 0.87 | AI59: 0 | AJ59: 0 | AK59: 177 | AZ59: Included | BA59: No | BB59: 305
A60: 65 | B60: BLOCK INC | C60: XYZ-US | D60: US8522341036 | E60: USD | F60: 67.52006 | G60: 549574000 | H60: NYSE | I60: 37107.27 | J60: 5.830374e+08 | K60: 6.1606947e+08 | L60: 6.7461796e+08 | M60: 7.8455848e+08 | N60: 5.7696892e+08 | O60: XNYS | P60: 1 | Q60: XYZ.N | R60: 0.84373945 | S60: 0.62 | T60: 36.55 | U60: 0.71 | V60: Green | W60: Green | X60: Green | Y60: Green | Z60: Green | AA60: Green | AB60: Green | AC60: Green | AD60: Green | AE60: 0 | AF60: 0 | AH60: 0.71 | AI60: 0 | AJ60: 0 | AK60: 52 | AZ60: Included | BA60: No | BB60: 285
A61: 66 | B61: BOEING CO | C61: BA-US | D61: US0970231058 | E61: USD | F61: 196.3816 | G61: 756157700 | H61: NYSE | I61: 148495.5 | J61: 1.2125185e+09 | K61: 1.4563502e+09 | L61: 1.4757547e+09 | M61: 1.7098729e+09 | N61: 1.5341568e+09 | O61: XNYS | P61: 1 | Q61: BA.N | R61: 0.84373945 | S61: 2.83 | T61: 49.73 | U61: 0.92 | V61: Amber | W61: Amber | X61: Green | Y61: Green | Z61: Amber | AA61: Green | AB61: Not Collected | AC61: Green | AD61: Not Collected | AE61: 0 | AF61: 0 | AH61: 0.92 | AI61: 0 | AJ61: 0 | AK61: 336 | AS61: exclude_IncendiaryWeapons | AU61: exclude_WhitePhosphorus | AZ61: IncendiaryWeapons; WhitePhosphorus | BA61: Yes
A62: 67 | B62: BOOKING HOLDINGS INC | C62: BKNG-US | D62: US09857L1089 | E62: USD | F62: 4882.122 | G62: 32409885 | H62: NASDAQ | I62: 158229 | J62: 8.8038132e+08 | K62: 1.0902525e+09 | L62: 9.6734272e+08 | M62: 1.1206239e+09 | N62: 1.0542283e+09 | O62: XNGS | P62: 1 | Q62: BKNG.O | R62: 0.84373945 | S62: 1.37 | T62: 35.32 | U62: 0.5 | V62: Amber | W62: Green | X62: Green | Y62: Green | Z62: Green | AA62: Green | AB62: Green | AC62: Green | AD62: Green | AE62: 0 | AF62: 0 | AH62: 0.5 | AI62: 0 | AJ62: 0 | AK62: 146 | AL62: exclude_TrustMetric | AZ62: TrustMetric | BA62: Yes
A63: 68 | B63: BOSTON SCIENTIFIC | C63: BSX-US | D63: US1011371077 | E63: USD | F63: 90.60419 | G63: 1481751600 | H63: NYSE | I63: 134252.9 | J63: 5.5454207e+08 | K63: 7.171124e+08 | L63: 6.5893429e+08 | M63: 7.6381507e+08 | N63: 6.0011174e+08 | O63: XNYS | P63: 1 | Q63: BSX.N | R63: 0.84373945 | S63: 1.18 | T63: 55.95 | U63: 0.89 | V63: Green | W63: Green | X63: Green | Y63: Green | Z63: Green | AA63: Green | AB63: Green | AC63: Green | AD63: Green | AE63: 0 | AF63: 0 | AH63: 0.89 | AI63: 0 | AJ63: 0 | AK63: 124 | AZ63: Included | BA63: No | BB63: 92
A64: 69 | B64: BRISTOL MYERS SQUIBB | C64: BMY-US | D64: US1101221083 | E64: USD | F64: 40.89435 | G64: 2035435800 | H64: NYSE | I64: 83237.81 | J64: 4.1985774e+08 | K64: 6.2219419e+08 | L64: 5.2738665e+08 | M64: 6.1065594e+08 | N64: 5.9240885e+08 | O64: XNYS | P64: 1 | Q64: BMY.N | R64: 0.84373945 | S64: 0.34 | T64: 61.48 | U64: 0.97 | V64: Green | W64: Green | X64: Green | Y64: Green | Z64: Green | AA64: Green | AB64: Green | AC64: Green | AD64: Green | AE64: 0 | AF64: 0 | AH64: 0.97 | AI64: 0 | AJ64: 0 | AK64: 9 | AZ64: Included | BA64: No | BB64: 37
A65: 70 | B65: BROADCOM INC. | C65: AVGO-US | D65: US11135F1012 | E65: USD | F65: 250.8961 | G65: 4703471000 | H65: NASDAQ | I65: 1180082 | J65: 4.4284572e+09 | K65: 5.0063213e+09 | L65: 4.833545e+09 | M65: 5.5971754e+09 | N65: 5.1125496e+09 | O65: XNGS | P65: 1 | Q65: AVGO.O | R65: 0.84373945 | S65: 3.02 | T65: 44.8 | U65: 0.63 | V65: Green | W65: Green | X65: Green | Y65: Green | Z65: Green | AA65: Green | AB65: Green | AC65: Green | AD65: Green | AE65: 0 | AF65: 0 | AH65: 0.63 | AI65: 0 | AJ65: 0 | AK65: 355 | AZ65: Included | BA65: No | BB65: 221
A66: 71 | B66: BROADRIDGE FINANCIAL | C66: BR-US | D66: US11133T1034 | E66: USD | F66: 223.7412 | G66: 117129320 | H66: NYSE | I66: 26206.66 | J66: 1.8169192e+08 | K66: 1.3393678e+08 | L66: 1.4211338e+08 | M66: 1.6490879e+08 | N66: 1.180314e+08 | O66: XNYS | P66: 1 | Q66: BR.N | R66: 0.84373945 | S66: 0.17 | T66: 53.57 | U66: 0.92 | V66: Green | W66: Green | X66: Green | Y66: Green | Z66: Green | AA66: Green | AB66: Green | AC66: Green | AD66: Green | AE66: 0 | AF66: 0 | AH66: 0.92 | AI66: 0 | AJ66: 0 | AK66: 1 | AZ66: Included | BA66: No | BB66: 127
A67: 74 | B67: BROWN & BROWN INC. | C67: BRO-US | D67: US1152361010 | E67: USD | F67: 82.48848 | G67: 329842800 | H67: NYSE | I67: 27208.23 | J67: 2.3716157e+08 | K67: 2.6812555e+08 | L67: 3.3690392e+08 | M67: 3.9083409e+08 | N67: 2.0611085e+08 | O67: XNYS | P67: 0.85 | Q67: BRO.N | R67: 0.84373945 | S67: 2.57 | T67: 19.64 | U67: Not Applicable | V67: Green | W67: Green | X67: Green | Y67: Green | Z67: Green | AA67: Green | AB67: Green | AC67: Green | AD67: Green | AE67: 0 | AF67: 0 | AI67: 0 | AJ67: 0 | AK67: 305 | AZ67: Included | BA67: No | BB67: 317
A68: 75 | B68: BURLINGTON STORES | C68: BURL-US | D68: US1220171060 | E68: USD | F68: 239.6655 | G68: 63086660 | H68: NYSE | I68: 15119.69 | J68: 2.1003135e+08 | K68: 2.6430641e+08 | L68: 2.2992691e+08 | M68: 2.6594799e+08 | N68: 2.396319e+08 | O68: XNYS | P68: 1 | Q68: BURL.N | R68: 0.84373945 | S68: 1.95 | T68: 39.43 | U68: 0.67 | V68: Green | W68: Green | X68: Green | Y68: Green | Z68: Green | AA68: Green | AB68: Green | AC68: Green | AD68: Green | AE68: 0 | AF68: 0 | AH68: 0.67 | AI68: 0 | AJ68: 0 | AK68: 219 | AZ68: Included | BA68: No | BB68: 267
A69: 76 | B69: CADENCE DESIGN SYST. | C69: CDNS-US | D69: US1273871087 | E69: USD | F69: 298.37 | G69: 272490000 | H69: NASDAQ | I69: 81302.85 | J69: 4.3794543e+08 | K69: 5.3859672e+08 | L69: 5.2651361e+08 | M69: 6.0883081e+08 | N69: 5.1202628e+08 | O69: XNGS | P69: 1 | Q69: CDNS.O | R69: 0.84373945 | S69: 0.44 | T69: 57.4 | U69: 0.85 | V69: Green | W69: Green | X69: Green | Y69: Green | Z69: Green | AA69: Green | AB69: Green | AC69: Green | AD69: Green | AE69: 0 | AF69: 0 | AH69: 0.85 | AI69: 0 | AJ69: 0 | AK69: 22 | AZ69: Included | BA69: No | BB69: 76
A70: 81 | B70: CAPITAL ONE FIN. | C70: COF-US | D70: US14040H1059 | E70: USD | F70: 188.7865 | G70: 639517330 | H70: NYSE | I70: 120732.2 | J70: 6.0243937e+08 | K70: 7.9197106e+08 | L70: 7.0009094e+08 | M70: 8.113917e+08 | N70: 6.3588293e+08 | O70: XNYS | P70: 1 | Q70: COF.N | R70: 0.84373945 | S70: 0.54 | T70: 31.93 | U70: 0.9 | V70: Green | W70: Green | X70: Green | Y70: Green | Z70: Green | AA70: Green | AB70: Green | AC70: Green | AD70: Green | AE70: 0 | AF70: 0 | AH70: 0.9 | AI70: 0 | AJ70: 0 | AK70: 36 | AZ70: Included | BA70: No | BB70: 299
A71: 82 | B71: CARDINAL HEALTH INC. | C71: CAH-US | D71: US14149Y1082 | E71: USD | F71: 126.3868 | G71: 238793640 | H71: NYSE | I71: 30180.36 | J71: 3.7158331e+08 | K71: 3.15455e+08 | L71: 3.0491819e+08 | M71: 3.5372422e+08 | N71: 2.7695422e+08 | O71: XNYS | P71: 1 | Q71: CAH.N | R71: 0.84373945 | S71: 2.23 | T71: 58.54 | U71: 0.97 | V71: Amber | W71: Green | X71: Green | Y71: Green | Z71: Green | AA71: Green | AB71: Green | AC71: Green | AD71: Green | AE71: 0 | AF71: 0 | AH71: 0.97 | AI71: 0 | AJ71: 0 | AK71: 256 | AZ71: Included | BA71: No | BB71: 63
A72: 83 | B72: CARNIVAL CORPORATION | C72: CCL-US | D72: PA1436583006 | E72: USD | F72: 26.71104 | G72: 1167404000 | H72: NYSE | I72: 31182.58 | J72: 3.9449503e+08 | K72: 5.0107017e+08 | L72: 5.2092371e+08 | M72: 6.0457422e+08 | N72: 4.9950074e+08 | O72: XNYS | P72: 0.9 | Q72: CCL.N | R72: 0.84373945 | S72: 1.97 | T72: 51.99 | U72: 0.98 | V72: Green | W72: Green | X72: Green | Y72: Green | Z72: Green | AA72: Green | AB72: Green | AC72: Green | AD72: Green | AE72: 0 | AF72: 0 | AH72: 0.98 | AI72: 0 | AJ72: 0 | AK72: 223 | AZ72: Included | BA72: No | BB72: 153
A73: 84 | B73: CARRIER GLOBAL CORP. | C73: CARR-US | D73: US14448C1045 | E73: USD | F73: 57.81703 | G73: 851022800 | H73: NYSE | I73: 49203.61 | J73: 2.6416604e+08 | K73: 3.0961137e+08 | L73: 2.8792098e+08 | M73: 3.3353575e+08 | N73: 3.116966e+08 | O73: XNYS | P73: 0.95 | Q73: CARR.N | R73: 0.84373945 | S73: 0.76 | T73: 54.46 | U73: 0.68 | V73: Green | W73: Green | X73: Green | Y73: Green | Z73: Green | AA73: Green | AB73: Green | AC73: Green | AD73: Green | AE73: 0 | AF73: 0 | AH73: 0.68 | AI73: 0 | AJ73: 0 | AK73: 73 | AZ73: Included | BA73: No | BB73: 114
A74: 85 | B74: CARVANA CO | C74: CVNA-US | D74: US1468691027 | E74: USD | F74: 305.3507 | G74: 138083500 | H74: NYSE | I74: 42163.89 | J74: 8.3264931e+08 | K74: 9.7479766e+08 | L74: 9.5432603e+08 | M74: 1.1049575e+09 | N74: 8.0910274e+08 | O74: XNYS | P74: 1 | Q74: CVNA.N | R74: 0.84373945 | S74: 4.63 | T74: 16.23 | U74: Not Applicable | V74: Green | W74: Green | X74: Green | Y74: Green | Z74: Green | AA74: Green | AB74: Green | AC74: Green | AD74: Green | AE74: 0 | AF74: 0 | AI74: 0 | AJ74: 0 | AK74: 418 | AY74: exclude_CarbonBudget | AZ74: CarbonBudget | BA74: Yes
A75: 86 | B75: CASEYS GENERAL STORE | C75: CASY-US | D75: US1475281036 | E75: USD | F75: 429.476 | G75: 37180984 | H75: NASDAQ | I75: 15968.34 | J75: 1.0013506e+08 | K75: 1.5117861e+08 | L75: 1.5087733e+08 | M75: 1.7455161e+08 | N75: 1.2193578e+08 | O75: XNGS | P75: 1 | Q75: CASY.O | R75: 0.84373945 | S75: 2.22 | T75: 31.54 | U75: 0.66 | V75: Green | W75: Green | X75: Green | Y75: Green | Z75: Green | AA75: Green | AB75: Green | AC75: Green | AD75: Green | AE75: 0 | AF75: 0 | AH75: 0.66 | AI75: 0 | AJ75: 0 | AK75: 254 | AZ75: Included | BA75: No | BB75: 300
A76: 87 | B76: CATERPILLAR | C76: CAT-US | D76: US1491231015 | E76: USD | F76: 371.7955 | G76: 468478900 | H76: NYSE | I76: 174178.4 | J76: 1.2661215e+09 | K76: 9.1027018e+08 | L76: 9.6307729e+08 | M76: 1.1173007e+09 | N76: 8.5326647e+08 | O76: XNYS | P76: 1 | Q76: CAT.N | R76: 0.84373945 | S76: 2.76 | T76: 50.68 | U76: 0.99 | V76: Green | W76: Green | X76: Green | Y76: Green | Z76: Green | AA76: Green | AB76: Green | AC76: Green | AD76: Green | AE76: 0 | AF76: 0 | AH76: 0.99 | AI76: 0 | AJ76: 0 | AK76: 329 | AZ76: Included | BA76: No | BB76: 167
A77: 88 | B77: CBRE GROUP INC. | C77: CBRE-US | D77: US12504L1098 | E77: USD | F77: 140.3055 | G77: 297554320 | H77: NYSE | I77: 41748.51 | J77: 1.948771e+08 | K77: 2.1323221e+08 | L77: 1.9661068e+08 | M77: 2.2761095e+08 | N77: 2.1825078e+08 | O77: XNYS | P77: 1 | Q77: CBRE.N | R77: 0.84373945 | S77: 0.34 | T77: 65.1 | U77: 0.93 | V77: Green | W77: Green | X77: Green | Y77: Green | Z77: Green | AA77: Green | AB77: Green | AC77: Green | AD77: Green | AE77: 0 | AF77: 0 | AH77: 0.93 | AI77: 0 | AJ77: 0 | AK77: 9 | AZ77: Included | BA77: No | BB77: 22
A78: 89 | B78: CDW CORP. | C78: CDW-US | D78: US12514G1085 | E78: USD | F78: 142.5158 | G78: 131060750 | H78: NASDAQ | I78: 18678.23 | J78: 1.9870005e+08 | K78: 1.9697858e+08 | L78: 1.671545e+08 | M78: 1.9364908e+08 | N78: 2.0756047e+08 | O78: XNGS | P78: 1 | Q78: CDW.O | R78: 0.84373945 | S78: 1.55 | T78: 53.48 | U78: 0.62 | V78: Green | W78: Green | X78: Green | Y78: Green | Z78: Green | AA78: Green | AB78: Green | AC78: Green | AD78: Green | AE78: 0 | AF78: 0 | AH78: 0.62 | AI78: 0 | AJ78: 0 | AK78: 165 | AZ78: Included | BA78: No | BB78: 128
A79: 91 | B79: CENCORA | C79: COR-US | D79: US03073E1055 | E79: USD | F79: 249.7013 | G79: 193877880 | H79: NYSE | I79: 48411.57 | J79: 3.7411896e+08 | K79: 3.9735851e+08 | L79: 3.2836328e+08 | M79: 3.8039533e+08 | N79: 3.557558e+08 | O79: XNYS | P79: 1 | Q79: COR.N | R79: 0.84373945 | S79: 2.32 | T79: 52.48 | U79: 0.88 | V79: Amber | W79: Green | X79: Green | Y79: Green | Z79: Green | AA79: Green | AB79: Green | AC79: Green | AD79: Green | AE79: 0 | AF79: 0 | AH79: 0.88 | AI79: 0 | AJ79: 0 | AK79: 266 | AZ79: Included | BA79: No | BB79: 146
A80: 93 | B80: CENTERPOINT ENERGY | C80: CNP-US | D80: US15189T1079 | E80: USD | F80: 32.47141 | G80: 652864870 | H80: NYSE | I80: 21199.44 | J80: 1.36112e+08 | K80: 1.806457e+08 | L80: 1.7379579e+08 | M80: 2.012412e+08 | N80: 1.6197056e+08 | O80: XNYS | P80: 1 | Q80: CNP.N | R80: 0.84373945 | S80: 2.23 | T80: 49.18 | U80: 0.87 | V80: Green | W80: Green | X80: Green | Y80: Green | Z80: Green | AA80: Green | AB80: Green | AC80: Green | AD80: Green | AE80: 0 | AF80: 0.061 | AH80: 0.87 | AI80: 0 | AJ80: 0.061 | AK80: 256 | AZ80: Included | BA80: No | BB80: 183
A81: 95 | B81: CHARLES SCHWAB CORP. | C81: SCHW-US | D81: US8085131055 | E81: USD | F81: 81.78017 | G81: 1815219400 | H81: NYSE | I81: 148448.9 | J81: 6.7640722e+08 | K81: 6.9979386e+08 | L81: 6.5371556e+08 | M81: 7.5855694e+08 | N81: 6.7173071e+08 | O81: XNYS | P81: 0.95 | Q81: SCHW.N | R81: 0.84373945 | S81: 2.42 | T81: 38.33 | U81: 0.72 | V81: Green | W81: Green | X81: Green | Y81: Green | Z81: Green | AA81: Green | AB81: Green | AC81: Green | AD81: Green | AE81: 0 | AF81: 0 | AH81: 0.72 | AI81: 0 | AJ81: 0 | AK81: 286 | AZ81: Included | BA81: No | BB81: 277
A82: 96 | B82: CHARTER COM. CLASS A | C82: CHTR-US | D82: US16119P1084 | E82: USD | F82: 236.8834 | G82: 136627990 | H82: NASDAQ | I82: 32364.91 | J82: 4.5364545e+08 | K82: 4.9450728e+08 | L82: 5.0148956e+08 | M82: 5.8158532e+08 | N82: 4.4348571e+08 | O82: XNGS | P82: 0.7 | Q82: CHTR.O | R82: 0.84373945 | S82: 3.01 | T82: 45.81 | U82: 0.66 | V82: Green | W82: Green | X82: Green | Y82: Green | Z82: Green | AA82: Green | AB82: Green | AC82: Green | AD82: Green | AE82: 0 | AF82: 0 | AH82: 0.66 | AI82: 0 | AJ82: 0 | AK82: 354 | AZ82: Included | BA82: No | BB82: 213
A83: 97 | B83: CHENIERE ENERGY | C83: LNG-US | D83: US16411R2085 | E83: USD | F83: 202.7308 | G83: 219768100 | H83: NYSE | I83: 44553.77 | J83: 3.5445793e+08 | K83: 4.0997499e+08 | L83: 3.9862263e+08 | M83: 4.6165575e+08 | N83: 3.8159767e+08 | O83: XNYS | P83: 1 | Q83: LNG.N | R83: 0.84373945 | S83: 2.85 | T83: 48.78 | U83: 0.87 | V83: Green | W83: Green | X83: Green | Y83: Green | Z83: Green | AA83: Green | AB83: Green | AC83: Green | AD83: Green | AE83: 0 | AF83: 0 | AH83: 0.87 | AI83: 0 | AJ83: 0 | AK83: 339 | AZ83: Included | BA83: No | BB83: 187
A84: 98 | B84: CHEVRON CORPORATION | C84: CVX-US | D84: US1667641005 | E84: USD | F84: 134.9889 | G84: 2047393900 | H84: NYSE | I84: 276375.5 | J84: 1.0527285e+09 | K84: 1.295121e+09 | L84: 1.2915266e+09 | M84: 1.4984398e+09 | N84: 1.1907335e+09 | O84: XNYS | P84: 0.95 | Q84: CVX.N | R84: 0.84373945 | S84: 5.5 | T84: 37.03 | U84: 0.99 | V84: Amber | W84: Green | X84: Green | Y84: Green | Z84: Green | AA84: Green | AB84: Green | AC84: Green | AD84: Green | AE84: 0 | AF84: 0.0099 | AG84: Production | AH84: 0.99 | AI84: 0 | AJ84: 0.0099 | AK84: 426 | AX84: exclude_ShaleOilGas | AY84: exclude_CarbonBudget | AZ84: ShaleOilGas; CarbonBudget | BA84: Yes
A85: 99 | B85: CHIPOTLE MEX. GRILL | C85: CMG-US | D85: US1696561059 | E85: USD | F85: 37.24185 | G85: 1340885000 | H85: NYSE | I85: 49937.04 | J85: 6.1885516e+08 | K85: 6.5827088e+08 | L85: 6.7435932e+08 | M85: 7.8285077e+08 | N85: 5.979666e+08 | O85: XNYS | P85: 1 | Q85: CMG.N | R85: 0.84373945 | S85: 0.79 | T85: 47.44 | U85: 0.93 | V85: Green | W85: Green | X85: Green | Y85: Green | Z85: Green | AA85: Green | AB85: Green | AC85: Green | AD85: Green | AE85: 0 | AF85: 0 | AH85: 0.93 | AI85: 0 | AJ85: 0 | AK85: 77 | AZ85: Included | BA85: No | BB85: 197
A86: 100 | B86: CHUBB LIMITED | C86: CB-US | D86: CH0044328745 | E86: USD | F86: 236.9773 | G86: 398690300 | H86: NYSE | I86: 94480.55 | J86: 3.6320186e+08 | K86: 4.5705631e+08 | L86: 4.3746583e+08 | M86: 5.0743723e+08 | N86: 4.3803608e+08 | O86: XNYS | P86: 0.95 | Q86: CB.N | R86: 0.84373945 | S86: 2.51 | T86: 41.89 | U86: 0.95 | V86: Green | W86: Green | X86: Green | Y86: Green | Z86: Green | AA86: Green | AB86: Green | AC86: Green | AD86: Green | AE86: 0 | AF86: 0 | AH86: 0.95 | AI86: 0 | AJ86: 0 | AK86: 296 | AZ86: Included | BA86: No | BB86: 249
A87: 101 | B87: CHURCH & DWIGHT CO | C87: CHD-US | D87: US1713401024 | E87: USD | F87: 81.08892 | G87: 243608690 | H87: NYSE | I87: 19753.97 | J87: 1.6873648e+08 | K87: 1.9273885e+08 | L87: 1.9056749e+08 | M87: 2.2059092e+08 | N87: 1.6975386e+08 | O87: XNYS | P87: 1 | Q87: CHD.N | R87: 0.84373945 | S87: 2.2 | T87: 52.75 | U87: 0.94 | V87: Green | W87: Green | X87: Green | Y87: Green | Z87: Green | AA87: Green | AB87: Green | AC87: Green | AD87: Green | AE87: 0 | AF87: 0 | AH87: 0.94 | AI87: 0 | AJ87: 0 | AK87: 252 | AZ87: Included | BA87: No | BB87: 141
A88: 103 | B88: CIGNA GROUP | C88: CI-US | D88: US1255231003 | E88: USD | F88: 259.7286 | G88: 266928070 | H88: NYSE | I88: 69328.87 | J88: 4.5528226e+08 | K88: 5.1334735e+08 | L88: 4.9067012e+08 | M88: 5.6858536e+08 | N88: 5.1729069e+08 | O88: XNYS | P88: 1 | Q88: CI.N | R88: 0.84373945 | S88: 2.22 | T88: 67.99 | U88: 0.93 | V88: Green | W88: Green | X88: Green | Y88: Green | Z88: Green | AA88: Green | AB88: Green | AC88: Green | AD88: Green | AE88: 0 | AF88: 0 | AH88: 0.93 | AI88: 0 | AJ88: 0 | AK88: 254 | AZ88: Included | BA88: No | BB88: 11
A89: 104 | B89: CINCINNATI FINANCIAL | C89: CINF-US | D89: US1720621010 | E89: USD | F89: 132.6165 | G89: 156376420 | H89: NASDAQ | I89: 20738.09 | J89: 67787864 | K89: 86436162 | L89: 72106660 | M89: 83557387 | N89: 83369202 | O89: XNGS | P89: 1 | Q89: CINF.O | R89: 0.84373945 | S89: 3.22 | T89: 34.07 | U89: 0.66 | V89: Green | W89: Green | X89: Green | Y89: Green | Z89: Green | AA89: Green | AB89: Green | AC89: Green | AD89: Green | AE89: 0 | AF89: 0 | AH89: 0.66 | AI89: 0 | AJ89: 0 | AK89: 365 | AZ89: Included | BA89: No | BB89: 292
A90: 105 | B90: CINTAS CORPORATION | C90: CTAS-US | D90: US1729081059 | E90: USD | F90: 183.9819 | G90: 402977940 | H90: NASDAQ | I90: 74140.64 | J90: 2.6648445e+08 | K90: 3.1312471e+08 | L90: 2.7400287e+08 | M90: 3.1752454e+08 | N90: 3.1233906e+08 | O90: XNGS | P90: 0.85 | Q90: CTAS.O | R90: 0.84373945 | S90: 1.63 | T90: 45.18 | U90: 0.67 | V90: Green | W90: Green | X90: Green | Y90: Green | Z90: Green | AA90: Green | AB90: Green | AC90: Green | AD90: Green | AE90: 0 | AF90: 0 | AH90: 0.67 | AI90: 0 | AJ90: 0 | AK90: 172 | AZ90: Included | BA90: No | BB90: 218
A91: 106 | B91: Circle Internet Group, Inc. Class A | C91: CRCL-US | D91: US1725731079 | E91: USD | F91: 115.2415 | G91: 211836560 | H91: NYSE | I91: 24412.36 | J91: 1.733602e+09 | K91: 4.1953084e+09 | L91: 4.1953084e+09 | M91: 4.8696275e+09 | N91: 4.1953084e+09 | O91: XNYS | P91: 0.75 | Q91: CRCL.N | R91: 0.84373945 | U91: Not Collected | V91: Not Collected | W91: Green | X91: Green | Y91: Green | Z91: Green | AA91: Green | AB91: Green | AC91: Green | AD91: Green | AE91: 0 | AF91: 0 | AI91: 0 | AJ91: 0 | AK91: 454 | AL91: exclude_TrustMetric | AM91: exclude_NBROverallFlag | AY91: exclude_CarbonBudget | AZ91: TrustMetric; NBROverallFlag; CarbonBudget | BA91: Yes
A92: 107 | B92: CISCO SYSTEMS INC | C92: CSCO-US | D92: US17275R1023 | E92: USD | F92: 57.45008 | G92: 3959998300 | H92: NASDAQ | I92: 227502.2 | J92: 1.4308107e+09 | K92: 1.2342565e+09 | L92: 1.1800785e+09 | M92: 1.3689942e+09 | N92: 1.1150463e+09 | O92: XNGS | P92: 1 | Q92: CSCO.O | R92: 0.84373945 | S92: 0.25 | T92: 65.66 | U92: 0.99 | V92: Green | W92: Green | X92: Green | Y92: Green | Z92: Green | AA92: Green | AB92: Green | AC92: Green | AD92: Green | AE92: 0 | AF92: 0 | AH92: 0.99 | AI92: 0 | AJ92: 0 | AK92: 5 | AZ92: Included | BA92: No | BB92: 18
A93: 108 | B93: CITIGROUP INC | C93: C-US | D93: US1729674242 | E93: USD | F93: 81.29374 | G93: 1840898000 | H93: NYSE | I93: 149653.5 | J93: 1.1484754e+09 | K93: 1.0800098e+09 | L93: 1.0824221e+09 | M93: 1.2567213e+09 | N93: 9.9311001e+08 | O93: XNYS | P93: 1 | Q93: C.N | R93: 0.84373945 | S93: 0.56 | T93: 53.38 | U93: 0.96 | V93: Green | W93: Green | X93: Green | Y93: Green | Z93: Green | AA93: Green | AB93: Green | AC93: Green | AD93: Green | AE93: 0 | AF93: 0 | AH93: 0.96 | AI93: 0 | AJ93: 0 | AK93: 39 | AZ93: Included | BA93: No | BB93: 131
A94: 109 | B94: CITIZENS FIN. GROUP | C94: CFG-US | D94: US1746101054 | E94: USD | F94: 43.32651 | G94: 431349000 | H94: NYSE | I94: 18688.85 | J94: 1.5906096e+08 | K94: 1.8931385e+08 | L94: 1.9697454e+08 | M94: 2.284569e+08 | N94: 1.8402927e+08 | O94: XNYS | P94: 1 | Q94: CFG.N | R94: 0.84373945 | S94: 2.86 | T94: 34.54 | U94: 0.88 | V94: Green | W94: Green | X94: Green | Y94: Green | Z94: Green | AA94: Green | AB94: Green | AC94: Green | AD94: Green | AE94: 0 | AF94: 0 | AH94: 0.88 | AI94: 0 | AJ94: 0 | AK94: 340 | AZ94: Included | BA94: No | BB94: 291
A95: 110 | B95: CLOUDFLARE INC | C95: NET-US | D95: US18915M1071 | E95: USD | F95: 167.4091 | G95: 312872200 | H95: NYSE | I95: 52377.66 | J95: 4.1471291e+08 | K95: 4.7469568e+08 | L95: 5.1191103e+08 | M95: 5.932709e+08 | N95: 3.9351655e+08 | O95: XNYS | P95: 1 | Q95: NET.N | R95: 0.84373945 | S95: 9.48 | T95: 55.44 | U95: 0.82 | V95: Green | W95: Green | X95: Green | Y95: Green | Z95: Green | AA95: Green | AB95: Green | AC95: Green | AD95: Green | AE95: 0 | AF95: 0 | AH95: 0.82 | AI95: 0 | AJ95: 0 | AK95: 446 | AY95: exclude_CarbonBudget | AZ95: CarbonBudget | BA95: Yes
A96: 111 | B96: CME GROUP CLASS A | C96: CME-US | D96: US12572Q1058 | E96: USD | F96: 230.0051 | G96: 360377040 | H96: NASDAQ | I96: 82888.56 | J96: 4.356316e+08 | K96: 5.8882885e+08 | L96: 5.467271e+08 | M96: 6.3317071e+08 | N96: 5.0473538e+08 | O96: XNGS | P96: 1 | Q96: CME.O | R96: 0.84373945 | S96: 2.28 | T96: 43.34 | U96: 0.61 | V96: Green | W96: Green | X96: Green | Y96: Green | Z96: Green | AA96: Green | AB96: Green | AC96: Green | AD96: Green | AE96: 0 | AF96: 0 | AH96: 0.61 | AI96: 0 | AJ96: 0 | AK96: 262 | AZ96: Included | BA96: No | BB96: 234
A97: 112 | B97: CMS ENERGY CORP | C97: CMS-US | D97: US1258961002 | E97: USD | F97: 62.39973 | G97: 299335450 | H97: NYSE | I97: 18678.45 | J97: 1.4997623e+08 | K97: 1.6351341e+08 | L97: 1.4499445e+08 | M97: 1.6790146e+08 | N97: 1.5109611e+08 | O97: XNYS | P97: 1 | Q97: CMS.N | R97: 0.84373945 | S97: 3.23 | T97: 44.26 | U97: 0.91 | V97: Green | W97: Green | X97: Green | Y97: Green | Z97: Green | AA97: Green | AB97: Green | AC97: Green | AD97: Green | AE97: 0 | AF97: 0.451 | AH97: 0.91 | AI97: 0 | AJ97: 0.451 | AK97: 366 | AW97: exclude_ThermalPower | AZ97: ThermalPower | BA97: Yes
A98: 113 | B98: COCA-COLA CO | C98: KO-US | D98: US1912161007 | E98: USD | F98: 59.84809 | G98: 4303667500 | H98: NYSE | I98: 257566.3 | J98: 7.2645929e+08 | K98: 1.051613e+09 | L98: 9.1423038e+08 | M98: 1.0599458e+09 | N98: 1.0225264e+09 | O98: XNYS | P98: 0.9 | Q98: KO.N | R98: 0.84373945 | S98: 0.67 | T98: 44.27 | U98: 0.93 | V98: Amber | W98: Green | X98: Green | Y98: Green | Z98: Green | AA98: Green | AB98: Green | AC98: Green | AD98: Green | AE98: 0 | AF98: 0 | AH98: 0.93 | AI98: 0 | AJ98: 0 | AK98: 61 | AZ98: Included | BA98: No | BB98: 224
A99: 114 | B99: COCA-COLA EUROPACIF. | C99: CCEP-US | D99: GB00BDCPN049 | E99: USD | F99: 77.09506 | G99: 460780980 | H99: NASDAQ | I99: 35523.94 | J99: 1.6299581e+08 | K99: 1.8014714e+08 | L99: 1.5069389e+08 | M99: 1.7455601e+08 | N99: 1.4423449e+08 | O99: XNGS | P99: 0.45 | Q99: CCEP.O | R99: 0.84373945 | S99: 0.66 | T99: 55.82 | U99: 0.94 | V99: Amber | W99: Green | X99: Green | Y99: Green | Z99: Green | AA99: Green | AB99: Green | AC99: Green | AD99: Green | AE99: 0 | AF99: 0 | AH99: 0.94 | AI99: 0 | AJ99: 0 | AK99: 60 | AZ99: Included | BA99: No | BB99: 97
A100: 115 | B100: COGNIZANT TECHN SOL | C100: CTSH-US | D100: US1924461023 | E100: USD | F100: 61.75969 | G100: 488395940 | H100: NASDAQ | I100: 30163.18 | J100: 2.4887808e+08 | K100: 2.7036006e+08 | L100: 2.4495973e+08 | M100: 2.836539e+08 | N100: 2.5139346e+08 | O100: XNGS | P100: 1 | Q100: CTSH.O | R100: 0.84373945 | S100: 0.96 | T100: 66.89 | U100: 0.96 | V100: Green | W100: Green | X100: Green | Y100: Green | Z100: Green | AA100: Green | AB100: Green | AC100: Green | AD100: Green | AE100: 0 | AF100: 0 | AH100: 0.96 | AI100: 0 | AJ100: 0 | AK100: 103 | AZ100: Included | BA100: No | BB100: 15
...

Sheet Top 250
A1: Rank | B1: Company | C1: Ticker | D1: ISIN | E1: Currency (Local) | F1: Price (EUR) | G1: NOSH | H1: Exchange Name (VND) | I1: Sec Market Value (EUR) | J1: 20 days aver. turn EUR | K1: 6 month aver. turnover EUR | L1: 3 month average turnover EUR | M1: 3 months aver. Turnover USD | N1: 12 month aver. turnover EUR | O1: MIC | P1: Free Float | Q1: #Symbol | R1: FX/Index Ccy | S1: ClimateCuAlignIEANZTgt2050-values | T1: ESG Performance Score | U1: Reported Emissions - Emissions Trust Metric | V1: NBR Overall Flag | W1: Anti-personnel Mines - Overall Flag | X1: Biological Weapons - Overall Flag | Y1: Chemical Weapons - Overall Flag | Z1: Cluster Munitions - Overall Flag | AA1: Depleted Uranium - Overall Flag | AB1: Incendiary Weapons - Overall Flag | AC1: Nuclear Weapons Outside NPT - Overall Flag | AD1: White Phosphorous Weapons - Overall Flag | AE1: Thermal Coal Mining - Maximum Percentage of Revenues (%) | AF1: Power Generation - Thermal Maximum Percentage of Revenues (%) | AG1: Shale Oil and/or Gas - Involvement tie | AH1: Trust Metric Numeric | AI1: Coal Mining Numeric | AJ1: Thermal Power Numeric | AK1: Carbon Budget Rank | AL1: exclusion_1_TrustMetric | AM1: exclusion_2_NBROverallFlag | AN1: exclusion_3_APMines | AO1: exclusion_4_BiologicalWeapons | AP1: exclusion_5_ChemicalWeapons | AQ1: exclusion_6_ClusterMunitions | AR1: exclusion_7_DepletedUranium | AS1: exclusion_8_IncendiaryWeapons | AT1: exclusion_9_NuclearWeaponsNonNPT | AU1: exclusion_10_WhitePhosphorus | AV1: exclusion_11_CoalMining | AW1: exclusion_12_ThermalPower | AX1: exclusion_13_ShaleOilGas | AY1: exclusion_14_CarbonBudget | AZ1: Exclusion Summary | BA1: Excluded | BB1: ESG Performance Rank | BC1: Symbol | BD1: Close Prc_EOD | BE1: Price in Index Currency | BF1: FFMC | BG1: FFMC Rank
A2: 305 | B2: MICROSOFT CORP | C2: MSFT-US | D2: US5949181045 | E2: USD | F2: 432.864 | G2: 7433166500 | H2: NASDAQ | I2: 3217550 | J2: 9.4369412e+09 | K2: 8.7216266e+09 | L2: 8.529722e+09 | M2: 9.8852136e+09 | N2: 8.4822591e+09 | O2: XNGS | P2: 1 | Q2: MSFT.O | R2: 0.84373945 | S2: 0.47 | T2: 65.25 | U2: 0.91 | V2: Amber | W2: Green | X2: Green | Y2: Green | Z2: Green | AA2: Green | AB2: Green | AC2: Green | AD2: Green | AE2: 0 | AF2: 0 | AH2: 0.91 | AI2: 0 | AJ2: 0 | AK2: 24 | AZ2: Included | BA2: No | BB2: 21 | BC2: MSFT.O | BD2: 509.04 | BE2: 429.49713 | BF2: 2.714774e+12 | BG2: 1
A3: 36 | B3: APPLE | C3: AAPL-US | D3: US0378331005 | E3: USD | F3: 194.3676 | G3: 14840390000 | H3: NASDAQ | I3: 2884492 | J3: 1.1742442e+10 | K3: 1.0834249e+10 | L3: 1.0078044e+10 | M3: 1.1681697e+10 | N3: 1.0788743e+10 | O3: XNGS | P3: 1 | Q3: AAPL.O | R3: 0.84373945 | S3: 0.42 | T3: 64.95 | U3: 0.93 | V3: Amber | W3: Green | X3: Green | Y3: Green | Z3: Green | AA3: Green | AB3: Green | AC3: Green | AD3: Green | AE3: 0 | AF3: 0 | AH3: 0.93 | AI3: 0 | AJ3: 0 | AK3: 18 | AZ3: Included | BA3: No | BB3: 25 | BC3: AAPL.O | BD3: 238.15 | BE3: 200.93655 | BF3: 2.4337588e+12 | BG3: 2
A4: 19 | B4: AMAZON | C4: AMZN-US | D4: US0231351067 | E4: USD | F4: 195.2893 | G4: 10664912000 | H4: NASDAQ | I4: 2082743 | J4: 7.9772001e+09 | K4: 8.5104795e+09 | L4: 7.9912963e+09 | M4: 9.2643579e+09 | N4: 7.8246173e+09 | O4: XNGS | P4: 0.9 | Q4: AMZN.O | R4: 0.84373945 | S4: 1.36 | T4: 43.66 | U4: 0.93 | V4: Amber | W4: Green | X4: Green | Y4: Green | Z4: Green | AA4: Green | AB4: Green | AC4: Green | AD4: Green | AE4: 0 | AF4: 0 | AH4: 0.93 | AI4: 0 | AJ4: 0 | AK4: 145 | AZ4: Included | BA4: No | BB4: 232 | BC4: AMZN.O | BD4: 234.05 | BE4: 197.47722 | BF4: 1.5815633e+12 | BG4: 3
A5: 300 | B5: META PLTFORM ORD | C5: META-US | D5: US30303M1027 | E5: USD | F5: 644.1287 | G5: 2168962400 | H5: NASDAQ | I5: 1397091 | J5: 7.2998813e+09 | K5: 8.553469e+09 | L5: 7.5540757e+09 | M5: 8.7499585e+09 | N5: 7.956731e+09 | O5: XNGS | P5: 1 | Q5: META.O | R5: 0.84373945 | S5: 0.84 | T5: 44.17 | U5: 0.91 | V5: Amber | W5: Green | X5: Green | Y5: Green | Z5: Green | AA5: Green | AB5: Green | AC5: Green | AD5: Green | AE5: 0 | AF5: 0 | AH5: 0.91 | AI5: 0 | AJ5: 0 | AK5: 85 | AZ5: Included | BA5: No | BB5: 226 | BC5: META.O | BD5: 779 | BE5: 657.27303 | BF5: 1.1787807e+12 | BG5: 4
A6: 70 | B6: BROADCOM INC. | C6: AVGO-US | D6: US11135F1012 | E6: USD | F6: 250.8961 | G6: 4703471000 | H6: NASDAQ | I6: 1180082 | J6: 4.4284572e+09 | K6: 5.0063213e+09 | L6: 4.833545e+09 | M6: 5.5971754e+09 | N6: 5.1125496e+09 | O6: XNGS | P6: 1 | Q6: AVGO.O | R6: 0.84373945 | S6: 3.02 | T6: 44.8 | U6: 0.63 | V6: Green | W6: Green | X6: Green | Y6: Green | Z6: Green | AA6: Green | AB6: Green | AC6: Green | AD6: Green | AE6: 0 | AF6: 0 | AH6: 0.63 | AI6: 0 | AJ6: 0 | AK6: 355 | AZ6: Included | BA6: No | BB6: 221 | BC6: AVGO.O | BD6: 360 | BE6: 303.7462 | BF6: 9.9568219e+11 | BG6: 5
A7: 17 | B7: ALPHABET CLASS A | C7: GOOGL-US | D7: US02079K3059 | E7: USD | F7: 175.8747 | G7: 5817000000 | H7: NASDAQ | I7: 1023063 | J7: 4.9248801e+09 | K7: 5.8717197e+09 | L7: 5.9033678e+09 | M7: 6.8459395e+09 | N7: 5.1699677e+09 | O7: XNGS | P7: 1 | Q7: GOOGL.O | R7: 0.84373945 | S7: 0.65 | T7: 57.27 | U7: 0.84 | V7: Amber | W7: Green | X7: Green | Y7: Green | Z7: Green | AA7: Green | AB7: Green | AC7: Green | AD7: Green | AE7: 0 | AF7: 0 | AH7: 0.84 | AI7: 0 | AJ7: 0 | AK7: 58 | AZ7: Included | BA7: No | BB7: 79 | BC7: GOOGL.O | BD7: 251.16 | BE7: 211.9136 | BF7: 8.6319872e+11 | BG7: 6
A8: 433 | B8: TESLA INC | C8: TSLA-US | D8: US88160R1014 | E8: USD | F8: 290.1604 | G8: 3225449000 | H8: NASDAQ | I8: 935897.7 | J8: 2.1367951e+10 | K8: 2.9445717e+10 | L8: 2.7999684e+10 | M8: 3.241537e+10 | N8: 2.7610006e+10 | O8: XNGS | P8: 0.85 | Q8: TSLA.O | R8: 0.84373945 | S8: 2.89 | T8: 60.66 | U8: 0.91 | V8: Amber | W8: Green | X8: Green | Y8: Green | Z8: Green | AA8: Green | AB8: Green | AC8: Green | AD8: Green | AE8: 0 | AF8: 0 | AH8: 0.91 | AI8: 0 | AJ8: 0 | AK8: 342 | AZ8: Included | BA8: No | BB8: 45 | BC8: TSLA.O | BD8: 421.62 | BE8: 355.73743 | BF8: 6.7120565e+11 | BG8: 7
A9: 258 | B9: JP MORGAN CHASE & CO | C9: JPM-US | D9: US46625H1005 | E9: USD | F9: 252.8076 | G9: 2749754000 | H9: NYSE | I9: 695158.8 | J9: 1.7506895e+09 | K9: 2.2815889e+09 | L9: 2.0406602e+09 | M9: 2.3670612e+09 | N9: 2.1415283e+09 | O9: XNYS | P9: 1 | Q9: JPM.N | R9: 0.84373945 | S9: 1.76 | T9: 47.38 | U9: 0.94 | V9: Green | W9: Green | X9: Green | Y9: Green | Z9: Green | AA9: Green | AB9: Green | AC9: Green | AD9: Green | AE9: 0 | AF9: 0 | AH9: 0.94 | AI9: 0 | AJ9: 0 | AK9: 191 | AZ9: Included | BA9: No | BB9: 199 | BC9: JPM.N | BD9: 309.19 | BE9: 260.8758 | BF9: 5.8653283e+11 | BG9: 8
A10: 471 | B10: VISA INC | C10: V-US | D10: US92826C8394 | E10: USD | F10: 298.7199 | G10: 1698682500 | H10: NYSE | I10: 507430.3 | J10: 1.7368346e+09 | K10: 2.083355e+09 | L10: 1.9676343e+09 | M10: 2.2791641e+09 | N10: 1.929801e+09 | O10: XNYS | P10: 1 | Q10: V.N | R10: 0.84373945 | S10: 0.82 | T10: 55.33 | U10: 0.87 | V10: Green | W10: Green | X10: Green | Y10: Green | Z10: Green | AA10: Green | AB10: Green | AC10: Green | AD10: Green | AE10: 0 | AF10: 0 | AH10: 0.87 | AI10: 0 | AJ10: 0 | AK10: 82 | AZ10: Included | BA10: No | BB10: 100 | BC10: V.N | BD10: 340.03 | BE10: 286.89673 | BF10: 4.2813893e+11 | BG10: 9
A11: 172 | B11: ELI LILLY AND CO | C11: LLY-US | D11: US5324571083 | E11: USD | F11: 607.3391 | G11: 946456800 | H11: NYSE | I11: 574820.2 | J11: 4.4289558e+09 | K11: 2.9085759e+09 | L11: 2.7474037e+09 | M11: 3.1851577e+09 | N11: 2.816072e+09 | O11: XNYS | P11: 0.85 | Q11: LLY.N | R11: 0.84373945 | S11: 2.55 | T11: 59.02 | U11: 1 | V11: Green | W11: Green | X11: Green | Y11: Green | Z11: Green | AA11: Green | AB11: Green | AC11: Green | AD11: Green | AE11: 0 | AF11: 0 | AH11: 1 | AI11: 0 | AJ11: 0 | AK11: 302 | AZ11: Included | BA11: No | BB11: 57 | BC11: LLY.N | BD11: 764.71 | BE11: 645.21599 | BF11: 4.1224872e+11 | BG11: 10
A12: 319 | B12: NETFLIX INC. | C12: NFLX-US | D12: US64110L1061 | E12: USD | F12: 1028.034 | G12: 424926360 | H12: NASDAQ | I12: 436838.7 | J12: 2.9174361e+09 | K12: 3.9762351e+09 | L12: 3.4028095e+09 | M12: 3.9478521e+09 | N12: 3.3245206e+09 | O12: XNGS | P12: 1 | Q12: NFLX.O | R12: 0.84373945 | S12: 1.85 | T12: 44.05 | U12: 0.8 | V12: Green | W12: Green | X12: Green | Y12: Green | Z12: Green | AA12: Green | AB12: Green | AC12: Green | AD12: Green | AE12: 0 | AF12: 0 | AH12: 0.8 | AI12: 0 | AJ12: 0 | AK12: 203 | AZ12: Included | BA12: No | BB12: 227 | BC12: NFLX.O | BD12: 1200.51 | BE12: 1012.9176 | BF12: 3.6857808e+11 | BG12: 11
A13: 293 | B13: MASTERCARD INC | C13: MA-US | D13: US57636Q1040 | E13: USD | F13: 511.1453 | G13: 897274200 | H13: NYSE | I13: 458637.4 | J13: 1.2482194e+09 | K13: 1.3987234e+09 | L13: 1.3689725e+09 | M13: 1.5866785e+09 | N13: 1.3074093e+09 | O13: XNYS | P13: 0.9 | Q13: MA.N | R13: 0.84373945 | S13: 0.57 | T13: 58.24 | U13: 0.86 | V13: Green | W13: Green | X13: Green | Y13: Green | Z13: Green | AA13: Green | AB13: Green | AC13: Green | AD13: Green | AE13: 0 | AF13: 0 | AH13: 0.86 | AI13: 0 | AJ13: 0 | AK13: 43 | AZ13: Included | BA13: No | BB13: 69 | BC13: MA.N | BD13: 586.42 | BE13: 494.78569 | BF13: 3.4827349e+11 | BG13: 12
... A52: 220 | B52: GILEAD SCIENCES INC. | C52: GILD-US | D52: US3755581036 | E52: USD | F52: 97.94333 | G52: 1240806900 | H52: NASDAQ | I52: 121528.8 | J52: 6.8788614e+08 | K52: 8.2666118e+08 | L52: 6.9104648e+08 | M52: 8.0031528e+08 | N52: 7.0710623e+08 | O52: XNGS | P52: 1 | Q52: GILD.O | R52: 0.84373945 | S52: 0.57 | T52: 55.84 | U52: 0.89 | V52: Green | W52: Green | X52: Green | Y52: Green | Z52: Green | AA52: Green | AB52: Green | AC52: Green | AD52: Green | AE52: 0 | AF52: 0 | AH52: 0.89 | AI52: 0 | AJ52: 0 | AK52: 43 | AZ52: Included | BA52: No | BB52: 96 | BC52: GILD.O | BD52: 110.86 | BE52: 93.536955 | BF52: 1.0253861e+11 | BG52: 51
A53: 232 | B53: HONEYWELL INTER. INC | C53: HON-US | D53: US4385161066 | E53: USD | F53: 190.1604 | G53: 634896550 | H53: NASDAQ | I53: 120732.2 | J53: 5.9014427e+08 | K53: 7.6908309e+08 | L53: 6.6576827e+08 | M53: 7.7195475e+08 | N53: 7.7663867e+08 | O53: XNGS | P53: 1 | Q53: HON.O | R53: 0.84373945 | S53: 0.56 | T53: 53.96 | U53: 0.89 | V53: Green | W53: Green | X53: Green | Y53: Green | Z53: Green | AA53: Green | AB53: Green | AC53: Green | AD53: Green | AE53: 0 | AF53: 0 | AG53: Services | AH53: 0.89 | AI53: 0 | AJ53: 0 | AK53: 39 | AZ53: Included | BA53: No | BB53: 120 | BC53: HON.O | BD53: 210.95 | BE53: 177.98684 | BF53: 1.018665e+11 | BG53: 52
A54: 144 | B54: DANAHER CORPORATION | C54: DHR-US | D54: US2358511028 | E54: USD | F54: 180.7476 | G54: 716051600 | H54: NYSE | I54: 129424.6 | J54: 5.8575044e+08 | K54: 7.272495e+08 | L54: 6.7680308e+08 | M54: 7.8485664e+08 | N54: 7.3025046e+08 | O54: XNYS | P54: 0.9 | Q54: DHR.N | R54: 0.84373945 | S54: 1.57 | T54: 57.15 | U54: 0.63 | V54: Green | W54: Green | X54: Green | Y54: Green | Z54: Green | AA54: Green | AB54: Green | AC54: Green | AD54: Green | AE54: 0 | AF54: 0 | AH54: 0.63 | AI54: 0 | AJ54: 0 | AK54: 166 | AZ54: Included | BA54: No | BB54: 80 | BC54: DHR.N | BD54: 190.47 | BE54: 160.70705 | BF54: 9.8280583e+10 | BG54: 53
A55: 165 | B55: EATON CORP. PLC | C55: ETN-US | D55: IE00B8KQN827 | E55: USD | F55: 296.6462 | G55: 389300000 | H55: NYSE | I55: 115484.4 | J55: 8.2685783e+08 | K55: 8.1398401e+08 | L55: 6.9814216e+08 | M55: 8.0936852e+08 | N55: 7.6758201e+08 | O55: XNYS | P55: 1 | Q55: ETN.N | R55: 0.84373945 | S55: 2.6 | T55: 54.76 | U55: 0.99 | V55: Green | W55: Green | X55: Green | Y55: Green | Z55: Green | AA55: Green | AB55: Green | AC55: Green | AD55: Green | AE55: 0 | AF55: 0 | AG55: Services | AH55: 0.99 | AI55: 0 | AJ55: 0 | AK55: 308 | AZ55: Included | BA55: No | BB55: 110 | BC55: ETN.N | BD55: 371.19 | BE55: 313.18765 | BF55: 9.7438715e+10 | BG55: 54
A56: 455 | B56: UNION PACIFIC CORP | C56: UNP-US | D56: US9078181081 | E56: USD | F56: 194.4444 | G56: 593039860 | H56: NYSE | I56: 115313.3 | J56: 7.3027253e+08 | K56: 7.103976e+08 | L56: 7.71268e+08 | M56: 8.9392519e+08 | N56: 6.43011e+08 | O56: XNYS | P56: 1 | Q56: UNP.N | R56: 0.84373945 | S56: 1.44 | T56: 54.72 | U56: 0.97 | V56: Green | W56: Green | X56: Green | Y56: Green | Z56: Green | AA56: Green | AB56: Green | AC56: Green | AD56: Amber | AE56: 0 | AF56: 0 | AG56: Services | AH56: 0.97 | AI56: 0 | AJ56: 0 | AK56: 154 | AZ56: Included | BA56: No | BB56: 111 | BC56: UNP.N | BD56: 216 | BE56: 182.24772 | BF56: 9.7294363e+10 | BG56: 55
A57: 30 | B57: AMPHENOL COR CLASS A | C57: APH-US | D57: US0320951017 | E57: USD | F57: 93.32651 | G57: 1220921100 | H57: NYSE | I57: 113944.3 | J57: 6.8199416e+08 | K57: 6.456871e+08 | L57: 7.4146339e+08 | M57: 8.5991509e+08 | N57: 5.4344609e+08 | O57: XNYS | P57: 1 | Q57: APH.N | R57: 0.84373945 | S57: 1.2 | T57: 47.59 | U57: 0.67 | V57: Green | W57: Green | X57: Green | Y57: Green | Z57: Green | AA57: Green | AB57: Green | AC57: Green | AD57: Green | AE57: 0 | AF57: 0 | AH57: 0.67 | AI57: 0 | AJ57: 0 | AK57: 126 | AZ57: Included | BA57: No | BB57: 196 | BC57: APH.N | BD57: 119.04 | BE57: 100.43874 | BF57: 9.6139305e+10 | BG57: 56
A58: 304 | B58: MICRON TECHNOLOGY | C58: MU-US | D58: US5951121038 | E58: USD | F58: 100.4267 | G58: 1119125100 | H58: NASDAQ | I58: 112390 | J58: 1.9268302e+09 | K58: 2.0156003e+09 | L58: 2.1964685e+09 | M58: 2.54895e+09 | N58: 2.0712965e+09 | O58: XNGS | P58: 1 | Q58: MU.O | R58: 0.84373945 | S58: 2.35 | T58: 52.37 | U58: 0.85 | V58: Green | W58: Green | X58: Green | Y58: Green | Z58: Green | AA58: Green | AB58: Green | AC58: Green | AD58: Green | AE58: 0 | AF58: 0 | AH58: 0.85 | AI58: 0 | AJ58: 0 | AK58: 273 | AZ58: Included | BA58: No | BB58: 147 | BC58: MU.O | BD58: 158.82 | BE58: 134.0027 | BF58: 9.4827911e+10 | BG58: 57
A59: 37 | B59: APPLIED MATERIALS | C59: AMAT-US | D59: US0382221051 | E59: USD | F59: 138.667 | G59: 796642460 | H59: NASDAQ | I59: 110468 | J59: 1.30406e+09 | K59: 1.1013615e+09 | L59: 1.1110164e+09 | M59: 1.2883422e+09 | N59: 1.1167945e+09 | O59: XNGS | P59: 1 | Q59: AMAT.O | R59: 0.84373945 | S59: 1.06 | T59: 58.08 | U59: 0.99 | V59: Green | W59: Green | X59: Green | Y59: Green | Z59: Green | AA59: Green | AB59: Green | AC59: Green | AD59: Green | AE59: 0 | AF59: 0 | AH59: 0.99 | AI59: 0 | AJ59: 0 | AK59: 113 | AZ59: Included | BA59: No | BB59: 70 | BC59: AMAT.O | BD59: 173.54 | BE59: 146.42254 | BF59: 9.3206226e+10 | BG59: 58
A60: 147 | B60: DEERE & CO | C60: DE-US | D60: US2441991054 | E60: USD | F60: 423.2719 | G60: 270827060 | H60: NYSE | I60: 114633.5 | J60: 6.5746806e+08 | K60: 5.7939163e+08 | L60: 5.409376e+08 | M60: 6.2728905e+08 | N60: 5.4904284e+08 | O60: XNYS | P60: 0.95 | Q60: DE.N | R60: 0.84373945 | S60: 1.65 | T60: 58.74 | U60: 0.99 | V60: Green | W60: Green | X60: Green | Y60: Green | Z60: Green | AA60: Green | AB60: Green | AC60: Green | AD60: Green | AE60: 0 | AF60: 0 | AH60: 0.99 | AI60: 0 | AJ60: 0 | AK60: 178 | AZ60: Included | BA60: No | BB60: 60 | BC60: DE.N | BD60: 468.7 | BE60: 395.46068 | BF60: 9.1884753e+10 | BG60: 59
A61: 118 | B61: COMCAST | C61: CMCSA-US | D61: US20030N1019 | E61: USD | F61: 29.1432 | G61: 3682762200 | H61: NASDAQ | I61: 107327.5 | J61: 6.1617247e+08 | K61: 7.2922211e+08 | L61: 6.1986807e+08 | M61: 7.1795622e+08 | N61: 7.5155177e+08 | O61: XNGS | P61: 1 | Q61: CMCSA.O | R61: 0.84373945 | S61: 1.76 | T61: 51.68 | U61: 0.92 | V61: Green | W61: Green | X61: Green | Y61: Green | Z61: Green | AA61: Green | AB61: Green | AC61: Green | AD61: Green | AE61: 0 | AF61: 0 | AH61: 0.92 | AI61: 0 | AJ61: 0 | AK61: 191 | AZ61: Included | BA61: No | BB61: 159 | BC61: CMCSA.O | BD61: 32.29 | BE61: 27.244347 | BF61: 9.0556425e+10 | BG61: 60
A62: 49 | B62: AUTOM. DATA PROCESSI | C62: ADP-US | D62: US0530151036 | E62: USD | F62: 262.8008 | G62: 405043150 | H62: NASDAQ | I62: 106445.7 | J62: 3.7148242e+08 | K62: 4.7709362e+08 | L62: 4.2288049e+08 | M62: 4.8969548e+08 | N62: 4.6326217e+08 | O62: XNGS | P62: 1 | Q62: ADP.O | R62: 0.84373945 | S62: 1.86 | T62: 59.95 | U62: 0.89 | V62: Green | W62: Green | X62: Green | Y62: Green | Z62: Green | AA62: Green | AB62: Green | AC62: Green | AD62: Green | AE62: 0 | AF62: 0 | AH62: 0.89 | AI62: 0 | AJ62: 0 | AK62: 204 | AZ62: Included | BA62: No | BB62: 50 | BC62: ADP.O | BD62: 288.69 | BE62: 243.57914 | BF62: 8.9812406e+10 | BG62: 61
A63: 32 | B63: ANALOG DEVICES INC | C63: ADI-US | D63: US0326541051 | E63: USD | F63: 215.2244 | G63: 491955440 | H63: NASDAQ | I63: 105880.8 | J63: 7.8648679e+08 | K63: 7.6823978e+08 | L63: 7.3965538e+08 | M63: 8.5692957e+08 | N63: 7.1141108e+08 | O63: XNGS | P63: 1 | Q63: ADI.O | R63: 0.84373945 | S63: 0.29 | T63: 54.21 | U63: 0.94 | V63: Green | W63: Green | X63: Green | Y63: Green | Z63: Green | AA63: Green | AB63: Green | AC63: Green | AD63: Green | AE63: 0 | AF63: 0 | AH63: 0.94 | AI63: 0 | AJ63: 0 | AK63: 6 | AZ63: Included | BA63: No | BB63: 118 | BC63: ADI.O | BD63: 244.1 | BE63: 205.9568 | BF63: 8.933582e+10 | BG63: 62
A64: 297 | B64: MEDTRONIC PLC | C64: MDT-US | D64: IE00BTN1Y115 | E64: USD | F64: 79.1176 | G64: 1281264600 | H64: NYSE | I64: 101483 | J64: 6.4158453e+08 | K64: 6.0478856e+08 | L64: 6.0217139e+08 | M64: 6.9785897e+08 | N64: 5.6903676e+08 | O64: XNYS | P64: 1 | Q64: MDT.N | R64: 0.84373945 | S64: 1.33 | T64: 63.53 | U64: 0.96 | V64: Green | W64: Green | X64: Green | Y64: Green | Z64: Green | AA64: Green | AB64: Green | AC64: Green | AD64: Green | AE64: 0 | AF64: 0 | AH64: 0.96 | AI64: 0 | AJ64: 0 | AK64: 143 | AZ64: Included | BA64: No | BB64: 28 | BC64: MDT.N | BD64: 94.19 | BE64: 79.471819 | BF64: 8.5530358e+10 | BG64: 63
A65: 268 | B65: KLA CORPORATION | C65: KLAC-US | D65: US4824801009 | E65: USD | F65: 742.6865 | G65: 131961360 | H65: NASDAQ | I65: 98005.91 | J65: 7.6879403e+08 | K65: 7.9744869e+08 | L65: 8.2526447e+08 | M65: 9.5556304e+08 | N65: 7.5777953e+08 | O65: XNGS | P65: 1 | Q65: KLAC.O | R65: 0.84373945 | S65: 1.51 | T65: 50.03 | U65: 0.91 | V65: Green | W65: Green | X65: Green | Y65: Green | Z65: Green | AA65: Green | AB65: Green | AC65: Green | AD65: Green | AE65: 0 | AF65: 0 | AH65: 0.91 | AI65: 0 | AJ65: 0 | AK65: 160 | AZ65: Included | BA65: No | BB65: 174 | BC65: KLAC.O | BD65: 990.57 | BE65: 835.78299 | BF65: 8.2691462e+10 | BG65: 64
A66: 18 | B66: ALTRIA GROUP INC | C66: MO-US | D66: US02209S1033 | E66: USD | F66: 57.74876 | G66: 1679891000 | H66: NYSE | I66: 97011.62 | J66: 4.328411e+08 | K66: 5.0524081e+08 | L66: 4.5528886e+08 | M66: 5.2787621e+08 | N66: 4.4449354e+08 | O66: XNYS | P66: 1 | Q66: MO.N | R66: 0.84373945 | S66: 0.79 | T66: 43.06 | U66: 0.99 | V66: Green | W66: Green | X66: Green | Y66: Green | Z66: Green | AA66: Green | AB66: Green | AC66: Green | AD66: Green | AE66: 0 | AF66: 0 | AH66: 0.99 | AI66: 0 | AJ66: 0 | AK66: 77 | AZ66: Included | BA66: No | BB66: 242 | BC66: MO.N | BD66: 64.81 | BE66: 54.682754 | BF66: 8.1852533e+10 | BG66: 65
A67: 421 | B67: SYNOPSYS INC. | C67: SNPS-US | D67: US8716071076 | E67: USD | F67: 517.5969 | G67: 185043640 | H67: NASDAQ | I67: 95778 | J67: 5.5977571e+08 | K67: 6.7536349e+08 | L67: 8.2125405e+08 | M67: 9.5168815e+08 | N67: 5.9997564e+08 | O67: XNGS | P67: 1 | Q67: SNPS.O | R67: 0.84373945 | S67: 1.75 | T67: 58 | U67: 0.9 | V67: Green | W67: Green | X67: Green | Y67: Green | Z67: Green | AA67: Green | AB67: Green | AC67: Green | AD67: Green | AE67: 0 | AF67: 0 | AH67: 0.9 | AI67: 0 | AJ67: 0 | AK67: 189 | AZ67: Included | BA67: No | BB67: 71 | BC67: SNPS.O | BD67: 425.97 | BE67: 359.40769 | BF67: 8.0811689e+10 | BG67: 66
A68: 483 | B68: WELLTOWER INC | C68: WELL-US | D68: US95040Q1040 | E68: USD | F68: 140.3226 | G68: 667943900 | H68: NYSE | I68: 93727.6 | J68: 3.4774103e+08 | K68: 4.0724809e+08 | L68: 3.8523147e+08 | M68: 4.4602975e+08 | N68: 3.7334679e+08 | O68: XNYS | P68: 1 | Q68: WELL.N | R68: 0.84373945 | S68: 2.04 | T68: 58.28 | U68: 0.84 | V68: Green | W68: Green | X68: Green | Y68: Green | Z68: Green | AA68: Green | AB68: Green | AC68: Green | AD68: Green | AE68: 0 | AF68: 0 | AH68: 0.84 | AI68: 0 | AJ68: 0 | AK68: 230 | AZ68: Included | BA68: No | BB68: 66 | BC68: WELL.N | BD68: 165.21 | BE68: 139.39419 | BF68: 7.9081695e+10 | BG68: 67
... A81: 445 | B81: TRANE TECHNOLOGIES | C81: TT-US | D81: IE00BK9ZQ967 | E81: USD | F81: 361.9304 | G81: 222515370 | H81: NYSE | I81: 80535.06 | J81: 3.7250815e+08 | K81: 5.011852e+08 | L81: 4.5667544e+08 | M81: 5.2905725e+08 | N81: 4.6765553e+08 | O81: XNYS | P81: 1 | Q81: TT.N | R81: 0.84373945 | S81: 1.65 | T81: 61.74 | U81: 0.98 | V81: Green | W81: Green | X81: Green | Y81: Green | Z81: Green | AA81: Green | AB81: Green | AC81: Green | AD81: Green | AE81: 0 | AF81: 0 | AH81: 0.98 | AI81: 0 | AJ81: 0 | AK81: 178 | AZ81: Included | BA81: No | BB81: 35 | BC81: TT.N | BD81: 399.99 | BE81: 337.48734 | BF81: 6.7950621e+10 | BG81: 80
A82: 322 | B82: NIKE INC | C82: NKE-US | D82: US6541061031 | E82: USD | F82: 66.88854 | G82: 1188015700 | H82: NYSE | I82: 79464.64 | J82: 5.370476e+08 | K82: 1.0234951e+09 | L82: 9.0130919e+08 | M82: 1.0473027e+09 | N82: 9.622578e+08 | O82: XNYS | P82: 1 | Q82: NKE.N | R82: 0.84373945 | S82: 0.42 | T82: 56.09 | U82: Not Applicable | V82: Green | W82: Green | X82: Green | Y82: Green | Z82: Green | AA82: Green | AB82: Green | AC82: Green | AD82: Green | AE82: 0 | AF82: 0 | AI82: 0 | AJ82: 0 | AK82: 18 | AZ82: Included | BA82: No | BB82: 91 | BC82: NKE.N | BD82: 72.75 | BE82: 61.382045 | BF82: 6.7047448e+10 | BG82: 81
A83: 141 | B83: CVS HEALTH CORP. | C83: CVS-US | D83: US1266501006 | E83: USD | F83: 60.84657 | G83: 1268326400 | H83: NYSE | I83: 77173.3 | J83: 3.7150935e+08 | K83: 5.2036635e+08 | L83: 4.2818274e+08 | M83: 4.958411e+08 | N83: 5.8738684e+08 | O83: XNYS | P83: 1 | Q83: CVS.N | R83: 0.84373945 | S83: 0.46 | T83: 61.35 | U83: 0.99 | V83: Amber | W83: Green | X83: Green | Y83: Green | Z83: Green | AA83: Green | AB83: Green | AC83: Green | AD83: Green | AE83: 0 | AF83: 0 | AH83: 0.99 | AI83: 0 | AJ83: 0 | AK83: 23 | AZ83: Included | BA83: No | BB83: 38 | BC83: CVS.N | BD83: 73.48 | BE83: 61.997975 | BF83: 6.5114167e+10 | BG83: 82
A84: 391 | B84: ROYAL CARIBBEAN | C84: RCL-US | D84: LR0008862868 | E84: USD | F84: 294.1372 | G84: 271627660 | H84: NYSE | I84: 79895.8 | J84: 5.255555e+08 | K84: 5.7522895e+08 | L84: 6.2235401e+08 | M84: 7.2238473e+08 | N84: 4.9708978e+08 | O84: XNYS | P84: 0.95 | Q84: RCL.N | R84: 0.84373945 | S84: 1.06 | T84: 51.2 | U84: 0.93 | V84: Green | W84: Green | X84: Green | Y84: Green | Z84: Green | AA84: Green | AB84: Green | AC84: Green | AD84: Green | AE84: 0 | AF84: 0 | AH84: 0.93 | AI84: 0 | AJ84: 0 | AK84: 113 | AZ84: Included | BA84: No | BB84: 162 | BC84: RCL.N | BD84: 321.7 | BE84: 271.43098 | BF84: 6.4040676e+10 | BG84: 83
A85: 1 | B85: 3M CO | C85: MMM-US | D85: US88579Y1010 | E85: USD | F85: 135.4497 | G85: 532629700 | H85: NYSE | I85: 72144.55 | J85: 4.0894509e+08 | K85: 4.9663707e+08 | L85: 4.4055249e+08 | M85: 5.1103236e+08 | N85: 4.7372284e+08 | O85: XNYS | P85: 1 | Q85: MMM.N | R85: 0.84373945 | S85: 2.06 | T85: 62.06 | U85: 0.99 | V85: Green | W85: Green | X85: Green | Y85: Green | Z85: Green | AA85: Green | AB85: Green | AC85: Green | AD85: Green | AE85: 0 | AF85: 0 | AG85: Services | AH85: 0.99 | AI85: 0 | AJ85: 0 | AK85: 233 | AZ85: Included | BA85: No | BB85: 34 | BC85: MMM.N | BD85: 156.5 | BE85: 132.04522 | BF85: 6.0871189e+10 | BG85: 84
A86: 479 | B86: WASTE MANAGEMENT | C86: WM-US | D86: US94106L1098 | E86: USD | F86: 193.7361 | G86: 402830320 | H86: NYSE | I86: 78042.77 | J86: 3.4990151e+08 | K86: 3.5546445e+08 | L86: 3.3357195e+08 | M86: 3.8671755e+08 | N86: 3.3180569e+08 | O86: XNYS | P86: 0.9 | Q86: WM.N | R86: 0.84373945 | S86: 2.13 | T86: 57.3 | U86: 0.95 | V86: Green | W86: Green | X86: Green | Y86: Green | Z86: Green | AA86: Green | AB86: Green | AC86: Green | AD86: Green | AE86: 0 | AF86: 0 | AH86: 0.95 | AI86: 0 | AJ86: 0 | AK86: 243 | AZ86: Included | BA86: No | BB86: 78 | BC86: WM.N | BD86: 213.88 | BE86: 180.45899 | BF86: 5.9262991e+10 | BG86: 85
A87: 306 | B87: MONDELEZ INT CLASS A | C87: MDLZ-US | D87: US6092071058 | E87: USD | F87: 54.11333 | G87: 1293945400 | H87: NASDAQ | I87: 70019.7 | J87: 3.8302632e+08 | K87: 4.9191745e+08 | L87: 4.2270167e+08 | M87: 4.8984579e+08 | N87: 4.9200633e+08 | O87: XNGS | P87: 1 | Q87: MDLZ.O | R87: 0.84373945 | S87: 0.78 | T87: 49.02 | U87: 0.96 | V87: Green | W87: Green | X87: Green | Y87: Green | Z87: Green | AA87: Green | AB87: Green | AC87: Green | AD87: Green | AE87: 0 | AF87: 0 | AH87: 0.96 | AI87: 0 | AJ87: 0 | AK87: 74 | AZ87: Included | BA87: No | BB87: 184 | BC87: MDLZ.O | BD87: 62.7 | BE87: 52.902464 | BF87: 5.9078378e+10 | BG87: 86
A88: 103 | B88: CIGNA GROUP | C88: CI-US | D88: US1255231003 | E88: USD | F88: 259.7286 | G88: 266928070 | H88: NYSE | I88: 69328.87 | J88: 4.5528226e+08 | K88: 5.1334735e+08 | L88: 4.9067012e+08 | M88: 5.6858536e+08 | N88: 5.1729069e+08 | O88: XNYS | P88: 1 | Q88: CI.N | R88: 0.84373945 | S88: 2.22 | T88: 67.99 | U88: 0.93 | V88: Green | W88: Green | X88: Green | Y88: Green | Z88: Green | AA88: Green | AB88: Green | AC88: Green | AD88: Green | AE88: 0 | AF88: 0 | AH88: 0.93 | AI88: 0 | AJ88: 0 | AK88: 254 | AZ88: Included | BA88: No | BB88: 11 | BC88: CI.N | BD88: 294.21 | BE88: 248.23658 | BF88: 5.8495489e+10 | BG88: 87
A89: 357 | B89: PNC FINANCIAL SERV. | C89: PNC-US | D89: US6934751057 | E89: USD | F89: 172.1198 | G89: 393807370 | H89: NYSE | I89: 67782.05 | J89: 2.4355779e+08 | K89: 3.6918784e+08 | L89: 3.4360391e+08 | M89: 3.9881033e+08 | N89: 3.5815657e+08 | O89: XNYS | P89: 1 | Q89: PNC.N | R89: 0.84373945 | S89: 2.32 | T89: 41.84 | U89: 0.97 | V89: Green | W89: Green | X89: Green | Y89: Green | Z89: Green | AA89: Green | AB89: Green | AC89: Green | AD89: Green | AE89: 0 | AF89: 0 | AH89: 0.97 | AI89: 0 | AJ89: 0 | AK89: 266 | AZ89: Included | BA89: No | BB89: 250 | BC89: PNC.N | BD89: 200.94 | BE89: 169.54101 | BF89: 5.7190386e+10 | BG89: 88
A90: 310 | B90: MOODY'S CORPORATION | C90: MCO-US | D90: US6153691059 | E90: USD | F90: 440.3567 | G90: 179400000 | H90: NYSE | I90: 78999.99 | J90: 2.6250783e+08 | K90: 3.341081e+08 | L90: 2.952486e+08 | M90: 3.4235821e+08 | N90: 3.2711697e+08 | O90: XNYS | P90: 0.85 | Q90: MCO.N | R90: 0.84373945 | S90: 0.71 | T90: 65.7 | U90: 0.88 | V90: Green | W90: Green | X90: Green | Y90: Green | Z90: Green | AA90: Green | AB90: Green | AC90: Green | AD90: Green | AE90: 0 | AF90: 0 | AH90: 0.88 | AI90: 0 | AJ90: 0 | AK90: 64 | AZ90: Included | BA90: No | BB90: 17 | BC90: MCO.N | BD90: 508 | BE90: 428.61964 | BF90: 5.6657098e+10 | BG90: 89
A91: 320 | B91: NEWMONT COR | C91: NEM-US | D91: US6516391066 | E91: USD | F91: 60.39426 | G91: 1098449700 | H91: NYSE | I91: 66340.06 | J91: 4.7767843e+08 | K91: 5.9477303e+08 | L91: 5.9187351e+08 | M91: 6.861976e+08 | N91: 5.0699874e+08 | O91: XNYS | P91: 1 | Q91: NEM.N | R91: 0.84373945 | S91: 1.2 | T91: 53.39 | U91: 0.99 | V91: Green | W91: Green | X91: Green | Y91: Green | Z91: Green | AA91: Green | AB91: Green | AC91: Green | AD91: Green | AE91: 0 | AF91: 0 | AH91: 0.99 | AI91: 0 | AJ91: 0 | AK91: 126 | AZ91: Included | BA91: No | BB91: 130 | BC91: NEM.N | BD91: 79.02 | BE91: 66.672291 | BF91: 5.5973723e+10 | BG91: 90
A92: 182 | B92: EQUINIX INC | C92: EQIX-US | D92: US29444U7000 | E92: USD | F92: 671.164 | G92: 97863980 | H92: NASDAQ | I92: 65682.78 | J92: 2.6129573e+08 | K92: 4.7905709e+08 | L92: 4.3610951e+08 | M92: 5.0608717e+08 | N92: 4.4548547e+08 | O92: XNGS | P92: 1 | Q92: EQIX.O | R92: 0.84373945 | S92: 1.41 | T92: 72.6 | U92: 0.9 | V92: Green | W92: Green | X92: Green | Y92: Green | Z92: Green | AA92: Green | AB92: Green | AC92: Green | AD92: Green | AE92: 0 | AF92: 0 | AH92: 0.9 | AI92: 0 | AJ92: 0 | AK92: 151 | AZ92: Included | BA92: No | BB92: 1 | BC92: EQIX.O | BD92: 779.31 | BE92: 657.53459 | BF92: 5.5419153e+10 | BG92: 91
A93: 312 | B93: MOTOROLA SOLUTIONS | C93: MSI-US | D93: US6200763075 | E93: USD | F93: 394.1884 | G93: 166603900 | H93: NYSE | I93: 65673.32 | J93: 4.218201e+08 | K93: 3.5295298e+08 | L93: 3.5202481e+08 | M93: 4.0760551e+08 | N93: 3.4649365e+08 | O93: XNYS | P93: 1 | Q93: MSI.N | R93: 0.84373945 | S93: 1.13 | T93: 54.27 | U93: 0.99 | V93: Green | W93: Green | X93: Green | Y93: Green | Z93: Green | AA93: Green | AB93: Green | AC93: Green | AD93: Green | AE93: 0 | AF93: 0 | AH93: 0.99 | AI93: 0 | AJ93: 0 | AK93: 121 | AZ93: Included | BA93: No | BB93: 117 | BC93: MSI.N | BD93: 476.84 | BE93: 402.32872 | BF93: 5.5411175e+10 | BG93: 92
A94: 202 | B94: FISERV INC. | C94: FI-US | D94: US3377381088 | E94: USD | F94: 119.2012 | G94: 543593200 | H94: NYSE | I94: 64796.97 | J94: 5.2352578e+08 | K94: 7.5404277e+08 | L94: 7.2445457e+08 | M94: 8.3883184e+08 | N94: 6.3084895e+08 | O94: XNYS | P94: 1 | Q94: FI.N | R94: 0.84373945 | S94: 2.11 | T94: 42.72 | U94: Not Applicable | V94: Green | W94: Green | X94: Green | Y94: Green | Z94: Green | AA94: Green | AB94: Green | AC94: Green | AD94: Green | AE94: 0 | AF94: 0 | AI94: 0 | AJ94: 0 | AK94: 240 | AZ94: Included | BA94: No | BB94: 243 | BC94: FI.N | BD94: 132.75 | BE94: 112.00641 | BF94: 5.4671753e+10 | BG94: 93
A95: 174 | B95: EMERSON ELECTRIC CO. | C95: EMR-US | D95: US2910111044 | E95: USD | F95: 114.1577 | G95: 562800000 | H95: NYSE | I95: 64247.96 | J95: 4.5375172e+08 | K95: 3.4840051e+08 | L95: 3.6917941e+08 | M95: 4.2794588e+08 | N95: 3.3606161e+08 | O95: XNYS | P95: 1 | Q95: EMR.N | R95: 0.84373945 | S95: 0.93 | T95: 44.23 | U95: 0.88 | V95: Green | W95: Green | X95: Green | Y95: Green | Z95: Green | AA95: Green | AB95: Green | AC95: Green | AD95: Green | AE95: 0 | AF95: 0 | AG95: Services | AH95: 0.88 | AI95: 0 | AJ95: 0 | AK95: 99 | AZ95: Included | BA95: No | BB95: 225 | BC95: EMR.N | BD95: 129.03 | BE95: 108.8677 | BF95: 5.4208533e+10 | BG95: 94
A96: 452 | B96: U.S. BANCORP | C96: USB-US | D96: US9029733048 | E96: USD | F96: 41.20157 | G96: 1556189500 | H96: NYSE | I96: 64117.45 | J96: 2.8902598e+08 | K96: 4.2043407e+08 | L96: 3.9963562e+08 | M96: 4.6386285e+08 | N96: 3.9398764e+08 | O96: XNYS | P96: 1 | Q96: USB.N | R96: 0.84373945 | S96: 2.82 | T96: 44.37 | U96: 0.9 | V96: Green | W96: Green | X96: Green | Y96: Green | Z96: Green | AA96: Green | AB96: Green | AC96: Green | AD96: Green | AE96: 0 | AF96: 0 | AH96: 0.9 | AI96: 0 | AJ96: 0 | AK96: 335 | AZ96: Included | BA96: No | BB96: 223 | BC96: USB.N | BD96: 48.39 | BE96: 40.828552 | BF96: 5.4098423e+10 | BG96: 95
A97: 105 | B97: CINTAS CORPORATION | C97: CTAS-US | D97: US1729081059 | E97: USD | F97: 183.9819 | G97: 402977940 | H97: NASDAQ | I97: 74140.64 | J97: 2.6648445e+08 | K97: 3.1312471e+08 | L97: 2.7400287e+08 | M97: 3.1752454e+08 | N97: 3.1233906e+08 | O97: XNGS | P97: 0.85 | Q97: CTAS.O | R97: 0.84373945 | S97: 1.63 | T97: 45.18 | U97: 0.67 | V97: Green | W97: Green | X97: Green | Y97: Green | Z97: Green | AA97: Green | AB97: Green | AC97: Green | AD97: Green | AE97: 0 | AF97: 0 | AH97: 0.67 | AI97: 0 | AJ97: 0 | AK97: 172 | AZ97: Included | BA97: No | BB97: 218 | BC97: CTAS.O | BD97: 199.29 | BE97: 168.14883 | BF97: 5.317208e+10 | BG97: 96
A98: 167 | B98: ECOLAB INC | C98: ECL-US | D98: US2788651006 | E98: USD | F98: 242.1318 | G98: 283624900 | H98: NYSE | I98: 68674.6 | J98: 2.5390407e+08 | K98: 3.0507542e+08 | L98: 2.7818354e+08 | M98: 3.2246474e+08 | N98: 2.7562163e+08 | O98: XNYS | P98: 0.9 | Q98: ECL.N | R98: 0.84373945 | S98: 0.89 | T98: 65.46 | U98: 0.96 | V98: Green | W98: Green | X98: Green | Y98: Green | Z98: Green | AA98: Green | AB98: Green | AC98: Green | AD98: Green | AE98: 0 | AF98: 0 | AH98: 0.96 | AI98: 0 | AJ98: 0 | AK98: 95 | AZ98: Included | BA98: No | BB98: 20 | BC98: ECL.N | BD98: 264.06 | BE98: 222.79784 | BF98: 5.2149128e+10 | BG98: 97
A99: 54 | B99: BANK NY MELLON | C99: BK-US | D99: US0640581007 | E99: USD | F99: 87.5064 | G99: 705240840 | H99: NYSE | I99: 61713.09 | J99: 2.8362823e+08 | K99: 3.3194394e+08 | L99: 3.2749875e+08 | M99: 3.7987025e+08 | N99: 3.0725332e+08 | O99: XNYS | P99: 1 | Q99: BK.N | R99: 0.84373945 | S99: 0.31 | T99: 55.08 | U99: 0.97 | V99: Green | W99: Green | X99: Green | Y99: Green | Z99: Green | AA99: Green | AB99: Green | AC99: Green | AD99: Green | AE99: 0 | AF99: 0 | AH99: 0.97 | AI99: 0 | AJ99: 0 | AK99: 8 | AZ99: Included | BA99: No | BB99: 103 | BC99: BK.N | BD99: 105.49 | BE99: 89.006075 | BF99: 5.2069766e+10 | BG99: 98
A100: 241 | B100: ILLINOIS TOOL WORKS | C100: ITW-US | D100: US4523081093 | E100: USD | F100: 229.9113 | G100: 291500000 | H100: NYSE | I100: 67019.13 | J100: 2.0607239e+08 | K100: 2.4855162e+08 | L100: 2.1031567e+08 | M100: 2.4376053e+08 | N100: 2.3049726e+08 | O100: XNYS | P100: 0.9 | Q100: ITW.N | R100: 0.84373945 | S100: 2.35 | T100: 45.47 | U100: 0.95 | V100: Green | W100: Green | X100: Green | Y100: Green | Z100: Green | AA100: Green | AB100: Green | AC100: Green | AD100: Green | AE100: 0 | AF100: 0 | AH100: 0.95 | AI100: 0 | AJ100: 0 | AK100: 273 | AZ100: Included | BA100: No | BB100: 216 | BC100: ITW.N | BD100: 261.84 | BE100: 220.92474 | BF100: 5.0892026e+10 | BG100: 99
A101: 257 | B101: JOHNSON CONTROLS INT | C101: JCI-US | D101: IE00BY7QL619 | E101: USD | F101: 91.53439 | G101: 654385440 | H101: NYSE | I101: 59898.78 | J101: 4.7044319e+08 | K101: 4.0199274e+08 | L101: 4.4336482e+08 | M101: 5.1395483e+08 | N101: 3.464294e+08 | O101: XNYS | P101: 1 | Q101: JCI.N | R101: 0.84373945 | S101: 0.72 | T101: 58.76 | U101: 0.88 | V101: Green | W101: Green | X101: Green | Y101: Green | Z101: Green | AA101: Green | AB101: Green | AC101: Green | AD101: Green | AE101: 0 | AF101: 0 | AH101: 0.88 | AI101: 0 | AJ101: 0 | AK101: 67 | AZ101: Included | BA101: No | BB101: 59 | BC101: JCI.N | BD101: 106.96 | BE101: 90.246372 | BF101: 5.0538957e+10 | BG101: 100
A102: 489 | B102: WILLIAMS COMPANIES | C102: WMB-US | D102: US9694571004 | E102: USD | F102: 48.70285 | G102: 1221177400 | H102: NYSE | I102: 59474.82 | J102: 3.4514675e+08 | K102: 3.9936716e+08 | L102: 4.0681634e+08 | M102: 4.7132163e+08 | N102: 3.6472294e+08 | O102: XNYS | P102: 1 | Q102: WMB.N | R102: 0.84373945 | S102: 2.01 | T102: 50.62 | U102: 0.93 | V102: Green | W102: Green | X102: Green | Y102: Green | Z102: Green | AA102: Green | AB102: Green | AC102: Green | AD102: Green | AE102: 0 | AF102: 0 | AH102: 0.93 | AI102: 0 | AJ102: 0 | AK102: 226 | AZ102: Included | BA102: No | BB102: 168 | BC102: WMB.N | BD102: 57.95 | BE102: 48.894701 | BF102: 5.0181252e+10 | BG102: 101
A103: 117 | B103: COLGATE-PALMOLIVE CO | C103: CL-US | D103: US1941621039 | E103: USD | F103: 73.34016 | G103: 808220800 | H103: NYSE | I103: 59275.05 | J103: 3.3539042e+08 | K103: 4.2564213e+08 | L103: 3.8537358e+08 | M103: 4.4629709e+08 | N103: 4.1393607e+08 | O103: XNYS | P103: 1 | Q103: CL.N | R103: 0.84373945 | S103: 0.83 | T103: 57.12 | U103: 0.97 | V103: Green | W103: Green | X103: Green | Y103: Green | Z103: Green | AA103: Green | AB103: Green | AC103: Green | AD103: Green | AE103: 0 | AF103: 0 | AH103: 0.97 | AI103: 0 | AJ103: 0 | AK103: 83 | AZ103: Included | BA103: No | BB103: 82 | BC103: CL.N | BD103: 81.48 | BE103: 68.74789 | BF103: 5.0012692e+10 | BG103: 102
A104: 498 | B104: ZOETIS INC. CLASS A | C104: ZTS-US | D104: US98978V1035 | E104: USD | F104: 133.6576 | G104: 443183470 | H104: NYSE | I104: 59234.85 | J104: 4.5291828e+08 | K104: 4.2445156e+08 | L104: 4.2606054e+08 | M104: 4.9367988e+08 | N104: 4.172802e+08 | O104: XNYS | P104: 1 | Q104: ZTS.N | R104: 0.84373945 | S104: 2.48 | T104: 46.76 | U104: 0.67 | V104: Green | W104: Green | X104: Green | Y104: Green | Z104: Green | AA104: Green | AB104: Green | AC104: Green | AD104: Green | AE104: 0 | AF104: 0 | AH104: 0.67 | AI104: 0 | AJ104: 0 | AK104: 291 | AZ104: Included | BA104: No | BB104: 202 | BC104: ZTS.N | BD104: 147.46 | BE104: 124.41782 | BF104: 4.997877e+10 | BG104: 103
A105: 233 | B105: HOWMET AEROSPACE | C105: HWM-US | D105: US4432011082 | E105: USD | F105: 145.9293 | G105: 403126300 | H105: NYSE | I105: 58827.96 | J105: 3.623232e+08 | K105: 4.2985822e+08 | L105: 4.8473112e+08 | M105: 5.6239416e+08 | N105: 3.4247557e+08 | O105: XNYS | P105: 1 | Q105: HWM.N | R105: 0.84373945 | S105: 0.3 | T105: 49.41 | U105: 0.91 | V105: Green | W105: Green | X105: Green | Y105: Green | Z105: Green | AA105: Green | AB105: Green | AC105: Green | AD105: Green | AE105: 0 | AF105: 0 | AH105: 0.91 | AI105: 0 | AJ105: 0 | AK105: 7 | AZ105: Included | BA105: No | BB105: 180 | BC105: HWM.N | BD105: 187.46 | BE105: 158.1674 | BF105: 4.9635453e+10 | BG105: 104
A106: 348 | B106: PAYPAL HOLDINGS INC | C106: PYPL-US | D106: US70450Y1038 | E106: USD | F106: 59.65182 | G106: 955378400 | H106: NASDAQ | I106: 56990.06 | J106: 5.8584999e+08 | K106: 6.7986231e+08 | L106: 6.5479191e+08 | M106: 7.5866733e+08 | N106: 7.3229142e+08 | O106: XNGS | P106: 1 | Q106: PYPL.O | R106: 0.84373945 | S106: 0.98 | T106: 43.23 | U106: 0.86 | V106: Green | W106: Green | X106: Green | Y106: Green | Z106: Green | AA106: Green | AB106: Green | AC106: Green | AD106: Green | AE106: 0 | AF106: 0 | AH106: 0.86 | AI106: 0 | AJ106: 0 | AK106: 105 | AZ106: Included | BA106: No | BB106: 238 | BC106: PYPL.O | BD106: 66.85 | BE106: 56.403982 | BF106: 4.8084762e+10 | BG106: 105
A107: 12 | B107: AIR PROD & CHEMICALS | C107: APD-US | D107: US0091581068 | E107: USD | F107: 255.419 | G107: 222553630 | H107: NYSE | I107: 56844.43 | J107: 2.19176e+08 | K107: 2.9626585e+08 | L107: 2.6904217e+08 | M107: 3.1152427e+08 | N107: 3.583009e+08 | O107: XNYS | P107: 1 | Q107: APD.N | R107: 0.84373945 | S107: 2.75 | T107: 58.25 | U107: 0.99 | V107: Green | W107: Green | X107: Green | Y107: Green | Z107: Green | AA107: Green | AB107: Green | AC107: Green | AD107: Green | AE107: 0 | AF107: 0.01 | AG107: Services | AH107: 0.99 | AI107: 0 | AJ107: 0.01 | AK107: 328 | AZ107: Included | BA107: No | BB107: 68 | BC107: APD.N | BD107: 284.95 | BE107: 240.42356 | BF107: 4.7961884e+10 | BG107: 106
A108: 227 | B108: HCA HEALTHCARE INC | C108: HCA-US | D108: US40412C1018 | E108: USD | F108: 345.5965 | G108: 233993500 | H108: NYSE | I108: 80867.34 | J108: 3.9042313e+08 | K108: 4.8538252e+08 | L108: 4.5525901e+08 | M108: 5.2771136e+08 | N108: 4.7390689e+08 | O108: XNYS | P108: 0.7 | Q108: HCA.N | R108: 0.84373945 | S108: 2.29 | T108: 56.82 | U108: Not Applicable | V108: Green | W108: Green | X108: Green | Y108: Green | Z108: Green | AA108: Green | AB108: Green | AC108: Green | AD108: Green | AE108: 0 | AF108: 0 | AI108: 0 | AJ108: 0 | AK108: 263 | AZ108: Included | BA108: No | BB108: 86 | BC108: HCA.N | BD108: 399.75 | BE108: 337.28485 | BF108: 4.7761672e+10 | BG108: 107
A109: 138 | B109: CSX CORP | C109: CSX-US | D109: US1264081035 | E109: USD | F109: 29.51016 | G109: 1864277000 | H109: NASDAQ | I109: 55015.11 | J109: 6.734269e+08 | K109: 4.8544815e+08 | L109: 5.4733115e+08 | M109: 6.3495151e+08 | N109: 4.3630293e+08 | O109: XNGS | P109: 1 | Q109: CSX.O | R109: 0.84373945 | S109: 1.86 | T109: 57.31 | U109: 0.99 | V109: Green | W109: Green | X109: Green | Y109: Green | Z109: Green | AA109: Green | AB109: Green | AC109: Green | AD109: Green | AE109: 0 | AF109: 0 | AH109: 0.99 | AI109: 0 | AJ109: 0 | AK109: 204 | AZ109: Included | BA109: No | BB109: 77 | BC109: CSX.O | BD109: 32.47 | BE109: 27.39622 | BF109: 4.6418421e+10 | BG109: 108
A110: 324 | B110: NORFOLK SOUTHERN COR | C110: NSC-US | D110: US6558441084 | E110: USD | F110: 242.8742 | G110: 224354310 | H110: NYSE | I110: 54489.88 | J110: 4.9236117e+08 | K110: 3.7555702e+08 | L110: 4.7581239e+08 | M110: 5.518352e+08 | N110: 3.294807e+08 | O110: XNYS | P110: 1 | Q110: NSC.N | R110: 0.84373945 | S110: 2.1 | T110: 50.39 | U110: 0.98 | V110: Amber | W110: Green | X110: Green | Y110: Green | Z110: Green | AA110: Green | AB110: Green | AC110: Green | AD110: Green | AE110: 0 | AF110: 0 | AH110: 0.98 | AI110: 0 | AJ110: 0 | AK110: 237 | AZ110: Included | BA110: No | BB110: 171 | BC110: NSC.N | BD110: 278.09 | BE110: 234.6355 | BF110: 4.5975256e+10 | BG110: 109
A111: 448 | B111: TRAVELERS COMPANIES | C111: TRV-US | D111: US89417E1091 | E111: USD | F111: 235.7826 | G111: 225133830 | H111: NYSE | I111: 53082.63 | J111: 2.7440085e+08 | K111: 3.08836e+08 | L111: 2.9176584e+08 | M111: 3.3808316e+08 | N111: 2.9893854e+08 | O111: XNYS | P111: 1 | Q111: TRV.N | R111: 0.84373945 | S111: 1.96 | T111: 42.71 | U111: 0.94 | V111: Green | W111: Green | X111: Green | Y111: Green | Z111: Green | AA111: Green | AB111: Green | AC111: Green | AD111: Green | AE111: 0 | AF111: 0 | AH111: 0.94 | AI111: 0 | AJ111: 0 | AK111: 221 | AZ111: Included | BA111: No | BB111: 244 | BC111: TRV.N | BD111: 271.95 | BE111: 229.45494 | BF111: 4.4787917e+10 | BG111: 110
A112: 209 | B112: FREEPORT-MCMORAN | C112: FCX-US | D112: US35671D8570 | E112: USD | F112: 36.93463 | G112: 1435774200 | H112: NYSE | I112: 53029.79 | J112: 3.5888355e+08 | K112: 5.5202523e+08 | L112: 5.2752846e+08 | M112: 6.1191314e+08 | N112: 5.2199729e+08 | O112: XNYS | P112: 1 | Q112: FCX.N | R112: 0.84373945 | S112: 2.14 | T112: 46.03 | U112: 0.99 | V112: Amber | W112: Green | X112: Green | Y112: Green | Z112: Green | AA112: Green | AB112: Green | AC112: Green | AD112: Green | AE112: 0 | AF112: 0.01 | AH112: 0.99 | AI112: 0 | AJ112: 0.01 | AK112: 245 | AZ112: Included | BA112: No | BB112: 211 | BC112: FCX.N | BD112: 45.3 | BE112: 38.221397 | BF112: 4.4743325e+10 | BG112: 111
A113: 48 | B113: AUTODESK INC | C113: ADSK-US | D113: US0527691069 | E113: USD | F113: 247.6788 | G113: 213944530 | H113: NASDAQ | I113: 52989.52 | J113: 3.380718e+08 | K113: 4.1120825e+08 | L113: 4.0485391e+08 | M113: 4.69139e+08 | N113: 3.9985913e+08 | O113: XNGS | P113: 1 | Q113: ADSK.O | R113: 0.84373945 | S113: 2.47 | T113: 60.39 | U113: 0.91 | V113: Green | W113: Green | X113: Green | Y113: Green | Z113: Green | AA113: Green | AB113: Green | AC113: Green | AD113: Green | AE113: 0 | AF113: 0 | AH113: 0.91 | AI113: 0 | AJ113: 0 | AK113: 290 | AZ113: Included | BA113: No | BB113: 46 | BC113: ADSK.O | BD113: 318.51 | BE113: 268.73945 | BF113: 4.4709352e+10 | BG113: 112
A114: 378 | B114: REGENERON PHARMA | C114: REGN-US | D114: US75886F1075 | E114: USD | F114: 503.0551 | G114: 104170296 | H114: NASDAQ | I114: 52403.4 | J114: 5.076737e+08 | K114: 5.9249489e+08 | L114: 5.4753844e+08 | M114: 6.3303544e+08 | N114: 6.046254e+08 | O114: XNGS | P114: 1 | Q114: REGN.O | R114: 0.84373945 | S114: 2.1 | T114: 66.21 | U114: 0.93 | V114: Green | W114: Green | X114: Green | Y114: Green | Z114: Green | AA114: Green | AB114: Green | AC114: Green | AD114: Green | AE114: 0 | AF114: 0 | AH114: 0.93 | AI114: 0 | AJ114: 0 | AK114: 237 | AZ114: Included | BA114: No | BB114: 16 | BC114: REGN.O | BD114: 575.06 | BE114: 485.20081 | BF114: 4.4214815e+10 | BG114: 113
A115: 429 | B115: TE CONNECTIVITY LTD. | C115: TEL-US | D115: IE000IVNQZ81 | E115: USD | F115: 174.9445 | G115: 295481480 | H115: NYSE | I115: 51692.87 | J115: 2.7951972e+08 | K115: 2.7197914e+08 | L115: 2.8769904e+08 | M115: 3.3380647e+08 | N115: 2.4627025e+08 | O115: XNYS | P115: 1 | Q115: TEL.N | R115: 0.84373945 | S115: 1.78 | T115: 53.47 | U115: 0.98 | V115: Green | W115: Green | X115: Green | Y115: Green | Z115: Green | AA115: Green | AB115: Green | AC115: Green | AD115: Green | AE115: 0 | AF115: 0 | AH115: 0.98 | AI115: 0 | AJ115: 0 | AK115: 194 | AZ115: Included | BA115: No | BB115: 129 | BC115: TEL.N | BD115: 212.56 | BE115: 179.34526 | BF115: 4.3615305e+10 | BG115: 114
A116: 458 | B116: UNITED RENTALS INC | C116: URI-US | D116: US9113631090 | E116: USD | F116: 793.6082 | G116: 64341225 | H116: NYSE | I116: 51061.72 | J116: 3.4663285e+08 | K116: 3.9681587e+08 | L116: 3.7063839e+08 | M116: 4.305796e+08 | N116: 3.9480447e+08 | O116: XNYS | P116: 1 | Q116: URI.N | R116: 0.84373945 | S116: 1.3 | T116: 52.25 | U116: 0.66 | V116: Green | W116: Green | X116: Green | Y116: Green | Z116: Green | AA116: Green | AB116: Green | AC116: Green | AD116: Green | AE116: 0 | AF116: 0 | AH116: 0.66 | AI116: 0 | AJ116: 0 | AK116: 140 | AZ116: Included | BA116: No | BB116: 149 | BC116: URI.N | BD116: 958.65 | BE116: 808.85082 | BF116: 4.3082791e+10 | BG116: 115
A117: 334 | B117: NXP SEMICONDUCTORS | C117: NXPI-US | D117: NL0009538784 | E117: USD | F117: 200.4011 | G117: 252114600 | H117: NASDAQ | I117: 50524.04 | J117: 5.4332267e+08 | K117: 5.5137561e+08 | L117: 5.0320283e+08 | M117: 5.8363885e+08 | N117: 5.4275544e+08 | O117: XNGS | P117: 1 | Q117: NXPI.O | R117: 0.84373945 | S117: 2.12 | T117: 63.08 | U117: 0.67 | V117: Green | W117: Green | X117: Green | Y117: Green | Z117: Green | AA117: Green | AB117: Green | AC117: Green | AD117: Green | AE117: 0 | AF117: 0 | AH117: 0.67 | AI117: 0 | AJ117: 0 | AK117: 241 | AZ117: Included | BA117: No | BB117: 30 | BC117: NXPI.O | BD117: 220.99 | BE117: 186.45798 | BF117: 4.2629128e+10 | BG117: 116
A118: 99 | B118: CHIPOTLE MEX. GRILL | C118: CMG-US | D118: US1696561059 | E118: USD | F118: 37.24185 | G118: 1340885000 | H118: NYSE | I118: 49937.04 | J118: 6.1885516e+08 | K118: 6.5827088e+08 | L118: 6.7435932e+08 | M118: 7.8285077e+08 | N118: 5.979666e+08 | O118: XNYS | P118: 1 | Q118: CMG.N | R118: 0.84373945 | S118: 0.79 | T118: 47.44 | U118: 0.93 | V118: Green | W118: Green | X118: Green | Y118: Green | Z118: Green | AA118: Green | AB118: Green | AC118: Green | AD118: Green | AE118: 0 | AF118: 0 | AH118: 0.93 | AI118: 0 | AJ118: 0 | AK118: 77 | AZ118: Included | BA118: No | BB118: 197 | BC118: CMG.N | BD118: 39.3 | BE118: 33.15896 | BF118: 4.2133849e+10 | BG118: 117
A119: 194 | B119: FASTENAL COMPANY | C119: FAST-US | D119: US3119001044 | E119: USD | F119: 43.00222 | G119: 1147636600 | H119: NASDAQ | I119: 49350.93 | J119: 2.3068542e+08 | K119: 2.479974e+08 | L119: 2.3102303e+08 | M119: 2.6808629e+08 | N119: 2.2048795e+08 | O119: XNGS | P119: 1 | Q119: FAST.O | R119: 0.84373945 | S119: 2.98 | T119: 50.89 | U119: 0.61 | V119: Green | W119: Green | X119: Green | Y119: Green | Z119: Green | AA119: Green | AB119: Green | AC119: Green | AD119: Green | AE119: 0 | AF119: 0 | AH119: 0.61 | AI119: 0 | AJ119: 0 | AK119: 351 | AZ119: Included | BA119: No | BB119: 164 | BC119: FAST.O | BD119: 47.25 | BE119: 39.866689 | BF119: 4.1639319e+10 | BG119: 118
A120: 388 | B120: ROPER TECHNOLOGIES | C120: ROP-US | D120: US7766961061 | E120: USD | F120: 458.1328 | G120: 107613820 | H120: NASDAQ | I120: 49301.43 | J120: 3.3985826e+08 | K120: 3.099805e+08 | L120: 2.9169062e+08 | M120: 3.3845256e+08 | N120: 2.9101788e+08 | O120: XNGS | P120: 1 | Q120: ROP.O | R120: 0.84373945 | S120: 1.26 | T120: 49.6 | U120: 0.63 | V120: Green | W120: Green | X120: Green | Y120: Green | Z120: Green | AA120: Green | AB120: Green | AC120: Green | AD120: Green | AE120: 0 | AF120: 0 | AG120: Services | AH120: 0.63 | AI120: 0 | AJ120: 0 | AK120: 135 | AZ120: Included | BA120: No | BB120: 178 | BC120: ROP.O | BD120: 502.44 | BE120: 423.92845 | BF120: 4.1597554e+10 | BG120: 119
A121: 402 | B121: SIMON PROPERTY GROUP | C121: SPG-US | D121: US8288061091 | E121: USD | F121: 150.6742 | G121: 326484770 | H121: NYSE | I121: 49192.83 | J121: 2.2037592e+08 | K121: 2.4697191e+08 | L121: 2.1305143e+08 | M121: 2.4686243e+08 | N121: 2.3783427e+08 | O121: XNYS | P121: 1 | Q121: SPG.N | R121: 0.84373945 | S121: 2.15 | T121: 53.09 | U121: 0.87 | V121: Green | W121: Green | X121: Green | Y121: Green | Z121: Green | AA121: Green | AB121: Green | AC121: Green | AD121: Green | AE121: 0 | AF121: 0 | AH121: 0.87 | AI121: 0 | AJ121: 0 | AK121: 246 | AZ121: Included | BA121: No | BB121: 136 | BC121: SPG.N | BD121: 181.52 | BE121: 153.15558 | BF121: 4.1505933e+10 | BG121: 120
A122: 91 | B122: CENCORA | C122: COR-US | D122: US03073E1055 | E122: USD | F122: 249.7013 | G122: 193877880 | H122: NYSE | I122: 48411.57 | J122: 3.7411896e+08 | K122: 3.9735851e+08 | L122: 3.2836328e+08 | M122: 3.8039533e+08 | N122: 3.557558e+08 | O122: XNYS | P122: 1 | Q122: COR.N | R122: 0.84373945 | S122: 2.32 | T122: 52.48 | U122: 0.88 | V122: Amber | W122: Green | X122: Green | Y122: Green | Z122: Green | AA122: Green | AB122: Green | AC122: Green | AD122: Green | AE122: 0 | AF122: 0 | AH122: 0.88 | AI122: 0 | AJ122: 0 | AK122: 266 | AZ122: Included | BA122: No | BB122: 146 | BC122: COR.N | BD122: 290 | BE122: 244.68444 | BF122: 4.0846742e+10 | BG122: 121
A123: 218 | B123: GENERAL MOTORS COMP. | C123: GM-US | D123: US37045V1008 | E123: USD | F123: 49.81225 | G123: 952077800 | H123: NYSE | I123: 47425.14 | J123: 3.0584782e+08 | K123: 5.2440062e+08 | L123: 4.1108028e+08 | M123: 4.7659799e+08 | N123: 5.4451815e+08 | O123: XNYS | P123: 1 | Q123: GM.N | R123: 0.84373945 | S123: 1.26 | T123: 52.5 | U123: 0.98 | V123: Green | W123: Green | X123: Green | Y123: Green | Z123: Green | AA123: Green | AB123: Green | AC123: Green | AD123: Green | AE123: 0 | AF123: 0 | AH123: 0.98 | AI123: 0 | AJ123: 0 | AK123: 135 | AZ123: Included | BA123: No | BB123: 145 | BC123: GM.N | BD123: 58.46 | BE123: 49.325008 | BF123: 4.0014459e+10 | BG123: 122
A124: 139 | B124: CUMMINS INC. | C124: CMI-US | D124: US2310211063 | E124: USD | F124: 343.318 | G124: 137786040 | H124: NYSE | I124: 47304.42 | J124: 3.2113285e+08 | K124: 2.640284e+08 | L124: 2.5464385e+08 | M124: 2.955163e+08 | N124: 2.4407924e+08 | O124: XNYS | P124: 1 | Q124: CMI.N | R124: 0.84373945 | S124: 0.73 | T124: 56.85 | U124: 0.99 | V124: Green | W124: Green | X124: Green | Y124: Green | Z124: Green | AA124: Green | AB124: Green | AC124: Green | AD124: Green | AE124: 0 | AF124: 0 | AG124: Services | AH124: 0.99 | AI124: 0 | AJ124: 0 | AK124: 70 | AZ124: Included | BA124: No | BB124: 85 | BC124: CMI.N | BD124: 415.44 | BE124: 350.52312 | BF124: 3.9912612e+10 | BG124: 123
A125: 84 | B125: CARRIER GLOBAL CORP. | C125: CARR-US | D125: US14448C1045 | E125: USD | F125: 57.81703 | G125: 851022800 | H125: NYSE | I125: 49203.61 | J125: 2.6416604e+08 | K125: 3.0961137e+08 | L125: 2.8792098e+08 | M125: 3.3353575e+08 | N125: 3.116966e+08 | O125: XNYS | P125: 0.95 | Q125: CARR.N | R125: 0.84373945 | S125: 0.76 | T125: 54.46 | U125: 0.68 | V125: Green | W125: Green | X125: Green | Y125: Green | Z125: Green | AA125: Green | AB125: Green | AC125: Green | AD125: Green | AE125: 0 | AF125: 0 | AH125: 0.68 | AI125: 0 | AJ125: 0 | AK125: 73 | AZ125: Included | BA125: No | BB125: 114 | BC125: CARR.N | BD125: 60.93 | BE125: 51.409045 | BF125: 3.9439276e+10 | BG125: 124
A126: 15 | B126: ALLSTATE CORPORATION | C126: ALL-US | D126: US0200021014 | E126: USD | F126: 175.3883 | G126: 263505340 | H126: NYSE | I126: 46215.75 | J126: 2.3016961e+08 | K126: 3.0072871e+08 | L126: 2.7287305e+08 | M126: 3.1614098e+08 | N126: 2.9194916e+08 | O126: XNYS | P126: 1 | Q126: ALL.N | R126: 0.84373945 | S126: 0.48 | T126: 52.89 | U126: 0.99 | V126: Green | W126: Green | X126: Green | Y126: Green | Z126: Green | AA126: Green | AB126: Green | AC126: Green | AD126: Green | AE126: 0 | AF126: 0 | AH126: 0.99 | AI126: 0 | AJ126: 0 | AK126: 26 | AZ126: Included | BA126: No | BB126: 139 | BC126: ALL.N | BD126: 196.3 | BE126: 165.62605 | BF126: 3.8994055e+10 | BG126: 125
A127: 153 | B127: DIGITAL REALTY TRUST | C127: DLR-US | D127: US2538681030 | E127: USD | F127: 142.567 | G127: 341050450 | H127: NYSE | I127: 48622.53 | J127: 1.9216966e+08 | K127: 2.8763341e+08 | L127: 2.48743e+08 | M127: 2.8818937e+08 | N127: 3.0581442e+08 | O127: XNYS | P127: 0.95 | Q127: DLR.N | R127: 0.84373945 | S127: 2.26 | T127: 57.88 | U127: 0.87 | V127: Green | W127: Green | X127: Green | Y127: Green | Z127: Green | AA127: Green | AB127: Green | AC127: Green | AD127: Green | AE127: 0 | AF127: 0 | AH127: 0.87 | AI127: 0 | AJ127: 0 | AK127: 260 | AZ127: Included | BA127: No | BB127: 72 | BC127: DLR.N | BD127: 173.86 | BE127: 146.69254 | BF127: 3.8973517e+10 | BG127: 126
A128: 396 | B128: SCHLUMBERGER LTD | C128: SLB-US | D128: AN8068571086 | E128: USD | F128: 30.38914 | G128: 1500867600 | H128: NYSE | I128: 45610.07 | J128: 3.2694643e+08 | K128: 5.3680089e+08 | L128: 4.653236e+08 | M128: 5.3933352e+08 | N128: 5.1792962e+08 | O128: XNYS | P128: 1 | Q128: SLB.N | R128: 0.84373945 | S128: 0.43 | T128: 43.23 | U128: 0.92 | V128: Amber | W128: Green | X128: Green | Y128: Green | Z128: Green | AA128: Green | AB128: Green | AC128: Green | AD128: Green | AE128: 0 | AF128: 0 | AG128: Services | AH128: 0.92 | AI128: 0 | AJ128: 0 | AK128: 20 | AZ128: Included | BA128: No | BB128: 238 | BC128: SLB.N | BD128: 35.24 | BE128: 29.733378 | BF128: 3.848302e+10 | BG128: 127
A129: 97 | B129: CHENIERE ENERGY | C129: LNG-US | D129: US16411R2085 | E129: USD | F129: 202.7308 | G129: 219768100 | H129: NYSE | I129: 44553.77 | J129: 3.5445793e+08 | K129: 4.0997499e+08 | L129: 3.9862263e+08 | M129: 4.6165575e+08 | N129: 3.8159767e+08 | O129: XNYS | P129: 1 | Q129: LNG.N | R129: 0.84373945 | S129: 2.85 | T129: 48.78 | U129: 0.87 | V129: Green | W129: Green | X129: Green | Y129: Green | Z129: Green | AA129: Green | AB129: Green | AC129: Green | AD129: Green | AE129: 0 | AF129: 0 | AH129: 0.87 | AI129: 0 | AJ129: 0 | AK129: 339 | AZ129: Included | BA129: No | BB129: 187 | BC129: LNG.N | BD129: 234.9 | BE129: 198.1944 | BF129: 3.7591767e+10 | BG129: 128
A130: 9 | B130: AFLAC INCORPORATED | C130: AFL-US | D130: US0010551028 | E130: USD | F130: 92.55846 | G130: 534831500 | H130: NYSE | I130: 49503.18 | J130: 2.3656445e+08 | K130: 2.1079298e+08 | L130: 2.1836058e+08 | M130: 2.5326599e+08 | N130: 2.0951413e+08 | O130: XNYS | P130: 0.9 | Q130: AFL.N | R130: 0.84373945 | S130: 0.81 | T130: 47.44 | U130: 0.95 | V130: Green | W130: Green | X130: Green | Y130: Green | Z130: Green | AA130: Green | AB130: Green | AC130: Green | AD130: Green | AE130: 0 | AF130: 0 | AH130: 0.95 | AI130: 0 | AJ130: 0 | AK130: 80 | AZ130: Included | BA130: No | BB130: 197 | BC130: AFL.N | BD130: 107.63 | BE130: 90.811677 | BF130: 3.7591007e+10 | BG130: 129
A131: 206 | B131: FORTINET INC. | C131: FTNT-US | D131: US34959E1091 | E131: USD | F131: 68.2881 | G131: 766266050 | H131: NASDAQ | I131: 52326.86 | J131: 9.1437016e+08 | K131: 4.8569773e+08 | L131: 5.0768873e+08 | M131: 5.8872003e+08 | N131: 4.3452355e+08 | O131: XNGS | P131: 0.85 | Q131: FTNT.O | R131: 0.84373945 | S131: 0.88 | T131: 58.72 | U131: 0.83 | V131: Green | W131: Green | X131: Green | Y131: Green | Z131: Green | AA131: Green | AB131: Green | AC131: Green | AD131: Green | AE131: 0 | AF131: 0 | AH131: 0.83 | AI131: 0 | AJ131: 0 | AK131: 93 | AZ131: Included | BA131: No | BB131: 62 | BC131: FTNT.O | BD131: 79.78 | BE131: 67.313533 | BF131: 3.7527695e+10 | BG131: 130
A132: 240 | B132: IDEXX LABORATORIES | C132: IDXX-US | D132: US45168D1046 | E132: USD | F132: 550.9046 | G132: 80004690 | H132: NASDAQ | I132: 44074.96 | J132: 4.4581013e+08 | K132: 3.1436412e+08 | L132: 2.9081063e+08 | M132: 3.3690463e+08 | N132: 2.8212902e+08 | O132: XNGS | P132: 1 | Q132: IDXX.O | R132: 0.84373945 | S132: 2.76 | T132: 44.05 | U132: 0.66 | V132: Green | W132: Green | X132: Green | Y132: Green | Z132: Green | AA132: Green | AB132: Green | AC132: Green | AD132: Green | AE132: 0 | AF132: 0 | AH132: 0.66 | AI132: 0 | AJ132: 0 | AK132: 329 | AZ132: Included | BA132: No | BB132: 227 | BC132: IDXX.O | BD132: 645.65 | BE132: 544.76038 | BF132: 3.7187776e+10 | BG132: 131
A133: 127 | B133: CORNING INC | C133: GLW-US | D133: US2193501051 | E133: USD | F133: 56.12732 | G133: 856618700 | H133: NYSE | I133: 48079.71 | J133: 2.7251857e+08 | K133: 2.50141e+08 | L133: 2.3685856e+08 | M133: 2.7431606e+08 | N133: 2.2978305e+08 | O133: XNYS | P133: 0.9 | Q133: GLW.N | R133: 0.84373945 | S133: 2.34 | T133: 43.59 | U133: 0.96 | V133: Green | W133: Green | X133: Green | Y133: Green | Z133: Green | AA133: Green | AB133: Green | AC133: Green | AD133: Green | AE133: 0 | AF133: 0 | AH133: 0.96 | AI133: 0 | AJ133: 0 | AK133: 269 | AZ133: Included | BA133: No | BB133: 233 | BC133: GLW.N | BD133: 78.7 | BE133: 66.402295 | BF133: 3.6510075e+10 | BG133: 132
A134: 88 | B134: CBRE GROUP INC. | C134: CBRE-US | D134: US12504L1098 | E134: USD | F134: 140.3055 | G134: 297554320 | H134: NYSE | I134: 41748.51 | J134: 1.948771e+08 | K134: 2.1323221e+08 | L134: 1.9661068e+08 | M134: 2.2761095e+08 | N134: 2.1825078e+08 | O134: XNYS | P134: 1 | Q134: CBRE.N | R134: 0.84373945 | S134: 0.34 | T134: 65.1 | U134: 0.93 | V134: Green | W134: Green | X134: Green | Y134: Green | Z134: Green | AA134: Green | AB134: Green | AC134: Green | AD134: Green | AE134: 0 | AF134: 0 | AH134: 0.93 | AI134: 0 | AJ134: 0 | AK134: 9 | AZ134: Included | BA134: No | BB134: 22 | BC134: CBRE.N | BD134: 162.84 | BE134: 137.39453 | BF134: 3.5224863e+10 | BG134: 133
A135: 27 | B135: AMERIPRISE FINANCIAL | C135: AMP-US | D135: US03076C1062 | E135: USD | F135: 441.1333 | G135: 94271570 | H135: NYSE | I135: 41586.33 | J135: 1.6819253e+08 | K135: 2.1774123e+08 | L135: 2.0042298e+08 | M135: 2.3224784e+08 | N135: 2.2542364e+08 | O135: XNYS | P135: 1 | Q135: AMP.N | R135: 0.84373945 | S135: 2.6 | T135: 51.83 | U135: 0.74 | V135: Green | W135: Green | X135: Green | Y135: Green | Z135: Green | AA135: Green | AB135: Green | AC135: Green | AD135: Green | AE135: 0 | AF135: 0 | AH135: 0.74 | AI135: 0 | AJ135: 0 | AK135: 308 | AZ135: Included | BA135: No | BB135: 157 | BC135: AMP.N | BD135: 486.13 | BE135: 410.16706 | BF135: 3.5088026e+10 | BG135: 134
A136: 169 | B136: EDWARDS LIFESCIENCES | C136: EW-US | D136: US28176E1082 | E136: USD | F136: 69.83274 | G136: 587100000 | H136: NYSE | I136: 40998.81 | J136: 2.6010625e+08 | K136: 3.009781e+08 | L136: 2.8473311e+08 | M136: 3.3004618e+08 | N136: 3.2664139e+08 | O136: XNYS | P136: 1 | Q136: EW.N | R136: 0.84373945 | S136: 1.73 | T136: 64.23 | U136: 0.88 | V136: Green | W136: Green | X136: Green | Y136: Green | Z136: Green | AA136: Green | AB136: Green | AC136: Green | AD136: Green | AE136: 0 | AF136: 0 | AH136: 0.88 | AI136: 0 | AJ136: 0 | AK136: 188 | AZ136: Included | BA136: No | BB136: 27 | BC136: EW.N | BD136: 75.09 | BE136: 63.356395 | BF136: 3.4592306e+10 | BG136: 135
A137: 492 | B137: WORKDAY INC. CLASS A | C137: WDAY-US | D137: US98138H1014 | E137: USD | F137: 188.8292 | G137: 217000000 | H137: NASDAQ | I137: 40975.93 | J137: 7.7994884e+08 | K137: 5.3801927e+08 | L137: 5.742572e+08 | M137: 6.6503386e+08 | N137: 5.9814408e+08 | O137: XNGS | P137: 1 | Q137: WDAY.O | R137: 0.84373945 | S137: 0.36 | T137: 69.25 | U137: 0.86 | V137: Green | W137: Green | X137: Green | Y137: Green | Z137: Green | AA137: Green | AB137: Green | AC137: Green | AD137: Green | AE137: 0 | AF137: 0 | AH137: 0.86 | AI137: 0 | AJ137: 0 | AK137: 12 | AZ137: Included | BA137: No | BB137: 6 | BC137: WDAY.O | BD137: 219.01 | BE137: 184.78738 | BF137: 3.4573014e+10 | BG137: 136
A138: 261 | B138: KEURIG DR PEPPER INC | C138: KDP-US | D138: US49271V1008 | E138: USD | F138: 29.98378 | G138: 1358435300 | H138: NASDAQ | I138: 40731.03 | J138: 2.1633298e+08 | K138: 3.8168615e+08 | L138: 2.8474739e+08 | M138: 3.2985546e+08 | N138: 3.4131342e+08 | O138: XNGS | P138: 1 | Q138: KDP.O | R138: 0.84373945 | S138: 0.81 | T138: 49.72 | U138: 0.94 | V138: Green | W138: Green | X138: Green | Y138: Green | Z138: Green | AA138: Green | AB138: Green | AC138: Green | AD138: Green | AE138: 0 | AF138: 0 | AH138: 0.94 | AI138: 0 | AJ138: 0 | AK138: 80 | AZ138: Included | BA138: No | BB138: 176 | BC138: KDP.O | BD138: 26.96 | BE138: 22.747216 | BF138: 3.4366373e+10 | BG138: 137
A139: 380 | B139: REPUBLIC SERVICES | C139: RSG-US | D139: US7607591002 | E139: USD | F139: 199.9659 | G139: 312215820 | H139: NYSE | I139: 62432.5 | J139: 2.3817516e+08 | K139: 2.923625e+08 | L139: 2.8342649e+08 | M139: 3.2828041e+08 | N139: 2.4143941e+08 | O139: XNYS | P139: 0.65 | Q139: RSG.N | R139: 0.84373945 | S139: 2.34 | T139: 55.05 | U139: 0.94 | V139: Green | W139: Green | X139: Green | Y139: Green | Z139: Green | AA139: Green | AB139: Green | AC139: Green | AD139: Green | AE139: 0 | AF139: 0 | AG139: Services | AH139: 0.94 | AI139: 0 | AJ139: 0 | AK139: 269 | AZ139: Included | BA139: No | BB139: 105 | BC139: RSG.N | BD139: 225.33 | BE139: 190.11981 | BF139: 3.4239906e+10 | BG139: 138
A140: 338 | B140: ONEOK INC. | C140: OKE-US | D140: US6826801036 | E140: USD | F140: 63.86755 | G140: 629756000 | H140: NYSE | I140: 40220.97 | J140: 2.365559e+08 | K140: 2.9658603e+08 | L140: 2.5848924e+08 | M140: 2.9915282e+08 | N140: 2.9846203e+08 | O140: XNYS | P140: 1 | Q140: OKE.N | R140: 0.84373945 | S140: 2.79 | T140: 44.03 | U140: 0.89 | V140: Green | W140: Green | X140: Green | Y140: Green | Z140: Green | AA140: Green | AB140: Green | AC140: Green | AD140: Green | AE140: 0 | AF140: 0 | AH140: 0.89 | AI140: 0 | AJ140: 0 | AK140: 332 | AZ140: Included | BA140: No | BB140: 229 | BC140: OKE.N | BD140: 72.58 | BE140: 61.238609 | BF140: 3.3936021e+10 | BG140: 139
A141: 301 | B141: METLIFE INC. | C141: MET-US | D141: US59156R1086 | E141: USD | F141: 69.54258 | G141: 665026060 | H141: NYSE | I141: 46247.63 | J141: 2.3035618e+08 | K141: 2.3076684e+08 | L141: 2.0303429e+08 | M141: 2.3524849e+08 | N141: 2.4456113e+08 | O141: XNYS | P141: 0.85 | Q141: MET.N | R141: 0.84373945 | S141: 0.43 | T141: 60.99 | U141: 0.83 | V141: Green | W141: Green | X141: Green | Y141: Green | Z141: Green | AA141: Green | AB141: Green | AC141: Green | AD141: Green | AE141: 0 | AF141: 0 | AH141: 0.83 | AI141: 0 | AJ141: 0 | AK141: 20 | AZ141: Included | BA141: No | BB141: 40 | BC141: MET.N | BD141: 78.73 | BE141: 66.427607 | BF141: 3.3167806e+10 | BG141: 140
A142: 205 | B142: FORD MOTOR CO | C142: F-US | D142: US3453708600 | E142: USD | F142: 10.01877 | G142: 3909008300 | H142: NYSE | I142: 39163.47 | J142: 5.5590776e+08 | K142: 9.5669825e+08 | L142: 7.7297573e+08 | M142: 8.9498461e+08 | N142: 7.6857116e+08 | O142: XNYS | P142: 1 | Q142: F.N | R142: 0.84373945 | S142: 0.58 | T142: 54.39 | U142: 0.92 | V142: Green | W142: Green | X142: Green | Y142: Green | Z142: Green | AA142: Green | AB142: Green | AC142: Green | AD142: Green | AE142: 0 | AF142: 0 | AH142: 0.92 | AI142: 0 | AJ142: 0 | AK142: 45 | AZ142: Included | BA142: No | BB142: 116 | BC142: F.N | BD142: 11.61 | BE142: 9.795815 | BF142: 3.3043752e+10 | BG142: 141
A143: 347 | B143: PAYCHEX INC. | C143: PAYX-US | D143: US7043261079 | E143: USD | F143: 120.1656 | G143: 360243870 | H143: NASDAQ | I143: 43288.91 | J143: 2.5390047e+08 | K143: 2.9502991e+08 | L143: 2.8892014e+08 | M143: 3.3540167e+08 | N143: 2.6367132e+08 | O143: XNGS | P143: 0.9 | Q143: PAYX.O | R143: 0.84373945 | S143: 0.61 | T143: 56.33 | U143: 0.67 | V143: Green | W143: Green | X143: Green | Y143: Green | Z143: Green | AA143: Green | AB143: Green | AC143: Green | AD143: Green | AE143: 0 | AF143: 0 | AH143: 0.67 | AI143: 0 | AJ143: 0 | AK143: 50 | AZ143: Included | BA143: No | BB143: 90 | BC143: PAYX.O | BD143: 131.62 | BE143: 111.05299 | BF143: 3.2872113e+10 | BG143: 142
A144: 166 | B144: EBAY INC. | C144: EBAY-US | D144: US2786421030 | E144: USD | F144: 84.67316 | G144: 457000000 | H144: NASDAQ | I144: 38695.63 | J144: 4.7730455e+08 | K144: 3.9451806e+08 | L144: 4.1675931e+08 | M144: 4.827122e+08 | N144: 3.3328121e+08 | O144: XNGS | P144: 1 | Q144: EBAY.O | R144: 0.84373945 | S144: 1.37 | T144: 54.15 | U144: 0.91 | V144: Green | W144: Green | X144: Green | Y144: Green | Z144: Green | AA144: Green | AB144: Green | AC144: Green | AD144: Green | AE144: 0 | AF144: 0 | AH144: 0.91 | AI144: 0 | AJ144: 0 | AK144: 146 | AZ144: Included | BA144: No | BB144: 119 | BC144: EBAY.O | BD144: 88.85 | BE144: 74.96625 | BF144: 3.2649033e+10 | BG144: 143
A145: 137 | B145: CROWN CASTLE INC | C145: CCI-US | D145: US22822V1017 | E145: USD | F145: 88.57314 | G145: 435470060 | H145: NYSE | I145: 38570.95 | J145: 2.5466513e+08 | K145: 3.0308101e+08 | L145: 2.7769855e+08 | M145: 3.2194862e+08 | N145: 2.8310894e+08 | O145: XNYS | P145: 1 | Q145: CCI.N | R145: 0.84373945 | S145: 2.53 | T145: 47.82 | U145: 0.85 | V145: Green | W145: Green | X145: Green | Y145: Green | Z145: Green | AA145: Green | AB145: Green | AC145: Green | AD145: Green | AE145: 0 | AF145: 0 | AH145: 0.85 | AI145: 0 | AJ145: 0 | AK145: 299 | AZ145: Included | BA145: No | BB145: 195 | BC145: CCI.N | BD145: 93.57 | BE145: 78.9487 | BF145: 3.2543833e+10 | BG145: 144
A146: 427 | B146: TARGET CORPORATION | C146: TGT-US | D146: US87612E1064 | E146: USD | F146: 84.69022 | G146: 454365900 | H146: NYSE | I146: 38480.34 | J146: 7.4517831e+08 | K146: 6.9279537e+08 | L146: 5.6189422e+08 | M146: 6.5148672e+08 | N146: 6.9447935e+08 | O146: XNYS | P146: 1 | Q146: TGT.N | R146: 0.84373945 | S146: 0.58 | T146: 53.73 | U146: 0.93 | V146: Amber | W146: Green | X146: Green | Y146: Green | Z146: Green | AA146: Green | AB146: Green | AC146: Green | AD146: Green | AE146: 0 | AF146: 0 | AH146: 0.93 | AI146: 0 | AJ146: 0 | AK146: 45 | AZ146: Included | BA146: No | BB146: 125 | BC146: TGT.N | BD146: 89.72 | BE146: 75.700303 | BF146: 3.2467388e+10 | BG146: 145
A147: 314 | B147: MSCI INC. CLASS A | C147: MSCI-US | D147: US55354G1004 | E147: USD | F147: 490.553 | G147: 77365234 | H147: NYSE | I147: 37951.75 | J147: 3.0355129e+08 | K147: 3.036923e+08 | L147: 3.2042109e+08 | M147: 3.7198367e+08 | N147: 2.8393823e+08 | O147: XNYS | P147: 1 | Q147: MSCI.N | R147: 0.84373945 | S147: 0.63 | T147: 65.08 | U147: 0.86 | V147: Green | W147: Green | X147: Green | Y147: Green | Z147: Green | AA147: Green | AB147: Green | AC147: Green | AD147: Green | AE147: 0 | AF147: 0 | AH147: 0.86 | AI147: 0 | AJ147: 0 | AK147: 56 | AZ147: Included | BA147: No | BB147: 24 | BC147: MSCI.N | BD147: 567.02 | BE147: 478.41714 | BF147: 3.2021387e+10 | BG147: 146
A148: 264 | B148: KIMBERLY-CLARK CORP | C148: KMB-US | D148: US4943681035 | E148: USD | F148: 113.9188 | G148: 331779940 | H148: NASDAQ | I148: 37795.96 | J148: 2.6583148e+08 | K148: 2.8240571e+08 | L148: 2.6945507e+08 | M148: 3.1195645e+08 | N148: 2.7385645e+08 | O148: XNGS | P148: 1 | Q148: KMB.O | R148: 0.84373945 | S148: 1.84 | T148: 54.42 | U148: 1 | V148: Green | W148: Green | X148: Green | Y148: Green | Z148: Green | AA148: Green | AB148: Green | AC148: Green | AD148: Green | AE148: 0 | AF148: 0 | AH148: 1 | AI148: 0 | AJ148: 0 | AK148: 202 | AZ148: Included | BA148: No | BB148: 115 | BC148: KMB.O | BD148: 125.04 | BE148: 105.50118 | BF148: 3.1889953e+10 | BG148: 147
A149: 315 | B149: NASDAQ INC. | C149: NDAQ-US | D149: US6311031081 | E149: USD | F149: 80.85851 | G149: 573795200 | H149: NASDAQ | I149: 46396.23 | J149: 2.2078573e+08 | K149: 2.522457e+08 | L149: 2.5644808e+08 | M149: 2.9733837e+08 | N149: 2.209739e+08 | O149: XNGS | P149: 0.8 | Q149: NDAQ.O | R149: 0.84373945 | S149: 1.53 | T149: 58.38 | U149: 0.73 | V149: Green | W149: Green | X149: Green | Y149: Green | Z149: Green | AA149: Green | AB149: Green | AC149: Green | AD149: Green | AE149: 0 | AF149: 0 | AH149: 0.73 | AI149: 0 | AJ149: 0 | AK149: 161 | AZ149: Included | BA149: No | BB149: 65 | BC149: NDAQ.O | BD149: 92.54 | BE149: 78.079649 | BF149: 3.131706e+10 | BG149: 148
A150: 381 | B150: RESMED INC. | C150: RMD-US | D150: US7611521078 | E150: USD | F150: 250.6656 | G150: 146414840 | H150: NYSE | I150: 36701.17 | J150: 2.4425416e+08 | K150: 2.1797172e+08 | L150: 2.0801192e+08 | M150: 2.4120408e+08 | N150: 2.1593124e+08 | O150: XNYS | P150: 1 | Q150: RMD.N | R150: 0.84373945 | S150: 3 | T150: 55.05 | U150: 0.69 | V150: Green | W150: Green | X150: Green | Y150: Green | Z150: Green | AA150: Green | AB150: Green | AC150: Green | AD150: Green | AE150: 0 | AF150: 0 | AH150: 0.69 | AI150: 0 | AJ150: 0 | AK150: 352 | AZ150: Included | BA150: No | BB150: 105 | BC150: RMD.N | BD150: 272.6 | BE150: 230.00337 | BF150: 3.096622e+10 | BG150: 149
...

Sheet Final Selection
A1: Rank | B1: Company | C1: Ticker | D1: ISIN | E1: Currency (Local) | F1: Price (EUR) | G1: NOSH | H1: Exchange Name (VND) | I1: Sec Market Value (EUR) | J1: 20 days aver. turn EUR | K1: 6 month aver. turnover EUR | L1: 3 month average turnover EUR | M1: 3 months aver. Turnover USD | N1: 12 month aver. turnover EUR | O1: MIC | P1: Free Float | R1: #Symbol | S1: FX/Index Ccy | T1: ClimateCuAlignIEANZTgt2050-values | U1: ESG Performance Score | V1: Reported Emissions - Emissions Trust Metric | W1: NBR Overall Flag | X1: Anti-personnel Mines - Overall Flag | Y1: Biological Weapons - Overall Flag | Z1: Chemical Weapons - Overall Flag | AA1: Cluster Munitions - Overall Flag | AB1: Depleted Uranium - Overall Flag | AC1: Incendiary Weapons - Overall Flag | AD1: Nuclear Weapons Outside NPT - Overall Flag | AE1: White Phosphorous Weapons - Overall Flag | AF1: Thermal Coal Mining - Maximum Percentage of Revenues (%) | AG1: Power Generation - Thermal Maximum Percentage of Revenues (%) | AH1: Shale Oil and/or Gas - Involvement tie | AI1: Trust Metric Numeric | AJ1: Coal Mining Numeric | AK1: Thermal Power Numeric | AL1: Carbon Budget Rank | AM1: exclusion_1_TrustMetric | AN1: exclusion_2_NBROverallFlag | AO1: exclusion_3_APMines | AP1: exclusion_4_BiologicalWeapons | AQ1: exclusion_5_ChemicalWeapons | AR1: exclusion_6_ClusterMunitions | AS1: exclusion_7_DepletedUranium | AT1: exclusion_8_IncendiaryWeapons | AU1: exclusion_9_NuclearWeaponsNonNPT | AV1: exclusion_10_WhitePhosphorus | AW1: exclusion_11_CoalMining | AX1: exclusion_12_ThermalPower | AY1: exclusion_13_ShaleOilGas | AZ1: exclusion_14_CarbonBudget | BA1: Exclusion Summary | BB1: Excluded | BC1: ESG Performance Rank | BD1: Symbol | BE1: Close Prc_EOD | BF1: Price in Index Currency | BH1: FFMC | BI1: FFMC Rank | BJ1: Unrounded NOSH | BK1: Rounded NOSH | BL1: Capping Factor | BM1: Effective Date of Review
A2: 17 | B2: ALPHABET CLASS A | C2: GOOGL-US | D2: US02079K3059 | E2: USD | F2: 175.8747 | G2: 5817000000 | H2: NASDAQ | I2: 1023063 | J2: 4.9248801e+09 | K2: 5.8717197e+09 | L2: 5.9033678e+09 | M2: 6.8459395e+09 | N2: 5.1699677e+09 | O2: XNGS | P2: 1 | Q2: =_xlfn.XLOOKUP(D2,'Top 250'!$D$2:$D$251,'Top 250'!$P$2:$P$251) -> 1 | R2: GOOGL.O | S2: 0.84373945 | T2: 0.65 | U2: 57.27 | V2: 0.84 | W2: Amber | X2: Green | Y2: Green | Z2: Green | AA2: Green | AB2: Green | AC2: Green | AD2: Green | AE2: Green | AF2: 0 | AG2: 0 | AI2: 0.84 | AJ2: 0 | AK2: 0 | AL2: 58 | BA2: Included | BB2: No | BC2: 79 | BD2: GOOGL.O | BE2: 251.16 | BF2: 211.9136 | BG2: =F2*G2*Q2*S2 -> 8.6319872e+11 | BH2: 8.6319872e+11 | BI2: 6 | BJ2: 973105.81 | BK2: 973106 | BL2: 1 | BM2: 22-Sep-25
A3: 19 | B3: AMAZON | C3: AMZN-US | D3: US0231351067 | E3: USD | F3: 195.2893 | G3: 10664912000 | H3: NASDAQ | I3: 2082743 | J3: 7.9772001e+09 | K3: 8.5104795e+09 | L3: 7.9912963e+09 | M3: 9.2643579e+09 | N3: 7.8246173e+09 | O3: XNGS | P3: 1 | Q3: =_xlfn.XLOOKUP(D3,'Top 250'!$D$2:$D$251,'Top 250'!$P$2:$P$251) -> 0.9 | R3: AMZN.O | S3: 0.84373945 | T3: 1.36 | U3: 43.66 | V3: 0.93 | W3: Amber | X3: Green | Y3: Green | Z3: Green | AA3: Green | AB3: Green | AC3: Green | AD3: Green | AE3: Green | AF3: 0 | AG3: 0 | AI3: 0.93 | AJ3: 0 | AK3: 0 | AL3: 145 | BA3: Included | BB3: No | BC3: 232 | BD3: AMZN.O | BE3: 234.05 | BF3: 197.47722 | BG3: =F3*G3*Q3*S3 -> 1.5815633e+12 | BH3: 1.5815633e+12 | BI3: 3 | BJ3: 1044243.8 | BK3: 1044244 | BL3: 1 | BM3: 22-Sep-25
A4: 36 | B4: APPLE | C4: AAPL-US | D4: US0378331005 | E4: USD | F4: 194.3676 | G4: 14840390000 | H4: NASDAQ | I4: 2884492 | J4: 1.1742442e+10 | K4: 1.0834249e+10 | L4: 1.0078044e+10 | M4: 1.1681697e+10 | N4: 1.0788743e+10 | O4: XNGS | P4: 1 | Q4: =_xlfn.XLOOKUP(D4,'Top 250'!$D$2:$D$251,'Top 250'!$P$2:$P$251) -> 1 | R4: AAPL.O | S4: 0.84373945 | T4: 0.42 | U4: 64.95 | V4: 0.93 | W4: Amber | X4: Green | Y4: Green | Z4: Green | AA4: Green | AB4: Green | AC4: Green | AD4: Green | AE4: Green | AF4: 0 | AG4: 0 | AI4: 0.93 | AJ4: 0 | AK4: 0 | AL4: 18 | BA4: Included | BB4: No | BC4: 25 | BD4: AAPL.O | BE4: 238.15 | BF4: 200.93655 | BG4: =F4*G4*Q4*S4 -> 2.4337588e+12 | BH4: 2.4337588e+12 | BI4: 2 | BJ4: 1026266 | BK4: 1026266 | BL4: 1 | BM4: 22-Sep-25
A5: 55 | B5: BANK OF AMERICA | C5: BAC-US | D5: US0605051046 | E5: USD | F5: 42.22564 | G5: 7406947300 | H5: NYSE | I5: 312763.1 | J5: 1.3268499e+09 | K5: 1.6718114e+09 | L5: 1.5432748e+09 | M5: 1.7896074e+09 | N5: 1.5611002e+09 | O5: XNYS | P5: 1 | Q5: =_xlfn.XLOOKUP(D5,'Top 250'!$D$2:$D$251,'Top 250'!$P$2:$P$251) -> 0.9 | R5: BAC.N | S5: 0.84373945 | T5: 1.8 | U5: 45.4 | V5: 0.96 | W5: Amber | X5: Green | Y5: Green | Z5: Green | AA5: Green | AB5: Green | AC5: Green | AD5: Green | AE5: Green | AF5: 0 | AG5: 0 | AI5: 0.96 | AJ5: 0 | AK5: 0 | AL5: 197 | BA5: Included | BB5: No | BC5: 217 | BD5: BAC.N | BE5: 50.66 | BF5: 42.743841 | BG5: =F5*G5*Q5*S5 -> 2.375015e+11 | BH5: 2.375015e+11 | BI5: 19 | BJ5: 4824422.7 | BK5: 4824423 | BL5: 1 | BM5: 22-Sep-25
A6: 70 | B6: BROADCOM INC. | C6: AVGO-US | D6: US11135F1012 | E6: USD | F6: 250.8961 | G6: 4703471000 | H6: NASDAQ | I6: 1180082 | J6: 4.4284572e+09 | K6: 5.0063213e+09 | L6: 4.833545e+09 | M6: 5.5971754e+09 | N6: 5.1125496e+09 | O6: XNGS | P6: 1 | Q6: =_xlfn.XLOOKUP(D6,'Top 250'!$D$2:$D$251,'Top 250'!$P$2:$P$251) -> 1 | R6: AVGO.O | S6: 0.84373945 | T6: 3.02 | U6: 44.8 | V6: 0.63 | W6: Green | X6: Green | Y6: Green | Z6: Green | AA6: Green | AB6: Green | AC6: Green | AD6: Green | AE6: Green | AF6: 0 | AG6: 0 | AI6: 0.63 | AJ6: 0 | AK6: 0 | AL6: 355 | BA6: Included | BB6: No | BC6: 221 | BD6: AVGO.O | BE6: 360 | BF6: 303.7462 | BG6: =F6*G6*Q6*S6 -> 9.9568219e+11 | BH6: 9.9568219e+11 | BI6: 5 | BJ6: 678903.49 | BK6: 678903 | BL6: 1 | BM6: 22-Sep-25
A7: 107 | B7: CISCO SYSTEMS INC | C7: CSCO-US | D7: US17275R1023 | E7: USD | F7: 57.45008 | G7: 3959998300 | H7: NASDAQ | I7: 227502.2 | J7: 1.4308107e+09 | K7: 1.2342565e+09 | L7: 1.1800785e+09 | M7: 1.3689942e+09 | N7: 1.1150463e+09 | O7: XNGS | P7: 1 | Q7: =_xlfn.XLOOKUP(D7,'Top 250'!$D$2:$D$251,'Top 250'!$P$2:$P$251) -> 1 | R7: CSCO.O | S7: 0.84373945 | T7: 0.25 | U7: 65.66 | V7: 0.99 | W7: Green | X7: Green | Y7: Green | Z7: Green | AA7: Green | AB7: Green | AC7: Green | AD7: Green | AE7: Green | AF7: 0 | AG7: 0 | AI7: 0.99 | AJ7: 0 | AK7: 0 | AL7: 5 | BA7: Included | BB7: No | BC7: 18 | BD7: CSCO.O | BE7: 66.93 | BF7: 56.471481 | BG7: =F7*G7*Q7*S7 -> 1.919526e+11 | BH7: 1.919526e+11 | BI7: 24 | BJ7: 3651654.8 | BK7: 3651655 | BL7: 1 | BM7: 22-Sep-25
A8: 113 | B8: COCA-COLA CO | C8: KO-US | D8: US1912161007 | E8: USD | F8: 59.84809 | G8: 4303667500 | H8: NYSE | I8: 257566.3 | J8: 7.2645929e+08 | K8: 1.051613e+09 | L8: 9.1423038e+08 | M8: 1.0599458e+09 | N8: 1.0225264e+09 | O8: XNYS | P8: 1 | Q8: =_xlfn.XLOOKUP(D8,'Top 250'!$D$2:$D$251,'Top 250'!$P$2:$P$251) -> 0.9 | R8: KO.N | S8: 0.84373945 | T8: 0.67 | U8: 44.27 | V8: 0.93 | W8: Amber | X8: Green | Y8: Green | Z8: Green | AA8: Green | AB8: Green | AC8: Green | AD8: Green | AE8: Green | AF8: 0 | AG8: 0 | AI8: 0.93 | AJ8: 0 | AK8: 0 | AL8: 61 | BA8: Included | BB8: No | BC8: 224 | BD8: KO.N | BE8: 66.24 | BF8: 55.889301 | BG8: =F8*G8*Q8*S8 -> 1.9558695e+11 | BH8: 1.9558695e+11 | BI8: 22 | BJ8: 3689692.9 | BK8: 3689693 | BL8: 1 | BM8: 22-Sep-25
A9: 172 | B9: ELI LILLY AND CO | C9: LLY-US | D9: US5324571083 | E9: USD | F9: 607.3391 | G9: 946456800 | H9: NYSE | I9: 574820.2 | J9: 4.4289558e+09 | K9: 2.9085759e+09 | L9: 2.7474037e+09 | M9: 3.1851577e+09 | N9: 2.816072e+09 | O9: XNYS | P9: 1 | Q9: =_xlfn.XLOOKUP(D9,'Top 250'!$D$2:$D$251,'Top 250'!$P$2:$P$251) -> 0.85 | R9: LLY.N | S9: 0.84373945 | T9: 2.55 | U9: 59.02 | V9: 1 | W9: Green | X9: Green | Y9: Green | Z9: Green | AA9: Green | AB9: Green | AC9: Green | AD9: Green | AE9: Green | AF9: 0 | AG9: 0 | AI9: 1 | AJ9: 0 | AK9: 0 | AL9: 302 | BA9: Included | BB9: No | BC9: 57 | BD9: LLY.N | BE9: 764.71 | BF9: 645.21599 | BG9: =F9*G9*Q9*S9 -> 4.1224872e+11 | BH9: 4.1224872e+11 | BI9: 10 | BJ9: 319605.15 | BK9: 319605 | BL9: 1 | BM9: 22-Sep-25
A10: 212 | B10: GE AEROSPACE | C10: GE-US | D10: US3696043013 | E10: USD | F10: 227.4535 | G10: 1060439300 | H10: NYSE | I10: 241200.6 | J10: 9.5417228e+08 | K10: 1.2320011e+09 | L10: 1.3985867e+09 | M10: 1.6210481e+09 | N10: 1.0353715e+09 | O10: XNYS | P10: 1 | Q10: =_xlfn.XLOOKUP(D10,'Top 250'!$D$2:$D$251,'Top 250'!$P$2:$P$251) -> 1 | R10: GE.N | S10: 0.84373945 | T10: 0.17 | U10: 42 | V10: 0.98 | W10: Green | X10: Green | Y10: Green | Z10: Green | AA10: Green | AB10: Green | AC10: Green | AD10: Green | AE10: Green | AF10: 0 | AG10: 0 | AI10: 0.98 | AJ10: 0 | AK10: 0 | AL10: 1 | BA10: Included | BB10: No | BC10: 247 | BD10: GE.N | BE10: 292.97 | BF10: 247.19035 | BG10: =F10*G10*Q10*S10 -> 2.0351049e+11 | BH10: 2.0351049e+11 | BI10: 20 | BJ10: 834233.05 | BK10: 834233 | BL10: 1 | BM10: 22-Sep-25
A11: 231 | B11: HOME DEPOT INC | C11: HD-US | D11: US4370761029 | E11: USD | F11: 352.27 | G11: 994928000 | H11: NYSE | I11: 350644.9 | J11: 1.2735606e+09 | K11: 1.2063169e+09 | L11: 1.1396214e+09 | M11: 1.321827e+09 | N11: 1.200889e+09 | O11: XNYS | P11: 1 | Q11: =_xlfn.XLOOKUP(D11,'Top 250'!$D$2:$D$251,'Top 250'!$P$2:$P$251) -> 1 | R11: HD.N | S11: 0.84373945 | T11: 1.57 | U11: 45.49 | V11: 0.97 | W11: Green | X11: Green | Y11: Green | Z11: Green | AA11: Green | AB11: Green | AC11: Green | AD11: Green | AE11: Green | AF11: 0 | AG11: 0 | AI11: 0.97 | AJ11: 0 | AK11: 0 | AL11: 166 | BA11: Included | BB11: No | BC11: 215 | BD11: HD.N | BE11: 421.45 | BF11: 355.59399 | BG11: =F11*G11*Q11*S11 -> 2.9571658e+11 | BH11: 2.9571658e+11 | BI11: 15 | BJ11: 579915.19 | BK11: 579915 | BL11: 1 | BM11: 22-Sep-25
A12: 256 | B12: JOHNSON & JOHNSON | C12: JNJ-US | D12: US4781601046 | E12: USD | F12: 153.0039 | G12: 2408338900 | H12: NYSE | I12: 368485.3 | J12: 1.3121106e+09 | K12: 1.2815092e+09 | L12: 1.1780158e+09 | M12: 1.3655866e+09 | N12: 1.1875347e+09 | O12: XNYS | P12: 1 | Q12: =_xlfn.XLOOKUP(D12,'Top 250'!$D$2:$D$251,'Top 250'!$P$2:$P$251) -> 1 | R12: JNJ.N | S12: 0.84373945 | T12: 0.49 | U12: 67.86 | V12: 0.98 | W12: Amber | X12: Green | Y12: Green | Z12: Green | AA12: Green | AB12: Green | AC12: Green | AD12: Green | AE12: Green | AF12: 0 | AG12: 0 | AI12: 0.98 | AJ12: 0 | AK12: 0 | AL12: 29 | BA12: Included | BB12: No | BC12: 13 | BD12: JNJ.N | BE12: 176.46 | BF12: 148.88626 | BG12: =F12*G12*Q12*S12 -> 3.1090554e+11 | BH12: 3.1090554e+11 | BI12: 13 | BJ12: 1385046.2 | BK12: 1385046 | BL12: 1 | BM12: 22-Sep-25
A13: 258 | B13: JP MORGAN CHASE & CO | C13: JPM-US | D13: US46625H1005 | E13: USD | F13: 252.8076 | G13: 2749754000 | H13: NYSE | I13: 695158.8 | J13: 1.7506895e+09 | K13: 2.2815889e+09 | L13: 2.0406602e+09 | M13: 2.3670612e+09 | N13: 2.1415283e+09 | O13: XNYS | P13: 1 | Q13: =_xlfn.XLOOKUP(D13,'Top 250'!$D$2:$D$251,'Top 250'!$P$2:$P$251) -> 1 | R13: JPM.N | S13: 0.84373945 | T13: 1.76 | U13: 47.38 | V13: 0.94 | W13: Green | X13: Green | Y13: Green | Z13: Green | AA13: Green | AB13: Green | AC13: Green | AD13: Green | AE13: Green | AF13: 0 | AG13: 0 | AI13: 0.94 | AJ13: 0 | AK13: 0 | AL13: 191 | BA13: Included | BB13: No | BC13: 199 | BD13: JPM.N | BE13: 309.19 | BF13: 260.8758 | BG13: =F13*G13*Q13*S13 -> 5.8653283e+11 | BH13: 5.8653283e+11 | BI13: 8 | BJ13: 790469.47 | BK13: 790469 | BL13: 1 | BM13: 22-Sep-25
... A15: 300 | B15: META PLTFORM ORD | C15: META-US | D15: US30303M1027 | E15: USD | F15: 644.1287 | G15: 2168962400 | H15: NASDAQ | I15: 1397091 | J15: 7.2998813e+09 | K15: 8.553469e+09 | L15: 7.5540757e+09 | M15: 8.7499585e+09 | N15: 7.956731e+09 | O15: XNGS | P15: 1 | Q15: =_xlfn.XLOOKUP(D15,'Top 250'!$D$2:$D$251,'Top 250'!$P$2:$P$251) -> 1 | R15: META.O | S15: 0.84373945 | T15: 0.84 | U15: 44.17 | V15: 0.91 | W15: Amber | X15: Green | Y15: Green | Z15: Green | AA15: Green | AB15: Green | AC15: Green | AD15: Green | AE15: Green | AF15: 0 | AG15: 0 | AI15: 0.91 | AJ15: 0 | AK15: 0 | AL15: 85 | BA15: Included | BB15: No | BC15: 226 | BD15: META.O | BE15: 779 | BF15: 657.27303 | BG15: =F15*G15*Q15*S15 -> 1.1787807e+12 | BH15: 1.1787807e+12 | BI15: 4 | BJ15: 313742.3 | BK15: 313742 | BL15: 1 | BM15: 22-Sep-25
A16: 305 | B16: MICROSOFT CORP | C16: MSFT-US | D16: US5949181045 | E16: USD | F16: 432.864 | G16: 7433166500 | H16: NASDAQ | I16: 3217550 | J16: 9.4369412e+09 | K16: 8.7216266e+09 | L16: 8.529722e+09 | M16: 9.8852136e+09 | N16: 8.4822591e+09 | O16: XNGS | P16: 1 | Q16: =_xlfn.XLOOKUP(D16,'Top 250'!$D$2:$D$251,'Top 250'!$P$2:$P$251) -> 1 | R16: MSFT.O | S16: 0.84373945 | T16: 0.47 | U16: 65.25 | V16: 0.91 | W16: Amber | X16: Green | Y16: Green | Z16: Green | AA16: Green | AB16: Green | AC16: Green | AD16: Green | AE16: Green | AF16: 0 | AG16: 0 | AI16: 0.91 | AJ16: 0 | AK16: 0 | AL16: 24 | BA16: Included | BB16: No | BC16: 21 | BD16: MSFT.O | BE16: 509.04 | BF16: 429.49713 | BG16: =BE16*G16*Q16 -> 3783779075160 | BH16: 2.714774e+12 | BI16: 1 | BJ16: 480129.76 | BK16: 480130 | BL16: 1 | BM16: 22-Sep-25
A17: 319 | B17: NETFLIX INC. | C17: NFLX-US | D17: US64110L1061 | E17: USD | F17: 1028.034 | G17: 424926360 | H17: NASDAQ | I17: 436838.7 | J17: 2.9174361e+09 | K17: 3.9762351e+09 | L17: 3.4028095e+09 | M17: 3.9478521e+09 | N17: 3.3245206e+09 | O17: XNGS | P17: 1 | Q17: =_xlfn.XLOOKUP(D17,'Top 250'!$D$2:$D$251,'Top 250'!$P$2:$P$251) -> 1 | R17: NFLX.O | S17: 0.84373945 | T17: 1.85 | U17: 44.05 | V17: 0.8 | W17: Green | X17: Green | Y17: Green | Z17: Green | AA17: Green | AB17: Green | AC17: Green | AD17: Green | AE17: Green | AF17: 0 | AG17: 0 | AI17: 0.8 | AJ17: 0 | AK17: 0 | AL17: 203 | BA17: Included | BB17: No | BC17: 227 | BD17: NFLX.O | BE17: 1200.51 | BF17: 1012.9176 | BG17: =F17*G17*Q17*S17 -> 3.6857808e+11 | BH17: 3.6857808e+11 | BI17: 11 | BJ17: 203584.52 | BK17: 203585 | BL17: 1 | BM17: 22-Sep-25
A18: 339 | B18: ORACLE CORP | C18: ORCL-US | D18: US68389X1054 | E18: USD | F18: 201.7153 | G18: 2808833000 | H18: NYSE | I18: 566584.6 | J18: 2.2063885e+09 | K18: 1.9667346e+09 | L18: 2.544095e+09 | M18: 2.9536055e+09 | N18: 1.7520544e+09 | O18: XNYS | P18: 1 | Q18: =_xlfn.XLOOKUP(D18,'Top 250'!$D$2:$D$251,'Top 250'!$P$2:$P$251) -> 0.6 | R18: ORCL.N | S18: 0.84373945 | T18: 0.84 | U18: 65.1 | V18: 0.89 | W18: Green | X18: Green | Y18: Green | Z18: Green | AA18: Green | AB18: Green | AC18: Green | AD18: Green | AE18: Green | AF18: 0 | AG18: 0 | AI18: 0.89 | AJ18: 0 | AK18: 0 | AL18: 85 | BA18: Included | BB18: No | BC18: 22 | BD18: ORCL.N | BE18: 306.65 | BF18: 258.7327 | BG18: =F18*G18*Q18*S18 -> 2.8682986e+11 | BH18: 2.8682986e+11 | BI18: 16 | BJ18: 797016.98 | BK18: 797017 | BL18: 1 | BM18: 22-Sep-25
A19: 344 | B19: PALANTIR TECH | C19: PLTR-US | D19: US69608A1088 | E19: USD | F19: 135.4668 | G19: 2274261500 | H19: NASDAQ | I19: 308086.9 | J19: 1.287121e+10 | K19: 9.5917747e+09 | L19: 9.7491801e+09 | M19: 1.1299342e+10 | N19: 7.2820765e+09 | O19: XNGS | P19: 1 | Q19: =_xlfn.XLOOKUP(D19,'Top 250'!$D$2:$D$251,'Top 250'!$P$2:$P$251) -> 1 | R19: PLTR.O | S19: 0.84373945 | T19: 1.07 | U19: 53.9 | V19: 0.6 | W19: Green | X19: Green | Y19: Green | Z19: Green | AA19: Green | AB19: Green | AC19: Green | AD19: Green | AE19: Green | AF19: 0 | AG19: 0 | AI19: 0.6 | AJ19: 0 | AK19: 0 | AL19: 116 | BA19: Included | BB19: No | BC19: 122 | BD19: PLTR.O | BE19: 170.26 | BF19: 143.65508 | BG19: =F19*G19*Q19*S19 -> 2.5994509e+11 | BH19: 2.5994509e+11 | BI19: 18 | BJ19: 1435482.5 | BK19: 1435483 | BL19: 1 | BM19: 22-Sep-25
A20: 354 | B20: PHILIP MORRIS INT | C20: PM-US | D20: US7181721090 | E20: USD | F20: 146.5694 | G20: 1556589400 | H20: NYSE | I20: 228148.3 | J20: 6.5664806e+08 | K20: 8.9938317e+08 | L20: 8.4235336e+08 | M20: 9.7631998e+08 | N20: 7.746336e+08 | O20: XNYS | P20: 1 | Q20: =_xlfn.XLOOKUP(D20,'Top 250'!$D$2:$D$251,'Top 250'!$P$2:$P$251) -> 1 | R20: PM.N | S20: 0.84373945 | T20: 0.61 | U20: 51.95 | V20: 0.98 | W20: Amber | X20: Green | Y20: Green | Z20: Green | AA20: Green | AB20: Green | AC20: Green | AD20: Green | AE20: Green | AF20: 0 | AG20: 0 | AI20: 0.98 | AJ20: 0 | AK20: 0 | AL20: 50 | BA20: Included | BB20: No | BC20: 155 | BD20: PM.N | BE20: 162.96 | BF20: 137.49578 | BG20: =F20*G20*Q20*S20 -> 1.9249778e+11 | BH20: 1.9249778e+11 | BI20: 23 | BJ20: 1499786.8 | BK20: 1499787 | BL20: 1 | BM20: 22-Sep-25
A21: 362 | B21: PROCTER & GAMBLE CO | C21: PG-US | D21: US7427181091 | E21: USD | F21: 135.4071 | G21: 2342371600 | H21: NYSE | I21: 317173.6 | J21: 9.2305167e+08 | K21: 1.2051344e+09 | L21: 1.1101249e+09 | M21: 1.2870492e+09 | N21: 1.1567534e+09 | O21: XNYS | P21: 1 | Q21: =_xlfn.XLOOKUP(D21,'Top 250'!$D$2:$D$251,'Top 250'!$P$2:$P$251) -> 1 | R21: PG.N | S21: 0.84373945 | T21: 0.79 | U21: 58.74 | V21: 0.99 | W21: Green | X21: Green | Y21: Green | Z21: Green | AA21: Green | AB21: Green | AC21: Green | AD21: Green | AE21: Green | AF21: 0 | AG21: 0 | AI21: 0.99 | AJ21: 0 | AK21: 0 | AL21: 77 | BA21: Included | BB21: No | BC21: 60 | BD21: PG.N | BE21: 158.05 | BF21: 133.35302 | BG21: =F21*G21*Q21*S21 -> 2.67612e+11 | BH21: 2.67612e+11 | BI21: 17 | BJ21: 1546379.3 | BK21: 1546379 | BL21: 1 | BM21: 22-Sep-25
A22: 394 | B22: SALESFORCE INC | C22: CRM-US | D22: US79466L3024 | E22: USD | F22: 211.8877 | G22: 956000000 | H22: NYSE | I22: 202564.6 | J22: 1.7713037e+09 | K22: 1.7747846e+09 | L22: 1.824998e+09 | M22: 2.1118624e+09 | N22: 1.7846106e+09 | O22: XNYS | P22: 1 | Q22: =_xlfn.XLOOKUP(D22,'Top 250'!$D$2:$D$251,'Top 250'!$P$2:$P$251) -> 1 | R22: CRM.N | S22: 0.84373945 | T22: 0.98 | U22: 65.48 | V22: 0.9 | W22: Green | X22: Green | Y22: Green | Z22: Green | AA22: Green | AB22: Green | AC22: Green | AD22: Green | AE22: Green | AF22: 0 | AG22: 0 | AI22: 0.9 | AJ22: 0 | AK22: 0 | AL22: 105 | BA22: Included | BB22: No | BC22: 19 | BD22: CRM.N | BE22: 239.31 | BF22: 201.91529 | BG22: =F22*G22*Q22*S22 -> 1.7091178e+11 | BH22: 1.7091178e+11 | BI22: 25 | BJ22: 1021291.4 | BK22: 1021291 | BL22: 1 | BM22: 22-Sep-25
A23: 433 | B23: TESLA INC | C23: TSLA-US | D23: US88160R1014 | E23: USD | F23: 290.1604 | G23: 3225449000 | H23: NASDAQ | I23: 935897.7 | J23: 2.1367951e+10 | K23: 2.9445717e+10 | L23: 2.7999684e+10 | M23: 3.241537e+10 | N23: 2.7610006e+10 | O23: XNGS | P23: 1 | Q23: =_xlfn.XLOOKUP(D23,'Top 250'!$D$2:$D$251,'Top 250'!$P$2:$P$251) -> 0.85 | R23: TSLA.O | S23: 0.84373945 | T23: 2.89 | U23: 60.66 | V23: 0.91 | W23: Amber | X23: Green | Y23: Green | Z23: Green | AA23: Green | AB23: Green | AC23: Green | AD23: Green | AE23: Green | AF23: 0 | AG23: 0 | AI23: 0.91 | AJ23: 0 | AK23: 0 | AL23: 342 | BA23: Included | BB23: No | BC23: 45 | BD23: TSLA.O | BE23: 421.62 | BF23: 355.73743 | BG23: =F23*G23*Q23*S23 -> 6.7120565e+11 | BH23: 6.7120565e+11 | BI23: 7 | BJ23: 579681.36 | BK23: 579681 | BL23: 1 | BM23: 22-Sep-25
A24: 457 | B24: UNITED HEALTH GROUP | C24: UNH-US | D24: US91324P1021 | E24: USD | F24: 262.3485 | G24: 905673650 | H24: NYSE | I24: 237602.1 | J24: 5.1760968e+09 | K24: 4.3389626e+09 | L24: 4.1429386e+09 | M24: 4.8018659e+09 | N24: 3.2631414e+09 | O24: XNYS | P24: 1 | Q24: =_xlfn.XLOOKUP(D24,'Top 250'!$D$2:$D$251,'Top 250'!$P$2:$P$251) -> 1 | R24: UNH.N | S24: 0.84373945 | T24: 1.72 | U24: 70.21 | V24: 0.87 | W24: Green | X24: Green | Y24: Green | Z24: Green | AA24: Green | AB24: Green | AC24: Green | AD24: Green | AE24: Green | AF24: 0 | AG24: 0 | AI24: 0.87 | AJ24: 0 | AK24: 0 | AL24: 186 | BA24: Included | BB24: No | BC24: 4 | BD24: UNH.N | BE24: 339.78 | BF24: 286.68579 | BG24: =F24*G24*Q24*S24 -> 2.0047429e+11 | BH24: 2.0047429e+11 | BI24: 21 | BJ24: 719304.42 | BK24: 719304 | BL24: 1 | BM24: 22-Sep-25
A25: 471 | B25: VISA INC | C25: V-US | D25: US92826C8394 | E25: USD | F25: 298.7199 | G25: 1698682500 | H25: NYSE | I25: 507430.3 | J25: 1.7368346e+09 | K25: 2.083355e+09 | L25: 1.9676343e+09 | M25: 2.2791641e+09 | N25: 1.929801e+09 | O25: XNYS | P25: 1 | Q25: =_xlfn.XLOOKUP(D25,'Top 250'!$D$2:$D$251,'Top 250'!$P$2:$P$251) -> 1 | R25: V.N | S25: 0.84373945 | T25: 0.82 | U25: 55.33 | V25: 0.87 | W25: Green | X25: Green | Y25: Green | Z25: Green | AA25: Green | AB25: Green | AC25: Green | AD25: Green | AE25: Green | AF25: 0 | AG25: 0 | AI25: 0.87 | AJ25: 0 | AK25: 0 | AL25: 82 | BA25: Included | BB25: No | BC25: 100 | BD25: V.N | BE25: 340.03 | BF25: 286.89673 | BG25: =F25*G25*Q25*S25 -> 4.2813893e+11 | BH25: 4.2813893e+11 | BI25: 9 | BJ25: 718775.57 | BK25: 718776 | BL25: 1 | BM25: 22-Sep-25
A26: 476 | B26: WALMART INC | C26: WMT-US | D26: US9311421039 | E26: USD | F26: 82.63356 | G26: 7980418000 | H26: NYSE | I26: 659450.4 | J26: 1.6824011e+09 | K26: 1.6572351e+09 | L26: 1.3797586e+09 | M26: 1.5991246e+09 | N26: 1.5022539e+09 | O26: XNYS | P26: 1 | Q26: =_xlfn.XLOOKUP(D26,'Top 250'!$D$2:$D$251,'Top 250'!$P$2:$P$251) -> 0.55 | R26: WMT.N | S26: 0.84373945 | T26: 0.53 | U26: 44.93 | V26: 0.99 | W26: Amber | X26: Green | Y26: Green | Z26: Green | AA26: Green | AB26: Green | AC26: Green | AD26: Green | AE26: Green | AF26: 0 | AG26: 0 | AI26: 0.99 | AJ26: 0 | AK26: 0 | AL26: 34 | BA26: Included | BB26: No | BC26: 219 | BD26: WMT.N | BE26: 103.42 | BF26: 87.259534 | BG26: =F26*G26*Q26*S26 -> 3.0602235e+11 | BH26: 3.0602235e+11 | BI26: 14 | BJ26: 2363230.1 | BK26: 2363230 | BL26: 1 | BM26: 22-Sep-25
